Workbook
Name DepartmentNum: '.c12_inputs.hr'!$E$4

Sheet registry
A2: Year | E2: 45657 | F2: 46022 | G2: 46112 | H2: 46203 | I2: 46022 | J2: 46112 | K2: 46203 | L2: 46295 | M2: 46387 | N2: 46477 | O2: 46568 | P2: 46660 | Q2: 46752
E3: actual | I3: i/o
R4: src_page
A6: [not sourced from c12]
A7: [not sourced from c12]
A8: [not sourced from c12]
A11: [not sourced from c12]
A12: [not sourced from c12]
A13: [not sourced from c12]
A14: [not sourced from c12]
A15: [not sourced from c12]
A16: [not sourced from c12]
A17: [not sourced from c12]
A18: [not sourced from c12]
A19: [not sourced from c12]
... A44: [not sourced from c12]
A47: Total LGH HM Fees | E47: =+'c12_hm'!E60 -> 0 | F47: =+'c12_hm'!F60 -> 447597 | G47: =+'c12_hm'!G60 -> 310715.79 | H47: =+'c12_hm'!H60 -> 0 | I47: =+'c12_hm'!I60 -> 447597 | J47: =+'c12_hm'!J60 -> 310715.79 | K47: =+'c12_hm'!K60 -> 902637.29 | L47: =+'c12_hm'!L60 -> 948110.97 | ... Q47: =+'c12_hm'!Q60 -> 1223469.7 | R47: c12_hm
A48: c12 Participation | E48: =+'c12_hm'!E70 -> 0 | F48: =+'c12_hm'!F70 -> 447597 | G48: =+'c12_hm'!G70 -> 63035.789 | H48: =+'c12_hm'!H70 -> 0 | I48: =+'c12_hm'!I70 -> 447597 | J48: =+'c12_hm'!J70 -> 63035.789 | K48: =+'c12_hm'!K70 -> 398173.65 | L48: =+'c12_hm'!L70 -> 400447.34 | ... Q48: =+'c12_hm'!Q70 -> 255971.76 | R48: c12_hm
A50: [not sourced from c12]
A51: [not sourced from c12]
A52: [not sourced from c12]
A56: Total LGH D&s Fees | E56: ='c12_d&s'!E60 -> 0 | F56: ='c12_d&s'!F60 -> 911235.5 | G56: ='c12_d&s'!G60 -> 1735259.1 | H56: ='c12_d&s'!H60 -> 0 | I56: ='c12_d&s'!I60 -> 911235.5 | J56: ='c12_d&s'!J60 -> 1829009.1 | K56: ='c12_d&s'!K60 -> 2567569.8 | L56: ='c12_d&s'!L60 -> 2299388.8 | ... Q56: ='c12_d&s'!Q60 -> 4550380.3 | R56: c12_d&s
A57: c12 D&s Participation | E57: ='c12_d&s'!E70 -> 0 | F57: ='c12_d&s'!F70 -> 455617.75 | G57: ='c12_d&s'!G70 -> 806580.95 | H57: ='c12_d&s'!H70 -> 0 | I57: ='c12_d&s'!I70 -> 455617.75 | J57: ='c12_d&s'!J70 -> 839393.45 | K57: ='c12_d&s'!K70 -> 1048217.6 | L57: ='c12_d&s'!L70 -> 968127.09 | ... Q57: ='c12_d&s'!Q70 -> 1555733.1 | R57: c12_d&s
A59: total c12 participation | E59: ='c12_oc'!E10 -> 2452451 | F59: ='c12_oc'!F10 -> 903214.75 | G59: ='c12_oc'!G10 -> 886331.48 | H59: ='c12_oc'!H10 -> 0 | I59: ='c12_oc'!I10 -> 903214.75 | J59: ='c12_oc'!J10 -> 919143.98 | K59: ='c12_oc'!K10 -> 1463106 | L59: ='c12_oc'!L10 -> 1390973.4 | ... Q59: ='c12_oc'!Q10 -> 1838752 | R59: c12_oc
A60: total lgh revenue | E60: ='c12_oc'!E87 -> 0 | F60: ='c12_oc'!F87 -> 1358832.5 | G60: ='c12_oc'!G87 -> 2200269.7 | H60: ='c12_oc'!H87 -> 0 | I60: ='c12_oc'!I87 -> 1358832.5 | J60: ='c12_oc'!J87 -> 2294019.7 | K60: ='c12_oc'!K87 -> 3624501.8 | L60: ='c12_oc'!L87 -> 3515478.7 | ... Q60: ='c12_oc'!Q87 -> 6134792.1 | R60: c12_oc
A61: art leases | E61: ='c12_sk'!E7 -> 0 | F61: ='c12_sk'!F7 -> 0 | G61: ='c12_sk'!G7 -> 0 | H61: ='c12_sk'!H7 -> 0 | I61: ='c12_sk'!I7 -> 0 | J61: ='c12_sk'!J7 -> 50000 | K61: ='c12_sk'!K7 -> 50000 | L61: ='c12_sk'!L7 -> 50000 | ... Q61: ='c12_sk'!Q7 -> 50000 | R61: c12_sk
A63: [not sourced from c12]
A64: [not sourced from c12]
A67: [not sourced from c12]
A68: [not sourced from c12]
A69: [not sourced from c12]
A72: [not sourced from c12]
A73: [not sourced from c12]
A74: [not sourced from c12]
A78: [not sourced from c12]
A79: [not sourced from c12]
A80: [not sourced from c12]
A83: [not sourced from c12]
A84: guarantee payments | E84: ='c12_sk'!E8 -> 0 | F84: ='c12_sk'!F8 -> -250000 | G84: ='c12_sk'!G8 -> -250000 | H84: ='c12_sk'!H8 -> 0 | I84: ='c12_sk'!I8 -> -250000 | J84: ='c12_sk'!J8 -> -250000 | K84: ='c12_sk'!K8 -> -250000 | L84: ='c12_sk'!L8 -> -250000 | ... Q84: ='c12_sk'!Q8 -> -250000 | R84: c12_sk
A87: [not sourced from c12]
A88: [not sourced from c12]
A92: [not sourced from c12]
A94: [not sourced from c12]
A95: [not sourced from c12]
A96: Total c12 Operating Expenses | E96: =+'c12_oc'!E39 -> -5450569 | F96: =+'c12_oc'!F39 -> -2917273 | G96: =+'c12_oc'!G39 -> -4057849.9 | H96: =+'c12_oc'!H39 -> 0 | I96: =+'c12_oc'!I39 -> -2917273 | J96: =+'c12_oc'!J39 -> -4057849.9 | K96: =+'c12_oc'!K39 -> -4457407 | L96: =+'c12_oc'!L39 -> -2834607 | ... Q96: =+'c12_oc'!Q39 -> -4930793.2 | R96: c12_oc
A97: [not sourced from c12]
A98: [not sourced from c12]
A99: [not sourced from c12]
A100: [not sourced from c12]
A101: [not sourced from c12]
A102: [not sourced from c12]
A103: lgh cuda buy back | E103: ='c12_sk'!E9 -> 0 | F103: ='c12_sk'!F9 -> 0 | G103: ='c12_sk'!G9 -> -1200000 | H103: ='c12_sk'!H9 -> 0 | I103: ='c12_sk'!I9 -> 0 | J103: ='c12_sk'!J9 -> 0 | K103: ='c12_sk'!K9 -> 0 | L103: ='c12_sk'!L9 -> 0 | ... Q103: ='c12_sk'!Q9 -> 0 | R103: c12_sk
A105: c12 loc balance | E105: =-'c12_oc'!E62 -> 1540999 | F105: =-'c12_oc'!F62 -> 1924884.3 | G105: =-'c12_oc'!G62 -> 0 | H105: =-'c12_oc'!H62 -> 0 | I105: =-'c12_oc'!I62 -> 1924884.3 | J105: =-'c12_oc'!J62 -> 48632.013 | K105: =-'c12_oc'!K62 -> 0 | L105: =-'c12_oc'!L62 -> 0 | ... Q105: =-'c12_oc'!Q62 -> 0 | R105: c12_oc
A106: LGH Fee AR/AP | E106: =+'c12_oc'!E68 -> 0 | F106: =+'c12_oc'!F68 -> 5365480 | G106: =+'c12_oc'!G68 -> 6120868.3 | H106: =+'c12_oc'!H68 -> 0 | I106: =+'c12_oc'!I68 -> 5365480 | J106: =+'c12_oc'!J68 -> 6120868.3 | K106: =+'c12_oc'!K68 -> 5640774.4 | L106: =+'c12_oc'!L68 -> 5378861.5 | ... Q106: =+'c12_oc'!Q68 -> 13345268 | R106: c12_oc
A107: C12 Fee Particpiation AR/AP | E107: =-'c12_oc'!E74 -> 0 | F107: =-'c12_oc'!F74 -> -2964570.5 | G107: =-'c12_oc'!G74 -> -2970159.3 | H107: =-'c12_oc'!H74 -> 0 | I107: =-'c12_oc'!I74 -> -2964570.5 | J107: =-'c12_oc'!J74 -> -2970159.3 | K107: =-'c12_oc'!K74 -> -2465036.1 | L107: =-'c12_oc'!L74 -> -2022503.4 | ... Q107: =-'c12_oc'!Q74 -> -4604945.5 | R107: c12_oc

Sheet c12_inputs
A2: Year
A3: Period
B4: i/o | C4: field_name | D4: index
A5: cost inflation | B5: i | C5: cost_inflation_rate_actual | E5: 0.03
A7: Charge Back Percentage | B7: i | C7: chargeback_pct_actual | E7: 0.05
A8: participation% | B8: i | C8: participation_pct_actual | E8: 0.35
A11: actual thru | B11: i | C11: actuals_thru | E11: 46112
A12: projections from | B12: i | C12: projections_from | E12: 46203
A13: projections to | B13: i | C13: projections_to | E13: 46752

Sheet c12_oc
A2: Year | E2: 45657 | F2: 46022 | G2: 46112 | H2: 46203 | I2: 46022 | J2: 46112 | K2: 46203 | L2: 46295 | M2: 46387 | N2: 46477 | O2: 46568 | P2: 46660 | Q2: 46752
E3: actual | I3: i/o
B4: i/o | C4: field_name | D4: index
A5: C12 Participation Revenue (not c/b reimb)
A6: HM Fees | F6: 447597 | G6: 63035.789 | I6: 447597 | J6: ='c12_hm'!J70 -> 63035.789 | K6: ='c12_hm'!K70 -> 398173.65 | L6: ='c12_hm'!L70 -> 400447.34 | M6: ='c12_hm'!M70 -> 662529.63 | N6: ='c12_hm'!N70 -> 255971.76 | O6: ='c12_hm'!O70 -> 255971.76 | P6: ='c12_hm'!P70 -> 255971.76 | Q6: ='c12_hm'!Q70 -> 255971.76
A7: BI&F Fees | F7: 0 | G7: 16714.737 | I7: 0 | J7: ='c12_bi&F'!J70 -> 16714.737 | K7: ='c12_bi&F'!K70 -> 16714.737 | L7: ='c12_bi&F'!L70 -> 22398.947 | M7: ='c12_bi&F'!M70 -> 27047.105 | N7: ='c12_bi&F'!N70 -> 27047.105 | O7: ='c12_bi&F'!O70 -> 27047.105 | P7: ='c12_bi&F'!P70 -> 27047.105 | Q7: ='c12_bi&F'!Q70 -> 27047.105
A8: DS Fees | F8: 455617.75 | G8: 806580.95 | I8: 455617.75 | J8: ='c12_d&s'!J70 -> 839393.45 | K8: ='c12_d&s'!K70 -> 1048217.6 | L8: ='c12_d&s'!L70 -> 968127.09 | M8: ='c12_d&s'!M70 -> 2241733.1 | N8: ='c12_d&s'!N70 -> 1555733.1 | O8: ='c12_d&s'!O70 -> 1555733.1 | P8: ='c12_d&s'!P70 -> 1555733.1 | Q8: ='c12_d&s'!Q70 -> 1555733.1
A10: total participation revenue | B10: o | C10: total_participation_revenue_actual | E10: 2452451 | F10: 903214.75 | G10: 886331.48 | I10: 903214.75 | J10: =SUM(J6:J9) -> 919143.98 | K10: =SUM(K6:K9) -> 1463106 | L10: =SUM(L6:L9) -> 1390973.4 | M10: =SUM(M6:M9) -> 2931309.9 | N10: =SUM(N6:N9) -> 1838752 | O10: =SUM(O6:O9) -> 1838752 | P10: =SUM(P6:P9) -> 1838752 | Q10: =SUM(Q6:Q9) -> 1838752
A12: Infrastructure | B12: i | C12: nonrecur_exp | D12: infrastructure
A13: Professional services | B13: i | C13: nonrecur_exp | D13: professional_services | K13: 100000 | L13: 100000
A14: Hiring Costs | B14: i | C14: nonrecur_exp | D14: hiring_costs | K14: 100000
A15: signing bonuses | B15: i | C15: nonrecur_exp | D15: signing_bonus
A16: Restructuring | B16: i | C16: nonrecur_exp | D16: restructuring | G16: 0 | J16: 0 | K16: 0 | L16: 0 | M16: 0 | N16: 0 | O16: 0 | P16: 0 | Q16: 0
A17: housing | B17: i | C17: nonrecur_exp | D17: housing | G17: 0 | J17: 0 | K17: 0 | L17: 0 | M17: 0 | N17: 0 | O17: 0 | P17: 0 | Q17: 0
A18: Total | B18: c | C18: total_nonrecur_exp | F18: 0 | G18: 0 | I18: 0 | J18: =SUM(J12:J17) -> 0 | K18: =SUM(K12:K17) -> 200000 | L18: =SUM(L12:L17) -> 100000 | M18: =SUM(M12:M17) -> 0 | N18: =SUM(N12:N17) -> 0 | O18: =SUM(O12:O17) -> 0 | P18: =SUM(P12:P17) -> 0 | Q18: =SUM(Q12:Q17) -> 0
A20: Reimbursable Operating Expenses (inc holtel) | F20: 2917273 | G20: 4057849.9 | I20: 2917273 | J20: =-J39 -> 4057849.9 | K20: =-K39 -> 4457407 | L20: =-L39 -> 2834607 | M20: =-M39 -> 4930793.2 | N20: =-N39 -> 4930793.2 | O20: =-O39 -> 4930793.2 | P20: =-P39 -> 4930793.2 | Q20: =-Q39 -> 4930793.2
A22: revenue from lgh | F22: 3820487.8 | G22: 4944181.3 | I22: 3820487.8 | J22: =J20+J10 -> 4976993.8 | K22: =K20+K10 -> 5920513 | L22: =L20+L10 -> 4225580.4 | M22: =M20+M10 -> 7862103.1 | N22: =N20+N10 -> 6769545.2 | O22: =O20+O10 -> 6769545.2 | P22: =P20+P10 -> 6769545.2 | Q22: =Q20+Q10 -> 6769545.2
A24: compensation
A25: Hotel Management | F25: -770825 | G25: -391680 | I25: -770825 | J25: =-('c12_hm'!J78+'c12_hm'!J79) -> -391680 | K25: =-('c12_hm'!K78+'c12_hm'!K79) -> -391680 | L25: =-('c12_hm'!L78+'c12_hm'!L79) -> -434880 | M25: =-('c12_hm'!M78+'c12_hm'!M79) -> -949185 | N25: =-('c12_hm'!N78+'c12_hm'!N79) -> -949185 | O25: =-('c12_hm'!O78+'c12_hm'!O79) -> -949185 | P25: =-('c12_hm'!P78+'c12_hm'!P79) -> -949185 | Q25: =-('c12_hm'!Q78+'c12_hm'!Q79) -> -949185
A26: Business Infrastructure & Finance | F26: -602497.5 | G26: -296640 | I26: -602497.5 | J26: =-('c12_bi&F'!J78+'c12_bi&F'!J79) -> -296640 | K26: =-('c12_bi&F'!K78+'c12_bi&F'!K79) -> -477677.14 | L26: =-('c12_bi&F'!L78+'c12_bi&F'!L79) -> -672077.14 | M26: =-('c12_bi&F'!M78+'c12_bi&F'!M79) -> -1173394.6 | N26: =-('c12_bi&F'!N78+'c12_bi&F'!N79) -> -1173394.6 | O26: =-('c12_bi&F'!O78+'c12_bi&F'!O79) -> -1173394.6 | P26: =-('c12_bi&F'!P78+'c12_bi&F'!P79) -> -1173394.6 | Q26: =-('c12_bi&F'!Q78+'c12_bi&F'!Q79) -> -1173394.6
A27: Development & Structuring | F27: -1652177.5 | G27: -560160 | I27: -1652177.5 | J27: =-('c12_d&s'!J78+'c12_d&s'!J79) -> -560160 | K27: =-('c12_d&s'!K78+'c12_d&s'!K79) -> -520560 | L27: =-('c12_d&s'!L78+'c12_d&s'!L79) -> -560160 | M27: =-('c12_d&s'!M78+'c12_d&s'!M79) -> -1221223.8 | N27: =-('c12_d&s'!N78+'c12_d&s'!N79) -> -1221223.8 | O27: =-('c12_d&s'!O78+'c12_d&s'!O79) -> -1221223.8 | P27: =-('c12_d&s'!P78+'c12_d&s'!P79) -> -1221223.8 | Q27: =-('c12_d&s'!Q78+'c12_d&s'!Q79) -> -1221223.8
A28: C12 headoffice | F28: -472542.86 | G28: -805022.86 | I28: -472542.86 | J28: =-(J78-J81) -> -805022.86 | K28: =-(K78-K81) -> -383142.86 | L28: =-(L78-L81) -> -383142.86 | M28: =-(M78-M81) -> -902642.86 | N28: =-(N78-N81) -> -902642.86 | O28: =-(O78-O81) -> -902642.86 | P28: =-(P78-P81) -> -902642.86 | Q28: =-(Q78-Q81) -> -902642.86
A29: Head office expenses
A30: office costs (rent & reoccuring) | B30: i | C30: ho_exp | D30: office_costs | F30: -47485 | G30: -135000 | I30: -47485 | J30: =-540000/4 -> -135000 | K30: =-540000/4 -> -135000 | L30: =-540000/4 -> -135000 | M30: =-540000/4 -> -135000 | N30: -135000 | O30: -135000 | P30: -135000 | Q30: -135000
A31: Departmental OOP paid via sk | F31: -249431 | G31: -174347 | I31: -249431 | J31: ='c12_sk'!J6 -> -174347 | K31: ='c12_sk'!K6 -> -174347 | L31: ='c12_sk'!L6 -> -174347 | M31: ='c12_sk'!M6 -> -174347 | N31: ='c12_sk'!N6 -> -174347 | O31: ='c12_sk'!O6 -> -174347 | P31: ='c12_sk'!P6 -> -174347 | Q31: ='c12_sk'!Q6 -> -174347
A32: Departmental OOP not paid via sk | B32: i | C32: ho_exp | D32: oop_notsk | G32: -75000 | J32: -75000 | K32: -75000 | L32: -75000 | M32: -75000 | N32: -75000 | O32: -75000 | P32: -75000 | Q32: -75000
A33: Non-recurring Items paid by LGH | B33: i | C33: ho_exp | D33: nonrecur_lgh | F33: 0 | G33: 0 | I33: 0 | J33: =-J18 -> 0 | K33: =-K18 -> -200000 | L33: =-L18 -> -100000 | M33: =-M18 -> 0 | N33: 0 | O33: 0 | P33: 0 | Q33: 0
A34: C12 Accounts Payable | B34: i | C34: ho_exp | D34: accounts_payable | F34: -599728 | G34: -1620000 | I34: -599728 | J34: -1620000 | K34: -2100000 | L34: -300000 | M34: -300000 | N34: -300000 | O34: -300000 | P34: -300000 | Q34: -300000
A35: inflation multiplier | B35: i | C35: inflation_multiplier | F35: 1 | G35: 1 | I35: 1 | J35: 1 | K35: 1 | L35: 1 | M35: 1 | N35: 1 | O35: 1 | P35: 1 | Q35: 1
A36: Inflation | B36: c | C36: inflation | F36: 0 | G36: 0 | I36: 0 | J36: =(J35-1)*SUM(J25:J34) -> 0 | K36: =(K35-1)*SUM(K25:K34) -> 0 | L36: =(L35-1)*SUM(L25:L34) -> 0 | M36: =(M35-1)*SUM(M25:M34) -> 0 | N36: =(N35-1)*SUM(N25:N34) -> 0 | O36: =(O35-1)*SUM(O25:O34) -> 0 | P36: =(P35-1)*SUM(P25:P34) -> 0 | Q36: =(Q35-1)*SUM(Q25:Q34) -> 0
A37: Compensation - total | B37: o | C37: compensation_total | E37: -3970569 | F37: -1645629 | G37: -2053502.9 | I37: -1645629 | J37: =IF(AND((G37<>""),(J$2<46204)),(G37),SUM(J25:J28)) -> -2053502.9 | K37: =IF(AND((H37<>""),(K$2<46204)),(H37),SUM(K25:K28)) -> -1773060 | L37: =IF(AND((I37<>""),(L$2<46204)),(I37),SUM(L25:L28)) -> -2050260 | M37: =IF(AND((J37<>""),(M$2<46204)),(J37),SUM(M25:M28)) -> -4246446.2 | N37: =IF(AND((K37<>""),(N$2<46204)),(K37),SUM(N25:N28)) -> -4246446.2 | O37: =IF(AND((L37<>""),(O$2<46204)),(L37),SUM(O25:O28)) -> -4246446.2 | P37: =IF(AND((M37<>""),(P$2<46204)),(M37),SUM(P25:P28)) -> -4246446.2 | Q37: =IF(AND((N37<>""),(Q$2<46204)),(N37),SUM(Q25:Q28)) -> -4246446.2
A38: Direct compensation not via trinet | B38: i | C38: compensation_direct | F38: -375000 | G38: 0 | I38: -375000 | J38: =IF(AND((G38<>""),(J$2<46204)),(G38),0) -> 0 | K38: =IF(AND((H38<>""),(K$2<46204)),(H38),0) -> 0 | L38: =IF(AND((I38<>""),(L$2<46204)),(I38),0) -> 0 | M38: =IF(AND((J38<>""),(M$2<46204)),(J38),0) -> 0 | N38: 0 | O38: 0 | P38: 0 | Q38: 0
A39: Total c12 Expenses paid by LGH | B39: o | C39: total_c12_exp_lgh_actual | E39: -5450569 | F39: -2917273 | G39: -4057849.9 | I39: -2917273 | J39: =SUM(J30:J34,J36,J37:J38) -> -4057849.9 | K39: =SUM(K30:K34,K36,K37:K38) -> -4457407 | L39: =SUM(L30:L34,L36,L37:L38) -> -2834607 | M39: =SUM(M30:M34,M36,M37:M38) -> -4930793.2 | N39: =SUM(N30:N34,N36,N37:N38) -> -4930793.2 | O39: =SUM(O30:O34,O36,O37:O38) -> -4930793.2 | P39: =SUM(P30:P34,P36,P37:P38) -> -4930793.2 | Q39: =SUM(Q30:Q34,Q36,Q37:Q38) -> -4930793.2
A41: C12 H/O compensation not paid by lgh | F41: -42318.571 | G41: -58237.714 | I41: -42318.571 | J41: =-J81 -> -58237.714 | K41: =-K81 -> -58237.714 | L41: =-L81 -> -58237.714 | M41: =-M81 -> -79017.714 | N41: =-N81 -> -79017.714 | O41: =-O81 -> -79017.714 | P41: =-P81 -> -79017.714 | Q41: =-Q81 -> -79017.714
A42: Roots donation by c12 | B42: i | C42: roots_donation | M42: -200000 | N42: -200000 | O42: -200000 | P42: -200000 | Q42: -200000
A43: Total c12 Expenses Not paid by lgh | B43: c | C43: total_c12_exp_not_lgh | F43: -42318.571 | G43: -58237.714 | I43: -42318.571 | J43: =SUM(J41:J42) -> -58237.714 | K43: =SUM(K41:K42) -> -58237.714 | L43: =SUM(L41:L42) -> -58237.714 | M43: =SUM(M41:M42) -> -279017.71 | N43: =SUM(N41:N42) -> -279017.71 | O43: =SUM(O41:O42) -> -279017.71 | P43: =SUM(P41:P42) -> -279017.71 | Q43: =SUM(Q41:Q42) -> -279017.71
A45: total costs | B45: c | C45: total_c12_costs | F45: -2959591.6 | G45: -4116087.6 | I45: -2959591.6 | J45: =J43+J39 -> -4116087.6 | K45: =K43+K39 -> -4515644.7 | L45: =L43+L39 -> -2892844.7 | M45: =M43+M39 -> -5209811 | N45: =N43+N39 -> -5209811 | O45: =O43+O39 -> -5209811 | P45: =P43+P39 -> -5209811 | Q45: =Q43+Q39 -> -5209811
A47: Total C12 Profit | B47: o | C47: total_c12_profit_actual | E47: 3119951 | F47: 860896.18 | G47: 828093.76 | I47: 860896.18 | J47: =J22+J45 -> 860906.26 | K47: =K22+K45 -> 1404868.3 | L47: =L22+L45 -> 1332735.7 | M47: =M22+M45 -> 2652292.1 | N47: =N22+N45 -> 1559734.3 | O47: =O22+O45 -> 1559734.3 | P47: =P22+P45 -> 1559734.3 | Q47: =Q22+Q45 -> 1559734.3
A48: c12 profit margin | B48: c | C48: c12_profit_margin | F48: 0.22533672 | G48: 0.16748855 | I48: 0.22533672 | J48: =J47/J22 -> 0.17297716 | K48: =K47/K22 -> 0.23728827 | L48: =L47/L22 -> 0.31539707 | M48: =M47/M22 -> 0.33735148 | N48: =N47/N22 -> 0.23040459 | O48: =O47/O22 -> 0.23040459 | P48: =P47/P22 -> 0.23040459 | Q48: =Q47/Q22 -> 0.23040459
A51: Bank transfers (actual or danielle)
A52: Bank transfers | F52: -1925382 | G52: 0 | I52: -1925382 | J52: ='c12_sk'!J5 -> -1375000 | K52: ='c12_sk'!K5 -> -1375000 | L52: ='c12_sk'!L5 -> -1375000 | M52: ='c12_sk'!M5 -> -1375000 | N52: ='c12_sk'!N5 -> -1375000 | O52: ='c12_sk'!O5 -> -1375000 | P52: ='c12_sk'!P5 -> -1375000 | Q52: ='c12_sk'!Q5 -> -1375000
A53: oop | F53: 249431 | G53: 174347 | I53: 249431 | J53: =-J31 -> 174347 | K53: =-K31 -> 174347 | L53: =-L31 -> 174347 | M53: =-M31 -> 174347 | N53: =-N31 -> 174347 | O53: =-O31 -> 174347 | P53: =-P31 -> 174347 | Q53: =-Q31 -> 174347
A54: art | F54: 0 | G54: 50000 | I54: 0 | J54: ='c12_sk'!J7 -> 50000 | K54: ='c12_sk'!K7 -> 50000 | L54: ='c12_sk'!L7 -> 50000 | M54: ='c12_sk'!M7 -> 50000 | N54: ='c12_sk'!N7 -> 50000 | O54: ='c12_sk'!O7 -> 50000 | P54: ='c12_sk'!P7 -> 50000 | Q54: ='c12_sk'!Q7 -> 50000
A55: pay | F55: 375000 | G55: 375000 | I55: 375000 | J55: ='.c12_oc_hr'!J6 -> 375000 | K55: ='.c12_oc_hr'!K6 -> 375000 | L55: ='.c12_oc_hr'!L6 -> 375000 | M55: ='.c12_oc_hr'!M6 -> 375000 | N55: ='.c12_oc_hr'!N6 -> 375000 | O55: ='.c12_oc_hr'!O6 -> 375000 | P55: ='.c12_oc_hr'!P6 -> 375000 | Q55: ='.c12_oc_hr'!Q6 -> 375000
A56: guarantess | F56: 250000 | G56: 250000 | I56: 250000 | J56: =-'c12_sk'!J8 -> 250000 | K56: =-'c12_sk'!K8 -> 250000 | L56: =-'c12_sk'!L8 -> 250000 | M56: =-'c12_sk'!M8 -> 250000 | N56: =-'c12_sk'!N8 -> 250000 | O56: =-'c12_sk'!O8 -> 250000 | P56: =-'c12_sk'!P8 -> 250000 | Q56: =-'c12_sk'!Q8 -> 250000
A58: cuda buy back | F58: 0 | G58: 0 | I58: 0 | J58: =-'c12_sk'!J9 -> 0 | K58: =-'c12_sk'!K9 -> 0 | L58: =-'c12_sk'!L9 -> 0 | M58: =-'c12_sk'!M9 -> 0 | N58: =-'c12_sk'!N9 -> 0 | O58: =-'c12_sk'!O9 -> 0 | P58: =-'c12_sk'!P9 -> 0 | Q58: =-'c12_sk'!Q9 -> 0
A59: Distributions | B59: o | C59: distribution_required | E59: -4651000 | F59: -1050951 | G59: 849347 | I59: -1050951 | J59: =SUM(J52:J58) -> -525653 | K59: =SUM(K52:K58) -> -525653 | L59: =SUM(L52:L58) -> -525653 | M59: =SUM(M52:M58) -> -525653 | N59: =SUM(N52:N58) -> -525653 | O59: =SUM(O52:O58) -> -525653 | P59: =SUM(P52:P58) -> -525653 | Q59: =SUM(Q52:Q58) -> -525653
A60: Distribution after c12 profit | B60: c | C60: loc_draw | E60: -1531049 | F60: -190054.82 | G60: 1677440.8 | I60: -190054.82 | J60: =+(J47+J59) -> 335253.26 | K60: =+(K47+K59) -> 879215.26 | L60: =+(L47+L59) -> 807082.66 | M60: =+(M47+M59) -> 2126639.1 | N60: =+(N47+N59) -> 1034081.3 | O60: =+(O47+O59) -> 1034081.3 | P60: =+(P47+P59) -> 1034081.3 | Q60: =+(Q47+Q59) -> 1034081.3
A61: 2024LOC writeoff | B61: i | C61: loc_writeoff | G61: 1540999 | J61: 1540999
A62: Balance of c12 LOC | B62: o | C62: loc_balance | E62: -1540999 | F62: -1924884.3 | G62: 0 | I62: -1924884.3 | J62: =MIN(J60+I62+J61,0) -> -48632.013 | K62: =MIN(K60+J62+K61,0) -> 0 | L62: =MIN(L60+K62+L61,0) -> 0 | M62: =MIN(M60+L62+M61,0) -> 0 | N62: =MIN(N60+M62+N61,0) -> 0 | O62: =MIN(O60+N62+O61,0) -> 0 | P62: =MIN(P60+O62+P61,0) -> 0 | Q62: =MIN(Q60+P62+Q61,0) -> 0
A64: LGH Accounts Receivable
A65: Hotel Management | F65: 563661 | G65: 1162988.6 | I65: 563661 | J65: =-'c12_hm'!J62 -> 1162988.6 | K65: =-'c12_hm'!K62 -> 1170394.7 | L65: =-'c12_hm'!L62 -> 1177800.8 | M65: =-'c12_hm'!M62 -> 16206.87 | N65: =-'c12_hm'!N62 -> 16206.87 | O65: =-'c12_hm'!O62 -> 16206.87 | P65: =-'c12_hm'!P62 -> 16206.87 | Q65: =-'c12_hm'!Q62 -> 16206.87
A66: Business Infrastructure & Finance | F66: 0 | G66: 0 | I66: 0 | J66: ='c12_bi&F'!J62 -> 0 | K66: ='c12_bi&F'!K62 -> 0 | L66: ='c12_bi&F'!L62 -> 0 | M66: ='c12_bi&F'!M62 -> 0 | N66: ='c12_bi&F'!N62 -> 0 | O66: ='c12_bi&F'!O62 -> 0 | P66: ='c12_bi&F'!P62 -> 0 | Q66: ='c12_bi&F'!Q62 -> 0
A67: Development & Structuring | F67: 4801819 | G67: 4957879.7 | I67: 4801819 | J67: =-'c12_d&s'!J62 -> 4957879.7 | K67: =-'c12_d&s'!K62 -> 4470379.7 | L67: =-'c12_d&s'!L62 -> 4201060.7 | M67: =-'c12_d&s'!M62 -> 4929060.7 | N67: =-'c12_d&s'!N62 -> 7029060.7 | O67: =-'c12_d&s'!O62 -> 9129060.7 | P67: =-'c12_d&s'!P62 -> 11229061 | Q67: =-'c12_d&s'!Q62 -> 13329061
A68: Total | B68: o | C68: total_lgh_acc_rec | F68: 5365480 | G68: 6120868.3 | I68: 5365480 | J68: =SUM(J65:J67) -> 6120868.3 | K68: =SUM(K65:K67) -> 5640774.4 | L68: =SUM(L65:L67) -> 5378861.5 | M68: =SUM(M65:M67) -> 4945267.5 | N68: =SUM(N65:N67) -> 7045267.5 | O68: =SUM(O65:O67) -> 9145267.6 | P68: =SUM(P65:P67) -> 11245268 | Q68: =SUM(Q65:Q67) -> 13345268
A70: C12 Accounts Receivable
A71: Hotel Management | F71: 563661 | G71: 740925.66 | I71: 563661 | J71: =+'c12_hm'!J74 -> 740925.66 | K71: =+'c12_hm'!K74 -> 583052.45 | L71: =+'c12_hm'!L74 -> 425179.25 | M71: =+'c12_hm'!M74 -> 18621.38 | N71: =+'c12_hm'!N74 -> 18621.38 | O71: =+'c12_hm'!O74 -> 18621.38 | P71: =+'c12_hm'!P74 -> 18621.38 | Q71: =+'c12_hm'!Q74 -> 18621.38
A72: BI&f | F72: 0 | G72: 0 | I72: 0 | J72: ='c12_bi&F'!J74 -> 0 | K72: ='c12_bi&F'!K74 -> 0 | L72: ='c12_bi&F'!L74 -> 0 | M72: ='c12_bi&F'!M74 -> 0 | N72: ='c12_bi&F'!N74 -> 0 | O72: ='c12_bi&F'!O74 -> 0 | P72: ='c12_bi&F'!P74 -> 0 | Q72: ='c12_bi&F'!Q74 -> 0
A73: Development & Structuring | F73: 2400909.5 | G73: 2229233.6 | I73: 2400909.5 | J73: ='c12_d&s'!J74 -> 2229233.6 | K73: ='c12_d&s'!K74 -> 1881983.6 | L73: ='c12_d&s'!L74 -> 1597324.1 | M73: ='c12_d&s'!M74 -> 1646324.1 | N73: ='c12_d&s'!N74 -> 2381324.1 | O73: ='c12_d&s'!O74 -> 3116324.1 | P73: ='c12_d&s'!P74 -> 3851324.1 | Q73: ='c12_d&s'!Q74 -> 4586324.1
A74: Total | B74: o | C74: total_c12_acc_rec | F74: 2964570.5 | G74: 2970159.3 | I74: 2964570.5 | J74: =SUM(J71:J73) -> 2970159.3 | K74: =SUM(K71:K73) -> 2465036.1 | L74: =SUM(L71:L73) -> 2022503.4 | M74: =SUM(M71:M73) -> 1664945.5 | N74: =SUM(N71:N73) -> 2399945.5 | O74: =SUM(O71:O73) -> 3134945.5 | P74: =SUM(P71:P73) -> 3869945.5 | Q74: =SUM(Q71:Q73) -> 4604945.5
A77: C12 oc compensation expense (not divisons)
A78: ='.c12_oc_hr'!A30 -> Grand Total | F78: 514861.43 | G78: 863260.57 | I78: 514861.43 | J78: ='.c12_oc_hr'!J30 -> 863260.57 | K78: ='.c12_oc_hr'!K30 -> 441380.57 | L78: ='.c12_oc_hr'!L30 -> 441380.57 | M78: ='.c12_oc_hr'!M30 -> 981660.57 | N78: ='.c12_oc_hr'!N30 -> 981660.57 | O78: ='.c12_oc_hr'!O30 -> 981660.57 | P78: ='.c12_oc_hr'!P30 -> 981660.57 | Q78: ='.c12_oc_hr'!Q30 -> 981660.57
A79: ='.c12_oc_hr'!A31 -> reimbersable to hotel | F79: 0 | G79: 0 | I79: 0 | J79: ='.c12_oc_hr'!J31 -> 0 | K79: ='.c12_oc_hr'!K31 -> 0 | L79: ='.c12_oc_hr'!L31 -> 0 | M79: ='.c12_oc_hr'!M31 -> 0 | N79: ='.c12_oc_hr'!N31 -> 0 | O79: ='.c12_oc_hr'!O31 -> 0 | P79: ='.c12_oc_hr'!P31 -> 0 | Q79: ='.c12_oc_hr'!Q31 -> 0
A80: ='.c12_oc_hr'!A32 -> not reimbersable by hotel, but paid by lgh | F80: 472542.86 | G80: 805022.86 | I80: 472542.86 | J80: ='.c12_oc_hr'!J32 -> 805022.86 | K80: ='.c12_oc_hr'!K32 -> 383142.86 | L80: ='.c12_oc_hr'!L32 -> 383142.86 | M80: ='.c12_oc_hr'!M32 -> 902642.86 | N80: ='.c12_oc_hr'!N32 -> 902642.86 | O80: ='.c12_oc_hr'!O32 -> 902642.86 | P80: ='.c12_oc_hr'!P32 -> 902642.86 | Q80: ='.c12_oc_hr'!Q32 -> 902642.86
A81: ='.c12_oc_hr'!A33 -> only paid by c12 | F81: 42318.571 | G81: 58237.714 | I81: 42318.571 | J81: ='.c12_oc_hr'!J33 -> 58237.714 | K81: ='.c12_oc_hr'!K33 -> 58237.714 | L81: ='.c12_oc_hr'!L33 -> 58237.714 | M81: ='.c12_oc_hr'!M33 -> 79017.714 | N81: ='.c12_oc_hr'!N33 -> 79017.714 | O81: ='.c12_oc_hr'!O33 -> 79017.714 | P81: ='.c12_oc_hr'!P33 -> 79017.714 | Q81: ='.c12_oc_hr'!Q33 -> 79017.714
A83: lgh revenue
A84: hm | E84: 1639651 | F84: 447597 | G84: 310715.79 | I84: 447597 | J84: ='c12_hm'!J60 -> 310715.79 | K84: ='c12_hm'!K60 -> 902637.29 | L84: ='c12_hm'!L60 -> 948110.97 | M84: ='c12_hm'!M60 -> 2385063.6 | N84: ='c12_hm'!N60 -> 1223469.7 | O84: ='c12_hm'!O60 -> 1223469.7 | P84: ='c12_hm'!P60 -> 1223469.7 | Q84: ='c12_hm'!Q60 -> 1223469.7
A85: d&s | E85: 1480300 | F85: 911235.5 | G85: 1735259.1 | I85: 911235.5 | J85: ='c12_d&s'!J60 -> 1829009.1 | K85: ='c12_d&s'!K60 -> 2567569.8 | L85: ='c12_d&s'!L60 -> 2299388.8 | M85: ='c12_d&s'!M60 -> 5922380.3 | N85: ='c12_d&s'!N60 -> 4550380.3 | O85: ='c12_d&s'!O60 -> 4550380.3 | P85: ='c12_d&s'!P60 -> 4550380.3 | Q85: ='c12_d&s'!Q60 -> 4550380.3
A86: bif | F86: 0 | G86: 154294.74 | I86: 0 | J86: ='c12_bi&F'!J60 -> 154294.74 | K86: ='c12_bi&F'!K60 -> 154294.74 | L86: ='c12_bi&F'!L60 -> 267978.95 | M86: ='c12_bi&F'!M60 -> 360942.11 | N86: ='c12_bi&F'!N60 -> 360942.11 | O86: ='c12_bi&F'!O60 -> 360942.11 | P86: ='c12_bi&F'!P60 -> 360942.11 | Q86: ='c12_bi&F'!Q60 -> 360942.11
A87: total rev attributable to lgh | B87: o | C87: total_lgh_revenue | F87: 1358832.5 | G87: 2200269.7 | I87: 1358832.5 | J87: =SUM(J84:J86) -> 2294019.7 | K87: =SUM(K84:K86) -> 3624501.8 | L87: =SUM(L84:L86) -> 3515478.7 | M87: =SUM(M84:M86) -> 8668386 | N87: =SUM(N84:N86) -> 6134792.1 | O87: =SUM(O84:O86) -> 6134792.1 | P87: =SUM(P84:P86) -> 6134792.1 | Q87: =SUM(Q84:Q86) -> 6134792.1

Sheet c12_sk
A2: Year | E2: 45657 | F2: 46022 | G2: 46112 | H2: 46203 | I2: 46022 | J2: 46112 | K2: 46203 | L2: 46295 | M2: 46387 | N2: 46477 | O2: 46568 | P2: 46660 | Q2: 46752
E3: actual | I3: i/o
B4: i/o | C4: field_name | D4: index
A5: Bank transfers | B5: i | C5: bank_transfers | D5: sk | F5: -1925382 | G5: -1925382 | I5: -1925382 | J5: -1375000 | K5: -1375000 | L5: -1375000 | M5: -1375000 | N5: -1375000 | O5: -1375000 | P5: -1375000 | Q5: -1375000
A6: Departmental OOP paid via sk | B6: i | C6: ho_exp | D6: oop_sk | F6: -112553 | G6: -186705 | I6: -249431 | J6: -174347 | K6: -174347 | L6: -174347 | M6: -174347 | N6: -174347 | O6: -174347 | P6: -174347 | Q6: -174347
A7: art lease payments to sk | B7: i | C7: lease_payments | D7: sk | E7: 0 | F7: 0 | G7: 0 | I7: 0 | J7: 50000 | K7: 50000 | L7: 50000 | M7: 50000 | N7: 50000 | O7: 50000 | P7: 50000 | Q7: 50000
A8: guarantee fees to sk | B8: i | C8: guarantee_fees | D8: sk | E8: 0 | F8: -250000 | G8: -250000 | I8: -250000 | J8: -250000 | K8: -250000 | L8: -250000 | M8: -250000 | N8: -250000 | O8: -250000 | P8: -250000 | Q8: -250000
A9: cuda buy back | B9: i | C9: cuda_buyback | D9: sk | G9: -1200000
A10: c12 to sk (jp dist) | B10: i | C10: jp_payment | D10: sk

Sheet c12_bs
A2: Year | E2: 45657 | F2: 46022 | G2: 46112 | H2: 46203 | I2: 46022 | J2: 46112 | K2: 46203 | L2: 46295 | M2: 46387 | N2: 46477 | O2: 46568 | P2: 46660 | Q2: 46752
E3: actual | I3: i/o
B4: i/o | C4: field_name | D4: index
A5: assets
A6: cash open | I6: 9950 | J6: =I11 -> 9950 | K6: =J11 -> 9950 | L6: =K11 -> 9950 | M6: =L11 -> 9950 | N6: =M11 -> 9950 | O6: =N11 -> 9950 | P6: =O11 -> 9950 | Q6: =P11 -> 9950
A7: c12 profit | I7: ='c12_oc'!I47 -> 860896.18 | J7: ='c12_oc'!J47 -> 860906.26 | K7: ='c12_oc'!K47 -> 1404868.3 | L7: ='c12_oc'!L47 -> 1332735.7 | M7: ='c12_oc'!M47 -> 2652292.1 | N7: ='c12_oc'!N47 -> 1559734.3 | O7: ='c12_oc'!O47 -> 1559734.3 | P7: ='c12_oc'!P47 -> 1559734.3 | Q7: ='c12_oc'!Q47 -> 1559734.3
A8: borrow from c12 loc | I8: =-'c12_oc'!I60 -> 190054.82 | J8: =-'c12_oc'!J60 -> -335253.26 | K8: =-'c12_oc'!K60 -> -879215.26 | L8: =-'c12_oc'!L60 -> -807082.66 | M8: =-'c12_oc'!M60 -> -2126639.1 | N8: =-'c12_oc'!N60 -> -1034081.3 | O8: =-'c12_oc'!O60 -> -1034081.3 | P8: =-'c12_oc'!P60 -> -1034081.3 | Q8: =-'c12_oc'!Q60 -> -1034081.3
A9: LGH to sk (from danielle) | I9: ='c12_oc'!I59 -> -1050951 | J9: ='c12_oc'!J59 -> -525653 | K9: ='c12_oc'!K59 -> -525653 | L9: ='c12_oc'!L59 -> -525653 | M9: ='c12_oc'!M59 -> -525653 | N9: ='c12_oc'!N59 -> -525653 | O9: ='c12_oc'!O59 -> -525653 | P9: ='c12_oc'!P59 -> -525653 | Q9: ='c12_oc'!Q59 -> -525653
A11: cash close | I11: =SUM(I6:I9) -> 9950 | J11: =SUM(J6:J9) -> 9950 | K11: =SUM(K6:K9) -> 9950 | L11: =SUM(L6:L9) -> 9950 | M11: =SUM(M6:M9) -> 9950 | N11: =SUM(N6:N9) -> 9950 | O11: =SUM(O6:O9) -> 9950 | P11: =SUM(P6:P9) -> 9950 | Q11: =SUM(Q6:Q9) -> 9950
A12: participation accrual | I12: =-'c12_oc'!I74 -> -2964570.5 | J12: =-'c12_oc'!J74 -> -2970159.3 | K12: =-'c12_oc'!K74 -> -2465036.1 | L12: =-'c12_oc'!L74 -> -2022503.4 | M12: =-'c12_oc'!M74 -> -1664945.5 | N12: =-'c12_oc'!N74 -> -2399945.5 | O12: =-'c12_oc'!O74 -> -3134945.5 | P12: =-'c12_oc'!P74 -> -3869945.5 | Q12: =-'c12_oc'!Q74 -> -4604945.5
A13: total assets | I13: =SUM(I11:I12) -> -2954620.5 | J13: =SUM(J11:J12) -> -2960209.3 | K13: =SUM(K11:K12) -> -2455086.1 | L13: =SUM(L11:L12) -> -2012553.4 | M13: =SUM(M11:M12) -> -1654995.5 | N13: =SUM(N11:N12) -> -2389995.5 | O13: =SUM(O11:O12) -> -3124995.5 | P13: =SUM(P11:P12) -> -3859995.5 | Q13: =SUM(Q11:Q12) -> -4594995.5
A15: liabilities
A16: c12loc | I16: ='c12_oc'!I62 -> -1924884.3 | J16: ='c12_oc'!J62 -> -48632.013 | K16: ='c12_oc'!K62 -> 0 | L16: ='c12_oc'!L62 -> 0 | M16: ='c12_oc'!M62 -> 0 | N16: ='c12_oc'!N62 -> 0 | O16: ='c12_oc'!O62 -> 0 | P16: ='c12_oc'!P62 -> 0 | Q16: ='c12_oc'!Q62 -> 0
A18: NAV | I18: =I16+I13 -> -4879504.8 | J18: =J16+J13 -> -3008841.3 | K18: =K16+K13 -> -2455086.1 | L18: =L16+L13 -> -2012553.4 | M18: =M16+M13 -> -1654995.5 | N18: =N16+N13 -> -2389995.5 | O18: =O16+O13 -> -3124995.5 | P18: =P16+P13 -> -3859995.5 | Q18: =Q16+Q13 -> -4594995.5

Sheet c12_hm
A2: Year | E2: 45657 | F2: 46022 | G2: 46112 | H2: 46203 | I2: 46022 | J2: 46112 | K2: 46203 | L2: 46295 | M2: 46387 | N2: 46477 | O2: 46568 | P2: 46660 | Q2: 46752
E3: actual | I3: i/o
B4: i/o | C4: field_name | D4: index
A5: LGH Fee Revenue | C5: lgh_fee_revenue_section
A6: Bermuda PB Mgt | B6: i | C6: mgmt_fee | D6: pb | E6: 535096.5 | F6: 174125 | G6: 186369 | I6: 174125 | J6: =745476/4 -> 186369 | K6: =745476/4 -> 186369 | L6: =745476/4 -> 186369 | M6: =745476/4 -> 186369 | N6: 186369 | O6: 186369 | P6: 186369 | Q6: 186369
A7: Bermuda PB Inc | B7: i | C7: incentive_fee | D7: pb | E7: 535096.5 | F7: 176042 | G7: 181323.26 | I7: 176042 | J7: =+I7*1.03 -> 181323.26 | K7: =+J7 -> 181323.26 | L7: =+K7 -> 181323.26 | M7: =+L7 -> 181323.26 | N7: 181323.26 | O7: 181323.26 | P7: 181323.26 | Q7: 181323.26
A8: Austin Mgt | B8: i | C8: mgmt_fee | D8: austin | E8: 569458 | F8: 161030 | G8: 208682.75 | I8: 161030 | J8: =834731/4 -> 208682.75 | K8: =834731/4 -> 208682.75 | L8: =834731/4 -> 208682.75 | M8: =834731/4 -> 208682.75 | N8: 208682.75 | O8: 208682.75 | P8: 208682.75 | Q8: 208682.75
A9: Austin Inc | B9: i | C9: incentive_fee | D9: austin | F9: 70827.75 | G9: 72952.583 | I9: 70827.75 | J9: =+I9*1.03 -> 72952.583 | K9: =+J9 -> 72952.583 | L9: =+K9 -> 72952.583 | M9: =+L9 -> 72952.583 | N9: 72952.583 | O9: 72952.583 | P9: 72952.583 | Q9: 72952.583
A10: Turks Mgt | B10: i | C10: mgmt_fee | D10: turks | F10: 0 | G10: 0 | I10: 0 | J10: 0 | K10: 0 | L10: 0 | M10: 0 | N10: 0 | O10: 0 | P10: 0 | Q10: 0
A11: Turks Inc | B11: i | C11: incentive_fee | D11: turks
A12: Frithholme | B12: i | C12: mgmt_fee | D12: fritholme | F12: 0 | G12: 0 | I12: 0 | J12: 0 | K12: 0 | L12: 0 | M12: 0 | N12: 0 | O12: 0 | P12: 0 | Q12: 0
A13: Elbow | B13: i | C13: mgmt_fee | D13: elbow | F13: 0 | G13: 0 | I13: 0 | J13: 0
A14: [LSAT] | B14: i | C14: mgmt_fee | D14: lsat | M14: 0 | N14: 0 | O14: 0 | P14: 0 | Q14: 0
A15: [blank]
A16: [blank]
A17: [blank]
A18: [blank]
A19: [blank]
A20: [blank]
A21: [blank]
A22: [blank]
A23: [blank]
A24: [L4] | B24: i | C24: mgmt_fee | D24: l4
A25: Total LGH Fees Earned | B25: c | C25: total_fees_earned | F25: 582024.75 | G25: 649327.59 | I25: 582024.75 | J25: =SUM(J6:J24) -> 649327.59 | K25: =SUM(K6:K24) -> 649327.59 | L25: =SUM(L6:L24) -> 649327.59 | M25: =SUM(M6:M24) -> 649327.59 | N25: =SUM(N6:N24) -> 649327.59 | O25: =SUM(O6:O24) -> 649327.59 | P25: =SUM(P6:P24) -> 649327.59 | Q25: =SUM(Q6:Q24) -> 649327.59
A27: Deferred Period Fee | B27: i | C27: deferred_fee | F27: -182177.75 | G27: -649327.59 | I27: -182177.75 | J27: =-J25 -> -649327.59 | K27: =-K7-K9 -> -254275.84 | L27: =-L7-L9 -> -254275.84 | M27: =-M7-M9-M14 -> -254275.84
A28: Paid Fee Accruals | B28: i | C28: paid_fee_accruals | G28: 50000 | J28: 50000 | K28: 246869.75 | L28: 246869.75 | M28: 1246869.8
A29: Cumm. Balance Accrued Fee | B29: c | C29: cumm_accrued_fee | F29: -394661 | G29: -993988.59 | I29: -394661 | J29: =+J27+I29+J28 -> -993988.59 | K29: =+K27+J29+K28 -> -1001394.7 | L29: =+L27+K29+L28 -> -1008800.8 | M29: =+M27+L29+M28 -> -16206.87 | N29: =+N27+M29+N28 -> -16206.87 | O29: =+O27+N29+O28 -> -16206.87 | P29: =+P27+O29+P28 -> -16206.87 | Q29: =+Q27+P29+Q28 -> -16206.87
A31: Paid Current Fees | B31: c | C31: paid_current_fees | F31: 399847 | G31: 0 | I31: 399847 | J31: =+J25+J27 -> 0 | K31: =+K25+K27 -> 395051.75 | L31: =+L25+L27 -> 395051.75 | M31: =+M25+M27 -> 395051.75 | N31: =+N25+N27 -> 649327.59 | O31: =+O25+O27 -> 649327.59 | P31: =+P25+P27 -> 649327.59 | Q31: =+Q25+Q27 -> 649327.59
A32: Total Fees Paid | B32: c | C32: total_fees_paid | F32: 399847 | G32: 50000 | I32: 399847 | J32: =+J28+J31 -> 50000 | K32: =+K28+K31 -> 641921.5 | L32: =+L28+L31 -> 641921.5 | M32: =+M28+M31 -> 1641921.5 | N32: =+N28+N31 -> 649327.59 | O32: =+O28+O31 -> 649327.59 | P32: =+P28+P31 -> 649327.59 | Q32: =+Q28+Q31 -> 649327.59
A34: LGH Service Revenue
A35: Bermuda PB | B35: i | C35: hm_service_fee | D35: pb | F35: 47750 | G35: 0 | I35: 47750 | J35: 0 | K35: 0 | L35: 0 | M35: 0 | N35: 0 | O35: 0 | P35: 0 | Q35: 0
A36: Austin | B36: i | C36: hm_service_fee | D36: austin | F36: 42250 | G36: 0 | I36: 42250 | J36: 0 | K36: 0 | L36: 0 | M36: 0 | N36: 0 | O36: 0 | P36: 0 | Q36: 0
A37: Turks | B37: i | C37: hm_service_fee | D37: turks | F37: 0 | G37: 0 | I37: 0 | J37: 0 | K37: 0 | L37: 0 | M37: 0 | N37: 0 | O37: 0 | P37: 0 | Q37: 0
A38: Elbow | B38: i | C38: hm_service_fee | D38: elbow | F38: 0 | G38: 0 | I38: 0 | J38: 0 | K38: 0 | L38: 0 | M38: 0 | N38: 0 | O38: 0 | P38: 0 | Q38: 0
A39: [blank]
A40: [blank]
A41: [blank]
A42: [blank]
A43: [blank]
A44: [blank]
A45: Frith | B45: i | C45: service_fee | D45: fritholme | F45: 0 | G45: 0 | I45: 0 | J45: 0 | K45: 0 | L45: 0 | M45: 0 | N45: 0 | O45: 0 | P45: 0 | Q45: 0
A46: Total LGH HM Service Revenue | B46: c | C46: total_service_revenue | F46: 90000 | G46: 0 | I46: 90000 | J46: =SUM(J35:J45) -> 0 | K46: =SUM(K35:K45) -> 0 | L46: =SUM(L35:L45) -> 0 | M46: =SUM(M35:M45) -> 0 | N46: =SUM(N35:N45) -> 0 | O46: =SUM(O35:O45) -> 0 | P46: =SUM(P35:P45) -> 0 | Q46: =SUM(Q35:Q45) -> 0
A48: Deferred Period Fee | B48: i | C48: deferred_service_fee | F48: -42250 | G48: 0 | I48: -42250 | J48: 0 | K48: =-SUM(K35:K45) -> 0 | L48: =-SUM(L35:L45) -> 0 | M48: =-SUM(M35:M45) -> 0 | N48: 0 | O48: 0 | P48: 0 | Q48: 0
A49: Paid Service Accruals | B49: i | C49: paid_service_accruals | M49: 169000
A50: Cumm. Balance Accrued Service Fee | B50: c | C50: cumm_accrued_service_fee | F50: -169000 | G50: -169000 | I50: -169000 | J50: =+J48+I50+J49 -> -169000 | K50: =+K48+J50+K49 -> -169000 | L50: =+L48+K50+L49 -> -169000 | M50: =+M48+L50+M49 -> 0 | N50: =+N48+M50+N49 -> 0 | O50: =+O48+N50+O49 -> 0 | P50: =+P48+O50+P49 -> 0 | Q50: =+Q48+P50+Q49 -> 0
A52: Paid Current Service Fees | B52: c | C52: paid_current_service_fees | F52: 47750 | G52: 0 | I52: 47750 | J52: =+J46+J48 -> 0 | K52: =+K46+K48 -> 0 | L52: =+L46+L48 -> 0 | M52: =+M46+M48 -> 0 | N52: =+N46+N48 -> 0 | O52: =+O46+O48 -> 0 | P52: =+P46+P48 -> 0 | Q52: =+Q46+Q48 -> 0
A53: Total Service Revenue Paid | B53: c | C53: total_service_revenue_paid | F53: 47750 | G53: 0 | I53: 47750 | J53: =+J49+J52 -> 0 | K53: =+K49+K52 -> 0 | L53: =+L49+L52 -> 0 | M53: =+M49+M52 -> 169000 | N53: =+N49+N52 -> 0 | O53: =+O49+O52 -> 0 | P53: =+P49+P52 -> 0 | Q53: =+Q49+Q52 -> 0
A55: LGH Chargebacks
A56: chargeback fee | B56: c | C56: chargeback_multiplier | F56: 1.0526316 | G56: 1.0526316 | I56: 1.0526316 | J56: =1/(1-'c12_inputs'!$E$7) -> 1.0526316 | K56: =1/(1-'c12_inputs'!$E$7) -> 1.0526316 | L56: =1/(1-'c12_inputs'!$E$7) -> 1.0526316 | M56: =1/(1-'c12_inputs'!$E$7) -> 1.0526316 | N56: =1/(1-'c12_inputs'!$E$7) -> 1.0526316 | O56: =1/(1-'c12_inputs'!$E$7) -> 1.0526316 | P56: =1/(1-'c12_inputs'!$E$7) -> 1.0526316 | Q56: =1/(1-'c12_inputs'!$E$7) -> 1.0526316
A57: reimbursable by hotels to LGH | B57: o | C57: reimbursable_by_hotels | F57: 0 | G57: 247680 | I57: 0 | J57: =IF(AND((G57<>""),(J$2<46204)),(G57),J78) -> 247680 | K57: =IF(AND((H57<>""),(K$2<46204)),(H57),K78) -> 247680 | L57: =IF(AND((I57<>""),(L$2<46204)),(I57),L78) -> 290880 | M57: =IF(AND((J57<>""),(M$2<46204)),(J57),M78) -> 545435 | N57: =IF(AND((K57<>""),(N$2<46204)),(K57),N78) -> 545435 | O57: =IF(AND((L57<>""),(O$2<46204)),(L57),O78) -> 545435 | P57: =IF(AND((M57<>""),(P$2<46204)),(M57),P78) -> 545435 | Q57: =IF(AND((N57<>""),(Q$2<46204)),(N57),Q78) -> 545435
A58: Total LGH HM Charge Back | B58: c | C58: total_chargeback | F58: 0 | G58: 260715.79 | I58: 0 | J58: =J57*J56 -> 260715.79 | K58: =K57*K56 -> 260715.79 | L58: =L57*L56 -> 306189.47 | M58: =M57*M56 -> 574142.11 | N58: =N57*N56 -> 574142.11 | O58: =O57*O56 -> 574142.11 | P58: =P57*P56 -> 574142.11 | Q58: =Q57*Q56 -> 574142.11
A60: total LGH HM revenue | B60: o | C60: total_lgh_hm_revenue | F60: 447597 | G60: 310715.79 | I60: 447597 | J60: =+J53+J32+J58 -> 310715.79 | K60: =+K53+K32+K58 -> 902637.29 | L60: =+L53+L32+L58 -> 948110.97 | M60: =+M53+M32+M58 -> 2385063.6 | N60: =+N53+N32+N58 -> 1223469.7 | O60: =+O53+O32+O58 -> 1223469.7 | P60: =+P53+P32+P58 -> 1223469.7 | Q60: =+Q53+Q32+Q58 -> 1223469.7
A62: LGH Accounts Receivable Cumm. | B62: o | C62: lgh_ar_cumm | F62: -563661 | G62: -1162988.6 | I62: -563661 | J62: =+J29+J50 -> -1162988.6 | K62: =+K29+K50 -> -1170394.7 | L62: =+L29+L50 -> -1177800.8 | M62: =+M29+M50 -> -16206.87 | N62: =+N29+N50 -> -16206.87 | O62: =+O29+O50 -> -16206.87 | P62: =+P29+P50 -> -16206.87 | Q62: =+Q29+Q50 -> -16206.87
A64: C12 Participation % | B64: c | C64: c12_participation_pct | F64: 0.35 | G64: 0.35 | I64: 0.35 | J64: ='c12_inputs'!$E$8 -> 0.35 | K64: ='c12_inputs'!$E$8 -> 0.35 | L64: ='c12_inputs'!$E$8 -> 0.35 | M64: ='c12_inputs'!$E$8 -> 0.35 | N64: ='c12_inputs'!$E$8 -> 0.35 | O64: ='c12_inputs'!$E$8 -> 0.35 | P64: ='c12_inputs'!$E$8 -> 0.35 | Q64: ='c12_inputs'!$E$8 -> 0.35
A65: pre-modification extra | B65: i | C65: pre_mod_extra_pct | F65: 0.65 | G65: 0 | I65: 0.65 | J65: 0 | K65: 0 | L65: 0 | M65: 0 | N65: 0 | O65: 0 | P65: 0 | Q65: 0
A66: catchup extra% | B66: i | C66: catchup_extra_pct | F66: 0.65 | G66: 0.65 | I66: 0.65 | J66: 0.65 | K66: 0.65 | L66: 0.65 | M66: 0 | N66: 0 | O66: 0 | P66: 0 | Q66: 0
A67: charge back percentrage | B67: c | C67: chargeback_pct | F67: 0.05 | G67: 0.05 | I67: 0.05 | J67: ='c12_inputs'!$E$7 -> 0.05 | K67: ='c12_inputs'!$E$7 -> 0.05 | L67: ='c12_inputs'!$E$7 -> 0.05 | M67: ='c12_inputs'!$E$7 -> 0.05 | N67: ='c12_inputs'!$E$7 -> 0.05 | O67: ='c12_inputs'!$E$7 -> 0.05 | P67: ='c12_inputs'!$E$7 -> 0.05 | Q67: ='c12_inputs'!$E$7 -> 0.05
A68: C12 Participation $ | B68: c | C68: c12_participation_amt | F68: 447597 | G68: 50000 | I68: 447597 | J68: =(J64+J65)*(J31+J52)+(J64+J66)*(J49+J28) -> 50000 | K68: =(K64+K65)*(K31+K52)+(K64+K66)*(K49+K28) -> 385137.86 | L68: =(L64+L65)*(L31+L52)+(L64+L66)*(L49+L28) -> 385137.86 | M68: =(M64+M65)*(M31+M52)+(M64+M66)*(M49+M28) -> 633822.52 | N68: =(N64+N65)*(N31+N52)+(N64+N66)*(N49+N28) -> 227264.66 | O68: =(O64+O65)*(O31+O52)+(O64+O66)*(O49+O28) -> 227264.66 | P68: =(P64+P65)*(P31+P52)+(P64+P66)*(P49+P28) -> 227264.66 | Q68: =(Q64+Q65)*(Q31+Q52)+(Q64+Q66)*(Q49+Q28) -> 227264.66
A69: chargebacks fees | B69: c | C69: chargeback_fees | F69: 0 | G69: 13035.789 | I69: 0 | J69: =J67*J58 -> 13035.789 | K69: =K67*K58 -> 13035.789 | L69: =L67*L58 -> 15309.474 | M69: =M67*M58 -> 28707.105 | N69: =N67*N58 -> 28707.105 | O69: =O67*O58 -> 28707.105 | P69: =P67*P58 -> 28707.105 | Q69: =Q67*Q58 -> 28707.105
A70: Total C12 HM revenue | B70: o | C70: total_c12_hm_revenue | F70: 447597 | G70: 63035.789 | I70: 447597 | J70: =J69+J68 -> 63035.789 | K70: =K69+K68 -> 398173.65 | L70: =L69+L68 -> 400447.34 | M70: =M69+M68 -> 662529.63 | N70: =N69+N68 -> 255971.76 | O70: =O69+O68 -> 255971.76 | P70: =P69+P68 -> 255971.76 | Q70: =Q69+Q68 -> 255971.76
A72: increase in accrued participation | B72: c | C72: increase_accrued_participation | F72: 224427.75 | G72: 227264.66 | I72: 224427.75 | J72: =-(J64+J65)*(J27+J48) -> 227264.66 | K72: =-(K64+K65)*(K27+K48) -> 88996.545 | L72: =-(L64+L65)*(L27+L48) -> 88996.545 | M72: =-(M64+M65)*(M27+M48) -> 88996.545 | N72: =-(N64+N65)*(N27+N48) -> 0 | O72: =-(O64+O65)*(O27+O48) -> 0 | P72: =-(P64+P65)*(P27+P48) -> 0 | Q72: =-(Q64+Q65)*(Q27+Q48) -> 0
A73: decrease in accrued partipation | B73: c | C73: decrease_accrued_participation | F73: 0 | G73: -50000 | I73: 0 | J73: =-(J64+J66)*(J28+J49) -> -50000 | K73: =-(K64+K66)*(K28+K49) -> -246869.75 | L73: =-(L64+L66)*(L28+L49) -> -246869.75 | M73: =-(M64+M66)*(M28+M49) -> -495554.41 | N73: =-(N64+N66)*(N28+N49) -> 0 | O73: =-(O64+O66)*(O28+O49) -> 0 | P73: =-(P64+P66)*(P28+P49) -> 0 | Q73: =-(Q64+Q66)*(Q28+Q49) -> 0
A74: Cumm. Total Accrued Participation | B74: o | C74: cumm_accrued_participation | F74: 563661 | G74: 740925.66 | I74: 563661 | J74: =SUM(J72:J73)+I74 -> 740925.66 | K74: =SUM(K72:K73)+J74 -> 583052.45 | L74: =SUM(L72:L73)+K74 -> 425179.25 | M74: =SUM(M72:M73)+L74 -> 18621.38 | N74: =SUM(N72:N73)+M74 -> 18621.38 | O74: =SUM(O72:O73)+N74 -> 18621.38 | P74: =SUM(P72:P73)+O74 -> 18621.38 | Q74: =SUM(Q72:Q73)+P74 -> 18621.38
A76: from HR sheet
A77: Grand Total | B77: c | C77: hr_grand_total | F77: 770825 | G77: 391680 | I77: 770825 | J77: ='.c12_hm_hr'!J31 -> 391680 | K77: ='.c12_hm_hr'!K31 -> 391680 | L77: ='.c12_hm_hr'!L31 -> 434880 | M77: ='.c12_hm_hr'!M31 -> 949185 | N77: ='.c12_hm_hr'!N31 -> 949185 | O77: ='.c12_hm_hr'!O31 -> 949185 | P77: ='.c12_hm_hr'!P31 -> 949185 | Q77: ='.c12_hm_hr'!Q31 -> 949185
A78: reimbersable to hotel | B78: o | C78: hr_reimbursable | F78: 367075 | G78: 247680 | I78: 367075 | J78: ='.c12_hm_hr'!J32 -> 247680 | K78: ='.c12_hm_hr'!K32 -> 247680 | L78: ='.c12_hm_hr'!L32 -> 290880 | M78: ='.c12_hm_hr'!M32 -> 545435 | N78: ='.c12_hm_hr'!N32 -> 545435 | O78: ='.c12_hm_hr'!O32 -> 545435 | P78: ='.c12_hm_hr'!P32 -> 545435 | Q78: ='.c12_hm_hr'!Q32 -> 545435
A79: not reimbersable by hotel, but paid by lgh | B79: o | C79: hr_not_reimbursable | F79: 403750 | G79: 144000 | I79: 403750 | J79: ='.c12_hm_hr'!J33 -> 144000 | K79: ='.c12_hm_hr'!K33 -> 144000 | L79: ='.c12_hm_hr'!L33 -> 144000 | M79: ='.c12_hm_hr'!M33 -> 403750 | N79: ='.c12_hm_hr'!N33 -> 403750 | O79: ='.c12_hm_hr'!O33 -> 403750 | P79: ='.c12_hm_hr'!P33 -> 403750 | Q79: ='.c12_hm_hr'!Q33 -> 403750
A80: only paid by c12 | B80: c | C80: hr_only_c12 | F80: 0 | G80: 0 | I80: 0 | J80: ='.c12_hm_hr'!J34 -> 0 | K80: ='.c12_hm_hr'!K34 -> 0 | L80: ='.c12_hm_hr'!L34 -> 0 | M80: ='.c12_hm_hr'!M34 -> 0 | N80: ='.c12_hm_hr'!N34 -> 0 | O80: ='.c12_hm_hr'!O34 -> 0 | P80: ='.c12_hm_hr'!P34 -> 0 | Q80: ='.c12_hm_hr'!Q34 -> 0

Sheet c12_d&s
A2: Year | E2: 45657 | F2: 46022 | G2: 46112 | H2: 46203 | I2: 46022 | J2: 46112 | K2: 46203 | L2: 46295 | M2: 46387 | N2: 46477 | O2: 46568 | P2: 46660 | Q2: 46752
E3: actual | I3: i/o
B4: i/o | C4: field_name | D4: index
A5: LGH Fee Revenue
A6: Pink Beach Design Fee | B6: i | C6: design_fee | D6: pb | F6: 0 | G6: 0 | I6: 0 | J6: 0 | K6: 0 | L6: 0 | M6: 0 | N6: 0 | O6: 0 | P6: 0 | Q6: 0
A7: Pink Beach Development Fee | B7: i | C7: development_fee | D7: pb | F7: 0 | G7: 0 | I7: 0 | J7: 0 | K7: 0 | L7: 0 | M7: 0 | N7: 0 | O7: 0 | P7: 0 | Q7: 0
A8: Pink Beach Structuring Fee | B8: i | C8: structuring_fee | D8: pb | K8: 0 | M8: 0 | N8: 0 | O8: 0 | P8: 0 | Q8: 0
A9: Austin Design Fee | B9: i | C9: design_fee | D9: austin | F9: 0 | G9: 0 | I9: 0 | J9: 0 | K9: 0 | L9: 0 | M9: 0 | N9: 0 | O9: 0 | P9: 0 | Q9: 0
A10: Austin Development Fee | B10: i | C10: development_fee | D10: austin | F10: 0 | G10: 0 | I10: 0 | J10: 0 | K10: 0 | L10: 0 | M10: 0 | N10: 0 | O10: 0 | P10: 0 | Q10: 0
A11: Turks Design Fee | B11: i | C11: design_fee | D11: turks | F11: 50000 | G11: 0 | I11: 50000 | J11: 0 | K11: 0 | L11: 0 | M11: 0 | N11: 0 | O11: 0 | P11: 0 | Q11: 0
A12: Turks Development Fee | B12: i | C12: development_fee | D12: turks | E12: 812800 | F12: 340000 | G12: 549375 | I12: 340000 | J12: =2930000/16*3 -> 549375 | K12: =2930000/16*3 -> 549375 | L12: =2930000/16*3 -> 549375 | M12: =2930000/16*3 -> 549375 | N12: 549375 | O12: 549375 | P12: 549375 | Q12: 549375
A13: Turks Structuring Fee | B13: i | C13: structuring_fee | D13: turks | F13: 250000 | G13: 0 | I13: 250000 | J13: 0 | K13: 0 | L13: 0 | M13: 0 | N13: 0 | O13: 0 | P13: 0 | Q13: 0
A14: Elbow Design Fee | B14: i | C14: design_fee | D14: elbow | F14: 375000 | G14: 487500 | I14: 375000 | J14: =(4500000*0.6-SUM($I$14:$I$14))/4 -> 581250 | K14: =(4500000*0.6-SUM($I$14:$I$14))/4 -> 581250 | L14: =(4500000*0.6-SUM($I$14:$I$14))/4 -> 581250 | M14: =(4500000*0.6-SUM($I$14:$I$14))/4 -> 581250 | N14: 581250 | O14: 581250 | P14: 581250 | Q14: 581250
A15: Elbow Development Fee | B15: i | C15: development_fee | D15: elbow | F15: 500000 | G15: 433333.33 | I15: 500000 | J15: =5200000/3/4 -> 433333.33 | K15: =5200000/3/4 -> 433333.33 | L15: =5200000/3/4 -> 433333.33 | M15: =5200000/3/4 -> 433333.33 | N15: 433333.33 | O15: 433333.33 | P15: 433333.33 | Q15: 433333.33
A16: Elbow Structuring Fee | B16: i | C16: structuring_fee | D16: elbow | F16: 0 | G16: 0 | I16: 0 | J16: 0 | K16: 0 | L16: 0 | M16: 0 | N16: 0 | O16: 0 | P16: 0 | Q16: 0
A17: Elbow Construction Fee | B17: i | C17: construction_fee | D17: elbow | G17: 0 | J17: 0 | K17: 0 | L17: 0 | M17: 0 | N17: 0 | O17: 0 | P17: 0 | Q17: 0
A18: Elbow Acquisition Fee | B18: i | C18: acquisition_fee | D18: elbow
A19: [blank] | F19: 0 | G19: 0 | I19: 0 | J19: 0 | K19: 0 | L19: 0 | M19: 0 | N19: 0 | O19: 0 | P19: 0 | Q19: 0
A20: Frith Acq Fee | B20: i | C20: acquisition_fee | D20: fritholme | F20: 0 | G20: 0 | I20: 0 | J20: 0 | K20: 0 | L20: 0 | M20: 0 | N20: 0 | O20: 0 | P20: 0 | Q20: 0
A21: [blank] | F21: 0 | G21: 0 | I21: 0 | J21: 0 | K21: 0 | L21: 0 | M21: 0 | N21: 0 | O21: 0 | P21: 0 | Q21: 0
A22: Frith Disposition fee | B22: i | C22: disposition_fee | D22: fritholme | F22: 0 | G22: 0 | I22: 0 | J22: 0 | K22: 0 | L22: 0 | M22: 2500000 | N22: 2500000 | O22: 2500000 | P22: 2500000 | Q22: 2500000
A23: SAT | B23: i | C23: development_fee | D23: lsat | M23: =500000+1600000 -> 2100000 | N23: 2100000 | O23: 2100000 | P23: 2100000 | Q23: 2100000
A24: [L4] | B24: i | C24: development_fee | D24: l4 | L24: 0 | M24: 0 | N24: 0 | O24: 0 | P24: 0 | Q24: 0
A25: Total LGH Fees Earned | B25: c | C25: total_fees_earned | F25: 1515000 | G25: 1470208.3 | I25: 1515000 | J25: =SUM(J6:J24) -> 1563958.3 | K25: =SUM(K6:K24) -> 1563958.3 | L25: =SUM(L6:L24) -> 1563958.3 | M25: =SUM(M6:M24) -> 6163958.3 | N25: =SUM(N6:N24) -> 6163958.3 | O25: =SUM(O6:O24) -> 6163958.3 | P25: =SUM(P6:P24) -> 6163958.3 | Q25: =SUM(Q6:Q24) -> 6163958.3
A27: Deferred Period Fee | B27: i | C27: deferred_fee | F27: -745000 | G27: -1470208 | I27: -745000 | J27: -1470208 | K27: =-1000000+310000 -> -690000 | L27: -1000000 | M27: -2100000 | N27: -2100000 | O27: -2100000 | P27: -2100000 | Q27: -2100000
A28: Paid Fee Accruals | B28: i | C28: paid_fee_accruals | G28: 1508647.3 | J28: 1508647.3 | K28: 1177500 | L28: 1177500 | M28: 1177500
A29: Cumm. Balance Accrued Fee | B29: c | C29: cumm_accrued_fee | F29: -4710000 | G29: -4671560.7 | I29: -4710000 | J29: =+J27+I29+J28 -> -4671560.7 | K29: =+K27+J29+K28 -> -4184060.7 | L29: =+L27+K29+L28 -> -4006560.7 | M29: =+M27+L29+M28 -> -4929060.7 | N29: =+N27+M29+N28 -> -7029060.7 | O29: =+O27+N29+O28 -> -9129060.7 | P29: =+P27+O29+P28 -> -11229061 | Q29: =+Q27+P29+Q28 -> -13329061
A31: Paid Current Fees | B31: c | C31: paid_current_fees | F31: 770000 | G31: 0.33333333 | I31: 770000 | J31: =+J25+J27 -> 93750.333 | K31: =+K25+K27 -> 873958.33 | L31: =+L25+L27 -> 563958.33 | M31: =+M25+M27 -> 4063958.3 | N31: =+N25+N27 -> 4063958.3 | O31: =+O25+O27 -> 4063958.3 | P31: =+P25+P27 -> 4063958.3 | Q31: =+Q25+Q27 -> 4063958.3
A32: Total Fees Paid | B32: c | C32: total_fees_paid | F32: 770000 | G32: 1508647.7 | I32: 770000 | J32: =+J28+J31 -> 1602397.7 | K32: =+K28+K31 -> 2051458.3 | L32: =+L28+L31 -> 1741458.3 | M32: =+M28+M31 -> 5241458.3 | N32: =+N28+N31 -> 4063958.3 | O32: =+O28+O31 -> 4063958.3 | P32: =+P28+P31 -> 4063958.3 | Q32: =+Q28+Q31 -> 4063958.3
A34: LGH Service Revenue
A35: PB Design Services | B35: i | C35: design_service_fee | D35: pb | F35: 22110.5 | G35: 45000 | I35: 22110.5 | J35: =180000/4 -> 45000 | K35: =180000/4 -> 45000 | L35: =180000/4 -> 45000 | M35: =180000/4 -> 45000 | N35: 45000 | O35: 45000 | P35: 45000 | Q35: 45000
A36: Austin Design Services | B36: i | C36: design_service_fee | D36: austin | E36: 667500 | F36: 22954.75 | G36: 60000 | I36: 22954.75 | J36: =240000/4 -> 60000 | K36: =240000/4 -> 60000 | L36: =240000/4 -> 60000 | M36: =240000/4 -> 60000 | N36: 60000 | O36: 60000 | P36: 60000 | Q36: 60000
A37: Turks Design Services | B37: i | C37: design_service_fee | D37: turks | F37: 0 | G37: 50000 | I37: 0 | J37: =200000/4 -> 50000 | K37: =400000/4 -> 100000 | L37: =200000/4 -> 50000 | M37: =200000/4 -> 50000 | N37: 50000 | O37: 50000 | P37: 50000 | Q37: 50000
A38: Elbow Design Services | B38: i | C38: design_service_fee | D38: elbow | F38: 0 | G38: 0 | I38: 0 | J38: 0 | K38: =180000/4 -> 45000 | L38: =180000/4 -> 45000 | M38: =+L38 -> 45000 | N38: 45000 | O38: 45000 | P38: 45000 | Q38: 45000
A39: Elbow AM | B39: i | C39: am_fee | D39: elbow | F39: 0 | G39: 0 | I39: 0 | J39: 0 | K39: 0 | L39: 0 | M39: 0 | N39: 0 | O39: 0 | P39: 0 | Q39: 0
A40: Frith Design Services | B40: i | C40: design_service_fee | D40: fritholme | F40: 0 | G40: 27000 | I40: 0 | J40: =108000/4 -> 27000 | K40: =+J40 -> 27000 | L40: =+K40 -> 27000 | M40: =+L40 -> 27000 | N40: 27000 | O40: 27000 | P40: 27000 | Q40: 27000
A41: Frith AM | B41: i | C41: am_fee | D41: fritholme | F41: 12500 | G41: 12500 | I41: 12500 | J41: 12500 | K41: 12500 | L41: 12500
A42: Bermuda PB AM | B42: i | C42: am_fee | D42: pb | F42: 57077.25 | G42: 72879 | I42: 57077.25 | J42: 72879 | K42: 72879 | L42: 72879 | M42: 72879 | N42: 72879 | O42: 72879 | P42: 72879 | Q42: 72879
A43: AustinAM | B43: i | C43: am_fee | D43: austin | F43: 49547.75 | G43: 63543 | I43: 49547.75 | J43: 63543 | K43: 63543 | L43: 63543 | M43: 63543 | N43: 63543 | O43: 63543 | P43: 63543 | Q43: 63543
A44: [blank]
A45: SAT | B45: i | C45: design_service_fee | D45: sat
A46: Total LGH HM Service Revenue | B46: c | C46: total_service_revenue | F46: 164190.25 | G46: 330922 | I46: 164190.25 | J46: =SUM(J35:J45) -> 330922 | K46: =SUM(K35:K45) -> 425922 | L46: =SUM(L35:L45) -> 375922 | M46: =SUM(M35:M45) -> 363422 | N46: =SUM(N35:N45) -> 363422 | O46: =SUM(O35:O45) -> 363422 | P46: =SUM(P35:P45) -> 363422 | Q46: =SUM(Q35:Q45) -> 363422
A48: Deferred Period Fee | B48: i | C48: deferred_service_fee | F48: -22954.75 | G48: -194500 | I48: -22954.75 | J48: -194500
A49: Paid Accruals | B49: i | C49: paid_service_accruals | L49: 91819 | M49: 194500
A50: Cumm. Balance Accrued Service Fee | B50: c | C50: cumm_accrued_service_fee | F50: -91819 | G50: -286319 | I50: -91819 | J50: =+J48+I50+J49 -> -286319 | K50: =+K48+J50+K49 -> -286319 | L50: =+L48+K50+L49 -> -194500 | M50: =+M48+L50+M49 -> 0 | N50: =+N48+M50+N49 -> 0 | O50: =+O48+N50+O49 -> 0 | P50: =+P48+O50+P49 -> 0 | Q50: =+Q48+P50+Q49 -> 0
A52: Paid Current Service Fees | B52: c | C52: paid_current_service_fees | F52: 141235.5 | G52: 136422 | I52: 141235.5 | J52: =+J46+J48 -> 136422 | K52: =+K46+K48 -> 425922 | L52: =+L46+L48 -> 375922 | M52: =+M46+M48 -> 363422 | N52: =+N46+N48 -> 363422 | O52: =+O46+O48 -> 363422 | P52: =+P46+P48 -> 363422 | Q52: =+Q46+Q48 -> 363422
A53: Total Service Revenue Paid | B53: c | C53: total_service_revenue_paid | F53: 141235.5 | G53: 136422 | I53: 141235.5 | J53: =+J49+J52 -> 136422 | K53: =+K49+K52 -> 425922 | L53: =+L49+L52 -> 467741 | M53: =+M49+M52 -> 557922 | N53: =+N49+N52 -> 363422 | O53: =+O49+O52 -> 363422 | P53: =+P49+P52 -> 363422 | Q53: =+Q49+Q52 -> 363422
A55: LGH Chargebacks
A56: chargeback fee | B56: c | C56: chargeback_multiplier | F56: 1.0526316 | G56: 1.0526316 | I56: 1.0526316 | J56: =1/(1-'c12_inputs'!$E$7) -> 1.0526316 | K56: =1/(1-'c12_inputs'!$E$7) -> 1.0526316 | L56: =1/(1-'c12_inputs'!$E$7) -> 1.0526316 | M56: =1/(1-'c12_inputs'!$E$7) -> 1.0526316 | N56: =1/(1-'c12_inputs'!$E$7) -> 1.0526316 | O56: =1/(1-'c12_inputs'!$E$7) -> 1.0526316 | P56: =1/(1-'c12_inputs'!$E$7) -> 1.0526316 | Q56: =1/(1-'c12_inputs'!$E$7) -> 1.0526316
A57: reimbursable by hotels to LGH | B57: o | C57: reimbursable_by_hotels | F57: 0 | G57: 85680 | I57: 0 | J57: =IF(AND((G57<>""),(J$2<46204)),(G57),J78) -> 85680 | K57: =IF(AND((H57<>""),(K$2<46204)),(H57),K78) -> 85680 | L57: =IF(AND((I57<>""),(L$2<46204)),(I57),L78) -> 85680 | M57: =IF(AND((J57<>""),(M$2<46204)),(J57),M78) -> 116850 | N57: =IF(AND((K57<>""),(N$2<46204)),(K57),N78) -> 116850 | O57: =IF(AND((L57<>""),(O$2<46204)),(L57),O78) -> 116850 | P57: =IF(AND((M57<>""),(P$2<46204)),(M57),P78) -> 116850 | Q57: =IF(AND((N57<>""),(Q$2<46204)),(N57),Q78) -> 116850
A58: Total LGH D&S Charge Back chk | B58: c | C58: total_chargeback | F58: 0 | G58: 90189.474 | I58: 0 | J58: =J57*J56 -> 90189.474 | K58: =K57*K56 -> 90189.474 | L58: =L57*L56 -> 90189.474 | M58: =M57*M56 -> 123000 | N58: =N57*N56 -> 123000 | O58: =O57*O56 -> 123000 | P58: =P57*P56 -> 123000 | Q58: =Q57*Q56 -> 123000
A60: total LGH D&S revenue | B60: o | C60: total_lgh_ds_revenue | F60: 911235.5 | G60: 1735259.1 | I60: 911235.5 | J60: =+J53+J32+J58 -> 1829009.1 | K60: =+K53+K32+K58 -> 2567569.8 | L60: =+L53+L32+L58 -> 2299388.8 | M60: =+M53+M32+M58 -> 5922380.3 | N60: =+N53+N32+N58 -> 4550380.3 | O60: =+O53+O32+O58 -> 4550380.3 | P60: =+P53+P32+P58 -> 4550380.3 | Q60: =+Q53+Q32+Q58 -> 4550380.3
A62: LGH Accounts Receivable Cumm. | B62: o | C62: lgh_ar_cumm | F62: -4801819 | G62: -4957879.7 | I62: -4801819 | J62: =+J29+J50 -> -4957879.7 | K62: =+K29+K50 -> -4470379.7 | L62: =+L29+L50 -> -4201060.7 | M62: =+M29+M50 -> -4929060.7 | N62: =+N29+N50 -> -7029060.7 | O62: =+O29+O50 -> -9129060.7 | P62: =+P29+P50 -> -11229061 | Q62: =+Q29+Q50 -> -13329061
A64: C12 Participation % | B64: c | C64: c12_participation_pct | F64: 0.35 | G64: 0.35 | I64: 0.35 | J64: ='c12_inputs'!$E$8 -> 0.35 | K64: ='c12_inputs'!$E$8 -> 0.35 | L64: ='c12_inputs'!$E$8 -> 0.35 | M64: ='c12_inputs'!$E$8 -> 0.35 | N64: ='c12_inputs'!$E$8 -> 0.35 | O64: ='c12_inputs'!$E$8 -> 0.35 | P64: ='c12_inputs'!$E$8 -> 0.35 | Q64: ='c12_inputs'!$E$8 -> 0.35
A65: pre-modification extra | B65: i | C65: pre_mod_extra_pct | F65: 0.15 | G65: 0 | I65: 0.15 | J65: 0 | K65: 0 | L65: 0 | M65: 0 | N65: 0 | O65: 0 | P65: 0 | Q65: 0
A66: catchup extra% | B66: i | C66: catchup_extra_pct | F66: 0.15 | G66: 0.15 | I66: 0.15 | J66: 0.15 | K66: 0.15 | L66: 0.15 | M66: 0.15 | N66: 0.15 | O66: 0.15 | P66: 0.15 | Q66: 0.15
A67: charge back percentrage | B67: c | C67: chargeback_pct | F67: 0.05 | G67: 0.05 | I67: 0.05 | J67: ='c12_inputs'!$E$7 -> 0.05 | K67: ='c12_inputs'!$E$7 -> 0.05 | L67: ='c12_inputs'!$E$7 -> 0.05 | M67: ='c12_inputs'!$E$7 -> 0.05 | N67: ='c12_inputs'!$E$7 -> 0.05 | O67: ='c12_inputs'!$E$7 -> 0.05 | P67: ='c12_inputs'!$E$7 -> 0.05 | Q67: ='c12_inputs'!$E$7 -> 0.05
A68: C12 Participation $ | B68: c | C68: c12_participation_amt | F68: 455617.75 | G68: 802071.48 | I68: 455617.75 | J68: =(J64+J65)*(J31+J52)+(J64+J66)*(J49+J28) -> 834883.98 | K68: =(K64+K65)*(K31+K52)+(K64+K66)*(K49+K28) -> 1043708.1 | L68: =(L64+L65)*(L31+L52)+(L64+L66)*(L49+L28) -> 963617.62 | M68: =(M64+M65)*(M31+M52)+(M64+M66)*(M49+M28) -> 2235583.1 | N68: =(N64+N65)*(N31+N52)+(N64+N66)*(N49+N28) -> 1549583.1 | O68: =(O64+O65)*(O31+O52)+(O64+O66)*(O49+O28) -> 1549583.1 | P68: =(P64+P65)*(P31+P52)+(P64+P66)*(P49+P28) -> 1549583.1 | Q68: =(Q64+Q65)*(Q31+Q52)+(Q64+Q66)*(Q49+Q28) -> 1549583.1
A69: chargebacks fees | B69: c | C69: chargeback_fees | F69: 0 | G69: 4509.4737 | I69: 0 | J69: =J67*J58 -> 4509.4737 | K69: =K67*K58 -> 4509.4737 | L69: =L67*L58 -> 4509.4737 | M69: =M67*M58 -> 6150 | N69: =N67*N58 -> 6150 | O69: =O67*O58 -> 6150 | P69: =P67*P58 -> 6150 | Q69: =Q67*Q58 -> 6150
A70: Total C12 D&S revenue | B70: o | C70: total_c12_ds_revenue | F70: 455617.75 | G70: 806580.95 | I70: 455617.75 | J70: =J69+J68 -> 839393.45 | K70: =K69+K68 -> 1048217.6 | L70: =L69+L68 -> 968127.09 | M70: =M69+M68 -> 2241733.1 | N70: =N69+N68 -> 1555733.1 | O70: =O69+O68 -> 1555733.1 | P70: =P69+P68 -> 1555733.1 | Q70: =Q69+Q68 -> 1555733.1
A72: increase in accrued participation | B72: c | C72: increase_accrued_participation | F72: 383977.38 | G72: 582647.8 | I72: 383977.38 | J72: =-(J64+J65)*(J27+J48) -> 582647.8 | K72: =-(K64+K65)*(K27+K48) -> 241500 | L72: =-(L64+L65)*(L27+L48) -> 350000 | M72: =-(M64+M65)*(M27+M48) -> 735000 | N72: =-(N64+N65)*(N27+N48) -> 735000 | O72: =-(O64+O65)*(O27+O48) -> 735000 | P72: =-(P64+P65)*(P27+P48) -> 735000 | Q72: =-(Q64+Q65)*(Q27+Q48) -> 735000
A73: decrease in accrued partipation | B73: c | C73: decrease_accrued_participation | F73: 0 | G73: -754323.66 | I73: 0 | J73: =-(J64+J66)*(J28+J49) -> -754323.66 | K73: =-(K64+K66)*(K28+K49) -> -588750 | L73: =-(L64+L66)*(L28+L49) -> -634659.5 | M73: =-(M64+M66)*(M28+M49) -> -686000 | N73: =-(N64+N66)*(N28+N49) -> 0 | O73: =-(O64+O66)*(O28+O49) -> 0 | P73: =-(P64+P66)*(P28+P49) -> 0 | Q73: =-(Q64+Q66)*(Q28+Q49) -> 0
A74: Cumm. Total Accrued Participation | B74: o | C74: cumm_accrued_participation | F74: 2400909.5 | G74: 2229233.6 | I74: 2400909.5 | J74: =SUM(J72:J73)+I74 -> 2229233.6 | K74: =SUM(K72:K73)+J74 -> 1881983.6 | L74: =SUM(L72:L73)+K74 -> 1597324.1 | M74: =SUM(M72:M73)+L74 -> 1646324.1 | N74: =SUM(N72:N73)+M74 -> 2381324.1 | O74: =SUM(O72:O73)+N74 -> 3116324.1 | P74: =SUM(P72:P73)+O74 -> 3851324.1 | Q74: =SUM(Q72:Q73)+P74 -> 4586324.1
A76: from HR sheet
A77: Grand Total | B77: c | C77: hr_grand_total | F77: 1652177.5 | G77: 560160 | I77: 1652177.5 | J77: ='.c12_d&s_hr'!J45 -> 560160 | K77: ='.c12_d&s_hr'!K45 -> 520560 | L77: ='.c12_d&s_hr'!L45 -> 560160 | M77: ='.c12_d&s_hr'!M45 -> 1221223.8 | N77: ='.c12_d&s_hr'!N45 -> 1221223.8 | O77: ='.c12_d&s_hr'!O45 -> 1221223.8 | P77: ='.c12_d&s_hr'!P45 -> 1221223.8 | Q77: ='.c12_d&s_hr'!Q45 -> 1221223.8
A78: reimbersable to hotel | B78: o | C78: hr_reimbursable | F78: 123922.5 | G78: 85680 | I78: 123922.5 | J78: ='.c12_d&s_hr'!J46 -> 85680 | K78: ='.c12_d&s_hr'!K46 -> 85680 | L78: ='.c12_d&s_hr'!L46 -> 85680 | M78: ='.c12_d&s_hr'!M46 -> 116850 | N78: ='.c12_d&s_hr'!N46 -> 116850 | O78: ='.c12_d&s_hr'!O46 -> 116850 | P78: ='.c12_d&s_hr'!P46 -> 116850 | Q78: ='.c12_d&s_hr'!Q46 -> 116850
A79: not reimbersable by hotel, but paid by lgh | B79: o | C79: hr_not_reimbursable | F79: 1528255 | G79: 474480 | I79: 1528255 | J79: ='.c12_d&s_hr'!J47 -> 474480 | K79: ='.c12_d&s_hr'!K47 -> 434880 | L79: ='.c12_d&s_hr'!L47 -> 474480 | M79: ='.c12_d&s_hr'!M47 -> 1104373.8 | N79: ='.c12_d&s_hr'!N47 -> 1104373.8 | O79: ='.c12_d&s_hr'!O47 -> 1104373.8 | P79: ='.c12_d&s_hr'!P47 -> 1104373.8 | Q79: ='.c12_d&s_hr'!Q47 -> 1104373.8
A80: only paid by c12 | B80: c | C80: hr_only_c12 | F80: 0 | G80: 0 | I80: 0 | J80: ='.c12_d&s_hr'!J48 -> 0 | K80: ='.c12_d&s_hr'!K48 -> 0 | L80: ='.c12_d&s_hr'!L48 -> 0 | M80: ='.c12_d&s_hr'!M48 -> 0 | N80: ='.c12_d&s_hr'!N48 -> 0 | O80: ='.c12_d&s_hr'!O48 -> 0 | P80: ='.c12_d&s_hr'!P48 -> 0 | Q80: ='.c12_d&s_hr'!Q48 -> 0

Sheet c12_bi&F
A2: Year | E2: 45657 | F2: 46022 | G2: 46112 | H2: 46203 | I2: 46022 | J2: 46112 | K2: 46203 | L2: 46295 | M2: 46387 | N2: 46477 | O2: 46568 | P2: 46660 | Q2: 46752
E3: actual | I3: i/o
B4: i/o | C4: field_name | D4: index
A5: LGH Fee Revenue | C5: lgh_fee_revenue_section
A6: [blank]
A7: [blank]
A8: [blank]
A9: [blank]
A10: [blank]
A11: [blank]
A12: [blank]
A13: [blank]
A14: [blank]
A15: [blank]
A16: [blank]
A17: [blank]
... A21: [blank]
A22: [blank] | F22: 0 | G22: 0 | I22: 0 | J22: 0 | K22: 0 | L22: 0 | M22: 0 | N22: 0 | O22: 0 | P22: 0 | Q22: 0
A23: [blank] | F23: 0 | G23: 0 | I23: 0 | J23: 0 | K23: 0 | L23: 0 | M23: 0 | N23: 0 | O23: 0 | P23: 0 | Q23: 0
A24: [blank] | F24: 0 | G24: 0 | I24: 0 | J24: 0 | K24: 0 | L24: 0 | M24: 0 | N24: 0 | O24: 0 | P24: 0 | Q24: 0
A25: Total LGH Fees Earned | B25: c | C25: total_fees_earned | F25: 0 | G25: 0 | I25: 0 | J25: =SUM(J22:J24) -> 0 | K25: =SUM(K22:K24) -> 0 | L25: =SUM(L22:L24) -> 0 | M25: =SUM(M22:M24) -> 0 | N25: =SUM(N22:N24) -> 0 | O25: =SUM(O22:O24) -> 0 | P25: =SUM(P22:P24) -> 0 | Q25: =SUM(Q22:Q24) -> 0
A27: Deferred Period Fee | B27: i | C27: deferred_fee | F27: 0 | G27: 0 | I27: 0 | J27: 0 | K27: 0 | L27: 0 | M27: 0 | N27: 0 | O27: 0 | P27: 0 | Q27: 0
A28: Paid Fee Accruals | B28: i | C28: paid_fee_accruals | F28: 0 | G28: 0 | I28: 0 | J28: 0 | K28: 0 | L28: 0 | M28: 0 | N28: 0 | O28: 0 | P28: 0 | Q28: 0
A29: Cumm. Balance Accrued Fee | B29: c | C29: cumm_accrued_fee | F29: 0 | G29: 0 | I29: 0 | J29: =+J27+I29+J28 -> 0 | K29: =+K27+J29+K28 -> 0 | L29: =+L27+K29+L28 -> 0 | M29: =+M27+L29+M28 -> 0 | N29: =+N27+M29+N28 -> 0 | O29: =+O27+N29+O28 -> 0 | P29: =+P27+O29+P28 -> 0 | Q29: =+Q27+P29+Q28 -> 0
A31: Paid Current Fees | B31: c | C31: paid_current_fees | F31: 0 | G31: 0 | I31: 0 | J31: =+J25+J27 -> 0 | K31: =+K25+K27 -> 0 | L31: =+L25+L27 -> 0 | M31: =+M25+M27 -> 0 | N31: =+N25+N27 -> 0 | O31: =+O25+O27 -> 0 | P31: =+P25+P27 -> 0 | Q31: =+Q25+Q27 -> 0
A32: Total Fees Paid | B32: c | C32: total_fees_paid | F32: 0 | G32: 0 | I32: 0 | J32: =+J28+J31 -> 0 | K32: =+K28+K31 -> 0 | L32: =+L28+L31 -> 0 | M32: =+M28+M31 -> 0 | N32: =+N28+N31 -> 0 | O32: =+O28+O31 -> 0 | P32: =+P28+P31 -> 0 | Q32: =+Q28+Q31 -> 0
A34: LGH Service Revenue | C34: lgh_service_revenue_section
A35: Bermuda PB | B35: i | C35: accting_fee | D35: pb | F35: 0 | G35: 15000 | I35: 0 | J35: =60000/4 -> 15000 | K35: =60000/4 -> 15000 | L35: =60000/4 -> 15000 | M35: =60000/4 -> 15000 | N35: 15000 | O35: 15000 | P35: 15000 | Q35: 15000
A36: 7f | B36: i | C36: accting_fee | D36: austin | F36: 0 | G36: 15000 | I36: 0 | J36: =60000/4 -> 15000 | K36: =60000/4 -> 15000 | L36: =60000/4 -> 15000 | M36: =60000/4 -> 15000 | N36: 15000 | O36: 15000 | P36: 15000 | Q36: 15000
A37: Turks | B37: i | C37: accting_fee | D37: turks | F37: 0 | G37: 0 | I37: 0 | J37: 0 | K37: 0 | L37: 0 | M37: 0 | N37: 0 | O37: 0 | P37: 0 | Q37: 0
A38: Elbow | B38: i | C38: accting_fee | D38: elbow | F38: 0 | G38: 0 | I38: 0 | J38: 0 | K38: 0 | L38: 0 | M38: 0 | N38: 0 | O38: 0 | P38: 0 | Q38: 0
A39: Frith | B39: i | C39: accting_fee | D39: fritholme | F39: 0 | G39: 0 | I39: 0 | J39: 0 | K39: =+J39 -> 0 | L39: =+K39 -> 0 | M39: =+L39 -> 0 | N39: 0 | O39: 0 | P39: 0 | Q39: 0
A40: [blank]
A41: [blank]
A42: [blank]
A43: [blank]
A44: [blank]
A45: [LSAT] | B45: i | C45: accting_fee | D45: lsat
A46: Total LGH Bi&F Service Revenue | B46: c | C46: total_service_revenue | F46: 0 | G46: 30000 | I46: 0 | J46: =SUM(J35:J45) -> 30000 | K46: =SUM(K35:K45) -> 30000 | L46: =SUM(L35:L45) -> 30000 | M46: =SUM(M35:M45) -> 30000 | N46: =SUM(N35:N45) -> 30000 | O46: =SUM(O35:O45) -> 30000 | P46: =SUM(P35:P45) -> 30000 | Q46: =SUM(Q35:Q45) -> 30000
A48: Deferred Period Fee | B48: i | C48: deferred_service_fee
A49: Paid Accruals | B49: i | C49: paid_service_accruals
A50: Cumm. Balance Accrued Service Fee | B50: c | C50: cumm_accrued_service_fee | F50: 0 | G50: 0 | I50: 0 | J50: =+J48+I50+J49 -> 0 | K50: =+K48+J50+K49 -> 0 | L50: =+L48+K50+L49 -> 0 | M50: =+M48+L50+M49 -> 0 | N50: =+N48+M50+N49 -> 0 | O50: =+O48+N50+O49 -> 0 | P50: =+P48+O50+P49 -> 0 | Q50: =+Q48+P50+Q49 -> 0
A52: Paid Current Service Fees | B52: c | C52: paid_current_service_fees | F52: 0 | G52: 30000 | I52: 0 | J52: =+J46+J48 -> 30000 | K52: =+K46+K48 -> 30000 | L52: =+L46+L48 -> 30000 | M52: =+M46+M48 -> 30000 | N52: =+N46+N48 -> 30000 | O52: =+O46+O48 -> 30000 | P52: =+P46+P48 -> 30000 | Q52: =+Q46+Q48 -> 30000
A53: Total Service Revenue Paid | B53: c | C53: total_service_revenue_paid | F53: 0 | G53: 30000 | I53: 0 | J53: =+J49+J52 -> 30000 | K53: =+K49+K52 -> 30000 | L53: =+L49+L52 -> 30000 | M53: =+M49+M52 -> 30000 | N53: =+N49+N52 -> 30000 | O53: =+O49+O52 -> 30000 | P53: =+P49+P52 -> 30000 | Q53: =+Q49+Q52 -> 30000
A55: LGH Chargebacks
A56: chargeback fee | B56: c | C56: chargeback_multiplier | F56: 1.0526316 | G56: 1.0526316 | I56: 1.0526316 | J56: =1/(1-'c12_inputs'!$E$7) -> 1.0526316 | K56: =1/(1-'c12_inputs'!$E$7) -> 1.0526316 | L56: =1/(1-'c12_inputs'!$E$7) -> 1.0526316 | M56: =1/(1-'c12_inputs'!$E$7) -> 1.0526316 | N56: =1/(1-'c12_inputs'!$E$7) -> 1.0526316 | O56: =1/(1-'c12_inputs'!$E$7) -> 1.0526316 | P56: =1/(1-'c12_inputs'!$E$7) -> 1.0526316 | Q56: =1/(1-'c12_inputs'!$E$7) -> 1.0526316
A57: reimbursable by hotels to LGH | B57: o | C57: reimbursable_by_hotels | F57: 0 | G57: 118080 | I57: 0 | J57: =IF(AND((G57<>""),(J$2<46204)),(G57),J78) -> 118080 | K57: =IF(AND((H57<>""),(K$2<46204)),(H57),K78) -> 118080 | L57: =IF(AND((I57<>""),(L$2<46204)),(I57),L78) -> 226080 | M57: =IF(AND((J57<>""),(M$2<46204)),(J57),M78) -> 314395 | N57: =IF(AND((K57<>""),(N$2<46204)),(K57),N78) -> 314395 | O57: =IF(AND((L57<>""),(O$2<46204)),(L57),O78) -> 314395 | P57: =IF(AND((M57<>""),(P$2<46204)),(M57),P78) -> 314395 | Q57: =IF(AND((N57<>""),(Q$2<46204)),(N57),Q78) -> 314395
A58: Total LGH Bi&F Charge Back chk | B58: c | C58: total_chargeback | F58: 0 | G58: 124294.74 | I58: 0 | J58: =J57*J56 -> 124294.74 | K58: =K57*K56 -> 124294.74 | L58: =L57*L56 -> 237978.95 | M58: =M57*M56 -> 330942.11 | N58: =N57*N56 -> 330942.11 | O58: =O57*O56 -> 330942.11 | P58: =P57*P56 -> 330942.11 | Q58: =Q57*Q56 -> 330942.11
A60: total LGH Bi&F revenue | B60: o | C60: total_lgh_bif_revenue | F60: 0 | G60: 154294.74 | I60: 0 | J60: =+J53+J32+J58 -> 154294.74 | K60: =+K53+K32+K58 -> 154294.74 | L60: =+L53+L32+L58 -> 267978.95 | M60: =+M53+M32+M58 -> 360942.11 | N60: =+N53+N32+N58 -> 360942.11 | O60: =+O53+O32+O58 -> 360942.11 | P60: =+P53+P32+P58 -> 360942.11 | Q60: =+Q53+Q32+Q58 -> 360942.11
A62: LGH Accounts Receivable Cumm. | B62: o | C62: lgh_ar_cumm | F62: 0 | G62: 0 | I62: 0 | J62: =+J29+J50 -> 0 | K62: =+K29+K50 -> 0 | L62: =+L29+L50 -> 0 | M62: =+M29+M50 -> 0 | N62: =+N29+N50 -> 0 | O62: =+O29+O50 -> 0 | P62: =+P29+P50 -> 0 | Q62: =+Q29+Q50 -> 0
A64: C12 Participation % | B64: c | C64: c12_participation_pct | F64: 0.35 | G64: 0.35 | I64: 0.35 | J64: ='c12_inputs'!$E$8 -> 0.35 | K64: ='c12_inputs'!$E$8 -> 0.35 | L64: ='c12_inputs'!$E$8 -> 0.35 | M64: ='c12_inputs'!$E$8 -> 0.35 | N64: ='c12_inputs'!$E$8 -> 0.35 | O64: ='c12_inputs'!$E$8 -> 0.35 | P64: ='c12_inputs'!$E$8 -> 0.35 | Q64: ='c12_inputs'!$E$8 -> 0.35
A65: pre-modification extra | B65: i | C65: pre_mod_extra_pct | F65: 0.15 | G65: 0 | I65: 0.15 | J65: 0 | K65: 0 | L65: 0 | M65: 0 | N65: 0 | O65: 0 | P65: 0 | Q65: 0
A66: catchup extra% | B66: i | C66: catchup_extra_pct | F66: 0.15 | G66: 0.15 | I66: 0.15 | J66: 0.15 | K66: 0.15 | L66: 0.15 | M66: 0.15 | N66: 0.15 | O66: 0.15 | P66: 0.15 | Q66: 0.15
A67: charge back percentrage | B67: c | C67: chargeback_pct | F67: 0.05 | G67: 0.05 | I67: 0.05 | J67: ='c12_inputs'!$E$7 -> 0.05 | K67: ='c12_inputs'!$E$7 -> 0.05 | L67: ='c12_inputs'!$E$7 -> 0.05 | M67: ='c12_inputs'!$E$7 -> 0.05 | N67: ='c12_inputs'!$E$7 -> 0.05 | O67: ='c12_inputs'!$E$7 -> 0.05 | P67: ='c12_inputs'!$E$7 -> 0.05 | Q67: ='c12_inputs'!$E$7 -> 0.05
A68: C12 Participation $ | B68: c | C68: c12_participation_amt | F68: 0 | G68: 10500 | I68: 0 | J68: =(J64+J65)*(J32+J52)+(J64+J66)*(J49+J29) -> 10500 | K68: =(K64+K65)*(K32+K52)+(K64+K66)*(K49+K29) -> 10500 | L68: =(L64+L65)*(L32+L52)+(L64+L66)*(L49+L29) -> 10500 | M68: =(M64+M65)*(M32+M52)+(M64+M66)*(M49+M29) -> 10500 | N68: =(N64+N65)*(N32+N52)+(N64+N66)*(N49+N29) -> 10500 | O68: =(O64+O65)*(O32+O52)+(O64+O66)*(O49+O29) -> 10500 | P68: =(P64+P65)*(P32+P52)+(P64+P66)*(P49+P29) -> 10500 | Q68: =(Q64+Q65)*(Q32+Q52)+(Q64+Q66)*(Q49+Q29) -> 10500
A69: chargebacks | B69: c | C69: chargeback_fees | F69: 0 | G69: 6214.7368 | I69: 0 | J69: =J58*J67 -> 6214.7368 | K69: =K58*K67 -> 6214.7368 | L69: =L58*L67 -> 11898.947 | M69: =M58*M67 -> 16547.105 | N69: =N58*N67 -> 16547.105 | O69: =O58*O67 -> 16547.105 | P69: =P58*P67 -> 16547.105 | Q69: =Q58*Q67 -> 16547.105
A70: Total C12 Bi&f revenue | B70: o | C70: total_c12_bif_revenue | F70: 0 | G70: 16714.737 | I70: 0 | J70: =J69+J68 -> 16714.737 | K70: =K69+K68 -> 16714.737 | L70: =L69+L68 -> 22398.947 | M70: =M69+M68 -> 27047.105 | N70: =N69+N68 -> 27047.105 | O70: =O69+O68 -> 27047.105 | P70: =P69+P68 -> 27047.105 | Q70: =Q69+Q68 -> 27047.105
A72: increase in accrued participation | B72: c | C72: increase_accrued_participation | F72: 0 | G72: 0 | I72: 0 | J72: =-(J64+J65)*(J27+J48) -> 0 | K72: =-(K64+K65)*(K27+K48) -> 0 | L72: =-(L64+L65)*(L27+L48) -> 0 | M72: =-(M64+M65)*(M27+M48) -> 0 | N72: =-(N64+N65)*(N27+N48) -> 0 | O72: =-(O64+O65)*(O27+O48) -> 0 | P72: =-(P64+P65)*(P27+P48) -> 0 | Q72: =-(Q64+Q65)*(Q27+Q48) -> 0
A73: decrease in accrued partipation | B73: c | C73: decrease_accrued_participation | F73: 0 | G73: 0 | I73: 0 | J73: =-(J64+J66)*(J28+J49) -> 0 | K73: =-(K64+K66)*(K28+K49) -> 0 | L73: =-(L64+L66)*(L28+L49) -> 0 | M73: =-(M64+M66)*(M28+M49) -> 0 | N73: =-(N64+N66)*(N28+N49) -> 0 | O73: =-(O64+O66)*(O28+O49) -> 0 | P73: =-(P64+P66)*(P28+P49) -> 0 | Q73: =-(Q64+Q66)*(Q28+Q49) -> 0
A74: Cumm. Total Accrued Participation | B74: o | C74: cumm_accrued_participation | F74: 0 | G74: 0 | I74: 0 | J74: =SUM(J72:J73)+I74 -> 0 | K74: =SUM(K72:K73)+J74 -> 0 | L74: =SUM(L72:L73)+K74 -> 0 | M74: =SUM(M72:M73)+L74 -> 0 | N74: =SUM(N72:N73)+M74 -> 0 | O74: =SUM(O72:O73)+N74 -> 0 | P74: =SUM(P72:P73)+O74 -> 0 | Q74: =SUM(Q72:Q73)+P74 -> 0
A76: from HR sheet
A77: Grand Total | B77: c | C77: hr_grand_total | F77: 602497.5 | G77: 296640 | I77: 602497.5 | J77: ='.c12_bi&f_hr'!J48 -> 296640 | K77: ='.c12_bi&f_hr'!K48 -> 477677.14 | L77: ='.c12_bi&f_hr'!L48 -> 672077.14 | M77: ='.c12_bi&f_hr'!M48 -> 1173394.6 | N77: ='.c12_bi&f_hr'!N48 -> 1173394.6 | O77: ='.c12_bi&f_hr'!O48 -> 1173394.6 | P77: ='.c12_bi&f_hr'!P48 -> 1173394.6 | Q77: ='.c12_bi&f_hr'!Q48 -> 1173394.6
A78: reimbersable to hotel | B78: o | C78: hr_reimbursable | F78: 154162.5 | G78: 118080 | I78: 154162.5 | J78: ='.c12_bi&f_hr'!J49 -> 118080 | K78: ='.c12_bi&f_hr'!K49 -> 118080 | L78: ='.c12_bi&f_hr'!L49 -> 226080 | M78: ='.c12_bi&f_hr'!M49 -> 314395 | N78: ='.c12_bi&f_hr'!N49 -> 314395 | O78: ='.c12_bi&f_hr'!O49 -> 314395 | P78: ='.c12_bi&f_hr'!P49 -> 314395 | Q78: ='.c12_bi&f_hr'!Q49 -> 314395
A79: not reimbersable by hotel, but paid by lgh | B79: o | C79: hr_not_reimbursable | F79: 448335 | G79: 178560 | I79: 448335 | J79: ='.c12_bi&f_hr'!J50 -> 178560 | K79: ='.c12_bi&f_hr'!K50 -> 359597.14 | L79: ='.c12_bi&f_hr'!L50 -> 445997.14 | M79: ='.c12_bi&f_hr'!M50 -> 858999.64 | N79: ='.c12_bi&f_hr'!N50 -> 858999.64 | O79: ='.c12_bi&f_hr'!O50 -> 858999.64 | P79: ='.c12_bi&f_hr'!P50 -> 858999.64 | Q79: ='.c12_bi&f_hr'!Q50 -> 858999.64
A80: only paid by c12 | B80: c | C80: hr_only_c12 | F80: 0 | G80: 0 | I80: 0 | J80: ='.c12_bi&f_hr'!J51 -> 0 | K80: ='.c12_bi&f_hr'!K51 -> 0 | L80: ='.c12_bi&f_hr'!L51 -> 0 | M80: ='.c12_bi&f_hr'!M51 -> 0 | N80: ='.c12_bi&f_hr'!N51 -> 0 | O80: ='.c12_bi&f_hr'!O51 -> 0 | P80: ='.c12_bi&f_hr'!P51 -> 0 | Q80: ='.c12_bi&f_hr'!Q51 -> 0

Sheet .c12_inputs.hr
B4: i/o | C4: field_name | D4: index
A5: ocBenefits | B5: i | C5: benefits_rate | D5: oc | E5: 0.021714286 | F5: adjusted down to assume sk doesn’t pay
A6: ocBonus Tax | B6: i | C6: bonus_tax_rate_actual | D6: oc | E6: 0.039
A8: hmBenefits | B8: i | C8: benefits_rate_actual | D8: hm | E8: 0.152
A9: hmBonus Tax | B9: i | C9: bonus_tax_rate_actual | D9: hm | E9: 0.039
A11: bfBenefits | B11: i | C11: benefits_rate_actual | D11: bif | E11: 0.152
A12: bfBonus Tax | B12: i | C12: bonus_tax_rate_actual | D12: bif | E12: 0.039
A15: dsBenefits | B15: i | C15: benefits_rate_actual | D15: ds | E15: 0.152
A16: dsBonus Tax | B16: i | C16: bonus_tax_rate_actual | D16: ds | E16: 0.039

Sheet .c12_oc_hr
A2: Year | E2: 45657 | F2: 46022 | G2: 46112 | H2: 46203 | I2: 46022 | J2: 46112 | K2: 46203 | L2: 46295 | M2: 46387 | N2: 46477 | O2: 46568 | P2: 46660 | Q2: 46752
E3: actual | I3: i/o
B4: i/o | C4: field_name | D4: index
A5: Base
A6: Managing Member (SK) | B6: i | C6: base_salary | D6: sk | F6: 375000 | G6: 375000 | I6: 375000 | J6: 375000 | K6: 375000 | L6: 375000 | M6: 375000 | N6: 375000 | O6: 375000 | P6: 375000 | Q6: 375000
A7: Philanropy senior exec (LM) (100%roots) | B7: i | C7: base_salary | D7: lm | F7: 0 | G7: 0 | I7: 0 | J7: 0 | K7: 0 | L7: 0 | M7: 0 | N7: 0 | O7: 0 | P7: 0 | Q7: 0
A8: Bookkeeper (DD) | B8: i | C8: base_salary | D8: dd | F8: 0 | G8: 25750 | I8: 0 | J8: 25750 | K8: 25750 | L8: 25750 | M8: 25750 | N8: 25750 | O8: 25750 | P8: 25750 | Q8: 25750
A9: Personal Assistant (CD) | B9: i | C9: base_salary | D9: cd | F9: 31250 | G9: 31250 | I9: 31250 | J9: 31250 | K9: 31250 | L9: 31250 | M9: 31250 | N9: 31250 | O9: 31250 | P9: 31250 | Q9: 31250
A10: philanthropy assist (100%roots) | B10: i | C10: base_salary | D10: philanthropy | F10: 0 | G10: 0 | I10: 0 | J10: 0 | K10: 0 | L10: 0 | M10: 0 | N10: 0 | O10: 0 | P10: 0 | Q10: 0
A11: TM (gone) | B11: i | C11: base_salary | D11: tm | F11: 87500 | G11: 87500 | I11: 87500 | J11: 87500 | K11: 0 | L11: 0 | M11: 0 | N11: 0 | O11: 0 | P11: 0 | Q11: 0
A12: Total | F12: 493750 | G12: 519500 | I12: 493750 | J12: =SUM(J6:J11) -> 519500 | K12: =SUM(K6:K11) -> 432000 | L12: =SUM(L6:L11) -> 432000 | M12: =SUM(M6:M11) -> 432000 | N12: =SUM(N6:N11) -> 432000 | O12: =SUM(O6:O11) -> 432000 | P12: =SUM(P6:P11) -> 432000 | Q12: =SUM(Q6:Q11) -> 432000
A13: Bonus
A14: =+A6 -> Managing Member (SK) | B14: i | C14: bonus | D14: sk | F14: 0 | G14: 0 | I14: 0 | J14: 0 | K14: 0 | L14: 0 | M14: 0 | N14: 0 | O14: 0 | P14: 0 | Q14: 0
A15: =+A7 -> Philanropy senior exec (LM) (100%roots) | B15: i | C15: bonus | D15: lm | F15: 0 | G15: 0 | I15: 0 | J15: 0 | K15: 0 | L15: 0 | M15: 0 | N15: 0 | O15: 0 | P15: 0 | Q15: 0
A16: =+A8 -> Bookkeeper (DD) | B16: i | C16: bonus | D16: dd | F16: 10000 | G16: 0 | I16: 10000 | J16: 0 | K16: 0 | L16: 0 | M16: 5000 | N16: 5000 | O16: 5000 | P16: 5000 | Q16: 5000
A17: =+A9 -> Personal Assistant (CD) | B17: i | C17: bonus | D17: cd | F17: 0 | G17: 0 | I17: 0 | J17: 0 | K17: 0 | L17: 0 | M17: 15000 | N17: 15000 | O17: 15000 | P17: 15000 | Q17: 15000
A18: =+A10 -> philanthropy assist (100%roots) | B18: i | C18: bonus | D18: philanthropy | F18: 0 | G18: 0 | I18: 0 | J18: 0 | K18: 0 | L18: 0 | M18: 0 | N18: 0 | O18: 0 | P18: 0 | Q18: 0
A19: =+A11 -> TM (gone) | B19: i | C19: bonus | D19: tm | F19: 0 | G19: 320000 | I19: 0 | J19: 320000 | K19: 0 | L19: 0 | M19: 500000 | N19: 500000 | O19: 500000 | P19: 500000 | Q19: 500000
A20: Total | F20: 10000 | G20: 320000 | I20: 10000 | J20: =SUM(J14:J19) -> 320000 | K20: =SUM(K14:K19) -> 0 | L20: =SUM(L14:L19) -> 0 | M20: =SUM(M14:M19) -> 520000 | N20: =SUM(N14:N19) -> 520000 | O20: =SUM(O14:O19) -> 520000 | P20: =SUM(P14:P19) -> 520000 | Q20: =SUM(Q14:Q19) -> 520000
A22: Total
A23: =+A6 -> Managing Member (SK) | B23: c | C23: total_salary | D23: sk | F23: 383142.86 | G23: 383142.86 | I23: 383142.86 | J23: =J6*(1+'.c12_inputs.hr'!$E$5)+(J14*(1+'.c12_inputs.hr'!$E$6)) -> 383142.86 | K23: =K6*(1+'.c12_inputs.hr'!$E$5)+(K14*(1+'.c12_inputs.hr'!$E$6)) -> 383142.86 | L23: =L6*(1+'.c12_inputs.hr'!$E$5)+(L14*(1+'.c12_inputs.hr'!$E$6)) -> 383142.86 | M23: =M6*(1+'.c12_inputs.hr'!$E$5)+(M14*(1+'.c12_inputs.hr'!$E$6)) -> 383142.86 | N23: =N6*(1+'.c12_inputs.hr'!$E$5)+(N14*(1+'.c12_inputs.hr'!$E$6)) -> 383142.86 | O23: =O6*(1+'.c12_inputs.hr'!$E$5)+(O14*(1+'.c12_inputs.hr'!$E$6)) -> 383142.86 | P23: =P6*(1+'.c12_inputs.hr'!$E$5)+(P14*(1+'.c12_inputs.hr'!$E$6)) -> 383142.86 | Q23: =Q6*(1+'.c12_inputs.hr'!$E$5)+(Q14*(1+'.c12_inputs.hr'!$E$6)) -> 383142.86
A24: =+A7 -> Philanropy senior exec (LM) (100%roots) | B24: c | C24: total_salary | D24: lm | F24: 0 | G24: 0 | I24: 0 | J24: =J7*(1+'.c12_inputs.hr'!$E$5)+(J15*(1+'.c12_inputs.hr'!$E$6)) -> 0 | K24: =K7*(1+'.c12_inputs.hr'!$E$5)+(K15*(1+'.c12_inputs.hr'!$E$6)) -> 0 | L24: =L7*(1+'.c12_inputs.hr'!$E$5)+(L15*(1+'.c12_inputs.hr'!$E$6)) -> 0 | M24: =M7*(1+'.c12_inputs.hr'!$E$5)+(M15*(1+'.c12_inputs.hr'!$E$6)) -> 0 | N24: =N7*(1+'.c12_inputs.hr'!$E$5)+(N15*(1+'.c12_inputs.hr'!$E$6)) -> 0 | O24: =O7*(1+'.c12_inputs.hr'!$E$5)+(O15*(1+'.c12_inputs.hr'!$E$6)) -> 0 | P24: =P7*(1+'.c12_inputs.hr'!$E$5)+(P15*(1+'.c12_inputs.hr'!$E$6)) -> 0 | Q24: =Q7*(1+'.c12_inputs.hr'!$E$5)+(Q15*(1+'.c12_inputs.hr'!$E$6)) -> 0
A25: =+A8 -> Bookkeeper (DD) | B25: c | C25: total_salary | D25: dd | F25: 10390 | G25: 26309.143 | I25: 10390 | J25: =J8*(1+'.c12_inputs.hr'!$E$5)+(J16*(1+'.c12_inputs.hr'!$E$6)) -> 26309.143 | K25: =K8*(1+'.c12_inputs.hr'!$E$5)+(K16*(1+'.c12_inputs.hr'!$E$6)) -> 26309.143 | L25: =L8*(1+'.c12_inputs.hr'!$E$5)+(L16*(1+'.c12_inputs.hr'!$E$6)) -> 26309.143 | M25: =M8*(1+'.c12_inputs.hr'!$E$5)+(M16*(1+'.c12_inputs.hr'!$E$6)) -> 31504.143 | N25: =N8*(1+'.c12_inputs.hr'!$E$5)+(N16*(1+'.c12_inputs.hr'!$E$6)) -> 31504.143 | O25: =O8*(1+'.c12_inputs.hr'!$E$5)+(O16*(1+'.c12_inputs.hr'!$E$6)) -> 31504.143 | P25: =P8*(1+'.c12_inputs.hr'!$E$5)+(P16*(1+'.c12_inputs.hr'!$E$6)) -> 31504.143 | Q25: =Q8*(1+'.c12_inputs.hr'!$E$5)+(Q16*(1+'.c12_inputs.hr'!$E$6)) -> 31504.143
A26: =+A9 -> Personal Assistant (CD) | B26: c | C26: total_salary | D26: cd | F26: 31928.571 | G26: 31928.571 | I26: 31928.571 | J26: =J9*(1+'.c12_inputs.hr'!$E$5)+(J17*(1+'.c12_inputs.hr'!$E$6)) -> 31928.571 | K26: =K9*(1+'.c12_inputs.hr'!$E$5)+(K17*(1+'.c12_inputs.hr'!$E$6)) -> 31928.571 | L26: =L9*(1+'.c12_inputs.hr'!$E$5)+(L17*(1+'.c12_inputs.hr'!$E$6)) -> 31928.571 | M26: =M9*(1+'.c12_inputs.hr'!$E$5)+(M17*(1+'.c12_inputs.hr'!$E$6)) -> 47513.571 | N26: =N9*(1+'.c12_inputs.hr'!$E$5)+(N17*(1+'.c12_inputs.hr'!$E$6)) -> 47513.571 | O26: =O9*(1+'.c12_inputs.hr'!$E$5)+(O17*(1+'.c12_inputs.hr'!$E$6)) -> 47513.571 | P26: =P9*(1+'.c12_inputs.hr'!$E$5)+(P17*(1+'.c12_inputs.hr'!$E$6)) -> 47513.571 | Q26: =Q9*(1+'.c12_inputs.hr'!$E$5)+(Q17*(1+'.c12_inputs.hr'!$E$6)) -> 47513.571
A27: =+A10 -> philanthropy assist (100%roots) | B27: c | C27: total_salary | D27: philanthropy | F27: 0 | G27: 0 | I27: 0 | J27: =J10*(1+'.c12_inputs.hr'!$E$5)+(J18*(1+'.c12_inputs.hr'!$E$6)) -> 0 | K27: =K10*(1+'.c12_inputs.hr'!$E$5)+(K18*(1+'.c12_inputs.hr'!$E$6)) -> 0 | L27: =L10*(1+'.c12_inputs.hr'!$E$5)+(L18*(1+'.c12_inputs.hr'!$E$6)) -> 0 | M27: =M10*(1+'.c12_inputs.hr'!$E$5)+(M18*(1+'.c12_inputs.hr'!$E$6)) -> 0 | N27: =N10*(1+'.c12_inputs.hr'!$E$5)+(N18*(1+'.c12_inputs.hr'!$E$6)) -> 0 | O27: =O10*(1+'.c12_inputs.hr'!$E$5)+(O18*(1+'.c12_inputs.hr'!$E$6)) -> 0 | P27: =P10*(1+'.c12_inputs.hr'!$E$5)+(P18*(1+'.c12_inputs.hr'!$E$6)) -> 0 | Q27: =Q10*(1+'.c12_inputs.hr'!$E$5)+(Q18*(1+'.c12_inputs.hr'!$E$6)) -> 0
A28: =+A11 -> TM (gone) | B28: c | C28: total_salary | D28: tm | F28: 89400 | G28: 421880 | I28: 89400 | J28: =J11*(1+'.c12_inputs.hr'!$E$5)+(J19*(1+'.c12_inputs.hr'!$E$6)) -> 421880 | K28: =K11*(1+'.c12_inputs.hr'!$E$5)+(K19*(1+'.c12_inputs.hr'!$E$6)) -> 0 | L28: =L11*(1+'.c12_inputs.hr'!$E$5)+(L19*(1+'.c12_inputs.hr'!$E$6)) -> 0 | M28: =M11*(1+'.c12_inputs.hr'!$E$5)+(M19*(1+'.c12_inputs.hr'!$E$6)) -> 519500 | N28: =N11*(1+'.c12_inputs.hr'!$E$5)+(N19*(1+'.c12_inputs.hr'!$E$6)) -> 519500 | O28: =O11*(1+'.c12_inputs.hr'!$E$5)+(O19*(1+'.c12_inputs.hr'!$E$6)) -> 519500 | P28: =P11*(1+'.c12_inputs.hr'!$E$5)+(P19*(1+'.c12_inputs.hr'!$E$6)) -> 519500 | Q28: =Q11*(1+'.c12_inputs.hr'!$E$5)+(Q19*(1+'.c12_inputs.hr'!$E$6)) -> 519500
A30: Grand Total | B30: o | C30: hr_grand_total | F30: 514861.43 | G30: 863260.57 | I30: 514861.43 | J30: =SUM(J23:J28) -> 863260.57 | K30: =SUM(K23:K28) -> 441380.57 | L30: =SUM(L23:L28) -> 441380.57 | M30: =SUM(M23:M28) -> 981660.57 | N30: =SUM(N23:N28) -> 981660.57 | O30: =SUM(O23:O28) -> 981660.57 | P30: =SUM(P23:P28) -> 981660.57 | Q30: =SUM(Q23:Q28) -> 981660.57
A31: reimbersable to hotel | B31: o | C31: hr_reimbursable | F31: 0 | G31: 0 | I31: 0 | J31: =SUMPRODUCT('.c12_alloc'!$H$6:$H$11,J23:J28) -> 0 | K31: =SUMPRODUCT('.c12_alloc'!$H$6:$H$11,K23:K28) -> 0 | L31: =SUMPRODUCT('.c12_alloc'!$H$6:$H$11,L23:L28) -> 0 | M31: =SUMPRODUCT('.c12_alloc'!$H$6:$H$11,M23:M28) -> 0 | N31: =SUMPRODUCT('.c12_alloc'!$H$6:$H$11,N23:N28) -> 0 | O31: =SUMPRODUCT('.c12_alloc'!$H$6:$H$11,O23:O28) -> 0 | P31: =SUMPRODUCT('.c12_alloc'!$H$6:$H$11,P23:P28) -> 0 | Q31: =SUMPRODUCT('.c12_alloc'!$H$6:$H$11,Q23:Q28) -> 0
A32: not reimbersable by hotel, but paid by lgh | B32: o | C32: hr_not_reimbursable | F32: 472542.86 | G32: 805022.86 | I32: 472542.86 | J32: =SUMPRODUCT('.c12_alloc'!$G$6:$G$11,J23:J28) -> 805022.86 | K32: =SUMPRODUCT('.c12_alloc'!$G$6:$G$11,K23:K28) -> 383142.86 | L32: =SUMPRODUCT('.c12_alloc'!$G$6:$G$11,L23:L28) -> 383142.86 | M32: =SUMPRODUCT('.c12_alloc'!$G$6:$G$11,M23:M28) -> 902642.86 | N32: =SUMPRODUCT('.c12_alloc'!$G$6:$G$11,N23:N28) -> 902642.86 | O32: =SUMPRODUCT('.c12_alloc'!$G$6:$G$11,O23:O28) -> 902642.86 | P32: =SUMPRODUCT('.c12_alloc'!$G$6:$G$11,P23:P28) -> 902642.86 | Q32: =SUMPRODUCT('.c12_alloc'!$G$6:$G$11,Q23:Q28) -> 902642.86
A33: only paid by c12 | B33: o | C33: hr_only_c12 | F33: 42318.571 | G33: 58237.714 | I33: 42318.571 | J33: =SUMPRODUCT('.c12_alloc'!$E$6:$E$11,J23:J28) -> 58237.714 | K33: =SUMPRODUCT('.c12_alloc'!$E$6:$E$11,K23:K28) -> 58237.714 | L33: =SUMPRODUCT('.c12_alloc'!$E$6:$E$11,L23:L28) -> 58237.714 | M33: =SUMPRODUCT('.c12_alloc'!$E$6:$E$11,M23:M28) -> 79017.714 | N33: =SUMPRODUCT('.c12_alloc'!$E$6:$E$11,N23:N28) -> 79017.714 | O33: =SUMPRODUCT('.c12_alloc'!$E$6:$E$11,O23:O28) -> 79017.714 | P33: =SUMPRODUCT('.c12_alloc'!$E$6:$E$11,P23:P28) -> 79017.714 | Q33: =SUMPRODUCT('.c12_alloc'!$E$6:$E$11,Q23:Q28) -> 79017.714

Sheet .c12_hm_hr
A2: Year | E2: 45657 | F2: 46022 | G2: 46112 | H2: 46203 | I2: 46022 | J2: 46112 | K2: 46203 | L2: 46295 | M2: 46387 | N2: 46477 | O2: 46568 | P2: 46660 | Q2: 46752
E3: actual | I3: i/o
B4: i/o | C4: field_name | D4: index
A5: base
A6: ACEO Loren Hotels (CE) | B6: i | C6: base_salary | D6: ce | F6: 125000 | G6: 125000 | I6: 125000 | J6: 125000 | K6: 125000 | L6: 125000 | M6: 125000 | N6: 125000 | O6: 125000 | P6: 125000 | Q6: 125000
A7: VP Operations (WS) | B7: i | C7: base_salary | D7: ws | F7: 68750 | G7: 72500 | I7: 68750 | J7: 72500 | K7: 72500 | L7: 72500 | M7: 72500 | N7: 72500 | O7: 72500 | P7: 72500 | Q7: 72500
A8: seniorS&Mexe (CL) | B8: i | C8: base_salary | D8: cl | F8: 0 | G8: 75000 | I8: 0 | J8: 75000 | K8: 75000 | L8: 75000 | M8: 75000 | N8: 75000 | O8: 75000 | P8: 75000 | Q8: 75000
A9: Senior Associate (RF) | B9: i | C9: base_salary | D9: rf | F9: 37500 | G9: 40000 | I9: 37500 | J9: 40000 | K9: 40000 | L9: 40000 | M9: 40000 | N9: 40000 | O9: 40000 | P9: 40000 | Q9: 40000
A10: associate (MT) | B10: i | C10: base_salary | D10: mt | F10: 27500 | G10: 27500 | I10: 27500 | J10: 27500 | K10: 27500 | L10: 27500 | M10: 27500 | N10: 27500 | O10: 27500 | P10: 27500 | Q10: 27500
A11: project manager | B11: i | C11: base_salary | D11: project | F11: 0 | G11: 0 | I11: 0 | J11: 0 | K11: 0 | L11: 37500 | M11: 37500 | N11: 37500 | O11: 37500 | P11: 37500 | Q11: 37500
A12: Total | F12: 258750 | G12: 340000 | I12: 258750 | J12: =SUM(J6:J11) -> 340000 | K12: =SUM(K6:K11) -> 340000 | L12: =SUM(L6:L11) -> 377500 | M12: =SUM(M6:M11) -> 377500 | N12: =SUM(N6:N11) -> 377500 | O12: =SUM(O6:O11) -> 377500 | P12: =SUM(P6:P11) -> 377500 | Q12: =SUM(Q6:Q11) -> 377500
A14: Bonus
A15: =A6 -> ACEO Loren Hotels (CE) | B15: i | C15: bonus | D15: ce | F15: 250000 | G15: 0 | I15: 250000 | J15: 0 | K15: 0 | L15: 0 | M15: 250000 | N15: 250000 | O15: 250000 | P15: 250000 | Q15: 250000
A16: =A7 -> VP Operations (WS) | B16: i | C16: bonus | D16: ws | F16: 115000 | G16: 0 | I16: 115000 | J16: 0 | K16: 0 | L16: 0 | M16: 75000 | N16: 75000 | O16: 75000 | P16: 75000 | Q16: 75000
A17: =A8 -> seniorS&Mexe (CL) | B17: i | C17: bonus | D17: cl | F17: 20000 | G17: 0 | I17: 20000 | J17: 0 | K17: 0 | L17: 0 | M17: 75000 | N17: 75000 | O17: 75000 | P17: 75000 | Q17: 75000
A18: =A9 -> Senior Associate (RF) | B18: i | C18: bonus | D18: rf | F18: 50000 | G18: 0 | I18: 50000 | J18: 0 | K18: 0 | L18: 0 | M18: 50000 | N18: 50000 | O18: 50000 | P18: 50000 | Q18: 50000
A19: =A10 -> associate (MT) | B19: i | C19: bonus | D19: mt | F19: 20000 | G19: 0 | I19: 20000 | J19: 0 | K19: 0 | L19: 0 | M19: 40000 | N19: 40000 | O19: 40000 | P19: 40000 | Q19: 40000
A20: =A11 -> project manager | B20: i | C20: bonus | D20: project | F20: 0 | G20: 0 | I20: 0 | J20: 0 | K20: 0 | L20: 0 | M20: 5000 | N20: 5000 | O20: 5000 | P20: 5000 | Q20: 5000
A21: Total | F21: 455000 | G21: 0 | I21: 455000 | J21: =SUM(J15:J20) -> 0 | K21: =SUM(K15:K20) -> 0 | L21: =SUM(L15:L20) -> 0 | M21: =SUM(M15:M20) -> 495000 | N21: =SUM(N15:N20) -> 495000 | O21: =SUM(O15:O20) -> 495000 | P21: =SUM(P15:P20) -> 495000 | Q21: =SUM(Q15:Q20) -> 495000
A23: Total Salaries
A24: =A15 -> ACEO Loren Hotels (CE) | B24: c | C24: total_salary | D24: ce | F24: 403750 | G24: 144000 | I24: 403750 | J24: =J6*(1+'.c12_inputs.hr'!$E$8)+(J15*(1+'.c12_inputs.hr'!$E$9)) -> 144000 | K24: =K6*(1+'.c12_inputs.hr'!$E$8)+(K15*(1+'.c12_inputs.hr'!$E$9)) -> 144000 | L24: =L6*(1+'.c12_inputs.hr'!$E$8)+(L15*(1+'.c12_inputs.hr'!$E$9)) -> 144000 | M24: =M6*(1+'.c12_inputs.hr'!$E$8)+(M15*(1+'.c12_inputs.hr'!$E$9)) -> 403750 | N24: =N6*(1+'.c12_inputs.hr'!$E$8)+(N15*(1+'.c12_inputs.hr'!$E$9)) -> 403750 | O24: =O6*(1+'.c12_inputs.hr'!$E$8)+(O15*(1+'.c12_inputs.hr'!$E$9)) -> 403750 | P24: =P6*(1+'.c12_inputs.hr'!$E$8)+(P15*(1+'.c12_inputs.hr'!$E$9)) -> 403750 | Q24: =Q6*(1+'.c12_inputs.hr'!$E$8)+(Q15*(1+'.c12_inputs.hr'!$E$9)) -> 403750
A25: =A16 -> VP Operations (WS) | B25: c | C25: total_salary | D25: ws | F25: 198685 | G25: 83520 | I25: 198685 | J25: =J7*(1+'.c12_inputs.hr'!$E$8)+(J16*(1+'.c12_inputs.hr'!$E$9)) -> 83520 | K25: =K7*(1+'.c12_inputs.hr'!$E$8)+(K16*(1+'.c12_inputs.hr'!$E$9)) -> 83520 | L25: =L7*(1+'.c12_inputs.hr'!$E$8)+(L16*(1+'.c12_inputs.hr'!$E$9)) -> 83520 | M25: =M7*(1+'.c12_inputs.hr'!$E$8)+(M16*(1+'.c12_inputs.hr'!$E$9)) -> 161445 | N25: =N7*(1+'.c12_inputs.hr'!$E$8)+(N16*(1+'.c12_inputs.hr'!$E$9)) -> 161445 | O25: =O7*(1+'.c12_inputs.hr'!$E$8)+(O16*(1+'.c12_inputs.hr'!$E$9)) -> 161445 | P25: =P7*(1+'.c12_inputs.hr'!$E$8)+(P16*(1+'.c12_inputs.hr'!$E$9)) -> 161445 | Q25: =Q7*(1+'.c12_inputs.hr'!$E$8)+(Q16*(1+'.c12_inputs.hr'!$E$9)) -> 161445
A26: =A17 -> seniorS&Mexe (CL) | B26: c | C26: total_salary | D26: cl | F26: 20780 | G26: 86400 | I26: 20780 | J26: =J8*(1+'.c12_inputs.hr'!$E$8)+(J17*(1+'.c12_inputs.hr'!$E$9)) -> 86400 | K26: =K8*(1+'.c12_inputs.hr'!$E$8)+(K17*(1+'.c12_inputs.hr'!$E$9)) -> 86400 | L26: =L8*(1+'.c12_inputs.hr'!$E$8)+(L17*(1+'.c12_inputs.hr'!$E$9)) -> 86400 | M26: =M8*(1+'.c12_inputs.hr'!$E$8)+(M17*(1+'.c12_inputs.hr'!$E$9)) -> 164325 | N26: =N8*(1+'.c12_inputs.hr'!$E$8)+(N17*(1+'.c12_inputs.hr'!$E$9)) -> 164325 | O26: =O8*(1+'.c12_inputs.hr'!$E$8)+(O17*(1+'.c12_inputs.hr'!$E$9)) -> 164325 | P26: =P8*(1+'.c12_inputs.hr'!$E$8)+(P17*(1+'.c12_inputs.hr'!$E$9)) -> 164325 | Q26: =Q8*(1+'.c12_inputs.hr'!$E$8)+(Q17*(1+'.c12_inputs.hr'!$E$9)) -> 164325
A27: =A18 -> Senior Associate (RF) | B27: c | C27: total_salary | D27: rf | F27: 95150 | G27: 46080 | I27: 95150 | J27: =J9*(1+'.c12_inputs.hr'!$E$8)+(J18*(1+'.c12_inputs.hr'!$E$9)) -> 46080 | K27: =K9*(1+'.c12_inputs.hr'!$E$8)+(K18*(1+'.c12_inputs.hr'!$E$9)) -> 46080 | L27: =L9*(1+'.c12_inputs.hr'!$E$8)+(L18*(1+'.c12_inputs.hr'!$E$9)) -> 46080 | M27: =M9*(1+'.c12_inputs.hr'!$E$8)+(M18*(1+'.c12_inputs.hr'!$E$9)) -> 98030 | N27: =N9*(1+'.c12_inputs.hr'!$E$8)+(N18*(1+'.c12_inputs.hr'!$E$9)) -> 98030 | O27: =O9*(1+'.c12_inputs.hr'!$E$8)+(O18*(1+'.c12_inputs.hr'!$E$9)) -> 98030 | P27: =P9*(1+'.c12_inputs.hr'!$E$8)+(P18*(1+'.c12_inputs.hr'!$E$9)) -> 98030 | Q27: =Q9*(1+'.c12_inputs.hr'!$E$8)+(Q18*(1+'.c12_inputs.hr'!$E$9)) -> 98030
A28: =A19 -> associate (MT) | B28: c | C28: total_salary | D28: mt | F28: 52460 | G28: 31680 | I28: 52460 | J28: =J10*(1+'.c12_inputs.hr'!$E$8)+(J19*(1+'.c12_inputs.hr'!$E$9)) -> 31680 | K28: =K10*(1+'.c12_inputs.hr'!$E$8)+(K19*(1+'.c12_inputs.hr'!$E$9)) -> 31680 | L28: =L10*(1+'.c12_inputs.hr'!$E$8)+(L19*(1+'.c12_inputs.hr'!$E$9)) -> 31680 | M28: =M10*(1+'.c12_inputs.hr'!$E$8)+(M19*(1+'.c12_inputs.hr'!$E$9)) -> 73240 | N28: =N10*(1+'.c12_inputs.hr'!$E$8)+(N19*(1+'.c12_inputs.hr'!$E$9)) -> 73240 | O28: =O10*(1+'.c12_inputs.hr'!$E$8)+(O19*(1+'.c12_inputs.hr'!$E$9)) -> 73240 | P28: =P10*(1+'.c12_inputs.hr'!$E$8)+(P19*(1+'.c12_inputs.hr'!$E$9)) -> 73240 | Q28: =Q10*(1+'.c12_inputs.hr'!$E$8)+(Q19*(1+'.c12_inputs.hr'!$E$9)) -> 73240
A29: =A20 -> project manager | B29: c | C29: total_salary | D29: project | F29: 0 | G29: 0 | I29: 0 | J29: =J11*(1+'.c12_inputs.hr'!$E$8)+(J20*(1+'.c12_inputs.hr'!$E$9)) -> 0 | K29: =K11*(1+'.c12_inputs.hr'!$E$8)+(K20*(1+'.c12_inputs.hr'!$E$9)) -> 0 | L29: =L11*(1+'.c12_inputs.hr'!$E$8)+(L20*(1+'.c12_inputs.hr'!$E$9)) -> 43200 | M29: =M11*(1+'.c12_inputs.hr'!$E$8)+(M20*(1+'.c12_inputs.hr'!$E$9)) -> 48395 | N29: =N11*(1+'.c12_inputs.hr'!$E$8)+(N20*(1+'.c12_inputs.hr'!$E$9)) -> 48395 | O29: =O11*(1+'.c12_inputs.hr'!$E$8)+(O20*(1+'.c12_inputs.hr'!$E$9)) -> 48395 | P29: =P11*(1+'.c12_inputs.hr'!$E$8)+(P20*(1+'.c12_inputs.hr'!$E$9)) -> 48395 | Q29: =Q11*(1+'.c12_inputs.hr'!$E$8)+(Q20*(1+'.c12_inputs.hr'!$E$9)) -> 48395
A31: Grand Total | B31: o | C31: hr_grand_total | F31: 770825 | G31: 391680 | I31: 770825 | J31: =SUM(J24:J29) -> 391680 | K31: =SUM(K24:K29) -> 391680 | L31: =SUM(L24:L29) -> 434880 | M31: =SUM(M24:M29) -> 949185 | N31: =SUM(N24:N29) -> 949185 | O31: =SUM(O24:O29) -> 949185 | P31: =SUM(P24:P29) -> 949185 | Q31: =SUM(Q24:Q29) -> 949185
A32: reimbersable to hotel | B32: o | C32: hr_reimbursable | F32: 367075 | G32: 247680 | I32: 367075 | J32: =SUMPRODUCT('.c12_alloc'!$H$15:$H$20,'.c12_hm_hr'!J$24:J$29) -> 247680 | K32: =SUMPRODUCT('.c12_alloc'!$H$15:$H$20,'.c12_hm_hr'!K$24:K$29) -> 247680 | L32: =SUMPRODUCT('.c12_alloc'!$H$15:$H$20,'.c12_hm_hr'!L$24:L$29) -> 290880 | M32: =SUMPRODUCT('.c12_alloc'!$H$15:$H$20,'.c12_hm_hr'!M$24:M$29) -> 545435 | N32: =SUMPRODUCT('.c12_alloc'!$H$15:$H$20,'.c12_hm_hr'!N$24:N$29) -> 545435 | O32: =SUMPRODUCT('.c12_alloc'!$H$15:$H$20,'.c12_hm_hr'!O$24:O$29) -> 545435 | P32: =SUMPRODUCT('.c12_alloc'!$H$15:$H$20,'.c12_hm_hr'!P$24:P$29) -> 545435 | Q32: =SUMPRODUCT('.c12_alloc'!$H$15:$H$20,'.c12_hm_hr'!Q$24:Q$29) -> 545435
A33: not reimbersable by hotel, but paid by lgh | B33: o | C33: hr_not_reimbursable | F33: 403750 | G33: 144000 | I33: 403750 | J33: =SUMPRODUCT('.c12_alloc'!$G$15:$G$20,'.c12_hm_hr'!J$24:J$29) -> 144000 | K33: =SUMPRODUCT('.c12_alloc'!$G$15:$G$20,'.c12_hm_hr'!K$24:K$29) -> 144000 | L33: =SUMPRODUCT('.c12_alloc'!$G$15:$G$20,'.c12_hm_hr'!L$24:L$29) -> 144000 | M33: =SUMPRODUCT('.c12_alloc'!$G$15:$G$20,'.c12_hm_hr'!M$24:M$29) -> 403750 | N33: =SUMPRODUCT('.c12_alloc'!$G$15:$G$20,'.c12_hm_hr'!N$24:N$29) -> 403750 | O33: =SUMPRODUCT('.c12_alloc'!$G$15:$G$20,'.c12_hm_hr'!O$24:O$29) -> 403750 | P33: =SUMPRODUCT('.c12_alloc'!$G$15:$G$20,'.c12_hm_hr'!P$24:P$29) -> 403750 | Q33: =SUMPRODUCT('.c12_alloc'!$G$15:$G$20,'.c12_hm_hr'!Q$24:Q$29) -> 403750
A34: only paid by c12 | B34: o | C34: hr_only_c12 | F34: 0 | G34: 0 | I34: 0 | J34: =SUMPRODUCT('.c12_alloc'!$E$15:$E$20,'.c12_hm_hr'!J$24:J$29) -> 0 | K34: =SUMPRODUCT('.c12_alloc'!$E$15:$E$20,'.c12_hm_hr'!K$24:K$29) -> 0 | L34: =SUMPRODUCT('.c12_alloc'!$E$15:$E$20,'.c12_hm_hr'!L$24:L$29) -> 0 | M34: =SUMPRODUCT('.c12_alloc'!$E$15:$E$20,'.c12_hm_hr'!M$24:M$29) -> 0 | N34: =SUMPRODUCT('.c12_alloc'!$E$15:$E$20,'.c12_hm_hr'!N$24:N$29) -> 0 | O34: =SUMPRODUCT('.c12_alloc'!$E$15:$E$20,'.c12_hm_hr'!O$24:O$29) -> 0 | P34: =SUMPRODUCT('.c12_alloc'!$E$15:$E$20,'.c12_hm_hr'!P$24:P$29) -> 0 | Q34: =SUMPRODUCT('.c12_alloc'!$E$15:$E$20,'.c12_hm_hr'!Q$24:Q$29) -> 0

Sheet .c12_d&s_hr
A2: Year | E2: 45657 | F2: 46022 | G2: 46112 | H2: 46203 | I2: 46022 | J2: 46112 | K2: 46203 | L2: 46295 | M2: 46387 | N2: 46477 | O2: 46568 | P2: 46660 | Q2: 46752
E3: actual | I3: i/o
B4: i/o | C4: field_name | D4: index
A5: base
A6: HODS (RB) | B6: i | C6: base_salary | D6: rb | F6: 87500 | G6: 187500 | I6: 87500 | J6: 187500 | K6: 187500 | L6: 187500 | M6: 187500 | N6: 187500 | O6: 187500 | P6: 187500 | Q6: 187500
A7: Project Executive (LS) (100%) | B7: i | C7: base_salary | D7: ls | F7: 46250 | G7: 46250 | I7: 46250 | J7: 46250 | K7: 46250 | L7: 46250 | M7: 46250 | N7: 46250 | O7: 46250 | P7: 46250 | Q7: 46250
A8: Project Manager (BD) (100%) | B8: i | C8: base_salary | D8: bd | F8: 27500 | G8: 28125 | I8: 27500 | J8: 28125 | K8: 28125 | L8: 28125 | M8: 28125 | N8: 28125 | O8: 28125 | P8: 28125 | Q8: 28125
A9: Counsel (KT) | B9: i | C9: base_salary | D9: kt | F9: 62500 | G9: 65000 | I9: 62500 | J9: 65000 | K9: 65000 | L9: 65000 | M9: 65000 | N9: 65000 | O9: 65000 | P9: 65000 | Q9: 65000
A10: Development Manager??? (alexi?) | B10: i | C10: base_salary | D10: development | F10: 0 | G10: 0 | I10: 0 | J10: 0 | K10: 0 | L10: 0 | M10: 0 | N10: 0 | O10: 0 | P10: 0 | Q10: 0
A11: Banker (tBD) | B11: i | C11: base_salary | D11: banker | F11: 75000 | G11: 0 | I11: 75000 | J11: 0 | K11: 0 | L11: 0 | M11: 0 | N11: 0 | O11: 0 | P11: 0 | Q11: 0
A12: Senior Design Manager (AM) | B12: i | C12: base_salary | D12: am | F12: 45000 | G12: 47500 | I12: 45000 | J12: 47500 | K12: 47500 | L12: 47500 | M12: 47500 | N12: 47500 | O12: 47500 | P12: 47500 | Q12: 47500
A13: Design Manager (AL) (gone) | B13: i | C13: base_salary | D13: al | F13: 32500 | G13: 34375 | I13: 32500 | J13: 34375 | K13: 0 | L13: 0 | M13: 0 | N13: 0 | O13: 0 | P13: 0 | Q13: 0
A14: new design manager (TBD) | B14: i | C14: base_salary | D14: tbd | F14: 0 | G14: 0 | I14: 0 | J14: 0 | K14: 0 | L14: 34375 | M14: 34375 | N14: 34375 | O14: 34375 | P14: 34375 | Q14: 34375
A15: FF&E (SB) | B15: i | C15: base_salary | D15: sb | F15: 27500 | G15: 27500 | I15: 27500 | J15: 27500 | K15: 27500 | L15: 27500 | M15: 27500 | N15: 27500 | O15: 27500 | P15: 27500 | Q15: 27500
A16: Senior Financial Analyst (KS) | B16: i | C16: base_salary | D16: ks | G16: 50000 | I16: 0 | J16: 50000 | K16: 50000 | L16: 50000 | M16: 50000 | N16: 50000 | O16: 50000 | P16: 50000 | Q16: 50000
A17: Total | F17: 403750 | G17: 486250 | I17: 403750 | J17: =SUM(J6:J16) -> 486250 | K17: =SUM(K6:K16) -> 451875 | L17: =SUM(L6:L16) -> 486250 | M17: =SUM(M6:M16) -> 486250 | N17: =SUM(N6:N16) -> 486250 | O17: =SUM(O6:O16) -> 486250 | P17: =SUM(P6:P16) -> 486250 | Q17: =SUM(Q6:Q16) -> 486250
A19: Bonus
A20: =+A6 -> HODS (RB) | B20: i | C20: bonus | D20: rb | F20: 685000 | G20: 0 | I20: 685000 | J20: 0 | K20: 0 | L20: 0 | M20: 250000 | N20: 250000 | O20: 250000 | P20: 250000 | Q20: 250000
A21: =+A7 -> Project Executive (LS) (100%) | B21: i | C21: bonus | D21: ls | F21: 20000 | G21: 0 | I21: 20000 | J21: 0 | K21: 0 | L21: 0 | M21: 15000 | N21: 15000 | O21: 15000 | P21: 15000 | Q21: 15000
A22: =+A8 -> Project Manager (BD) (100%) | B22: i | C22: bonus | D22: bd | F22: 17500 | G22: 0 | I22: 17500 | J22: 0 | K22: 0 | L22: 0 | M22: 15000 | N22: 15000 | O22: 15000 | P22: 15000 | Q22: 15000
A23: =+A9 -> Counsel (KT) | B23: i | C23: bonus | D23: kt | F23: 230000 | G23: 0 | I23: 230000 | J23: 0 | K23: 0 | L23: 0 | M23: 125000 | N23: 125000 | O23: 125000 | P23: 125000 | Q23: 125000
A24: =+A10 -> Development Manager??? (alexi?) | B24: i | C24: bonus | D24: development | F24: 0 | G24: 0 | I24: 0 | J24: 0 | K24: 0 | L24: 0 | M24: 0 | N24: 0 | O24: 0 | P24: 0 | Q24: 0
A25: =+A11 -> Banker (tBD) | B25: i | C25: bonus | D25: banker | F25: 50000 | G25: 0 | I25: 50000 | J25: 0 | K25: 0 | L25: 0 | M25: 100000 | N25: 100000 | O25: 100000 | P25: 100000 | Q25: 100000
A26: =+A12 -> Senior Design Manager (AM) | B26: i | C26: bonus | D26: am | F26: 65000 | G26: 0 | I26: 65000 | J26: 0 | K26: 0 | L26: 0 | M26: 55000 | N26: 55000 | O26: 55000 | P26: 55000 | Q26: 55000
A27: =+A13 -> Design Manager (AL) (gone) | B27: i | C27: bonus | D27: al | F27: 25000 | G27: 0 | I27: 25000 | J27: 0 | K27: 0 | L27: 0 | M27: 0 | N27: 0 | O27: 0 | P27: 0 | Q27: 0
A28: =+A14 -> new design manager (TBD) | B28: i | C28: bonus | D28: tbd | F28: 0 | G28: 0 | I28: 0 | J28: 0 | K28: 0 | L28: 0 | M28: 11250 | N28: 11250 | O28: 11250 | P28: 11250 | Q28: 11250
A29: =+A15 -> FF&E (SB) | B29: i | C29: bonus | D29: sb | F29: 0 | G29: 0 | I29: 0 | J29: 0 | K29: 0 | L29: 0 | M29: 15000 | N29: 15000 | O29: 15000 | P29: 15000 | Q29: 15000
A30: =+A16 -> Senior Financial Analyst (KS) | B30: i | C30: bonus | D30: ks | F30: 50000 | I30: 50000 | M30: 50000 | N30: 50000 | O30: 50000 | P30: 50000 | Q30: 50000
A31: Total | F31: 1142500 | G31: 0 | I31: 1142500 | J31: 0 | K31: 0 | L31: 0 | M31: 897500 | N31: 897500 | O31: 897500 | P31: 897500 | Q31: 897500
A33: Total Salaries
A34: =+A6 -> HODS (RB) | B34: c | C34: total_salary | D34: rb | F34: 812515 | G34: 216000 | I34: 812515 | J34: =+J6*(1+'.c12_inputs.hr'!$E$15)+(J20*(1+'.c12_inputs.hr'!$E$16)) -> 216000 | K34: =+K6*(1+'.c12_inputs.hr'!$E$15)+(K20*(1+'.c12_inputs.hr'!$E$16)) -> 216000 | L34: =+L6*(1+'.c12_inputs.hr'!$E$15)+(L20*(1+'.c12_inputs.hr'!$E$16)) -> 216000 | M34: =+M6*(1+'.c12_inputs.hr'!$E$15)+(M20*(1+'.c12_inputs.hr'!$E$16)) -> 475750 | N34: =+N6*(1+'.c12_inputs.hr'!$E$15)+(N20*(1+'.c12_inputs.hr'!$E$16)) -> 475750 | O34: =+O6*(1+'.c12_inputs.hr'!$E$15)+(O20*(1+'.c12_inputs.hr'!$E$16)) -> 475750 | P34: =+P6*(1+'.c12_inputs.hr'!$E$15)+(P20*(1+'.c12_inputs.hr'!$E$16)) -> 475750 | Q34: =+Q6*(1+'.c12_inputs.hr'!$E$15)+(Q20*(1+'.c12_inputs.hr'!$E$16)) -> 475750
A35: =+A7 -> Project Executive (LS) (100%) | B35: c | C35: total_salary | D35: ls | F35: 74060 | G35: 53280 | I35: 74060 | J35: =+J7*(1+'.c12_inputs.hr'!$E$15)+(J21*(1+'.c12_inputs.hr'!$E$16)) -> 53280 | K35: =+K7*(1+'.c12_inputs.hr'!$E$15)+(K21*(1+'.c12_inputs.hr'!$E$16)) -> 53280 | L35: =+L7*(1+'.c12_inputs.hr'!$E$15)+(L21*(1+'.c12_inputs.hr'!$E$16)) -> 53280 | M35: =+M7*(1+'.c12_inputs.hr'!$E$15)+(M21*(1+'.c12_inputs.hr'!$E$16)) -> 68865 | N35: =+N7*(1+'.c12_inputs.hr'!$E$15)+(N21*(1+'.c12_inputs.hr'!$E$16)) -> 68865 | O35: =+O7*(1+'.c12_inputs.hr'!$E$15)+(O21*(1+'.c12_inputs.hr'!$E$16)) -> 68865 | P35: =+P7*(1+'.c12_inputs.hr'!$E$15)+(P21*(1+'.c12_inputs.hr'!$E$16)) -> 68865 | Q35: =+Q7*(1+'.c12_inputs.hr'!$E$15)+(Q21*(1+'.c12_inputs.hr'!$E$16)) -> 68865
A36: =+A8 -> Project Manager (BD) (100%) | B36: c | C36: total_salary | D36: bd | F36: 49862.5 | G36: 32400 | I36: 49862.5 | J36: =+J8*(1+'.c12_inputs.hr'!$E$15)+(J22*(1+'.c12_inputs.hr'!$E$16)) -> 32400 | K36: =+K8*(1+'.c12_inputs.hr'!$E$15)+(K22*(1+'.c12_inputs.hr'!$E$16)) -> 32400 | L36: =+L8*(1+'.c12_inputs.hr'!$E$15)+(L22*(1+'.c12_inputs.hr'!$E$16)) -> 32400 | M36: =+M8*(1+'.c12_inputs.hr'!$E$15)+(M22*(1+'.c12_inputs.hr'!$E$16)) -> 47985 | N36: =+N8*(1+'.c12_inputs.hr'!$E$15)+(N22*(1+'.c12_inputs.hr'!$E$16)) -> 47985 | O36: =+O8*(1+'.c12_inputs.hr'!$E$15)+(O22*(1+'.c12_inputs.hr'!$E$16)) -> 47985 | P36: =+P8*(1+'.c12_inputs.hr'!$E$15)+(P22*(1+'.c12_inputs.hr'!$E$16)) -> 47985 | Q36: =+Q8*(1+'.c12_inputs.hr'!$E$15)+(Q22*(1+'.c12_inputs.hr'!$E$16)) -> 47985
A37: =+A9 -> Counsel (KT) | B37: c | C37: total_salary | D37: kt | F37: 310970 | G37: 74880 | I37: 310970 | J37: =+J9*(1+'.c12_inputs.hr'!$E$15)+(J23*(1+'.c12_inputs.hr'!$E$16)) -> 74880 | K37: =+K9*(1+'.c12_inputs.hr'!$E$15)+(K23*(1+'.c12_inputs.hr'!$E$16)) -> 74880 | L37: =+L9*(1+'.c12_inputs.hr'!$E$15)+(L23*(1+'.c12_inputs.hr'!$E$16)) -> 74880 | M37: =+M9*(1+'.c12_inputs.hr'!$E$15)+(M23*(1+'.c12_inputs.hr'!$E$16)) -> 204755 | N37: =+N9*(1+'.c12_inputs.hr'!$E$15)+(N23*(1+'.c12_inputs.hr'!$E$16)) -> 204755 | O37: =+O9*(1+'.c12_inputs.hr'!$E$15)+(O23*(1+'.c12_inputs.hr'!$E$16)) -> 204755 | P37: =+P9*(1+'.c12_inputs.hr'!$E$15)+(P23*(1+'.c12_inputs.hr'!$E$16)) -> 204755 | Q37: =+Q9*(1+'.c12_inputs.hr'!$E$15)+(Q23*(1+'.c12_inputs.hr'!$E$16)) -> 204755
A38: =+A10 -> Development Manager??? (alexi?) | B38: c | C38: total_salary | D38: development | F38: 0 | G38: 0 | I38: 0 | J38: =+J10*(1+'.c12_inputs.hr'!$E$15)+(J24*(1+'.c12_inputs.hr'!$E$16)) -> 0 | K38: =+K10*(1+'.c12_inputs.hr'!$E$15)+(K24*(1+'.c12_inputs.hr'!$E$16)) -> 0 | L38: =+L10*(1+'.c12_inputs.hr'!$E$15)+(L24*(1+'.c12_inputs.hr'!$E$16)) -> 0 | M38: =+M10*(1+'.c12_inputs.hr'!$E$15)+(M24*(1+'.c12_inputs.hr'!$E$16)) -> 0 | N38: =+N10*(1+'.c12_inputs.hr'!$E$15)+(N24*(1+'.c12_inputs.hr'!$E$16)) -> 0 | O38: =+O10*(1+'.c12_inputs.hr'!$E$15)+(O24*(1+'.c12_inputs.hr'!$E$16)) -> 0 | P38: =+P10*(1+'.c12_inputs.hr'!$E$15)+(P24*(1+'.c12_inputs.hr'!$E$16)) -> 0 | Q38: =+Q10*(1+'.c12_inputs.hr'!$E$15)+(Q24*(1+'.c12_inputs.hr'!$E$16)) -> 0
A39: =+A11 -> Banker (tBD) | B39: c | C39: total_salary | D39: banker | F39: 138350 | G39: 0 | I39: 138350 | J39: =+J11*(1+'.c12_inputs.hr'!$E$15)+(J25*(1+'.c12_inputs.hr'!$E$16)) -> 0 | K39: =+K11*(1+'.c12_inputs.hr'!$E$15)+(K25*(1+'.c12_inputs.hr'!$E$16)) -> 0 | L39: =+L11*(1+'.c12_inputs.hr'!$E$15)+(L25*(1+'.c12_inputs.hr'!$E$16)) -> 0 | M39: =+M11*(1+'.c12_inputs.hr'!$E$15)+(M25*(1+'.c12_inputs.hr'!$E$16)) -> 103900 | N39: =+N11*(1+'.c12_inputs.hr'!$E$15)+(N25*(1+'.c12_inputs.hr'!$E$16)) -> 103900 | O39: =+O11*(1+'.c12_inputs.hr'!$E$15)+(O25*(1+'.c12_inputs.hr'!$E$16)) -> 103900 | P39: =+P11*(1+'.c12_inputs.hr'!$E$15)+(P25*(1+'.c12_inputs.hr'!$E$16)) -> 103900 | Q39: =+Q11*(1+'.c12_inputs.hr'!$E$15)+(Q25*(1+'.c12_inputs.hr'!$E$16)) -> 103900
A40: =+A12 -> Senior Design Manager (AM) | B40: c | C40: total_salary | D40: am | F40: 119375 | G40: 54720 | I40: 119375 | J40: =+J12*(1+'.c12_inputs.hr'!$E$15)+(J26*(1+'.c12_inputs.hr'!$E$16)) -> 54720 | K40: =+K12*(1+'.c12_inputs.hr'!$E$15)+(K26*(1+'.c12_inputs.hr'!$E$16)) -> 54720 | L40: =+L12*(1+'.c12_inputs.hr'!$E$15)+(L26*(1+'.c12_inputs.hr'!$E$16)) -> 54720 | M40: =+M12*(1+'.c12_inputs.hr'!$E$15)+(M26*(1+'.c12_inputs.hr'!$E$16)) -> 111865 | N40: =+N12*(1+'.c12_inputs.hr'!$E$15)+(N26*(1+'.c12_inputs.hr'!$E$16)) -> 111865 | O40: =+O12*(1+'.c12_inputs.hr'!$E$15)+(O26*(1+'.c12_inputs.hr'!$E$16)) -> 111865 | P40: =+P12*(1+'.c12_inputs.hr'!$E$15)+(P26*(1+'.c12_inputs.hr'!$E$16)) -> 111865 | Q40: =+Q12*(1+'.c12_inputs.hr'!$E$15)+(Q26*(1+'.c12_inputs.hr'!$E$16)) -> 111865
A41: =+A13 -> Design Manager (AL) (gone) | B41: c | C41: total_salary | D41: al | F41: 63415 | G41: 39600 | I41: 63415 | J41: =+J13*(1+'.c12_inputs.hr'!$E$15)+(J27*(1+'.c12_inputs.hr'!$E$16)) -> 39600 | K41: =+K13*(1+'.c12_inputs.hr'!$E$15)+(K27*(1+'.c12_inputs.hr'!$E$16)) -> 0 | L41: =+L13*(1+'.c12_inputs.hr'!$E$15)+(L27*(1+'.c12_inputs.hr'!$E$16)) -> 0 | M41: =+M13*(1+'.c12_inputs.hr'!$E$15)+(M27*(1+'.c12_inputs.hr'!$E$16)) -> 0 | N41: =+N13*(1+'.c12_inputs.hr'!$E$15)+(N27*(1+'.c12_inputs.hr'!$E$16)) -> 0 | O41: =+O13*(1+'.c12_inputs.hr'!$E$15)+(O27*(1+'.c12_inputs.hr'!$E$16)) -> 0 | P41: =+P13*(1+'.c12_inputs.hr'!$E$15)+(P27*(1+'.c12_inputs.hr'!$E$16)) -> 0 | Q41: =+Q13*(1+'.c12_inputs.hr'!$E$15)+(Q27*(1+'.c12_inputs.hr'!$E$16)) -> 0
A42: =+A14 -> new design manager (TBD) | B42: c | C42: total_salary | D42: tbd | F42: 0 | G42: 0 | I42: 0 | J42: =+J14*(1+'.c12_inputs.hr'!$E$15)+(J28*(1+'.c12_inputs.hr'!$E$16)) -> 0 | K42: =+K14*(1+'.c12_inputs.hr'!$E$15)+(K28*(1+'.c12_inputs.hr'!$E$16)) -> 0 | L42: =+L14*(1+'.c12_inputs.hr'!$E$15)+(L28*(1+'.c12_inputs.hr'!$E$16)) -> 39600 | M42: =+M14*(1+'.c12_inputs.hr'!$E$15)+(M28*(1+'.c12_inputs.hr'!$E$16)) -> 51288.75 | N42: =+N14*(1+'.c12_inputs.hr'!$E$15)+(N28*(1+'.c12_inputs.hr'!$E$16)) -> 51288.75 | O42: =+O14*(1+'.c12_inputs.hr'!$E$15)+(O28*(1+'.c12_inputs.hr'!$E$16)) -> 51288.75 | P42: =+P14*(1+'.c12_inputs.hr'!$E$15)+(P28*(1+'.c12_inputs.hr'!$E$16)) -> 51288.75 | Q42: =+Q14*(1+'.c12_inputs.hr'!$E$15)+(Q28*(1+'.c12_inputs.hr'!$E$16)) -> 51288.75
A43: =+A15 -> FF&E (SB) | B43: c | C43: total_salary | D43: sb | F43: 31680 | G43: 31680 | I43: 31680 | J43: =+J15*(1+'.c12_inputs.hr'!$E$15)+(J29*(1+'.c12_inputs.hr'!$E$16)) -> 31680 | K43: =+K15*(1+'.c12_inputs.hr'!$E$15)+(K29*(1+'.c12_inputs.hr'!$E$16)) -> 31680 | L43: =+L15*(1+'.c12_inputs.hr'!$E$15)+(L29*(1+'.c12_inputs.hr'!$E$16)) -> 31680 | M43: =+M15*(1+'.c12_inputs.hr'!$E$15)+(M29*(1+'.c12_inputs.hr'!$E$16)) -> 47265 | N43: =+N15*(1+'.c12_inputs.hr'!$E$15)+(N29*(1+'.c12_inputs.hr'!$E$16)) -> 47265 | O43: =+O15*(1+'.c12_inputs.hr'!$E$15)+(O29*(1+'.c12_inputs.hr'!$E$16)) -> 47265 | P43: =+P15*(1+'.c12_inputs.hr'!$E$15)+(P29*(1+'.c12_inputs.hr'!$E$16)) -> 47265 | Q43: =+Q15*(1+'.c12_inputs.hr'!$E$15)+(Q29*(1+'.c12_inputs.hr'!$E$16)) -> 47265
A44: =+A16 -> Senior Financial Analyst (KS) | B44: c | C44: total_salary | D44: ks | F44: 51950 | G44: 57600 | I44: 51950 | J44: =+J16*(1+'.c12_inputs.hr'!$E$15)+(J30*(1+'.c12_inputs.hr'!$E$16)) -> 57600 | K44: =+K16*(1+'.c12_inputs.hr'!$E$15)+(K30*(1+'.c12_inputs.hr'!$E$16)) -> 57600 | L44: =+L16*(1+'.c12_inputs.hr'!$E$15)+(L30*(1+'.c12_inputs.hr'!$E$16)) -> 57600 | M44: =+M16*(1+'.c12_inputs.hr'!$E$15)+(M30*(1+'.c12_inputs.hr'!$E$16)) -> 109550 | N44: =+N16*(1+'.c12_inputs.hr'!$E$15)+(N30*(1+'.c12_inputs.hr'!$E$16)) -> 109550 | O44: =+O16*(1+'.c12_inputs.hr'!$E$15)+(O30*(1+'.c12_inputs.hr'!$E$16)) -> 109550 | P44: =+P16*(1+'.c12_inputs.hr'!$E$15)+(P30*(1+'.c12_inputs.hr'!$E$16)) -> 109550 | Q44: =+Q16*(1+'.c12_inputs.hr'!$E$15)+(Q30*(1+'.c12_inputs.hr'!$E$16)) -> 109550
A45: Grand Total | B45: o | C45: hr_grand_total | F45: 1652177.5 | G45: 560160 | I45: 1652177.5 | J45: =SUM(J34:J44) -> 560160 | K45: =SUM(K34:K44) -> 520560 | L45: =SUM(L34:L44) -> 560160 | M45: =SUM(M34:M44) -> 1221223.8 | N45: =SUM(N34:N44) -> 1221223.8 | O45: =SUM(O34:O44) -> 1221223.8 | P45: =SUM(P34:P44) -> 1221223.8 | Q45: =SUM(Q34:Q44) -> 1221223.8
A46: reimbersable to hotel | B46: o | C46: hr_reimbursable | F46: 123922.5 | G46: 85680 | I46: 123922.5 | J46: =SUMPRODUCT('.c12_alloc'!$H$24:$H$34,'.c12_d&s_hr'!J$34:J$44) -> 85680 | K46: =SUMPRODUCT('.c12_alloc'!$H$24:$H$34,'.c12_d&s_hr'!K$34:K$44) -> 85680 | L46: =SUMPRODUCT('.c12_alloc'!$H$24:$H$34,'.c12_d&s_hr'!L$34:L$44) -> 85680 | M46: =SUMPRODUCT('.c12_alloc'!$H$24:$H$34,'.c12_d&s_hr'!M$34:M$44) -> 116850 | N46: =SUMPRODUCT('.c12_alloc'!$H$24:$H$34,'.c12_d&s_hr'!N$34:N$44) -> 116850 | O46: =SUMPRODUCT('.c12_alloc'!$H$24:$H$34,'.c12_d&s_hr'!O$34:O$44) -> 116850 | P46: =SUMPRODUCT('.c12_alloc'!$H$24:$H$34,'.c12_d&s_hr'!P$34:P$44) -> 116850 | Q46: =SUMPRODUCT('.c12_alloc'!$H$24:$H$34,'.c12_d&s_hr'!Q$34:Q$44) -> 116850
A47: not reimbersable by hotel, but paid by lgh | B47: o | C47: hr_not_reimbursable | F47: 1528255 | G47: 474480 | I47: 1528255 | J47: =SUMPRODUCT('.c12_alloc'!$G$24:$G$34,'.c12_d&s_hr'!J$34:J$44) -> 474480 | K47: =SUMPRODUCT('.c12_alloc'!$G$24:$G$34,'.c12_d&s_hr'!K$34:K$44) -> 434880 | L47: =SUMPRODUCT('.c12_alloc'!$G$24:$G$34,'.c12_d&s_hr'!L$34:L$44) -> 474480 | M47: =SUMPRODUCT('.c12_alloc'!$G$24:$G$34,'.c12_d&s_hr'!M$34:M$44) -> 1104373.8 | N47: =SUMPRODUCT('.c12_alloc'!$G$24:$G$34,'.c12_d&s_hr'!N$34:N$44) -> 1104373.8 | O47: =SUMPRODUCT('.c12_alloc'!$G$24:$G$34,'.c12_d&s_hr'!O$34:O$44) -> 1104373.8 | P47: =SUMPRODUCT('.c12_alloc'!$G$24:$G$34,'.c12_d&s_hr'!P$34:P$44) -> 1104373.8 | Q47: =SUMPRODUCT('.c12_alloc'!$G$24:$G$34,'.c12_d&s_hr'!Q$34:Q$44) -> 1104373.8
A48: only paid by c12 | B48: o | C48: hr_only_c12 | F48: 0 | G48: 0 | I48: 0 | J48: =SUMPRODUCT('.c12_alloc'!$E$24:$E$34,'.c12_d&s_hr'!J$34:J$44) -> 0 | K48: =SUMPRODUCT('.c12_alloc'!$E$24:$E$34,'.c12_d&s_hr'!K$34:K$44) -> 0 | L48: =SUMPRODUCT('.c12_alloc'!$E$24:$E$34,'.c12_d&s_hr'!L$34:L$44) -> 0 | M48: =SUMPRODUCT('.c12_alloc'!$E$24:$E$34,'.c12_d&s_hr'!M$34:M$44) -> 0 | N48: =SUMPRODUCT('.c12_alloc'!$E$24:$E$34,'.c12_d&s_hr'!N$34:N$44) -> 0 | O48: =SUMPRODUCT('.c12_alloc'!$E$24:$E$34,'.c12_d&s_hr'!O$34:O$44) -> 0 | P48: =SUMPRODUCT('.c12_alloc'!$E$24:$E$34,'.c12_d&s_hr'!P$34:P$44) -> 0 | Q48: =SUMPRODUCT('.c12_alloc'!$E$24:$E$34,'.c12_d&s_hr'!Q$34:Q$44) -> 0

Sheet .c12_bi&f_hr
A2: Year | E2: 45657 | F2: 46022 | G2: 46112 | H2: 46203 | I2: 46022 | J2: 46112 | K2: 46203 | L2: 46295 | M2: 46387 | N2: 46477 | O2: 46568 | P2: 46660 | Q2: 46752
E3: actual | I3: i/o
B4: i/o | C4: field_name | D4: index
A5: base
A6: HOBI (CW) | B6: i | C6: base_salary | D6: cw | F6: 93750 | G6: 93750 | I6: 93750 | J6: 93750 | K6: 93750 | L6: 93750 | M6: 93750 | N6: 93750 | O6: 93750 | P6: 93750 | Q6: 93750
A7: CFO (ZS) | B7: i | C7: base_salary | D7: zs | F7: 0 | G7: 0 | I7: 0 | J7: 0 | K7: 125000 | L7: 125000 | M7: 125000 | N7: 125000 | O7: 125000 | P7: 125000 | Q7: 125000
A8: Financial Analyst (NR) | B8: i | C8: base_salary | D8: nr | F8: 21250 | G8: 21250 | I8: 21250 | J8: 21250 | K8: 21250 | L8: 21250 | M8: 21250 | N8: 21250 | O8: 21250 | P8: 21250 | Q8: 21250
A9: Fin Controls (TB) - 100% | B9: i | C9: base_salary | D9: tb | F9: 46250 | G9: 48750 | I9: 46250 | J9: 48750 | K9: 48750 | L9: 48750 | M9: 48750 | N9: 48750 | O9: 48750 | P9: 48750 | Q9: 48750
A10: Administrative Assistant (AM) | B10: i | C10: base_salary | D10: am | F10: 31250 | G10: 0 | I10: 31250 | J10: 0 | K10: 0 | L10: 0 | M10: 0 | N10: 0 | O10: 0 | P10: 0 | Q10: 0
A11: Administrative Assistant (PT) | B11: i | C11: base_salary | D11: pt | F11: 0 | G11: 0 | I11: 0 | J11: 0 | K11: 36250 | L11: 36250 | M11: 36250 | N11: 36250 | O11: 36250 | P11: 36250 | Q11: 36250
A12: Financial Director (DV) - 100% | B12: i | C12: base_salary | D12: dv | F12: 53750 | G12: 53750 | I12: 53750 | J12: 53750 | K12: 53750 | L12: 53750 | M12: 53750 | N12: 53750 | O12: 53750 | P12: 53750 | Q12: 53750
A13: IM (TW) | B13: i | C13: base_salary | D13: tw | F13: 40000 | G13: 40000 | I13: 40000 | J13: 40000 | K13: 40000 | L13: 40000 | M13: 40000 | N13: 40000 | O13: 40000 | P13: 40000 | Q13: 40000
A14: HR (100%) | B14: i | C14: base_salary | D14: hr | F14: 0 | G14: 0 | I14: 0 | J14: 0 | K14: 0 | L14: 37500 | M14: 37500 | N14: 37500 | O14: 37500 | P14: 37500 | Q14: 37500
A15: Legal (100%) | B15: i | C15: base_salary | D15: legal | F15: 0 | G15: 0 | I15: 0 | J15: 0 | K15: 0 | L15: 56250 | M15: 56250 | N15: 56250 | O15: 56250 | P15: 56250 | Q15: 56250
A16: Tech1 | B16: i | C16: base_salary | D16: tech1 | F16: 0 | G16: 0 | I16: 0 | J16: 0 | K16: 0 | L16: 56250 | M16: 56250 | N16: 56250 | O16: 56250 | P16: 56250 | Q16: 56250
A17: Tech2 | B17: i | C17: base_salary | D17: tech2 | F17: 0 | G17: 0 | I17: 0 | J17: 0 | K17: 0 | L17: 18750 | M17: 18750 | N17: 18750 | O17: 18750 | P17: 18750 | Q17: 18750
A18: Total | F18: 286250 | G18: 257500 | I18: 286250 | J18: =SUM(J6:J17) -> 257500 | K18: =SUM(K6:K17) -> 418750 | L18: =SUM(L6:L17) -> 587500 | M18: =SUM(M6:M17) -> 587500 | N18: =SUM(N6:N17) -> 587500 | O18: =SUM(O6:O17) -> 587500 | P18: =SUM(P6:P17) -> 587500 | Q18: =SUM(Q6:Q17) -> 587500
A20: Bonus
A21: =+A6 -> HOBI (CW) | B21: i | C21: bonus | D21: cw | F21: 125000 | G21: 0 | I21: 125000 | J21: 0 | K21: 0 | L21: 0 | M21: 225000 | N21: 225000 | O21: 225000 | P21: 225000 | Q21: 225000
A22: =+A7 -> CFO (ZS) | B22: i | C22: bonus | D22: zs | F22: 60000 | G22: 0 | I22: 60000 | J22: 0 | K22: 0 | L22: 0 | M22: 100000 | N22: 100000 | O22: 100000 | P22: 100000 | Q22: 100000
A23: =+A8 -> Financial Analyst (NR) | B23: i | C23: bonus | D23: nr | F23: 5000 | G23: 0 | I23: 5000 | J23: 0 | K23: 0 | L23: 0 | M23: 7500 | N23: 7500 | O23: 7500 | P23: 7500 | Q23: 7500
A24: =+A9 -> Fin Controls (TB) - 100% | B24: i | C24: bonus | D24: tb | F24: 17500 | G24: 0 | I24: 17500 | J24: 0 | K24: 0 | L24: 0 | M24: 15000 | N24: 15000 | O24: 15000 | P24: 15000 | Q24: 15000
A25: =+A10 -> Administrative Assistant (AM) | B25: i | C25: bonus | D25: am | F25: 10000 | G25: 0 | I25: 10000 | J25: 0 | K25: 0 | L25: 0 | M25: 0 | N25: 0 | O25: 0 | P25: 0 | Q25: 0
A26: =+A11 -> Administrative Assistant (PT) | B26: i | C26: bonus | D26: pt | F26: 0 | G26: 0 | I26: 0 | J26: 0 | K26: 0 | L26: 0 | M26: 10000 | N26: 10000 | O26: 10000 | P26: 10000 | Q26: 10000
A27: =+A12 -> Financial Director (DV) - 100% | B27: i | C27: bonus | D27: dv | F27: 20000 | G27: 0 | I27: 20000 | J27: 0 | K27: 0 | L27: 0 | M27: 40000 | N27: 40000 | O27: 40000 | P27: 40000 | Q27: 40000
A28: =+A13 -> IM (TW) | B28: i | C28: bonus | D28: tw | F28: 25000 | G28: 0 | I28: 25000 | J28: 0 | K28: 0 | L28: 0 | M28: 25000 | N28: 25000 | O28: 25000 | P28: 25000 | Q28: 25000
A29: =+A14 -> HR (100%) | B29: i | C29: bonus | D29: hr | F29: 0 | G29: 0 | I29: 0 | J29: 0 | K29: 0 | L29: 0 | M29: 15000 | N29: 15000 | O29: 15000 | P29: 15000 | Q29: 15000
A30: =+A15 -> Legal (100%) | B30: i | C30: bonus | D30: legal | F30: 0 | G30: 0 | I30: 0 | J30: 0 | K30: 0 | L30: 0 | M30: 15000 | N30: 15000 | O30: 15000 | P30: 15000 | Q30: 15000
A31: =+A16 -> Tech1 | B31: i | C31: bonus | D31: tech1 | F31: 0 | G31: 0 | I31: 0 | J31: 0 | K31: 0 | L31: 0 | M31: 15000 | N31: 15000 | O31: 15000 | P31: 15000 | Q31: 15000
A32: =+A17 -> Tech2 | B32: i | C32: bonus | D32: tech2 | F32: 0 | G32: 0 | I32: 0 | J32: 0 | K32: 0 | L32: 0 | M32: 15000 | N32: 15000 | O32: 15000 | P32: 15000 | Q32: 15000
A33: Total | F33: 262500 | G33: 0 | I33: 262500 | J33: =SUM(J21:J32) -> 0 | K33: =SUM(K21:K32) -> 0 | L33: =SUM(L21:L32) -> 0 | M33: =SUM(M21:M32) -> 482500 | N33: =SUM(N21:N32) -> 482500 | O33: =SUM(O21:O32) -> 482500 | P33: =SUM(P21:P32) -> 482500 | Q33: =SUM(Q21:Q32) -> 482500
A35: Total Salaries
A36: =+A6 -> HOBI (CW) | B36: c | C36: total_salary | D36: cw | F36: 237875 | G36: 108000 | I36: 237875 | J36: =+J6*(1+'.c12_inputs.hr'!$E$15)+(J21*(1+'.c12_inputs.hr'!$E$16)) -> 108000 | K36: =+K6*(1+'.c12_inputs.hr'!$E$15)+(K21*(1+'.c12_inputs.hr'!$E$16)) -> 108000 | L36: =+L6*(1+'.c12_inputs.hr'!$E$15)+(L21*(1+'.c12_inputs.hr'!$E$16)) -> 108000 | M36: =+M6*(1+'.c12_inputs.hr'!$E$15)+(M21*(1+'.c12_inputs.hr'!$E$16)) -> 341775 | N36: =+N6*(1+'.c12_inputs.hr'!$E$15)+(N21*(1+'.c12_inputs.hr'!$E$16)) -> 341775 | O36: =+O6*(1+'.c12_inputs.hr'!$E$15)+(O21*(1+'.c12_inputs.hr'!$E$16)) -> 341775 | P36: =+P6*(1+'.c12_inputs.hr'!$E$15)+(P21*(1+'.c12_inputs.hr'!$E$16)) -> 341775 | Q36: =+Q6*(1+'.c12_inputs.hr'!$E$15)+(Q21*(1+'.c12_inputs.hr'!$E$16)) -> 341775
A37: =+A7 -> CFO (ZS) | B37: c | C37: total_salary | D37: zs | F37: 62340 | G37: 0 | I37: 62340 | J37: =+J7*(1+'.c12_inputs.hr'!$E$15)+(J22*(1+'.c12_inputs.hr'!$E$16)) -> 0 | K37: =+K7*(1+'.c12_inputs.hr'!$E$15)+(K22*(1+'.c12_inputs.hr'!$E$16)) -> 144000 | L37: =+L7*(1+'.c12_inputs.hr'!$E$15)+(L22*(1+'.c12_inputs.hr'!$E$16)) -> 144000 | M37: =+M7*(1+'.c12_inputs.hr'!$E$15)+(M22*(1+'.c12_inputs.hr'!$E$16)) -> 247900 | N37: =+N7*(1+'.c12_inputs.hr'!$E$15)+(N22*(1+'.c12_inputs.hr'!$E$16)) -> 247900 | O37: =+O7*(1+'.c12_inputs.hr'!$E$15)+(O22*(1+'.c12_inputs.hr'!$E$16)) -> 247900 | P37: =+P7*(1+'.c12_inputs.hr'!$E$15)+(P22*(1+'.c12_inputs.hr'!$E$16)) -> 247900 | Q37: =+Q7*(1+'.c12_inputs.hr'!$E$15)+(Q22*(1+'.c12_inputs.hr'!$E$16)) -> 247900
A38: =+A8 -> Financial Analyst (NR) | B38: c | C38: total_salary | D38: nr | F38: 29675 | G38: 24480 | I38: 29675 | J38: =+J8*(1+'.c12_inputs.hr'!$E$15)+(J23*(1+'.c12_inputs.hr'!$E$16)) -> 24480 | K38: =+K8*(1+'.c12_inputs.hr'!$E$15)+(K23*(1+'.c12_inputs.hr'!$E$16)) -> 24480 | L38: =+L8*(1+'.c12_inputs.hr'!$E$15)+(L23*(1+'.c12_inputs.hr'!$E$16)) -> 24480 | M38: =+M8*(1+'.c12_inputs.hr'!$E$15)+(M23*(1+'.c12_inputs.hr'!$E$16)) -> 32272.5 | N38: =+N8*(1+'.c12_inputs.hr'!$E$15)+(N23*(1+'.c12_inputs.hr'!$E$16)) -> 32272.5 | O38: =+O8*(1+'.c12_inputs.hr'!$E$15)+(O23*(1+'.c12_inputs.hr'!$E$16)) -> 32272.5 | P38: =+P8*(1+'.c12_inputs.hr'!$E$15)+(P23*(1+'.c12_inputs.hr'!$E$16)) -> 32272.5 | Q38: =+Q8*(1+'.c12_inputs.hr'!$E$15)+(Q23*(1+'.c12_inputs.hr'!$E$16)) -> 32272.5
A39: =+A9 -> Fin Controls (TB) - 100% | B39: c | C39: total_salary | D39: tb | F39: 71462.5 | G39: 56160 | I39: 71462.5 | J39: =+J9*(1+'.c12_inputs.hr'!$E$15)+(J24*(1+'.c12_inputs.hr'!$E$16)) -> 56160 | K39: =+K9*(1+'.c12_inputs.hr'!$E$15)+(K24*(1+'.c12_inputs.hr'!$E$16)) -> 56160 | L39: =+L9*(1+'.c12_inputs.hr'!$E$15)+(L24*(1+'.c12_inputs.hr'!$E$16)) -> 56160 | M39: =+M9*(1+'.c12_inputs.hr'!$E$15)+(M24*(1+'.c12_inputs.hr'!$E$16)) -> 71745 | N39: =+N9*(1+'.c12_inputs.hr'!$E$15)+(N24*(1+'.c12_inputs.hr'!$E$16)) -> 71745 | O39: =+O9*(1+'.c12_inputs.hr'!$E$15)+(O24*(1+'.c12_inputs.hr'!$E$16)) -> 71745 | P39: =+P9*(1+'.c12_inputs.hr'!$E$15)+(P24*(1+'.c12_inputs.hr'!$E$16)) -> 71745 | Q39: =+Q9*(1+'.c12_inputs.hr'!$E$15)+(Q24*(1+'.c12_inputs.hr'!$E$16)) -> 71745
A40: =+A10 -> Administrative Assistant (AM) | B40: c | C40: total_salary | D40: am | F40: 46390 | G40: 0 | I40: 46390 | J40: =+J10*(1+'.c12_inputs.hr'!$E$15)+(J25*(1+'.c12_inputs.hr'!$E$16)) -> 0 | K40: =+K10*(1+'.c12_inputs.hr'!$E$15)+(K25*(1+'.c12_inputs.hr'!$E$16)) -> 0 | L40: =+L10*(1+'.c12_inputs.hr'!$E$15)+(L25*(1+'.c12_inputs.hr'!$E$16)) -> 0 | M40: =+M10*(1+'.c12_inputs.hr'!$E$15)+(M25*(1+'.c12_inputs.hr'!$E$16)) -> 0 | N40: =+N10*(1+'.c12_inputs.hr'!$E$15)+(N25*(1+'.c12_inputs.hr'!$E$16)) -> 0 | O40: =+O10*(1+'.c12_inputs.hr'!$E$15)+(O25*(1+'.c12_inputs.hr'!$E$16)) -> 0 | P40: =+P10*(1+'.c12_inputs.hr'!$E$15)+(P25*(1+'.c12_inputs.hr'!$E$16)) -> 0 | Q40: =+Q10*(1+'.c12_inputs.hr'!$E$15)+(Q25*(1+'.c12_inputs.hr'!$E$16)) -> 0
A41: =+A11 -> Administrative Assistant (PT) | B41: c | C41: total_salary | D41: pt | F41: 0 | G41: 0 | I41: 0 | J41: ='.c12_bi&f_hr'!J11*(1+'.c12_inputs.hr'!$E$5)+('.c12_bi&f_hr'!J26*(1+'.c12_inputs.hr'!$E$6)) -> 0 | K41: ='.c12_bi&f_hr'!K11*(1+'.c12_inputs.hr'!$E$5)+('.c12_bi&f_hr'!K26*(1+'.c12_inputs.hr'!$E$6)) -> 37037.143 | L41: ='.c12_bi&f_hr'!L11*(1+'.c12_inputs.hr'!$E$5)+('.c12_bi&f_hr'!L26*(1+'.c12_inputs.hr'!$E$6)) -> 37037.143 | M41: ='.c12_bi&f_hr'!M11*(1+'.c12_inputs.hr'!$E$5)+('.c12_bi&f_hr'!M26*(1+'.c12_inputs.hr'!$E$6)) -> 47427.143 | N41: ='.c12_bi&f_hr'!N11*(1+'.c12_inputs.hr'!$E$5)+('.c12_bi&f_hr'!N26*(1+'.c12_inputs.hr'!$E$6)) -> 47427.143 | O41: ='.c12_bi&f_hr'!O11*(1+'.c12_inputs.hr'!$E$5)+('.c12_bi&f_hr'!O26*(1+'.c12_inputs.hr'!$E$6)) -> 47427.143 | P41: ='.c12_bi&f_hr'!P11*(1+'.c12_inputs.hr'!$E$5)+('.c12_bi&f_hr'!P26*(1+'.c12_inputs.hr'!$E$6)) -> 47427.143 | Q41: ='.c12_bi&f_hr'!Q11*(1+'.c12_inputs.hr'!$E$5)+('.c12_bi&f_hr'!Q26*(1+'.c12_inputs.hr'!$E$6)) -> 47427.143
A42: =+A12 -> Financial Director (DV) - 100% | B42: c | C42: total_salary | D42: dv | F42: 82700 | G42: 61920 | I42: 82700 | J42: =+J12*(1+'.c12_inputs.hr'!$E$15)+(J27*(1+'.c12_inputs.hr'!$E$16)) -> 61920 | K42: =+K12*(1+'.c12_inputs.hr'!$E$15)+(K27*(1+'.c12_inputs.hr'!$E$16)) -> 61920 | L42: =+L12*(1+'.c12_inputs.hr'!$E$15)+(L27*(1+'.c12_inputs.hr'!$E$16)) -> 61920 | M42: =+M12*(1+'.c12_inputs.hr'!$E$15)+(M27*(1+'.c12_inputs.hr'!$E$16)) -> 103480 | N42: =+N12*(1+'.c12_inputs.hr'!$E$15)+(N27*(1+'.c12_inputs.hr'!$E$16)) -> 103480 | O42: =+O12*(1+'.c12_inputs.hr'!$E$15)+(O27*(1+'.c12_inputs.hr'!$E$16)) -> 103480 | P42: =+P12*(1+'.c12_inputs.hr'!$E$15)+(P27*(1+'.c12_inputs.hr'!$E$16)) -> 103480 | Q42: =+Q12*(1+'.c12_inputs.hr'!$E$15)+(Q27*(1+'.c12_inputs.hr'!$E$16)) -> 103480
A43: =+A13 -> IM (TW) | B43: c | C43: total_salary | D43: tw | F43: 72055 | G43: 46080 | I43: 72055 | J43: =+J13*(1+'.c12_inputs.hr'!$E$15)+(J28*(1+'.c12_inputs.hr'!$E$16)) -> 46080 | K43: =+K13*(1+'.c12_inputs.hr'!$E$15)+(K28*(1+'.c12_inputs.hr'!$E$16)) -> 46080 | L43: =+L13*(1+'.c12_inputs.hr'!$E$15)+(L28*(1+'.c12_inputs.hr'!$E$16)) -> 46080 | M43: =+M13*(1+'.c12_inputs.hr'!$E$15)+(M28*(1+'.c12_inputs.hr'!$E$16)) -> 72055 | N43: =+N13*(1+'.c12_inputs.hr'!$E$15)+(N28*(1+'.c12_inputs.hr'!$E$16)) -> 72055 | O43: =+O13*(1+'.c12_inputs.hr'!$E$15)+(O28*(1+'.c12_inputs.hr'!$E$16)) -> 72055 | P43: =+P13*(1+'.c12_inputs.hr'!$E$15)+(P28*(1+'.c12_inputs.hr'!$E$16)) -> 72055 | Q43: =+Q13*(1+'.c12_inputs.hr'!$E$15)+(Q28*(1+'.c12_inputs.hr'!$E$16)) -> 72055
A44: =+A14 -> HR (100%) | B44: c | C44: total_salary | D44: hr | F44: 0 | G44: 0 | I44: 0 | J44: =+J14*(1+'.c12_inputs.hr'!$E$15)+(J29*(1+'.c12_inputs.hr'!$E$16)) -> 0 | K44: =+K14*(1+'.c12_inputs.hr'!$E$15)+(K29*(1+'.c12_inputs.hr'!$E$16)) -> 0 | L44: =+L14*(1+'.c12_inputs.hr'!$E$15)+(L29*(1+'.c12_inputs.hr'!$E$16)) -> 43200 | M44: =+M14*(1+'.c12_inputs.hr'!$E$15)+(M29*(1+'.c12_inputs.hr'!$E$16)) -> 58785 | N44: =+N14*(1+'.c12_inputs.hr'!$E$15)+(N29*(1+'.c12_inputs.hr'!$E$16)) -> 58785 | O44: =+O14*(1+'.c12_inputs.hr'!$E$15)+(O29*(1+'.c12_inputs.hr'!$E$16)) -> 58785 | P44: =+P14*(1+'.c12_inputs.hr'!$E$15)+(P29*(1+'.c12_inputs.hr'!$E$16)) -> 58785 | Q44: =+Q14*(1+'.c12_inputs.hr'!$E$15)+(Q29*(1+'.c12_inputs.hr'!$E$16)) -> 58785
A45: =+A15 -> Legal (100%) | B45: c | C45: total_salary | D45: legal | F45: 0 | G45: 0 | I45: 0 | J45: =+J15*(1+'.c12_inputs.hr'!$E$15)+(J30*(1+'.c12_inputs.hr'!$E$16)) -> 0 | K45: =+K15*(1+'.c12_inputs.hr'!$E$15)+(K30*(1+'.c12_inputs.hr'!$E$16)) -> 0 | L45: =+L15*(1+'.c12_inputs.hr'!$E$15)+(L30*(1+'.c12_inputs.hr'!$E$16)) -> 64800 | M45: =+M15*(1+'.c12_inputs.hr'!$E$15)+(M30*(1+'.c12_inputs.hr'!$E$16)) -> 80385 | N45: =+N15*(1+'.c12_inputs.hr'!$E$15)+(N30*(1+'.c12_inputs.hr'!$E$16)) -> 80385 | O45: =+O15*(1+'.c12_inputs.hr'!$E$15)+(O30*(1+'.c12_inputs.hr'!$E$16)) -> 80385 | P45: =+P15*(1+'.c12_inputs.hr'!$E$15)+(P30*(1+'.c12_inputs.hr'!$E$16)) -> 80385 | Q45: =+Q15*(1+'.c12_inputs.hr'!$E$15)+(Q30*(1+'.c12_inputs.hr'!$E$16)) -> 80385
A46: =+A16 -> Tech1 | B46: c | C46: total_salary | D46: tech1 | F46: 0 | G46: 0 | I46: 0 | J46: =+J16*(1+'.c12_inputs.hr'!$E$15)+(J31*(1+'.c12_inputs.hr'!$E$16)) -> 0 | K46: =+K16*(1+'.c12_inputs.hr'!$E$15)+(K31*(1+'.c12_inputs.hr'!$E$16)) -> 0 | L46: =+L16*(1+'.c12_inputs.hr'!$E$15)+(L31*(1+'.c12_inputs.hr'!$E$16)) -> 64800 | M46: =+M16*(1+'.c12_inputs.hr'!$E$15)+(M31*(1+'.c12_inputs.hr'!$E$16)) -> 80385 | N46: =+N16*(1+'.c12_inputs.hr'!$E$15)+(N31*(1+'.c12_inputs.hr'!$E$16)) -> 80385 | O46: =+O16*(1+'.c12_inputs.hr'!$E$15)+(O31*(1+'.c12_inputs.hr'!$E$16)) -> 80385 | P46: =+P16*(1+'.c12_inputs.hr'!$E$15)+(P31*(1+'.c12_inputs.hr'!$E$16)) -> 80385 | Q46: =+Q16*(1+'.c12_inputs.hr'!$E$15)+(Q31*(1+'.c12_inputs.hr'!$E$16)) -> 80385
A47: =+A17 -> Tech2 | B47: c | C47: total_salary | D47: tech2 | F47: 0 | G47: 0 | I47: 0 | J47: =+J17*(1+'.c12_inputs.hr'!$E$15)+(J32*(1+'.c12_inputs.hr'!$E$16)) -> 0 | K47: =+K17*(1+'.c12_inputs.hr'!$E$15)+(K32*(1+'.c12_inputs.hr'!$E$16)) -> 0 | L47: =+L17*(1+'.c12_inputs.hr'!$E$15)+(L32*(1+'.c12_inputs.hr'!$E$16)) -> 21600 | M47: =+M17*(1+'.c12_inputs.hr'!$E$15)+(M32*(1+'.c12_inputs.hr'!$E$16)) -> 37185 | N47: =+N17*(1+'.c12_inputs.hr'!$E$15)+(N32*(1+'.c12_inputs.hr'!$E$16)) -> 37185 | O47: =+O17*(1+'.c12_inputs.hr'!$E$15)+(O32*(1+'.c12_inputs.hr'!$E$16)) -> 37185 | P47: =+P17*(1+'.c12_inputs.hr'!$E$15)+(P32*(1+'.c12_inputs.hr'!$E$16)) -> 37185 | Q47: =+Q17*(1+'.c12_inputs.hr'!$E$15)+(Q32*(1+'.c12_inputs.hr'!$E$16)) -> 37185
A48: Grand Total | B48: o | C48: hr_grand_total | F48: 602497.5 | G48: 296640 | I48: 602497.5 | J48: =SUM(J36:J47) -> 296640 | K48: =SUM(K36:K47) -> 477677.14 | L48: =SUM(L36:L47) -> 672077.14 | M48: =SUM(M36:M47) -> 1173394.6 | N48: =SUM(N36:N47) -> 1173394.6 | O48: =SUM(O36:O47) -> 1173394.6 | P48: =SUM(P36:P47) -> 1173394.6 | Q48: =SUM(Q36:Q47) -> 1173394.6
A49: reimbersable to hotel | B49: o | C49: hr_reimbursable | F49: 154162.5 | G49: 118080 | I49: 154162.5 | J49: =SUMPRODUCT('.c12_alloc'!$H$38:$H$49,'.c12_bi&f_hr'!J$36:J$47) -> 118080 | K49: =SUMPRODUCT('.c12_alloc'!$H$38:$H$49,'.c12_bi&f_hr'!K$36:K$47) -> 118080 | L49: =SUMPRODUCT('.c12_alloc'!$H$38:$H$49,'.c12_bi&f_hr'!L$36:L$47) -> 226080 | M49: =SUMPRODUCT('.c12_alloc'!$H$38:$H$49,'.c12_bi&f_hr'!M$36:M$47) -> 314395 | N49: =SUMPRODUCT('.c12_alloc'!$H$38:$H$49,'.c12_bi&f_hr'!N$36:N$47) -> 314395 | O49: =SUMPRODUCT('.c12_alloc'!$H$38:$H$49,'.c12_bi&f_hr'!O$36:O$47) -> 314395 | P49: =SUMPRODUCT('.c12_alloc'!$H$38:$H$49,'.c12_bi&f_hr'!P$36:P$47) -> 314395 | Q49: =SUMPRODUCT('.c12_alloc'!$H$38:$H$49,'.c12_bi&f_hr'!Q$36:Q$47) -> 314395
A50: not reimbersable by hotel, but paid by lgh | B50: o | C50: hr_not_reimbursable | F50: 448335 | G50: 178560 | I50: 448335 | J50: =SUMPRODUCT('.c12_alloc'!$G$38:$G$49,'.c12_bi&f_hr'!J$36:J$47) -> 178560 | K50: =SUMPRODUCT('.c12_alloc'!$G$38:$G$49,'.c12_bi&f_hr'!K$36:K$47) -> 359597.14 | L50: =SUMPRODUCT('.c12_alloc'!$G$38:$G$49,'.c12_bi&f_hr'!L$36:L$47) -> 445997.14 | M50: =SUMPRODUCT('.c12_alloc'!$G$38:$G$49,'.c12_bi&f_hr'!M$36:M$47) -> 858999.64 | N50: =SUMPRODUCT('.c12_alloc'!$G$38:$G$49,'.c12_bi&f_hr'!N$36:N$47) -> 858999.64 | O50: =SUMPRODUCT('.c12_alloc'!$G$38:$G$49,'.c12_bi&f_hr'!O$36:O$47) -> 858999.64 | P50: =SUMPRODUCT('.c12_alloc'!$G$38:$G$49,'.c12_bi&f_hr'!P$36:P$47) -> 858999.64 | Q50: =SUMPRODUCT('.c12_alloc'!$G$38:$G$49,'.c12_bi&f_hr'!Q$36:Q$47) -> 858999.64
A51: only paid by c12 | B51: o | C51: hr_only_c12 | F51: 0 | G51: 0 | I51: 0 | J51: =SUMPRODUCT('.c12_alloc'!$E$38:$E$49,'.c12_bi&f_hr'!J$36:J$47) -> 0 | K51: =SUMPRODUCT('.c12_alloc'!$E$38:$E$49,'.c12_bi&f_hr'!K$36:K$47) -> 0 | L51: =SUMPRODUCT('.c12_alloc'!$E$38:$E$49,'.c12_bi&f_hr'!L$36:L$47) -> 0 | M51: =SUMPRODUCT('.c12_alloc'!$E$38:$E$49,'.c12_bi&f_hr'!M$36:M$47) -> 0 | N51: =SUMPRODUCT('.c12_alloc'!$E$38:$E$49,'.c12_bi&f_hr'!N$36:N$47) -> 0 | O51: =SUMPRODUCT('.c12_alloc'!$E$38:$E$49,'.c12_bi&f_hr'!O$36:O$47) -> 0 | P51: =SUMPRODUCT('.c12_alloc'!$E$38:$E$49,'.c12_bi&f_hr'!P$36:P$47) -> 0 | Q51: =SUMPRODUCT('.c12_alloc'!$E$38:$E$49,'.c12_bi&f_hr'!Q$36:Q$47) -> 0

Sheet .c12_alloc
B3: i/o | C3: field_name | D3: index
A4: CY Project Time Allocation
A5: HO | E5: unalloc | F5: alloc | G5: lgh | H5: reimb | I5: BDA | J5: Aus | K5: Turks | L5: ELBOW | M5: sat | N5: Frith | O5: ROOTS | P5: FO
A6: Managing Member (SK) | B6: i | C6: time_alloc | D6: hm_sk | E6: =1-F6 -> 0 | F6: =G6+H6 -> 1 | G6: =1-H6-P6 -> 1 | H6: =+SUM(I6:O6) -> 0 | I6: 0 | J6: 0 | K6: 0 | L6: 0 | M6: 0 | N6: 0 | O6: 0 | P6: 0
A7: Philanropy senior exec (LM) (100%roots) | B7: i | C7: time_alloc | D7: hm_lm | E7: =1-F7 -> 0 | F7: =G7+H7 -> 1 | G7: =1-H7-P7 -> 0 | H7: =+SUM(I7:O7) -> 1 | I7: 0 | J7: 0 | K7: 0 | L7: 0 | M7: 0 | N7: 0 | O7: 1 | P7: 0
A8: Bookkeeper (DD) | B8: i | C8: time_alloc | D8: hm_dd | E8: =1-F8 -> 1 | F8: =G8+H8 -> 0 | G8: =1-H8-P8 -> 0 | H8: =+SUM(I8:O8) -> 0 | I8: 0 | J8: 0 | K8: 0 | L8: 0 | M8: 0 | N8: 0 | O8: 0 | P8: 1
A9: Personal Assistant (CD) | B9: i | C9: time_alloc | D9: hm_cd | E9: =1-F9 -> 1 | F9: =G9+H9 -> 0 | G9: =1-H9-P9 -> 0 | H9: =+SUM(I9:O9) -> 0 | I9: 0 | J9: 0 | K9: 0 | L9: 0 | M9: 0 | N9: 0 | O9: 0 | P9: 1
A10: philanthropy assist (100%roots) | B10: i | C10: time_alloc | D10: hm_philanthropy | E10: =1-F10 -> 0 | F10: =G10+H10 -> 1 | G10: =1-H10-P10 -> 0 | H10: =+SUM(I10:O10) -> 1 | I10: 0 | J10: 0 | K10: 0 | L10: 0 | M10: 0 | N10: 0 | O10: 1 | P10: 0
A11: TM (gone) | B11: i | C11: time_alloc | D11: hm_tm | E11: =1-F11 -> 0 | F11: =G11+H11 -> 1 | G11: =1-H11-P11 -> 1 | H11: =+SUM(I11:O11) -> 0 | I11: 0 | J11: 0 | K11: 0 | L11: 0 | M11: 0 | N11: 0 | O11: 0 | P11: 0
A13: CY Project Time Allocation
A14: Hotel Management | E14: unalloc | F14: alloc | G14: lgh | H14: reimb | I14: BDA | J14: Aus | K14: Turks | L14: ELBOW | M14: sat | N14: Frith | O14: ROOTS | P14: FO
A15: ACEO Loren Hotels (CE) | B15: i | C15: time_alloc | D15: hm_ce | E15: =1-F15 -> 0 | F15: =G15+H15 -> 1 | G15: =1-H15 -> 1 | H15: =+SUM(I15:O15) -> 0 | I15: 0 | J15: 0 | K15: 0 | L15: 0 | M15: 0 | N15: 0 | O15: 0 | P15: 0
A16: VP Operations (WS) | B16: i | C16: time_alloc | D16: hm_ws | E16: =1-F16 -> 0 | F16: =G16+H16 -> 1 | G16: =1-H16 -> 0 | H16: =+SUM(I16:O16) -> 1 | I16: 0.25 | J16: 0.25 | K16: 0.25 | L16: 0 | M16: 0.25 | N16: 0 | O16: 0 | P16: 0
A17: seniorS&Mexe (CL) | B17: i | C17: time_alloc | D17: hm_cl | E17: =1-F17 -> 0 | F17: =G17+H17 -> 1 | G17: =1-H17 -> 0 | H17: =+SUM(I17:O17) -> 1 | I17: 0.25 | J17: 0.25 | K17: 0.25 | L17: 0 | M17: 0.25 | N17: 0 | O17: 0 | P17: 0
A18: Senior Associate (RF) | B18: i | C18: time_alloc | D18: hm_rf | E18: =1-F18 -> 0 | F18: =G18+H18 -> 1 | G18: =1-H18 -> 0 | H18: =+SUM(I18:O18) -> 1 | I18: 0.25 | J18: 0.25 | K18: 0.25 | L18: 0 | M18: 0.25 | N18: 0 | O18: 0 | P18: 0
A19: associate (MT) | B19: i | C19: time_alloc | D19: hm_mt | E19: =1-F19 -> 0 | F19: =G19+H19 -> 1 | G19: =1-H19 -> 0 | H19: =+SUM(I19:O19) -> 1 | I19: 0.25 | J19: 0.25 | K19: 0.25 | L19: 0 | M19: 0.25 | N19: 0 | O19: 0 | P19: 0
A20: project manager | B20: i | C20: time_alloc | D20: hm_project | E20: =1-F20 -> 0 | F20: =G20+H20 -> 1 | G20: =1-H20 -> 0 | H20: =+SUM(I20:O20) -> 1 | I20: 0 | J20: 0 | K20: 0.5 | L20: 0 | M20: 0.5 | N20: 0 | O20: 0 | P20: 0
A22: CY Project Time Allocation
A23: D&S | E23: unalloc | F23: alloc | G23: lgh | H23: reimb | I23: BDA | J23: Aus | K23: Turks | L23: ELBOW | M23: sat | N23: Frith | O23: ROOTS | P23: FO
A24: HODS (RB) | B24: i | C24: time_alloc | D24: ds_rb | E24: =1-F24 -> 0 | F24: =G24+H24 -> 1 | G24: =1-H24 -> 1 | H24: =+SUM(I24:O24) -> 0 | I24: 0 | J24: 0 | K24: 0 | L24: 0 | M24: 0 | N24: 0 | O24: 0 | P24: 0
A25: Project Executive (LS) (100%) | B25: i | C25: time_alloc | D25: ds_ls | E25: =1-F25 -> 0 | F25: =G25+H25 -> 1 | G25: =1-H25 -> 0 | H25: =+SUM(I25:O25) -> 1 | I25: 0 | J25: 0 | K25: 0.5 | L25: 0.5 | M25: 0 | N25: 0 | O25: 0 | P25: 0
A26: Project Manager (BD) (100%) | B26: i | C26: time_alloc | D26: ds_bd | E26: =1-F26 -> 0 | F26: =G26+H26 -> 1 | G26: =1-H26 -> 0 | H26: =+SUM(I26:O26) -> 1 | I26: 0 | J26: 0 | K26: 0.5 | L26: 0.5 | M26: 0 | N26: 0 | O26: 0 | P26: 0
A27: Counsel (KT) | B27: i | C27: time_alloc | D27: ds_kt | E27: =1-F27 -> 0 | F27: =G27+H27 -> 1 | G27: =1-H27 -> 1 | H27: =+SUM(I27:O27) -> 0 | I27: 0 | J27: 0 | K27: 0 | L27: 0 | M27: 0 | N27: 0 | O27: 0 | P27: 0
A28: Development Manager??? (alexi?) | B28: i | C28: time_alloc | D28: ds_development | E28: =1-F28 -> 0 | F28: =G28+H28 -> 1 | G28: =1-H28 -> 1 | H28: =+SUM(I28:O28) -> 0 | I28: 0 | J28: 0 | K28: 0 | L28: 0 | M28: 0 | N28: 0 | O28: 0 | P28: 0
A29: Banker (tBD) | B29: i | C29: time_alloc | D29: ds_banker | E29: =1-F29 -> 0 | F29: =G29+H29 -> 1 | G29: =1-H29 -> 1 | H29: =+SUM(I29:O29) -> 0 | I29: 0 | J29: 0 | K29: 0 | L29: 0 | M29: 0 | N29: 0 | O29: 0 | P29: 0
A30: Senior Design Manager (AM) | B30: i | C30: time_alloc | D30: ds_am | E30: =1-F30 -> 0 | F30: =G30+H30 -> 1 | G30: =1-H30 -> 1 | H30: =+SUM(I30:O30) -> 0 | I30: 0 | J30: 0 | K30: 0 | L30: 0 | M30: 0 | N30: 0 | O30: 0 | P30: 0
A31: Design Manager (AL) (gone) | B31: i | C31: time_alloc | D31: ds_al | E31: =1-F31 -> 0 | F31: =G31+H31 -> 1 | G31: =1-H31 -> 1 | H31: =+SUM(I31:O31) -> 0 | I31: 0 | J31: 0 | K31: 0 | L31: 0 | M31: 0 | N31: 0 | O31: 0 | P31: 0
A32: new design manager (TBD) | B32: i | C32: time_alloc | D32: ds_tbd | E32: =1-F32 -> 0 | F32: =G32+H32 -> 1 | G32: =1-H32 -> 1 | H32: =+SUM(I32:O32) -> 0 | I32: 0 | J32: 0 | K32: 0 | L32: 0 | M32: 0 | N32: 0 | O32: 0 | P32: 0
A33: FF&E (SB) | B33: i | C33: time_alloc | D33: ds_sb | E33: =1-F33 -> 0 | F33: =G33+H33 -> 1 | G33: =1-H33 -> 1 | H33: =+SUM(I33:O33) -> 0 | I33: 0 | J33: 0 | K33: 0 | L33: 0 | M33: 0 | N33: 0 | O33: 0 | P33: 0
A34: Senior Financial Analyst (KS) | B34: i | C34: time_alloc | D34: ds_ks | E34: =1-F34 -> 0 | F34: =G34+H34 -> 1 | G34: =1-H34 -> 1 | H34: =+SUM(I34:O34) -> 0 | I34: 0 | J34: 0 | K34: 0 | L34: 0 | M34: 0 | N34: 0 | O34: 0 | P34: 0
A36: CY Project Time Allocation
A37: Bi&F | E37: unalloc | F37: alloc | G37: lgh | H37: reimb | I37: BDA | J37: Aus | K37: Turks | L37: ELBOW | M37: sat | N37: Frith | O37: ROOTS | P37: FO
A38: HOBI (CW) | B38: i | C38: time_alloc | D38: bif_cw | E38: =1-F38 -> 0 | F38: =G38+H38 -> 1 | G38: =1-H38 -> 1 | H38: =+SUM(I38:O38) -> 0 | I38: 0 | J38: 0 | K38: 0 | L38: 0 | M38: 0 | N38: 0 | O38: 0 | P38: 0
A39: CFO (ZS) | B39: i | C39: time_alloc | D39: bif_zs | E39: =1-F39 -> 0 | F39: =G39+H39 -> 1 | G39: =1-H39 -> 1 | H39: =+SUM(I39:O39) -> 0 | I39: 0 | J39: 0 | K39: 0 | L39: 0 | M39: 0 | N39: 0 | O39: 0 | P39: 0
A40: Financial Analyst (NR) | B40: i | C40: time_alloc | D40: bif_nr | E40: =1-F40 -> 0 | F40: =G40+H40 -> 1 | G40: =1-H40 -> 1 | H40: =+SUM(I40:O40) -> 0 | I40: 0 | J40: 0 | K40: 0 | L40: 0 | M40: 0 | N40: 0 | O40: 0 | P40: 0
A41: Fin Controls (TB) - 100% | B41: i | C41: time_alloc | D41: bif_tb | E41: =1-F41 -> 0 | F41: =G41+H41 -> 1 | G41: =1-H41 -> 0 | H41: =+SUM(I41:O41) -> 1 | I41: 0.25 | J41: 0.25 | K41: 0.25 | L41: 0 | M41: 0.25 | N41: 0 | O41: 0 | P41: 0
A42: Administrative Assistant (AM) | B42: i | C42: time_alloc | D42: bif_am | E42: =1-F42 -> 0 | F42: =G42+H42 -> 1 | G42: =1-H42 -> 1 | H42: =+SUM(I42:O42) -> 0 | I42: 0 | J42: 0 | K42: 0 | L42: 0 | M42: 0 | N42: 0 | O42: 0 | P42: 0
A43: Administrative Assistant (PT) | B43: i | C43: time_alloc | D43: bif_pt | E43: =1-F43 -> 0 | F43: =G43+H43 -> 1 | G43: =1-H43-P43 -> 1 | H43: =+SUM(I43:O43) -> 0 | I43: 0 | J43: 0 | K43: 0 | L43: 0 | M43: 0 | N43: 0 | O43: 0 | P43: 0
A44: Financial Director (DV) - 100% | B44: i | C44: time_alloc | D44: bif_dv | E44: =1-F44 -> 0 | F44: =G44+H44 -> 1 | G44: =1-H44 -> 0 | H44: =+SUM(I44:O44) -> 1 | I44: 0.25 | J44: 0.25 | K44: 0.25 | L44: 0 | M44: 0.25 | N44: 0 | O44: 0 | P44: 0
A45: IM (TW) | B45: i | C45: time_alloc | D45: bif_tw | E45: =1-F45 -> 0 | F45: =G45+H45 -> 1 | G45: =1-H45 -> 1 | H45: =+SUM(I45:O45) -> 0 | I45: 0 | J45: 0 | K45: 0 | L45: 0 | M45: 0 | N45: 0 | O45: 0 | P45: 0
A46: HR (100%) | B46: i | C46: time_alloc | D46: bif_hr | E46: =1-F46 -> 0 | F46: =G46+H46 -> 1 | G46: =1-H46 -> 0 | H46: =+SUM(I46:O46) -> 1 | I46: 0.25 | J46: 0.25 | K46: 0.25 | L46: 0 | M46: 0.25 | N46: 0 | O46: 0 | P46: 0
A47: Legal (100%) | B47: i | C47: time_alloc | D47: bif_legal | E47: =1-F47 -> 0 | F47: =G47+H47 -> 1 | G47: =1-H47 -> 0 | H47: =+SUM(I47:O47) -> 1 | I47: 0.25 | J47: 0.25 | K47: 0.25 | L47: 0 | M47: 0.25 | N47: 0 | O47: 0 | P47: 0
A48: Tech1 | B48: i | C48: time_alloc | D48: bif_tech1 | E48: =1-F48 -> 0 | F48: =G48+H48 -> 1 | G48: =1-H48 -> 1 | H48: =+SUM(I48:O48) -> 0 | I48: 0 | J48: 0 | K48: 0 | L48: 0 | M48: 0 | N48: 0 | O48: 0 | P48: 0
A49: Tech2 | B49: i | C49: time_alloc | D49: bif_tech2 | E49: =1-F49 -> 0 | F49: =G49+H49 -> 1 | G49: =1-H49 -> 1 | H49: =+SUM(I49:O49) -> 0 | I49: 0 | J49: 0 | K49: 0 | L49: 0 | M49: 0 | N49: 0 | O49: 0 | P49: 0

Sheet c12_diags
E1: LIVE (Python) | I1: BASELINE (frozen) | M1: ERROR = live - baseline
E2: 46203 | F2: 46295 | G2: 46387 | I2: 46203 | J2: 46295 | K2: 46387 | M2: 46203 | N2: 46295 | O2: 46387
E3: Q2_2026 | F3: Q3_2026 | G3: Q4_2026 | I3: Q2_2026 | J3: Q3_2026 | K3: Q4_2026 | M3: Q2_2026 | N3: Q3_2026 | O3: Q4_2026
A4: sheet | B4: field_name | C4: index | D4: label
A5: c12_hm | B5: reimbursable_by_hotels | D5: reimbursable by hotels to LGH | E5: 247680 | F5: 290880 | G5: 545435 | I5: 247680 | J5: 290880 | K5: 545435 | M5: =IF(E5="","",E5-I5) -> 0 | N5: =IF(F5="","",F5-J5) -> 0 | O5: =IF(G5="","",G5-K5) -> 0
A6: c12_hm | B6: total_lgh_hm_revenue | D6: total LGH HM revenue | E6: 902637.29 | F6: 948110.97 | G6: 2385063.6 | I6: 902637.29 | J6: 948110.97 | K6: 2385063.6 | M6: =IF(E6="","",E6-I6) -> 0 | N6: =IF(F6="","",F6-J6) -> 0 | O6: =IF(G6="","",G6-K6) -> 0
A7: c12_hm | B7: lgh_ar_cumm | D7: LGH Accounts Receivable Cumm. | E7: -1170394.7 | F7: -1177800.8 | G7: -16206.87 | I7: -1170394.7 | J7: -1177800.8 | K7: -16206.87 | M7: =IF(E7="","",E7-I7) -> 0 | N7: =IF(F7="","",F7-J7) -> 0 | O7: =IF(G7="","",G7-K7) -> 0
A8: c12_hm | B8: total_c12_hm_revenue | D8: Total C12 HM revenue | E8: 398173.65 | F8: 400447.34 | G8: 662529.63 | I8: 398173.65 | J8: 400447.34 | K8: 662529.63 | M8: =IF(E8="","",E8-I8) -> 0 | N8: =IF(F8="","",F8-J8) -> 0 | O8: =IF(G8="","",G8-K8) -> 0
A9: c12_hm | B9: hr_reimbursable | D9: reimbersable to hotel | E9: 247680 | F9: 290880 | G9: 545435 | I9: 247680 | J9: 290880 | K9: 545435 | M9: =IF(E9="","",E9-I9) -> 0 | N9: =IF(F9="","",F9-J9) -> 0 | O9: =IF(G9="","",G9-K9) -> 0
A10: c12_hm | B10: hr_not_reimbursable | D10: not reimbersable by hotel, but paid by lgh | E10: 144000 | F10: 144000 | G10: 403750 | I10: 144000 | J10: 144000 | K10: 403750 | M10: =IF(E10="","",E10-I10) -> 0 | N10: =IF(F10="","",F10-J10) -> 0 | O10: =IF(G10="","",G10-K10) -> 0
A11: c12_hm | B11: cumm_accrued_participation | D11: Cumm. Accrued Participation | E11: 583052.45 | F11: 425179.25 | G11: 18621.38 | I11: 583052.45 | J11: 425179.25 | K11: 18621.38 | M11: =IF(E11="","",E11-I11) -> 0 | N11: =IF(F11="","",F11-J11) -> 0 | O11: =IF(G11="","",G11-K11) -> 0
A12: c12_d&s | B12: reimbursable_by_hotels | D12: reimbursable by hotels to LGH | E12: 85680 | F12: 85680 | G12: 116850 | I12: 85680 | J12: 85680 | K12: 116850 | M12: =IF(E12="","",E12-I12) -> 0 | N12: =IF(F12="","",F12-J12) -> 0 | O12: =IF(G12="","",G12-K12) -> 0
A13: c12_d&s | B13: total_lgh_ds_revenue | D13: total LGH D&S revenue | E13: 2473819.8 | F13: 2205638.8 | G13: 5828630.3 | I13: 2473819.8 | J13: 2205638.8 | K13: 5828630.3 | M13: =IF(E13="","",E13-I13) -> 0 | N13: =IF(F13="","",F13-J13) -> 0 | O13: =IF(G13="","",G13-K13) -> 0
A14: c12_d&s | B14: lgh_ar_cumm | D14: LGH Accounts Receivable Cumm. | E14: -4470379.7 | F14: -4201060.7 | G14: -4929060.7 | I14: -4470379.7 | J14: -4201060.7 | K14: -4929060.7 | M14: =IF(E14="","",E14-I14) -> 0 | N14: =IF(F14="","",F14-J14) -> 0 | O14: =IF(G14="","",G14-K14) -> 0
A15: c12_d&s | B15: total_c12_ds_revenue | D15: Total C12 D&S revenue | E15: 1015405.1 | F15: 935314.59 | G15: 2208920.6 | I15: 1015405.1 | J15: 935314.59 | K15: 2208920.6 | M15: =IF(E15="","",E15-I15) -> 0 | N15: =IF(F15="","",F15-J15) -> 0 | O15: =IF(G15="","",G15-K15) -> 0
A16: c12_d&s | B16: hr_reimbursable | D16: reimbersable to hotel | E16: 85680 | F16: 85680 | G16: 116850 | I16: 85680 | J16: 85680 | K16: 116850 | M16: =IF(E16="","",E16-I16) -> 0 | N16: =IF(F16="","",F16-J16) -> 0 | O16: =IF(G16="","",G16-K16) -> 0
... A34: c12_oc | B34: total_lgh_revenue | D34: total rev attributable to lgh | E34: 3530751.8 | F34: 3421728.7 | G34: 8574636 | I34: 3530751.8 | J34: 3421728.7 | K34: 8574636 | M34: =IF(E34="","",E34-I34) -> 0 | N34: =IF(F34="","",F34-J34) -> 0 | O34: =IF(G34="","",G34-K34) -> 0
