Workbook
Name DepartmentNum: '.c12_inputs.hr'!$E$4

Sheet registry
A1: Year | E1: 45657 | F1: 45747 | G1: 45838 | H1: 45930 | I1: 46022 | J1: 46112 | K1: 46203 | L1: 45747 | M1: 45838 | N1: 45930 | O1: 46022 | P1: 46112 | Q1: 46203 | R1: 46295 | S1: 46387
E2: actual | L2: i/o
T3: io | U3: field | V3: index | W3: src_row | X3: src_page
A5: [not sourced from c12]
A6: [not sourced from c12]
A7: [not sourced from c12]
A10: [not sourced from c12]
A11: [not sourced from c12]
A12: [not sourced from c12]
A13: [not sourced from c12]
A14: [not sourced from c12]
A15: [not sourced from c12]
A16: [not sourced from c12]
A17: [not sourced from c12]
A18: [not sourced from c12]
... A43: [not sourced from c12]
A46: Total LGH HM Fees | E46: =+'c12_hm'!E60 -> 0 | F46: =+'c12_hm'!F60 -> 0 | G46: =+'c12_hm'!G60 -> 0 | H46: =+'c12_hm'!H60 -> 0 | I46: =+'c12_hm'!I60 -> 447597 | J46: =+'c12_hm'!J60 -> 310715.79 | K46: =+'c12_hm'!K60 -> 0 | L46: =+'c12_hm'!L60 -> 558947 | ... S46: =+'c12_hm'!S60 -> 2385063.6 | T46: o | U46: total_lgh_hm_revenue | W46: 60 | X46: c12_hm
A47: c12 Participation | E47: =+'c12_hm'!E70 -> 0 | F47: =+'c12_hm'!F70 -> 0 | G47: =+'c12_hm'!G70 -> 0 | H47: =+'c12_hm'!H70 -> 0 | I47: =+'c12_hm'!I70 -> 447597 | J47: =+'c12_hm'!J70 -> 63035.789 | K47: =+'c12_hm'!K70 -> 0 | L47: =+'c12_hm'!L70 -> 558947 | ... S47: =+'c12_hm'!S70 -> 662529.63 | T47: o | U47: total_c12_hm_revenue | W47: 70 | X47: c12_hm
A49: [not sourced from c12]
A50: [not sourced from c12]
A51: [not sourced from c12]
A55: Total LGH D&s Fees | E55: ='c12_d&s'!E60 -> 0 | F55: ='c12_d&s'!F60 -> 0 | G55: ='c12_d&s'!G60 -> 0 | H55: ='c12_d&s'!H60 -> 0 | I55: ='c12_d&s'!I60 -> 911235.5 | J55: ='c12_d&s'!J60 -> 1735259.1 | K55: ='c12_d&s'!K60 -> 0 | L55: ='c12_d&s'!L60 -> 128735.5 | ... S55: ='c12_d&s'!S60 -> 5828630.3 | T55: o | U55: total_lgh_ds_revenue | W55: 60 | X55: c12_d&s
A56: c12 D&s Participation | E56: ='c12_d&s'!E70 -> 0 | F56: ='c12_d&s'!F70 -> 0 | G56: ='c12_d&s'!G70 -> 0 | H56: ='c12_d&s'!H70 -> 0 | I56: ='c12_d&s'!I70 -> 455617.75 | J56: ='c12_d&s'!J70 -> 806580.95 | K56: ='c12_d&s'!K70 -> 0 | L56: ='c12_d&s'!L70 -> 64367.75 | ... S56: ='c12_d&s'!S70 -> 2208920.6 | T56: o | U56: total_c12_ds_revenue | W56: 70 | X56: c12_d&s
A58: total c12 participation | E58: ='c12_oc'!E10 -> 2452451 | F58: ='c12_oc'!F10 -> 0 | G58: ='c12_oc'!G10 -> 0 | H58: ='c12_oc'!H10 -> 0 | I58: ='c12_oc'!I10 -> 0 | J58: ='c12_oc'!J10 -> 0 | K58: ='c12_oc'!K10 -> 0 | L58: ='c12_oc'!L10 -> 623314.75 | ... S58: ='c12_oc'!S10 -> 2898497.4 | T58: o | U58: total_participation_revenue_actual | W58: 10 | X58: c12_oc
A59: total lgh revenue | E59: ='c12_oc'!E87 -> 0 | F59: ='c12_oc'!F87 -> 0 | G59: ='c12_oc'!G87 -> 0 | H59: ='c12_oc'!H87 -> 0 | I59: ='c12_oc'!I87 -> 0 | J59: ='c12_oc'!J87 -> 0 | K59: ='c12_oc'!K87 -> 0 | L59: ='c12_oc'!L87 -> 687682.5 | ... S59: ='c12_oc'!S87 -> 8574636 | T59: o | U59: total_lgh_revenue | W59: 87 | X59: c12_oc
A60: art leases | E60: ='c12_sk'!E7 -> 0 | F60: ='c12_sk'!F7 -> 0 | G60: ='c12_sk'!G7 -> 0 | H60: ='c12_sk'!H7 -> 0 | I60: ='c12_sk'!I7 -> 0 | J60: ='c12_sk'!J7 -> 0 | K60: ='c12_sk'!K7 -> 0 | L60: ='c12_sk'!L7 -> 0 | ... S60: ='c12_sk'!S7 -> 50000 | T60: i | U60: lease_payments | V60: sk | W60: 7 | X60: c12_sk
A62: [not sourced from c12]
A63: [not sourced from c12]
A66: [not sourced from c12]
A67: [not sourced from c12]
A68: [not sourced from c12]
A71: [not sourced from c12]
A72: [not sourced from c12]
A73: [not sourced from c12]
A77: [not sourced from c12]
A78: [not sourced from c12]
A79: [not sourced from c12]
A82: [not sourced from c12]
A83: guarantee payments | E83: ='c12_sk'!E8 -> 0 | F83: ='c12_sk'!F8 -> 0 | G83: ='c12_sk'!G8 -> 0 | H83: ='c12_sk'!H8 -> 0 | I83: ='c12_sk'!I8 -> 0 | J83: ='c12_sk'!J8 -> 0 | K83: ='c12_sk'!K8 -> 0 | L83: ='c12_sk'!L8 -> -250000 | ... S83: ='c12_sk'!S8 -> -250000 | T83: i | U83: guarantee_fees | V83: sk | W83: 8 | X83: c12_sk
A86: [not sourced from c12]
A87: [not sourced from c12]
A91: [not sourced from c12]
A93: [not sourced from c12]
A94: [not sourced from c12]
A95: Total c12 Operating Expenses | E95: =+'c12_oc'!E39 -> -5450569 | F95: =+'c12_oc'!F39 -> 0 | G95: =+'c12_oc'!G39 -> 0 | H95: =+'c12_oc'!H39 -> 0 | I95: =+'c12_oc'!I39 -> 0 | J95: =+'c12_oc'!J39 -> 0 | K95: =+'c12_oc'!K39 -> 0 | L95: =+'c12_oc'!L39 -> -1637186 | ... S95: =+'c12_oc'!S39 -> -4930793.2 | T95: o | U95: total_c12_exp_lgh_actual | W95: 39 | X95: c12_oc
A96: [not sourced from c12]
A97: [not sourced from c12]
A98: [not sourced from c12]
A99: [not sourced from c12]
A100: [not sourced from c12]
A101: [not sourced from c12]
A102: lgh cuda buy back | E102: ='c12_sk'!E9 -> 0 | F102: ='c12_sk'!F9 -> 0 | G102: ='c12_sk'!G9 -> 0 | H102: ='c12_sk'!H9 -> 0 | I102: ='c12_sk'!I9 -> 0 | J102: ='c12_sk'!J9 -> 0 | K102: ='c12_sk'!K9 -> 0 | L102: ='c12_sk'!L9 -> 0 | ... S102: ='c12_sk'!S9 -> 0 | T102: i | U102: cuda_buyback | V102: sk | W102: 9 | X102: c12_sk
A104: c12 loc balance | E104: =-'c12_oc'!E62 -> 1540999 | F104: =-'c12_oc'!F62 -> 0 | G104: =-'c12_oc'!G62 -> 0 | H104: =-'c12_oc'!H62 -> 0 | I104: =-'c12_oc'!I62 -> 0 | J104: =-'c12_oc'!J62 -> 0 | K104: =-'c12_oc'!K62 -> 0 | L104: =-'c12_oc'!L62 -> 2137441.8 | ... S104: =-'c12_oc'!S62 -> 0 | T104: o | U104: loc_balance | W104: 62 | X104: c12_oc
A105: LGH Fee AR/AP | E105: =+'c12_oc'!E68 -> 0 | F105: =+'c12_oc'!F68 -> 0 | G105: =+'c12_oc'!G68 -> 0 | H105: =+'c12_oc'!H68 -> 0 | I105: =+'c12_oc'!I68 -> 0 | J105: =+'c12_oc'!J68 -> 0 | K105: =+'c12_oc'!K68 -> 0 | L105: =+'c12_oc'!L68 -> 416032.5 | ... S105: =+'c12_oc'!S68 -> 4945267.5 | T105: o | U105: total_lgh_acc_rec | W105: 68 | X105: c12_oc
A106: C12 Fee Particpiation AR/AP | E106: =-'c12_oc'!E74 -> 0 | F106: =-'c12_oc'!F74 -> 0 | G106: =-'c12_oc'!G74 -> 0 | H106: =-'c12_oc'!H74 -> 0 | I106: =-'c12_oc'!I74 -> 0 | J106: =-'c12_oc'!J74 -> 0 | K106: =-'c12_oc'!K74 -> 0 | L106: =-'c12_oc'!L74 -> -264555.12 | ... S106: =-'c12_oc'!S74 -> -1664945.5 | T106: o | U106: total_c12_acc_rec | W106: 74 | X106: c12_oc

Sheet c12_inputs
A2: Year
A3: Period
B4: i/o | C4: field_name | D4: index
A5: cost inflation | B5: i | C5: cost_inflation_rate_actual | E5: 0.03
A7: Charge Back Percentage | B7: i | C7: chargeback_pct_actual | E7: 0.05
A8: participation% | B8: i | C8: participation_pct_actual | E8: 0.35
A11: actual thru | B11: i | C11: actuals_thru | E11: 46112
A12: projections from | B12: i | C12: projections_from | E12: 46203
A13: projections to | B13: i | C13: projections_to | E13: 46387

Sheet c12_oc
A2: Year | E2: 45657 | F2: 45747 | G2: 45838 | H2: 45930 | I2: 46022 | J2: 46112 | K2: 46203 | L2: 45747 | M2: 45838 | N2: 45930 | O2: 46022 | P2: 46112 | Q2: 46203 | R2: 46295 | S2: 46387
E3: actual | L3: i/o
B4: i/o | C4: field_name | D4: index
A5: C12 Participation Revenue (not c/b reimb)
A6: HM Fees | L6: ='c12_hm'!L70 -> 558947 | M6: ='c12_hm'!M70 -> 558947 | N6: ='c12_hm'!N70 -> 558947 | O6: ='c12_hm'!O70 -> 447597 | P6: ='c12_hm'!P70 -> 63035.789 | Q6: ='c12_hm'!Q70 -> 398173.65 | R6: ='c12_hm'!R70 -> 400447.34 | S6: ='c12_hm'!S70 -> 662529.63
A7: BI&F Fees | L7: ='c12_bi&F'!L70 -> 0 | M7: ='c12_bi&F'!M70 -> 0 | N7: ='c12_bi&F'!N70 -> 0 | O7: ='c12_bi&F'!O70 -> 0 | P7: ='c12_bi&F'!P70 -> 16714.737 | Q7: ='c12_bi&F'!Q70 -> 16714.737 | R7: ='c12_bi&F'!R70 -> 22398.947 | S7: ='c12_bi&F'!S70 -> 27047.105
A8: DS Fees | L8: ='c12_d&s'!L70 -> 64367.75 | M8: ='c12_d&s'!M70 -> 64367.75 | N8: ='c12_d&s'!N70 -> 349567.75 | O8: ='c12_d&s'!O70 -> 455617.75 | P8: ='c12_d&s'!P70 -> 806580.95 | Q8: ='c12_d&s'!Q70 -> 1015405.1 | R8: ='c12_d&s'!R70 -> 935314.59 | S8: ='c12_d&s'!S70 -> 2208920.6
A10: total participation revenue | B10: o | C10: total_participation_revenue_actual | E10: 2452451 | L10: =SUM(L6:L9) -> 623314.75 | M10: =SUM(M6:M9) -> 623314.75 | N10: =SUM(N6:N9) -> 908514.75 | O10: =SUM(O6:O9) -> 903214.75 | P10: =SUM(P6:P9) -> 886331.48 | Q10: =SUM(Q6:Q9) -> 1430293.5 | R10: =SUM(R6:R9) -> 1358160.9 | S10: =SUM(S6:S9) -> 2898497.4 | T10: revenues in nominal dollars
A12: Infrastructure | B12: i | C12: nonrecur_exp | D12: infrastructure | T12: this now two people in bi&f
A13: Professional services | B13: i | C13: nonrecur_exp | D13: professional_services | Q13: 100000 | R13: 100000
A14: Hiring Costs | B14: i | C14: nonrecur_exp | D14: hiring_costs | Q14: 100000
A15: signing bonuses | B15: i | C15: nonrecur_exp | D15: signing_bonus
A16: Restructuring | B16: i | C16: nonrecur_exp | D16: restructuring | P16: 0 | Q16: 0 | R16: 0 | S16: 0 | T16: put this in c12_oc_hr costs
A17: housing | B17: i | C17: nonrecur_exp | D17: housing | P17: 0 | Q17: 0 | R17: 0 | S17: 0 | T17: I think this is in oop cos paid by me
A18: Total | B18: c | C18: total_nonrecur_exp | L18: =SUM(L12:L17) -> 0 | M18: =SUM(M12:M17) -> 0 | N18: =SUM(N12:N17) -> 0 | O18: =SUM(O12:O17) -> 0 | P18: =SUM(P12:P17) -> 0 | Q18: =SUM(Q12:Q17) -> 200000 | R18: =SUM(R12:R17) -> 100000 | S18: =SUM(S12:S17) -> 0
A20: Reimbursable Operating Expenses (inc holtel) | L20: =-L39 -> 1637186 | M20: =-M39 -> 1733477 | N20: =-N39 -> 1694124 | O20: =-O39 -> 2917273 | P20: =-P39 -> 4057849.9 | Q20: =-Q39 -> 4457407 | R20: =-R39 -> 2834607 | S20: =-S39 -> 4930793.2
A22: revenue from lgh | L22: =L20+L10 -> 2260500.8 | M22: =M20+M10 -> 2356791.8 | N22: =N20+N10 -> 2602638.8 | O22: =O20+O10 -> 3820487.8 | P22: =P20+P10 -> 4944181.3 | Q22: =Q20+Q10 -> 5887700.5 | R22: =R20+R10 -> 4192767.9 | S22: =S20+S10 -> 7829290.6
A24: compensation
A25: Hotel Management | L25: =-('c12_hm'!L78+'c12_hm'!L79) -> -298080 | M25: =-('c12_hm'!M78+'c12_hm'!M79) -> -298080 | N25: =-('c12_hm'!N78+'c12_hm'!N79) -> -298080 | O25: =-('c12_hm'!O78+'c12_hm'!O79) -> -770825 | P25: =-('c12_hm'!P78+'c12_hm'!P79) -> -391680 | Q25: =-('c12_hm'!Q78+'c12_hm'!Q79) -> -391680 | R25: =-('c12_hm'!R78+'c12_hm'!R79) -> -434880 | S25: =-('c12_hm'!S78+'c12_hm'!S79) -> -949185
A26: Business Infrastructure & Finance | L26: =-('c12_bi&F'!L78+'c12_bi&F'!L79) -> -250560 | M26: =-('c12_bi&F'!M78+'c12_bi&F'!M79) -> -250560 | N26: =-('c12_bi&F'!N78+'c12_bi&F'!N79) -> -336960 | O26: =-('c12_bi&F'!O78+'c12_bi&F'!O79) -> -602497.5 | P26: =-('c12_bi&F'!P78+'c12_bi&F'!P79) -> -296640 | Q26: =-('c12_bi&F'!Q78+'c12_bi&F'!Q79) -> -477677.14 | R26: =-('c12_bi&F'!R78+'c12_bi&F'!R79) -> -672077.14 | S26: =-('c12_bi&F'!S78+'c12_bi&F'!S79) -> -1173394.6
A27: Development & Structuring | L27: =-('c12_d&s'!L78+'c12_d&s'!L79) -> -515520 | M27: =-('c12_d&s'!M78+'c12_d&s'!M79) -> -515520 | N27: =-('c12_d&s'!N78+'c12_d&s'!N79) -> -515520 | O27: =-('c12_d&s'!O78+'c12_d&s'!O79) -> -1652177.5 | P27: =-('c12_d&s'!P78+'c12_d&s'!P79) -> -560160 | Q27: =-('c12_d&s'!Q78+'c12_d&s'!Q79) -> -520560 | R27: =-('c12_d&s'!R78+'c12_d&s'!R79) -> -560160 | S27: =-('c12_d&s'!S78+'c12_d&s'!S79) -> -1221223.8
A28: C12 headoffice | L28: =-(L78-L81) -> -472542.86 | M28: =-(M78-M81) -> -472542.86 | N28: =-(N78-N81) -> -472542.86 | O28: =-(O78-O81) -> -472542.86 | P28: =-(P78-P81) -> -805022.86 | Q28: =-(Q78-Q81) -> -383142.86 | R28: =-(R78-R81) -> -383142.86 | S28: =-(S78-S81) -> -902642.86 | T28: this was double counting sk, deleted 1.5m
A29: Head office expenses
A30: office costs (rent & reoccuring) | B30: i | C30: ho_exp | D30: office_costs | L30: =-189940/4 -> -47485 | M30: =-189940/4 -> -47485 | N30: =-189940/4 -> -47485 | O30: =-189940/4 -> -47485 | P30: =-540000/4 -> -135000 | Q30: =-540000/4 -> -135000 | R30: =-540000/4 -> -135000 | S30: =-540000/4 -> -135000 | T30: is this updated?
A31: Departmental OOP paid via sk | L31: ='c12_sk'!L6 -> -112553 | M31: ='c12_sk'!M6 -> -186705 | N31: ='c12_sk'!N6 -> -148699 | O31: ='c12_sk'!O6 -> -249431 | P31: ='c12_sk'!P6 -> -174347 | Q31: ='c12_sk'!Q6 -> -174347 | R31: ='c12_sk'!R6 -> -174347 | S31: ='c12_sk'!S6 -> -174347 | T31: should come from danielle
A32: Departmental OOP not paid via sk | B32: i | C32: ho_exp | D32: oop_notsk | P32: -75000 | Q32: -75000 | R32: -75000 | S32: -75000 | T32: added mastercard cos not all paid by sk
A33: Non-recurring Items paid by LGH | B33: i | C33: ho_exp | D33: nonrecur_lgh | L33: =-L18 -> 0 | M33: =-M18 -> 0 | N33: =-N18 -> 0 | O33: =-O18 -> 0 | P33: =-P18 -> 0 | Q33: =-Q18 -> -200000 | R33: =-R18 -> -100000 | S33: =-S18 -> 0
A34: C12 Accounts Payable | B34: i | C34: ho_exp | D34: accounts_payable | N34: -45000 | O34: -599728 | P34: -1620000 | Q34: -2100000 | R34: -300000 | S34: -300000 | T34: WHAT IS THIS? Not double counting?
A35: inflation multiplier | B35: i | C35: inflation_multiplier | L35: 1 | M35: 1 | N35: 1 | O35: 1 | P35: 1 | Q35: 1 | R35: 1 | S35: 1
A36: Inflation | B36: c | C36: inflation | L36: =(L35-1)*SUM(L25:L34) -> 0 | M36: =(M35-1)*SUM(M25:M34) -> 0 | N36: =(N35-1)*SUM(N25:N34) -> 0 | O36: =(O35-1)*SUM(O25:O34) -> 0 | P36: =(P35-1)*SUM(P25:P34) -> 0 | Q36: =(Q35-1)*SUM(Q25:Q34) -> 0 | R36: =(R35-1)*SUM(R25:R34) -> 0 | S36: =(S35-1)*SUM(S25:S34) -> 0 | T36: revs in nominal dollars cos business forecast nominal, but personnel costs real
A37: Compensation - total | B37: o | C37: compensation_total | E37: -3970569 | F37: -1102148 | G37: -1124287 | H37: -1077940 | I37: -1645629 | L37: =IF(AND((F37<>""),(L$2<46204)),(F37),SUM(L25:L28)) -> -1102148 | M37: =IF(AND((G37<>""),(M$2<46204)),(G37),SUM(M25:M28)) -> -1124287 | N37: =IF(AND((H37<>""),(N$2<46204)),(H37),SUM(N25:N28)) -> -1077940 | O37: =IF(AND((I37<>""),(O$2<46204)),(I37),SUM(O25:O28)) -> -1645629 | P37: =IF(AND((J37<>""),(P$2<46204)),(J37),SUM(P25:P28)) -> -2053502.9 | Q37: =IF(AND((K37<>""),(Q$2<46204)),(K37),SUM(Q25:Q28)) -> -1773060 | R37: =IF(AND((L37<>""),(R$2<46204)),(L37),SUM(R25:R28)) -> -2050260 | S37: =IF(AND((M37<>""),(S$2<46204)),(M37),SUM(S25:S28)) -> -4246446.2
A38: Direct compensation not via trinet | B38: i | C38: compensation_direct | F38: -375000 | G38: -375000 | H38: -375000 | I38: -375000 | L38: =IF(AND((F38<>""),(L$2<46204)),(F38),0) -> -375000 | M38: =IF(AND((G38<>""),(M$2<46204)),(G38),0) -> -375000 | N38: =IF(AND((H38<>""),(N$2<46204)),(H38),0) -> -375000 | O38: =IF(AND((I38<>""),(O$2<46204)),(I38),0) -> -375000 | P38: =IF(AND((J38<>""),(P$2<46204)),(J38),0) -> 0 | Q38: =IF(AND((K38<>""),(Q$2<46204)),(K38),0) -> 0 | R38: =IF(AND((L38<>""),(R$2<46204)),(L38),0) -> 0 | S38: =IF(AND((M38<>""),(S$2<46204)),(M38),0) -> 0
A39: Total c12 Expenses paid by LGH | B39: o | C39: total_c12_exp_lgh_actual | E39: -5450569 | L39: =SUM(L30:L34,L36,L37:L38) -> -1637186 | M39: =SUM(M30:M34,M36,M37:M38) -> -1733477 | N39: =SUM(N30:N34,N36,N37:N38) -> -1694124 | O39: =SUM(O30:O34,O36,O37:O38) -> -2917273 | P39: =SUM(P30:P34,P36,P37:P38) -> -4057849.9 | Q39: =SUM(Q30:Q34,Q36,Q37:Q38) -> -4457407 | R39: =SUM(R30:R34,R36,R37:R38) -> -2834607 | S39: =SUM(S30:S34,S36,S37:S38) -> -4930793.2
A41: C12 H/O compensation not paid by lgh | L41: =-L81 -> -31928.571 | M41: =-M81 -> -31928.571 | N41: =-N81 -> -31928.571 | O41: =-O81 -> -42318.571 | P41: =-P81 -> -58237.714 | Q41: =-Q81 -> -58237.714 | R41: =-R81 -> -58237.714 | S41: =-S81 -> -79017.714
A42: Roots donation by c12 | B42: i | C42: roots_donation | S42: -200000
A43: Total c12 Expenses Not paid by lgh | B43: c | C43: total_c12_exp_not_lgh | L43: =SUM(L41:L42) -> -31928.571 | M43: =SUM(M41:M42) -> -31928.571 | N43: =SUM(N41:N42) -> -31928.571 | O43: =SUM(O41:O42) -> -42318.571 | P43: =SUM(P41:P42) -> -58237.714 | Q43: =SUM(Q41:Q42) -> -58237.714 | R43: =SUM(R41:R42) -> -58237.714 | S43: =SUM(S41:S42) -> -279017.71
A45: total costs | B45: c | C45: total_c12_costs | L45: =L43+L39 -> -1669114.6 | M45: =M43+M39 -> -1765405.6 | N45: =N43+N39 -> -1726052.6 | O45: =O43+O39 -> -2959591.6 | P45: =P43+P39 -> -4116087.6 | Q45: =Q43+Q39 -> -4515644.7 | R45: =R43+R39 -> -2892844.7 | S45: =S43+S39 -> -5209811
A47: Total C12 Profit | B47: o | C47: total_c12_profit_actual | E47: 3119951 | L47: =L22+L45 -> 591386.18 | M47: =M22+M45 -> 591386.18 | N47: =N22+N45 -> 876586.18 | O47: =O22+O45 -> 860896.18 | P47: =P22+P45 -> 828093.76 | Q47: =Q22+Q45 -> 1372055.8 | R47: =R22+R45 -> 1299923.2 | S47: =S22+S45 -> 2619479.6
A48: c12 profit margin | B48: c | C48: c12_profit_margin | L48: =L47/L22 -> 0.26161733 | M48: =M47/M22 -> 0.25092848 | N48: =N47/N22 -> 0.3368067 | O48: =O47/O22 -> 0.22533672 | P48: =P47/P22 -> 0.16748855 | Q48: =Q47/Q22 -> 0.23303763 | R48: =R47/R22 -> 0.31003938 | S48: =S47/S22 -> 0.33457433
A51: Bank transfers (actual or danielle)
A52: Bank transfers | L52: ='c12_sk'!L5 -> -1925382 | M52: ='c12_sk'!M5 -> -1925382 | N52: ='c12_sk'!N5 -> -1925382 | O52: ='c12_sk'!O5 -> -1925382 | P52: ='c12_sk'!P5 -> 0 | Q52: ='c12_sk'!Q5 -> 0 | R52: ='c12_sk'!R5 -> 0 | S52: ='c12_sk'!S5 -> 0
A53: oop | L53: =-L31 -> 112553 | M53: =-M31 -> 186705 | N53: =-N31 -> 148699 | O53: =-O31 -> 249431 | P53: =-P31 -> 174347 | Q53: =-Q31 -> 174347 | R53: =-R31 -> 174347 | S53: =-S31 -> 174347
A54: art | L54: ='c12_sk'!L7 -> 0 | M54: ='c12_sk'!M7 -> 0 | N54: ='c12_sk'!N7 -> 0 | O54: ='c12_sk'!O7 -> 0 | P54: ='c12_sk'!P7 -> 50000 | Q54: ='c12_sk'!Q7 -> 50000 | R54: ='c12_sk'!R7 -> 50000 | S54: ='c12_sk'!S7 -> 50000
A55: pay | L55: ='.c12_oc_hr'!L6 -> 375000 | M55: ='.c12_oc_hr'!M6 -> 375000 | N55: ='.c12_oc_hr'!N6 -> 375000 | O55: ='.c12_oc_hr'!O6 -> 375000 | P55: ='.c12_oc_hr'!P6 -> 375000 | Q55: ='.c12_oc_hr'!Q6 -> 375000 | R55: ='.c12_oc_hr'!R6 -> 375000 | S55: ='.c12_oc_hr'!S6 -> 375000
A56: guarantess | L56: =-'c12_sk'!L8 -> 250000 | M56: =-'c12_sk'!M8 -> 250000 | N56: =-'c12_sk'!N8 -> 250000 | O56: =-'c12_sk'!O8 -> 250000 | P56: =-'c12_sk'!P8 -> 250000 | Q56: =-'c12_sk'!Q8 -> 250000 | R56: =-'c12_sk'!R8 -> 250000 | S56: =-'c12_sk'!S8 -> 250000
A58: cuda buy back | L58: =-'c12_sk'!L9 -> 0 | M58: =-'c12_sk'!M9 -> 1200000 | N58: =-'c12_sk'!N9 -> 0 | O58: =-'c12_sk'!O9 -> 0 | P58: =-'c12_sk'!P9 -> 0 | Q58: =-'c12_sk'!Q9 -> 0 | R58: =-'c12_sk'!R9 -> 0 | S58: =-'c12_sk'!S9 -> 0
A59: Distributions | B59: o | C59: distribution_required | E59: -4651000 | L59: =SUM(L52:L58) -> -1187829 | M59: =SUM(M52:M58) -> 86323.002 | N59: =SUM(N52:N58) -> -1151683 | O59: =SUM(O52:O58) -> -1050951 | P59: =SUM(P52:P58) -> 849347 | Q59: =SUM(Q52:Q58) -> 849347 | R59: =SUM(R52:R58) -> 849347 | S59: =SUM(S52:S58) -> 849347
A60: Distribution after c12 profit | B60: c | C60: loc_draw | E60: -1531049 | L60: =+(L47+L59) -> -596442.82 | M60: =+(M47+M59) -> 677709.18 | N60: =+(N47+N59) -> -275096.82 | O60: =+(O47+O59) -> -190054.82 | P60: =+(P47+P59) -> 1677440.8 | Q60: =+(Q47+Q59) -> 2221402.8 | R60: =+(R47+R59) -> 2149270.2 | S60: =+(S47+S59) -> 3468826.6
A61: 2024LOC writeoff | B61: i | C61: loc_writeoff | P61: 1540999
A62: Balance of c12 LOC | B62: o | C62: loc_balance | E62: -1540999 | L62: =MIN(L60+E62+L61,0) -> -2137441.8 | M62: =MIN(M60+L62+M61,0) -> -1459732.6 | N62: =MIN(N60+M62+N61,0) -> -1734829.5 | O62: =MIN(O60+N62+O61,0) -> -1924884.3 | P62: =MIN(P60+O62+P61,0) -> 0 | Q62: =MIN(Q60+P62+Q61,0) -> 0 | R62: =MIN(R60+Q62+R61,0) -> 0 | S62: =MIN(S60+R62+S61,0) -> 0
A64: LGH Accounts Receivable
A65: Hotel Management | L65: =-'c12_hm'!L62 -> 113077.75 | M65: =-'c12_hm'!M62 -> 226155.5 | N65: =-'c12_hm'!N62 -> 339233.25 | O65: =-'c12_hm'!O62 -> 563661 | P65: =-'c12_hm'!P62 -> 1162988.6 | Q65: =-'c12_hm'!Q62 -> 1170394.7 | R65: =-'c12_hm'!R62 -> 1177800.8 | S65: =-'c12_hm'!S62 -> 16206.87
A66: Business Infrastructure & Finance | L66: ='c12_bi&F'!L62 -> 0 | M66: ='c12_bi&F'!M62 -> 0 | N66: ='c12_bi&F'!N62 -> 0 | O66: ='c12_bi&F'!O62 -> 0 | P66: ='c12_bi&F'!P62 -> 0 | Q66: ='c12_bi&F'!Q62 -> 0 | R66: ='c12_bi&F'!R62 -> 0 | S66: ='c12_bi&F'!S62 -> 0
A67: Development & Structuring | L67: =-'c12_d&s'!L62 -> 302954.75 | M67: =-'c12_d&s'!M62 -> 2855909.5 | N67: =-'c12_d&s'!N62 -> 4033864.2 | O67: =-'c12_d&s'!O62 -> 4801819 | P67: =-'c12_d&s'!P62 -> 4957879.7 | Q67: =-'c12_d&s'!Q62 -> 4470379.7 | R67: =-'c12_d&s'!R62 -> 4201060.7 | S67: =-'c12_d&s'!S62 -> 4929060.7
A68: Total | B68: o | C68: total_lgh_acc_rec | L68: =SUM(L65:L67) -> 416032.5 | M68: =SUM(M65:M67) -> 3082065 | N68: =SUM(N65:N67) -> 4373097.5 | O68: =SUM(O65:O67) -> 5365480 | P68: =SUM(P65:P67) -> 6120868.3 | Q68: =SUM(Q65:Q67) -> 5640774.4 | R68: =SUM(R65:R67) -> 5378861.5 | S68: =SUM(S65:S67) -> 4945267.5
A70: C12 Accounts Receivable
A71: Hotel Management | L71: =+'c12_hm'!L74 -> 113077.75 | M71: =+'c12_hm'!M74 -> 226155.5 | N71: =+'c12_hm'!N74 -> 339233.25 | O71: =+'c12_hm'!O74 -> 563661 | P71: =+'c12_hm'!P74 -> 740925.66 | Q71: =+'c12_hm'!Q74 -> 583052.45 | R71: =+'c12_hm'!R74 -> 425179.25 | S71: =+'c12_hm'!S74 -> 18621.38
A72: BI&f | L72: ='c12_bi&F'!L74 -> 0 | M72: ='c12_bi&F'!M74 -> 0 | N72: ='c12_bi&F'!N74 -> 0 | O72: ='c12_bi&F'!O74 -> 0 | P72: ='c12_bi&F'!P74 -> 0 | Q72: ='c12_bi&F'!Q74 -> 0 | R72: ='c12_bi&F'!R74 -> 0 | S72: ='c12_bi&F'!S74 -> 0
A73: Development & Structuring | L73: ='c12_d&s'!L74 -> 151477.38 | M73: ='c12_d&s'!M74 -> 1427954.8 | N73: ='c12_d&s'!N74 -> 2016932.1 | O73: ='c12_d&s'!O74 -> 2400909.5 | P73: ='c12_d&s'!P74 -> 2229233.6 | Q73: ='c12_d&s'!Q74 -> 1881983.6 | R73: ='c12_d&s'!R74 -> 1597324.1 | S73: ='c12_d&s'!S74 -> 1646324.1
A74: Total | B74: o | C74: total_c12_acc_rec | L74: =SUM(L71:L73) -> 264555.12 | M74: =SUM(M71:M73) -> 1654110.2 | N74: =SUM(N71:N73) -> 2356165.4 | O74: =SUM(O71:O73) -> 2964570.5 | P74: =SUM(P71:P73) -> 2970159.3 | Q74: =SUM(Q71:Q73) -> 2465036.1 | R74: =SUM(R71:R73) -> 2022503.4 | S74: =SUM(S71:S73) -> 1664945.5
A77: C12 oc compensation expense (not divisons)
A78: ='.c12_oc_hr'!A30 -> Grand Total | L78: ='.c12_oc_hr'!L30 -> 504471.43 | M78: ='.c12_oc_hr'!M30 -> 504471.43 | N78: ='.c12_oc_hr'!N30 -> 504471.43 | O78: ='.c12_oc_hr'!O30 -> 514861.43 | P78: ='.c12_oc_hr'!P30 -> 863260.57 | Q78: ='.c12_oc_hr'!Q30 -> 441380.57 | R78: ='.c12_oc_hr'!R30 -> 441380.57 | S78: ='.c12_oc_hr'!S30 -> 981660.57
A79: ='.c12_oc_hr'!A31 -> reimbersable to hotel | L79: ='.c12_oc_hr'!L31 -> 0 | M79: ='.c12_oc_hr'!M31 -> 0 | N79: ='.c12_oc_hr'!N31 -> 0 | O79: ='.c12_oc_hr'!O31 -> 0 | P79: ='.c12_oc_hr'!P31 -> 0 | Q79: ='.c12_oc_hr'!Q31 -> 0 | R79: ='.c12_oc_hr'!R31 -> 0 | S79: ='.c12_oc_hr'!S31 -> 0
A80: ='.c12_oc_hr'!A32 -> not reimbersable by hotel, but paid by lgh | L80: ='.c12_oc_hr'!L32 -> 472542.86 | M80: ='.c12_oc_hr'!M32 -> 472542.86 | N80: ='.c12_oc_hr'!N32 -> 472542.86 | O80: ='.c12_oc_hr'!O32 -> 472542.86 | P80: ='.c12_oc_hr'!P32 -> 805022.86 | Q80: ='.c12_oc_hr'!Q32 -> 383142.86 | R80: ='.c12_oc_hr'!R32 -> 383142.86 | S80: ='.c12_oc_hr'!S32 -> 902642.86
A81: ='.c12_oc_hr'!A33 -> only paid by c12 | L81: ='.c12_oc_hr'!L33 -> 31928.571 | M81: ='.c12_oc_hr'!M33 -> 31928.571 | N81: ='.c12_oc_hr'!N33 -> 31928.571 | O81: ='.c12_oc_hr'!O33 -> 42318.571 | P81: ='.c12_oc_hr'!P33 -> 58237.714 | Q81: ='.c12_oc_hr'!Q33 -> 58237.714 | R81: ='.c12_oc_hr'!R33 -> 58237.714 | S81: ='.c12_oc_hr'!S33 -> 79017.714
A83: lgh revenue
A84: hm | E84: 1639651 | L84: ='c12_hm'!L60 -> 558947 | M84: ='c12_hm'!M60 -> 558947 | N84: ='c12_hm'!N60 -> 558947 | O84: ='c12_hm'!O60 -> 447597 | P84: ='c12_hm'!P60 -> 310715.79 | Q84: ='c12_hm'!Q60 -> 902637.29 | R84: ='c12_hm'!R60 -> 948110.97 | S84: ='c12_hm'!S60 -> 2385063.6
A85: d&s | E85: 1480300 | L85: ='c12_d&s'!L60 -> 128735.5 | M85: ='c12_d&s'!M60 -> 128735.5 | N85: ='c12_d&s'!N60 -> 699135.5 | O85: ='c12_d&s'!O60 -> 911235.5 | P85: ='c12_d&s'!P60 -> 1735259.1 | Q85: ='c12_d&s'!Q60 -> 2473819.8 | R85: ='c12_d&s'!R60 -> 2205638.8 | S85: ='c12_d&s'!S60 -> 5828630.3
A86: bif | L86: ='c12_bi&F'!L60 -> 0 | M86: ='c12_bi&F'!M60 -> 0 | N86: ='c12_bi&F'!N60 -> 0 | O86: ='c12_bi&F'!O60 -> 0 | P86: ='c12_bi&F'!P60 -> 154294.74 | Q86: ='c12_bi&F'!Q60 -> 154294.74 | R86: ='c12_bi&F'!R60 -> 267978.95 | S86: ='c12_bi&F'!S60 -> 360942.11
A87: total rev attributable to lgh | B87: o | C87: total_lgh_revenue | L87: =SUM(L84:L86) -> 687682.5 | M87: =SUM(M84:M86) -> 687682.5 | N87: =SUM(N84:N86) -> 1258082.5 | O87: =SUM(O84:O86) -> 1358832.5 | P87: =SUM(P84:P86) -> 2200269.7 | Q87: =SUM(Q84:Q86) -> 3530751.8 | R87: =SUM(R84:R86) -> 3421728.7 | S87: =SUM(S84:S86) -> 8574636

Sheet c12_sk
A2: Year | E2: 45657 | F2: 45747 | G2: 45838 | H2: 45930 | I2: 46022 | J2: 46112 | K2: 46203 | L2: 45747 | M2: 45838 | N2: 45930 | O2: 46022 | P2: 46112 | Q2: 46203 | R2: 46295 | S2: 46387
E3: actual | L3: i/o
B4: i/o | C4: field_name | D4: index
A5: Bank transfers | B5: i | C5: bank_transfers | D5: sk | L5: =-7701527.99/4 -> -1925382 | M5: =L5 -> -1925382 | N5: =M5 -> -1925382 | O5: =N5 -> -1925382 | P5: =+P4 -> 0 | Q5: =+Q4 -> 0 | R5: =+R4 -> 0 | S5: =+S4 -> 0
A6: Departmental OOP paid via sk | B6: i | C6: ho_exp | D6: oop_sk | L6: -112553 | M6: -186705 | N6: -148699 | O6: -249431 | P6: -174347 | Q6: -174347 | R6: -174347 | S6: -174347 | T6: should come from danielle
A7: art lease payments to sk | B7: i | C7: lease_payments | D7: sk | E7: 0 | L7: 0 | M7: 0 | N7: 0 | O7: 0 | P7: 50000 | Q7: 50000 | R7: 50000 | S7: 50000
A8: guarantee fees to sk | B8: i | C8: guarantee_fees | D8: sk | E8: 0 | L8: -250000 | M8: -250000 | N8: -250000 | O8: -250000 | P8: -250000 | Q8: -250000 | R8: -250000 | S8: -250000
A9: cuda buy back | B9: i | C9: cuda_buyback | D9: sk | M9: -1200000

Sheet c12_bs
A2: Year | E2: 45657 | F2: 45747 | G2: 45838 | H2: 45930 | I2: 46022 | J2: 46112 | K2: 46203 | L2: 45747 | M2: 45838 | N2: 45930 | O2: 46022 | P2: 46112 | Q2: 46203 | R2: 46295 | S2: 46387
E3: actual | L3: i/o
B4: i/o | C4: field_name | D4: index
A5: assets
A6: cash open | E6: =0 -> 0 | I6: 9950 | J6: 9950 | L6: =E11 -> 9950 | M6: =L11 -> 9950 | N6: =M11 -> 9950 | O6: =N11 -> 9950 | P6: =O11 -> 9950 | Q6: =P11 -> 1303505.5 | R6: =Q11 -> 3524908.3 | S6: =R11 -> 5674178.4
A7: c12 profit | E7: ='c12_oc'!E47 -> 3119951 | I7: 860896.18 | J7: 828093.76 | L7: ='c12_oc'!L47 -> 591386.18 | M7: ='c12_oc'!M47 -> 591386.18 | N7: ='c12_oc'!N47 -> 876586.18 | O7: ='c12_oc'!O47 -> 860896.18 | P7: ='c12_oc'!P47 -> 828093.76 | Q7: ='c12_oc'!Q47 -> 1372055.8 | R7: ='c12_oc'!R47 -> 1299923.2 | S7: ='c12_oc'!S47 -> 2619479.6
A8: borrow from c12 loc | E8: =-'c12_oc'!E62 -> 1540999 | I8: -1009945.2 | J8: -383885.28 | L8: =-'c12_oc'!L62+'c12_oc'!E62+'c12_oc'!L61 -> 596442.82 | M8: =-'c12_oc'!M62+'c12_oc'!L62+'c12_oc'!M61 -> -677709.18 | N8: =-'c12_oc'!N62+'c12_oc'!M62+'c12_oc'!N61 -> 275096.82 | O8: =-'c12_oc'!O62+'c12_oc'!N62+'c12_oc'!O61 -> 190054.82 | P8: =-'c12_oc'!P62+'c12_oc'!O62+'c12_oc'!P61 -> -383885.28 | Q8: =-'c12_oc'!Q62+'c12_oc'!P62+'c12_oc'!Q61 -> 0 | R8: =-'c12_oc'!R62+'c12_oc'!Q62+'c12_oc'!R61 -> 0 | S8: =-'c12_oc'!S62+'c12_oc'!R62+'c12_oc'!S61 -> 0
A9: LGH to sk (from danielle) | E9: ='c12_oc'!E59 -> -4651000 | I9: 149049 | J9: 849347 | L9: ='c12_oc'!L59 -> -1187829 | M9: ='c12_oc'!M59 -> 86323.002 | N9: ='c12_oc'!N59 -> -1151683 | O9: ='c12_oc'!O59 -> -1050951 | P9: ='c12_oc'!P59 -> 849347 | Q9: ='c12_oc'!Q59 -> 849347 | R9: ='c12_oc'!R59 -> 849347 | S9: ='c12_oc'!S59 -> 849347
A10: c12 to sk (jp dist) | B10: i
A11: cash close | E11: =SUM(E6:E10) -> 9950 | I11: 9950 | J11: 1303505.5 | L11: =SUM(L6:L10) -> 9950 | M11: =SUM(M6:M10) -> 9950 | N11: =SUM(N6:N10) -> 9950 | O11: =SUM(O6:O10) -> 9950 | P11: =SUM(P6:P10) -> 1303505.5 | Q11: =SUM(Q6:Q10) -> 3524908.3 | R11: =SUM(R6:R10) -> 5674178.4 | S11: =SUM(S6:S10) -> 9143005
A12: participation accrual | E12: =-'c12_oc'!E74 -> 0 | I12: -2964570.5 | J12: -2970159.3 | L12: =-'c12_oc'!L74 -> -264555.12 | M12: =-'c12_oc'!M74 -> -1654110.2 | N12: =-'c12_oc'!N74 -> -2356165.4 | O12: =-'c12_oc'!O74 -> -2964570.5 | P12: =-'c12_oc'!P74 -> -2970159.3 | Q12: =-'c12_oc'!Q74 -> -2465036.1 | R12: =-'c12_oc'!R74 -> -2022503.4 | S12: =-'c12_oc'!S74 -> -1664945.5
A13: total assets | E13: =SUM(E11:E12) -> 9950 | I13: -2954620.5 | J13: -1666653.8 | L13: =SUM(L11:L12) -> -254605.12 | M13: =SUM(M11:M12) -> -1644160.2 | N13: =SUM(N11:N12) -> -2346215.4 | O13: =SUM(O11:O12) -> -2954620.5 | P13: =SUM(P11:P12) -> -1666653.8 | Q13: =SUM(Q11:Q12) -> 1059872.2 | R13: =SUM(R11:R12) -> 3651675 | S13: =SUM(S11:S12) -> 7478059.5
A15: liabilities
A16: c12loc | E16: ='c12_oc'!E62 -> -1540999 | I16: -1924884.3 | J16: 0 | L16: ='c12_oc'!L62 -> -2137441.8 | M16: ='c12_oc'!M62 -> -1459732.6 | N16: ='c12_oc'!N62 -> -1734829.5 | O16: ='c12_oc'!O62 -> -1924884.3 | P16: ='c12_oc'!P62 -> 0 | Q16: ='c12_oc'!Q62 -> 0 | R16: ='c12_oc'!R62 -> 0 | S16: ='c12_oc'!S62 -> 0
A18: NAV | E18: =E16+E13 -> -1531049 | I18: -4879504.8 | J18: -1666653.8 | L18: =L16+L13 -> -2392046.9 | M18: =M16+M13 -> -3103892.9 | N18: =N16+N13 -> -4081044.8 | O18: =O16+O13 -> -4879504.8 | P18: =P16+P13 -> -1666653.8 | Q18: =Q16+Q13 -> 1059872.2 | R18: =R16+R13 -> 3651675 | S18: =S16+S13 -> 7478059.5

Sheet c12_hm
A2: Year | E2: 45657 | F2: 45747 | G2: 45838 | H2: 45930 | I2: 46022 | J2: 46112 | K2: 46203 | L2: 45747 | M2: 45838 | N2: 45930 | O2: 46022 | P2: 46112 | Q2: 46203 | R2: 46295 | S2: 46387
E3: actual | L3: i/o
B4: i/o | C4: field_name | D4: index
A5: LGH Fee Revenue | C5: lgh_fee_revenue_section
A6: Bermuda PB Mgt | B6: i | C6: mgmt_fee | D6: pb | E6: 535096.5 | I6: 174125 | J6: 186369 | L6: =696500/4 -> 174125 | M6: =696500/4 -> 174125 | N6: =696500/4 -> 174125 | O6: =696500/4 -> 174125 | P6: =745476/4 -> 186369 | Q6: =745476/4 -> 186369 | R6: =745476/4 -> 186369 | S6: =745476/4 -> 186369 | T6: INPUT
A7: Bermuda PB Inc | B7: i | C7: incentive_fee | D7: pb | E7: 535096.5 | I7: 176042 | J7: 181323.26 | L7: =704168/4 -> 176042 | M7: =704168/4 -> 176042 | N7: =704168/4 -> 176042 | O7: =704168/4 -> 176042 | P7: =+O7*1.03 -> 181323.26 | Q7: =+P7 -> 181323.26 | R7: =+Q7 -> 181323.26 | S7: =+R7 -> 181323.26
A8: Austin Mgt | B8: i | C8: mgmt_fee | D8: austin | E8: 569458 | I8: 161030 | J8: 208682.75 | L8: =644120/4 -> 161030 | M8: =644120/4 -> 161030 | N8: =644120/4 -> 161030 | O8: =644120/4 -> 161030 | P8: =834731/4 -> 208682.75 | Q8: =834731/4 -> 208682.75 | R8: =834731/4 -> 208682.75 | S8: =834731/4 -> 208682.75
A9: Austin Inc | B9: i | C9: incentive_fee | D9: austin | I9: 70827.75 | J9: 72952.583 | L9: =283311/4 -> 70827.75 | M9: =283311/4 -> 70827.75 | N9: =283311/4 -> 70827.75 | O9: =283311/4 -> 70827.75 | P9: =+O9*1.03 -> 72952.583 | Q9: =+P9 -> 72952.583 | R9: =+Q9 -> 72952.583 | S9: =+R9 -> 72952.583
A10: Turks Mgt | B10: i | C10: mgmt_fee | D10: turks | I10: 0 | J10: 0 | L10: 0 | M10: 0 | N10: 0 | O10: 0 | P10: 0 | Q10: 0 | R10: 0 | S10: 0
A11: Turks Inc | B11: i | C11: incentive_fee | D11: turks
A12: Frithholme | B12: i | C12: mgmt_fee | D12: fritholme | I12: 0 | J12: 0 | L12: 0 | M12: 0 | N12: 0 | O12: 0 | P12: 0 | Q12: 0 | R12: 0 | S12: 0
A13: Elbow | B13: i | C13: mgmt_fee | D13: elbow | I13: 0 | J13: 0 | L13: 0 | M13: 0 | N13: 0 | O13: 0 | P13: 0
A14: [LSAT] | B14: i | C14: mgmt_fee | D14: lsat | S14: 0
A15: [blank]
A16: [blank]
A17: [blank]
A18: [blank]
A19: [blank]
A20: [blank]
A21: [blank]
A22: [blank]
A23: [blank]
A24: [L4] | B24: i | C24: mgmt_fee | D24: l4
A25: Total LGH Fees Earned | B25: c | C25: total_fees_earned | I25: 582024.75 | J25: 649327.59 | L25: =SUM(L6:L24) -> 582024.75 | M25: =SUM(M6:M24) -> 582024.75 | N25: =SUM(N6:N24) -> 582024.75 | O25: =SUM(O6:O24) -> 582024.75 | P25: =SUM(P6:P24) -> 649327.59 | Q25: =SUM(Q6:Q24) -> 649327.59 | R25: =SUM(R6:R24) -> 649327.59 | S25: =SUM(S6:S24) -> 649327.59
A27: Deferred Period Fee | B27: i | C27: deferred_fee | I27: -182177.75 | J27: -649327.59 | L27: =-L9 -> -70827.75 | M27: =-M9 -> -70827.75 | N27: =-N9 -> -70827.75 | O27: =-O9-111350 -> -182177.75 | P27: =-P25 -> -649327.59 | Q27: =-Q7-Q9 -> -254275.84 | R27: =-R7-R9 -> -254275.84 | S27: =-S7-S9-S14 -> -254275.84 | T27: INPUT
A28: Paid Fee Accruals | B28: i | C28: paid_fee_accruals | J28: 50000 | P28: 50000 | Q28: 246869.75 | R28: 246869.75 | S28: 1246869.8
A29: Cumm. Balance Accrued Fee | B29: c | C29: cumm_accrued_fee | I29: -394661 | J29: -993988.59 | L29: =+L27+E29+L28 -> -70827.75 | M29: =+M27+L29+M28 -> -141655.5 | N29: =+N27+M29+N28 -> -212483.25 | O29: =+O27+N29+O28 -> -394661 | P29: =+P27+O29+P28 -> -993988.59 | Q29: =+Q27+P29+Q28 -> -1001394.7 | R29: =+R27+Q29+R28 -> -1008800.8 | S29: =+S27+R29+S28 -> -16206.87
A31: Paid Current Fees | B31: c | C31: paid_current_fees | I31: 399847 | J31: 0 | L31: =+L25+L27 -> 511197 | M31: =+M25+M27 -> 511197 | N31: =+N25+N27 -> 511197 | O31: =+O25+O27 -> 399847 | P31: =+P25+P27 -> 0 | Q31: =+Q25+Q27 -> 395051.75 | R31: =+R25+R27 -> 395051.75 | S31: =+S25+S27 -> 395051.75
A32: Total Fees Paid | B32: c | C32: total_fees_paid | I32: 399847 | J32: 50000 | L32: =+L28+L31 -> 511197 | M32: =+M28+M31 -> 511197 | N32: =+N28+N31 -> 511197 | O32: =+O28+O31 -> 399847 | P32: =+P28+P31 -> 50000 | Q32: =+Q28+Q31 -> 641921.5 | R32: =+R28+R31 -> 641921.5 | S32: =+S28+S31 -> 1641921.5
A34: LGH Service Revenue
A35: Bermuda PB | B35: i | C35: hm_service_fee | D35: pb | I35: 47750 | J35: 0 | L35: =191000/4 -> 47750 | M35: =191000/4 -> 47750 | N35: =191000/4 -> 47750 | O35: =191000/4 -> 47750 | P35: 0 | Q35: 0 | R35: 0 | S35: 0 | T35: INPUT
A36: Austin | B36: i | C36: hm_service_fee | D36: austin | I36: 42250 | J36: 0 | L36: =169000/4 -> 42250 | M36: =169000/4 -> 42250 | N36: =169000/4 -> 42250 | O36: =169000/4 -> 42250 | P36: 0 | Q36: 0 | R36: 0 | S36: 0
A37: Turks | B37: i | C37: hm_service_fee | D37: turks | I37: 0 | J37: 0 | L37: 0 | M37: 0 | N37: 0 | O37: 0 | P37: 0 | Q37: 0 | R37: 0 | S37: 0
A38: Elbow | B38: i | C38: hm_service_fee | D38: elbow | I38: 0 | J38: 0 | L38: 0 | M38: 0 | N38: 0 | O38: 0 | P38: 0 | Q38: 0 | R38: 0 | S38: 0
A39: [blank]
A40: [blank]
A41: [blank]
A42: [blank]
A43: [blank]
A44: [blank]
A45: Frith | B45: i | C45: service_fee | D45: fritholme | I45: 0 | J45: 0 | L45: 0 | M45: 0 | N45: 0 | O45: 0 | P45: 0 | Q45: 0 | R45: 0 | S45: 0
A46: Total LGH HM Service Revenue | B46: c | C46: total_service_revenue | I46: 90000 | J46: 0 | L46: =SUM(L35:L45) -> 90000 | M46: =SUM(M35:M45) -> 90000 | N46: =SUM(N35:N45) -> 90000 | O46: =SUM(O35:O45) -> 90000 | P46: =SUM(P35:P45) -> 0 | Q46: =SUM(Q35:Q45) -> 0 | R46: =SUM(R35:R45) -> 0 | S46: =SUM(S35:S45) -> 0
A48: Deferred Period Fee | B48: i | C48: deferred_service_fee | I48: -42250 | J48: 0 | L48: -42250 | M48: -42250 | N48: -42250 | O48: -42250 | P48: 0 | Q48: =-SUM(Q35:Q45) -> 0 | R48: =-SUM(R35:R45) -> 0 | S48: =-SUM(S35:S45) -> 0 | T48: INPUT
A49: Paid Service Accruals | B49: i | C49: paid_service_accruals | S49: 169000
A50: Cumm. Balance Accrued Service Fee | B50: c | C50: cumm_accrued_service_fee | I50: -169000 | J50: -169000 | L50: =+L48+E50+L49 -> -42250 | M50: =+M48+L50+M49 -> -84500 | N50: =+N48+M50+N49 -> -126750 | O50: =+O48+N50+O49 -> -169000 | P50: =+P48+O50+P49 -> -169000 | Q50: =+Q48+P50+Q49 -> -169000 | R50: =+R48+Q50+R49 -> -169000 | S50: =+S48+R50+S49 -> 0
A52: Paid Current Service Fees | B52: c | C52: paid_current_service_fees | I52: 47750 | J52: 0 | L52: =+L46+L48 -> 47750 | M52: =+M46+M48 -> 47750 | N52: =+N46+N48 -> 47750 | O52: =+O46+O48 -> 47750 | P52: =+P46+P48 -> 0 | Q52: =+Q46+Q48 -> 0 | R52: =+R46+R48 -> 0 | S52: =+S46+S48 -> 0
A53: Total Service Revenue Paid | B53: c | C53: total_service_revenue_paid | I53: 47750 | J53: 0 | L53: =+L49+L52 -> 47750 | M53: =+M49+M52 -> 47750 | N53: =+N49+N52 -> 47750 | O53: =+O49+O52 -> 47750 | P53: =+P49+P52 -> 0 | Q53: =+Q49+Q52 -> 0 | R53: =+R49+R52 -> 0 | S53: =+S49+S52 -> 169000
A55: LGH Chargebacks
A56: chargeback fee | B56: c | C56: chargeback_multiplier | I56: 1.0526316 | J56: 1.0526316 | L56: =1/(1-'c12_inputs'!$E$7) -> 1.0526316 | M56: =1/(1-'c12_inputs'!$E$7) -> 1.0526316 | N56: =1/(1-'c12_inputs'!$E$7) -> 1.0526316 | O56: =1/(1-'c12_inputs'!$E$7) -> 1.0526316 | P56: =1/(1-'c12_inputs'!$E$7) -> 1.0526316 | Q56: =1/(1-'c12_inputs'!$E$7) -> 1.0526316 | R56: =1/(1-'c12_inputs'!$E$7) -> 1.0526316 | S56: =1/(1-'c12_inputs'!$E$7) -> 1.0526316
A57: reimbursable by hotels to LGH | B57: o | C57: reimbursable_by_hotels | F57: 0 | G57: 0 | H57: 0 | I57: 0 | J57: 247680 | L57: =IF(AND((F57<>""),(L$2<46204)),(F57),L78) -> 0 | M57: =IF(AND((G57<>""),(M$2<46204)),(G57),M78) -> 0 | N57: =IF(AND((H57<>""),(N$2<46204)),(H57),N78) -> 0 | O57: =IF(AND((I57<>""),(O$2<46204)),(I57),O78) -> 0 | P57: =IF(AND((J57<>""),(P$2<46204)),(J57),P78) -> 247680 | Q57: =IF(AND((K57<>""),(Q$2<46204)),(K57),Q78) -> 247680 | R57: =IF(AND((L57<>""),(R$2<46204)),(L57),R78) -> 290880 | S57: =IF(AND((M57<>""),(S$2<46204)),(M57),S78) -> 545435
A58: Total LGH HM Charge Back | B58: c | C58: total_chargeback | I58: 0 | J58: 260715.79 | L58: =L57*L56 -> 0 | M58: =M57*M56 -> 0 | N58: =N57*N56 -> 0 | O58: =O57*O56 -> 0 | P58: =P57*P56 -> 260715.79 | Q58: =Q57*Q56 -> 260715.79 | R58: =R57*R56 -> 306189.47 | S58: =S57*S56 -> 574142.11
A60: total LGH HM revenue | B60: o | C60: total_lgh_hm_revenue | I60: 447597 | J60: 310715.79 | L60: =+L53+L32+L58 -> 558947 | M60: =+M53+M32+M58 -> 558947 | N60: =+N53+N32+N58 -> 558947 | O60: =+O53+O32+O58 -> 447597 | P60: =+P53+P32+P58 -> 310715.79 | Q60: =+Q53+Q32+Q58 -> 902637.29 | R60: =+R53+R32+R58 -> 948110.97 | S60: =+S53+S32+S58 -> 2385063.6
A62: LGH Accounts Receivable Cumm. | B62: o | C62: lgh_ar_cumm | I62: -563661 | J62: -1162988.6 | L62: =+L29+L50 -> -113077.75 | M62: =+M29+M50 -> -226155.5 | N62: =+N29+N50 -> -339233.25 | O62: =+O29+O50 -> -563661 | P62: =+P29+P50 -> -1162988.6 | Q62: =+Q29+Q50 -> -1170394.7 | R62: =+R29+R50 -> -1177800.8 | S62: =+S29+S50 -> -16206.87
A64: C12 Participation % | B64: c | C64: c12_participation_pct | I64: 0.35 | J64: 0.35 | L64: ='c12_inputs'!$E$8 -> 0.35 | M64: ='c12_inputs'!$E$8 -> 0.35 | N64: ='c12_inputs'!$E$8 -> 0.35 | O64: ='c12_inputs'!$E$8 -> 0.35 | P64: ='c12_inputs'!$E$8 -> 0.35 | Q64: ='c12_inputs'!$E$8 -> 0.35 | R64: ='c12_inputs'!$E$8 -> 0.35 | S64: ='c12_inputs'!$E$8 -> 0.35
A65: pre-modification extra | B65: i | C65: pre_mod_extra_pct | I65: 0.65 | J65: 0 | L65: 0.65 | M65: 0.65 | N65: 0.65 | O65: 0.65 | P65: 0 | Q65: 0 | R65: 0 | S65: 0
A66: catchup extra% | B66: i | C66: catchup_extra_pct | I66: 0.65 | J66: 0.65 | L66: 0.65 | M66: 0.65 | N66: 0.65 | O66: 0.65 | P66: 0.65 | Q66: 0.65 | R66: 0.65 | S66: 0
A67: charge back percentrage | B67: c | C67: chargeback_pct | I67: 0.05 | J67: 0.05 | L67: ='c12_inputs'!$E$7 -> 0.05 | M67: ='c12_inputs'!$E$7 -> 0.05 | N67: ='c12_inputs'!$E$7 -> 0.05 | O67: ='c12_inputs'!$E$7 -> 0.05 | P67: ='c12_inputs'!$E$7 -> 0.05 | Q67: ='c12_inputs'!$E$7 -> 0.05 | R67: ='c12_inputs'!$E$7 -> 0.05 | S67: ='c12_inputs'!$E$7 -> 0.05
A68: C12 Participation $ | B68: c | C68: c12_participation_amt | I68: 447597 | J68: 50000 | L68: =(L64+L65)*(L31+L52)+(L64+L66)*(L49+L28) -> 558947 | M68: =(M64+M65)*(M31+M52)+(M64+M66)*(M49+M28) -> 558947 | N68: =(N64+N65)*(N31+N52)+(N64+N66)*(N49+N28) -> 558947 | O68: =(O64+O65)*(O31+O52)+(O64+O66)*(O49+O28) -> 447597 | P68: =(P64+P65)*(P31+P52)+(P64+P66)*(P49+P28) -> 50000 | Q68: =(Q64+Q65)*(Q31+Q52)+(Q64+Q66)*(Q49+Q28) -> 385137.86 | R68: =(R64+R65)*(R31+R52)+(R64+R66)*(R49+R28) -> 385137.86 | S68: =(S64+S65)*(S31+S52)+(S64+S66)*(S49+S28) -> 633822.52
A69: chargebacks fees | B69: c | C69: chargeback_fees | I69: 0 | J69: 13035.789 | L69: =L67*L58 -> 0 | M69: =M67*M58 -> 0 | N69: =N67*N58 -> 0 | O69: =O67*O58 -> 0 | P69: =P67*P58 -> 13035.789 | Q69: =Q67*Q58 -> 13035.789 | R69: =R67*R58 -> 15309.474 | S69: =S67*S58 -> 28707.105
A70: Total C12 HM revenue | B70: o | C70: total_c12_hm_revenue | I70: 447597 | J70: 63035.789 | L70: =L69+L68 -> 558947 | M70: =M69+M68 -> 558947 | N70: =N69+N68 -> 558947 | O70: =O69+O68 -> 447597 | P70: =P69+P68 -> 63035.789 | Q70: =Q69+Q68 -> 398173.65 | R70: =R69+R68 -> 400447.34 | S70: =S69+S68 -> 662529.63
A72: increase in accrued participation | B72: c | C72: increase_accrued_participation | I72: 224427.75 | J72: 227264.66 | L72: =-(L64+L65)*(L27+L48) -> 113077.75 | M72: =-(M64+M65)*(M27+M48) -> 113077.75 | N72: =-(N64+N65)*(N27+N48) -> 113077.75 | O72: =-(O64+O65)*(O27+O48) -> 224427.75 | P72: =-(P64+P65)*(P27+P48) -> 227264.66 | Q72: =-(Q64+Q65)*(Q27+Q48) -> 88996.545 | R72: =-(R64+R65)*(R27+R48) -> 88996.545 | S72: =-(S64+S65)*(S27+S48) -> 88996.545
A73: decrease in accrued partipation | B73: c | C73: decrease_accrued_participation | I73: 0 | J73: -50000 | L73: =-(L64+L66)*(L28+L49) -> 0 | M73: =-(M64+M66)*(M28+M49) -> 0 | N73: =-(N64+N66)*(N28+N49) -> 0 | O73: =-(O64+O66)*(O28+O49) -> 0 | P73: =-(P64+P66)*(P28+P49) -> -50000 | Q73: =-(Q64+Q66)*(Q28+Q49) -> -246869.75 | R73: =-(R64+R66)*(R28+R49) -> -246869.75 | S73: =-(S64+S66)*(S28+S49) -> -495554.41
A74: Cumm. Total Accrued Participation | B74: o | C74: cumm_accrued_participation | I74: 563661 | J74: 740925.66 | L74: =SUM(L72:L73)+E74 -> 113077.75 | M74: =SUM(M72:M73)+L74 -> 226155.5 | N74: =SUM(N72:N73)+M74 -> 339233.25 | O74: =SUM(O72:O73)+N74 -> 563661 | P74: =SUM(P72:P73)+O74 -> 740925.66 | Q74: =SUM(Q72:Q73)+P74 -> 583052.45 | R74: =SUM(R72:R73)+Q74 -> 425179.25 | S74: =SUM(S72:S73)+R74 -> 18621.38 | T74: if paydown % were correct then this last number would be zeri
A76: from HR sheet
A77: Grand Total | B77: c | C77: hr_grand_total | I77: 770825 | J77: 391680 | L77: ='.c12_hm_hr'!L31 -> 298080 | M77: ='.c12_hm_hr'!M31 -> 298080 | N77: ='.c12_hm_hr'!N31 -> 298080 | O77: ='.c12_hm_hr'!O31 -> 770825 | P77: ='.c12_hm_hr'!P31 -> 391680 | Q77: ='.c12_hm_hr'!Q31 -> 391680 | R77: ='.c12_hm_hr'!R31 -> 434880 | S77: ='.c12_hm_hr'!S31 -> 949185
A78: reimbersable to hotel | B78: o | C78: hr_reimbursable | I78: 367075 | J78: 247680 | L78: ='.c12_hm_hr'!L32 -> 154080 | M78: ='.c12_hm_hr'!M32 -> 154080 | N78: ='.c12_hm_hr'!N32 -> 154080 | O78: ='.c12_hm_hr'!O32 -> 367075 | P78: ='.c12_hm_hr'!P32 -> 247680 | Q78: ='.c12_hm_hr'!Q32 -> 247680 | R78: ='.c12_hm_hr'!R32 -> 290880 | S78: ='.c12_hm_hr'!S32 -> 545435
A79: not reimbersable by hotel, but paid by lgh | B79: o | C79: hr_not_reimbursable | I79: 403750 | J79: 144000 | L79: ='.c12_hm_hr'!L33 -> 144000 | M79: ='.c12_hm_hr'!M33 -> 144000 | N79: ='.c12_hm_hr'!N33 -> 144000 | O79: ='.c12_hm_hr'!O33 -> 403750 | P79: ='.c12_hm_hr'!P33 -> 144000 | Q79: ='.c12_hm_hr'!Q33 -> 144000 | R79: ='.c12_hm_hr'!R33 -> 144000 | S79: ='.c12_hm_hr'!S33 -> 403750
A80: only paid by c12 | B80: c | C80: hr_only_c12 | I80: 0 | J80: 0 | L80: ='.c12_hm_hr'!L34 -> 0 | M80: ='.c12_hm_hr'!M34 -> 0 | N80: ='.c12_hm_hr'!N34 -> 0 | O80: ='.c12_hm_hr'!O34 -> 0 | P80: ='.c12_hm_hr'!P34 -> 0 | Q80: ='.c12_hm_hr'!Q34 -> 0 | R80: ='.c12_hm_hr'!R34 -> 0 | S80: ='.c12_hm_hr'!S34 -> 0

Sheet c12_d&s
A2: Year | E2: 45657 | F2: 45747 | G2: 45838 | H2: 45930 | I2: 46022 | J2: 46112 | K2: 46203 | L2: 45747 | M2: 45838 | N2: 45930 | O2: 46022 | P2: 46112 | Q2: 46203 | R2: 46295 | S2: 46387
E3: actual | L3: i/o
B4: i/o | C4: field_name | D4: index
A5: LGH Fee Revenue
A6: Pink Beach Design Fee | B6: i | C6: design_fee | D6: pb | I6: 0 | J6: 0 | O6: 0 | P6: 0 | Q6: 0 | R6: 0 | S6: 0
A7: Pink Beach Development Fee | B7: i | C7: development_fee | D7: pb | I7: 0 | J7: 0 | O7: 0 | P7: 0 | Q7: 0 | R7: 0 | S7: 0
A8: Pink Beach Structuring Fee | B8: i | C8: structuring_fee | D8: pb | N8: =520000 -> 520000 | Q8: 0 | S8: 0
A9: Austin Design Fee | B9: i | C9: design_fee | D9: austin | I9: 0 | J9: 0 | O9: 0 | P9: 0 | Q9: 0 | R9: 0 | S9: 0
A10: Austin Development Fee | B10: i | C10: development_fee | D10: austin | I10: 0 | J10: 0 | O10: 0 | P10: 0 | Q10: 0 | R10: 0 | S10: 0
A11: Turks Design Fee | B11: i | C11: design_fee | D11: turks | I11: 50000 | J11: 0 | O11: 50000 | P11: 0 | Q11: 0 | R11: 0 | S11: 0
A12: Turks Development Fee | B12: i | C12: development_fee | D12: turks | E12: 812800 | I12: 340000 | J12: 549375 | L12: 280000 | M12: 280000 | N12: 280000 | O12: 340000 | P12: =2930000/16*3 -> 549375 | Q12: =2930000/16*3 -> 549375 | R12: =2930000/16*3 -> 549375 | S12: =2930000/16*3 -> 549375
A13: Turks Structuring Fee | B13: i | C13: structuring_fee | D13: turks | I13: 250000 | J13: 0 | O13: 250000 | P13: 0 | Q13: 0 | R13: 0 | S13: 0
A14: Elbow Design Fee | B14: i | C14: design_fee | D14: elbow | I14: 375000 | J14: 487500 | N14: =750000/2 -> 375000 | O14: =750000/2 -> 375000 | P14: =(4500000*0.6-SUM($N$14:$O$14))/4 -> 487500 | Q14: =(4500000*0.6-SUM($N$14:$O$14))/4 -> 487500 | R14: =(4500000*0.6-SUM($N$14:$O$14))/4 -> 487500 | S14: =(4500000*0.6-SUM($N$14:$O$14))/4 -> 487500
A15: Elbow Development Fee | B15: i | C15: development_fee | D15: elbow | I15: 500000 | J15: 433333.33 | N15: =1000000/2 -> 500000 | O15: =1000000/2 -> 500000 | P15: =5200000/3/4 -> 433333.33 | Q15: =5200000/3/4 -> 433333.33 | R15: =5200000/3/4 -> 433333.33 | S15: =5200000/3/4 -> 433333.33
A16: Elbow Structuring Fee | B16: i | C16: structuring_fee | D16: elbow | I16: 0 | J16: 0 | L16: 0 | M16: 0 | N16: 0 | O16: 0 | P16: 0 | Q16: 0 | R16: 0 | S16: 0
A17: Elbow Construction Fee | B17: i | C17: construction_fee | D17: elbow | J17: 0 | P17: 0 | Q17: 0 | R17: 0 | S17: 0
A18: Elbow Acquisition Fee | B18: i | C18: acquisition_fee | D18: elbow | M18: 1000000
A19: [blank] | I19: 0 | J19: 0 | L19: 0 | M19: 0 | N19: 0 | O19: 0 | P19: 0 | Q19: 0 | R19: 0 | S19: 0
A20: Frith Acq Fee | B20: i | C20: acquisition_fee | D20: fritholme | I20: 0 | J20: 0 | L20: 0 | M20: 1250000 | N20: 0 | O20: 0 | P20: 0 | Q20: 0 | R20: 0 | S20: 0
A21: [blank] | I21: 0 | J21: 0 | L21: 0 | M21: 0 | N21: 0 | O21: 0 | P21: 0 | Q21: 0 | R21: 0 | S21: 0
A22: Frith Disposition fee | B22: i | C22: disposition_fee | D22: fritholme | I22: 0 | J22: 0 | O22: 0 | P22: 0 | Q22: 0 | R22: 0 | S22: 2500000
A23: SAT | B23: i | C23: development_fee | D23: lsat | S23: =500000+1600000 -> 2100000
A24: [L4] | B24: i | C24: development_fee | D24: l4 | R24: 0 | S24: 0
A25: Total LGH Fees Earned | B25: c | C25: total_fees_earned | I25: 1515000 | J25: 1470208.3 | L25: =SUM(L6:L24) -> 280000 | M25: =SUM(M6:M24) -> 2530000 | N25: =SUM(N6:N24) -> 1675000 | O25: =SUM(O6:O24) -> 1515000 | P25: =SUM(P6:P24) -> 1470208.3 | Q25: =SUM(Q6:Q24) -> 1470208.3 | R25: =SUM(R6:R24) -> 1470208.3 | S25: =SUM(S6:S24) -> 6070208.3
A27: Deferred Period Fee | B27: i | C27: deferred_fee | I27: -745000 | J27: -1470208 | L27: =-SUM(L6:L24) -> -280000 | M27: =-SUM(M6:M24) -> -2530000 | N27: -1155000 | O27: -745000 | P27: -1470208 | Q27: =-1000000+310000 -> -690000 | R27: -1000000 | S27: -2100000
A28: Paid Fee Accruals | B28: i | C28: paid_fee_accruals | J28: 1508647.3 | P28: 1508647.3 | Q28: 1177500 | R28: 1177500 | S28: 1177500
A29: Cumm. Balance Accrued Fee | B29: c | C29: cumm_accrued_fee | I29: -4710000 | J29: -4671560.7 | L29: =+L27+E29+L28 -> -280000 | M29: =+M27+L29+M28 -> -2810000 | N29: =+N27+M29+N28 -> -3965000 | O29: =+O27+N29+O28 -> -4710000 | P29: =+P27+O29+P28 -> -4671560.7 | Q29: =+Q27+P29+Q28 -> -4184060.7 | R29: =+R27+Q29+R28 -> -4006560.7 | S29: =+S27+R29+S28 -> -4929060.7
A31: Paid Current Fees | B31: c | C31: paid_current_fees | I31: 770000 | J31: 0.33333333 | L31: =+L25+L27 -> 0 | M31: =+M25+M27 -> 0 | N31: =+N25+N27 -> 520000 | O31: =+O25+O27 -> 770000 | P31: =+P25+P27 -> 0.33333333 | Q31: =+Q25+Q27 -> 780208.33 | R31: =+R25+R27 -> 470208.33 | S31: =+S25+S27 -> 3970208.3
A32: Total Fees Paid | B32: c | C32: total_fees_paid | I32: 770000 | J32: 1508647.7 | L32: =+L28+L31 -> 0 | M32: =+M28+M31 -> 0 | N32: =+N28+N31 -> 520000 | O32: =+O28+O31 -> 770000 | P32: =+P28+P31 -> 1508647.7 | Q32: =+Q28+Q31 -> 1957708.3 | R32: =+R28+R31 -> 1647708.3 | S32: =+S28+S31 -> 5147708.3
A34: LGH Service Revenue
A35: PB Design Services | B35: i | C35: design_service_fee | D35: pb | I35: 22110.5 | J35: 45000 | L35: =88442/4 -> 22110.5 | M35: =88442/4 -> 22110.5 | N35: =88442/4 -> 22110.5 | O35: =88442/4 -> 22110.5 | P35: =180000/4 -> 45000 | Q35: =180000/4 -> 45000 | R35: =180000/4 -> 45000 | S35: =180000/4 -> 45000
A36: Austin Design Services | B36: i | C36: design_service_fee | D36: austin | E36: 667500 | I36: 22954.75 | J36: 60000 | L36: =91819/4 -> 22954.75 | M36: =91819/4 -> 22954.75 | N36: =91819/4 -> 22954.75 | O36: =91819/4 -> 22954.75 | P36: =240000/4 -> 60000 | Q36: =240000/4 -> 60000 | R36: =240000/4 -> 60000 | S36: =240000/4 -> 60000
A37: Turks Design Services | B37: i | C37: design_service_fee | D37: turks | I37: 0 | J37: 50000 | L37: =200000/4*0 -> 0 | M37: =200000/4*0 -> 0 | N37: =200000/4*0 -> 0 | O37: =200000/4*0 -> 0 | P37: =200000/4 -> 50000 | Q37: =400000/4 -> 100000 | R37: =200000/4 -> 50000 | S37: =200000/4 -> 50000
A38: Elbow Design Services | B38: i | C38: design_service_fee | D38: elbow | I38: 0 | J38: 0 | L38: 0 | M38: 0 | N38: 0 | O38: 0 | P38: 0 | Q38: =180000/4 -> 45000 | R38: =180000/4 -> 45000 | S38: =+R38 -> 45000
A39: Elbow AM | B39: i | C39: am_fee | D39: elbow | I39: 0 | J39: 0 | L39: 0 | M39: 0 | N39: 0 | O39: 0 | P39: 0 | Q39: 0 | R39: 0 | S39: 0
A40: Frith Design Services | B40: i | C40: design_service_fee | D40: fritholme | I40: 0 | J40: 27000 | M40: =108000/4*0 -> 0 | N40: =108000/4*0 -> 0 | O40: =108000/4*0 -> 0 | P40: =108000/4 -> 27000 | Q40: =+P40 -> 27000 | R40: =+Q40 -> 27000 | S40: =+R40 -> 27000
A41: Frith AM | B41: i | C41: am_fee | D41: fritholme | I41: 12500 | J41: 12500 | L41: 0 | M41: 0 | N41: 50400 | O41: 12500 | P41: 12500 | Q41: 12500 | R41: 12500
A42: Bermuda PB AM | B42: i | C42: am_fee | D42: pb | I42: 57077.25 | J42: 72879 | L42: 57077.25 | M42: 57077.25 | N42: 57077.25 | O42: 57077.25 | P42: 72879 | Q42: 72879 | R42: 72879 | S42: 72879
A43: AustinAM | B43: i | C43: am_fee | D43: austin | I43: 49547.75 | J43: 63543 | L43: 49547.75 | M43: 49547.75 | N43: 49547.75 | O43: 49547.75 | P43: 63543 | Q43: 63543 | R43: 63543 | S43: 63543
A44: [blank]
A45: SAT | B45: i | C45: design_service_fee | D45: sat
A46: Total LGH HM Service Revenue | B46: c | C46: total_service_revenue | I46: 164190.25 | J46: 330922 | L46: =SUM(L35:L45) -> 151690.25 | M46: =SUM(M35:M45) -> 151690.25 | N46: =SUM(N35:N45) -> 202090.25 | O46: =SUM(O35:O45) -> 164190.25 | P46: =SUM(P35:P45) -> 330922 | Q46: =SUM(Q35:Q45) -> 425922 | R46: =SUM(R35:R45) -> 375922 | S46: =SUM(S35:S45) -> 363422
A48: Deferred Period Fee | B48: i | C48: deferred_service_fee | I48: -22954.75 | J48: -194500 | L48: =-L36 -> -22954.75 | M48: =-M36 -> -22954.75 | N48: =-N36 -> -22954.75 | O48: =-O36 -> -22954.75 | P48: -194500
A49: Paid Accruals | B49: i | C49: paid_service_accruals | R49: 91819 | S49: 194500
A50: Cumm. Balance Accrued Service Fee | B50: c | C50: cumm_accrued_service_fee | I50: -91819 | J50: -286319 | L50: =+L48+E50+L49 -> -22954.75 | M50: =+M48+L50+M49 -> -45909.5 | N50: =+N48+M50+N49 -> -68864.25 | O50: =+O48+N50+O49 -> -91819 | P50: =+P48+O50+P49 -> -286319 | Q50: =+Q48+P50+Q49 -> -286319 | R50: =+R48+Q50+R49 -> -194500 | S50: =+S48+R50+S49 -> 0
A52: Paid Current Service Fees | B52: c | C52: paid_current_service_fees | I52: 141235.5 | J52: 136422 | L52: =+L46+L48 -> 128735.5 | M52: =+M46+M48 -> 128735.5 | N52: =+N46+N48 -> 179135.5 | O52: =+O46+O48 -> 141235.5 | P52: =+P46+P48 -> 136422 | Q52: =+Q46+Q48 -> 425922 | R52: =+R46+R48 -> 375922 | S52: =+S46+S48 -> 363422
A53: Total Service Revenue Paid | B53: c | C53: total_service_revenue_paid | I53: 141235.5 | J53: 136422 | L53: =+L49+L52 -> 128735.5 | M53: =+M49+M52 -> 128735.5 | N53: =+N49+N52 -> 179135.5 | O53: =+O49+O52 -> 141235.5 | P53: =+P49+P52 -> 136422 | Q53: =+Q49+Q52 -> 425922 | R53: =+R49+R52 -> 467741 | S53: =+S49+S52 -> 557922
A55: LGH Chargebacks
A56: chargeback fee | B56: c | C56: chargeback_multiplier | I56: 1.0526316 | J56: 1.0526316 | L56: =1/(1-'c12_inputs'!$E$7) -> 1.0526316 | M56: =1/(1-'c12_inputs'!$E$7) -> 1.0526316 | N56: =1/(1-'c12_inputs'!$E$7) -> 1.0526316 | O56: =1/(1-'c12_inputs'!$E$7) -> 1.0526316 | P56: =1/(1-'c12_inputs'!$E$7) -> 1.0526316 | Q56: =1/(1-'c12_inputs'!$E$7) -> 1.0526316 | R56: =1/(1-'c12_inputs'!$E$7) -> 1.0526316 | S56: =1/(1-'c12_inputs'!$E$7) -> 1.0526316
A57: reimbursable by hotels to LGH | B57: o | C57: reimbursable_by_hotels | F57: 0 | G57: 0 | H57: 0 | I57: 0 | J57: 85680 | L57: =IF(AND((F57<>""),(L$2<46204)),(F57),L78) -> 0 | M57: =IF(AND((G57<>""),(M$2<46204)),(G57),M78) -> 0 | N57: =IF(AND((H57<>""),(N$2<46204)),(H57),N78) -> 0 | O57: =IF(AND((I57<>""),(O$2<46204)),(I57),O78) -> 0 | P57: =IF(AND((J57<>""),(P$2<46204)),(J57),P78) -> 85680 | Q57: =IF(AND((K57<>""),(Q$2<46204)),(K57),Q78) -> 85680 | R57: =IF(AND((L57<>""),(R$2<46204)),(L57),R78) -> 85680 | S57: =IF(AND((M57<>""),(S$2<46204)),(M57),S78) -> 116850
A58: Total LGH D&S Charge Back chk | B58: c | C58: total_chargeback | I58: 0 | J58: 90189.474 | L58: =L57*L56 -> 0 | M58: =M57*M56 -> 0 | N58: =N57*N56 -> 0 | O58: =O57*O56 -> 0 | P58: =P57*P56 -> 90189.474 | Q58: =Q57*Q56 -> 90189.474 | R58: =R57*R56 -> 90189.474 | S58: =S57*S56 -> 123000
A60: total LGH D&S revenue | B60: o | C60: total_lgh_ds_revenue | I60: 911235.5 | J60: 1735259.1 | L60: =+L53+L32+L58 -> 128735.5 | M60: =+M53+M32+M58 -> 128735.5 | N60: =+N53+N32+N58 -> 699135.5 | O60: =+O53+O32+O58 -> 911235.5 | P60: =+P53+P32+P58 -> 1735259.1 | Q60: =+Q53+Q32+Q58 -> 2473819.8 | R60: =+R53+R32+R58 -> 2205638.8 | S60: =+S53+S32+S58 -> 5828630.3
A62: LGH Accounts Receivable Cumm. | B62: o | C62: lgh_ar_cumm | I62: -4801819 | J62: -4957879.7 | L62: =+L29+L50 -> -302954.75 | M62: =+M29+M50 -> -2855909.5 | N62: =+N29+N50 -> -4033864.2 | O62: =+O29+O50 -> -4801819 | P62: =+P29+P50 -> -4957879.7 | Q62: =+Q29+Q50 -> -4470379.7 | R62: =+R29+R50 -> -4201060.7 | S62: =+S29+S50 -> -4929060.7
A64: C12 Participation % | B64: c | C64: c12_participation_pct | I64: 0.35 | J64: 0.35 | L64: ='c12_inputs'!$E$8 -> 0.35 | M64: ='c12_inputs'!$E$8 -> 0.35 | N64: ='c12_inputs'!$E$8 -> 0.35 | O64: ='c12_inputs'!$E$8 -> 0.35 | P64: ='c12_inputs'!$E$8 -> 0.35 | Q64: ='c12_inputs'!$E$8 -> 0.35 | R64: ='c12_inputs'!$E$8 -> 0.35 | S64: ='c12_inputs'!$E$8 -> 0.35
A65: pre-modification extra | B65: i | C65: pre_mod_extra_pct | I65: 0.15 | J65: 0 | L65: 0.15 | M65: 0.15 | N65: 0.15 | O65: 0.15 | P65: 0 | Q65: 0 | R65: 0 | S65: 0
A66: catchup extra% | B66: i | C66: catchup_extra_pct | I66: 0.15 | J66: 0.15 | L66: 0.15 | M66: 0.15 | N66: 0.15 | O66: 0.15 | P66: 0.15 | Q66: 0.15 | R66: 0.15 | S66: 0.15
A67: charge back percentrage | B67: c | C67: chargeback_pct | I67: 0.05 | J67: 0.05 | L67: ='c12_inputs'!$E$7 -> 0.05 | M67: ='c12_inputs'!$E$7 -> 0.05 | N67: ='c12_inputs'!$E$7 -> 0.05 | O67: ='c12_inputs'!$E$7 -> 0.05 | P67: ='c12_inputs'!$E$7 -> 0.05 | Q67: ='c12_inputs'!$E$7 -> 0.05 | R67: ='c12_inputs'!$E$7 -> 0.05 | S67: ='c12_inputs'!$E$7 -> 0.05
A68: C12 Participation $ | B68: c | C68: c12_participation_amt | I68: 455617.75 | J68: 802071.48 | L68: =(L64+L65)*(L31+L52)+(L64+L66)*(L49+L28) -> 64367.75 | M68: =(M64+M65)*(M31+M52)+(M64+M66)*(M49+M28) -> 64367.75 | N68: =(N64+N65)*(N31+N52)+(N64+N66)*(N49+N28) -> 349567.75 | O68: =(O64+O65)*(O31+O52)+(O64+O66)*(O49+O28) -> 455617.75 | P68: =(P64+P65)*(P31+P52)+(P64+P66)*(P49+P28) -> 802071.48 | Q68: =(Q64+Q65)*(Q31+Q52)+(Q64+Q66)*(Q49+Q28) -> 1010895.6 | R68: =(R64+R65)*(R31+R52)+(R64+R66)*(R49+R28) -> 930805.12 | S68: =(S64+S65)*(S31+S52)+(S64+S66)*(S49+S28) -> 2202770.6
A69: chargebacks fees | B69: c | C69: chargeback_fees | I69: 0 | J69: 4509.4737 | L69: =L67*L58 -> 0 | M69: =M67*M58 -> 0 | N69: =N67*N58 -> 0 | O69: =O67*O58 -> 0 | P69: =P67*P58 -> 4509.4737 | Q69: =Q67*Q58 -> 4509.4737 | R69: =R67*R58 -> 4509.4737 | S69: =S67*S58 -> 6150
A70: Total C12 D&S revenue | B70: o | C70: total_c12_ds_revenue | I70: 455617.75 | J70: 806580.95 | L70: =L69+L68 -> 64367.75 | M70: =M69+M68 -> 64367.75 | N70: =N69+N68 -> 349567.75 | O70: =O69+O68 -> 455617.75 | P70: =P69+P68 -> 806580.95 | Q70: =Q69+Q68 -> 1015405.1 | R70: =R69+R68 -> 935314.59 | S70: =S69+S68 -> 2208920.6
A72: increase in accrued participation | B72: c | C72: increase_accrued_participation | I72: 383977.38 | J72: 582647.8 | L72: =-(L64+L65)*(L27+L48) -> 151477.38 | M72: =-(M64+M65)*(M27+M48) -> 1276477.4 | N72: =-(N64+N65)*(N27+N48) -> 588977.38 | O72: =-(O64+O65)*(O27+O48) -> 383977.38 | P72: =-(P64+P65)*(P27+P48) -> 582647.8 | Q72: =-(Q64+Q65)*(Q27+Q48) -> 241500 | R72: =-(R64+R65)*(R27+R48) -> 350000 | S72: =-(S64+S65)*(S27+S48) -> 735000
A73: decrease in accrued partipation | B73: c | C73: decrease_accrued_participation | I73: 0 | J73: -754323.66 | L73: =-(L64+L66)*(L28+L49) -> 0 | M73: =-(M64+M66)*(M28+M49) -> 0 | N73: =-(N64+N66)*(N28+N49) -> 0 | O73: =-(O64+O66)*(O28+O49) -> 0 | P73: =-(P64+P66)*(P28+P49) -> -754323.66 | Q73: =-(Q64+Q66)*(Q28+Q49) -> -588750 | R73: =-(R64+R66)*(R28+R49) -> -634659.5 | S73: =-(S64+S66)*(S28+S49) -> -686000
A74: Cumm. Total Accrued Participation | B74: o | C74: cumm_accrued_participation | I74: 2400909.5 | J74: 2229233.6 | L74: =SUM(L72:L73)+E74 -> 151477.38 | M74: =SUM(M72:M73)+L74 -> 1427954.8 | N74: =SUM(N72:N73)+M74 -> 2016932.1 | O74: =SUM(O72:O73)+N74 -> 2400909.5 | P74: =SUM(P72:P73)+O74 -> 2229233.6 | Q74: =SUM(Q72:Q73)+P74 -> 1881983.6 | R74: =SUM(R72:R73)+Q74 -> 1597324.1 | S74: =SUM(S72:S73)+R74 -> 1646324.1
A76: from HR sheet
A77: Grand Total | B77: c | C77: hr_grand_total | I77: 1652177.5 | J77: 560160 | L77: ='.c12_d&s_hr'!L45 -> 515520 | M77: ='.c12_d&s_hr'!M45 -> 515520 | N77: ='.c12_d&s_hr'!N45 -> 515520 | O77: ='.c12_d&s_hr'!O45 -> 1652177.5 | P77: ='.c12_d&s_hr'!P45 -> 560160 | Q77: ='.c12_d&s_hr'!Q45 -> 520560 | R77: ='.c12_d&s_hr'!R45 -> 560160 | S77: ='.c12_d&s_hr'!S45 -> 1221223.8
A78: reimbersable to hotel | B78: o | C78: hr_reimbursable | I78: 123922.5 | J78: 85680 | L78: ='.c12_d&s_hr'!L46 -> 84960 | M78: ='.c12_d&s_hr'!M46 -> 84960 | N78: ='.c12_d&s_hr'!N46 -> 84960 | O78: ='.c12_d&s_hr'!O46 -> 123922.5 | P78: ='.c12_d&s_hr'!P46 -> 85680 | Q78: ='.c12_d&s_hr'!Q46 -> 85680 | R78: ='.c12_d&s_hr'!R46 -> 85680 | S78: ='.c12_d&s_hr'!S46 -> 116850
A79: not reimbersable by hotel, but paid by lgh | B79: o | C79: hr_not_reimbursable | I79: 1528255 | J79: 474480 | L79: ='.c12_d&s_hr'!L47 -> 430560 | M79: ='.c12_d&s_hr'!M47 -> 430560 | N79: ='.c12_d&s_hr'!N47 -> 430560 | O79: ='.c12_d&s_hr'!O47 -> 1528255 | P79: ='.c12_d&s_hr'!P47 -> 474480 | Q79: ='.c12_d&s_hr'!Q47 -> 434880 | R79: ='.c12_d&s_hr'!R47 -> 474480 | S79: ='.c12_d&s_hr'!S47 -> 1104373.8
A80: only paid by c12 | B80: c | C80: hr_only_c12 | I80: 0 | J80: 0 | L80: ='.c12_d&s_hr'!L48 -> 0 | M80: ='.c12_d&s_hr'!M48 -> 0 | N80: ='.c12_d&s_hr'!N48 -> 0 | O80: ='.c12_d&s_hr'!O48 -> 0 | P80: ='.c12_d&s_hr'!P48 -> 0 | Q80: ='.c12_d&s_hr'!Q48 -> 0 | R80: ='.c12_d&s_hr'!R48 -> 0 | S80: ='.c12_d&s_hr'!S48 -> 0

Sheet c12_bi&F
A2: Year | E2: 45657 | F2: 45747 | G2: 45838 | H2: 45930 | I2: 46022 | J2: 46112 | K2: 46203 | L2: 45747 | M2: 45838 | N2: 45930 | O2: 46022 | P2: 46112 | Q2: 46203 | R2: 46295 | S2: 46387
E3: actual | L3: i/o
B4: i/o | C4: field_name | D4: index
A5: LGH Fee Revenue | C5: lgh_fee_revenue_section
A6: [blank]
A7: [blank]
A8: [blank]
A9: [blank]
A10: [blank]
A11: [blank]
A12: [blank]
A13: [blank]
A14: [blank]
A15: [blank]
A16: [blank]
A17: [blank]
... A21: [blank]
A22: [blank] | I22: 0 | J22: 0 | L22: 0 | M22: 0 | N22: 0 | O22: 0 | P22: 0 | Q22: 0 | R22: 0 | S22: 0
A23: [blank] | I23: 0 | J23: 0 | L23: 0 | M23: 0 | N23: 0 | O23: 0 | P23: 0 | Q23: 0 | R23: 0 | S23: 0
A24: [blank] | I24: 0 | J24: 0 | L24: 0 | M24: 0 | N24: 0 | O24: 0 | P24: 0 | Q24: 0 | R24: 0 | S24: 0
A25: Total LGH Fees Earned | B25: c | C25: total_fees_earned | I25: 0 | J25: 0 | L25: =SUM(L22:L24) -> 0 | M25: =SUM(M22:M24) -> 0 | N25: =SUM(N22:N24) -> 0 | O25: =SUM(O22:O24) -> 0 | P25: =SUM(P22:P24) -> 0 | Q25: =SUM(Q22:Q24) -> 0 | R25: =SUM(R22:R24) -> 0 | S25: =SUM(S22:S24) -> 0
A27: Deferred Period Fee | B27: i | C27: deferred_fee | I27: 0 | J27: 0 | L27: 0 | M27: 0 | N27: 0 | O27: 0 | P27: 0 | Q27: 0 | R27: 0 | S27: 0
A28: Paid Fee Accruals | B28: i | C28: paid_fee_accruals | I28: 0 | J28: 0 | L28: 0 | M28: 0 | N28: 0 | O28: 0 | P28: 0 | Q28: 0 | R28: 0 | S28: 0
A29: Cumm. Balance Accrued Fee | B29: c | C29: cumm_accrued_fee | I29: 0 | J29: 0 | L29: =+L27+E29+L28 -> 0 | M29: =+M27+L29+M28 -> 0 | N29: =+N27+M29+N28 -> 0 | O29: =+O27+N29+O28 -> 0 | P29: =+P27+O29+P28 -> 0 | Q29: =+Q27+P29+Q28 -> 0 | R29: =+R27+Q29+R28 -> 0 | S29: =+S27+R29+S28 -> 0
A31: Paid Current Fees | B31: c | C31: paid_current_fees | I31: 0 | J31: 0 | L31: =+L25+L27 -> 0 | M31: =+M25+M27 -> 0 | N31: =+N25+N27 -> 0 | O31: =+O25+O27 -> 0 | P31: =+P25+P27 -> 0 | Q31: =+Q25+Q27 -> 0 | R31: =+R25+R27 -> 0 | S31: =+S25+S27 -> 0
A32: Total Fees Paid | B32: c | C32: total_fees_paid | I32: 0 | J32: 0 | L32: =+L28+L31 -> 0 | M32: =+M28+M31 -> 0 | N32: =+N28+N31 -> 0 | O32: =+O28+O31 -> 0 | P32: =+P28+P31 -> 0 | Q32: =+Q28+Q31 -> 0 | R32: =+R28+R31 -> 0 | S32: =+S28+S31 -> 0
A34: LGH Service Revenue | C34: lgh_service_revenue_section
A35: Bermuda PB | B35: i | C35: accting_fee | D35: pb | I35: 0 | J35: 15000 | L35: 0 | M35: 0 | N35: 0 | O35: 0 | P35: =60000/4 -> 15000 | Q35: =60000/4 -> 15000 | R35: =60000/4 -> 15000 | S35: =60000/4 -> 15000
A36: 7f | B36: i | C36: accting_fee | D36: austin | I36: 0 | J36: 15000 | L36: 0 | M36: 0 | N36: 0 | O36: 0 | P36: =60000/4 -> 15000 | Q36: =60000/4 -> 15000 | R36: =60000/4 -> 15000 | S36: =60000/4 -> 15000
A37: Turks | B37: i | C37: accting_fee | D37: turks | I37: 0 | J37: 0 | L37: 0 | M37: 0 | N37: 0 | O37: 0 | P37: 0 | Q37: 0 | R37: 0 | S37: 0
A38: Elbow | B38: i | C38: accting_fee | D38: elbow | I38: 0 | J38: 0 | L38: 0 | M38: 0 | N38: 0 | O38: 0 | P38: 0 | Q38: 0 | R38: 0 | S38: 0
A39: Frith | B39: i | C39: accting_fee | D39: fritholme | I39: 0 | J39: 0 | L39: 0 | M39: 0 | N39: 0 | O39: 0 | P39: 0 | Q39: =+P39 -> 0 | R39: =+Q39 -> 0 | S39: =+R39 -> 0
A40: [blank]
A41: [blank]
A42: [blank]
A43: [blank]
A44: [blank]
A45: [LSAT] | B45: i | C45: accting_fee | D45: lsat
A46: Total LGH Bi&F Service Revenue | B46: c | C46: total_service_revenue | I46: 0 | J46: 30000 | L46: =SUM(L35:L45) -> 0 | M46: =SUM(M35:M45) -> 0 | N46: =SUM(N35:N45) -> 0 | O46: =SUM(O35:O45) -> 0 | P46: =SUM(P35:P45) -> 30000 | Q46: =SUM(Q35:Q45) -> 30000 | R46: =SUM(R35:R45) -> 30000 | S46: =SUM(S35:S45) -> 30000
A48: Deferred Period Fee | B48: i | C48: deferred_service_fee | L48: =-L36 -> 0
A49: Paid Accruals | B49: i | C49: paid_service_accruals
A50: Cumm. Balance Accrued Service Fee | B50: c | C50: cumm_accrued_service_fee | I50: 0 | J50: 0 | L50: =+L48+E50+L49 -> 0 | M50: =+M48+L50+M49 -> 0 | N50: =+N48+M50+N49 -> 0 | O50: =+O48+N50+O49 -> 0 | P50: =+P48+O50+P49 -> 0 | Q50: =+Q48+P50+Q49 -> 0 | R50: =+R48+Q50+R49 -> 0 | S50: =+S48+R50+S49 -> 0
A52: Paid Current Service Fees | B52: c | C52: paid_current_service_fees | I52: 0 | J52: 30000 | L52: =+L46+L48 -> 0 | M52: =+M46+M48 -> 0 | N52: =+N46+N48 -> 0 | O52: =+O46+O48 -> 0 | P52: =+P46+P48 -> 30000 | Q52: =+Q46+Q48 -> 30000 | R52: =+R46+R48 -> 30000 | S52: =+S46+S48 -> 30000
A53: Total Service Revenue Paid | B53: c | C53: total_service_revenue_paid | I53: 0 | J53: 30000 | L53: =+L49+L52 -> 0 | M53: =+M49+M52 -> 0 | N53: =+N49+N52 -> 0 | O53: =+O49+O52 -> 0 | P53: =+P49+P52 -> 30000 | Q53: =+Q49+Q52 -> 30000 | R53: =+R49+R52 -> 30000 | S53: =+S49+S52 -> 30000
A55: LGH Chargebacks
A56: chargeback fee | B56: c | C56: chargeback_multiplier | I56: 1.0526316 | J56: 1.0526316 | L56: =1/(1-'c12_inputs'!$E$7) -> 1.0526316 | M56: =1/(1-'c12_inputs'!$E$7) -> 1.0526316 | N56: =1/(1-'c12_inputs'!$E$7) -> 1.0526316 | O56: =1/(1-'c12_inputs'!$E$7) -> 1.0526316 | P56: =1/(1-'c12_inputs'!$E$7) -> 1.0526316 | Q56: =1/(1-'c12_inputs'!$E$7) -> 1.0526316 | R56: =1/(1-'c12_inputs'!$E$7) -> 1.0526316 | S56: =1/(1-'c12_inputs'!$E$7) -> 1.0526316
A57: reimbursable by hotels to LGH | B57: o | C57: reimbursable_by_hotels | F57: 0 | G57: 0 | H57: 0 | I57: 0 | J57: 118080 | L57: =IF(AND((F57<>""),(L$2<46204)),(F57),L78) -> 0 | M57: =IF(AND((G57<>""),(M$2<46204)),(G57),M78) -> 0 | N57: =IF(AND((H57<>""),(N$2<46204)),(H57),N78) -> 0 | O57: =IF(AND((I57<>""),(O$2<46204)),(I57),O78) -> 0 | P57: =IF(AND((J57<>""),(P$2<46204)),(J57),P78) -> 118080 | Q57: =IF(AND((K57<>""),(Q$2<46204)),(K57),Q78) -> 118080 | R57: =IF(AND((L57<>""),(R$2<46204)),(L57),R78) -> 226080 | S57: =IF(AND((M57<>""),(S$2<46204)),(M57),S78) -> 314395
A58: Total LGH Bi&F Charge Back chk | B58: c | C58: total_chargeback | I58: 0 | J58: 124294.74 | L58: =L57*L56 -> 0 | M58: =M57*M56 -> 0 | N58: =N57*N56 -> 0 | O58: =O57*O56 -> 0 | P58: =P57*P56 -> 124294.74 | Q58: =Q57*Q56 -> 124294.74 | R58: =R57*R56 -> 237978.95 | S58: =S57*S56 -> 330942.11
A60: total LGH Bi&F revenue | B60: o | C60: total_lgh_bif_revenue | I60: 0 | J60: 154294.74 | L60: =+L53+L32+L58 -> 0 | M60: =+M53+M32+M58 -> 0 | N60: =+N53+N32+N58 -> 0 | O60: =+O53+O32+O58 -> 0 | P60: =+P53+P32+P58 -> 154294.74 | Q60: =+Q53+Q32+Q58 -> 154294.74 | R60: =+R53+R32+R58 -> 267978.95 | S60: =+S53+S32+S58 -> 360942.11
A62: LGH Accounts Receivable Cumm. | B62: o | C62: lgh_ar_cumm | I62: 0 | J62: 0 | L62: =+L29+L50 -> 0 | M62: =+M29+M50 -> 0 | N62: =+N29+N50 -> 0 | O62: =+O29+O50 -> 0 | P62: =+P29+P50 -> 0 | Q62: =+Q29+Q50 -> 0 | R62: =+R29+R50 -> 0 | S62: =+S29+S50 -> 0
A64: C12 Participation % | B64: c | C64: c12_participation_pct | I64: 0.35 | J64: 0.35 | L64: ='c12_inputs'!$E$8 -> 0.35 | M64: ='c12_inputs'!$E$8 -> 0.35 | N64: ='c12_inputs'!$E$8 -> 0.35 | O64: ='c12_inputs'!$E$8 -> 0.35 | P64: ='c12_inputs'!$E$8 -> 0.35 | Q64: ='c12_inputs'!$E$8 -> 0.35 | R64: ='c12_inputs'!$E$8 -> 0.35 | S64: ='c12_inputs'!$E$8 -> 0.35
A65: pre-modification extra | B65: i | C65: pre_mod_extra_pct | I65: 0.15 | J65: 0 | L65: 0.15 | M65: 0.15 | N65: 0.15 | O65: 0.15 | P65: 0 | Q65: 0 | R65: 0 | S65: 0
A66: catchup extra% | B66: i | C66: catchup_extra_pct | I66: 0.15 | J66: 0.15 | L66: 0.15 | M66: 0.15 | N66: 0.15 | O66: 0.15 | P66: 0.15 | Q66: 0.15 | R66: 0.15 | S66: 0.15
A67: charge back percentrage | B67: c | C67: chargeback_pct | I67: 0.05 | J67: 0.05 | L67: ='c12_inputs'!$E$7 -> 0.05 | M67: ='c12_inputs'!$E$7 -> 0.05 | N67: ='c12_inputs'!$E$7 -> 0.05 | O67: ='c12_inputs'!$E$7 -> 0.05 | P67: ='c12_inputs'!$E$7 -> 0.05 | Q67: ='c12_inputs'!$E$7 -> 0.05 | R67: ='c12_inputs'!$E$7 -> 0.05 | S67: ='c12_inputs'!$E$7 -> 0.05
A68: C12 Participation $ | B68: c | C68: c12_participation_amt | I68: 0 | J68: 10500 | L68: =(L64+L65)*(L32+L52)+(L64+L66)*(L49+L29) -> 0 | M68: =(M64+M65)*(M32+M52)+(M64+M66)*(M49+M29) -> 0 | N68: =(N64+N65)*(N32+N52)+(N64+N66)*(N49+N29) -> 0 | O68: =(O64+O65)*(O32+O52)+(O64+O66)*(O49+O29) -> 0 | P68: =(P64+P65)*(P32+P52)+(P64+P66)*(P49+P29) -> 10500 | Q68: =(Q64+Q65)*(Q32+Q52)+(Q64+Q66)*(Q49+Q29) -> 10500 | R68: =(R64+R65)*(R32+R52)+(R64+R66)*(R49+R29) -> 10500 | S68: =(S64+S65)*(S32+S52)+(S64+S66)*(S49+S29) -> 10500
A69: chargebacks | B69: c | C69: chargeback_fees | I69: 0 | J69: 6214.7368 | L69: =L58*L67 -> 0 | M69: =M58*M67 -> 0 | N69: =N58*N67 -> 0 | O69: =O58*O67 -> 0 | P69: =P58*P67 -> 6214.7368 | Q69: =Q58*Q67 -> 6214.7368 | R69: =R58*R67 -> 11898.947 | S69: =S58*S67 -> 16547.105
A70: Total C12 Bi&f revenue | B70: o | C70: total_c12_bif_revenue | I70: 0 | J70: 16714.737 | L70: =L69+L68 -> 0 | M70: =M69+M68 -> 0 | N70: =N69+N68 -> 0 | O70: =O69+O68 -> 0 | P70: =P69+P68 -> 16714.737 | Q70: =Q69+Q68 -> 16714.737 | R70: =R69+R68 -> 22398.947 | S70: =S69+S68 -> 27047.105
A72: increase in accrued participation | B72: c | C72: increase_accrued_participation | I72: 0 | J72: 0 | L72: =-(L64+L65)*(L27+L48) -> 0 | M72: =-(M64+M65)*(M27+M48) -> 0 | N72: =-(N64+N65)*(N27+N48) -> 0 | O72: =-(O64+O65)*(O27+O48) -> 0 | P72: =-(P64+P65)*(P27+P48) -> 0 | Q72: =-(Q64+Q65)*(Q27+Q48) -> 0 | R72: =-(R64+R65)*(R27+R48) -> 0 | S72: =-(S64+S65)*(S27+S48) -> 0
A73: decrease in accrued partipation | B73: c | C73: decrease_accrued_participation | I73: 0 | J73: 0 | L73: =-(L64+L66)*(L28+L49) -> 0 | M73: =-(M64+M66)*(M28+M49) -> 0 | N73: =-(N64+N66)*(N28+N49) -> 0 | O73: =-(O64+O66)*(O28+O49) -> 0 | P73: =-(P64+P66)*(P28+P49) -> 0 | Q73: =-(Q64+Q66)*(Q28+Q49) -> 0 | R73: =-(R64+R66)*(R28+R49) -> 0 | S73: =-(S64+S66)*(S28+S49) -> 0
A74: Cumm. Total Accrued Participation | B74: o | C74: cumm_accrued_participation | I74: 0 | J74: 0 | L74: =SUM(L72:L73)+E74 -> 0 | M74: =SUM(M72:M73)+L74 -> 0 | N74: =SUM(N72:N73)+M74 -> 0 | O74: =SUM(O72:O73)+N74 -> 0 | P74: =SUM(P72:P73)+O74 -> 0 | Q74: =SUM(Q72:Q73)+P74 -> 0 | R74: =SUM(R72:R73)+Q74 -> 0 | S74: =SUM(S72:S73)+R74 -> 0
A76: from HR sheet
A77: Grand Total | B77: c | C77: hr_grand_total | I77: 602497.5 | J77: 296640 | L77: ='.c12_bi&f_hr'!L48 -> 250560 | M77: ='.c12_bi&f_hr'!M48 -> 250560 | N77: ='.c12_bi&f_hr'!N48 -> 336960 | O77: ='.c12_bi&f_hr'!O48 -> 602497.5 | P77: ='.c12_bi&f_hr'!P48 -> 296640 | Q77: ='.c12_bi&f_hr'!Q48 -> 477677.14 | R77: ='.c12_bi&f_hr'!R48 -> 672077.14 | S77: ='.c12_bi&f_hr'!S48 -> 1173394.6
A78: reimbersable to hotel | B78: o | C78: hr_reimbursable | I78: 154162.5 | J78: 118080 | L78: ='.c12_bi&f_hr'!L49 -> 53280 | M78: ='.c12_bi&f_hr'!M49 -> 53280 | N78: ='.c12_bi&f_hr'!N49 -> 115200 | O78: ='.c12_bi&f_hr'!O49 -> 154162.5 | P78: ='.c12_bi&f_hr'!P49 -> 118080 | Q78: ='.c12_bi&f_hr'!Q49 -> 118080 | R78: ='.c12_bi&f_hr'!R49 -> 226080 | S78: ='.c12_bi&f_hr'!S49 -> 314395
A79: not reimbersable by hotel, but paid by lgh | B79: o | C79: hr_not_reimbursable | I79: 448335 | J79: 178560 | L79: ='.c12_bi&f_hr'!L50 -> 197280 | M79: ='.c12_bi&f_hr'!M50 -> 197280 | N79: ='.c12_bi&f_hr'!N50 -> 221760 | O79: ='.c12_bi&f_hr'!O50 -> 448335 | P79: ='.c12_bi&f_hr'!P50 -> 178560 | Q79: ='.c12_bi&f_hr'!Q50 -> 359597.14 | R79: ='.c12_bi&f_hr'!R50 -> 445997.14 | S79: ='.c12_bi&f_hr'!S50 -> 858999.64
A80: only paid by c12 | B80: c | C80: hr_only_c12 | I80: 0 | J80: 0 | L80: ='.c12_bi&f_hr'!L51 -> 0 | M80: ='.c12_bi&f_hr'!M51 -> 0 | N80: ='.c12_bi&f_hr'!N51 -> 0 | O80: ='.c12_bi&f_hr'!O51 -> 0 | P80: ='.c12_bi&f_hr'!P51 -> 0 | Q80: ='.c12_bi&f_hr'!Q51 -> 0 | R80: ='.c12_bi&f_hr'!R51 -> 0 | S80: ='.c12_bi&f_hr'!S51 -> 0

Sheet .c12_inputs.hr
B4: i/o | C4: field_name | D4: index
A5: ocBenefits | B5: i | C5: benefits_rate | D5: oc | E5: 0.021714286 | F5: adjusted down to assume sk doesn’t pay
A6: ocBonus Tax | B6: i | C6: bonus_tax_rate_actual | D6: oc | E6: 0.039
A8: hmBenefits | B8: i | C8: benefits_rate_actual | D8: hm | E8: 0.152
A9: hmBonus Tax | B9: i | C9: bonus_tax_rate_actual | D9: hm | E9: 0.039
A11: bfBenefits | B11: i | C11: benefits_rate_actual | D11: bif | E11: 0.152
A12: bfBonus Tax | B12: i | C12: bonus_tax_rate_actual | D12: bif | E12: 0.039
A15: dsBenefits | B15: i | C15: benefits_rate_actual | D15: ds | E15: 0.152
A16: dsBonus Tax | B16: i | C16: bonus_tax_rate_actual | D16: ds | E16: 0.039

Sheet .c12_oc_hr
A2: Year | E2: 45657 | F2: 45747 | G2: 45838 | H2: 45930 | I2: 46022 | J2: 46112 | K2: 46203 | L2: 45747 | M2: 45838 | N2: 45930 | O2: 46022 | P2: 46112 | Q2: 46203 | R2: 46295 | S2: 46387 | T2: 46752 | U2: 47118 | V2: 47483 | W2: 47848
E3: actual | L3: i/o
B4: i/o | C4: field_name | D4: index
A5: Base
A6: Managing Member (SK) | B6: i | C6: base_salary | D6: sk | I6: 375000 | J6: 375000 | L6: 375000 | M6: 375000 | N6: 375000 | O6: 375000 | P6: 375000 | Q6: 375000 | R6: 375000 | S6: 375000 | T6: 1500000 | U6: 1500000 | V6: 1500000 | W6: 1500000
A7: Philanropy senior exec (LM) (100%roots) | B7: i | C7: base_salary | D7: lm | I7: 0 | J7: 0 | L7: 0 | M7: 0 | N7: 0 | O7: 0 | P7: 0 | Q7: 0 | R7: 0 | S7: 0 | T7: 0 | U7: 0 | V7: 0 | W7: 0
A8: Bookkeeper (DD) | B8: i | C8: base_salary | D8: dd | I8: 0 | J8: 25750 | L8: 0 | M8: 0 | N8: 0 | O8: 0 | P8: 25750 | Q8: 25750 | R8: 25750 | S8: 25750 | T8: 103000 | U8: 103000 | V8: 103000 | W8: 103000
A9: Personal Assistant (CD) | B9: i | C9: base_salary | D9: cd | I9: 31250 | J9: 31250 | L9: 31250 | M9: 31250 | N9: 31250 | O9: 31250 | P9: 31250 | Q9: 31250 | R9: 31250 | S9: 31250 | T9: 125000 | U9: 125000 | V9: 125000 | W9: 125000
A10: philanthropy assist (100%roots) | B10: i | C10: base_salary | D10: philanthropy | I10: 0 | J10: 0 | L10: 0 | M10: 0 | N10: 0 | O10: 0 | P10: 0 | Q10: 0 | R10: 0 | S10: 0 | T10: 0 | U10: 0 | V10: 0 | W10: 0
A11: TM (gone) | B11: i | C11: base_salary | D11: tm | I11: 87500 | J11: 87500 | L11: 87500 | M11: 87500 | N11: 87500 | O11: 87500 | P11: 87500 | Q11: 0 | R11: 0 | S11: 0 | T11: 0 | U11: 0 | V11: 0 | W11: 0
A12: Total | I12: 493750 | J12: 519500 | L12: =SUM(L6:L11) -> 493750 | M12: =SUM(M6:M11) -> 493750 | N12: =SUM(N6:N11) -> 493750 | O12: =SUM(O6:O11) -> 493750 | P12: =SUM(P6:P11) -> 519500 | Q12: =SUM(Q6:Q11) -> 432000 | R12: =SUM(R6:R11) -> 432000 | S12: =SUM(S6:S11) -> 432000 | ... W12: =SUM(W6:W11) -> 1728000
A13: Bonus
A14: =+A6 -> Managing Member (SK) | B14: i | C14: bonus | D14: sk | I14: 0 | J14: 0 | L14: 0 | M14: 0 | N14: 0 | O14: 0 | P14: 0 | Q14: 0 | R14: 0 | S14: 0 | T14: 0 | U14: 0 | V14: 0 | W14: 0
A15: =+A7 -> Philanropy senior exec (LM) (100%roots) | B15: i | C15: bonus | D15: lm | I15: 0 | J15: 0 | L15: 0 | M15: 0 | N15: 0 | O15: 0 | P15: 0 | Q15: 0 | R15: 0 | S15: 0 | T15: 0 | U15: 0 | V15: 0 | W15: 0
A16: =+A8 -> Bookkeeper (DD) | B16: i | C16: bonus | D16: dd | I16: 10000 | J16: 0 | L16: 0 | N16: 0 | O16: 10000 | P16: 0 | Q16: 0 | R16: 0 | S16: 5000 | T16: 5000 | U16: 5000 | V16: 5000 | W16: 5000
A17: =+A9 -> Personal Assistant (CD) | B17: i | C17: bonus | D17: cd | I17: 0 | J17: 0 | L17: 0 | M17: 0 | N17: 0 | O17: 0 | P17: 0 | Q17: 0 | R17: 0 | S17: 15000 | T17: 15000 | U17: 15000 | V17: 15000 | W17: 15000
A18: =+A10 -> philanthropy assist (100%roots) | B18: i | C18: bonus | D18: philanthropy | I18: 0 | J18: 0 | L18: 0 | M18: 0 | N18: 0 | O18: 0 | P18: 0 | Q18: 0 | R18: 0 | S18: 0 | T18: 0 | U18: 0 | V18: 0 | W18: 0
A19: =+A11 -> TM (gone) | B19: i | C19: bonus | D19: tm | I19: 0 | J19: 320000 | L19: 0 | M19: 0 | N19: 0 | O19: 0 | P19: 320000 | Q19: 0 | R19: 0 | S19: 500000 | T19: 500000 | U19: 0 | V19: 0 | W19: 0
A20: Total | I20: 10000 | J20: 320000 | L20: =SUM(L14:L19) -> 0 | M20: =SUM(M14:M19) -> 0 | N20: =SUM(N14:N19) -> 0 | O20: =SUM(O14:O19) -> 10000 | P20: =SUM(P14:P19) -> 320000 | Q20: =SUM(Q14:Q19) -> 0 | R20: =SUM(R14:R19) -> 0 | S20: =SUM(S14:S19) -> 520000 | ... W20: =SUM(W14:W19) -> 20000
A22: Total
A23: =+A6 -> Managing Member (SK) | B23: c | C23: total_salary | D23: sk | I23: 383142.86 | J23: 383142.86 | L23: =L6*(1+'.c12_inputs.hr'!$E$5)+(L14*(1+'.c12_inputs.hr'!$E$6)) -> 383142.86 | M23: =M6*(1+'.c12_inputs.hr'!$E$5)+(M14*(1+'.c12_inputs.hr'!$E$6)) -> 383142.86 | N23: =N6*(1+'.c12_inputs.hr'!$E$5)+(N14*(1+'.c12_inputs.hr'!$E$6)) -> 383142.86 | O23: =O6*(1+'.c12_inputs.hr'!$E$5)+(O14*(1+'.c12_inputs.hr'!$E$6)) -> 383142.86 | P23: =P6*(1+'.c12_inputs.hr'!$E$5)+(P14*(1+'.c12_inputs.hr'!$E$6)) -> 383142.86 | Q23: =Q6*(1+'.c12_inputs.hr'!$E$5)+(Q14*(1+'.c12_inputs.hr'!$E$6)) -> 383142.86 | R23: =R6*(1+'.c12_inputs.hr'!$E$5)+(R14*(1+'.c12_inputs.hr'!$E$6)) -> 383142.86 | S23: =S6*(1+'.c12_inputs.hr'!$E$5)+(S14*(1+'.c12_inputs.hr'!$E$6)) -> 383142.86 | ... W23: =W6*(1+'.c12_inputs.hr'!$E$5)+(W14*(1+'.c12_inputs.hr'!$E$6)) -> 1532571.4
A24: =+A7 -> Philanropy senior exec (LM) (100%roots) | B24: c | C24: total_salary | D24: lm | I24: 0 | J24: 0 | L24: =L7*(1+'.c12_inputs.hr'!$E$5)+(L15*(1+'.c12_inputs.hr'!$E$6)) -> 0 | M24: =M7*(1+'.c12_inputs.hr'!$E$5)+(M15*(1+'.c12_inputs.hr'!$E$6)) -> 0 | N24: =N7*(1+'.c12_inputs.hr'!$E$5)+(N15*(1+'.c12_inputs.hr'!$E$6)) -> 0 | O24: =O7*(1+'.c12_inputs.hr'!$E$5)+(O15*(1+'.c12_inputs.hr'!$E$6)) -> 0 | P24: =P7*(1+'.c12_inputs.hr'!$E$5)+(P15*(1+'.c12_inputs.hr'!$E$6)) -> 0 | Q24: =Q7*(1+'.c12_inputs.hr'!$E$5)+(Q15*(1+'.c12_inputs.hr'!$E$6)) -> 0 | R24: =R7*(1+'.c12_inputs.hr'!$E$5)+(R15*(1+'.c12_inputs.hr'!$E$6)) -> 0 | S24: =S7*(1+'.c12_inputs.hr'!$E$5)+(S15*(1+'.c12_inputs.hr'!$E$6)) -> 0 | ... W24: =W7*(1+'.c12_inputs.hr'!$E$5)+(W15*(1+'.c12_inputs.hr'!$E$6)) -> 0
A25: =+A8 -> Bookkeeper (DD) | B25: c | C25: total_salary | D25: dd | I25: 10390 | J25: 26309.143 | L25: =L8*(1+'.c12_inputs.hr'!$E$5)+(L16*(1+'.c12_inputs.hr'!$E$6)) -> 0 | M25: =M8*(1+'.c12_inputs.hr'!$E$5)+(M16*(1+'.c12_inputs.hr'!$E$6)) -> 0 | N25: =N8*(1+'.c12_inputs.hr'!$E$5)+(N16*(1+'.c12_inputs.hr'!$E$6)) -> 0 | O25: =O8*(1+'.c12_inputs.hr'!$E$5)+(O16*(1+'.c12_inputs.hr'!$E$6)) -> 10390 | P25: =P8*(1+'.c12_inputs.hr'!$E$5)+(P16*(1+'.c12_inputs.hr'!$E$6)) -> 26309.143 | Q25: =Q8*(1+'.c12_inputs.hr'!$E$5)+(Q16*(1+'.c12_inputs.hr'!$E$6)) -> 26309.143 | R25: =R8*(1+'.c12_inputs.hr'!$E$5)+(R16*(1+'.c12_inputs.hr'!$E$6)) -> 26309.143 | S25: =S8*(1+'.c12_inputs.hr'!$E$5)+(S16*(1+'.c12_inputs.hr'!$E$6)) -> 31504.143 | ... W25: =W8*(1+'.c12_inputs.hr'!$E$5)+(W16*(1+'.c12_inputs.hr'!$E$6)) -> 110431.57
A26: =+A9 -> Personal Assistant (CD) | B26: c | C26: total_salary | D26: cd | I26: 31928.571 | J26: 31928.571 | L26: =L9*(1+'.c12_inputs.hr'!$E$5)+(L17*(1+'.c12_inputs.hr'!$E$6)) -> 31928.571 | M26: =M9*(1+'.c12_inputs.hr'!$E$5)+(M17*(1+'.c12_inputs.hr'!$E$6)) -> 31928.571 | N26: =N9*(1+'.c12_inputs.hr'!$E$5)+(N17*(1+'.c12_inputs.hr'!$E$6)) -> 31928.571 | O26: =O9*(1+'.c12_inputs.hr'!$E$5)+(O17*(1+'.c12_inputs.hr'!$E$6)) -> 31928.571 | P26: =P9*(1+'.c12_inputs.hr'!$E$5)+(P17*(1+'.c12_inputs.hr'!$E$6)) -> 31928.571 | Q26: =Q9*(1+'.c12_inputs.hr'!$E$5)+(Q17*(1+'.c12_inputs.hr'!$E$6)) -> 31928.571 | R26: =R9*(1+'.c12_inputs.hr'!$E$5)+(R17*(1+'.c12_inputs.hr'!$E$6)) -> 31928.571 | S26: =S9*(1+'.c12_inputs.hr'!$E$5)+(S17*(1+'.c12_inputs.hr'!$E$6)) -> 47513.571 | ... W26: =W9*(1+'.c12_inputs.hr'!$E$5)+(W17*(1+'.c12_inputs.hr'!$E$6)) -> 143299.29
A27: =+A10 -> philanthropy assist (100%roots) | B27: c | C27: total_salary | D27: philanthropy | I27: 0 | J27: 0 | L27: =L10*(1+'.c12_inputs.hr'!$E$5)+(L18*(1+'.c12_inputs.hr'!$E$6)) -> 0 | M27: =M10*(1+'.c12_inputs.hr'!$E$5)+(M18*(1+'.c12_inputs.hr'!$E$6)) -> 0 | N27: =N10*(1+'.c12_inputs.hr'!$E$5)+(N18*(1+'.c12_inputs.hr'!$E$6)) -> 0 | O27: =O10*(1+'.c12_inputs.hr'!$E$5)+(O18*(1+'.c12_inputs.hr'!$E$6)) -> 0 | P27: =P10*(1+'.c12_inputs.hr'!$E$5)+(P18*(1+'.c12_inputs.hr'!$E$6)) -> 0 | Q27: =Q10*(1+'.c12_inputs.hr'!$E$5)+(Q18*(1+'.c12_inputs.hr'!$E$6)) -> 0 | R27: =R10*(1+'.c12_inputs.hr'!$E$5)+(R18*(1+'.c12_inputs.hr'!$E$6)) -> 0 | S27: =S10*(1+'.c12_inputs.hr'!$E$5)+(S18*(1+'.c12_inputs.hr'!$E$6)) -> 0 | ... W27: =W10*(1+'.c12_inputs.hr'!$E$5)+(W18*(1+'.c12_inputs.hr'!$E$6)) -> 0
A28: =+A11 -> TM (gone) | B28: c | C28: total_salary | D28: tm | I28: 89400 | J28: 421880 | L28: =L11*(1+'.c12_inputs.hr'!$E$5)+(L19*(1+'.c12_inputs.hr'!$E$6)) -> 89400 | M28: =M11*(1+'.c12_inputs.hr'!$E$5)+(M19*(1+'.c12_inputs.hr'!$E$6)) -> 89400 | N28: =N11*(1+'.c12_inputs.hr'!$E$5)+(N19*(1+'.c12_inputs.hr'!$E$6)) -> 89400 | O28: =O11*(1+'.c12_inputs.hr'!$E$5)+(O19*(1+'.c12_inputs.hr'!$E$6)) -> 89400 | P28: =P11*(1+'.c12_inputs.hr'!$E$5)+(P19*(1+'.c12_inputs.hr'!$E$6)) -> 421880 | Q28: =Q11*(1+'.c12_inputs.hr'!$E$5)+(Q19*(1+'.c12_inputs.hr'!$E$6)) -> 0 | R28: =R11*(1+'.c12_inputs.hr'!$E$5)+(R19*(1+'.c12_inputs.hr'!$E$6)) -> 0 | S28: =S11*(1+'.c12_inputs.hr'!$E$5)+(S19*(1+'.c12_inputs.hr'!$E$6)) -> 519500 | ... W28: =W11*(1+'.c12_inputs.hr'!$E$5)+(W19*(1+'.c12_inputs.hr'!$E$6)) -> 0
A30: Grand Total | B30: o | C30: hr_grand_total | I30: 514861.43 | J30: 863260.57 | L30: =SUM(L23:L28) -> 504471.43 | M30: =SUM(M23:M28) -> 504471.43 | N30: =SUM(N23:N28) -> 504471.43 | O30: =SUM(O23:O28) -> 514861.43 | P30: =SUM(P23:P28) -> 863260.57 | Q30: =SUM(Q23:Q28) -> 441380.57 | R30: =SUM(R23:R28) -> 441380.57 | S30: =SUM(S23:S28) -> 981660.57 | ... W30: =SUM(W23:W28) -> 1786302.3
A31: reimbersable to hotel | B31: o | C31: hr_reimbursable | I31: 0 | J31: 0 | L31: =SUMPRODUCT('.c12_alloc'!$H$6:$H$11,L23:L28) -> 0 | M31: =SUMPRODUCT('.c12_alloc'!$H$6:$H$11,M23:M28) -> 0 | N31: =SUMPRODUCT('.c12_alloc'!$H$6:$H$11,N23:N28) -> 0 | O31: =SUMPRODUCT('.c12_alloc'!$H$6:$H$11,O23:O28) -> 0 | P31: =SUMPRODUCT('.c12_alloc'!$H$6:$H$11,P23:P28) -> 0 | Q31: =SUMPRODUCT('.c12_alloc'!$H$6:$H$11,Q23:Q28) -> 0 | R31: =SUMPRODUCT('.c12_alloc'!$H$6:$H$11,R23:R28) -> 0 | S31: =SUMPRODUCT('.c12_alloc'!$H$6:$H$11,S23:S28) -> 0 | ... W31: =SUMPRODUCT('.c12_alloc'!$H$6:$H$11,W23:W28) -> 0
A32: not reimbersable by hotel, but paid by lgh | B32: o | C32: hr_not_reimbursable | I32: 472542.86 | J32: 805022.86 | L32: =SUMPRODUCT('.c12_alloc'!$G$6:$G$11,L23:L28) -> 472542.86 | M32: =SUMPRODUCT('.c12_alloc'!$G$6:$G$11,M23:M28) -> 472542.86 | N32: =SUMPRODUCT('.c12_alloc'!$G$6:$G$11,N23:N28) -> 472542.86 | O32: =SUMPRODUCT('.c12_alloc'!$G$6:$G$11,O23:O28) -> 472542.86 | P32: =SUMPRODUCT('.c12_alloc'!$G$6:$G$11,P23:P28) -> 805022.86 | Q32: =SUMPRODUCT('.c12_alloc'!$G$6:$G$11,Q23:Q28) -> 383142.86 | R32: =SUMPRODUCT('.c12_alloc'!$G$6:$G$11,R23:R28) -> 383142.86 | S32: =SUMPRODUCT('.c12_alloc'!$G$6:$G$11,S23:S28) -> 902642.86 | ... W32: =SUMPRODUCT('.c12_alloc'!$G$6:$G$11,W23:W28) -> 1532571.4
A33: only paid by c12 | B33: o | C33: hr_only_c12 | I33: 42318.571 | J33: 58237.714 | L33: =SUMPRODUCT('.c12_alloc'!$E$6:$E$11,L23:L28) -> 31928.571 | M33: =SUMPRODUCT('.c12_alloc'!$E$6:$E$11,M23:M28) -> 31928.571 | N33: =SUMPRODUCT('.c12_alloc'!$E$6:$E$11,N23:N28) -> 31928.571 | O33: =SUMPRODUCT('.c12_alloc'!$E$6:$E$11,O23:O28) -> 42318.571 | P33: =SUMPRODUCT('.c12_alloc'!$E$6:$E$11,P23:P28) -> 58237.714 | Q33: =SUMPRODUCT('.c12_alloc'!$E$6:$E$11,Q23:Q28) -> 58237.714 | R33: =SUMPRODUCT('.c12_alloc'!$E$6:$E$11,R23:R28) -> 58237.714 | S33: =SUMPRODUCT('.c12_alloc'!$E$6:$E$11,S23:S28) -> 79017.714 | ... W33: =SUMPRODUCT('.c12_alloc'!$E$6:$E$11,W23:W28) -> 253730.86

Sheet .c12_hm_hr
A2: Year | E2: 45657 | F2: 45747 | G2: 45838 | H2: 45930 | I2: 46022 | J2: 46112 | K2: 46203 | L2: 45747 | M2: 45838 | N2: 45930 | O2: 46022 | P2: 46112 | Q2: 46203 | R2: 46295 | S2: 46387 | T2: 46752 | U2: 47118 | V2: 47483 | W2: 47848
E3: actual | L3: i/o
B4: i/o | C4: field_name | D4: index
A5: base
A6: ACEO Loren Hotels (CE) | B6: i | C6: base_salary | D6: ce | I6: 125000 | J6: 125000 | L6: 125000 | M6: 125000 | N6: 125000 | O6: 125000 | P6: 125000 | Q6: 125000 | R6: 125000 | S6: 125000 | T6: 500000 | U6: 500000 | V6: 500000 | W6: 500000
A7: VP Operations (WS) | B7: i | C7: base_salary | D7: ws | I7: 68750 | J7: 72500 | L7: 68750 | M7: 68750 | N7: 68750 | O7: 68750 | P7: 72500 | Q7: 72500 | R7: 72500 | S7: 72500 | T7: 290000 | U7: 290000 | V7: 290000 | W7: 290000
A8: seniorS&Mexe (CL) | B8: i | C8: base_salary | D8: cl | I8: 0 | J8: 75000 | L8: 0 | M8: 0 | N8: 0 | O8: 0 | P8: 75000 | Q8: 75000 | R8: 75000 | S8: 75000 | T8: 300000 | U8: 300000 | V8: 300000 | W8: 300000
A9: Senior Associate (RF) | B9: i | C9: base_salary | D9: rf | I9: 37500 | J9: 40000 | L9: 37500 | M9: 37500 | N9: 37500 | O9: 37500 | P9: 40000 | Q9: 40000 | R9: 40000 | S9: 40000 | T9: 160000 | U9: 160000 | V9: 160000 | W9: 160000
A10: associate (MT) | B10: i | C10: base_salary | D10: mt | I10: 27500 | J10: 27500 | L10: 27500 | M10: 27500 | N10: 27500 | O10: 27500 | P10: 27500 | Q10: 27500 | R10: 27500 | S10: 27500 | T10: 110000 | U10: 110000 | V10: 110000 | W10: 110000
A11: project manager | B11: i | C11: base_salary | D11: project | I11: 0 | J11: 0 | L11: 0 | M11: 0 | N11: 0 | O11: 0 | P11: 0 | Q11: 0 | R11: 37500 | S11: 37500 | T11: 150000 | U11: 150000 | V11: 150000 | W11: 150000
A12: Total | I12: 258750 | J12: 340000 | L12: =SUM(L6:L11) -> 258750 | M12: =SUM(M6:M11) -> 258750 | N12: =SUM(N6:N11) -> 258750 | O12: =SUM(O6:O11) -> 258750 | P12: =SUM(P6:P11) -> 340000 | Q12: =SUM(Q6:Q11) -> 340000 | R12: =SUM(R6:R11) -> 377500 | S12: =SUM(S6:S11) -> 377500 | ... W12: =SUM(W6:W11) -> 1510000
A14: Bonus
A15: =A6 -> ACEO Loren Hotels (CE) | B15: i | C15: bonus | D15: ce | I15: 250000 | J15: 0 | L15: 0 | M15: 0 | N15: 0 | O15: 250000 | P15: 0 | Q15: 0 | R15: 0 | S15: 250000 | T15: 500000 | U15: 500000 | V15: 500000 | W15: 500000
A16: =A7 -> VP Operations (WS) | B16: i | C16: bonus | D16: ws | I16: 115000 | J16: 0 | L16: 0 | M16: 0 | N16: 0 | O16: 115000 | P16: 0 | Q16: 0 | R16: 0 | S16: 75000 | T16: 75000 | U16: 75000 | V16: 75000 | W16: 75000
A17: =A8 -> seniorS&Mexe (CL) | B17: i | C17: bonus | D17: cl | I17: 20000 | J17: 0 | L17: 0 | M17: 0 | N17: 0 | O17: 20000 | P17: 0 | Q17: 0 | R17: 0 | S17: 75000 | T17: 75000 | U17: 75000 | V17: 75000 | W17: 75000
A18: =A9 -> Senior Associate (RF) | B18: i | C18: bonus | D18: rf | I18: 50000 | J18: 0 | L18: 0 | M18: 0 | N18: 0 | O18: 50000 | P18: 0 | Q18: 0 | R18: 0 | S18: 50000 | T18: 50000 | U18: 50000 | V18: 50000 | W18: 50000
A19: =A10 -> associate (MT) | B19: i | C19: bonus | D19: mt | I19: 20000 | J19: 0 | L19: 0 | M19: 0 | N19: 0 | O19: 20000 | P19: 0 | Q19: 0 | R19: 0 | S19: 40000 | T19: 40000 | U19: 40000 | V19: 40000 | W19: 40000
A20: =A11 -> project manager | B20: i | C20: bonus | D20: project | I20: 0 | J20: 0 | L20: 0 | M20: 0 | N20: 0 | O20: 0 | P20: 0 | Q20: 0 | R20: 0 | S20: 5000 | T20: 10000 | U20: 10000 | V20: 10000 | W20: 10000
A21: Total | I21: 455000 | J21: 0 | L21: =SUM(L15:L20) -> 0 | M21: =SUM(M15:M20) -> 0 | N21: =SUM(N15:N20) -> 0 | O21: =SUM(O15:O20) -> 455000 | P21: =SUM(P15:P20) -> 0 | Q21: =SUM(Q15:Q20) -> 0 | R21: =SUM(R15:R20) -> 0 | S21: =SUM(S15:S20) -> 495000 | ... W21: =SUM(W15:W20) -> 750000
A23: Total Salaries
A24: =A15 -> ACEO Loren Hotels (CE) | B24: c | C24: total_salary | D24: ce | I24: 403750 | J24: 144000 | L24: =L6*(1+'.c12_inputs.hr'!$E$8)+(L15*(1+'.c12_inputs.hr'!$E$9)) -> 144000 | M24: =M6*(1+'.c12_inputs.hr'!$E$8)+(M15*(1+'.c12_inputs.hr'!$E$9)) -> 144000 | N24: =N6*(1+'.c12_inputs.hr'!$E$8)+(N15*(1+'.c12_inputs.hr'!$E$9)) -> 144000 | O24: =O6*(1+'.c12_inputs.hr'!$E$8)+(O15*(1+'.c12_inputs.hr'!$E$9)) -> 403750 | P24: =P6*(1+'.c12_inputs.hr'!$E$8)+(P15*(1+'.c12_inputs.hr'!$E$9)) -> 144000 | Q24: =Q6*(1+'.c12_inputs.hr'!$E$8)+(Q15*(1+'.c12_inputs.hr'!$E$9)) -> 144000 | R24: =R6*(1+'.c12_inputs.hr'!$E$8)+(R15*(1+'.c12_inputs.hr'!$E$9)) -> 144000 | S24: =S6*(1+'.c12_inputs.hr'!$E$8)+(S15*(1+'.c12_inputs.hr'!$E$9)) -> 403750 | ... W24: =W6*(1+'.c12_inputs.hr'!$E$8)+(W15*(1+'.c12_inputs.hr'!$E$9)) -> 1095500
A25: =A16 -> VP Operations (WS) | B25: c | C25: total_salary | D25: ws | I25: 198685 | J25: 83520 | L25: =L7*(1+'.c12_inputs.hr'!$E$8)+(L16*(1+'.c12_inputs.hr'!$E$9)) -> 79200 | M25: =M7*(1+'.c12_inputs.hr'!$E$8)+(M16*(1+'.c12_inputs.hr'!$E$9)) -> 79200 | N25: =N7*(1+'.c12_inputs.hr'!$E$8)+(N16*(1+'.c12_inputs.hr'!$E$9)) -> 79200 | O25: =O7*(1+'.c12_inputs.hr'!$E$8)+(O16*(1+'.c12_inputs.hr'!$E$9)) -> 198685 | P25: =P7*(1+'.c12_inputs.hr'!$E$8)+(P16*(1+'.c12_inputs.hr'!$E$9)) -> 83520 | Q25: =Q7*(1+'.c12_inputs.hr'!$E$8)+(Q16*(1+'.c12_inputs.hr'!$E$9)) -> 83520 | R25: =R7*(1+'.c12_inputs.hr'!$E$8)+(R16*(1+'.c12_inputs.hr'!$E$9)) -> 83520 | S25: =S7*(1+'.c12_inputs.hr'!$E$8)+(S16*(1+'.c12_inputs.hr'!$E$9)) -> 161445 | ... W25: =W7*(1+'.c12_inputs.hr'!$E$8)+(W16*(1+'.c12_inputs.hr'!$E$9)) -> 412005
A26: =A17 -> seniorS&Mexe (CL) | B26: c | C26: total_salary | D26: cl | I26: 20780 | J26: 86400 | L26: =L8*(1+'.c12_inputs.hr'!$E$8)+(L17*(1+'.c12_inputs.hr'!$E$9)) -> 0 | M26: =M8*(1+'.c12_inputs.hr'!$E$8)+(M17*(1+'.c12_inputs.hr'!$E$9)) -> 0 | N26: =N8*(1+'.c12_inputs.hr'!$E$8)+(N17*(1+'.c12_inputs.hr'!$E$9)) -> 0 | O26: =O8*(1+'.c12_inputs.hr'!$E$8)+(O17*(1+'.c12_inputs.hr'!$E$9)) -> 20780 | P26: =P8*(1+'.c12_inputs.hr'!$E$8)+(P17*(1+'.c12_inputs.hr'!$E$9)) -> 86400 | Q26: =Q8*(1+'.c12_inputs.hr'!$E$8)+(Q17*(1+'.c12_inputs.hr'!$E$9)) -> 86400 | R26: =R8*(1+'.c12_inputs.hr'!$E$8)+(R17*(1+'.c12_inputs.hr'!$E$9)) -> 86400 | S26: =S8*(1+'.c12_inputs.hr'!$E$8)+(S17*(1+'.c12_inputs.hr'!$E$9)) -> 164325 | ... W26: =W8*(1+'.c12_inputs.hr'!$E$8)+(W17*(1+'.c12_inputs.hr'!$E$9)) -> 423525
A27: =A18 -> Senior Associate (RF) | B27: c | C27: total_salary | D27: rf | I27: 95150 | J27: 46080 | L27: =L9*(1+'.c12_inputs.hr'!$E$8)+(L18*(1+'.c12_inputs.hr'!$E$9)) -> 43200 | M27: =M9*(1+'.c12_inputs.hr'!$E$8)+(M18*(1+'.c12_inputs.hr'!$E$9)) -> 43200 | N27: =N9*(1+'.c12_inputs.hr'!$E$8)+(N18*(1+'.c12_inputs.hr'!$E$9)) -> 43200 | O27: =O9*(1+'.c12_inputs.hr'!$E$8)+(O18*(1+'.c12_inputs.hr'!$E$9)) -> 95150 | P27: =P9*(1+'.c12_inputs.hr'!$E$8)+(P18*(1+'.c12_inputs.hr'!$E$9)) -> 46080 | Q27: =Q9*(1+'.c12_inputs.hr'!$E$8)+(Q18*(1+'.c12_inputs.hr'!$E$9)) -> 46080 | R27: =R9*(1+'.c12_inputs.hr'!$E$8)+(R18*(1+'.c12_inputs.hr'!$E$9)) -> 46080 | S27: =S9*(1+'.c12_inputs.hr'!$E$8)+(S18*(1+'.c12_inputs.hr'!$E$9)) -> 98030 | ... W27: =W9*(1+'.c12_inputs.hr'!$E$8)+(W18*(1+'.c12_inputs.hr'!$E$9)) -> 236270
A28: =A19 -> associate (MT) | B28: c | C28: total_salary | D28: mt | I28: 52460 | J28: 31680 | L28: =L10*(1+'.c12_inputs.hr'!$E$8)+(L19*(1+'.c12_inputs.hr'!$E$9)) -> 31680 | M28: =M10*(1+'.c12_inputs.hr'!$E$8)+(M19*(1+'.c12_inputs.hr'!$E$9)) -> 31680 | N28: =N10*(1+'.c12_inputs.hr'!$E$8)+(N19*(1+'.c12_inputs.hr'!$E$9)) -> 31680 | O28: =O10*(1+'.c12_inputs.hr'!$E$8)+(O19*(1+'.c12_inputs.hr'!$E$9)) -> 52460 | P28: =P10*(1+'.c12_inputs.hr'!$E$8)+(P19*(1+'.c12_inputs.hr'!$E$9)) -> 31680 | Q28: =Q10*(1+'.c12_inputs.hr'!$E$8)+(Q19*(1+'.c12_inputs.hr'!$E$9)) -> 31680 | R28: =R10*(1+'.c12_inputs.hr'!$E$8)+(R19*(1+'.c12_inputs.hr'!$E$9)) -> 31680 | S28: =S10*(1+'.c12_inputs.hr'!$E$8)+(S19*(1+'.c12_inputs.hr'!$E$9)) -> 73240 | ... W28: =W10*(1+'.c12_inputs.hr'!$E$8)+(W19*(1+'.c12_inputs.hr'!$E$9)) -> 168280
A29: =A20 -> project manager | B29: c | C29: total_salary | D29: project | I29: 0 | J29: 0 | L29: =L11*(1+'.c12_inputs.hr'!$E$8)+(L20*(1+'.c12_inputs.hr'!$E$9)) -> 0 | M29: =M11*(1+'.c12_inputs.hr'!$E$8)+(M20*(1+'.c12_inputs.hr'!$E$9)) -> 0 | N29: =N11*(1+'.c12_inputs.hr'!$E$8)+(N20*(1+'.c12_inputs.hr'!$E$9)) -> 0 | O29: =O11*(1+'.c12_inputs.hr'!$E$8)+(O20*(1+'.c12_inputs.hr'!$E$9)) -> 0 | P29: =P11*(1+'.c12_inputs.hr'!$E$8)+(P20*(1+'.c12_inputs.hr'!$E$9)) -> 0 | Q29: =Q11*(1+'.c12_inputs.hr'!$E$8)+(Q20*(1+'.c12_inputs.hr'!$E$9)) -> 0 | R29: =R11*(1+'.c12_inputs.hr'!$E$8)+(R20*(1+'.c12_inputs.hr'!$E$9)) -> 43200 | S29: =S11*(1+'.c12_inputs.hr'!$E$8)+(S20*(1+'.c12_inputs.hr'!$E$9)) -> 48395 | ... W29: =W11*(1+'.c12_inputs.hr'!$E$8)+(W20*(1+'.c12_inputs.hr'!$E$9)) -> 183190
A31: Grand Total | B31: o | C31: hr_grand_total | I31: 770825 | J31: 391680 | L31: =SUM(L24:L29) -> 298080 | M31: =SUM(M24:M29) -> 298080 | N31: =SUM(N24:N29) -> 298080 | O31: =SUM(O24:O29) -> 770825 | P31: =SUM(P24:P29) -> 391680 | Q31: =SUM(Q24:Q29) -> 391680 | R31: =SUM(R24:R29) -> 434880 | S31: =SUM(S24:S29) -> 949185 | ... W31: =SUM(W24:W29) -> 2518770
A32: reimbersable to hotel | B32: o | C32: hr_reimbursable | I32: 367075 | J32: 247680 | L32: =SUMPRODUCT('.c12_alloc'!$H$15:$H$20,'.c12_hm_hr'!L$24:L$29) -> 154080 | M32: =SUMPRODUCT('.c12_alloc'!$H$15:$H$20,'.c12_hm_hr'!M$24:M$29) -> 154080 | N32: =SUMPRODUCT('.c12_alloc'!$H$15:$H$20,'.c12_hm_hr'!N$24:N$29) -> 154080 | O32: =SUMPRODUCT('.c12_alloc'!$H$15:$H$20,'.c12_hm_hr'!O$24:O$29) -> 367075 | P32: =SUMPRODUCT('.c12_alloc'!$H$15:$H$20,'.c12_hm_hr'!P$24:P$29) -> 247680 | Q32: =SUMPRODUCT('.c12_alloc'!$H$15:$H$20,'.c12_hm_hr'!Q$24:Q$29) -> 247680 | R32: =SUMPRODUCT('.c12_alloc'!$H$15:$H$20,'.c12_hm_hr'!R$24:R$29) -> 290880 | S32: =SUMPRODUCT('.c12_alloc'!$H$15:$H$20,'.c12_hm_hr'!S$24:S$29) -> 545435 | ... W32: =SUMPRODUCT('.c12_alloc'!$H$15:$H$20,'.c12_hm_hr'!W$24:W$29) -> 1423270
A33: not reimbersable by hotel, but paid by lgh | B33: o | C33: hr_not_reimbursable | I33: 403750 | J33: 144000 | L33: =SUMPRODUCT('.c12_alloc'!$G$15:$G$20,'.c12_hm_hr'!L$24:L$29) -> 144000 | M33: =SUMPRODUCT('.c12_alloc'!$G$15:$G$20,'.c12_hm_hr'!M$24:M$29) -> 144000 | N33: =SUMPRODUCT('.c12_alloc'!$G$15:$G$20,'.c12_hm_hr'!N$24:N$29) -> 144000 | O33: =SUMPRODUCT('.c12_alloc'!$G$15:$G$20,'.c12_hm_hr'!O$24:O$29) -> 403750 | P33: =SUMPRODUCT('.c12_alloc'!$G$15:$G$20,'.c12_hm_hr'!P$24:P$29) -> 144000 | Q33: =SUMPRODUCT('.c12_alloc'!$G$15:$G$20,'.c12_hm_hr'!Q$24:Q$29) -> 144000 | R33: =SUMPRODUCT('.c12_alloc'!$G$15:$G$20,'.c12_hm_hr'!R$24:R$29) -> 144000 | S33: =SUMPRODUCT('.c12_alloc'!$G$15:$G$20,'.c12_hm_hr'!S$24:S$29) -> 403750 | ... W33: =SUMPRODUCT('.c12_alloc'!$G$15:$G$20,'.c12_hm_hr'!W$24:W$29) -> 1095500
A34: only paid by c12 | B34: o | C34: hr_only_c12 | I34: 0 | J34: 0 | L34: =SUMPRODUCT('.c12_alloc'!$E$15:$E$20,'.c12_hm_hr'!L$24:L$29) -> 0 | M34: =SUMPRODUCT('.c12_alloc'!$E$15:$E$20,'.c12_hm_hr'!M$24:M$29) -> 0 | N34: =SUMPRODUCT('.c12_alloc'!$E$15:$E$20,'.c12_hm_hr'!N$24:N$29) -> 0 | O34: =SUMPRODUCT('.c12_alloc'!$E$15:$E$20,'.c12_hm_hr'!O$24:O$29) -> 0 | P34: =SUMPRODUCT('.c12_alloc'!$E$15:$E$20,'.c12_hm_hr'!P$24:P$29) -> 0 | Q34: =SUMPRODUCT('.c12_alloc'!$E$15:$E$20,'.c12_hm_hr'!Q$24:Q$29) -> 0 | R34: =SUMPRODUCT('.c12_alloc'!$E$15:$E$20,'.c12_hm_hr'!R$24:R$29) -> 0 | S34: =SUMPRODUCT('.c12_alloc'!$E$15:$E$20,'.c12_hm_hr'!S$24:S$29) -> 0 | ... W34: =SUMPRODUCT('.c12_alloc'!$E$15:$E$20,'.c12_hm_hr'!W$24:W$29) -> 0

Sheet .c12_d&s_hr
A2: Year | E2: 45657 | F2: 45747 | G2: 45838 | H2: 45930 | I2: 46022 | J2: 46112 | K2: 46203 | L2: 45747 | M2: 45838 | N2: 45930 | O2: 46022 | P2: 46112 | Q2: 46203 | R2: 46295 | S2: 46387 | T2: 46752 | U2: 47118 | V2: 47483 | W2: 47848
E3: actual | L3: i/o
B4: i/o | C4: field_name | D4: index
A5: base
A6: HODS (RB) | B6: i | C6: base_salary | D6: rb | I6: 87500 | J6: 187500 | L6: 87500 | M6: 87500 | N6: 87500 | O6: 87500 | P6: 187500 | Q6: 187500 | R6: 187500 | S6: 187500 | T6: 750000 | U6: 750000 | V6: 750000 | W6: 750000
A7: Project Executive (LS) (100%) | B7: i | C7: base_salary | D7: ls | I7: 46250 | J7: 46250 | L7: 46250 | M7: 46250 | N7: 46250 | O7: 46250 | P7: 46250 | Q7: 46250 | R7: 46250 | S7: 46250 | T7: 185000 | U7: 185000 | V7: 185000 | W7: 185000
A8: Project Manager (BD) (100%) | B8: i | C8: base_salary | D8: bd | I8: 27500 | J8: 28125 | L8: 27500 | M8: 27500 | N8: 27500 | O8: 27500 | P8: 28125 | Q8: 28125 | R8: 28125 | S8: 28125 | T8: 112500 | U8: 112500 | V8: 112500 | W8: 112500
A9: Counsel (KT) | B9: i | C9: base_salary | D9: kt | I9: 62500 | J9: 65000 | L9: 62500 | M9: 62500 | N9: 62500 | O9: 62500 | P9: 65000 | Q9: 65000 | R9: 65000 | S9: 65000 | T9: 260000 | U9: 260000 | V9: 260000 | W9: 260000
A10: Development Manager??? (alexi?) | B10: i | C10: base_salary | D10: development | I10: 0 | J10: 0 | L10: 43750 | M10: 43750 | N10: 43750 | O10: 0 | P10: 0 | Q10: 0 | R10: 0 | S10: 0 | T10: 0 | U10: 0 | V10: 0 | W10: 0
A11: Banker (tBD) | B11: i | C11: base_salary | D11: banker | I11: 75000 | J11: 0 | L11: 75000 | M11: 75000 | N11: 75000 | O11: 75000 | P11: 0 | Q11: 0 | R11: 0 | S11: 0 | T11: 0 | U11: 0 | V11: 0 | W11: 0
A12: Senior Design Manager (AM) | B12: i | C12: base_salary | D12: am | I12: 45000 | J12: 47500 | L12: 45000 | M12: 45000 | N12: 45000 | O12: 45000 | P12: 47500 | Q12: 47500 | R12: 47500 | S12: 47500 | T12: 190000 | U12: 190000 | V12: 190000 | W12: 190000
A13: Design Manager (AL) (gone) | B13: i | C13: base_salary | D13: al | I13: 32500 | J13: 34375 | L13: 32500 | M13: 32500 | N13: 32500 | O13: 32500 | P13: 34375 | Q13: 0 | R13: 0 | S13: 0 | T13: 0 | U13: 0 | V13: 0 | W13: 0
A14: new design manager (TBD) | B14: i | C14: base_salary | D14: tbd | I14: 0 | J14: 0 | L14: 0 | M14: 0 | N14: 0 | O14: 0 | P14: 0 | Q14: 0 | R14: 34375 | S14: 34375 | T14: 137500 | U14: 137500 | V14: 137500 | W14: 137500
A15: FF&E (SB) | B15: i | C15: base_salary | D15: sb | I15: 27500 | J15: 27500 | L15: 27500 | M15: 27500 | N15: 27500 | O15: 27500 | P15: 27500 | Q15: 27500 | R15: 27500 | S15: 27500 | T15: 110000 | U15: 110000 | V15: 110000 | W15: 110000
A16: Senior Financial Analyst (KS) | B16: i | C16: base_salary | D16: ks | J16: 50000 | P16: 50000 | Q16: 50000 | R16: 50000 | S16: 50000 | T16: 200000 | U16: 200000 | V16: 200000 | W16: 200000
A17: Total | I17: 403750 | J17: 486250 | L17: =SUM(L6:L16) -> 447500 | M17: =SUM(M6:M16) -> 447500 | N17: =SUM(N6:N16) -> 447500 | O17: =SUM(O6:O16) -> 403750 | P17: =SUM(P6:P16) -> 486250 | Q17: =SUM(Q6:Q16) -> 451875 | R17: =SUM(R6:R16) -> 486250 | S17: =SUM(S6:S16) -> 486250 | ... W17: =SUM(W6:W16) -> 1945000
A19: Bonus
A20: =+A6 -> HODS (RB) | B20: i | C20: bonus | D20: rb | I20: 685000 | J20: 0 | L20: 0 | M20: 0 | N20: 0 | O20: 685000 | P20: 0 | Q20: 0 | R20: 0 | S20: 250000 | T20: 250000 | U20: 250000 | V20: 250000 | W20: 250000
A21: =+A7 -> Project Executive (LS) (100%) | B21: i | C21: bonus | D21: ls | I21: 20000 | J21: 0 | L21: 0 | M21: 0 | N21: 0 | O21: 20000 | P21: 0 | Q21: 0 | R21: 0 | S21: 15000 | T21: 15000 | U21: 15000 | V21: 15000 | W21: 15000
A22: =+A8 -> Project Manager (BD) (100%) | B22: i | C22: bonus | D22: bd | I22: 17500 | J22: 0 | L22: 0 | M22: 0 | N22: 0 | O22: 17500 | P22: 0 | Q22: 0 | R22: 0 | S22: 15000 | T22: 15000 | U22: 15000 | V22: 15000 | W22: 15000
A23: =+A9 -> Counsel (KT) | B23: i | C23: bonus | D23: kt | I23: 230000 | J23: 0 | L23: 0 | M23: 0 | N23: 0 | O23: 230000 | P23: 0 | Q23: 0 | R23: 0 | S23: 125000 | T23: 125000 | U23: 125000 | V23: 125000 | W23: 125000
A24: =+A10 -> Development Manager??? (alexi?) | B24: i | C24: bonus | D24: development | I24: 0 | J24: 0 | L24: 0 | M24: 0 | N24: 0 | O24: 0 | P24: 0 | Q24: 0 | R24: 0 | S24: 0 | T24: 0 | U24: 0 | V24: 0 | W24: 0
A25: =+A11 -> Banker (tBD) | B25: i | C25: bonus | D25: banker | I25: 50000 | J25: 0 | L25: 0 | M25: 0 | N25: 0 | O25: 50000 | P25: 0 | Q25: 0 | R25: 0 | S25: 100000 | T25: 0 | U25: 0 | V25: 0 | W25: 0
A26: =+A12 -> Senior Design Manager (AM) | B26: i | C26: bonus | D26: am | I26: 65000 | J26: 0 | O26: 65000 | P26: 0 | Q26: 0 | R26: 0 | S26: 55000 | T26: 55000 | U26: 55000 | V26: 55000 | W26: 55000
A27: =+A13 -> Design Manager (AL) (gone) | B27: i | C27: bonus | D27: al | I27: 25000 | J27: 0 | L27: 0 | M27: 0 | N27: 0 | O27: 25000 | P27: 0 | Q27: 0 | R27: 0 | S27: 0 | T27: 0 | U27: 0 | V27: 0 | W27: 0
A28: =+A14 -> new design manager (TBD) | B28: i | C28: bonus | D28: tbd | I28: 0 | J28: 0 | L28: 0 | M28: 0 | N28: 0 | O28: 0 | P28: 0 | Q28: 0 | R28: 0 | S28: 11250 | T28: 22500 | U28: 22500 | V28: 22500 | W28: 22500
A29: =+A15 -> FF&E (SB) | B29: i | C29: bonus | D29: sb | I29: 0 | J29: 0 | L29: 0 | M29: 0 | N29: 0 | O29: 0 | P29: 0 | Q29: 0 | R29: 0 | S29: 15000 | T29: 15000 | U29: 15000 | V29: 15000 | W29: 15000
A30: =+A16 -> Senior Financial Analyst (KS) | B30: i | C30: bonus | D30: ks | I30: 50000 | L30: 0 | M30: 0 | N30: 0 | O30: 50000 | S30: 50000 | T30: 50000 | U30: 50000 | V30: 50000 | W30: 50000
A31: Total | I31: 1142500 | J31: 0 | L31: 0 | M31: 0 | N31: 0 | O31: 1142500 | P31: 0 | Q31: 0 | R31: 0 | S31: 897500 | T31: 797500 | U31: 797500 | V31: 797500 | W31: 797500
A33: Total Salaries
A34: =+A6 -> HODS (RB) | B34: c | C34: total_salary | D34: rb | I34: 812515 | J34: 216000 | L34: =+L6*(1+'.c12_inputs.hr'!$E$15)+(L20*(1+'.c12_inputs.hr'!$E$16)) -> 100800 | M34: =+M6*(1+'.c12_inputs.hr'!$E$15)+(M20*(1+'.c12_inputs.hr'!$E$16)) -> 100800 | N34: =+N6*(1+'.c12_inputs.hr'!$E$15)+(N20*(1+'.c12_inputs.hr'!$E$16)) -> 100800 | O34: =+O6*(1+'.c12_inputs.hr'!$E$15)+(O20*(1+'.c12_inputs.hr'!$E$16)) -> 812515 | P34: =+P6*(1+'.c12_inputs.hr'!$E$15)+(P20*(1+'.c12_inputs.hr'!$E$16)) -> 216000 | Q34: =+Q6*(1+'.c12_inputs.hr'!$E$15)+(Q20*(1+'.c12_inputs.hr'!$E$16)) -> 216000 | R34: =+R6*(1+'.c12_inputs.hr'!$E$15)+(R20*(1+'.c12_inputs.hr'!$E$16)) -> 216000 | S34: =+S6*(1+'.c12_inputs.hr'!$E$15)+(S20*(1+'.c12_inputs.hr'!$E$16)) -> 475750 | ... W34: =+W6*(1+'.c12_inputs.hr'!$E$15)+(W20*(1+'.c12_inputs.hr'!$E$16)) -> 1123750
A35: =+A7 -> Project Executive (LS) (100%) | B35: c | C35: total_salary | D35: ls | I35: 74060 | J35: 53280 | L35: =+L7*(1+'.c12_inputs.hr'!$E$15)+(L21*(1+'.c12_inputs.hr'!$E$16)) -> 53280 | M35: =+M7*(1+'.c12_inputs.hr'!$E$15)+(M21*(1+'.c12_inputs.hr'!$E$16)) -> 53280 | N35: =+N7*(1+'.c12_inputs.hr'!$E$15)+(N21*(1+'.c12_inputs.hr'!$E$16)) -> 53280 | O35: =+O7*(1+'.c12_inputs.hr'!$E$15)+(O21*(1+'.c12_inputs.hr'!$E$16)) -> 74060 | P35: =+P7*(1+'.c12_inputs.hr'!$E$15)+(P21*(1+'.c12_inputs.hr'!$E$16)) -> 53280 | Q35: =+Q7*(1+'.c12_inputs.hr'!$E$15)+(Q21*(1+'.c12_inputs.hr'!$E$16)) -> 53280 | R35: =+R7*(1+'.c12_inputs.hr'!$E$15)+(R21*(1+'.c12_inputs.hr'!$E$16)) -> 53280 | S35: =+S7*(1+'.c12_inputs.hr'!$E$15)+(S21*(1+'.c12_inputs.hr'!$E$16)) -> 68865 | ... W35: =+W7*(1+'.c12_inputs.hr'!$E$15)+(W21*(1+'.c12_inputs.hr'!$E$16)) -> 228705
A36: =+A8 -> Project Manager (BD) (100%) | B36: c | C36: total_salary | D36: bd | I36: 49862.5 | J36: 32400 | L36: =+L8*(1+'.c12_inputs.hr'!$E$15)+(L22*(1+'.c12_inputs.hr'!$E$16)) -> 31680 | M36: =+M8*(1+'.c12_inputs.hr'!$E$15)+(M22*(1+'.c12_inputs.hr'!$E$16)) -> 31680 | N36: =+N8*(1+'.c12_inputs.hr'!$E$15)+(N22*(1+'.c12_inputs.hr'!$E$16)) -> 31680 | O36: =+O8*(1+'.c12_inputs.hr'!$E$15)+(O22*(1+'.c12_inputs.hr'!$E$16)) -> 49862.5 | P36: =+P8*(1+'.c12_inputs.hr'!$E$15)+(P22*(1+'.c12_inputs.hr'!$E$16)) -> 32400 | Q36: =+Q8*(1+'.c12_inputs.hr'!$E$15)+(Q22*(1+'.c12_inputs.hr'!$E$16)) -> 32400 | R36: =+R8*(1+'.c12_inputs.hr'!$E$15)+(R22*(1+'.c12_inputs.hr'!$E$16)) -> 32400 | S36: =+S8*(1+'.c12_inputs.hr'!$E$15)+(S22*(1+'.c12_inputs.hr'!$E$16)) -> 47985 | ... W36: =+W8*(1+'.c12_inputs.hr'!$E$15)+(W22*(1+'.c12_inputs.hr'!$E$16)) -> 145185
A37: =+A9 -> Counsel (KT) | B37: c | C37: total_salary | D37: kt | I37: 310970 | J37: 74880 | L37: =+L9*(1+'.c12_inputs.hr'!$E$15)+(L23*(1+'.c12_inputs.hr'!$E$16)) -> 72000 | M37: =+M9*(1+'.c12_inputs.hr'!$E$15)+(M23*(1+'.c12_inputs.hr'!$E$16)) -> 72000 | N37: =+N9*(1+'.c12_inputs.hr'!$E$15)+(N23*(1+'.c12_inputs.hr'!$E$16)) -> 72000 | O37: =+O9*(1+'.c12_inputs.hr'!$E$15)+(O23*(1+'.c12_inputs.hr'!$E$16)) -> 310970 | P37: =+P9*(1+'.c12_inputs.hr'!$E$15)+(P23*(1+'.c12_inputs.hr'!$E$16)) -> 74880 | Q37: =+Q9*(1+'.c12_inputs.hr'!$E$15)+(Q23*(1+'.c12_inputs.hr'!$E$16)) -> 74880 | R37: =+R9*(1+'.c12_inputs.hr'!$E$15)+(R23*(1+'.c12_inputs.hr'!$E$16)) -> 74880 | S37: =+S9*(1+'.c12_inputs.hr'!$E$15)+(S23*(1+'.c12_inputs.hr'!$E$16)) -> 204755 | ... W37: =+W9*(1+'.c12_inputs.hr'!$E$15)+(W23*(1+'.c12_inputs.hr'!$E$16)) -> 429395
A38: =+A10 -> Development Manager??? (alexi?) | B38: c | C38: total_salary | D38: development | I38: 0 | J38: 0 | L38: =+L10*(1+'.c12_inputs.hr'!$E$15)+(L24*(1+'.c12_inputs.hr'!$E$16)) -> 50400 | M38: =+M10*(1+'.c12_inputs.hr'!$E$15)+(M24*(1+'.c12_inputs.hr'!$E$16)) -> 50400 | N38: =+N10*(1+'.c12_inputs.hr'!$E$15)+(N24*(1+'.c12_inputs.hr'!$E$16)) -> 50400 | O38: =+O10*(1+'.c12_inputs.hr'!$E$15)+(O24*(1+'.c12_inputs.hr'!$E$16)) -> 0 | P38: =+P10*(1+'.c12_inputs.hr'!$E$15)+(P24*(1+'.c12_inputs.hr'!$E$16)) -> 0 | Q38: =+Q10*(1+'.c12_inputs.hr'!$E$15)+(Q24*(1+'.c12_inputs.hr'!$E$16)) -> 0 | R38: =+R10*(1+'.c12_inputs.hr'!$E$15)+(R24*(1+'.c12_inputs.hr'!$E$16)) -> 0 | S38: =+S10*(1+'.c12_inputs.hr'!$E$15)+(S24*(1+'.c12_inputs.hr'!$E$16)) -> 0 | ... W38: =+W10*(1+'.c12_inputs.hr'!$E$15)+(W24*(1+'.c12_inputs.hr'!$E$16)) -> 0
A39: =+A11 -> Banker (tBD) | B39: c | C39: total_salary | D39: banker | I39: 138350 | J39: 0 | L39: =+L11*(1+'.c12_inputs.hr'!$E$15)+(L25*(1+'.c12_inputs.hr'!$E$16)) -> 86400 | M39: =+M11*(1+'.c12_inputs.hr'!$E$15)+(M25*(1+'.c12_inputs.hr'!$E$16)) -> 86400 | N39: =+N11*(1+'.c12_inputs.hr'!$E$15)+(N25*(1+'.c12_inputs.hr'!$E$16)) -> 86400 | O39: =+O11*(1+'.c12_inputs.hr'!$E$15)+(O25*(1+'.c12_inputs.hr'!$E$16)) -> 138350 | P39: =+P11*(1+'.c12_inputs.hr'!$E$15)+(P25*(1+'.c12_inputs.hr'!$E$16)) -> 0 | Q39: =+Q11*(1+'.c12_inputs.hr'!$E$15)+(Q25*(1+'.c12_inputs.hr'!$E$16)) -> 0 | R39: =+R11*(1+'.c12_inputs.hr'!$E$15)+(R25*(1+'.c12_inputs.hr'!$E$16)) -> 0 | S39: =+S11*(1+'.c12_inputs.hr'!$E$15)+(S25*(1+'.c12_inputs.hr'!$E$16)) -> 103900 | ... W39: =+W11*(1+'.c12_inputs.hr'!$E$15)+(W25*(1+'.c12_inputs.hr'!$E$16)) -> 0
A40: =+A12 -> Senior Design Manager (AM) | B40: c | C40: total_salary | D40: am | I40: 119375 | J40: 54720 | L40: =+L12*(1+'.c12_inputs.hr'!$E$15)+(L26*(1+'.c12_inputs.hr'!$E$16)) -> 51840 | M40: =+M12*(1+'.c12_inputs.hr'!$E$15)+(M26*(1+'.c12_inputs.hr'!$E$16)) -> 51840 | N40: =+N12*(1+'.c12_inputs.hr'!$E$15)+(N26*(1+'.c12_inputs.hr'!$E$16)) -> 51840 | O40: =+O12*(1+'.c12_inputs.hr'!$E$15)+(O26*(1+'.c12_inputs.hr'!$E$16)) -> 119375 | P40: =+P12*(1+'.c12_inputs.hr'!$E$15)+(P26*(1+'.c12_inputs.hr'!$E$16)) -> 54720 | Q40: =+Q12*(1+'.c12_inputs.hr'!$E$15)+(Q26*(1+'.c12_inputs.hr'!$E$16)) -> 54720 | R40: =+R12*(1+'.c12_inputs.hr'!$E$15)+(R26*(1+'.c12_inputs.hr'!$E$16)) -> 54720 | S40: =+S12*(1+'.c12_inputs.hr'!$E$15)+(S26*(1+'.c12_inputs.hr'!$E$16)) -> 111865 | ... W40: =+W12*(1+'.c12_inputs.hr'!$E$15)+(W26*(1+'.c12_inputs.hr'!$E$16)) -> 276025
A41: =+A13 -> Design Manager (AL) (gone) | B41: c | C41: total_salary | D41: al | I41: 63415 | J41: 39600 | L41: =+L13*(1+'.c12_inputs.hr'!$E$15)+(L27*(1+'.c12_inputs.hr'!$E$16)) -> 37440 | M41: =+M13*(1+'.c12_inputs.hr'!$E$15)+(M27*(1+'.c12_inputs.hr'!$E$16)) -> 37440 | N41: =+N13*(1+'.c12_inputs.hr'!$E$15)+(N27*(1+'.c12_inputs.hr'!$E$16)) -> 37440 | O41: =+O13*(1+'.c12_inputs.hr'!$E$15)+(O27*(1+'.c12_inputs.hr'!$E$16)) -> 63415 | P41: =+P13*(1+'.c12_inputs.hr'!$E$15)+(P27*(1+'.c12_inputs.hr'!$E$16)) -> 39600 | Q41: =+Q13*(1+'.c12_inputs.hr'!$E$15)+(Q27*(1+'.c12_inputs.hr'!$E$16)) -> 0 | R41: =+R13*(1+'.c12_inputs.hr'!$E$15)+(R27*(1+'.c12_inputs.hr'!$E$16)) -> 0 | S41: =+S13*(1+'.c12_inputs.hr'!$E$15)+(S27*(1+'.c12_inputs.hr'!$E$16)) -> 0 | ... W41: =+W13*(1+'.c12_inputs.hr'!$E$15)+(W27*(1+'.c12_inputs.hr'!$E$16)) -> 0
A42: =+A14 -> new design manager (TBD) | B42: c | C42: total_salary | D42: tbd | I42: 0 | J42: 0 | L42: =+L14*(1+'.c12_inputs.hr'!$E$15)+(L28*(1+'.c12_inputs.hr'!$E$16)) -> 0 | M42: =+M14*(1+'.c12_inputs.hr'!$E$15)+(M28*(1+'.c12_inputs.hr'!$E$16)) -> 0 | N42: =+N14*(1+'.c12_inputs.hr'!$E$15)+(N28*(1+'.c12_inputs.hr'!$E$16)) -> 0 | O42: =+O14*(1+'.c12_inputs.hr'!$E$15)+(O28*(1+'.c12_inputs.hr'!$E$16)) -> 0 | P42: =+P14*(1+'.c12_inputs.hr'!$E$15)+(P28*(1+'.c12_inputs.hr'!$E$16)) -> 0 | Q42: =+Q14*(1+'.c12_inputs.hr'!$E$15)+(Q28*(1+'.c12_inputs.hr'!$E$16)) -> 0 | R42: =+R14*(1+'.c12_inputs.hr'!$E$15)+(R28*(1+'.c12_inputs.hr'!$E$16)) -> 39600 | S42: =+S14*(1+'.c12_inputs.hr'!$E$15)+(S28*(1+'.c12_inputs.hr'!$E$16)) -> 51288.75 | ... W42: =+W14*(1+'.c12_inputs.hr'!$E$15)+(W28*(1+'.c12_inputs.hr'!$E$16)) -> 181777.5
A43: =+A15 -> FF&E (SB) | B43: c | C43: total_salary | D43: sb | I43: 31680 | J43: 31680 | L43: =+L15*(1+'.c12_inputs.hr'!$E$15)+(L29*(1+'.c12_inputs.hr'!$E$16)) -> 31680 | M43: =+M15*(1+'.c12_inputs.hr'!$E$15)+(M29*(1+'.c12_inputs.hr'!$E$16)) -> 31680 | N43: =+N15*(1+'.c12_inputs.hr'!$E$15)+(N29*(1+'.c12_inputs.hr'!$E$16)) -> 31680 | O43: =+O15*(1+'.c12_inputs.hr'!$E$15)+(O29*(1+'.c12_inputs.hr'!$E$16)) -> 31680 | P43: =+P15*(1+'.c12_inputs.hr'!$E$15)+(P29*(1+'.c12_inputs.hr'!$E$16)) -> 31680 | Q43: =+Q15*(1+'.c12_inputs.hr'!$E$15)+(Q29*(1+'.c12_inputs.hr'!$E$16)) -> 31680 | R43: =+R15*(1+'.c12_inputs.hr'!$E$15)+(R29*(1+'.c12_inputs.hr'!$E$16)) -> 31680 | S43: =+S15*(1+'.c12_inputs.hr'!$E$15)+(S29*(1+'.c12_inputs.hr'!$E$16)) -> 47265 | ... W43: =+W15*(1+'.c12_inputs.hr'!$E$15)+(W29*(1+'.c12_inputs.hr'!$E$16)) -> 142305
A44: =+A16 -> Senior Financial Analyst (KS) | B44: c | C44: total_salary | D44: ks | I44: 51950 | J44: 57600 | L44: =+L16*(1+'.c12_inputs.hr'!$E$15)+(L30*(1+'.c12_inputs.hr'!$E$16)) -> 0 | M44: =+M16*(1+'.c12_inputs.hr'!$E$15)+(M30*(1+'.c12_inputs.hr'!$E$16)) -> 0 | N44: =+N16*(1+'.c12_inputs.hr'!$E$15)+(N30*(1+'.c12_inputs.hr'!$E$16)) -> 0 | O44: =+O16*(1+'.c12_inputs.hr'!$E$15)+(O30*(1+'.c12_inputs.hr'!$E$16)) -> 51950 | P44: =+P16*(1+'.c12_inputs.hr'!$E$15)+(P30*(1+'.c12_inputs.hr'!$E$16)) -> 57600 | Q44: =+Q16*(1+'.c12_inputs.hr'!$E$15)+(Q30*(1+'.c12_inputs.hr'!$E$16)) -> 57600 | R44: =+R16*(1+'.c12_inputs.hr'!$E$15)+(R30*(1+'.c12_inputs.hr'!$E$16)) -> 57600 | S44: =+S16*(1+'.c12_inputs.hr'!$E$15)+(S30*(1+'.c12_inputs.hr'!$E$16)) -> 109550 | ... W44: =+W16*(1+'.c12_inputs.hr'!$E$15)+(W30*(1+'.c12_inputs.hr'!$E$16)) -> 282350
A45: Grand Total | B45: o | C45: hr_grand_total | I45: 1652177.5 | J45: 560160 | L45: =SUM(L34:L44) -> 515520 | M45: =SUM(M34:M44) -> 515520 | N45: =SUM(N34:N44) -> 515520 | O45: =SUM(O34:O44) -> 1652177.5 | P45: =SUM(P34:P44) -> 560160 | Q45: =SUM(Q34:Q44) -> 520560 | R45: =SUM(R34:R44) -> 560160 | S45: =SUM(S34:S44) -> 1221223.8 | ... W45: =SUM(W34:W44) -> 2809492.5
A46: reimbersable to hotel | B46: o | C46: hr_reimbursable | I46: 123922.5 | J46: 85680 | L46: =SUMPRODUCT('.c12_alloc'!$H$24:$H$34,'.c12_d&s_hr'!L$34:L$44) -> 84960 | M46: =SUMPRODUCT('.c12_alloc'!$H$24:$H$34,'.c12_d&s_hr'!M$34:M$44) -> 84960 | N46: =SUMPRODUCT('.c12_alloc'!$H$24:$H$34,'.c12_d&s_hr'!N$34:N$44) -> 84960 | O46: =SUMPRODUCT('.c12_alloc'!$H$24:$H$34,'.c12_d&s_hr'!O$34:O$44) -> 123922.5 | P46: =SUMPRODUCT('.c12_alloc'!$H$24:$H$34,'.c12_d&s_hr'!P$34:P$44) -> 85680 | Q46: =SUMPRODUCT('.c12_alloc'!$H$24:$H$34,'.c12_d&s_hr'!Q$34:Q$44) -> 85680 | R46: =SUMPRODUCT('.c12_alloc'!$H$24:$H$34,'.c12_d&s_hr'!R$34:R$44) -> 85680 | S46: =SUMPRODUCT('.c12_alloc'!$H$24:$H$34,'.c12_d&s_hr'!S$34:S$44) -> 116850 | ... W46: =SUMPRODUCT('.c12_alloc'!$H$24:$H$34,'.c12_d&s_hr'!W$34:W$44) -> 373890
A47: not reimbersable by hotel, but paid by lgh | B47: o | C47: hr_not_reimbursable | I47: 1528255 | J47: 474480 | L47: =SUMPRODUCT('.c12_alloc'!$G$24:$G$34,'.c12_d&s_hr'!L$34:L$44) -> 430560 | M47: =SUMPRODUCT('.c12_alloc'!$G$24:$G$34,'.c12_d&s_hr'!M$34:M$44) -> 430560 | N47: =SUMPRODUCT('.c12_alloc'!$G$24:$G$34,'.c12_d&s_hr'!N$34:N$44) -> 430560 | O47: =SUMPRODUCT('.c12_alloc'!$G$24:$G$34,'.c12_d&s_hr'!O$34:O$44) -> 1528255 | P47: =SUMPRODUCT('.c12_alloc'!$G$24:$G$34,'.c12_d&s_hr'!P$34:P$44) -> 474480 | Q47: =SUMPRODUCT('.c12_alloc'!$G$24:$G$34,'.c12_d&s_hr'!Q$34:Q$44) -> 434880 | R47: =SUMPRODUCT('.c12_alloc'!$G$24:$G$34,'.c12_d&s_hr'!R$34:R$44) -> 474480 | S47: =SUMPRODUCT('.c12_alloc'!$G$24:$G$34,'.c12_d&s_hr'!S$34:S$44) -> 1104373.8 | ... W47: =SUMPRODUCT('.c12_alloc'!$G$24:$G$34,'.c12_d&s_hr'!W$34:W$44) -> 2435602.5
A48: only paid by c12 | B48: o | C48: hr_only_c12 | I48: 0 | J48: 0 | L48: =SUMPRODUCT('.c12_alloc'!$E$24:$E$34,'.c12_d&s_hr'!L$34:L$44) -> 0 | M48: =SUMPRODUCT('.c12_alloc'!$E$24:$E$34,'.c12_d&s_hr'!M$34:M$44) -> 0 | N48: =SUMPRODUCT('.c12_alloc'!$E$24:$E$34,'.c12_d&s_hr'!N$34:N$44) -> 0 | O48: =SUMPRODUCT('.c12_alloc'!$E$24:$E$34,'.c12_d&s_hr'!O$34:O$44) -> 0 | P48: =SUMPRODUCT('.c12_alloc'!$E$24:$E$34,'.c12_d&s_hr'!P$34:P$44) -> 0 | Q48: =SUMPRODUCT('.c12_alloc'!$E$24:$E$34,'.c12_d&s_hr'!Q$34:Q$44) -> 0 | R48: =SUMPRODUCT('.c12_alloc'!$E$24:$E$34,'.c12_d&s_hr'!R$34:R$44) -> 0 | S48: =SUMPRODUCT('.c12_alloc'!$E$24:$E$34,'.c12_d&s_hr'!S$34:S$44) -> 0 | ... W48: =SUMPRODUCT('.c12_alloc'!$E$24:$E$34,'.c12_d&s_hr'!W$34:W$44) -> 0

Sheet .c12_bi&f_hr
A2: Year | E2: 45657 | F2: 45747 | G2: 45838 | H2: 45930 | I2: 46022 | J2: 46112 | K2: 46203 | L2: 45747 | M2: 45838 | N2: 45930 | O2: 46022 | P2: 46112 | Q2: 46203 | R2: 46295 | S2: 46387 | T2: 46752 | U2: 47118 | V2: 47483 | W2: 47848
E3: actual | L3: i/o
B4: i/o | C4: field_name | D4: index
A5: base
A6: HOBI (CW) | B6: i | C6: base_salary | D6: cw | I6: 93750 | J6: 93750 | L6: 93750 | M6: 93750 | N6: 93750 | O6: 93750 | P6: 93750 | Q6: 93750 | R6: 93750 | S6: 93750 | T6: 375000 | U6: 375000 | V6: 375000 | W6: 375000
A7: CFO (ZS) | B7: i | C7: base_salary | D7: zs | I7: 0 | J7: 0 | L7: 0 | M7: 0 | N7: 0 | O7: 0 | P7: 0 | Q7: 125000 | R7: 125000 | S7: 125000 | T7: 375000 | U7: 375000 | V7: 375000 | W7: 375000
A8: Financial Analyst (NR) | B8: i | C8: base_salary | D8: nr | I8: 21250 | J8: 21250 | L8: 0 | M8: 0 | N8: 21250 | O8: 21250 | P8: 21250 | Q8: 21250 | R8: 21250 | S8: 21250 | T8: 85000 | U8: 85000 | V8: 85000 | W8: 85000
A9: Fin Controls (TB) - 100% | B9: i | C9: base_salary | D9: tb | I9: 46250 | J9: 48750 | L9: 46250 | M9: 46250 | N9: 46250 | O9: 46250 | P9: 48750 | Q9: 48750 | R9: 48750 | S9: 48750 | T9: 195000 | U9: 195000 | V9: 195000 | W9: 195000
A10: Administrative Assistant (AM) | B10: i | C10: base_salary | D10: am | I10: 31250 | J10: 0 | L10: 37500 | M10: 37500 | N10: 37500 | O10: 31250 | P10: 0 | Q10: 0 | R10: 0 | S10: 0 | T10: 0 | U10: 0 | V10: 0 | W10: 0
A11: Administrative Assistant (PT) | B11: i | C11: base_salary | D11: pt | I11: 0 | J11: 0 | L11: 0 | M11: 0 | N11: 0 | O11: 0 | P11: 0 | Q11: 36250 | R11: 36250 | S11: 36250 | T11: 145000 | U11: 145000 | V11: 145000 | W11: 145000
A12: Financial Director (DV) - 100% | B12: i | C12: base_salary | D12: dv | I12: 53750 | J12: 53750 | L12: 0 | M12: 0 | N12: 53750 | O12: 53750 | P12: 53750 | Q12: 53750 | R12: 53750 | S12: 53750 | T12: 215000 | U12: 215000 | V12: 215000 | W12: 215000
A13: IM (TW) | B13: i | C13: base_salary | D13: tw | I13: 40000 | J13: 40000 | L13: 40000 | M13: 40000 | N13: 40000 | O13: 40000 | P13: 40000 | Q13: 40000 | R13: 40000 | S13: 40000 | T13: 200000 | U13: 200000 | V13: 200000 | W13: 200000
A14: HR (100%) | B14: i | C14: base_salary | D14: hr | I14: 0 | J14: 0 | L14: 0 | M14: 0 | N14: 0 | O14: 0 | P14: 0 | Q14: 0 | R14: 37500 | S14: 37500 | T14: 150000 | U14: 150000 | V14: 150000 | W14: 150000
A15: Legal (100%) | B15: i | C15: base_salary | D15: legal | I15: 0 | J15: 0 | L15: 0 | M15: 0 | N15: 0 | O15: 0 | P15: 0 | Q15: 0 | R15: 56250 | S15: 56250 | T15: 225000 | U15: 225000 | V15: 225000 | W15: 225000
A16: Tech1 | B16: i | C16: base_salary | D16: tech1 | I16: 0 | J16: 0 | L16: 0 | M16: 0 | N16: 0 | O16: 0 | P16: 0 | Q16: 0 | R16: 56250 | S16: 56250 | T16: 225000 | U16: 225000 | V16: 225000 | W16: 225000
A17: Tech2 | B17: i | C17: base_salary | D17: tech2 | I17: 0 | J17: 0 | L17: 0 | M17: 0 | N17: 0 | O17: 0 | P17: 0 | Q17: 0 | R17: 18750 | S17: 18750 | T17: 75000 | U17: 75000 | V17: 75000 | W17: 75000
A18: Total | I18: 286250 | J18: 257500 | L18: =SUM(L6:L17) -> 217500 | M18: =SUM(M6:M17) -> 217500 | N18: =SUM(N6:N17) -> 292500 | O18: =SUM(O6:O17) -> 286250 | P18: =SUM(P6:P17) -> 257500 | Q18: =SUM(Q6:Q17) -> 418750 | R18: =SUM(R6:R17) -> 587500 | S18: =SUM(S6:S17) -> 587500 | ... W18: =SUM(W6:W17) -> 2265000
A20: Bonus
A21: =+A6 -> HOBI (CW) | B21: i | C21: bonus | D21: cw | I21: 125000 | J21: 0 | L21: 0 | M21: 0 | N21: 0 | O21: 125000 | P21: 0 | Q21: 0 | R21: 0 | S21: 225000 | T21: 325000 | U21: 325000 | V21: 325000 | W21: 325000
A22: =+A7 -> CFO (ZS) | B22: i | C22: bonus | D22: zs | I22: 60000 | J22: 0 | L22: 0 | M22: 0 | N22: 0 | O22: 60000 | P22: 0 | Q22: 0 | R22: 0 | S22: 100000 | T22: 150000 | U22: 150000 | V22: 150000 | W22: 150000
A23: =+A8 -> Financial Analyst (NR) | B23: i | C23: bonus | D23: nr | I23: 5000 | J23: 0 | L23: 0 | M23: 0 | N23: 0 | O23: 5000 | P23: 0 | Q23: 0 | R23: 0 | S23: 7500 | T23: 7500 | U23: 7500 | V23: 7500 | W23: 7500
A24: =+A9 -> Fin Controls (TB) - 100% | B24: i | C24: bonus | D24: tb | I24: 17500 | J24: 0 | L24: 0 | M24: 0 | N24: 0 | O24: 17500 | P24: 0 | Q24: 0 | R24: 0 | S24: 15000 | T24: 15000 | U24: 15000 | V24: 15000 | W24: 15000
A25: =+A10 -> Administrative Assistant (AM) | B25: i | C25: bonus | D25: am | I25: 10000 | J25: 0 | L25: 0 | M25: 0 | N25: 0 | O25: 10000 | P25: 0 | Q25: 0 | R25: 0 | S25: 0 | T25: 0 | U25: 0 | V25: 0 | W25: 0
A26: =+A11 -> Administrative Assistant (PT) | B26: i | C26: bonus | D26: pt | I26: 0 | J26: 0 | L26: 0 | M26: 0 | N26: 0 | O26: 0 | P26: 0 | Q26: 0 | R26: 0 | S26: 10000 | T26: 10000 | U26: 10000 | V26: 10000 | W26: 10000
A27: =+A12 -> Financial Director (DV) - 100% | B27: i | C27: bonus | D27: dv | I27: 20000 | J27: 0 | L27: 0 | M27: 0 | N27: 0 | O27: 20000 | P27: 0 | Q27: 0 | R27: 0 | S27: 40000 | T27: 40000 | U27: 40000 | V27: 40000 | W27: 40000
A28: =+A13 -> IM (TW) | B28: i | C28: bonus | D28: tw | I28: 25000 | J28: 0 | L28: 0 | M28: 0 | N28: 0 | O28: 25000 | P28: 0 | Q28: 0 | R28: 0 | S28: 25000 | T28: 25000 | U28: 25000 | V28: 25000 | W28: 25000
A29: =+A14 -> HR (100%) | B29: i | C29: bonus | D29: hr | I29: 0 | J29: 0 | L29: 0 | M29: 0 | N29: 0 | O29: 0 | P29: 0 | Q29: 0 | R29: 0 | S29: 15000 | T29: 25000 | U29: 25000 | V29: 25000 | W29: 25000
A30: =+A15 -> Legal (100%) | B30: i | C30: bonus | D30: legal | I30: 0 | J30: 0 | L30: 0 | M30: 0 | N30: 0 | O30: 0 | P30: 0 | Q30: 0 | R30: 0 | S30: 15000 | T30: 25000 | U30: 25000 | V30: 25000 | W30: 25000
A31: =+A16 -> Tech1 | B31: i | C31: bonus | D31: tech1 | I31: 0 | J31: 0 | L31: 0 | M31: 0 | N31: 0 | O31: 0 | P31: 0 | Q31: 0 | R31: 0 | S31: 15000 | T31: 25000 | U31: 25000 | V31: 25000 | W31: 25000
A32: =+A17 -> Tech2 | B32: i | C32: bonus | D32: tech2 | I32: 0 | J32: 0 | L32: 0 | M32: 0 | N32: 0 | O32: 0 | P32: 0 | Q32: 0 | R32: 0 | S32: 15000 | T32: 25000 | U32: 25000 | V32: 25000 | W32: 25000
A33: Total | I33: 262500 | J33: 0 | L33: =SUM(L21:L32) -> 0 | M33: =SUM(M21:M32) -> 0 | N33: =SUM(N21:N32) -> 0 | O33: =SUM(O21:O32) -> 262500 | P33: =SUM(P21:P32) -> 0 | Q33: =SUM(Q21:Q32) -> 0 | R33: =SUM(R21:R32) -> 0 | S33: =SUM(S21:S32) -> 482500 | ... W33: =SUM(W21:W32) -> 672500
A35: Total Salaries
A36: =+A6 -> HOBI (CW) | B36: c | C36: total_salary | D36: cw | I36: 237875 | J36: 108000 | L36: =+L6*(1+'.c12_inputs.hr'!$E$15)+(L21*(1+'.c12_inputs.hr'!$E$16)) -> 108000 | M36: =+M6*(1+'.c12_inputs.hr'!$E$15)+(M21*(1+'.c12_inputs.hr'!$E$16)) -> 108000 | N36: =+N6*(1+'.c12_inputs.hr'!$E$15)+(N21*(1+'.c12_inputs.hr'!$E$16)) -> 108000 | O36: =+O6*(1+'.c12_inputs.hr'!$E$15)+(O21*(1+'.c12_inputs.hr'!$E$16)) -> 237875 | P36: =+P6*(1+'.c12_inputs.hr'!$E$15)+(P21*(1+'.c12_inputs.hr'!$E$16)) -> 108000 | Q36: =+Q6*(1+'.c12_inputs.hr'!$E$15)+(Q21*(1+'.c12_inputs.hr'!$E$16)) -> 108000 | R36: =+R6*(1+'.c12_inputs.hr'!$E$15)+(R21*(1+'.c12_inputs.hr'!$E$16)) -> 108000 | S36: =+S6*(1+'.c12_inputs.hr'!$E$15)+(S21*(1+'.c12_inputs.hr'!$E$16)) -> 341775 | ... W36: =+W6*(1+'.c12_inputs.hr'!$E$15)+(W21*(1+'.c12_inputs.hr'!$E$16)) -> 769675
A37: =+A7 -> CFO (ZS) | B37: c | C37: total_salary | D37: zs | I37: 62340 | J37: 0 | L37: =+L7*(1+'.c12_inputs.hr'!$E$15)+(L22*(1+'.c12_inputs.hr'!$E$16)) -> 0 | M37: =+M7*(1+'.c12_inputs.hr'!$E$15)+(M22*(1+'.c12_inputs.hr'!$E$16)) -> 0 | N37: =+N7*(1+'.c12_inputs.hr'!$E$15)+(N22*(1+'.c12_inputs.hr'!$E$16)) -> 0 | O37: =+O7*(1+'.c12_inputs.hr'!$E$15)+(O22*(1+'.c12_inputs.hr'!$E$16)) -> 62340 | P37: =+P7*(1+'.c12_inputs.hr'!$E$15)+(P22*(1+'.c12_inputs.hr'!$E$16)) -> 0 | Q37: =+Q7*(1+'.c12_inputs.hr'!$E$15)+(Q22*(1+'.c12_inputs.hr'!$E$16)) -> 144000 | R37: =+R7*(1+'.c12_inputs.hr'!$E$15)+(R22*(1+'.c12_inputs.hr'!$E$16)) -> 144000 | S37: =+S7*(1+'.c12_inputs.hr'!$E$15)+(S22*(1+'.c12_inputs.hr'!$E$16)) -> 247900 | ... W37: =+W7*(1+'.c12_inputs.hr'!$E$15)+(W22*(1+'.c12_inputs.hr'!$E$16)) -> 587850
A38: =+A8 -> Financial Analyst (NR) | B38: c | C38: total_salary | D38: nr | I38: 29675 | J38: 24480 | L38: =+L8*(1+'.c12_inputs.hr'!$E$15)+(L23*(1+'.c12_inputs.hr'!$E$16)) -> 0 | M38: =+M8*(1+'.c12_inputs.hr'!$E$15)+(M23*(1+'.c12_inputs.hr'!$E$16)) -> 0 | N38: =+N8*(1+'.c12_inputs.hr'!$E$15)+(N23*(1+'.c12_inputs.hr'!$E$16)) -> 24480 | O38: =+O8*(1+'.c12_inputs.hr'!$E$15)+(O23*(1+'.c12_inputs.hr'!$E$16)) -> 29675 | P38: =+P8*(1+'.c12_inputs.hr'!$E$15)+(P23*(1+'.c12_inputs.hr'!$E$16)) -> 24480 | Q38: =+Q8*(1+'.c12_inputs.hr'!$E$15)+(Q23*(1+'.c12_inputs.hr'!$E$16)) -> 24480 | R38: =+R8*(1+'.c12_inputs.hr'!$E$15)+(R23*(1+'.c12_inputs.hr'!$E$16)) -> 24480 | S38: =+S8*(1+'.c12_inputs.hr'!$E$15)+(S23*(1+'.c12_inputs.hr'!$E$16)) -> 32272.5 | ... W38: =+W8*(1+'.c12_inputs.hr'!$E$15)+(W23*(1+'.c12_inputs.hr'!$E$16)) -> 105712.5
A39: =+A9 -> Fin Controls (TB) - 100% | B39: c | C39: total_salary | D39: tb | I39: 71462.5 | J39: 56160 | L39: =+L9*(1+'.c12_inputs.hr'!$E$15)+(L24*(1+'.c12_inputs.hr'!$E$16)) -> 53280 | M39: =+M9*(1+'.c12_inputs.hr'!$E$15)+(M24*(1+'.c12_inputs.hr'!$E$16)) -> 53280 | N39: =+N9*(1+'.c12_inputs.hr'!$E$15)+(N24*(1+'.c12_inputs.hr'!$E$16)) -> 53280 | O39: =+O9*(1+'.c12_inputs.hr'!$E$15)+(O24*(1+'.c12_inputs.hr'!$E$16)) -> 71462.5 | P39: =+P9*(1+'.c12_inputs.hr'!$E$15)+(P24*(1+'.c12_inputs.hr'!$E$16)) -> 56160 | Q39: =+Q9*(1+'.c12_inputs.hr'!$E$15)+(Q24*(1+'.c12_inputs.hr'!$E$16)) -> 56160 | R39: =+R9*(1+'.c12_inputs.hr'!$E$15)+(R24*(1+'.c12_inputs.hr'!$E$16)) -> 56160 | S39: =+S9*(1+'.c12_inputs.hr'!$E$15)+(S24*(1+'.c12_inputs.hr'!$E$16)) -> 71745 | ... W39: =+W9*(1+'.c12_inputs.hr'!$E$15)+(W24*(1+'.c12_inputs.hr'!$E$16)) -> 240225
A40: =+A10 -> Administrative Assistant (AM) | B40: c | C40: total_salary | D40: am | I40: 46390 | J40: 0 | L40: =+L10*(1+'.c12_inputs.hr'!$E$15)+(L25*(1+'.c12_inputs.hr'!$E$16)) -> 43200 | M40: =+M10*(1+'.c12_inputs.hr'!$E$15)+(M25*(1+'.c12_inputs.hr'!$E$16)) -> 43200 | N40: =+N10*(1+'.c12_inputs.hr'!$E$15)+(N25*(1+'.c12_inputs.hr'!$E$16)) -> 43200 | O40: =+O10*(1+'.c12_inputs.hr'!$E$15)+(O25*(1+'.c12_inputs.hr'!$E$16)) -> 46390 | P40: =+P10*(1+'.c12_inputs.hr'!$E$15)+(P25*(1+'.c12_inputs.hr'!$E$16)) -> 0 | Q40: =+Q10*(1+'.c12_inputs.hr'!$E$15)+(Q25*(1+'.c12_inputs.hr'!$E$16)) -> 0 | R40: =+R10*(1+'.c12_inputs.hr'!$E$15)+(R25*(1+'.c12_inputs.hr'!$E$16)) -> 0 | S40: =+S10*(1+'.c12_inputs.hr'!$E$15)+(S25*(1+'.c12_inputs.hr'!$E$16)) -> 0 | ... W40: =+W10*(1+'.c12_inputs.hr'!$E$15)+(W25*(1+'.c12_inputs.hr'!$E$16)) -> 0
A41: =+A11 -> Administrative Assistant (PT) | B41: c | C41: total_salary | D41: pt | I41: 0 | J41: 0 | L41: ='.c12_bi&f_hr'!L11*(1+'.c12_inputs.hr'!$E$5)+('.c12_bi&f_hr'!L26*(1+'.c12_inputs.hr'!$E$6)) -> 0 | M41: ='.c12_bi&f_hr'!M11*(1+'.c12_inputs.hr'!$E$5)+('.c12_bi&f_hr'!M26*(1+'.c12_inputs.hr'!$E$6)) -> 0 | N41: ='.c12_bi&f_hr'!N11*(1+'.c12_inputs.hr'!$E$5)+('.c12_bi&f_hr'!N26*(1+'.c12_inputs.hr'!$E$6)) -> 0 | O41: ='.c12_bi&f_hr'!O11*(1+'.c12_inputs.hr'!$E$5)+('.c12_bi&f_hr'!O26*(1+'.c12_inputs.hr'!$E$6)) -> 0 | P41: ='.c12_bi&f_hr'!P11*(1+'.c12_inputs.hr'!$E$5)+('.c12_bi&f_hr'!P26*(1+'.c12_inputs.hr'!$E$6)) -> 0 | Q41: ='.c12_bi&f_hr'!Q11*(1+'.c12_inputs.hr'!$E$5)+('.c12_bi&f_hr'!Q26*(1+'.c12_inputs.hr'!$E$6)) -> 37037.143 | R41: ='.c12_bi&f_hr'!R11*(1+'.c12_inputs.hr'!$E$5)+('.c12_bi&f_hr'!R26*(1+'.c12_inputs.hr'!$E$6)) -> 37037.143 | S41: ='.c12_bi&f_hr'!S11*(1+'.c12_inputs.hr'!$E$5)+('.c12_bi&f_hr'!S26*(1+'.c12_inputs.hr'!$E$6)) -> 47427.143 | ... W41: ='.c12_bi&f_hr'!W11*(1+'.c12_inputs.hr'!$E$5)+('.c12_bi&f_hr'!W26*(1+'.c12_inputs.hr'!$E$6)) -> 158538.57
A42: =+A12 -> Financial Director (DV) - 100% | B42: c | C42: total_salary | D42: dv | I42: 82700 | J42: 61920 | L42: =+L12*(1+'.c12_inputs.hr'!$E$15)+(L27*(1+'.c12_inputs.hr'!$E$16)) -> 0 | M42: =+M12*(1+'.c12_inputs.hr'!$E$15)+(M27*(1+'.c12_inputs.hr'!$E$16)) -> 0 | N42: =+N12*(1+'.c12_inputs.hr'!$E$15)+(N27*(1+'.c12_inputs.hr'!$E$16)) -> 61920 | O42: =+O12*(1+'.c12_inputs.hr'!$E$15)+(O27*(1+'.c12_inputs.hr'!$E$16)) -> 82700 | P42: =+P12*(1+'.c12_inputs.hr'!$E$15)+(P27*(1+'.c12_inputs.hr'!$E$16)) -> 61920 | Q42: =+Q12*(1+'.c12_inputs.hr'!$E$15)+(Q27*(1+'.c12_inputs.hr'!$E$16)) -> 61920 | R42: =+R12*(1+'.c12_inputs.hr'!$E$15)+(R27*(1+'.c12_inputs.hr'!$E$16)) -> 61920 | S42: =+S12*(1+'.c12_inputs.hr'!$E$15)+(S27*(1+'.c12_inputs.hr'!$E$16)) -> 103480 | ... W42: =+W12*(1+'.c12_inputs.hr'!$E$15)+(W27*(1+'.c12_inputs.hr'!$E$16)) -> 289240
A43: =+A13 -> IM (TW) | B43: c | C43: total_salary | D43: tw | I43: 72055 | J43: 46080 | L43: =+L13*(1+'.c12_inputs.hr'!$E$15)+(L28*(1+'.c12_inputs.hr'!$E$16)) -> 46080 | M43: =+M13*(1+'.c12_inputs.hr'!$E$15)+(M28*(1+'.c12_inputs.hr'!$E$16)) -> 46080 | N43: =+N13*(1+'.c12_inputs.hr'!$E$15)+(N28*(1+'.c12_inputs.hr'!$E$16)) -> 46080 | O43: =+O13*(1+'.c12_inputs.hr'!$E$15)+(O28*(1+'.c12_inputs.hr'!$E$16)) -> 72055 | P43: =+P13*(1+'.c12_inputs.hr'!$E$15)+(P28*(1+'.c12_inputs.hr'!$E$16)) -> 46080 | Q43: =+Q13*(1+'.c12_inputs.hr'!$E$15)+(Q28*(1+'.c12_inputs.hr'!$E$16)) -> 46080 | R43: =+R13*(1+'.c12_inputs.hr'!$E$15)+(R28*(1+'.c12_inputs.hr'!$E$16)) -> 46080 | S43: =+S13*(1+'.c12_inputs.hr'!$E$15)+(S28*(1+'.c12_inputs.hr'!$E$16)) -> 72055 | ... W43: =+W13*(1+'.c12_inputs.hr'!$E$15)+(W28*(1+'.c12_inputs.hr'!$E$16)) -> 256375
A44: =+A14 -> HR (100%) | B44: c | C44: total_salary | D44: hr | I44: 0 | J44: 0 | L44: =+L14*(1+'.c12_inputs.hr'!$E$15)+(L29*(1+'.c12_inputs.hr'!$E$16)) -> 0 | M44: =+M14*(1+'.c12_inputs.hr'!$E$15)+(M29*(1+'.c12_inputs.hr'!$E$16)) -> 0 | N44: =+N14*(1+'.c12_inputs.hr'!$E$15)+(N29*(1+'.c12_inputs.hr'!$E$16)) -> 0 | O44: =+O14*(1+'.c12_inputs.hr'!$E$15)+(O29*(1+'.c12_inputs.hr'!$E$16)) -> 0 | P44: =+P14*(1+'.c12_inputs.hr'!$E$15)+(P29*(1+'.c12_inputs.hr'!$E$16)) -> 0 | Q44: =+Q14*(1+'.c12_inputs.hr'!$E$15)+(Q29*(1+'.c12_inputs.hr'!$E$16)) -> 0 | R44: =+R14*(1+'.c12_inputs.hr'!$E$15)+(R29*(1+'.c12_inputs.hr'!$E$16)) -> 43200 | S44: =+S14*(1+'.c12_inputs.hr'!$E$15)+(S29*(1+'.c12_inputs.hr'!$E$16)) -> 58785 | ... W44: =+W14*(1+'.c12_inputs.hr'!$E$15)+(W29*(1+'.c12_inputs.hr'!$E$16)) -> 198775
A45: =+A15 -> Legal (100%) | B45: c | C45: total_salary | D45: legal | I45: 0 | J45: 0 | L45: =+L15*(1+'.c12_inputs.hr'!$E$15)+(L30*(1+'.c12_inputs.hr'!$E$16)) -> 0 | M45: =+M15*(1+'.c12_inputs.hr'!$E$15)+(M30*(1+'.c12_inputs.hr'!$E$16)) -> 0 | N45: =+N15*(1+'.c12_inputs.hr'!$E$15)+(N30*(1+'.c12_inputs.hr'!$E$16)) -> 0 | O45: =+O15*(1+'.c12_inputs.hr'!$E$15)+(O30*(1+'.c12_inputs.hr'!$E$16)) -> 0 | P45: =+P15*(1+'.c12_inputs.hr'!$E$15)+(P30*(1+'.c12_inputs.hr'!$E$16)) -> 0 | Q45: =+Q15*(1+'.c12_inputs.hr'!$E$15)+(Q30*(1+'.c12_inputs.hr'!$E$16)) -> 0 | R45: =+R15*(1+'.c12_inputs.hr'!$E$15)+(R30*(1+'.c12_inputs.hr'!$E$16)) -> 64800 | S45: =+S15*(1+'.c12_inputs.hr'!$E$15)+(S30*(1+'.c12_inputs.hr'!$E$16)) -> 80385 | ... W45: =+W15*(1+'.c12_inputs.hr'!$E$15)+(W30*(1+'.c12_inputs.hr'!$E$16)) -> 285175
A46: =+A16 -> Tech1 | B46: c | C46: total_salary | D46: tech1 | I46: 0 | J46: 0 | L46: =+L16*(1+'.c12_inputs.hr'!$E$15)+(L31*(1+'.c12_inputs.hr'!$E$16)) -> 0 | M46: =+M16*(1+'.c12_inputs.hr'!$E$15)+(M31*(1+'.c12_inputs.hr'!$E$16)) -> 0 | N46: =+N16*(1+'.c12_inputs.hr'!$E$15)+(N31*(1+'.c12_inputs.hr'!$E$16)) -> 0 | O46: =+O16*(1+'.c12_inputs.hr'!$E$15)+(O31*(1+'.c12_inputs.hr'!$E$16)) -> 0 | P46: =+P16*(1+'.c12_inputs.hr'!$E$15)+(P31*(1+'.c12_inputs.hr'!$E$16)) -> 0 | Q46: =+Q16*(1+'.c12_inputs.hr'!$E$15)+(Q31*(1+'.c12_inputs.hr'!$E$16)) -> 0 | R46: =+R16*(1+'.c12_inputs.hr'!$E$15)+(R31*(1+'.c12_inputs.hr'!$E$16)) -> 64800 | S46: =+S16*(1+'.c12_inputs.hr'!$E$15)+(S31*(1+'.c12_inputs.hr'!$E$16)) -> 80385 | ... W46: =+W16*(1+'.c12_inputs.hr'!$E$15)+(W31*(1+'.c12_inputs.hr'!$E$16)) -> 285175
A47: =+A17 -> Tech2 | B47: c | C47: total_salary | D47: tech2 | I47: 0 | J47: 0 | L47: =+L17*(1+'.c12_inputs.hr'!$E$15)+(L32*(1+'.c12_inputs.hr'!$E$16)) -> 0 | M47: =+M17*(1+'.c12_inputs.hr'!$E$15)+(M32*(1+'.c12_inputs.hr'!$E$16)) -> 0 | N47: =+N17*(1+'.c12_inputs.hr'!$E$15)+(N32*(1+'.c12_inputs.hr'!$E$16)) -> 0 | O47: =+O17*(1+'.c12_inputs.hr'!$E$15)+(O32*(1+'.c12_inputs.hr'!$E$16)) -> 0 | P47: =+P17*(1+'.c12_inputs.hr'!$E$15)+(P32*(1+'.c12_inputs.hr'!$E$16)) -> 0 | Q47: =+Q17*(1+'.c12_inputs.hr'!$E$15)+(Q32*(1+'.c12_inputs.hr'!$E$16)) -> 0 | R47: =+R17*(1+'.c12_inputs.hr'!$E$15)+(R32*(1+'.c12_inputs.hr'!$E$16)) -> 21600 | S47: =+S17*(1+'.c12_inputs.hr'!$E$15)+(S32*(1+'.c12_inputs.hr'!$E$16)) -> 37185 | ... W47: =+W17*(1+'.c12_inputs.hr'!$E$15)+(W32*(1+'.c12_inputs.hr'!$E$16)) -> 112375
A48: Grand Total | B48: o | C48: hr_grand_total | I48: 602497.5 | J48: 296640 | L48: =SUM(L36:L47) -> 250560 | M48: =SUM(M36:M47) -> 250560 | N48: =SUM(N36:N47) -> 336960 | O48: =SUM(O36:O47) -> 602497.5 | P48: =SUM(P36:P47) -> 296640 | Q48: =SUM(Q36:Q47) -> 477677.14 | R48: =SUM(R36:R47) -> 672077.14 | S48: =SUM(S36:S47) -> 1173394.6 | ... W48: =SUM(W36:W47) -> 3289116.1
A49: reimbersable to hotel | B49: o | C49: hr_reimbursable | I49: 154162.5 | J49: 118080 | L49: =SUMPRODUCT('.c12_alloc'!$H$38:$H$49,'.c12_bi&f_hr'!L$36:L$47) -> 53280 | M49: =SUMPRODUCT('.c12_alloc'!$H$38:$H$49,'.c12_bi&f_hr'!M$36:M$47) -> 53280 | N49: =SUMPRODUCT('.c12_alloc'!$H$38:$H$49,'.c12_bi&f_hr'!N$36:N$47) -> 115200 | O49: =SUMPRODUCT('.c12_alloc'!$H$38:$H$49,'.c12_bi&f_hr'!O$36:O$47) -> 154162.5 | P49: =SUMPRODUCT('.c12_alloc'!$H$38:$H$49,'.c12_bi&f_hr'!P$36:P$47) -> 118080 | Q49: =SUMPRODUCT('.c12_alloc'!$H$38:$H$49,'.c12_bi&f_hr'!Q$36:Q$47) -> 118080 | R49: =SUMPRODUCT('.c12_alloc'!$H$38:$H$49,'.c12_bi&f_hr'!R$36:R$47) -> 226080 | S49: =SUMPRODUCT('.c12_alloc'!$H$38:$H$49,'.c12_bi&f_hr'!S$36:S$47) -> 314395 | ... W49: =SUMPRODUCT('.c12_alloc'!$H$38:$H$49,'.c12_bi&f_hr'!W$36:W$47) -> 1013415
A50: not reimbersable by hotel, but paid by lgh | B50: o | C50: hr_not_reimbursable | I50: 448335 | J50: 178560 | L50: =SUMPRODUCT('.c12_alloc'!$G$38:$G$49,'.c12_bi&f_hr'!L$36:L$47) -> 197280 | M50: =SUMPRODUCT('.c12_alloc'!$G$38:$G$49,'.c12_bi&f_hr'!M$36:M$47) -> 197280 | N50: =SUMPRODUCT('.c12_alloc'!$G$38:$G$49,'.c12_bi&f_hr'!N$36:N$47) -> 221760 | O50: =SUMPRODUCT('.c12_alloc'!$G$38:$G$49,'.c12_bi&f_hr'!O$36:O$47) -> 448335 | P50: =SUMPRODUCT('.c12_alloc'!$G$38:$G$49,'.c12_bi&f_hr'!P$36:P$47) -> 178560 | Q50: =SUMPRODUCT('.c12_alloc'!$G$38:$G$49,'.c12_bi&f_hr'!Q$36:Q$47) -> 359597.14 | R50: =SUMPRODUCT('.c12_alloc'!$G$38:$G$49,'.c12_bi&f_hr'!R$36:R$47) -> 445997.14 | S50: =SUMPRODUCT('.c12_alloc'!$G$38:$G$49,'.c12_bi&f_hr'!S$36:S$47) -> 858999.64 | ... W50: =SUMPRODUCT('.c12_alloc'!$G$38:$G$49,'.c12_bi&f_hr'!W$36:W$47) -> 2275701.1
A51: only paid by c12 | B51: o | C51: hr_only_c12 | I51: 0 | J51: 0 | L51: =SUMPRODUCT('.c12_alloc'!$E$38:$E$49,'.c12_bi&f_hr'!L$36:L$47) -> 0 | M51: =SUMPRODUCT('.c12_alloc'!$E$38:$E$49,'.c12_bi&f_hr'!M$36:M$47) -> 0 | N51: =SUMPRODUCT('.c12_alloc'!$E$38:$E$49,'.c12_bi&f_hr'!N$36:N$47) -> 0 | O51: =SUMPRODUCT('.c12_alloc'!$E$38:$E$49,'.c12_bi&f_hr'!O$36:O$47) -> 0 | P51: =SUMPRODUCT('.c12_alloc'!$E$38:$E$49,'.c12_bi&f_hr'!P$36:P$47) -> 0 | Q51: =SUMPRODUCT('.c12_alloc'!$E$38:$E$49,'.c12_bi&f_hr'!Q$36:Q$47) -> 0 | R51: =SUMPRODUCT('.c12_alloc'!$E$38:$E$49,'.c12_bi&f_hr'!R$36:R$47) -> 0 | S51: =SUMPRODUCT('.c12_alloc'!$E$38:$E$49,'.c12_bi&f_hr'!S$36:S$47) -> 0 | ... W51: =SUMPRODUCT('.c12_alloc'!$E$38:$E$49,'.c12_bi&f_hr'!W$36:W$47) -> 0

Sheet .c12_alloc
B3: i/o | C3: field_name | D3: index
A4: CY Project Time Allocation
A5: HO | E5: unalloc | F5: alloc | G5: lgh | H5: reimb | I5: BDA | J5: Aus | K5: Turks | L5: ELBOW | M5: sat | N5: Frith | O5: ROOTS | P5: FO
A6: Managing Member (SK) | B6: i | C6: time_alloc | D6: hm_sk | E6: =1-F6 -> 0 | F6: =G6+H6 -> 1 | G6: =1-H6-P6 -> 1 | H6: =+SUM(I6:O6) -> 0 | I6: 0 | J6: 0 | K6: 0 | L6: 0 | M6: 0 | N6: 0 | O6: 0 | P6: 0
A7: Philanropy senior exec (LM) (100%roots) | B7: i | C7: time_alloc | D7: hm_lm | E7: =1-F7 -> 0 | F7: =G7+H7 -> 1 | G7: =1-H7-P7 -> 0 | H7: =+SUM(I7:O7) -> 1 | I7: 0 | J7: 0 | K7: 0 | L7: 0 | M7: 0 | N7: 0 | O7: 1 | P7: 0
A8: Bookkeeper (DD) | B8: i | C8: time_alloc | D8: hm_dd | E8: =1-F8 -> 1 | F8: =G8+H8 -> 0 | G8: =1-H8-P8 -> 0 | H8: =+SUM(I8:O8) -> 0 | I8: 0 | J8: 0 | K8: 0 | L8: 0 | M8: 0 | N8: 0 | O8: 0 | P8: 1
A9: Personal Assistant (CD) | B9: i | C9: time_alloc | D9: hm_cd | E9: =1-F9 -> 1 | F9: =G9+H9 -> 0 | G9: =1-H9-P9 -> 0 | H9: =+SUM(I9:O9) -> 0 | I9: 0 | J9: 0 | K9: 0 | L9: 0 | M9: 0 | N9: 0 | O9: 0 | P9: 1
A10: philanthropy assist (100%roots) | B10: i | C10: time_alloc | D10: hm_philanthropy | E10: =1-F10 -> 0 | F10: =G10+H10 -> 1 | G10: =1-H10-P10 -> 0 | H10: =+SUM(I10:O10) -> 1 | I10: 0 | J10: 0 | K10: 0 | L10: 0 | M10: 0 | N10: 0 | O10: 1 | P10: 0
A11: TM (gone) | B11: i | C11: time_alloc | D11: hm_tm | E11: =1-F11 -> 0 | F11: =G11+H11 -> 1 | G11: =1-H11-P11 -> 1 | H11: =+SUM(I11:O11) -> 0 | I11: 0 | J11: 0 | K11: 0 | L11: 0 | M11: 0 | N11: 0 | O11: 0 | P11: 0
A13: CY Project Time Allocation
A14: Hotel Management | E14: unalloc | F14: alloc | G14: lgh | H14: reimb | I14: BDA | J14: Aus | K14: Turks | L14: ELBOW | M14: sat | N14: Frith | O14: ROOTS | P14: FO
A15: ACEO Loren Hotels (CE) | B15: i | C15: time_alloc | D15: hm_ce | E15: =1-F15 -> 0 | F15: =G15+H15 -> 1 | G15: =1-H15 -> 1 | H15: =+SUM(I15:O15) -> 0 | I15: 0 | J15: 0 | K15: 0 | L15: 0 | M15: 0 | N15: 0 | O15: 0 | P15: 0
A16: VP Operations (WS) | B16: i | C16: time_alloc | D16: hm_ws | E16: =1-F16 -> 0 | F16: =G16+H16 -> 1 | G16: =1-H16 -> 0 | H16: =+SUM(I16:O16) -> 1 | I16: 0.25 | J16: 0.25 | K16: 0.25 | L16: 0 | M16: 0.25 | N16: 0 | O16: 0 | P16: 0
A17: seniorS&Mexe (CL) | B17: i | C17: time_alloc | D17: hm_cl | E17: =1-F17 -> 0 | F17: =G17+H17 -> 1 | G17: =1-H17 -> 0 | H17: =+SUM(I17:O17) -> 1 | I17: 0.25 | J17: 0.25 | K17: 0.25 | L17: 0 | M17: 0.25 | N17: 0 | O17: 0 | P17: 0
A18: Senior Associate (RF) | B18: i | C18: time_alloc | D18: hm_rf | E18: =1-F18 -> 0 | F18: =G18+H18 -> 1 | G18: =1-H18 -> 0 | H18: =+SUM(I18:O18) -> 1 | I18: 0.25 | J18: 0.25 | K18: 0.25 | L18: 0 | M18: 0.25 | N18: 0 | O18: 0 | P18: 0
A19: associate (MT) | B19: i | C19: time_alloc | D19: hm_mt | E19: =1-F19 -> 0 | F19: =G19+H19 -> 1 | G19: =1-H19 -> 0 | H19: =+SUM(I19:O19) -> 1 | I19: 0.25 | J19: 0.25 | K19: 0.25 | L19: 0 | M19: 0.25 | N19: 0 | O19: 0 | P19: 0
A20: project manager | B20: i | C20: time_alloc | D20: hm_project | E20: =1-F20 -> 0 | F20: =G20+H20 -> 1 | G20: =1-H20 -> 0 | H20: =+SUM(I20:O20) -> 1 | I20: 0 | J20: 0 | K20: 0.5 | L20: 0 | M20: 0.5 | N20: 0 | O20: 0 | P20: 0
A22: CY Project Time Allocation
A23: D&S | E23: unalloc | F23: alloc | G23: lgh | H23: reimb | I23: BDA | J23: Aus | K23: Turks | L23: ELBOW | M23: sat | N23: Frith | O23: ROOTS | P23: FO
A24: HODS (RB) | B24: i | C24: time_alloc | D24: ds_rb | E24: =1-F24 -> 0 | F24: =G24+H24 -> 1 | G24: =1-H24 -> 1 | H24: =+SUM(I24:O24) -> 0 | I24: 0 | J24: 0 | K24: 0 | L24: 0 | M24: 0 | N24: 0 | O24: 0 | P24: 0
A25: Project Executive (LS) (100%) | B25: i | C25: time_alloc | D25: ds_ls | E25: =1-F25 -> 0 | F25: =G25+H25 -> 1 | G25: =1-H25 -> 0 | H25: =+SUM(I25:O25) -> 1 | I25: 0 | J25: 0 | K25: 0.5 | L25: 0.5 | M25: 0 | N25: 0 | O25: 0 | P25: 0
A26: Project Manager (BD) (100%) | B26: i | C26: time_alloc | D26: ds_bd | E26: =1-F26 -> 0 | F26: =G26+H26 -> 1 | G26: =1-H26 -> 0 | H26: =+SUM(I26:O26) -> 1 | I26: 0 | J26: 0 | K26: 0.5 | L26: 0.5 | M26: 0 | N26: 0 | O26: 0 | P26: 0
A27: Counsel (KT) | B27: i | C27: time_alloc | D27: ds_kt | E27: =1-F27 -> 0 | F27: =G27+H27 -> 1 | G27: =1-H27 -> 1 | H27: =+SUM(I27:O27) -> 0 | I27: 0 | J27: 0 | K27: 0 | L27: 0 | M27: 0 | N27: 0 | O27: 0 | P27: 0
A28: Development Manager??? (alexi?) | B28: i | C28: time_alloc | D28: ds_development | E28: =1-F28 -> 0 | F28: =G28+H28 -> 1 | G28: =1-H28 -> 1 | H28: =+SUM(I28:O28) -> 0 | I28: 0 | J28: 0 | K28: 0 | L28: 0 | M28: 0 | N28: 0 | O28: 0 | P28: 0
A29: Banker (tBD) | B29: i | C29: time_alloc | D29: ds_banker | E29: =1-F29 -> 0 | F29: =G29+H29 -> 1 | G29: =1-H29 -> 1 | H29: =+SUM(I29:O29) -> 0 | I29: 0 | J29: 0 | K29: 0 | L29: 0 | M29: 0 | N29: 0 | O29: 0 | P29: 0
A30: Senior Design Manager (AM) | B30: i | C30: time_alloc | D30: ds_am | E30: =1-F30 -> 0 | F30: =G30+H30 -> 1 | G30: =1-H30 -> 1 | H30: =+SUM(I30:O30) -> 0 | I30: 0 | J30: 0 | K30: 0 | L30: 0 | M30: 0 | N30: 0 | O30: 0 | P30: 0
A31: Design Manager (AL) (gone) | B31: i | C31: time_alloc | D31: ds_al | E31: =1-F31 -> 0 | F31: =G31+H31 -> 1 | G31: =1-H31 -> 1 | H31: =+SUM(I31:O31) -> 0 | I31: 0 | J31: 0 | K31: 0 | L31: 0 | M31: 0 | N31: 0 | O31: 0 | P31: 0
A32: new design manager (TBD) | B32: i | C32: time_alloc | D32: ds_tbd | E32: =1-F32 -> 0 | F32: =G32+H32 -> 1 | G32: =1-H32 -> 1 | H32: =+SUM(I32:O32) -> 0 | I32: 0 | J32: 0 | K32: 0 | L32: 0 | M32: 0 | N32: 0 | O32: 0 | P32: 0
A33: FF&E (SB) | B33: i | C33: time_alloc | D33: ds_sb | E33: =1-F33 -> 0 | F33: =G33+H33 -> 1 | G33: =1-H33 -> 1 | H33: =+SUM(I33:O33) -> 0 | I33: 0 | J33: 0 | K33: 0 | L33: 0 | M33: 0 | N33: 0 | O33: 0 | P33: 0
A34: Senior Financial Analyst (KS) | B34: i | C34: time_alloc | D34: ds_ks | E34: =1-F34 -> 0 | F34: =G34+H34 -> 1 | G34: =1-H34 -> 1 | H34: =+SUM(I34:O34) -> 0 | I34: 0 | J34: 0 | K34: 0 | L34: 0 | M34: 0 | N34: 0 | O34: 0 | P34: 0
A36: CY Project Time Allocation
A37: Bi&F | E37: unalloc | F37: alloc | G37: lgh | H37: reimb | I37: BDA | J37: Aus | K37: Turks | L37: ELBOW | M37: sat | N37: Frith | O37: ROOTS | P37: FO
A38: HOBI (CW) | B38: i | C38: time_alloc | D38: bif_cw | E38: =1-F38 -> 0 | F38: =G38+H38 -> 1 | G38: =1-H38 -> 1 | H38: =+SUM(I38:O38) -> 0 | I38: 0 | J38: 0 | K38: 0 | L38: 0 | M38: 0 | N38: 0 | O38: 0 | P38: 0
A39: CFO (ZS) | B39: i | C39: time_alloc | D39: bif_zs | E39: =1-F39 -> 0 | F39: =G39+H39 -> 1 | G39: =1-H39 -> 1 | H39: =+SUM(I39:O39) -> 0 | I39: 0 | J39: 0 | K39: 0 | L39: 0 | M39: 0 | N39: 0 | O39: 0 | P39: 0
A40: Financial Analyst (NR) | B40: i | C40: time_alloc | D40: bif_nr | E40: =1-F40 -> 0 | F40: =G40+H40 -> 1 | G40: =1-H40 -> 1 | H40: =+SUM(I40:O40) -> 0 | I40: 0 | J40: 0 | K40: 0 | L40: 0 | M40: 0 | N40: 0 | O40: 0 | P40: 0
A41: Fin Controls (TB) - 100% | B41: i | C41: time_alloc | D41: bif_tb | E41: =1-F41 -> 0 | F41: =G41+H41 -> 1 | G41: =1-H41 -> 0 | H41: =+SUM(I41:O41) -> 1 | I41: 0.25 | J41: 0.25 | K41: 0.25 | L41: 0 | M41: 0.25 | N41: 0 | O41: 0 | P41: 0
A42: Administrative Assistant (AM) | B42: i | C42: time_alloc | D42: bif_am | E42: =1-F42 -> 0 | F42: =G42+H42 -> 1 | G42: =1-H42 -> 1 | H42: =+SUM(I42:O42) -> 0 | I42: 0 | J42: 0 | K42: 0 | L42: 0 | M42: 0 | N42: 0 | O42: 0 | P42: 0
A43: Administrative Assistant (PT) | B43: i | C43: time_alloc | D43: bif_pt | E43: =1-F43 -> 0 | F43: =G43+H43 -> 1 | G43: =1-H43-P43 -> 1 | H43: =+SUM(I43:O43) -> 0 | I43: 0 | J43: 0 | K43: 0 | L43: 0 | M43: 0 | N43: 0 | O43: 0 | P43: 0
A44: Financial Director (DV) - 100% | B44: i | C44: time_alloc | D44: bif_dv | E44: =1-F44 -> 0 | F44: =G44+H44 -> 1 | G44: =1-H44 -> 0 | H44: =+SUM(I44:O44) -> 1 | I44: 0.25 | J44: 0.25 | K44: 0.25 | L44: 0 | M44: 0.25 | N44: 0 | O44: 0 | P44: 0
A45: IM (TW) | B45: i | C45: time_alloc | D45: bif_tw | E45: =1-F45 -> 0 | F45: =G45+H45 -> 1 | G45: =1-H45 -> 1 | H45: =+SUM(I45:O45) -> 0 | I45: 0 | J45: 0 | K45: 0 | L45: 0 | M45: 0 | N45: 0 | O45: 0 | P45: 0
A46: HR (100%) | B46: i | C46: time_alloc | D46: bif_hr | E46: =1-F46 -> 0 | F46: =G46+H46 -> 1 | G46: =1-H46 -> 0 | H46: =+SUM(I46:O46) -> 1 | I46: 0.25 | J46: 0.25 | K46: 0.25 | L46: 0 | M46: 0.25 | N46: 0 | O46: 0 | P46: 0
A47: Legal (100%) | B47: i | C47: time_alloc | D47: bif_legal | E47: =1-F47 -> 0 | F47: =G47+H47 -> 1 | G47: =1-H47 -> 0 | H47: =+SUM(I47:O47) -> 1 | I47: 0.25 | J47: 0.25 | K47: 0.25 | L47: 0 | M47: 0.25 | N47: 0 | O47: 0 | P47: 0
A48: Tech1 | B48: i | C48: time_alloc | D48: bif_tech1 | E48: =1-F48 -> 0 | F48: =G48+H48 -> 1 | G48: =1-H48 -> 1 | H48: =+SUM(I48:O48) -> 0 | I48: 0 | J48: 0 | K48: 0 | L48: 0 | M48: 0 | N48: 0 | O48: 0 | P48: 0
A49: Tech2 | B49: i | C49: time_alloc | D49: bif_tech2 | E49: =1-F49 -> 0 | F49: =G49+H49 -> 1 | G49: =1-H49 -> 1 | H49: =+SUM(I49:O49) -> 0 | I49: 0 | J49: 0 | K49: 0 | L49: 0 | M49: 0 | N49: 0 | O49: 0 | P49: 0

Sheet c12_diags
E1: LIVE (Python) | I1: BASELINE (frozen) | M1: ERROR = live - baseline
E2: 46203 | F2: 46295 | G2: 46387 | I2: 46203 | J2: 46295 | K2: 46387 | M2: 46203 | N2: 46295 | O2: 46387
E3: Q2_2026 | F3: Q3_2026 | G3: Q4_2026 | I3: Q2_2026 | J3: Q3_2026 | K3: Q4_2026 | M3: Q2_2026 | N3: Q3_2026 | O3: Q4_2026
A4: sheet | B4: field_name | C4: index | D4: label
A5: c12_hm | B5: reimbursable_by_hotels | D5: reimbursable by hotels to LGH | E5: 247680 | F5: 290880 | G5: 545435 | I5: 247680 | J5: 290880 | K5: 545435 | M5: =IF(E5="","",E5-I5) -> 0 | N5: =IF(F5="","",F5-J5) -> 0 | O5: =IF(G5="","",G5-K5) -> 0
A6: c12_hm | B6: total_lgh_hm_revenue | D6: total LGH HM revenue | E6: 902637.29 | F6: 948110.97 | G6: 2385063.6 | I6: 902637.29 | J6: 948110.97 | K6: 2385063.6 | M6: =IF(E6="","",E6-I6) -> 0 | N6: =IF(F6="","",F6-J6) -> 0 | O6: =IF(G6="","",G6-K6) -> 0
A7: c12_hm | B7: lgh_ar_cumm | D7: LGH Accounts Receivable Cumm. | E7: -1170394.7 | F7: -1177800.8 | G7: -16206.87 | I7: -1170394.7 | J7: -1177800.8 | K7: -16206.87 | M7: =IF(E7="","",E7-I7) -> 0 | N7: =IF(F7="","",F7-J7) -> 0 | O7: =IF(G7="","",G7-K7) -> 0
A8: c12_hm | B8: total_c12_hm_revenue | D8: Total C12 HM revenue | E8: 398173.65 | F8: 400447.34 | G8: 662529.63 | I8: 398173.65 | J8: 400447.34 | K8: 662529.63 | M8: =IF(E8="","",E8-I8) -> 0 | N8: =IF(F8="","",F8-J8) -> 0 | O8: =IF(G8="","",G8-K8) -> 0
A9: c12_hm | B9: hr_reimbursable | D9: reimbersable to hotel | E9: 247680 | F9: 290880 | G9: 545435 | I9: 247680 | J9: 290880 | K9: 545435 | M9: =IF(E9="","",E9-I9) -> 0 | N9: =IF(F9="","",F9-J9) -> 0 | O9: =IF(G9="","",G9-K9) -> 0
A10: c12_hm | B10: hr_not_reimbursable | D10: not reimbersable by hotel, but paid by lgh | E10: 144000 | F10: 144000 | G10: 403750 | I10: 144000 | J10: 144000 | K10: 403750 | M10: =IF(E10="","",E10-I10) -> 0 | N10: =IF(F10="","",F10-J10) -> 0 | O10: =IF(G10="","",G10-K10) -> 0
A11: c12_hm | B11: cumm_accrued_participation | D11: Cumm. Accrued Participation | E11: 583052.45 | F11: 425179.25 | G11: 18621.38 | I11: 583052.45 | J11: 425179.25 | K11: 18621.38 | M11: =IF(E11="","",E11-I11) -> 0 | N11: =IF(F11="","",F11-J11) -> 0 | O11: =IF(G11="","",G11-K11) -> 0
A12: c12_d&s | B12: reimbursable_by_hotels | D12: reimbursable by hotels to LGH | E12: 85680 | F12: 85680 | G12: 116850 | I12: 85680 | J12: 85680 | K12: 116850 | M12: =IF(E12="","",E12-I12) -> 0 | N12: =IF(F12="","",F12-J12) -> 0 | O12: =IF(G12="","",G12-K12) -> 0
A13: c12_d&s | B13: total_lgh_ds_revenue | D13: total LGH D&S revenue | E13: 2473819.8 | F13: 2205638.8 | G13: 5828630.3 | I13: 2473819.8 | J13: 2205638.8 | K13: 5828630.3 | M13: =IF(E13="","",E13-I13) -> 0 | N13: =IF(F13="","",F13-J13) -> 0 | O13: =IF(G13="","",G13-K13) -> 0
A14: c12_d&s | B14: lgh_ar_cumm | D14: LGH Accounts Receivable Cumm. | E14: -4470379.7 | F14: -4201060.7 | G14: -4929060.7 | I14: -4470379.7 | J14: -4201060.7 | K14: -4929060.7 | M14: =IF(E14="","",E14-I14) -> 0 | N14: =IF(F14="","",F14-J14) -> 0 | O14: =IF(G14="","",G14-K14) -> 0
A15: c12_d&s | B15: total_c12_ds_revenue | D15: Total C12 D&S revenue | E15: 1015405.1 | F15: 935314.59 | G15: 2208920.6 | I15: 1015405.1 | J15: 935314.59 | K15: 2208920.6 | M15: =IF(E15="","",E15-I15) -> 0 | N15: =IF(F15="","",F15-J15) -> 0 | O15: =IF(G15="","",G15-K15) -> 0
A16: c12_d&s | B16: hr_reimbursable | D16: reimbersable to hotel | E16: 85680 | F16: 85680 | G16: 116850 | I16: 85680 | J16: 85680 | K16: 116850 | M16: =IF(E16="","",E16-I16) -> 0 | N16: =IF(F16="","",F16-J16) -> 0 | O16: =IF(G16="","",G16-K16) -> 0
... A34: c12_oc | B34: total_lgh_revenue | D34: total rev attributable to lgh | E34: 3530751.8 | F34: 3421728.7 | G34: 8574636 | I34: 3530751.8 | J34: 3421728.7 | K34: 8574636 | M34: =IF(E34="","",E34-I34) -> 0 | N34: =IF(F34="","",F34-J34) -> 0 | O34: =IF(G34="","",G34-K34) -> 0
