Workbook
Name DepartmentNum: '.c12_inputs.hr'!$E$4

Sheet registry
A1: Year | B1: =+lgh_bs!D2 -> 45657 | C1: =+lgh_bs!E2 -> 45747 | D1: =+lgh_bs!F2 -> 45838 | E1: =+lgh_bs!G2 -> 45930 | F1: =+lgh_bs!H2 -> 46022 | G1: =+lgh_bs!I2 -> 46112 | H1: =+lgh_bs!J2 -> 46203 | I1: =+lgh_bs!K2 -> 46295 | ... N1: =+lgh_bs!P2 -> 47848
A2: subcategory | B2: =+lgh_bs!D3 -> Q4 | C2: =+lgh_bs!E3 -> Q1 | D2: =+lgh_bs!F3 -> Q2 | E2: =+lgh_bs!G3 -> Q3 | F2: =+lgh_bs!H3 -> Q4 | G2: =+lgh_bs!I3 -> Q1 | H2: =+lgh_bs!J3 -> Q2 | I2: =+lgh_bs!K3 -> Q3 | ... N2: =+lgh_bs!P3 -> Q4
A5: Cash Inflows | B5: =+pink_cs2!B17 -> 1562074 | C5: =+pink_cs2!C17 -> 3250000 | D5: =+pink_cs2!D17 -> 3388588 | E5: =+pink_cs2!E17 -> 1475962 | F5: =+pink_cs2!F17 -> 8336733 | G5: =+pink_cs2!G17 -> 0 | H5: =+pink_cs2!H17 -> 0 | I5: =+pink_cs2!I17 -> 0 | ... N5: =+pink_cs2!N17 -> 4123684
A6: Cash Outflows | B6: =+pink_cs2!B25 -> 0 | C6: =+pink_cs2!C25 -> -125000 | D6: =+pink_cs2!D25 -> -3717883 | E6: =+pink_cs2!E25 -> -3472013.3 | F6: =+pink_cs2!F25 -> 0 | G6: =+pink_cs2!G25 -> 0 | H6: =+pink_cs2!H25 -> 0 | I6: =+pink_cs2!I25 -> 0 | ... N6: =+pink_cs2!N25 -> 0
A7: Net Asset Value (NAV) | B7: =+pink_cs2!B60 -> 56391899 | C7: =+pink_cs2!C60 -> 48342875 | D7: =+pink_cs2!D60 -> 49230680 | E7: =+pink_cs2!E60 -> 51936303 | F7: =+pink_cs2!F60 -> 46803857 | G7: =+pink_cs2!G60 -> 46688396 | H7: =+pink_cs2!H60 -> 47318459 | I7: =+pink_cs2!I60 -> 47193849 | ... N7: =+pink_cs2!N60 -> 85421360
A10: Cash Inflows | B10: =+aus_cs2!E19 -> 814451.63 | C10: =+aus_cs2!F19 -> 5515000 | D10: =+aus_cs2!G19 -> 0 | E10: =+aus_cs2!H19 -> 525000 | F10: =+aus_cs2!I19 -> 0 | G10: =+aus_cs2!J19 -> 0 | H10: =+aus_cs2!K19 -> 0 | I10: =+aus_cs2!L19 -> 0 | ... N10: =+aus_cs2!Q19 -> 0
A11: Cash Outflows | B11: =+aus_cs2!E28 -> 0 | C11: =+aus_cs2!F28 -> -50000 | D11: =+aus_cs2!G28 -> -2025000 | E11: =+aus_cs2!H28 -> -230000 | F11: =+aus_cs2!I28 -> -289495 | G11: =+aus_cs2!J28 -> -1750000 | H11: =+aus_cs2!K28 -> -3420000 | I11: =+aus_cs2!L28 -> 0 | ... N11: =+aus_cs2!Q28 -> 0
A12: LGH NAV | B12: =+aus_cs2!E75 -> 15926855 | C12: =+aus_cs2!F75 -> 18088592 | D12: =+aus_cs2!G75 -> 17359150 | E12: =+aus_cs2!H75 -> 15109714 | F12: =+aus_cs2!I75 -> 7753407.4 | G12: =+aus_cs2!J75 -> 6038275.4 | H12: =+aus_cs2!K75 -> 4849926.1 | I12: =+aus_cs2!L75 -> 3974250.2 | ... N12: =+aus_cs2!Q75 -> 0
A13: Mezz Owned | B13: =+aus_cs2!E80 -> 8621252.7 | C13: =+aus_cs2!F80 -> 2691709.1 | D13: =+aus_cs2!G80 -> 2849465 | E13: =+aus_cs2!H80 -> 3017222.8 | F13: =+aus_cs2!I80 -> 4124556.9 | G13: =+aus_cs2!J80 -> 4237689.3 | H13: =+aus_cs2!K80 -> 6873678.2 | I13: =+aus_cs2!L80 -> 7084139.4 | ... N13: =+aus_cs2!Q80 -> 42318729
A14: Pref Owned | B14: =+aus_cs2!E83 -> 5608281.4 | C14: =+aus_cs2!F83 -> 5792434.5 | D14: =+aus_cs2!G83 -> 5984782.4 | E14: =+aus_cs2!H83 -> 6185737.8 | F14: =+aus_cs2!I83 -> 6393440.8 | G14: =+aus_cs2!J83 -> 6603375.3 | H14: =+aus_cs2!K83 -> 6822651.9 | I14: =+aus_cs2!L83 -> 7051741.1 | ... N14: =+aus_cs2!Q83 -> 4764456.8
A15: Net Asset Value (NAV) | B15: =+aus_cs2!E85 -> 30156389 | C15: =+aus_cs2!F85 -> 26572736 | D15: =+aus_cs2!G85 -> 26193398 | E15: =+aus_cs2!H85 -> 24312675 | F15: =+aus_cs2!I85 -> 6321102 | G15: =+aus_cs2!J85 -> 6506360 | H15: =+aus_cs2!K85 -> 9217684.1 | I15: =+aus_cs2!L85 -> 9506851.6 | ... N15: =+aus_cs2!Q85 -> 47083185
A16: Pref Liquidation adj. | B16: =+aus_cs2!E84-aus_cs2!E83 -> 0 | C16: =+aus_cs2!F84-aus_cs2!F83 -> 0 | D16: =+aus_cs2!G84-aus_cs2!G83 -> 0 | E16: =+aus_cs2!H84-aus_cs2!H83 -> 0 | F16: =+aus_cs2!I84-aus_cs2!I83 -> -4196895.7 | G16: =+aus_cs2!J84-aus_cs2!J83 -> -4334704.6 | H16: =+aus_cs2!K84-aus_cs2!K83 -> -4478646.1 | I16: =+aus_cs2!L84-aus_cs2!L83 -> -4629028.8 | ... N16: =+aus_cs2!Q84-aus_cs2!Q83 -> 0
A17: Equity Liquidation adj. | B17: =+aus_cs2!E76-aus_cs2!E75 -> 0 | C17: =+aus_cs2!F76-aus_cs2!F75 -> 0 | D17: =+aus_cs2!G76-aus_cs2!G75 -> 0 | E17: =+aus_cs2!H76-aus_cs2!H75 -> 0 | F17: =+aus_cs2!I76-aus_cs2!I75 -> -7753407.4 | G17: =+aus_cs2!J76-aus_cs2!J75 -> -6038275.4 | H17: =+aus_cs2!K76-aus_cs2!K75 -> -4849926.1 | I17: =+aus_cs2!L76-aus_cs2!L75 -> -3974250.2 | ... N17: =+aus_cs2!Q76-aus_cs2!Q75 -> 0
B18: 0 | C18: =-aus_cs2!F64 -> 215000 | D18: =-aus_cs2!G64 -> 289000 | E18: =-aus_cs2!H64 -> 0 | F18: =-aus_cs2!I64 -> 289495 | G18: =-aus_cs2!J64 -> 1289495 | H18: =-aus_cs2!K64 -> 1909495 | I18: =-aus_cs2!L64 -> 1909495 | J18: =-aus_cs2!M64 -> 2659495 | ... N18: =-aus_cs2!Q64 -> 0
A21: Cash Inflows | B21: =+turks_cs2!B20 -> 0 | C21: =+turks_cs2!C20 -> 0 | D21: =+turks_cs2!D20 -> 0 | E21: =+turks_cs2!E20 -> 0 | F21: =+turks_cs2!F20 -> 350000 | G21: =+turks_cs2!G20 -> 0 | H21: =+turks_cs2!H20 -> 350000 | I21: =+turks_cs2!I20 -> 0 | ... N21: =+turks_cs2!N20 -> 1371287
A22: Cash Outflows | B22: =+turks_cs2!B27 -> 0 | C22: =+turks_cs2!C27 -> -382967 | D22: =+turks_cs2!D27 -> -2326328 | E22: =+turks_cs2!E27 -> -3292886 | F22: =+turks_cs2!F27 -> -5106622 | G22: =+turks_cs2!G27 -> -420000 | H22: =+turks_cs2!H27 -> -200000 | I22: =+turks_cs2!I27 -> -150000 | ... N22: =+turks_cs2!N27 -> 0
A23: LGH NAV | B23: =+turks_cs2!B70 -> 30602658 | C23: =+turks_cs2!C70 -> 35723216 | D23: =+turks_cs2!D70 -> 38565928 | E23: =+turks_cs2!E70 -> 40379581 | F23: =+turks_cs2!F70 -> 40032701 | G23: =+turks_cs2!G70 -> 36265000 | H23: =+turks_cs2!H70 -> 38900747 | I23: =+turks_cs2!I70 -> 41760245 | ... N23: =+turks_cs2!N70 -> 37231193
A26: Cash Inflows | B26: =+frith_cs2!B17 -> 0 | C26: =+frith_cs2!C17 -> 0 | D26: =+frith_cs2!D17 -> 0 | E26: =+frith_cs2!E17 -> 0 | F26: =+frith_cs2!F17 -> 0 | G26: =+frith_cs2!G17 -> 2400000 | H26: =+frith_cs2!H17 -> 3600000 | I26: =+frith_cs2!I17 -> 0 | ... N26: =+frith_cs2!N17 -> 0
A27: Cash Outflows | B27: =+frith_cs2!B24 -> 0 | C27: =+frith_cs2!C24 -> 0 | D27: =+frith_cs2!D24 -> 0 | E27: =+frith_cs2!E24 -> 0 | F27: =+frith_cs2!F24 -> -860000 | G27: =+frith_cs2!G24 -> 0 | H27: =+frith_cs2!H24 -> -1750000 | I27: =+frith_cs2!I24 -> 0 | ... N27: =+frith_cs2!N24 -> 0
A28: LGH NAV | B28: =+frith_cs2!B60 -> 0 | C28: =+frith_cs2!C60 -> 11353680 | D28: =+frith_cs2!D60 -> 13799240 | E28: =+frith_cs2!E60 -> 15549103 | F28: =+frith_cs2!F60 -> 15839974 | G28: =+frith_cs2!G60 -> 15929659 | H28: =+frith_cs2!H60 -> 15182357 | I28: =+frith_cs2!I60 -> 17072720 | ... N28: =+frith_cs2!N60 -> 0
A31: Cash Inflows | B31: =+elbow_cs2!B18 -> 0 | C31: =+elbow_cs2!C18 -> 0 | D31: =+elbow_cs2!D18 -> 2500000 | E31: =+elbow_cs2!E18 -> 2500000 | F31: =+elbow_cs2!F18 -> 6137500 | G31: =+elbow_cs2!G18 -> 5640000 | H31: =+elbow_cs2!H18 -> 7300000 | I31: =+elbow_cs2!I18 -> 0 | ... N31: =+elbow_cs2!N18 -> 0
A32: Cash Outflows | B32: =+elbow_cs2!B24 -> 0 | C32: =+elbow_cs2!C24 -> -2500000 | D32: =+elbow_cs2!D24 -> 0 | E32: =+elbow_cs2!E24 -> 0 | F32: =+elbow_cs2!F24 -> 0 | G32: =+elbow_cs2!G24 -> -1000000 | H32: =+elbow_cs2!H24 -> -2040000 | I32: =+elbow_cs2!I24 -> -2000000 | ... N32: =+elbow_cs2!N24 -> 0
A33: LGH NAV | B33: =+elbow_cs2!B53 -> 5000000 | C33: =+elbow_cs2!C53 -> 17383391 | D33: =+elbow_cs2!D53 -> 19070671 | E33: =+elbow_cs2!E53 -> 20943032 | F33: =+elbow_cs2!F53 -> 22999222 | G33: =+elbow_cs2!G53 -> 28009536 | H33: =+elbow_cs2!H53 -> 30460557 | I33: =+elbow_cs2!I53 -> 33156609 | ... N33: =+elbow_cs2!N53 -> 104879625
B36: =sat_cs2!B24 -> 0 | C36: =sat_cs2!C24 -> 0 | D36: =sat_cs2!D24 -> 0 | E36: =sat_cs2!E24 -> 0 | F36: =sat_cs2!F24 -> 0 | G36: =sat_cs2!G24 -> 0 | H36: =sat_cs2!H24 -> 0 | I36: =sat_cs2!I24 -> 0 | ... N36: =sat_cs2!N24 -> 1750000
B37: =sat_cs2!B17 -> 0 | C37: =sat_cs2!C17 -> 0 | D37: =sat_cs2!D17 -> 0 | E37: =sat_cs2!E17 -> 0 | F37: =sat_cs2!F17 -> 0 | G37: =sat_cs2!G17 -> 0 | H37: =sat_cs2!H17 -> 0 | I37: =sat_cs2!I17 -> 0 | ... N37: =sat_cs2!N17 -> 0
A42: Division Expenses
A43: Guarentee Fees | B43: =-(+pink_cs2!B$31+elbow_cs2!B$29+aus_cs2!E$33+turks_cs2!B$32+frith_cs2!B$29) -> 0 | C43: =-(+pink_cs2!C$31+elbow_cs2!C$29+aus_cs2!F$33+turks_cs2!C$32+frith_cs2!C$29) -> 0 | D43: =-(+pink_cs2!D$31+elbow_cs2!D$29+aus_cs2!G$33+turks_cs2!D$32+frith_cs2!D$29) -> 0 | E43: =-(+pink_cs2!E$31+elbow_cs2!E$29+aus_cs2!H$33+turks_cs2!E$32+frith_cs2!E$29) -> 0 | F43: =-(+pink_cs2!F$31+elbow_cs2!F$29+aus_cs2!I$33+turks_cs2!F$32+frith_cs2!F$29) -> 0 | G43: =-(+pink_cs2!G$31+elbow_cs2!G$29+aus_cs2!J$33+turks_cs2!G$32+frith_cs2!G$29) -> 0 | H43: =-(+pink_cs2!H$31+elbow_cs2!H$29+aus_cs2!K$33+turks_cs2!H$32+frith_cs2!H$29) -> 0 | I43: =-(+pink_cs2!I$31+elbow_cs2!I$29+aus_cs2!L$33+turks_cs2!I$32+frith_cs2!I$29) -> 0 | ... N43: =-(+pink_cs2!N$31+elbow_cs2!N$29+aus_cs2!Q$33+turks_cs2!N$32+frith_cs2!N$29) -> 0
A46: Total LGH HM Fees | B46: =+'c12_hm'!E60 -> 0 | C46: =+'c12_hm'!F60 -> 721136.47 | D46: =+'c12_hm'!G60 -> 721136.47 | E46: =+'c12_hm'!H60 -> 721136.47 | F46: =+'c12_hm'!I60 -> 833991.74 | G46: =+'c12_hm'!J60 -> 310715.79 | H46: =+'c12_hm'!K60 -> 902637.29 | I46: =+'c12_hm'!L60 -> 948110.97 | ... N46: =+'c12_hm'!Q60 -> 8232870
A47: c12 Participation | B47: =+'c12_hm'!E70 -> 0 | C47: =+'c12_hm'!F70 -> 567056.47 | D47: =+'c12_hm'!G70 -> 567056.47 | E47: =+'c12_hm'!H70 -> 567056.47 | F47: =+'c12_hm'!I70 -> 466916.74 | G47: =+'c12_hm'!J70 -> 63035.789 | H47: =+'c12_hm'!K70 -> 398173.65 | I47: =+'c12_hm'!L70 -> 400447.34 | ... N47: =+'c12_hm'!Q70 -> 2432050.8
A49: PV Loren fees (Key money) | B49: =+lgh_manco!C8 -> 20000000 | C49: =+lgh_manco!D8 -> 20000000 | D49: =+lgh_manco!E8 -> 20000000 | E49: =+lgh_manco!F8 -> 20000000 | F49: =+lgh_manco!G8 -> 20000000 | G49: =+lgh_manco!H8 -> 20600000 | H49: =+lgh_manco!I8 -> 21218000 | I49: =+lgh_manco!J8 -> 26854540 | ... N49: =+lgh_manco!O8 -> 41436272
A50: Enterprise value | B50: =+lgh_manco!C10 -> 10000000 | C50: =+lgh_manco!D10 -> 10000000 | D50: =+lgh_manco!E10 -> 10000000 | E50: =+lgh_manco!F10 -> 10000000 | F50: =+lgh_manco!G10 -> 10000000 | G50: =+lgh_manco!H10 -> 10300000 | H50: =+lgh_manco!I10 -> 12730800 | I50: =+lgh_manco!J10 -> 18798178 | ... N50: =+lgh_manco!O10 -> 82872544
A51: Other EV | B51: =+lgh_manco!C11 -> 0 | C51: =+lgh_manco!D11 -> 0 | D51: =+lgh_manco!E11 -> 0 | E51: =+lgh_manco!F11 -> 0 | F51: =+lgh_manco!G11 -> 0 | G51: =+lgh_manco!H11 -> 0 | H51: =+lgh_manco!I11 -> 0 | I51: =+lgh_manco!J11 -> 0 | ... N51: =+lgh_manco!O11 -> 100000000
A55: Total LGH D&s Fees | B55: ='c12_d&s'!E60 -> 1480300 | C55: ='c12_d&s'!F60 -> 218167.08 | D55: ='c12_d&s'!G60 -> 218167.08 | E55: ='c12_d&s'!H60 -> 788567.08 | F55: ='c12_d&s'!I60 -> 1041680.2 | G55: ='c12_d&s'!J60 -> 1735259.1 | H55: ='c12_d&s'!K60 -> 2473819.8 | I55: ='c12_d&s'!L60 -> 2205638.8 | ... N55: ='c12_d&s'!Q60 -> 4361744.7
A56: c12 D&s Participation | B56: ='c12_d&s'!E70 -> 740150 | C56: ='c12_d&s'!F70 -> 68839.329 | D56: ='c12_d&s'!G70 -> 68839.329 | E56: ='c12_d&s'!H70 -> 354039.33 | F56: ='c12_d&s'!I70 -> 462139.99 | G56: ='c12_d&s'!J70 -> 806580.95 | H56: ='c12_d&s'!K70 -> 1015405.1 | I56: ='c12_d&s'!L70 -> 935314.59 | ... N56: ='c12_d&s'!Q70 -> 1408540.1
A58: total c12 participation | B58: ='c12_oc'!E10 -> 2452451 | C58: ='c12_oc'!F10 -> 638700.01 | D58: ='c12_oc'!G10 -> 638700.01 | E58: ='c12_oc'!H10 -> 927158.96 | F58: ='c12_oc'!I10 -> 937170.54 | G58: ='c12_oc'!J10 -> 886331.48 | H58: ='c12_oc'!K10 -> 1430293.5 | I58: ='c12_oc'!L10 -> 1358160.9 | ... N58: ='c12_oc'!Q10 -> 3977928.6
A59: total lgh revenue | B59: ='c12_oc'!E88 -> 0 | C59: ='c12_oc'!F88 -> 995387.76 | D59: ='c12_oc'!G88 -> 995387.76 | E59: ='c12_oc'!H88 -> 1630966.7 | F59: ='c12_oc'!I88 -> 2037948.3 | G59: ='c12_oc'!J88 -> 2200269.7 | H59: ='c12_oc'!K88 -> 3530751.8 | I59: ='c12_oc'!L88 -> 3421728.7 | ... N59: ='c12_oc'!Q88 -> 13901367
A60: art leases | B60: =lgh_oc!B8 -> 0 | C60: =lgh_oc!C8 -> 50000 | D60: =lgh_oc!D8 -> 50000 | E60: =lgh_oc!E8 -> 50000 | F60: =lgh_oc!F8 -> 50000 | G60: =lgh_oc!G8 -> 50000 | H60: =lgh_oc!H8 -> 50000 | I60: =lgh_oc!I8 -> 50000 | ... N60: =lgh_oc!N8 -> 250000
A62: balance | B62: =+lgh_pref_equity!L47 -> 51080209 | C62: =+lgh_pref_equity!M47 -> 49890886 | D62: =+lgh_pref_equity!N47 -> 50888704 | E62: =+lgh_pref_equity!O47 -> 51906478 | F62: =+lgh_pref_equity!P47 -> 54144869 | G62: =+lgh_pref_equity!Q47 -> 56742198 | H62: =+lgh_pref_equity!R47 -> 58896376 | I62: =+lgh_pref_equity!S47 -> 60074303 | ... N62: =+lgh_pref_equity!X47 -> 87446502
A63: Total Sources/In from Pref | B63: =+lgh_pref_equity!L55 -> 0 | C63: =+lgh_pref_equity!M55 -> 6050000 | D63: =+lgh_pref_equity!N55 -> 0 | E63: =+lgh_pref_equity!O55 -> 0 | F63: =+lgh_pref_equity!P55 -> 1200000 | G63: =+lgh_pref_equity!Q55 -> 1500000 | H63: =+lgh_pref_equity!R55 -> 1000000 | I63: =+lgh_pref_equity!S55 -> 0 | ... N63: =+lgh_pref_equity!X55 -> 0
A66: Balance: Principal and interest | B66: =+lgh_debt!G33 -> 25387077 | C66: =+lgh_debt!I33 -> 29007182 | D66: =+lgh_debt!K33 -> 30149897 | E66: =+lgh_debt!M33 -> 9136912.2 | F66: =+lgh_debt!O33 -> 8575632.5 | G66: =+lgh_debt!Q33 -> 7900128.8 | H66: =+lgh_debt!S33 -> 12239223 | I66: =+lgh_debt!U33 -> 12195992 | J66: =+lgh_debt!W33 -> 7400513.4 | K66: =+lgh_debt!Y33 -> 0 | L66: =+lgh_debt!AA33 -> 0 | M66: =+lgh_debt!AC33 -> 0 | N66: =+lgh_debt!AE33 -> 0
A67: Sources Table: Capital Inflows | B67: =+lgh_debt!G39 -> 23600000 | C67: =+lgh_debt!I39 -> 500000 | D67: =+lgh_debt!K39 -> 100000 | E67: =+lgh_debt!M39 -> 0 | F67: =+lgh_debt!O39 -> 2250000 | G67: =+lgh_debt!Q39 -> 250000 | H67: =+lgh_debt!S39 -> 4000000 | I67: =+lgh_debt!U39 -> 0 | J67: =+lgh_debt!W39 -> 0 | K67: =+lgh_debt!Y39 -> 0 | L67: =+lgh_debt!Z39 -> 0 | M67: =+lgh_debt!AA39 -> 0 | N67: =+lgh_debt!AB39 -> 0
A68: Sources Table: Capital outflows | B68: =+lgh_debt!H43 -> 0 | C68: =+lgh_debt!J43 -> -2098064.7 | D68: =+lgh_debt!L43 -> 0 | E68: =+lgh_debt!N43 -> 0 | F68: =+lgh_debt!P43 -> -3200000 | G68: =+lgh_debt!R43 -> 0 | H68: =+lgh_debt!T43 -> 0 | I68: =+lgh_debt!V43 -> -517878.34 | J68: =+lgh_debt!X43 -> -5284163.4 | K68: =+lgh_debt!Z43 -> -8541128.1 | L68: =+lgh_debt!AA43 -> 0 | M68: =+lgh_debt!AB43 -> 0 | N68: =+lgh_debt!AC43 -> 0
A71: balance | B71: =+lgh_other_liabs!F23 -> 812241.1 | C71: =+lgh_other_liabs!H23 -> 3383115.8 | D71: =+lgh_other_liabs!J23 -> 5020671.4 | E71: =+lgh_other_liabs!L23 -> 5081889.2 | F71: =+lgh_other_liabs!N23 -> 6989833.7 | G71: =+lgh_other_liabs!P23 -> 8001344.4 | H71: =+lgh_other_liabs!R23 -> 8575801.2 | I71: =+lgh_other_liabs!T23 -> 8582691.7 | J71: =+lgh_other_liabs!V23 -> 17286474 | K71: =+lgh_other_liabs!X23 -> 18797445 | L71: =+lgh_other_liabs!Z23 -> 21168562 | M71: =+lgh_other_liabs!AB23 -> 24343846 | N71: =+lgh_other_liabs!AD23 -> 27995423
A72: Total Sources/In | B72: =+lgh_other_liabs!F29 -> 62241.1 | C72: =+lgh_other_liabs!H29 -> -86000 | D72: =+lgh_other_liabs!J29 -> 142999.85 | E72: =+lgh_other_liabs!L29 -> 0 | F72: =+lgh_other_liabs!N29 -> 1625000 | G72: =+lgh_other_liabs!P29 -> 0 | H72: =+lgh_other_liabs!R29 -> 0 | I72: =+lgh_other_liabs!T29 -> 0 | J72: =+lgh_other_liabs!V29 -> 16000000 | K72: =+lgh_other_liabs!X29 -> 0 | L72: =+lgh_other_liabs!Z29 -> 0 | M72: =+lgh_other_liabs!AB29 -> 0 | N72: =+lgh_other_liabs!AD29 -> 0
A73: Total Uses/Out | B73: =+lgh_other_liabs!G33 -> 0 | C73: =+lgh_other_liabs!I33 -> 0 | D73: =+lgh_other_liabs!K33 -> 0 | E73: =+lgh_other_liabs!M33 -> 0 | F73: =+lgh_other_liabs!O33 -> -2671203.5 | G73: =+lgh_other_liabs!Q33 -> -435000 | H73: =+lgh_other_liabs!S33 -> -1052241.1 | I73: =+lgh_other_liabs!U33 -> 0 | J73: =+lgh_other_liabs!W33 -> -7309780.3 | K73: =+lgh_other_liabs!Y33 -> -890000 | L73: =+lgh_other_liabs!AA33 -> -390000 | M73: =+lgh_other_liabs!AC33 -> 0 | N73: =+lgh_other_liabs!AE33 -> 0
A77: Balance | B77: =+lgh_other_assets!B45 -> 3570254 | C77: =+lgh_other_assets!C45 -> 4252788.9 | D77: =+lgh_other_assets!D45 -> 5986171.9 | E77: =+lgh_other_assets!E45 -> 4752346.8 | F77: =+lgh_other_assets!F45 -> 4042423.2 | G77: =+lgh_other_assets!G45 -> 3150709 | H77: =+lgh_other_assets!H45 -> 3175738.3 | I77: =+lgh_other_assets!I45 -> 3356358.1 | ... N77: =+lgh_other_assets!N45 -> 5265898.3
A78: [SAT] Balance Sheet | B78: =+sat_cs2!B33 -> 0 | C78: =+sat_cs2!C33 -> 0 | D78: =+sat_cs2!D33 -> 0 | E78: =+sat_cs2!E33 -> 0 | F78: =+sat_cs2!F33 -> 0 | G78: =+sat_cs2!G33 -> 0 | H78: =+sat_cs2!H33 -> 0 | I78: =+sat_cs2!I33 -> 0 | ... N78: =+sat_cs2!N33 -> 21709416
A79: [WC] Balance Sheet | B79: =+lgh_other_assets!B31 -> 0 | C79: =+lgh_other_assets!C31 -> 0 | D79: =+lgh_other_assets!D31 -> 0 | E79: =+lgh_other_assets!E31 -> 0 | F79: =+lgh_other_assets!F31 -> 0 | G79: =+lgh_other_assets!G31 -> 0 | H79: =+lgh_other_assets!H31 -> 0 | I79: =+lgh_other_assets!I31 -> 0 | ... N79: =+lgh_other_assets!N31 -> 45000000
A82: Cumm cash balance | B82: =lgh_oc!B73 -> 251128 | C82: =lgh_oc!C73 -> 2637541.5 | D82: =lgh_oc!D73 -> -866943.45 | E82: =lgh_oc!E73 -> -2782648.6 | F82: =lgh_oc!F73 -> 420309.59 | G82: =lgh_oc!G73 -> 5306065 | H82: =lgh_oc!H73 -> 10576672 | I82: =lgh_oc!I73 -> 7017080.3 | ... N82: =lgh_oc!N73 -> 27568985
A83: guarantee payments | B83: =lgh_oc!B25 -> 0 | C83: =lgh_oc!C25 -> -250000 | D83: =lgh_oc!D25 -> -250000 | E83: =lgh_oc!E25 -> -250000 | F83: =lgh_oc!F25 -> -250000 | G83: =lgh_oc!G25 -> -250000 | H83: =lgh_oc!H25 -> -250000 | I83: =lgh_oc!I25 -> -250000 | ... N83: =lgh_oc!N25 -> -1000000
A86: total | B86: =+lgh_ci!B11 -> 0 | C86: =+lgh_ci!C11 -> 0 | D86: =+lgh_ci!D11 -> 0 | E86: =+lgh_ci!E11 -> 3805056.4 | F86: =+lgh_ci!F11 -> 1096872.2 | G86: =+lgh_ci!G11 -> 2875854.6 | H86: =+lgh_ci!H11 -> 5765639.9 | I86: =+lgh_ci!I11 -> 8978320.2 | ... N86: =+lgh_ci!N11 -> 83160179
A87: additional | B87: =+lgh_ci!B15 -> 0 | C87: =+lgh_ci!C15 -> 0 | D87: =+lgh_ci!D15 -> 0 | E87: =+lgh_ci!E15 -> 3500000 | F87: =+lgh_ci!F15 -> -682606.09 | G87: =+lgh_ci!G15 -> -25542.995 | H87: =+lgh_ci!H15 -> 1190779.7 | I87: =+lgh_ci!I15 -> 3568214.6 | ... N87: =+lgh_ci!N15 -> 64005390
A91: Total Capital Raised Other Projects | B91: =+lgh_other_assets!B35 -> 0 | C91: =+lgh_other_assets!C35 -> 0 | D91: =+lgh_other_assets!D35 -> 0 | E91: =+lgh_other_assets!E35 -> 0 | F91: =+lgh_other_assets!F35 -> 0 | G91: =+lgh_other_assets!G35 -> 0 | H91: =+lgh_other_assets!H35 -> 0 | I91: =+lgh_other_assets!I35 -> 0 | ... N91: =+lgh_other_assets!N35 -> 0
B93: =lgh_cuda!B11 -> 9000000 | C93: =lgh_cuda!C11 -> 1550000 | D93: =lgh_cuda!D11 -> 0 | E93: =lgh_cuda!E11 -> 0 | F93: =lgh_cuda!F11 -> 0 | G93: =lgh_cuda!G11 -> 0 | H93: =lgh_cuda!H11 -> 0 | I93: =lgh_cuda!I11 -> 0 | ... N93: =lgh_cuda!N11 -> 0
A94: Distribution (cuda for pref) | B94: =+lgh_cuda!B6 -> 6000000 | C94: =+lgh_cuda!C6 -> -6050000 | D94: =+lgh_cuda!D6 -> 0 | E94: =+lgh_cuda!E6 -> 0 | F94: =+lgh_cuda!F6 -> 0 | G94: =+lgh_cuda!G6 -> 0 | H94: =+lgh_cuda!H6 -> 0 | I94: =+lgh_cuda!I6 -> 0 | ... N94: =+lgh_cuda!N6 -> 0
A95: Total c12 Operating Expenses | B95: =+'c12_oc'!E40 -> -5450569 | C95: =+'c12_oc'!F40 -> -1262185 | D95: =+'c12_oc'!G40 -> -1358476 | E95: =+'c12_oc'!H40 -> -1319123 | F95: =+'c12_oc'!I40 -> -2542272 | G95: =+'c12_oc'!J40 -> -4057848.9 | H95: =+'c12_oc'!K40 -> -4457406 | I95: =+'c12_oc'!L40 -> -2834606 | ... N95: =+'c12_oc'!Q40 -> -12445130
A96: Guarentee Fees Accrued Cumm | B96: =+pink_cs2!B$32+elbow_cs2!B$30+aus_cs2!E$34+turks_cs2!B$33+frith_cs2!B$30 -> 0 | C96: =+pink_cs2!C$32+elbow_cs2!C$30+aus_cs2!F$34+turks_cs2!C$33+frith_cs2!C$30 -> 350000 | D96: =+pink_cs2!D$32+elbow_cs2!D$30+aus_cs2!G$34+turks_cs2!D$33+frith_cs2!D$30 -> 700000 | E96: =+pink_cs2!E$32+elbow_cs2!E$30+aus_cs2!H$34+turks_cs2!E$33+frith_cs2!E$30 -> 1050000 | F96: =+pink_cs2!F$32+elbow_cs2!F$30+aus_cs2!I$34+turks_cs2!F$33+frith_cs2!F$30 -> 1600000 | G96: =+pink_cs2!G$32+elbow_cs2!G$30+aus_cs2!J$34+turks_cs2!G$33+frith_cs2!G$30 -> 2150000 | H96: =+pink_cs2!H$32+elbow_cs2!H$30+aus_cs2!K$34+turks_cs2!H$33+frith_cs2!H$30 -> 2700000 | I96: =+pink_cs2!I$32+elbow_cs2!I$30+aus_cs2!L$34+turks_cs2!I$33+frith_cs2!I$30 -> 3250000 | ... N96: =+pink_cs2!N$32+elbow_cs2!N$30+aus_cs2!Q$34+turks_cs2!N$33+frith_cs2!N$30 -> 1900000
A97: Sources/In | B97: =+lgh_equity!B14 -> 0 | C97: =+lgh_equity!C14 -> 0 | D97: =+lgh_equity!D14 -> 23600000 | E97: =+lgh_equity!E14 -> 200000 | F97: =+lgh_equity!F14 -> 0 | G97: =+lgh_equity!G14 -> 0 | H97: =+lgh_equity!H14 -> 0 | I97: =+lgh_equity!I14 -> 0 | ... N97: =+lgh_equity!N14 -> 0
A98: Uses/Out | B98: =+lgh_equity!B18 -> 0 | C98: =+lgh_equity!C18 -> 0 | D98: =+lgh_equity!D18 -> -23600000 | E98: =+lgh_equity!E18 -> 0 | F98: =+lgh_equity!F18 -> 0 | G98: =+lgh_equity!G18 -> 0 | H98: =+lgh_equity!H18 -> 0 | I98: =+lgh_equity!I18 -> 0 | ... N98: =+lgh_equity!N18 -> 0
A99: CUDA Cash Outflows | B99: =+lgh_cuda!B19 -> 0 | C99: =+lgh_cuda!C19 -> -6050000 | D99: =+lgh_cuda!D19 -> -1200000 | E99: =+lgh_cuda!E19 -> 0 | F99: =+lgh_cuda!F19 -> 0 | G99: =+lgh_cuda!G19 -> 0 | H99: =+lgh_cuda!H19 -> 0 | I99: =+lgh_cuda!I19 -> 0 | ... N99: =+lgh_cuda!N19 -> 0
A100: CUDA Cash inflows | B100: =+lgh_cuda!B16 -> 6000000 | C100: =+lgh_cuda!C16 -> 0 | D100: =+lgh_cuda!D16 -> 0 | E100: =+lgh_cuda!E16 -> 0 | F100: =+lgh_cuda!F16 -> 0 | G100: =+lgh_cuda!G16 -> 0 | H100: =+lgh_cuda!H16 -> 0 | I100: =+lgh_cuda!I16 -> 0 | ... N100: =+lgh_cuda!N16 -> 0
A101: CF from Other Assets | B101: =+lgh_other_assets!B26 -> -1540999 | C101: =+lgh_other_assets!C26 -> -531057.56 | D101: =+lgh_other_assets!D26 -> 834926.44 | E101: =+lgh_other_assets!E26 -> 1193547.4 | F101: =+lgh_other_assets!F26 -> 1093901 | G101: =+lgh_other_assets!G26 -> 1641513.7 | H101: =+lgh_other_assets!H26 -> 0 | I101: =+lgh_other_assets!I26 -> 0 | ... N101: =+lgh_other_assets!N26 -> 0
A102: lgh cuda buy back | B102: =lgh_cuda!B7 -> 0 | C102: =lgh_cuda!C7 -> 0 | D102: =lgh_cuda!D7 -> -1200000 | E102: =lgh_cuda!E7 -> 0 | F102: =lgh_cuda!F7 -> 0 | G102: =lgh_cuda!G7 -> 0 | H102: =lgh_cuda!H7 -> 0 | I102: =lgh_cuda!I7 -> 0 | ... N102: =lgh_cuda!N7 -> 0
A104: Total c12 Operating Expenses | B104: -5450569 | C104: -1673186 | D104: -1769477 | E104: -1730124 | F104: -3241273 | G104: -4101794.4 | H104: -4904141.7 | I104: -3108345.4 | J104: -4841440.2 | K104: -14174255 | L104: -14541266 | M104: -13940724 | N104: -14237541
A106: c12 Advanced | B106: =-'c12_oc'!E63 -> 1540999 | C106: =-'c12_oc'!F63 -> 2072056.6 | D106: =-'c12_oc'!G63 -> 2528962.1 | E106: =-'c12_oc'!H63 -> 2735414.7 | F106: =-'c12_oc'!I63 -> 1641513.7 | G106: =-'c12_oc'!J63 -> 0 | H106: =-'c12_oc'!K63 -> 0 | I106: =-'c12_oc'!L63 -> 0 | ... N106: =-'c12_oc'!Q63 -> 0
A107: LGH Fee AR/AP | B107: =+'c12_oc'!E69 -> 0 | C107: =+'c12_oc'!F69 -> 416032.5 | D107: =+'c12_oc'!G69 -> 3082065 | E107: =+'c12_oc'!H69 -> 4373097.5 | F107: =+'c12_oc'!I69 -> 5365480 | G107: =+'c12_oc'!J69 -> 6120868.3 | H107: =+'c12_oc'!K69 -> 5640774.4 | I107: =+'c12_oc'!L69 -> 5378861.5 | ... N107: =+'c12_oc'!Q69 -> 8000000.3
A108: C12 Fee Particpiation AR/AP | B108: =-'c12_oc'!E75 -> 0 | C108: =-'c12_oc'!F75 -> -264555.12 | D108: =-'c12_oc'!G75 -> -1654110.2 | E108: =-'c12_oc'!H75 -> -2356165.4 | F108: =-'c12_oc'!I75 -> -2964570.5 | G108: =-'c12_oc'!J75 -> -2970159.3 | H108: =-'c12_oc'!K75 -> -2465036.1 | I108: =-'c12_oc'!L75 -> -2022503.4 | ... N108: =-'c12_oc'!Q75 -> -2734102

Sheet lgh_returns
D2: LEVERED RETURN ANCHORS | K2: UNLEVERED RETURN ANCHORS | R2: UNLEVERED RETURN ANCHORS
D3: Initial Adj. Common (Q1 2026) | E3: =(lgh_bs!I51*E4)/1000000 -> 107.56403 | K3: Initial Adj. Unlevered Equity (Q1 2026) | L3: =(lgh_bs!I53*$L$4)/1000000 -> 155.29344 | R3: Initial Adj. Unlevered Equity (Q1 2026) | S3: 154.45991
D4: Discount Factor (1.0 = no discount) | E4: =1-E5 -> 1 | K4: Discount Factor (1.0 = no discount) | L4: =1-L5 -> 1 | R4: Discount Factor (1.0 = no discount) | S4: 1
D5: Applied Discount | E5: 0 | K5: Applied Discount | L5: 0 | R5: Applied Discount | S5: 0
E8: Levered Return Metrics | L8: Unlevered Return Metrics | S8: Unlevered Return Metrics
C9: 2026 | D9: 2027 | E9: 2028 | F9: 2029 | G9: 2030 | J9: 2026 | K9: 2027 | L9: 2028 | M9: 2029 | N9: 2030 | Q9: 2026 | R9: 2027 | S9: 2028 | T9: 2029 | U9: 2030
C10: Common Equity | J10: Total Shareholder's Equity (SE) + Reserve - C/I | Q10: Total Shareholder's Equity (SE) + Reserve - C/I
C11: =(+lgh_bs!L38)/1000000 -> 113.01808 | D11: =(+lgh_bs!M38)/1000000 -> 129.73141 | E11: =(+lgh_bs!N38)/1000000 -> 155.88661 | F11: =(+lgh_bs!O38)/1000000 -> 186.97282 | G11: =(+lgh_bs!P38)/1000000 -> 216.99383 | J11: =(lgh_bs!L39-lgh_bs!L35+lgh_bs!L41+lgh_bs!L40)/1000000 -> 169.39255 | K11: =(lgh_bs!M39-lgh_bs!M35+lgh_bs!M41+lgh_bs!M40)/1000000 -> 195.1976 | L11: =(lgh_bs!N39-lgh_bs!N35+lgh_bs!N41+lgh_bs!N40)/1000000 -> 229.88256 | M11: =(lgh_bs!O39-lgh_bs!O35+lgh_bs!O41+lgh_bs!O40)/1000000 -> 267.16984 | N11: =(lgh_bs!P39-lgh_bs!P35+lgh_bs!P41+lgh_bs!P40)/1000000 -> 304.44033 | Q11: 168.53976 | R11: 194.24565 | S11: 228.88667 | T11: 266.12869 | U11: 303.35256
B12: Mult | C12: =+C11/$E3 -> 1.0507051 | D12: =+D11/$E3 -> 1.2060855 | E12: =+E11/$E3 -> 1.4492448 | F12: =+F11/$E3 -> 1.7382467 | G12: =+G11/$E3 -> 2.0173457 | I12: Mult | J12: =+J11/$L$3 -> 1.0907901 | K12: =+K11/$L$3 -> 1.2569598 | L12: =+L11/$L$3 -> 1.4803109 | M12: =+M11/$L$3 -> 1.7204194 | N12: =+N11/$L$3 -> 1.9604198 | P12: Mult | Q12: 1.0911554 | R12: 1.2575797 | S12: 1.4818516 | T12: 1.7229628 | U12: 1.9639566
B13: YoY | C13: =+C11/E3-1 -> 0.050705098 | D13: =+D11/C11-1 -> 0.14788199 | E13: =+E11/D11-1 -> 0.20161038 | F13: =+F11/E11-1 -> 0.19941549 | G13: =+G11/F11-1 -> 0.16056351 | I13: YoY | J13: =+J11/L3-1 -> 0.09079015 | K13: =+K11/J11-1 -> 0.15233875 | L13: =+L11/K11-1 -> 0.17769154 | M13: =+M11/L11-1 -> 0.16220143 | N13: =+N11/M11-1 -> 0.13950111 | P13: YoY | Q13: 0.09115538 | R13: 0.15252121 | S13: 0.17833613 | T13: 0.16270942 | U13: 0.13987169
B14: Q1 2026 | C14: =(C11/$E3)^(1/((lgh_bs!L$2-lgh_bs!$I$2)/365))-1 -> 0.067851673 | D14: =(D11/$E3)^(1/((lgh_bs!M$2-lgh_bs!$I$2)/365))-1 -> 0.11278417 | E14: =($E$11/$E$3)^(1/((lgh_bs!$N$2-lgh_bs!$I$2)/365))-1 -> 0.14410516 | F14: =(F11/$E3)^(1/((lgh_bs!O$2-lgh_bs!$I$2)/365))-1 -> 0.15857626 | G14: =($G$11/$E$3)^(1/((lgh_bs!$P$2-lgh_bs!$I$2)/365))-1 -> 0.15899381 | I14: Q1 2026 | J14: =+(J11/$L$3)^(1/((lgh_bs!L$2-lgh_bs!$I$2)/365))-1 -> 0.12225843 | K14: =+(K11/$L$3)^(1/((lgh_bs!M$2-lgh_bs!$I$2)/365))-1 -> 0.13931607 | L14: =+(L11/$L$3)^(1/((lgh_bs!N$2-lgh_bs!$I$2)/365))-1 -> 0.15294336 | M14: =+(M11/$L$3)^(1/((lgh_bs!O$2-lgh_bs!$I$2)/365))-1 -> 0.1554009 | N14: =+(N11/$L$3)^(1/((lgh_bs!P$2-lgh_bs!$I$2)/365))-1 -> 0.1520396 | P14: Q1 2026 | Q14: 0.1227572 | R14: 0.13963651 | S14: 0.15337861 | T14: 0.1558554 | U14: 0.15247627
C16: Common + Pref MTM + Austin Adj. + Loren EV | J16: Total SE + Reserve - C/I + Loren EV | Q16: Total SE + Reserve - C/I + Loren EV
C17: =C11+(SUM(lgh_bs!L40:L42)/1000000)*(1-lgh_inputs!$D$4)+(lgh_bs!L46/1000000) -> 130.97301 | D17: =D11+(SUM(lgh_bs!M40:M42)/1000000)*(1-lgh_inputs!$D$4)+(lgh_bs!M46/1000000) -> 154.71453 | E17: =E11+(SUM(lgh_bs!N40:N42)/1000000)*(1-lgh_inputs!$D$4)+(lgh_bs!N46/1000000) -> 191.76577 | F17: =F11+(SUM(lgh_bs!O40:O42)/1000000)*(1-lgh_inputs!$D$4)+(lgh_bs!O46/1000000) -> 228.45219 | G17: =G11+(SUM(lgh_bs!P40:P42)/1000000)*(1-lgh_inputs!$D$4)+(lgh_bs!P46/1000000) -> 270.86098 | J17: =J11+(lgh_bs!L42/1000000)*(1-lgh_inputs!$D$4) -> 183.77584 | K17: =K11+(lgh_bs!M42/1000000)*(1-lgh_inputs!$D$4) -> 215.56794 | L17: =L11+(lgh_bs!N42/1000000)*(1-lgh_inputs!$D$4) -> 261.13622 | M17: =M11+(lgh_bs!O42/1000000)*(1-lgh_inputs!$D$4) -> 306.25924 | N17: =N11+(lgh_bs!P42/1000000)*(1-lgh_inputs!$D$4) -> 358.30749 | Q17: 182.92306 | R17: 214.61599 | S17: 260.14033 | T17: 305.21809 | U17: 357.21971
B18: Mult | C18: =+C17/$E$3 -> 1.2176283 | D18: =+D17/$E$3 -> 1.4383482 | E18: =+E17/$E$3 -> 1.7828057 | F18: =+F17/$E$3 -> 2.1238716 | G18: =+G17/$E$3 -> 2.5181372 | I18: Mult | J18: =+J17/$L$3 -> 1.1834102 | K18: =+K17/$L$3 -> 1.388133 | L18: =+L17/$L$3 -> 1.6815664 | M18: =+M17/$L$3 -> 1.9721326 | N18: =+N17/$L$3 -> 2.3072932 | P18: Mult | Q18: 1.1842753 | R18: 1.3894608 | S18: 1.6841932 | T18: 1.9760343 | U18: 2.3127018
B19: YoY | C19: =+C17/E3-1 -> 0.21762828 | D19: =+D17/C17-1 -> 0.18127035 | E19: =+E17/D17-1 -> 0.23948135 | F19: =+F17/E17-1 -> 0.19130849 | G19: =+G17/F17-1 -> 0.1856353 | I19: YoY | J19: =+J17/L3-1 -> 0.18341024 | K19: =+K17/J17-1 -> 0.17299387 | L19: =+L17/K17-1 -> 0.21138712 | M19: =+M17/L17-1 -> 0.17279495 | N19: =+N17/M17-1 -> 0.16994832 | P19: YoY | Q19: 0.18427528 | R19: 0.17325828 | S19: 0.21211999 | T19: 0.17328246 | U19: 0.1703753
B20: Q1 2026 | C20: =(C17/$E$3)^(1/((lgh_bs!L$2-lgh_bs!$I$2)/365))-1 -> 0.29867765 | D20: =(D17/$E$3)^(1/((lgh_bs!M$2-lgh_bs!$I$2)/365))-1 -> 0.23035894 | E20: =(E17/$E$3)^(1/((lgh_bs!N$2-lgh_bs!$I$2)/365))-1 -> 0.23340678 | F20: =(F17/$E$3)^(1/((lgh_bs!O$2-lgh_bs!$I$2)/365))-1 -> 0.22205581 | G20: =(G17/$E$3)^(1/((lgh_bs!P$2-lgh_bs!$I$2)/365))-1 -> 0.21430652 | I20: Q1 2026 | J20: =(J17/$L3)^(1/((lgh_bs!L$2-lgh_bs!$I$2)/365))-1 -> 0.25046206 | K20: =(K17/$L3)^(1/((lgh_bs!M$2-lgh_bs!$I$2)/365))-1 -> 0.20567489 | L20: =(L17/$L3)^(1/((lgh_bs!N$2-lgh_bs!$I$2)/365))-1 -> 0.20751977 | M20: =(M17/$L3)^(1/((lgh_bs!O$2-lgh_bs!$I$2)/365))-1 -> 0.19817583 | N20: =(N17/$L3)^(1/((lgh_bs!P$2-lgh_bs!$I$2)/365))-1 -> 0.1921849 | P20: Q1 2026 | Q20: 0.2516754 | R20: 0.20633249 | S20: 0.20820382 | T20: 0.19880647 | U20: 0.19277193
C22: Common + Pref MTM + Austin Adj. + Loren EV + Other EV | J22: Total SE + Reserve - C/I + Loren EV + Other EV | Q22: Total SE + Reserve - C/I + Loren EV + Other EV
C23: =(+lgh_bs!L51)/1000000 -> 130.97301 | D23: =(+lgh_bs!M51)/1000000 -> 154.71453 | E23: =(+lgh_bs!N51)/1000000 -> 208.01577 | F23: =(+lgh_bs!O51)/1000000 -> 260.95219 | G23: =(+lgh_bs!P51)/1000000 -> 335.86098 | J23: =+lgh_bs!L53/1000000 -> 186.5413 | K23: =+lgh_bs!M53/1000000 -> 216.95102 | L23: =+lgh_bs!N53/1000000 -> 277.72759 | M23: =+lgh_bs!O53/1000000 -> 339.02943 | N23: =+lgh_bs!P53/1000000 -> 423.30749 | Q23: 185.68852 | R23: 215.99907 | S23: 276.7317 | T23: 337.98827 | U23: 422.21971
B24: Mult | C24: =+C23/$E3 -> 1.2176283 | D24: =+D23/$E3 -> 1.4383482 | E24: =+E23/$E3 -> 1.9338786 | F24: =+F23/$E3 -> 2.4260172 | G24: =+G23/$E3 -> 3.1224284 | I24: Mult | J24: =+J23/$L3 -> 1.2012182 | K24: =+K23/$L3 -> 1.3970392 | L24: =+L23/$L3 -> 1.7884052 | M24: =+M23/$L3 -> 2.1831536 | N24: =+N23/$L3 -> 2.7258556 | P24: Mult | Q24: 1.2021793 | R24: 1.3984151 | S24: 1.7916085 | T24: 2.1881941 | U24: 2.7335229
B25: YoY | C25: =+C23/E3-1 -> 0.21762828 | D25: =+D23/C23-1 -> 0.18127035 | E25: =+E23/D23-1 -> 0.3445135 | F25: =+F23/E23-1 -> 0.25448273 | G25: =+G23/F23-1 -> 0.28705944 | I25: YoY | J25: =+J23/L3-1 -> 0.2012182 | K25: =+K23/J23-1 -> 0.16301869 | L25: =+L23/K23-1 -> 0.28013958 | M25: =+M23/L23-1 -> 0.2207265 | N25: =+N23/M23-1 -> 0.24858626 | P25: YoY | Q25: 0.20217934 | R25: 0.16323334 | S25: 0.28117076 | T25: 0.22135728 | U25: 0.24921408
B26: Q1 2026 | C26: =(C23/$E3)^(1/((lgh_bs!L$2-lgh_bs!$I$2)/365))-1 -> 0.29867765 | D26: =(D23/$E3)^(1/((lgh_bs!M$2-lgh_bs!$I$2)/365))-1 -> 0.23035894 | E26: =(E23/$E3)^(1/((lgh_bs!N$2-lgh_bs!$I$2)/365))-1 -> 0.2703492 | F26: =(F23/$E3)^(1/((lgh_bs!O$2-lgh_bs!$I$2)/365))-1 -> 0.26610559 | G26: =(G23/$E3)^(1/((lgh_bs!P$2-lgh_bs!$I$2)/365))-1 -> 0.2704827 | I26: Q1 2026 | J26: =(J23/$L3)^(1/((lgh_bs!L$2-lgh_bs!$I$2)/365))-1 -> 0.27549859 | K26: =(K23/$L3)^(1/((lgh_bs!M$2-lgh_bs!$I$2)/365))-1 -> 0.21008054 | L26: =(L23/$L3)^(1/((lgh_bs!N$2-lgh_bs!$I$2)/365))-1 -> 0.23481091 | M26: =(M23/$L3)^(1/((lgh_bs!O$2-lgh_bs!$I$2)/365))-1 -> 0.23104544 | N26: =(N23/$L3)^(1/((lgh_bs!P$2-lgh_bs!$I$2)/365))-1 -> 0.23471288 | P26: Q1 2026 | Q26: 0.27685335 | R26: 0.21076007 | S26: 0.23561293 | T26: 0.23180149 | U26: 0.23544228
J27: * Unlevered Equity is the sum of Common and Preferred Equity | Q27: * Unlevered Equity is the sum of Common and Preferred Equity

Sheet lgh_inputs
C3: ASSUMPTION INPUTS from lgh_returns page
C4: CI % | D4: 0.35
C6: Pref MTM Discount Rate | D6: 0.12
C8: return on cash balances (lgh_oc) | D8: 0.03
C10: pref unit size in dollars | D10: 25
C11: from pref page
C13: Valuation Assumptions
C14: Inflation | D14: 0.03
C15: from lgh_manco

Sheet lgh_diags
A1: Entity | B1: Subcategory | C1: {=_xlfn.TEXTAFTER(CELL("filename",C1),"]")} -> lgh_diags | AB1: {=_xlfn.TEXTAFTER(CELL("filename",AB1),"]")} -> lgh_diags
C2: Year | D2: 45657 | E2: 45747 | F2: 45838 | G2: 45930 | H2: 46022 | I2: 46112 | J2: 46203 | K2: 46295 | L2: 46387 | M2: 46752 | N2: 47118 | O2: 47483 | P2: 47848 | R2: 46022 | S2: 46112 | T2: 46203 | U2: 46295 | V2: 46387 | W2: 46752 | X2: 47118 | Y2: 47483 | Z2: 47848 | AB2: Year | AC2: 46022 | AD2: 46112 | AE2: 46203 | AF2: 46295 | AG2: 46387 | AH2: 46752 | AI2: 47118 | AJ2: 47483 | AK2: 47848
C3: Period | D3: Q4 | E3: Q1 | F3: Q2 | G3: Q3 | H3: Q4 | I3: Q1 | J3: Q2 | K3: Q3 | L3: Q4 | M3: Q4 | N3: Q4 | O3: Q4 | P3: Q4 | R3: Q4 | S3: Q1 | T3: Q2 | U3: Q3 | V3: Q4 | W3: Q4 | X3: Q4 | Y3: Q4 | Z3: Q4 | AB3: Period | AC3: Q4 | AD3: Q1 | AE3: Q2 | AF3: Q3 | AG3: Q4 | AH3: Q4 | AI3: Q4 | AJ3: Q4 | AK3: Q4
C4: Assets | AB4: Assets
A5: lgh_oc | B5: Cumm cash balance | C5: Cash | D5: =lgh_bs!D5 -> 251128 | E5: =lgh_bs!E5 -> 2637541.5 | F5: =lgh_bs!F5 -> -866943.45 | G5: =lgh_bs!G5 -> -2782648.6 | H5: =lgh_bs!H5 -> 420309.59 | I5: =lgh_bs!I5 -> 5306065 | J5: =lgh_bs!J5 -> 10576672 | K5: =lgh_bs!K5 -> 7017080.3 | ... P5: =lgh_bs!P5 -> 27568985 | R5: 420309.59 | S5: 5306065 | T5: 10576672 | U5: 7017080.3 | V5: 2766709.9 | W5: 5785838.6 | X5: 13083445 | Y5: 22908452 | Z5: 27568985 | AB5: Cash | AC5: =H5-R5 -> 0 | AD5: =I5-S5 -> 0 | AE5: =J5-T5 -> 0 | AF5: =K5-U5 -> 0 | AG5: =L5-V5 -> 0 | AH5: =M5-W5 -> 0 | AI5: =N5-X5 -> 0 | AJ5: =O5-Y5 -> 0 | AK5: =P5-Z5 -> 0
C6: Bermuda | D6: =lgh_bs!D6 -> 56391899 | E6: =lgh_bs!E6 -> 48342875 | F6: =lgh_bs!F6 -> 49230680 | G6: =lgh_bs!G6 -> 51936303 | H6: =lgh_bs!H6 -> 46803857 | I6: =lgh_bs!I6 -> 46688396 | J6: =lgh_bs!J6 -> 47318459 | K6: =lgh_bs!K6 -> 47193849 | ... P6: =lgh_bs!P6 -> 85421360 | R6: 46803857 | S6: 46688396 | T6: 47318459 | U6: 47193849 | V6: 60232309 | W6: 68658853 | X6: 78031616 | Y6: 73752765 | Z6: 85421360 | AB6: Bermuda | AC6: =H6-R6 -> 0 | AD6: =I6-S6 -> 0 | AE6: =J6-T6 -> 0 | AF6: =K6-U6 -> 0 | AG6: =L6-V6 -> 0 | AH6: =M6-W6 -> 0 | AI6: =N6-X6 -> 0 | AJ6: =O6-Y6 -> 0 | AK6: =P6-Z6 -> 0
A7: Bermuda Pink Beach | B7: Level 1 | C7: Equity | D7: =lgh_bs!D7 -> 56391899 | E7: =lgh_bs!E7 -> 48342875 | F7: =lgh_bs!F7 -> 49230680 | G7: =lgh_bs!G7 -> 51936303 | H7: =lgh_bs!H7 -> 46803857 | I7: =lgh_bs!I7 -> 46688396 | J7: =lgh_bs!J7 -> 47318459 | K7: =lgh_bs!K7 -> 47193849 | ... P7: =lgh_bs!P7 -> 85421360 | R7: 46803857 | S7: 46688396 | T7: 47318459 | U7: 47193849 | V7: 60232309 | W7: 68658853 | X7: 78031616 | Y7: 73752765 | Z7: 85421360 | AB7: Equity | AC7: =H7-R7 -> 0 | AD7: =I7-S7 -> 0 | AE7: =J7-T7 -> 0 | AF7: =K7-U7 -> 0 | AG7: =L7-V7 -> 0 | AH7: =M7-W7 -> 0 | AI7: =N7-X7 -> 0 | AJ7: =O7-Y7 -> 0 | AK7: =P7-Z7 -> 0
C8: Austin | D8: =lgh_bs!D8 -> 30156389 | E8: =lgh_bs!E8 -> 26787736 | F8: =lgh_bs!F8 -> 26482398 | G8: =lgh_bs!G8 -> 24312675 | H8: =lgh_bs!H8 -> 18560900 | I8: =lgh_bs!I8 -> 18168835 | J8: =lgh_bs!J8 -> 20455751 | K8: =lgh_bs!K8 -> 20019626 | ... P8: =lgh_bs!P8 -> 47083185 | R8: 18560900 | S8: 18168835 | T8: 20455751 | U8: 20019626 | V8: 20380869 | W8: 20527642 | X8: 17612726 | Y8: 39638789 | Z8: 47083185 | AB8: Austin | AC8: =H8-R8 -> 0 | AD8: =I8-S8 -> 0 | AE8: =J8-T8 -> 0 | AF8: =K8-U8 -> 0 | AG8: =L8-V8 -> 0 | AH8: =M8-W8 -> 0 | AI8: =N8-X8 -> 0 | AJ8: =O8-Y8 -> 0 | AK8: =P8-Z8 -> 0
A9: Austin Lady Bird Lake | B9: LGH NAV | C9: Equity | D9: =lgh_bs!D9 -> 15926855 | E9: =lgh_bs!E9 -> 18088592 | F9: =lgh_bs!F9 -> 17359150 | G9: =lgh_bs!G9 -> 15109714 | H9: =lgh_bs!H9 -> 7753407.4 | I9: =lgh_bs!I9 -> 6038275.4 | J9: =lgh_bs!J9 -> 4849926.1 | K9: =lgh_bs!K9 -> 3974250.2 | ... P9: =lgh_bs!P9 -> 0 | R9: 7753407.4 | S9: 6038275.4 | T9: 4849926.1 | U9: 3974250.2 | V9: 3116853.8 | W9: 0 | X9: 0 | Y9: 0 | Z9: 0 | AB9: Equity | AC9: =H9-R9 -> 0 | AD9: =I9-S9 -> 0 | AE9: =J9-T9 -> 0 | AF9: =K9-U9 -> 0 | AG9: =L9-V9 -> 0 | AH9: =M9-W9 -> 0 | AI9: =N9-X9 -> 0 | AJ9: =O9-Y9 -> 0 | AK9: =P9-Z9 -> 0
A10: Austin Lady Bird Lake | B10: Pref Owned | C10: Preferred Equity | D10: =lgh_bs!D10 -> 5608281.4 | E10: =lgh_bs!E10 -> 5792434.5 | F10: =lgh_bs!F10 -> 5984782.4 | G10: =lgh_bs!G10 -> 6185737.8 | H10: =lgh_bs!H10 -> 6393440.8 | I10: =lgh_bs!I10 -> 6603375.3 | J10: =lgh_bs!J10 -> 6822651.9 | K10: =lgh_bs!K10 -> 7051741.1 | ... P10: =lgh_bs!P10 -> 4764456.8 | R10: 6393440.8 | S10: 6603375.3 | T10: 6822651.9 | U10: 7051741.1 | V10: 7288522.5 | W10: 6806296.5 | X10: 4230778.4 | Y10: 4951306.9 | Z10: 4764456.8 | AB10: Preferred Equity | AC10: =H10-R10 -> 0 | AD10: =I10-S10 -> 0 | AE10: =J10-T10 -> 0 | AF10: =K10-U10 -> 0 | AG10: =L10-V10 -> 0 | AH10: =M10-W10 -> 0 | AI10: =N10-X10 -> 0 | AJ10: =O10-Y10 -> 0 | AK10: =P10-Z10 -> 0
A11: Austin Lady Bird Lake | B11: Mezz Owned | C11: Mezz Loan | D11: =lgh_bs!D11 -> 8621252.7 | E11: =lgh_bs!E11 -> 2691709.1 | F11: =lgh_bs!F11 -> 2849465 | G11: =lgh_bs!G11 -> 3017222.8 | H11: =lgh_bs!H11 -> 4124556.9 | I11: =lgh_bs!I11 -> 4237689.3 | J11: =lgh_bs!J11 -> 6873678.2 | K11: =lgh_bs!K11 -> 7084139.4 | ... P11: =lgh_bs!P11 -> 42318729 | R11: 4124556.9 | S11: 4237689.3 | T11: 6873678.2 | U11: 7084139.4 | V11: 7315998.2 | W11: 10662926 | X11: 9864765.6 | Y11: 34687482 | Z11: 42318729 | AB11: Mezz Loan | AC11: =H11-R11 -> 0 | AD11: =I11-S11 -> 0 | AE11: =J11-T11 -> 0 | AF11: =K11-U11 -> 0 | AG11: =L11-V11 -> 0 | AH11: =M11-W11 -> 0 | AI11: =N11-X11 -> 0 | AJ11: =O11-Y11 -> 0 | AK11: =P11-Z11 -> 0
C12: STL | D12: =lgh_bs!D12 -> 0 | E12: =lgh_bs!E12 -> 215000 | F12: =lgh_bs!F12 -> 289000 | G12: =lgh_bs!G12 -> 0 | H12: =lgh_bs!H12 -> 289495 | I12: =lgh_bs!I12 -> 1289495 | J12: =lgh_bs!J12 -> 1909495 | K12: =lgh_bs!K12 -> 1909495 | ... P12: =lgh_bs!P12 -> 0 | R12: 289495 | S12: 1289495 | T12: 1909495 | U12: 1909495 | V12: 2659495 | W12: 3058419.2 | X12: 3517182.1 | Y12: 0 | Z12: 0 | AB12: STL | AC12: =H12-R12 -> 0 | AD12: =I12-S12 -> 0 | AE12: =J12-T12 -> 0 | AF12: =K12-U12 -> 0 | AG12: =L12-V12 -> 0 | AH12: =M12-W12 -> 0 | AI12: =N12-X12 -> 0 | AJ12: =O12-Y12 -> 0 | AK12: =P12-Z12 -> 0
C13: Turks | D13: =lgh_bs!D13 -> 30602658 | E13: =lgh_bs!E13 -> 35723216 | F13: =lgh_bs!F13 -> 38565928 | G13: =lgh_bs!G13 -> 40379581 | H13: =lgh_bs!H13 -> 40032701 | I13: =lgh_bs!I13 -> 36265000 | J13: =lgh_bs!J13 -> 38900747 | K13: =lgh_bs!K13 -> 41760245 | ... P13: =lgh_bs!P13 -> 37231193 | R13: 40032701 | S13: 36265000 | T13: 38900747 | U13: 41760245 | V13: 50265874 | W13: 32637075 | X13: 33952187 | Y13: 35273003 | Z13: 37231193 | AB13: Turks | AC13: =H13-R13 -> 0 | AD13: =I13-S13 -> 0 | AE13: =J13-T13 -> 0 | AF13: =K13-U13 -> 0 | AG13: =L13-V13 -> 0 | AH13: =M13-W13 -> 0 | AI13: =N13-X13 -> 0 | AJ13: =O13-Y13 -> 0 | AK13: =P13-Z13 -> 0
A14: Turks & Caicos | B14: LGH NAV | C14: Equity | D14: =lgh_bs!D14 -> 30602658 | E14: =lgh_bs!E14 -> 35723216 | F14: =lgh_bs!F14 -> 38565928 | G14: =lgh_bs!G14 -> 40379581 | H14: =lgh_bs!H14 -> 40032701 | I14: =lgh_bs!I14 -> 36265000 | J14: =lgh_bs!J14 -> 38900747 | K14: =lgh_bs!K14 -> 41760245 | ... P14: =lgh_bs!P14 -> 37231193 | R14: 40032701 | S14: 36265000 | T14: 38900747 | U14: 41760245 | V14: 50265874 | W14: 32637075 | X14: 33952187 | Y14: 35273003 | Z14: 37231193 | AB14: Equity | AC14: =H14-R14 -> 0 | AD14: =I14-S14 -> 0 | AE14: =J14-T14 -> 0 | AF14: =K14-U14 -> 0 | AG14: =L14-V14 -> 0 | AH14: =M14-W14 -> 0 | AI14: =N14-X14 -> 0 | AJ14: =O14-Y14 -> 0 | AK14: =P14-Z14 -> 0
C15: Elbow | D15: =lgh_bs!D15 -> 5000000 | E15: =lgh_bs!E15 -> 17383391 | F15: =lgh_bs!F15 -> 19070671 | G15: =lgh_bs!G15 -> 20943032 | H15: =lgh_bs!H15 -> 22999222 | I15: =lgh_bs!I15 -> 28009536 | J15: =lgh_bs!J15 -> 30460557 | K15: =lgh_bs!K15 -> 33156609 | ... P15: =lgh_bs!P15 -> 104879625 | R15: 22999222 | S15: 28009536 | T15: 30460557 | U15: 33156609 | V15: 36091288 | W15: 56628545 | X15: 76968139 | Y15: 97729625 | Z15: 104879625 | AB15: Elbow | AC15: =H15-R15 -> 0 | AD15: =I15-S15 -> 0 | AE15: =J15-T15 -> 0 | AF15: =K15-U15 -> 0 | AG15: =L15-V15 -> 0 | AH15: =M15-W15 -> 0 | AI15: =N15-X15 -> 0 | AJ15: =O15-Y15 -> 0 | AK15: =P15-Z15 -> 0
A16: Bermuda: Elbow Beach | B16: LGH NAV | C16: Elbow Beach | D16: =lgh_bs!D16 -> 5000000 | E16: =lgh_bs!E16 -> 17383391 | F16: =lgh_bs!F16 -> 19070671 | G16: =lgh_bs!G16 -> 20943032 | H16: =lgh_bs!H16 -> 22999222 | I16: =lgh_bs!I16 -> 28009536 | J16: =lgh_bs!J16 -> 30460557 | K16: =lgh_bs!K16 -> 33156609 | ... P16: =lgh_bs!P16 -> 104879625 | R16: 22999222 | S16: 28009536 | T16: 30460557 | U16: 33156609 | V16: 36091288 | W16: 56628545 | X16: 76968139 | Y16: 97729625 | Z16: 104879625 | AB16: Elbow Beach | AC16: =H16-R16 -> 0 | AD16: =I16-S16 -> 0 | AE16: =J16-T16 -> 0 | AF16: =K16-U16 -> 0 | AG16: =L16-V16 -> 0 | AH16: =M16-W16 -> 0 | AI16: =N16-X16 -> 0 | AJ16: =O16-Y16 -> 0 | AK16: =P16-Z16 -> 0
C17: Fritholme | D17: =lgh_bs!D17 -> 0 | E17: =lgh_bs!E17 -> 11353680 | F17: =lgh_bs!F17 -> 13799240 | G17: =lgh_bs!G17 -> 15549103 | H17: =lgh_bs!H17 -> 15839974 | I17: =lgh_bs!I17 -> 15929659 | J17: =lgh_bs!J17 -> 15182357 | K17: =lgh_bs!K17 -> 17072720 | ... P17: =lgh_bs!P17 -> 0 | R17: 15839974 | S17: 15929659 | T17: 15182357 | U17: 17072720 | V17: 0 | W17: 0 | X17: 0 | Y17: 0 | Z17: 0 | AB17: Fritholme | AC17: =H17-R17 -> 0 | AD17: =I17-S17 -> 0 | AE17: =J17-T17 -> 0 | AF17: =K17-U17 -> 0 | AG17: =L17-V17 -> 0 | AH17: =M17-W17 -> 0 | AI17: =N17-X17 -> 0 | AJ17: =O17-Y17 -> 0 | AK17: =P17-Z17 -> 0
A18: Fritholme | B18: LGH NAV | C18: Fritholme | D18: =lgh_bs!D18 -> 0 | E18: =lgh_bs!E18 -> 11353680 | F18: =lgh_bs!F18 -> 13799240 | G18: =lgh_bs!G18 -> 15549103 | H18: =lgh_bs!H18 -> 15839974 | I18: =lgh_bs!I18 -> 15929659 | J18: =lgh_bs!J18 -> 15182357 | K18: =lgh_bs!K18 -> 17072720 | ... P18: =lgh_bs!P18 -> 0 | R18: 15839974 | S18: 15929659 | T18: 15182357 | U18: 17072720 | V18: 0 | W18: 0 | X18: 0 | Y18: 0 | Z18: 0 | AB18: Fritholme | AC18: =H18-R18 -> 0 | AD18: =I18-S18 -> 0 | AE18: =J18-T18 -> 0 | AF18: =K18-U18 -> 0 | AG18: =L18-V18 -> 0 | AH18: =M18-W18 -> 0 | AI18: =N18-X18 -> 0 | AJ18: =O18-Y18 -> 0 | AK18: =P18-Z18 -> 0
C19: =+C20 -> [LSAT] | D19: =lgh_bs!D19 -> 0 | E19: =lgh_bs!E19 -> 0 | F19: =lgh_bs!F19 -> 0 | G19: =lgh_bs!G19 -> 0 | H19: =lgh_bs!H19 -> 0 | I19: =lgh_bs!I19 -> 0 | J19: =lgh_bs!J19 -> 0 | K19: =lgh_bs!K19 -> 0 | ... P19: =lgh_bs!P19 -> 21709416 | R19: 0 | S19: 0 | T19: 0 | U19: 0 | V19: 16000000 | W19: 16000000 | X19: 20333333 | Y19: 22077381 | Z19: 21709416 | AB19: =+AB20 -> [LSAT] | AC19: =H19-R19 -> 0 | AD19: =I19-S19 -> 0 | AE19: =J19-T19 -> 0 | AF19: =K19-U19 -> 0 | AG19: =L19-V19 -> 0 | AH19: =M19-W19 -> 0 | AI19: =N19-X19 -> 0 | AJ19: =O19-Y19 -> 0 | AK19: =P19-Z19 -> 0
A20: lgh_other_assets | B20: [SAT] Balance Sheet | C20: [LSAT] | D20: =lgh_bs!D20 -> 0 | E20: =lgh_bs!E20 -> 0 | F20: =lgh_bs!F20 -> 0 | G20: =lgh_bs!G20 -> 0 | H20: =lgh_bs!H20 -> 0 | I20: =lgh_bs!I20 -> 0 | J20: =lgh_bs!J20 -> 0 | K20: =lgh_bs!K20 -> 0 | ... P20: =lgh_bs!P20 -> 21709416 | R20: 0 | S20: 0 | T20: 0 | U20: 0 | V20: 16000000 | W20: 16000000 | X20: 20333333 | Y20: 22077381 | Z20: 21709416 | AB20: [LSAT] | AC20: =H20-R20 -> 0 | AD20: =I20-S20 -> 0 | AE20: =J20-T20 -> 0 | AF20: =K20-U20 -> 0 | AG20: =L20-V20 -> 0 | AH20: =M20-W20 -> 0 | AI20: =N20-X20 -> 0 | AJ20: =O20-Y20 -> 0 | AK20: =P20-Z20 -> 0
C21: =+C22 -> [L4] | D21: =lgh_bs!D21 -> 0 | E21: =lgh_bs!E21 -> 0 | F21: =lgh_bs!F21 -> 0 | G21: =lgh_bs!G21 -> 0 | H21: =lgh_bs!H21 -> 0 | I21: =lgh_bs!I21 -> 0 | J21: =lgh_bs!J21 -> 0 | K21: =lgh_bs!K21 -> 0 | ... P21: =lgh_bs!P21 -> 45000000 | R21: 0 | S21: 0 | T21: 0 | U21: 0 | V21: 0 | W21: 12500000 | X21: 18750000 | Y21: 25000000 | Z21: 45000000 | AB21: =+AB22 -> [L4] | AC21: =H21-R21 -> 0 | AD21: =I21-S21 -> 0 | AE21: =J21-T21 -> 0 | AF21: =K21-U21 -> 0 | AG21: =L21-V21 -> 0 | AH21: =M21-W21 -> 0 | AI21: =N21-X21 -> 0 | AJ21: =O21-Y21 -> 0 | AK21: =P21-Z21 -> 0
A22: lgh_other_assets | B22: [WC] Balance Sheet | C22: [L4] | D22: =lgh_bs!D22 -> 0 | E22: =lgh_bs!E22 -> 0 | F22: =lgh_bs!F22 -> 0 | G22: =lgh_bs!G22 -> 0 | H22: =lgh_bs!H22 -> 0 | I22: =lgh_bs!I22 -> 0 | J22: =lgh_bs!J22 -> 0 | K22: =lgh_bs!K22 -> 0 | ... P22: =lgh_bs!P22 -> 45000000 | R22: 0 | S22: 0 | T22: 0 | U22: 0 | V22: 0 | W22: 12500000 | X22: 18750000 | Y22: 25000000 | Z22: 45000000 | AB22: [L4] | AC22: =H22-R22 -> 0 | AD22: =I22-S22 -> 0 | AE22: =J22-T22 -> 0 | AF22: =K22-U22 -> 0 | AG22: =L22-V22 -> 0 | AH22: =M22-W22 -> 0 | AI22: =N22-X22 -> 0 | AJ22: =O22-Y22 -> 0 | AK22: =P22-Z22 -> 0
C23: =+C24 -> PV Loren fees (Key money) | D23: =lgh_bs!D23 -> 20000000 | E23: =lgh_bs!E23 -> 20000000 | F23: =lgh_bs!F23 -> 20000000 | G23: =lgh_bs!G23 -> 20000000 | H23: =lgh_bs!H23 -> 20000000 | I23: =lgh_bs!I23 -> 20600000 | J23: =lgh_bs!J23 -> 21218000 | K23: =lgh_bs!K23 -> 26854540 | ... P23: =lgh_bs!P23 -> 41436272 | R23: 20000000 | S23: 20600000 | T23: 21218000 | U23: 26854540 | V23: 27660176 | W23: 28489981 | X23: 34344681 | Y23: 35375021 | Z23: 41436272 | AB23: =+AB24 -> PV Loren fees (Key money) | AC23: =H23-R23 -> 0 | AD23: =I23-S23 -> 0 | AE23: =J23-T23 -> 0 | AF23: =K23-U23 -> 0 | AG23: =L23-V23 -> 0 | AH23: =M23-W23 -> 0 | AI23: =N23-X23 -> 0 | AJ23: =O23-Y23 -> 0 | AK23: =P23-Z23 -> 0
A24: c12_hm_oc | B24: PV Loren fees (Key money) | C24: PV Loren fees (Key money) | D24: =lgh_bs!D24 -> 20000000 | E24: =lgh_bs!E24 -> 20000000 | F24: =lgh_bs!F24 -> 20000000 | G24: =lgh_bs!G24 -> 20000000 | H24: =lgh_bs!H24 -> 20000000 | I24: =lgh_bs!I24 -> 20600000 | J24: =lgh_bs!J24 -> 21218000 | K24: =lgh_bs!K24 -> 26854540 | ... P24: =lgh_bs!P24 -> 41436272 | R24: 20000000 | S24: 20600000 | T24: 21218000 | U24: 26854540 | V24: 27660176 | W24: 28489981 | X24: 34344681 | Y24: 35375021 | Z24: 41436272 | AB24: PV Loren fees (Key money) | AC24: =H24-R24 -> 0 | AD24: =I24-S24 -> 0 | AE24: =J24-T24 -> 0 | AF24: =K24-U24 -> 0 | AG24: =L24-V24 -> 0 | AH24: =M24-W24 -> 0 | AI24: =N24-X24 -> 0 | AJ24: =O24-Y24 -> 0 | AK24: =P24-Z24 -> 0
C25: Other | D25: =lgh_bs!D25 -> 3570254 | E25: =lgh_bs!E25 -> 4252788.9 | F25: =lgh_bs!F25 -> 5986171.9 | G25: =lgh_bs!G25 -> 4752346.8 | H25: =lgh_bs!H25 -> 4042423.2 | I25: =lgh_bs!I25 -> 3150709 | J25: =lgh_bs!J25 -> 3175738.3 | K25: =lgh_bs!K25 -> 3356358.1 | ... P25: =lgh_bs!P25 -> 5265898.3 | R25: 4042423.2 | S25: 3150709 | T25: 3175738.3 | U25: 3356358.1 | V25: 3280322 | W25: 3183766.1 | X25: 2489194.6 | Y25: 4037736 | Z25: 5265898.3 | AB25: Other | AC25: =H25-R25 -> 0 | AD25: =I25-S25 -> 0 | AE25: =J25-T25 -> 0 | AF25: =K25-U25 -> 0 | AG25: =L25-V25 -> 0 | AH25: =M25-W25 -> 0 | AI25: =N25-X25 -> 0 | AJ25: =O25-Y25 -> 0 | AK25: =P25-Z25 -> 0
A26: lgh_other_assets | B26: Balance | C26: Other Assets | D26: =lgh_bs!D26 -> 3570254 | E26: =lgh_bs!E26 -> 4252788.9 | F26: =lgh_bs!F26 -> 5986171.9 | G26: =lgh_bs!G26 -> 4752346.8 | H26: =lgh_bs!H26 -> 4042423.2 | I26: =lgh_bs!I26 -> 3150709 | J26: =lgh_bs!J26 -> 3175738.3 | K26: =lgh_bs!K26 -> 3356358.1 | ... P26: =lgh_bs!P26 -> 5265898.3 | R26: 4042423.2 | S26: 3150709 | T26: 3175738.3 | U26: 3356358.1 | V26: 3280322 | W26: 3183766.1 | X26: 2489194.6 | Y26: 4037736 | Z26: 5265898.3 | AB26: Other Assets | AC26: =H26-R26 -> 0 | AD26: =I26-S26 -> 0 | AE26: =J26-T26 -> 0 | AF26: =K26-U26 -> 0 | AG26: =L26-V26 -> 0 | AH26: =M26-W26 -> 0 | AI26: =N26-X26 -> 0 | AJ26: =O26-Y26 -> 0 | AK26: =P26-Z26 -> 0
C27: Total assets incl. Cash | D27: =lgh_bs!D27 -> 1.4597233e+08 | E27: =lgh_bs!E27 -> 1.6648123e+08 | F27: =lgh_bs!F27 -> 1.7226815e+08 | G27: =lgh_bs!G27 -> 1.7509039e+08 | H27: =lgh_bs!H27 -> 1.6869939e+08 | I27: =lgh_bs!I27 -> 1.741182e+08 | J27: =lgh_bs!J27 -> 1.8728828e+08 | K27: =lgh_bs!K27 -> 1.9643103e+08 | ... P27: =lgh_bs!P27 -> 4.1559593e+08 | R27: 1.6869939e+08 | S27: 1.741182e+08 | T27: 1.8728828e+08 | U27: 1.9643103e+08 | V27: 2.1667755e+08 | W27: 2.444117e+08 | X27: 2.9556532e+08 | Y27: 3.5579277e+08 | Z27: 4.1559593e+08 | AB27: Total assets incl. Cash | AC27: =H27-R27 -> 0 | AD27: =I27-S27 -> 0 | AE27: =J27-T27 -> 0 | AF27: =K27-U27 -> 0 | AG27: =L27-V27 -> 0 | AH27: =M27-W27 -> 0 | AI27: =N27-X27 -> 0 | AJ27: =O27-Y27 -> 0 | AK27: =P27-Z27 -> 0
C28: Liabilities | D28: =lgh_bs!D28 -> 0 | E28: =lgh_bs!E28 -> 0 | F28: =lgh_bs!F28 -> 0 | G28: =lgh_bs!G28 -> 0 | H28: =lgh_bs!H28 -> 0 | I28: =lgh_bs!I28 -> 0 | J28: =lgh_bs!J28 -> 0 | K28: =lgh_bs!K28 -> 0 | ... P28: =lgh_bs!P28 -> 0 | R28: 0 | S28: 0 | T28: 0 | U28: 0 | V28: 0 | W28: 0 | X28: 0 | Y28: 0 | Z28: 0 | AB28: Liabilities | AC28: =H28-R28 -> 0 | AD28: =I28-S28 -> 0 | AE28: =J28-T28 -> 0 | AF28: =K28-U28 -> 0 | AG28: =L28-V28 -> 0 | AH28: =M28-W28 -> 0 | AI28: =N28-X28 -> 0 | AJ28: =O28-Y28 -> 0 | AK28: =P28-Z28 -> 0
A29: lgh_debt | B29: Balance: Principal and interest | C29: LGH Debt | D29: =lgh_bs!D29 -> 25387077 | E29: =lgh_bs!E29 -> 29007182 | F29: =lgh_bs!F29 -> 30149897 | G29: =lgh_bs!G29 -> 9136912.2 | H29: =lgh_bs!H29 -> 8575632.5 | I29: =lgh_bs!I29 -> 7900128.8 | J29: =lgh_bs!J29 -> 12239223 | K29: =lgh_bs!K29 -> 12195992 | ... P29: =lgh_bs!P29 -> 0 | R29: 8575632.5 | S29: 7900128.8 | T29: 12239223 | U29: 12195992 | V29: 7400513.4 | W29: 0 | X29: 0 | Y29: 0 | Z29: 0 | AB29: LGH Debt | AC29: =H29-R29 -> 0 | AD29: =I29-S29 -> 0 | AE29: =J29-T29 -> 0 | AF29: =K29-U29 -> 0 | AG29: =L29-V29 -> 0 | AH29: =M29-W29 -> 0 | AI29: =N29-X29 -> 0 | AJ29: =O29-Y29 -> 0 | AK29: =P29-Z29 -> 0
A30: lgh_other_assets | B30: Total Capital Raised Other Projects | C30: Other Project Capital needs | D30: =lgh_bs!D30 -> 0 | E30: =lgh_bs!E30 -> 0 | F30: =lgh_bs!F30 -> 0 | G30: =lgh_bs!G30 -> 0 | H30: =lgh_bs!H30 -> 0 | I30: =lgh_bs!I30 -> 0 | J30: =lgh_bs!J30 -> 0 | K30: =lgh_bs!K30 -> 0 | ... P30: =lgh_bs!P30 -> 0 | R30: 0 | S30: 0 | T30: 0 | U30: 0 | V30: 0 | W30: 0 | X30: 0 | Y30: 0 | Z30: 0 | AB30: Other Project Capital needs | AC30: =H30-R30 -> 0 | AD30: =I30-S30 -> 0 | AE30: =J30-T30 -> 0 | AF30: =K30-U30 -> 0 | AG30: =L30-V30 -> 0 | AH30: =M30-W30 -> 0 | AI30: =N30-X30 -> 0 | AJ30: =O30-Y30 -> 0 | AK30: =P30-Z30 -> 0
A31: lgh_other_liabs | B31: balance | C31: LGH other | D31: =lgh_bs!D31 -> 812241.1 | E31: =lgh_bs!E31 -> 3383115.8 | F31: =lgh_bs!F31 -> 5020671.4 | G31: =lgh_bs!G31 -> 5081889.2 | H31: =lgh_bs!H31 -> 6989833.7 | I31: =lgh_bs!I31 -> 8001344.4 | J31: =lgh_bs!J31 -> 8575801.2 | K31: =lgh_bs!K31 -> 8582691.7 | ... P31: =lgh_bs!P31 -> 27995423 | R31: 6989833.7 | S31: 8001344.4 | T31: 8575801.2 | U31: 8582691.7 | V31: 17286474 | W31: 18797445 | X31: 21168562 | Y31: 24343846 | Z31: 27995423 | AB31: LGH other | AC31: =H31-R31 -> 0 | AD31: =I31-S31 -> 0 | AE31: =J31-T31 -> 0 | AF31: =K31-U31 -> 0 | AG31: =L31-V31 -> 0 | AH31: =M31-W31 -> 0 | AI31: =N31-X31 -> 0 | AJ31: =O31-Y31 -> 0 | AK31: =P31-Z31 -> 0
C32: Total Liabilities | D32: =lgh_bs!D32 -> 26199318 | E32: =lgh_bs!E32 -> 32390298 | F32: =lgh_bs!F32 -> 35170568 | G32: =lgh_bs!G32 -> 14218801 | H32: =lgh_bs!H32 -> 15565466 | I32: =lgh_bs!I32 -> 15901473 | J32: =lgh_bs!J32 -> 20815024 | K32: =lgh_bs!K32 -> 20778684 | ... P32: =lgh_bs!P32 -> 27995423 | R32: 15565466 | S32: 15901473 | T32: 20815024 | U32: 20778684 | V32: 24686988 | W32: 18797445 | X32: 21168562 | Y32: 24343846 | Z32: 27995423 | AB32: Total Liabilities | AC32: =H32-R32 -> 0 | AD32: =I32-S32 -> 0 | AE32: =J32-T32 -> 0 | AF32: =K32-U32 -> 0 | AG32: =L32-V32 -> 0 | AH32: =M32-W32 -> 0 | AI32: =N32-X32 -> 0 | AJ32: =O32-Y32 -> 0 | AK32: =P32-Z32 -> 0
C33: Net Asset Value (NAV) | D33: =lgh_bs!D33 -> 1.1977301e+08 | E33: =lgh_bs!E33 -> 1.3409093e+08 | F33: =lgh_bs!F33 -> 1.3709758e+08 | G33: =lgh_bs!G33 -> 1.6087159e+08 | H33: =lgh_bs!H33 -> 1.5313392e+08 | I33: =lgh_bs!I33 -> 1.5821673e+08 | J33: =lgh_bs!J33 -> 1.6647326e+08 | K33: =lgh_bs!K33 -> 1.7565234e+08 | ... P33: =lgh_bs!P33 -> 3.8760051e+08 | R33: 1.5313392e+08 | S33: 1.5821673e+08 | T33: 1.6647326e+08 | U33: 1.7565234e+08 | V33: 1.9199056e+08 | W33: 2.2561426e+08 | X33: 2.7439676e+08 | Y33: 3.3144893e+08 | Z33: 3.8760051e+08 | AB33: Net Asset Value (NAV) | AC33: =H33-R33 -> 0 | AD33: =I33-S33 -> 0 | AE33: =J33-T33 -> 0 | AF33: =K33-U33 -> 0 | AG33: =L33-V33 -> 0 | AH33: =M33-W33 -> 0 | AI33: =N33-X33 -> 0 | AJ33: =O33-Y33 -> 0 | AK33: =P33-Z33 -> 0
C34: Shareholders' Equity | D34: =lgh_bs!D34 -> 0 | E34: =lgh_bs!E34 -> 0 | F34: =lgh_bs!F34 -> 0 | G34: =lgh_bs!G34 -> 0 | H34: =lgh_bs!H34 -> 0 | I34: =lgh_bs!I34 -> 0 | J34: =lgh_bs!J34 -> 0 | K34: =lgh_bs!K34 -> 0 | ... P34: =lgh_bs!P34 -> 0 | R34: 0 | S34: 0 | T34: 0 | U34: 0 | V34: 0 | W34: 0 | X34: 0 | Y34: 0 | Z34: 0 | AB34: Shareholders' Equity | AC34: =H34-R34 -> 0 | AD34: =I34-S34 -> 0 | AE34: =J34-T34 -> 0 | AF34: =K34-U34 -> 0 | AG34: =L34-V34 -> 0 | AH34: =M34-W34 -> 0 | AI34: =N34-X34 -> 0 | AJ34: =O34-Y34 -> 0 | AK34: =P34-Z34 -> 0
A35: lgh_ci | B35: total | C35: Carried Interest | D35: =lgh_bs!D35 -> 0 | E35: =lgh_bs!E35 -> 0 | F35: =lgh_bs!F35 -> 0 | G35: =lgh_bs!G35 -> 3805056.4 | H35: =lgh_bs!H35 -> 1096872.2 | I35: =lgh_bs!I35 -> 2875854.6 | J35: =lgh_bs!J35 -> 5765639.9 | K35: =lgh_bs!K35 -> 8978320.2 | ... P35: =lgh_bs!P35 -> 83160179 | R35: 1096872.2 | S35: 2875854.6 | T35: 5765639.9 | U35: 8978320.2 | V35: 14696697 | W35: 26464990 | X35: 43538866 | Y35: 63507124 | Z35: 83160179 | AB35: Carried Interest | AC35: =H35-R35 -> 0 | AD35: =I35-S35 -> 0 | AE35: =J35-T35 -> 0 | AF35: =K35-U35 -> 0 | AG35: =L35-V35 -> 0 | AH35: =M35-W35 -> 0 | AI35: =N35-X35 -> 0 | AJ35: =O35-Y35 -> 0 | AK35: =P35-Z35 -> 0
A36: lgh_pref | B36: balance | C36: Preferred Equity | D36: =lgh_bs!D36 -> 51080209 | E36: =lgh_bs!E36 -> 49890886 | F36: =lgh_bs!F36 -> 50888704 | G36: =lgh_bs!G36 -> 51906478 | H36: =lgh_bs!H36 -> 54144869 | I36: =lgh_bs!I36 -> 56742198 | J36: =lgh_bs!J36 -> 58896376 | K36: =lgh_bs!K36 -> 60074303 | ... P36: =lgh_bs!P36 -> 87446502 | R36: 54144869 | S36: 56742198 | T36: 58896376 | U36: 60074303 | V36: 64275789 | W36: 69417853 | X36: 74971281 | Y36: 80968983 | Z36: 87446502 | AB36: Preferred Equity | AC36: =H36-R36 -> 0 | AD36: =I36-S36 -> 0 | AE36: =J36-T36 -> 0 | AF36: =K36-U36 -> 0 | AG36: =L36-V36 -> 0 | AH36: =M36-W36 -> 0 | AI36: =N36-X36 -> 0 | AJ36: =O36-Y36 -> 0 | AK36: =P36-Z36 -> 0
A37: cuda | B37: Distribution (cuda for pref) | C37: CUDA | D37: =lgh_bs!D37 -> -6000000 | E37: =lgh_bs!E37 -> 6050000 | F37: =lgh_bs!F37 -> 0 | G37: =lgh_bs!G37 -> 0 | H37: =lgh_bs!H37 -> 0 | I37: =lgh_bs!I37 -> 0 | J37: =lgh_bs!J37 -> 0 | K37: =lgh_bs!K37 -> 0 | ... P37: =lgh_bs!P37 -> 0 | R37: 0 | S37: 0 | T37: 0 | U37: 0 | V37: 0 | W37: 0 | X37: 0 | Y37: 0 | Z37: 0 | AB37: CUDA | AC37: =H37-R37 -> 0 | AD37: =I37-S37 -> 0 | AE37: =J37-T37 -> 0 | AF37: =K37-U37 -> 0 | AG37: =L37-V37 -> 0 | AH37: =M37-W37 -> 0 | AI37: =N37-X37 -> 0 | AJ37: =O37-Y37 -> 0 | AK37: =P37-Z37 -> 0
C38: Common Equity | D38: =lgh_bs!D38 -> 74692801 | E38: =lgh_bs!E38 -> 78150044 | F38: =lgh_bs!F38 -> 86208873 | G38: =lgh_bs!G38 -> 1.0516006e+08 | H38: =lgh_bs!H38 -> 97892179 | I38: =lgh_bs!I38 -> 98598675 | J38: =lgh_bs!J38 -> 1.0181124e+08 | K38: =lgh_bs!K38 -> 1.0659972e+08 | ... P38: =lgh_bs!P38 -> 2.1699383e+08 | R38: 97892179 | S38: 98598675 | T38: 1.0181124e+08 | U38: 1.0659972e+08 | V38: 1.1301808e+08 | W38: 1.2973141e+08 | X38: 1.5588661e+08 | Y38: 1.8697282e+08 | Z38: 2.1699383e+08 | AB38: Common Equity | AC38: =H38-R38 -> 0 | AD38: =I38-S38 -> 0 | AE38: =J38-T38 -> 0 | AF38: =K38-U38 -> 0 | AG38: =L38-V38 -> 0 | AH38: =M38-W38 -> 0 | AI38: =N38-X38 -> 0 | AJ38: =O38-Y38 -> 0 | AK38: =P38-Z38 -> 0
C39: Total Shareholder's Equity | D39: =lgh_bs!D39 -> 1.1977301e+08 | E39: =lgh_bs!E39 -> 1.3409093e+08 | F39: =lgh_bs!F39 -> 1.3709758e+08 | G39: =lgh_bs!G39 -> 1.6087159e+08 | H39: =lgh_bs!H39 -> 1.5313392e+08 | I39: =lgh_bs!I39 -> 1.5821673e+08 | J39: =lgh_bs!J39 -> 1.6647326e+08 | K39: =lgh_bs!K39 -> 1.7565234e+08 | ... P39: =lgh_bs!P39 -> 3.8760051e+08 | R39: 1.5313392e+08 | S39: 1.5821673e+08 | T39: 1.6647326e+08 | U39: 1.7565234e+08 | V39: 1.9199056e+08 | W39: 2.2561426e+08 | X39: 2.7439676e+08 | Y39: 3.3144893e+08 | Z39: 3.8760051e+08 | AB39: Total Shareholder's Equity | AC39: =H39-R39 -> 0 | AD39: =I39-S39 -> 0 | AE39: =J39-T39 -> 0 | AF39: =K39-U39 -> 0 | AG39: =L39-V39 -> 0 | AH39: =M39-W39 -> 0 | AI39: =N39-X39 -> 0 | AJ39: =O39-Y39 -> 0 | AK39: =P39-Z39 -> 0
A40: Austin Lady Bird Lake | B40: Pref Liquidation adj. | C40: Austin Pref Liquidation adj. | D40: =lgh_bs!D40 -> 0 | E40: =lgh_bs!E40 -> 0 | F40: =lgh_bs!F40 -> 0 | G40: =lgh_bs!G40 -> 0 | H40: =lgh_bs!H40 -> -4196895.7 | I40: =lgh_bs!I40 -> -4334704.6 | J40: =lgh_bs!J40 -> -4478646.1 | K40: =lgh_bs!K40 -> -4629028.8 | ... P40: =lgh_bs!P40 -> 0 | R40: -4196895.7 | S40: -4334704.6 | T40: -4478646.1 | U40: -4629028.8 | V40: -4784461.1 | W40: -3951666.5 | X40: -975331.81 | Y40: -771958.81 | Z40: 0 | AB40: Austin Pref Liquidation adj. | AC40: =H40-R40 -> 0 | AD40: =I40-S40 -> 0 | AE40: =J40-T40 -> 0 | AF40: =K40-U40 -> 0 | AG40: =L40-V40 -> 0 | AH40: =M40-W40 -> 0 | AI40: =N40-X40 -> 0 | AJ40: =O40-Y40 -> 0 | AK40: =P40-Z40 -> 0
A41: Austin Lady Bird Lake | B41: Equity Liquidation adj. | C41: Austin Equity Liquidation adj. | D41: =lgh_bs!D41 -> 0 | E41: =lgh_bs!E41 -> 0 | F41: =lgh_bs!F41 -> 0 | G41: =lgh_bs!G41 -> 0 | H41: =lgh_bs!H41 -> -7753407.4 | I41: =lgh_bs!I41 -> -6038275.4 | J41: =lgh_bs!J41 -> -4849926.1 | K41: =lgh_bs!K41 -> -3974250.2 | ... P41: =lgh_bs!P41 -> 0 | R41: -7753407.4 | S41: -6038275.4 | T41: -4849926.1 | U41: -3974250.2 | V41: -3116853.8 | W41: 0 | X41: 0 | Y41: 0 | Z41: 0 | AB41: Austin Equity Liquidation adj. | AC41: =H41-R41 -> 0 | AD41: =I41-S41 -> 0 | AE41: =J41-T41 -> 0 | AF41: =K41-U41 -> 0 | AG41: =L41-V41 -> 0 | AH41: =M41-W41 -> 0 | AI41: =N41-X41 -> 0 | AJ41: =O41-Y41 -> 0 | AK41: =P41-Z41 -> 0
A42: c12_hm_oc | B42: Enterprise value | C42: Enterprise value Loren | D42: =lgh_bs!D42 -> 10000000 | E42: =lgh_bs!E42 -> 10000000 | F42: =lgh_bs!F42 -> 10000000 | G42: =lgh_bs!G42 -> 10000000 | H42: =lgh_bs!H42 -> 10000000 | I42: =lgh_bs!I42 -> 10300000 | J42: =lgh_bs!J42 -> 12730800 | K42: =lgh_bs!K42 -> 18798178 | ... P42: =lgh_bs!P42 -> 82872544 | R42: 10000000 | S42: 10300000 | T42: 12730800 | U42: 18798178 | V42: 22128141 | W42: 31338980 | X42: 48082553 | Y42: 60137536 | Z42: 82872544 | AB42: Enterprise value Loren | AC42: =H42-R42 -> 0 | AD42: =I42-S42 -> 0 | AE42: =J42-T42 -> 0 | AF42: =K42-U42 -> 0 | AG42: =L42-V42 -> 0 | AH42: =M42-W42 -> 0 | AI42: =N42-X42 -> 0 | AJ42: =O42-Y42 -> 0 | AK42: =P42-Z42 -> 0
A43: c12_hm_oc | B43: Other EV | C43: Other EV Value | D43: =lgh_bs!D43 -> 0 | E43: =lgh_bs!E43 -> 0 | F43: =lgh_bs!F43 -> 0 | G43: =lgh_bs!G43 -> 0 | H43: =lgh_bs!H43 -> 0 | I43: =lgh_bs!I43 -> 0 | J43: =lgh_bs!J43 -> 0 | K43: =lgh_bs!K43 -> 0 | ... P43: =lgh_bs!P43 -> 100000000 | R43: 0 | S43: 0 | T43: 0 | U43: 0 | V43: 0 | W43: 0 | X43: 25000000 | Y43: 50000000 | Z43: 100000000 | AB43: Other EV Value | AC43: =H43-R43 -> 0 | AD43: =I43-S43 -> 0 | AE43: =J43-T43 -> 0 | AF43: =K43-U43 -> 0 | AG43: =L43-V43 -> 0 | AH43: =M43-W43 -> 0 | AI43: =N43-X43 -> 0 | AJ43: =O43-Y43 -> 0 | AK43: =P43-Z43 -> 0
C44: Adjusted NAV | D44: =lgh_bs!D44 -> 1.2977301e+08 | E44: =lgh_bs!E44 -> 1.4409093e+08 | F44: =lgh_bs!F44 -> 1.4709758e+08 | G44: =lgh_bs!G44 -> 1.7087159e+08 | H44: =lgh_bs!H44 -> 1.5118362e+08 | I44: =lgh_bs!I44 -> 1.5814375e+08 | J44: =lgh_bs!J44 -> 1.6987548e+08 | K44: =lgh_bs!K44 -> 1.8584724e+08 | ... P44: =lgh_bs!P44 -> 5.7047306e+08 | R44: 1.5118362e+08 | S44: 1.5814375e+08 | T44: 1.6987548e+08 | U44: 1.8584724e+08 | V44: 2.0621739e+08 | W44: 2.5300157e+08 | X44: 3.4650398e+08 | Y44: 4.408145e+08 | Z44: 5.7047306e+08 | AB44: Adjusted NAV | AC44: =H44-R44 -> 0 | AD44: =I44-S44 -> 0 | AE44: =J44-T44 -> 0 | AF44: =K44-U44 -> 0 | AG44: =L44-V44 -> 0 | AH44: =M44-W44 -> 0 | AI44: =N44-X44 -> 0 | AJ44: =O44-Y44 -> 0 | AK44: =P44-Z44 -> 0
C45: Add. Carried Interest Val. | D45: =lgh_bs!D45 -> 0 | E45: =lgh_bs!E45 -> 0 | F45: =lgh_bs!F45 -> 0 | G45: =lgh_bs!G45 -> 3500000 | H45: =lgh_bs!H45 -> -682606.09 | I45: =lgh_bs!I45 -> -25542.995 | J45: =lgh_bs!J45 -> 1190779.7 | K45: =lgh_bs!K45 -> 3568214.6 | ... P45: =lgh_bs!P45 -> 64005390 | R45: -682606.09 | S45: -25542.995 | T45: 1190779.7 | U45: 3568214.6 | V45: 4979389.1 | W45: 9585559.6 | X45: 25237528 | Y45: 38277952 | Z45: 64005390 | AB45: Add. Carried Interest Val. | AC45: =H45-R45 -> 0 | AD45: =I45-S45 -> 0 | AE45: =J45-T45 -> 0 | AF45: =K45-U45 -> 0 | AG45: =L45-V45 -> 0 | AH45: =M45-W45 -> 0 | AI45: =N45-X45 -> 0 | AJ45: =O45-Y45 -> 0 | AK45: =P45-Z45 -> 0
C46: LGH Pref MTM | D46: =lgh_bs!D46 -> 17817146 | E46: =lgh_bs!E46 -> 9423344.8 | F46: =lgh_bs!F46 -> 9235852.2 | G46: =lgh_bs!G46 -> 9029325.8 | H46: =lgh_bs!H46 -> 9006828.7 | I46: =lgh_bs!I46 -> 9012792.6 | J46: =lgh_bs!J46 -> 8903722.3 | K46: =lgh_bs!K46 -> 8612217.9 | ... P46: =lgh_bs!P46 -> 0 | R46: 9006828.7 | S46: 9012792.6 | T46: 8903722.3 | U46: 8612217.9 | V46: 8707493.5 | W46: 7181361.2 | X46: 5259464.9 | Y46: 2891749.4 | Z46: 0 | AB46: LGH Pref MTM | AC46: =H46-R46 -> 0 | AD46: =I46-S46 -> 0 | AE46: =J46-T46 -> 0 | AF46: =K46-U46 -> 0 | AG46: =L46-V46 -> 0 | AH46: =M46-W46 -> 0 | AI46: =N46-X46 -> 0 | AJ46: =O46-Y46 -> 0 | AK46: =P46-Z46 -> 0
C47: Pref participation | D47: =lgh_bs!D47 -> 43497765 | E47: =lgh_bs!E47 -> 49728070 | F47: =lgh_bs!F47 -> 13405097 | G47: =lgh_bs!G47 -> 15679493 | H47: =lgh_bs!H47 -> 14925334 | I47: =lgh_bs!I47 -> 15840009 | J47: =lgh_bs!J47 -> 16666619 | K47: =lgh_bs!K47 -> 17585591 | ... P47: =lgh_bs!P47 -> 38804972 | R47: 14925334 | S47: 15840009 | T47: 16666619 | U47: 17585591 | V47: 19221307 | W47: 22587573 | X47: 27471477 | Y47: 33183305 | Z47: 38804972 | AB47: Pref participation | AC47: =H47-R47 -> 0 | AD47: =I47-S47 -> 0 | AE47: =J47-T47 -> 0 | AF47: =K47-U47 -> 0 | AG47: =L47-V47 -> 0 | AH47: =M47-W47 -> 0 | AI47: =N47-X47 -> 0 | AJ47: =O47-Y47 -> 0 | AK47: =P47-Z47 -> 0
C48: CUDA | D48: =lgh_bs!D48 -> -6000000 | E48: =lgh_bs!E48 -> 6050000 | F48: =lgh_bs!F48 -> 0 | G48: =lgh_bs!G48 -> 0 | H48: =lgh_bs!H48 -> 0 | I48: =lgh_bs!I48 -> 0 | J48: =lgh_bs!J48 -> 0 | K48: =lgh_bs!K48 -> 0 | ... P48: =lgh_bs!P48 -> 0 | R48: 0 | S48: 0 | T48: 0 | U48: 0 | V48: 0 | W48: 0 | X48: 0 | Y48: 0 | Z48: 0 | AB48: CUDA | AC48: =H48-R48 -> 0 | AD48: =I48-S48 -> 0 | AE48: =J48-T48 -> 0 | AF48: =K48-U48 -> 0 | AG48: =L48-V48 -> 0 | AH48: =M48-W48 -> 0 | AI48: =N48-X48 -> 0 | AJ48: =O48-Y48 -> 0 | AK48: =P48-Z48 -> 0
C49: Adj. Pref | D49: =lgh_bs!D49 -> 33263063 | E49: =lgh_bs!E49 -> 40467542 | F49: =lgh_bs!F49 -> 41652852 | G49: =lgh_bs!G49 -> 42877152 | H49: =lgh_bs!H49 -> 45138040 | I49: =lgh_bs!I49 -> 47729405 | J49: =lgh_bs!J49 -> 49992654 | K49: =lgh_bs!K49 -> 51462086 | ... P49: =lgh_bs!P49 -> 87446502 | R49: 45138040 | S49: 47729405 | T49: 49992654 | U49: 51462086 | V49: 55568296 | W49: 62236491 | X49: 69711816 | Y49: 78077234 | Z49: 87446502 | AB49: Adj. Pref | AC49: =H49-R49 -> 0 | AD49: =I49-S49 -> 0 | AE49: =J49-T49 -> 0 | AF49: =K49-U49 -> 0 | AG49: =L49-V49 -> 0 | AH49: =M49-W49 -> 0 | AI49: =N49-X49 -> 0 | AJ49: =O49-Y49 -> 0 | AK49: =P49-Z49 -> 0
C50: Adj. CI | D50: =lgh_bs!D50 -> 0 | E50: =lgh_bs!E50 -> 0 | F50: =lgh_bs!F50 -> 0 | G50: =lgh_bs!G50 -> 7305056.4 | H50: =lgh_bs!H50 -> 414266.07 | I50: =lgh_bs!I50 -> 2850311.6 | J50: =lgh_bs!J50 -> 6956419.6 | K50: =lgh_bs!K50 -> 12546535 | ... P50: =lgh_bs!P50 -> 1.4716557e+08 | R50: 414266.07 | S50: 2850311.6 | T50: 6956419.6 | U50: 12546535 | V50: 19676086 | W50: 36050549 | X50: 68776394 | Y50: 1.0178508e+08 | Z50: 1.4716557e+08 | AB50: Adj. CI | AC50: =H50-R50 -> 0 | AD50: =I50-S50 -> 0 | AE50: =J50-T50 -> 0 | AF50: =K50-U50 -> 0 | AG50: =L50-V50 -> 0 | AH50: =M50-W50 -> 0 | AI50: =N50-X50 -> 0 | AJ50: =O50-Y50 -> 0 | AK50: =P50-Z50 -> 0
C51: Adj. Common Equity | D51: =lgh_bs!D51 -> 1.0250995e+08 | E51: =lgh_bs!E51 -> 97573389 | F51: =lgh_bs!F51 -> 1.0544472e+08 | G51: =lgh_bs!G51 -> 1.2068938e+08 | H51: =lgh_bs!H51 -> 1.0563131e+08 | I51: =lgh_bs!I51 -> 1.0756403e+08 | J51: =lgh_bs!J51 -> 1.1292641e+08 | K51: =lgh_bs!K51 -> 1.2183862e+08 | ... P51: =lgh_bs!P51 -> 3.3586098e+08 | R51: 1.0563131e+08 | S51: 1.0756403e+08 | T51: 1.1292641e+08 | U51: 1.2183862e+08 | V51: 1.3097301e+08 | W51: 1.5471453e+08 | X51: 2.0801577e+08 | Y51: 2.6095219e+08 | Z51: 3.3586098e+08 | AB51: Adj. Common Equity | AC51: =H51-R51 -> 0 | AD51: =I51-S51 -> 0 | AE51: =J51-T51 -> 0 | AF51: =K51-U51 -> 0 | AG51: =L51-V51 -> 0 | AH51: =M51-W51 -> 0 | AI51: =N51-X51 -> 0 | AJ51: =O51-Y51 -> 0 | AK51: =P51-Z51 -> 0
C52: Adjusted Shareholder's Equity | D52: =lgh_bs!D52 -> 1.2977301e+08 | E52: =lgh_bs!E52 -> 1.4409093e+08 | F52: =lgh_bs!F52 -> 1.4709758e+08 | G52: =lgh_bs!G52 -> 1.7087159e+08 | H52: =lgh_bs!H52 -> 1.5118362e+08 | I52: =lgh_bs!I52 -> 1.5814375e+08 | J52: =lgh_bs!J52 -> 1.6987548e+08 | K52: =lgh_bs!K52 -> 1.8584724e+08 | ... P52: =lgh_bs!P52 -> 5.7047306e+08 | R52: 1.5118362e+08 | S52: 1.5814375e+08 | T52: 1.6987548e+08 | U52: 1.8584724e+08 | V52: 2.0621739e+08 | W52: 2.5300157e+08 | X52: 3.4650398e+08 | Y52: 4.408145e+08 | Z52: 5.7047306e+08 | AB52: Adjusted Shareholder's Equity | AC52: =H52-R52 -> 0 | AD52: =I52-S52 -> 0 | AE52: =J52-T52 -> 0 | AF52: =K52-U52 -> 0 | AG52: =L52-V52 -> 0 | AH52: =M52-W52 -> 0 | AI52: =N52-X52 -> 0 | AJ52: =O52-Y52 -> 0 | AK52: =P52-Z52 -> 0
C53: Adj. Unlevered Equity | D53: =lgh_bs!D53 -> 1.2977301e+08 | E53: =lgh_bs!E53 -> 0 | F53: =lgh_bs!F53 -> 0 | G53: =lgh_bs!G53 -> 0 | H53: =lgh_bs!H53 -> 1.5076935e+08 | I53: =lgh_bs!I53 -> 1.5529344e+08 | J53: =lgh_bs!J53 -> 1.6291907e+08 | K53: =lgh_bs!K53 -> 1.7330071e+08 | ... P53: =lgh_bs!P53 -> 4.2330749e+08 | R53: 1.5076935e+08 | S53: 1.5529344e+08 | T53: 1.6291907e+08 | U53: 1.7330071e+08 | V53: 1.865413e+08 | W53: 2.1695102e+08 | X53: 2.7772759e+08 | Y53: 3.3902943e+08 | Z53: 4.2330749e+08 | AB53: Adj. Unlevered Equity | AC53: =H53-R53 -> 0 | AD53: =I53-S53 -> 0 | AE53: =J53-T53 -> 0 | AF53: =K53-U53 -> 0 | AG53: =L53-V53 -> 0 | AH53: =M53-W53 -> 0 | AI53: =N53-X53 -> 0 | AJ53: =O53-Y53 -> 0 | AK53: =P53-Z53 -> 0

Sheet lgh_bs
A1: Entity | B1: Subcategory | C1: {=_xlfn.TEXTAFTER(CELL("filename",C1),"]")} -> lgh_bs
C2: Year | D2: 45657 | E2: 45747 | F2: 45838 | G2: 45930 | H2: 46022 | I2: 46112 | J2: 46203 | K2: 46295 | L2: 46387 | M2: 46752 | N2: 47118 | O2: 47483 | P2: 47848
C3: Period | D3: Q4 | E3: Q1 | F3: Q2 | G3: Q3 | H3: Q4 | I3: Q1 | J3: Q2 | K3: Q3 | L3: Q4 | M3: Q4 | N3: Q4 | O3: Q4 | P3: Q4
C4: Assets
A5: lgh_oc | B5: Cumm cash balance | C5: Cash | D5: 251128 | E5: =+registry!C82 -> 2637541.5 | F5: =+registry!D82 -> -866943.45 | G5: =+registry!E82 -> -2782648.6 | H5: =+registry!F82 -> 420309.59 | I5: =+registry!G82 -> 5306065 | J5: =+registry!H82 -> 10576672 | K5: =+registry!I82 -> 7017080.3 | L5: =+registry!J82 -> 2766709.9 | ... P5: =+registry!N82 -> 27568985
C6: Bermuda | D6: 56391899 | E6: =SUM(E7:E7) -> 48342875 | F6: =SUM(F7:F7) -> 49230680 | G6: =SUM(G7:G7) -> 51936303 | H6: =SUM(H7:H7) -> 46803857 | I6: =SUM(I7:I7) -> 46688396 | J6: =SUM(J7:J7) -> 47318459 | K6: =SUM(K7:K7) -> 47193849 | L6: =SUM(L7:L7) -> 60232309 | ... P6: =SUM(P7:P7) -> 85421360
A7: Bermuda Pink Beach | B7: Level 1 | C7: Equity | D7: 56391899 | E7: =+registry!C7 -> 48342875 | F7: =+registry!D7 -> 49230680 | G7: =+registry!E7 -> 51936303 | H7: =+registry!F7 -> 46803857 | I7: =+registry!G7 -> 46688396 | J7: =+registry!H7 -> 47318459 | K7: =+registry!I7 -> 47193849 | L7: =+registry!J7 -> 60232309 | ... P7: =+registry!N7 -> 85421360
C8: Austin | D8: 30156389 | E8: =SUM(E9:E12) -> 26787736 | F8: =SUM(F9:F12) -> 26482398 | G8: =SUM(G9:G12) -> 24312675 | H8: =SUM(H9:H12) -> 18560900 | I8: =SUM(I9:I12) -> 18168835 | J8: =SUM(J9:J12) -> 20455751 | K8: =SUM(K9:K12) -> 20019626 | L8: =SUM(L9:L12) -> 20380869 | ... P8: =SUM(P9:P12) -> 47083185
A9: Austin Lady Bird Lake | B9: LGH NAV | C9: Equity | D9: 15926855 | E9: =+registry!C12 -> 18088592 | F9: =+registry!D12 -> 17359150 | G9: =+registry!E12 -> 15109714 | H9: =+registry!F12 -> 7753407.4 | I9: =+registry!G12 -> 6038275.4 | J9: =+registry!H12 -> 4849926.1 | K9: =+registry!I12 -> 3974250.2 | L9: =+registry!J12 -> 3116853.8 | ... P9: =+registry!N12 -> 0
A10: Austin Lady Bird Lake | B10: Pref Owned | C10: Preferred Equity | D10: 5608281.4 | E10: =+registry!C14 -> 5792434.5 | F10: =+registry!D14 -> 5984782.4 | G10: =+registry!E14 -> 6185737.8 | H10: =+registry!F14 -> 6393440.8 | I10: =+registry!G14 -> 6603375.3 | J10: =+registry!H14 -> 6822651.9 | K10: =+registry!I14 -> 7051741.1 | L10: =+registry!J14 -> 7288522.5 | ... P10: =+registry!N14 -> 4764456.8
A11: Austin Lady Bird Lake | B11: Mezz Owned | C11: Mezz Loan | D11: 8621252.7 | E11: =+registry!C13 -> 2691709.1 | F11: =+registry!D13 -> 2849465 | G11: =+registry!E13 -> 3017222.8 | H11: =+registry!F13 -> 4124556.9 | I11: =+registry!G13 -> 4237689.3 | J11: =+registry!H13 -> 6873678.2 | K11: =+registry!I13 -> 7084139.4 | L11: =+registry!J13 -> 7315998.2 | ... P11: =+registry!N13 -> 42318729
C12: STL | D12: =registry!B18 -> 0 | E12: =registry!C18 -> 215000 | F12: =registry!D18 -> 289000 | G12: =registry!E18 -> 0 | H12: =registry!F18 -> 289495 | I12: =registry!G18 -> 1289495 | J12: =registry!H18 -> 1909495 | K12: =registry!I18 -> 1909495 | ... P12: =registry!N18 -> 0
C13: Turks | D13: 30602658 | E13: =SUM(E14) -> 35723216 | F13: =SUM(F14) -> 38565928 | G13: =SUM(G14) -> 40379581 | H13: =SUM(H14) -> 40032701 | I13: =SUM(I14) -> 36265000 | J13: =SUM(J14) -> 38900747 | K13: =SUM(K14) -> 41760245 | L13: =SUM(L14) -> 50265874 | ... P13: =SUM(P14) -> 37231193
A14: Turks & Caicos | B14: LGH NAV | C14: Equity | D14: 30602658 | E14: =+registry!C23 -> 35723216 | F14: =+registry!D23 -> 38565928 | G14: =+registry!E23 -> 40379581 | H14: =+registry!F23 -> 40032701 | I14: =+registry!G23 -> 36265000 | J14: =+registry!H23 -> 38900747 | K14: =+registry!I23 -> 41760245 | L14: =+registry!J23 -> 50265874 | ... P14: =+registry!N23 -> 37231193
C15: Elbow | D15: 5000000 | E15: =SUM(E16) -> 17383391 | F15: =SUM(F16) -> 19070671 | G15: =SUM(G16) -> 20943032 | H15: =SUM(H16) -> 22999222 | I15: =SUM(I16) -> 28009536 | J15: =SUM(J16) -> 30460557 | K15: =SUM(K16) -> 33156609 | L15: =SUM(L16) -> 36091288 | ... P15: =SUM(P16) -> 104879625
A16: Bermuda: Elbow Beach | B16: LGH NAV | C16: Elbow Beach | D16: 5000000 | E16: =+registry!C33 -> 17383391 | F16: =+registry!D33 -> 19070671 | G16: =+registry!E33 -> 20943032 | H16: =+registry!F33 -> 22999222 | I16: =+registry!G33 -> 28009536 | J16: =+registry!H33 -> 30460557 | K16: =+registry!I33 -> 33156609 | L16: =+registry!J33 -> 36091288 | ... P16: =+registry!N33 -> 104879625
C17: Fritholme | D17: 0 | E17: =SUM(E18) -> 11353680 | F17: =SUM(F18) -> 13799240 | G17: =SUM(G18) -> 15549103 | H17: =SUM(H18) -> 15839974 | I17: =SUM(I18) -> 15929659 | J17: =SUM(J18) -> 15182357 | K17: =SUM(K18) -> 17072720 | L17: =SUM(L18) -> 0 | ... P17: =SUM(P18) -> 0
A18: Fritholme | B18: LGH NAV | C18: Fritholme | D18: 0 | E18: =+registry!C28 -> 11353680 | F18: =+registry!D28 -> 13799240 | G18: =+registry!E28 -> 15549103 | H18: =+registry!F28 -> 15839974 | I18: =+registry!G28 -> 15929659 | J18: =+registry!H28 -> 15182357 | K18: =+registry!I28 -> 17072720 | L18: =+registry!J28 -> 0 | ... P18: =+registry!N28 -> 0
C19: =+C20 -> [LSAT] | D19: 0 | E19: =SUM(E20) -> 0 | F19: =SUM(F20) -> 0 | G19: =SUM(G20) -> 0 | H19: =SUM(H20) -> 0 | I19: =SUM(I20) -> 0 | J19: =SUM(J20) -> 0 | K19: =SUM(K20) -> 0 | L19: =SUM(L20) -> 16000000 | ... P19: =SUM(P20) -> 21709416
A20: lgh_other_assets | B20: [SAT] Balance Sheet | C20: [LSAT] | D20: 0 | E20: =+registry!C78 -> 0 | F20: =+registry!D78 -> 0 | G20: =+registry!E78 -> 0 | H20: =+registry!F78 -> 0 | I20: =+registry!G78 -> 0 | J20: =+registry!H78 -> 0 | K20: =+registry!I78 -> 0 | L20: =+registry!J78 -> 16000000 | ... P20: =+registry!N78 -> 21709416
C21: =+C22 -> [L4] | D21: 0 | E21: =SUM(E22) -> 0 | F21: =SUM(F22) -> 0 | G21: =SUM(G22) -> 0 | H21: =SUM(H22) -> 0 | I21: =SUM(I22) -> 0 | J21: =SUM(J22) -> 0 | K21: =SUM(K22) -> 0 | L21: =SUM(L22) -> 0 | ... P21: =SUM(P22) -> 45000000
A22: lgh_other_assets | B22: [WC] Balance Sheet | C22: [L4] | D22: 0 | E22: =+registry!C79 -> 0 | F22: =+registry!D79 -> 0 | G22: =+registry!E79 -> 0 | H22: =+registry!F79 -> 0 | I22: =+registry!G79 -> 0 | J22: =+registry!H79 -> 0 | K22: =+registry!I79 -> 0 | L22: =+registry!J79 -> 0 | ... P22: =+registry!N79 -> 45000000
C23: =+C24 -> PV Loren fees (Key money) | D23: 20000000 | E23: =SUM(E24) -> 20000000 | F23: =SUM(F24) -> 20000000 | G23: =SUM(G24) -> 20000000 | H23: =SUM(H24) -> 20000000 | I23: =SUM(I24) -> 20600000 | J23: =SUM(J24) -> 21218000 | K23: =SUM(K24) -> 26854540 | L23: =SUM(L24) -> 27660176 | ... P23: =SUM(P24) -> 41436272
A24: c12_hm_oc | B24: PV Loren fees (Key money) | C24: PV Loren fees (Key money) | D24: 20000000 | E24: =+registry!C49 -> 20000000 | F24: =+registry!D49 -> 20000000 | G24: =+registry!E49 -> 20000000 | H24: =+registry!F49 -> 20000000 | I24: =+registry!G49 -> 20600000 | J24: =+registry!H49 -> 21218000 | K24: =+registry!I49 -> 26854540 | L24: =+registry!J49 -> 27660176 | ... P24: =+registry!N49 -> 41436272
C25: Other | D25: 3570254 | E25: =SUM(E26:E26) -> 4252788.9 | F25: =SUM(F26:F26) -> 5986171.9 | G25: =SUM(G26:G26) -> 4752346.8 | H25: =SUM(H26:H26) -> 4042423.2 | I25: =SUM(I26:I26) -> 3150709 | J25: =SUM(J26:J26) -> 3175738.3 | K25: =SUM(K26:K26) -> 3356358.1 | L25: =SUM(L26:L26) -> 3280322 | ... P25: =SUM(P26:P26) -> 5265898.3
A26: lgh_other_assets | B26: Balance | C26: Other Assets | D26: 3570254 | E26: =+registry!C77 -> 4252788.9 | F26: =+registry!D77 -> 5986171.9 | G26: =+registry!E77 -> 4752346.8 | H26: =+registry!F77 -> 4042423.2 | I26: =+registry!G77 -> 3150709 | J26: =+registry!H77 -> 3175738.3 | K26: =+registry!I77 -> 3356358.1 | L26: =+registry!J77 -> 3280322 | ... P26: =+registry!N77 -> 5265898.3
C27: Total assets incl. Cash | D27: 1.4597233e+08 | E27: =SUM(E5,E6,E8,E13,E15,E17,E19,E21,E23,E25) -> 1.6648123e+08 | F27: =SUM(F5,F6,F8,F13,F15,F17,F19,F21,F23,F25) -> 1.7226815e+08 | G27: =SUM(G5,G6,G8,G13,G15,G17,G19,G21,G23,G25) -> 1.7509039e+08 | H27: =SUM(H5,H6,H8,H13,H15,H17,H19,H21,H23,H25) -> 1.6869939e+08 | I27: =SUM(I5,I6,I8,I13,I15,I17,I19,I21,I23,I25) -> 1.741182e+08 | J27: =SUM(J5,J6,J8,J13,J15,J17,J19,J21,J23,J25) -> 1.8728828e+08 | K27: =SUM(K5,K6,K8,K13,K15,K17,K19,K21,K23,K25) -> 1.9643103e+08 | L27: =SUM(L5,L6,L8,L13,L15,L17,L19,L21,L23,L25) -> 2.1667755e+08 | ... P27: =SUM(P5,P6,P8,P13,P15,P17,P19,P21,P23,P25) -> 4.1559593e+08
C28: Liabilities
A29: lgh_debt | B29: Balance: Principal and interest | C29: LGH Debt | D29: 25387077 | E29: =+registry!C66 -> 29007182 | F29: =+registry!D66 -> 30149897 | G29: =+registry!E66 -> 9136912.2 | H29: =+registry!F66 -> 8575632.5 | I29: =+registry!G66 -> 7900128.8 | J29: =+registry!H66 -> 12239223 | K29: =+registry!I66 -> 12195992 | L29: =+registry!J66 -> 7400513.4 | ... P29: =+registry!N66 -> 0
A30: lgh_other_assets | B30: Total Capital Raised Other Projects | C30: Other Project Capital needs | D30: 0 | E30: =+registry!C91 -> 0 | F30: =+registry!D91 -> 0 | G30: =+registry!E91 -> 0 | H30: =+registry!F91 -> 0 | I30: =+registry!G91 -> 0 | J30: =+registry!H91 -> 0 | K30: =+registry!I91 -> 0 | L30: =+registry!J91 -> 0 | ... P30: =+registry!N91 -> 0
A31: lgh_other_liabs | B31: balance | C31: LGH other | D31: 812241.1 | E31: =+registry!C71 -> 3383115.8 | F31: =+registry!D71 -> 5020671.4 | G31: =+registry!E71 -> 5081889.2 | H31: =+registry!F71 -> 6989833.7 | I31: =+registry!G71 -> 8001344.4 | J31: =+registry!H71 -> 8575801.2 | K31: =+registry!I71 -> 8582691.7 | L31: =+registry!J71 -> 17286474 | ... P31: =+registry!N71 -> 27995423
C32: Total Liabilities | D32: 26199318 | E32: =SUM(E29:E31) -> 32390298 | F32: =SUM(F29:F31) -> 35170568 | G32: =SUM(G29:G31) -> 14218801 | H32: =SUM(H29:H31) -> 15565466 | I32: =SUM(I29:I31) -> 15901473 | J32: =SUM(J29:J31) -> 20815024 | K32: =SUM(K29:K31) -> 20778684 | L32: =SUM(L29:L31) -> 24686988 | ... P32: =SUM(P29:P31) -> 27995423
C33: Net Asset Value (NAV) | D33: 1.1977301e+08 | E33: =+E27-E32 -> 1.3409093e+08 | F33: =+F27-F32 -> 1.3709758e+08 | G33: =+G27-G32 -> 1.6087159e+08 | H33: =+H27-H32 -> 1.5313392e+08 | I33: =+I27-I32 -> 1.5821673e+08 | J33: =+J27-J32 -> 1.6647326e+08 | K33: =+K27-K32 -> 1.7565234e+08 | L33: =+L27-L32 -> 1.9199056e+08 | ... P33: =+P27-P32 -> 3.8760051e+08
C34: Shareholders' Equity
A35: lgh_ci | B35: total | C35: Carried Interest | D35: 0 | E35: =+registry!C86 -> 0 | F35: =+registry!D86 -> 0 | G35: =+registry!E86 -> 3805056.4 | H35: =+registry!F86 -> 1096872.2 | I35: =+registry!G86 -> 2875854.6 | J35: =+registry!H86 -> 5765639.9 | K35: =+registry!I86 -> 8978320.2 | L35: =+registry!J86 -> 14696697 | ... P35: =+registry!N86 -> 83160179
A36: lgh_pref | B36: balance | C36: Preferred Equity | D36: 51080209 | E36: =+registry!C62 -> 49890886 | F36: =+registry!D62 -> 50888704 | G36: =+registry!E62 -> 51906478 | H36: =+registry!F62 -> 54144869 | I36: =+registry!G62 -> 56742198 | J36: =+registry!H62 -> 58896376 | K36: =+registry!I62 -> 60074303 | L36: =+registry!J62 -> 64275789 | ... P36: =+registry!N62 -> 87446502
A37: cuda | B37: Distribution (cuda for pref) | C37: CUDA | D37: -6000000 | E37: =-registry!C94 -> 6050000 | F37: =-registry!D94 -> 0 | G37: =-registry!E94 -> 0 | H37: =-registry!F94 -> 0 | I37: =-registry!G94 -> 0 | J37: =-registry!H94 -> 0 | K37: =-registry!I94 -> 0 | L37: =-registry!J94 -> 0 | ... P37: =-registry!N94 -> 0
C38: Common Equity | D38: 74692801 | E38: =+E33-E35-E36-E37 -> 78150044 | F38: =+F33-F35-F36-F37 -> 86208873 | G38: =+G33-G35-G36-G37 -> 1.0516006e+08 | H38: =+H33-H35-H36-H37 -> 97892179 | I38: =+I33-I35-I36-I37 -> 98598675 | J38: =+J33-J35-J36-J37 -> 1.0181124e+08 | K38: =+K33-K35-K36-K37 -> 1.0659972e+08 | L38: =+L33-L35-L36-L37 -> 1.1301808e+08 | ... P38: =+P33-P35-P36-P37 -> 2.1699383e+08
C39: Total Shareholder's Equity | D39: 1.1977301e+08 | E39: =SUM(E35:E38) -> 1.3409093e+08 | F39: =SUM(F35:F38) -> 1.3709758e+08 | G39: =SUM(G35:G38) -> 1.6087159e+08 | H39: =SUM(H35:H38) -> 1.5313392e+08 | I39: =SUM(I35:I38) -> 1.5821673e+08 | J39: =SUM(J35:J38) -> 1.6647326e+08 | K39: =SUM(K35:K38) -> 1.7565234e+08 | L39: =SUM(L35:L38) -> 1.9199056e+08 | ... P39: =SUM(P35:P38) -> 3.8760051e+08
A40: Austin Lady Bird Lake | B40: Pref Liquidation adj. | C40: Austin Pref Liquidation adj. | D40: 0 | E40: =+registry!C16 -> 0 | F40: =+registry!D16 -> 0 | G40: =+registry!E16 -> 0 | H40: =+registry!F16 -> -4196895.7 | I40: =+registry!G16 -> -4334704.6 | J40: =+registry!H16 -> -4478646.1 | K40: =+registry!I16 -> -4629028.8 | L40: =+registry!J16 -> -4784461.1 | ... P40: =+registry!N16 -> 0
A41: Austin Lady Bird Lake | B41: Equity Liquidation adj. | C41: Austin Equity Liquidation adj. | D41: 0 | E41: =+registry!C17 -> 0 | F41: =+registry!D17 -> 0 | G41: =+registry!E17 -> 0 | H41: =+registry!F17 -> -7753407.4 | I41: =+registry!G17 -> -6038275.4 | J41: =+registry!H17 -> -4849926.1 | K41: =+registry!I17 -> -3974250.2 | L41: =+registry!J17 -> -3116853.8 | ... P41: =+registry!N17 -> 0
A42: c12_hm_oc | B42: Enterprise value | C42: Enterprise value Loren | D42: 10000000 | E42: =+registry!C50 -> 10000000 | F42: =+registry!D50 -> 10000000 | G42: =+registry!E50 -> 10000000 | H42: =+registry!F50 -> 10000000 | I42: =+registry!G50 -> 10300000 | J42: =+registry!H50 -> 12730800 | K42: =+registry!I50 -> 18798178 | L42: =+registry!J50 -> 22128141 | ... P42: =+registry!N50 -> 82872544
A43: c12_hm_oc | B43: Other EV | C43: Other EV Value | D43: 0 | E43: =+registry!C51 -> 0 | F43: =+registry!D51 -> 0 | G43: =+registry!E51 -> 0 | H43: =+registry!F51 -> 0 | I43: =+registry!G51 -> 0 | J43: =+registry!H51 -> 0 | K43: =+registry!I51 -> 0 | L43: =+registry!J51 -> 0 | ... P43: =+registry!N51 -> 100000000
C44: Adjusted NAV | D44: 1.2977301e+08 | E44: =SUM(E39:E43) -> 1.4409093e+08 | F44: =SUM(F39:F43) -> 1.4709758e+08 | G44: =SUM(G39:G43) -> 1.7087159e+08 | H44: =SUM(H39:H43) -> 1.5118362e+08 | I44: =SUM(I39:I43) -> 1.5814375e+08 | J44: =SUM(J39:J43) -> 1.6987548e+08 | K44: =SUM(K39:K43) -> 1.8584724e+08 | L44: =SUM(L39:L43) -> 2.0621739e+08 | ... P44: =SUM(P39:P43) -> 5.7047306e+08
C45: Add. Carried Interest Val. | D45: 0 | E45: =+registry!C87 -> 0 | F45: =+registry!D87 -> 0 | G45: =+registry!E87 -> 3500000 | H45: =+registry!F87 -> -682606.09 | I45: =+registry!G87 -> -25542.995 | J45: =+registry!H87 -> 1190779.7 | K45: =+registry!I87 -> 3568214.6 | L45: =+registry!J87 -> 4979389.1 | ... P45: =+registry!N87 -> 64005390
C46: LGH Pref MTM | D46: 17817146 | E46: =+E36*(1-((1+lgh_pref_equity!$C$49)/(1+lgh_inputs!$D$6))^(($P$2-E2)/365)) -> 9423344.8 | F46: =+F36*(1-((1+lgh_pref_equity!$C$49)/(1+lgh_inputs!$D$6))^(($P$2-F2)/365)) -> 9235852.2 | G46: =+G36*(1-((1+lgh_pref_equity!$C$49)/(1+lgh_inputs!$D$6))^(($P$2-G2)/365)) -> 9029325.8 | H46: =+H36*(1-((1+lgh_pref_equity!$C$49)/(1+lgh_inputs!$D$6))^(($P$2-H2)/365)) -> 9006828.7 | I46: =+I36*(1-((1+lgh_pref_equity!$C$49)/(1+lgh_inputs!$D$6))^(($P$2-I2)/365)) -> 9012792.6 | J46: =+J36*(1-((1+lgh_pref_equity!$C$49)/(1+lgh_inputs!$D$6))^(($P$2-J2)/365)) -> 8903722.3 | K46: =+K36*(1-((1+lgh_pref_equity!$C$49)/(1+lgh_inputs!$D$6))^(($P$2-K2)/365)) -> 8612217.9 | L46: =+L36*(1-((1+lgh_pref_equity!$C$49)/(1+lgh_inputs!$D$6))^(($P$2-L2)/365)) -> 8707493.5 | ... P46: =+P36*(1-((1+lgh_pref_equity!$C$49)/(1+lgh_inputs!$D$6))^(($P$2-P2)/365)) -> 0
C47: Pref participation | D47: 43497765 | E47: =+lgh_pref_equity!C184 -> 49728070 | F47: =+lgh_pref_equity!D184 -> 13405097 | G47: =+lgh_pref_equity!E184 -> 15679493 | H47: =+lgh_pref_equity!F184 -> 14925334 | I47: =+lgh_pref_equity!G184 -> 15840009 | J47: =+lgh_pref_equity!H184 -> 16666619 | K47: =+lgh_pref_equity!I184 -> 17585591 | L47: =+lgh_pref_equity!J184 -> 19221307 | ... P47: =+lgh_pref_equity!N184 -> 38804972
C48: CUDA | D48: -6000000 | E48: =+E37 -> 6050000 | F48: =+F37 -> 0 | G48: =+G37 -> 0 | H48: =+H37 -> 0 | I48: =+I37 -> 0 | J48: =+J37 -> 0 | K48: =+K37 -> 0 | L48: =+L37 -> 0 | ... P48: =+P37 -> 0
C49: Adj. Pref | D49: 33263063 | E49: =+E36-E46 -> 40467542 | F49: =+F36-F46 -> 41652852 | G49: =+G36-G46 -> 42877152 | H49: =+H36-H46 -> 45138040 | I49: =+I36-I46 -> 47729405 | J49: =+J36-J46 -> 49992654 | K49: =+K36-K46 -> 51462086 | L49: =+L36-L46 -> 55568296 | ... P49: =+P36-P46 -> 87446502
C50: Adj. CI | D50: 0 | E50: =+E35+E45 -> 0 | F50: =+F35+F45 -> 0 | G50: =+G35+G45 -> 7305056.4 | H50: =+H35+H45 -> 414266.07 | I50: =+I35+I45 -> 2850311.6 | J50: =+J35+J45 -> 6956419.6 | K50: =+K35+K45 -> 12546535 | L50: =+L35+L45 -> 19676086 | ... P50: =+P35+P45 -> 1.4716557e+08
C51: Adj. Common Equity | D51: 1.0250995e+08 | E51: =E38+SUM(E40:E43)+E46-E45 -> 97573389 | F51: =F38+SUM(F40:F43)+F46-F45 -> 1.0544472e+08 | G51: =G38+SUM(G40:G43)+G46-G45 -> 1.2068938e+08 | H51: =H38+SUM(H40:H43)+H46-H45 -> 1.0563131e+08 | I51: =I38+SUM(I40:I43)+I46-I45 -> 1.0756403e+08 | J51: =J38+SUM(J40:J43)+J46-J45 -> 1.1292641e+08 | K51: =K38+SUM(K40:K43)+K46-K45 -> 1.2183862e+08 | L51: =L38+SUM(L40:L43)+L46-L45 -> 1.3097301e+08 | ... P51: =P38+SUM(P40:P43)+P46-P45 -> 3.3586098e+08
C52: Adjusted Shareholder's Equity | D52: 1.2977301e+08 | E52: =SUM(E48:E51) -> 1.4409093e+08 | F52: =SUM(F48:F51) -> 1.4709758e+08 | G52: =SUM(G48:G51) -> 1.7087159e+08 | H52: =SUM(H48:H51) -> 1.5118362e+08 | I52: =SUM(I48:I51) -> 1.5814375e+08 | J52: =SUM(J48:J51) -> 1.6987548e+08 | K52: =SUM(K48:K51) -> 1.8584724e+08 | L52: =SUM(L48:L51) -> 2.0621739e+08 | ... P52: =SUM(P48:P51) -> 5.7047306e+08
C53: Adj. Unlevered Equity | D53: 1.2977301e+08 | H53: =+H52-H50 -> 1.5076935e+08 | I53: =+I52-I50 -> 1.5529344e+08 | J53: =+J52-J50 -> 1.6291907e+08 | K53: =+K52-K50 -> 1.7330071e+08 | L53: =+L52-L50 -> 1.865413e+08 | M53: =+M52-M50 -> 2.1695102e+08 | N53: =+N52-N50 -> 2.7772759e+08 | O53: =+O52-O50 -> 3.3902943e+08 | P53: =+P52-P50 -> 4.2330749e+08

Sheet lgh_bs_errata

Sheet lgh_bs_qr

Sheet lgh_ci
A1: {=_xlfn.TEXTAFTER(CELL("filename",A1),"]")} -> lgh_ci
A2: Year | B2: 45657 | C2: =+lgh_bs!E2 -> 45747 | D2: =+lgh_bs!F2 -> 45838 | E2: =+lgh_bs!G2 -> 45930 | F2: =+lgh_bs!H2 -> 46022 | G2: =+lgh_bs!I2 -> 46112 | H2: =+lgh_bs!J2 -> 46203 | I2: =+lgh_bs!K2 -> 46295 | J2: =+lgh_bs!L2 -> 46387 | ... N2: =+lgh_bs!P2 -> 47848
A3: Period | B3: Q4 | C3: =+lgh_bs!E3 -> Q1 | D3: =+lgh_bs!F3 -> Q2 | E3: =+lgh_bs!G3 -> Q3 | F3: =+lgh_bs!H3 -> Q4 | G3: =+lgh_bs!I3 -> Q1 | H3: =+lgh_bs!J3 -> Q2 | I3: =+lgh_bs!K3 -> Q3 | J3: =+lgh_bs!L3 -> Q4 | ... N3: =+lgh_bs!P3 -> Q4
A4: NAV | B4: 1.1977301e+08 | C4: =+lgh_bs!E33 -> 1.3409093e+08 | D4: =+lgh_bs!F33 -> 1.3709758e+08 | E4: =+lgh_bs!G33 -> 1.6087159e+08 | F4: =+lgh_bs!H33 -> 1.5313392e+08 | G4: =+lgh_bs!I33 -> 1.5821673e+08 | H4: =+lgh_bs!J33 -> 1.6647326e+08 | I4: =+lgh_bs!K33 -> 1.7565234e+08 | J4: =+lgh_bs!L33 -> 1.9199056e+08 | ... N4: =+lgh_bs!P33 -> 3.8760051e+08
A5: adjusted NAV | B5: 1.2977301e+08 | C5: =lgh_bs!E44 -> 1.4409093e+08 | D5: =lgh_bs!F44 -> 1.4709758e+08 | E5: =lgh_bs!G44 -> 1.7087159e+08 | F5: =lgh_bs!H44 -> 1.5118362e+08 | G5: =lgh_bs!I44 -> 1.5814375e+08 | H5: =lgh_bs!J44 -> 1.6987548e+08 | I5: =lgh_bs!K44 -> 1.8584724e+08 | J5: =lgh_bs!L44 -> 2.0621739e+08 | ... N5: =lgh_bs!P44 -> 5.7047306e+08
A7: Common carried interest
B8: 0 | C8: =+lgh_inputs!$D$4 -> 0.35 | D8: =+lgh_inputs!$D$4 -> 0.35 | E8: =+lgh_inputs!$D$4 -> 0.35 | F8: =+lgh_inputs!$D$4 -> 0.35 | G8: =+lgh_inputs!$D$4 -> 0.35 | H8: =+lgh_inputs!$D$4 -> 0.35 | I8: =+lgh_inputs!$D$4 -> 0.35 | J8: =+lgh_inputs!$D$4 -> 0.35 | ... N8: =+lgh_inputs!$D$4 -> 0.35
A9: 150000000 | B9: 150000000 | C9: =$A9 -> 150000000 | D9: =$A9 -> 150000000 | E9: =$A9 -> 150000000 | F9: =$A9 -> 150000000 | G9: =$A9 -> 150000000 | H9: =$A9 -> 150000000 | I9: =$A9 -> 150000000 | J9: =$A9 -> 150000000 | ... N9: =$A9 -> 150000000
B10: 0 | C10: =MAX((C$4-C9)*C8,0) -> 0 | D10: =MAX((D$4-D9)*D8,0) -> 0 | E10: =MAX((E$4-E9)*E8,0) -> 3805056.4 | F10: =MAX((F$4-F9)*F8,0) -> 1096872.2 | G10: =MAX((G$4-G9)*G8,0) -> 2875854.6 | H10: =MAX((H$4-H9)*H8,0) -> 5765639.9 | I10: =MAX((I$4-I9)*I8,0) -> 8978320.2 | J10: =MAX((J$4-J9)*J8,0) -> 14696697 | ... N10: =MAX((N$4-N9)*N8,0) -> 83160179
A11: total | B11: 0 | C11: =+C10 -> 0 | D11: =+D10 -> 0 | E11: =+E10 -> 3805056.4 | F11: =+F10 -> 1096872.2 | G11: =+G10 -> 2875854.6 | H11: =+H10 -> 5765639.9 | I11: =+I10 -> 8978320.2 | J11: =+J10 -> 14696697 | ... N11: =+N10 -> 83160179
A12: Additional CI Val.
B13: 0 | C13: =+lgh_inputs!$D$4 -> 0.35 | D13: =+lgh_inputs!$D$4 -> 0.35 | E13: =+lgh_inputs!$D$4 -> 0.35 | F13: =+lgh_inputs!$D$4 -> 0.35 | G13: =+lgh_inputs!$D$4 -> 0.35 | H13: =+lgh_inputs!$D$4 -> 0.35 | I13: =+lgh_inputs!$D$4 -> 0.35 | J13: =+lgh_inputs!$D$4 -> 0.35 | ... N13: =+lgh_inputs!$D$4 -> 0.35
A14: 150000000 | B14: 150000000 | C14: =$A14 -> 150000000 | D14: =$A14 -> 150000000 | E14: =$A14 -> 150000000 | F14: =$A14 -> 150000000 | G14: =$A14 -> 150000000 | H14: =$A14 -> 150000000 | I14: =$A14 -> 150000000 | J14: =$A14 -> 150000000 | ... N14: =$A14 -> 150000000
B15: 0 | C15: =MAX((C$5-C14)*C13,0)-C10 -> 0 | D15: =MAX((D$5-D14)*D13,0)-D10 -> 0 | E15: =MAX((E$5-E14)*E13,0)-E10 -> 3500000 | F15: =MAX((F$5-F14)*F13,0)-F10 -> -682606.09 | G15: =MAX((G$5-G14)*G13,0)-G10 -> -25542.995 | H15: =MAX((H$5-H14)*H13,0)-H10 -> 1190779.7 | I15: =MAX((I$5-I14)*I13,0)-I10 -> 3568214.6 | J15: =MAX((J$5-J14)*J13,0)-J10 -> 4979389.1 | ... N15: =MAX((N$5-N14)*N13,0)-N10 -> 64005390

Sheet lgh_oc
A1: {=_xlfn.TEXTAFTER(CELL("filename",A1),"]")} -> lgh_oc
A2: Year | B2: 45657 | C2: =+lgh_bs!E2 -> 45747 | D2: =+lgh_bs!F2 -> 45838 | E2: =+lgh_bs!G2 -> 45930 | F2: =+lgh_bs!H2 -> 46022 | G2: =+lgh_bs!I2 -> 46112 | H2: =+lgh_bs!J2 -> 46203 | I2: =+lgh_bs!K2 -> 46295 | J2: =+lgh_bs!L2 -> 46387 | ... N2: =+lgh_bs!P2 -> 47848
A3: Period | B3: Q4 | C3: =+lgh_bs!E3 -> Q1 | D3: =+lgh_bs!F3 -> Q2 | E3: =+lgh_bs!G3 -> Q3 | F3: =+lgh_bs!H3 -> Q4 | G3: =+lgh_bs!I3 -> Q1 | H3: =+lgh_bs!J3 -> Q2 | I3: =+lgh_bs!K3 -> Q3 | J3: =+lgh_bs!L3 -> Q4 | ... N3: =+lgh_bs!P3 -> Q4
A4: fee, service, and charge backs
A5: Total Revenue | B5: =registry!B59 -> 0 | C5: =registry!C59 -> 995387.76 | D5: =registry!D59 -> 995387.76 | E5: =registry!E59 -> 1630966.7 | F5: =registry!F59 -> 2037948.3 | G5: =registry!G59 -> 2200269.7 | H5: =registry!H59 -> 3530751.8 | I5: =registry!I59 -> 3421728.7 | ... N5: =registry!N59 -> 13901367
A7: Other Income
A8: Art Leases | B8: 0 | C8: 50000 | D8: 50000 | E8: 50000 | F8: 50000 | G8: 50000 | H8: 50000 | I8: 50000 | J8: 50000 | K8: 250000 | L8: 250000 | M8: 250000 | N8: 250000
A9: Total Other Income | B9: 0 | C9: =SUM(C8:C8) -> 50000 | D9: =SUM(D8:D8) -> 50000 | E9: =SUM(E8:E8) -> 50000 | F9: =SUM(F8:F8) -> 50000 | G9: =SUM(G8:G8) -> 50000 | H9: =SUM(H8:H8) -> 50000 | I9: =SUM(I8:I8) -> 50000 | J9: =SUM(J8:J8) -> 50000 | ... N9: =SUM(N8:N8) -> 250000
A11: total lgh operating revenue | B11: =B9+B5 -> 0 | C11: =C9+C5 -> 1045387.8 | D11: =D9+D5 -> 1045387.8 | E11: =E9+E5 -> 1680966.7 | F11: =F9+F5 -> 2087948.3 | G11: =G9+G5 -> 2250269.7 | H11: =H9+H5 -> 3580751.8 | I11: =I9+I5 -> 3471728.7 | ... N11: =N9+N5 -> 14151367
A13: C12 Participation Expense
A14: Total C12 Participation (inc 5% for c/bs) | B14: =-registry!B58 -> -2452451 | C14: =-registry!C58 -> -638700.01 | D14: =-registry!D58 -> -638700.01 | E14: =-registry!E58 -> -927158.96 | F14: =-registry!F58 -> -937170.54 | G14: =-registry!G58 -> -886331.48 | H14: =-registry!H58 -> -1430293.5 | I14: =-registry!I58 -> -1358160.9 | ... N14: =-registry!N58 -> -3977928.6
A16: Total c12 Operating Expenses | B16: =+registry!B95 -> -5450569 | C16: =+registry!C95 -> -1262185 | D16: =+registry!D95 -> -1358476 | E16: =+registry!E95 -> -1319123 | F16: =+registry!F95 -> -2542272 | G16: =+registry!G95 -> -4057848.9 | H16: =+registry!H95 -> -4457406 | I16: =+registry!I95 -> -2834606 | ... N16: =+registry!N95 -> -12445130
A18: Total LGH Expenses | B18: -8570520 | C18: =+C14+C16 -> -1900885 | D18: =+D14+D16 -> -1997176 | E18: =+E14+E16 -> -2246282 | F18: =+F14+F16 -> -3479442.5 | G18: =+G14+G16 -> -4944180.3 | H18: =+H14+H16 -> -5887699.5 | I18: =+I14+I16 -> -4192766.9 | J18: =+J14+J16 -> -7829289.6 | ... N18: =+N14+N16 -> -16423059
A20: Total LGH Operating Profit | B20: =+B11+B18+B23 -> -8570520 | C20: =+C11+C18+C23 -> -855497.25 | D20: =+D11+D18+D23 -> -951788.25 | E20: =+E11+E18+E23 -> -565315.25 | F20: =+F11+F18+F23 -> -1391494.3 | G20: =+G11+G18+G23 -> -2693910.7 | H20: =+H11+H18+H23 -> -2306947.6 | I20: =+I11+I18+I23 -> -721038.15 | ... N20: =+N11+N18+N23 -> -2271691.4
A21: LGH opprofit / bs-1 | F21: =-SUM(C20:F20)/lgh_bs!H44 -> 0.024897506 | J21: =-SUM(G20:J20)/lgh_bs!L44 -> 0.019040829 | K21: =-K20/lgh_bs!M44 -> -0.0086507582 | L21: =-L20/lgh_bs!N44 -> 0.0028966932 | M21: =-M20/lgh_bs!O44 -> -0.004771546 | N21: =-N20/lgh_bs!P44 -> 0.0039821187
A23: Guarantee Fees Received | B23: 0 | C23: =+registry!C43 -> 0 | D23: =+registry!D43 -> 0 | E23: =+registry!E43 -> 0 | F23: =+registry!F43 -> 0 | G23: =+registry!G43 -> 0 | H23: =+registry!H43 -> 0 | I23: =+registry!I43 -> 0 | J23: =+registry!J43 -> 1000000 | ... N23: =+registry!N43 -> 0 | O23: need to be reflected in cs2s
A24: Guarentee Fees accrued cumm (PIK) | B24: =+registry!B96 -> 0 | C24: =+registry!C96 -> 350000 | D24: =+registry!D96 -> 700000 | E24: =+registry!E96 -> 1050000 | F24: =+registry!F96 -> 1600000 | G24: =+registry!G96 -> 2150000 | H24: =+registry!H96 -> 2700000 | I24: =+registry!I96 -> 3250000 | ... N24: =+registry!N96 -> 1900000
A25: Guarentee Fees Expense | B25: 0 | C25: -250000 | D25: -250000 | E25: -250000 | F25: -250000 | G25: -250000 | H25: -250000 | I25: -250000 | J25: -250000 | K25: -1000000 | L25: -1000000 | M25: -1000000 | N25: -1000000
A26: net guarantee fees | B26: =B23+B25 -> 0 | C26: =C23+C25 -> -250000 | D26: =D23+D25 -> -250000 | E26: =E23+E25 -> -250000 | F26: =F23+F25 -> -250000 | G26: =G23+G25 -> -250000 | H26: =H23+H25 -> -250000 | I26: =I23+I25 -> -250000 | ... N26: =N23+N25 -> -1000000
A28: Cash Flow from Properties
A29: Sources/In
A30: Bermuda PB | B30: 1562074 | C30: =+registry!C5 -> 3250000 | D30: =+registry!D5 -> 3388588 | E30: =+registry!E5 -> 1475962 | F30: =+registry!F5 -> 8336733 | G30: =+registry!G5 -> 0 | H30: =+registry!H5 -> 0 | I30: =+registry!I5 -> 0 | J30: =+registry!J5 -> 0 | ... N30: =+registry!N5 -> 4123684
A31: Austin | B31: 814451.63 | C31: =+registry!C10 -> 5515000 | D31: =+registry!D10 -> 0 | E31: =+registry!E10 -> 525000 | F31: =+registry!F10 -> 0 | G31: =+registry!G10 -> 0 | H31: =+registry!H10 -> 0 | I31: =+registry!I10 -> 0 | J31: =+registry!J10 -> 0 | ... N31: =+registry!N10 -> 0
A32: Turks | B32: 0 | C32: =+registry!C21 -> 0 | D32: =+registry!D21 -> 0 | E32: =+registry!E21 -> 0 | F32: =+registry!F21 -> 350000 | G32: =+registry!G21 -> 0 | H32: =+registry!H21 -> 350000 | I32: =+registry!I21 -> 0 | J32: =+registry!J21 -> 0 | ... N32: =+registry!N21 -> 1371287
A33: Frithholme | B33: 0 | C33: =+registry!C26 -> 0 | D33: =+registry!D26 -> 0 | E33: =+registry!E26 -> 0 | F33: =+registry!F26 -> 0 | G33: =+registry!G26 -> 2400000 | H33: =+registry!H26 -> 3600000 | I33: =+registry!I26 -> 0 | J33: =+registry!J26 -> 16900000 | ... N33: =+registry!N26 -> 0
A34: SAT | B34: =registry!B36 -> 0 | C34: =registry!C36 -> 0 | D34: =registry!D36 -> 0 | E34: =registry!E36 -> 0 | F34: =registry!F36 -> 0 | G34: =registry!G36 -> 0 | H34: =registry!H36 -> 0 | I34: =registry!I36 -> 0 | ... N34: =registry!N36 -> 1750000
A35: Bermuda Elbow | B35: 0 | C35: =+registry!C31 -> 0 | D35: =+registry!D31 -> 2500000 | E35: =+registry!E31 -> 2500000 | F35: =+registry!F31 -> 6137500 | G35: =+registry!G31 -> 5640000 | H35: =+registry!H31 -> 7300000 | I35: =+registry!I31 -> 0 | J35: =+registry!J31 -> 0 | ... N35: =+registry!N31 -> 0
A36: Total Sources | B36: 2376525.6 | C36: =SUM(C30:C35) -> 8765000 | D36: =SUM(D30:D35) -> 5888588 | E36: =SUM(E30:E35) -> 4500962 | F36: =SUM(F30:F35) -> 14824233 | G36: =SUM(G30:G35) -> 8040000 | H36: =SUM(H30:H35) -> 11250000 | I36: =SUM(I30:I35) -> 0 | J36: =SUM(J30:J35) -> 16900000 | ... N36: =SUM(N30:N35) -> 7244971
A37: Uses/out
A38: Bermuda PB | B38: 0 | C38: =+registry!C6 -> -125000 | D38: =+registry!D6 -> -3717883 | E38: =+registry!E6 -> -3472013.3 | F38: =+registry!F6 -> 0 | G38: =+registry!G6 -> 0 | H38: =+registry!H6 -> 0 | I38: =+registry!I6 -> 0 | J38: =+registry!J6 -> -4604401.2 | ... N38: =+registry!N6 -> 0
A39: Austin | B39: 0 | C39: =+registry!C11 -> -50000 | D39: =+registry!D11 -> -2025000 | E39: =+registry!E11 -> -230000 | F39: =+registry!F11 -> -289495 | G39: =+registry!G11 -> -1750000 | H39: =+registry!H11 -> -3420000 | I39: =+registry!I11 -> 0 | J39: =+registry!J11 -> -750000 | ... N39: =+registry!N11 -> 0
A40: Turks | B40: 0 | C40: =+registry!C22 -> -382967 | D40: =+registry!D22 -> -2326328 | E40: =+registry!E22 -> -3292886 | F40: =+registry!F22 -> -5106622 | G40: =+registry!G22 -> -420000 | H40: =+registry!H22 -> -200000 | I40: =+registry!I22 -> -150000 | J40: =+registry!J22 -> -550000 | ... N40: =+registry!N22 -> 0
A41: Frithholme | B41: 0 | C41: =+registry!C27 -> 0 | D41: =+registry!D27 -> 0 | E41: =+registry!E27 -> 0 | F41: =+registry!F27 -> -860000 | G41: =+registry!G27 -> 0 | H41: =+registry!H27 -> -1750000 | I41: =+registry!I27 -> 0 | J41: =+registry!J27 -> 0 | ... N41: =+registry!N27 -> 0
A42: SAT | B42: =registry!B37 -> 0 | C42: =registry!C37 -> 0 | D42: =registry!D37 -> 0 | E42: =registry!E37 -> 0 | F42: =registry!F37 -> 0 | G42: =registry!G37 -> 0 | H42: =registry!H37 -> 0 | I42: =registry!I37 -> 0 | ... N42: =registry!N37 -> 0
A43: Bermuda Elbow | B43: 0 | C43: =+registry!C32 -> -2500000 | D43: =+registry!D32 -> 0 | E43: =+registry!E32 -> 0 | F43: =+registry!F32 -> 0 | G43: =+registry!G32 -> -1000000 | H43: =+registry!H32 -> -2040000 | I43: =+registry!I32 -> -2000000 | J43: =+registry!J32 -> -8250000 | ... N43: =+registry!N32 -> 0
A44: Total Uses | B44: 0 | C44: =SUM(C38:C43) -> -3057967 | D44: =SUM(D38:D43) -> -8069211 | E44: =SUM(E38:E43) -> -6994899.3 | F44: =SUM(F38:F43) -> -6256117 | G44: =SUM(G38:G43) -> -3170000 | H44: =SUM(H38:H43) -> -7410000 | I44: =SUM(I38:I43) -> -2150000 | J44: =SUM(J38:J43) -> -30154401 | ... N44: =SUM(N38:N43) -> 0
A46: Total CF from Property Distributions | B46: 2376525.6 | C46: =+C36+C44 -> 5707033 | D46: =+D36+D44 -> -2180623 | E46: =+E36+E44 -> -2493937.3 | F46: =+F36+F44 -> 8568116 | G46: =+G36+G44 -> 4870000 | H46: =+H36+H44 -> 3840000 | I46: =+I36+I44 -> -2150000 | J46: =+J36+J44 -> -13254401 | ... N46: =+N36+N44 -> 7244971
A48: LGH DEPO Cash Flow
A50: Sources/In
A51: lgh equity | B51: 0 | C51: =+registry!C97 -> 0 | D51: =+registry!D97 -> 23600000 | E51: =+registry!E97 -> 200000 | F51: =+registry!F97 -> 0 | G51: =+registry!G97 -> 0 | H51: =+registry!H97 -> 0 | I51: =+registry!I97 -> 0 | J51: =+registry!J97 -> 0 | ... N51: =+registry!N97 -> 0
A52: lgh pref | B52: 0 | C52: =+registry!C63 -> 6050000 | D52: =+registry!D63 -> 0 | E52: =+registry!E63 -> 0 | F52: =+registry!F63 -> 1200000 | G52: =+registry!G63 -> 1500000 | H52: =+registry!H63 -> 1000000 | I52: =+registry!I63 -> 0 | J52: =+registry!J63 -> 3000000 | ... N52: =+registry!N63 -> 0
A53: lgh debt | B53: 23600000 | C53: =+registry!C67 -> 500000 | D53: =+registry!D67 -> 100000 | E53: =+registry!E67 -> 0 | F53: =+registry!F67 -> 2250000 | G53: =+registry!G67 -> 250000 | H53: =+registry!H67 -> 4000000 | I53: =+registry!I67 -> 0 | J53: =+registry!J67 -> 0 | ... N53: =+registry!N67 -> 0
A54: lgh other | B54: 62241.1 | C54: =+registry!C72 -> -86000 | D54: =+registry!D72 -> 142999.85 | E54: =+registry!E72 -> 0 | F54: =+registry!F72 -> 1625000 | G54: =+registry!G72 -> 0 | H54: =+registry!H72 -> 0 | I54: =+registry!I72 -> 0 | J54: =+registry!J72 -> 16000000 | ... N54: =+registry!N72 -> 0
A55: CUDA | B55: 6000000 | C55: =+registry!C100 -> 0 | D55: =+registry!D100 -> 0 | E55: =+registry!E100 -> 0 | F55: =+registry!F100 -> 0 | G55: =+registry!G100 -> 0 | H55: =+registry!H100 -> 0 | I55: =+registry!I100 -> 0 | J55: =+registry!J100 -> 0 | ... N55: =+registry!N100 -> 0
A56: Total Sources | B56: 29662241 | C56: =SUM(C51:C55) -> 6464000 | D56: =SUM(D51:D55) -> 23843000 | E56: =SUM(E51:E55) -> 200000 | F56: =SUM(F51:F55) -> 5075000 | G56: =SUM(G51:G55) -> 1750000 | H56: =SUM(H51:H55) -> 5000000 | I56: =SUM(I51:I55) -> 0 | J56: =SUM(J51:J55) -> 19000000 | ... N56: =SUM(N51:N55) -> 0
A57: Uses/Out
A58: lgh equity | B58: 0 | C58: =+registry!C98 -> 0 | D58: =+registry!D98 -> -23600000 | E58: =+registry!E98 -> 0 | F58: =+registry!F98 -> 0 | G58: =+registry!G98 -> 0 | H58: =+registry!H98 -> 0 | I58: =+registry!I98 -> 0 | J58: =+registry!J98 -> 0 | ... N58: =+registry!N98 -> 0
A59: lgh debt | B59: 0 | C59: =+registry!C68 -> -2098064.7 | D59: =+registry!D68 -> 0 | E59: =+registry!E68 -> 0 | F59: =+registry!F68 -> -3200000 | G59: =+registry!G68 -> 0 | H59: =+registry!H68 -> 0 | I59: =+registry!I68 -> -517878.34 | J59: =+registry!J68 -> -5284163.4 | ... N59: =+registry!N68 -> 0
A60: lgh other | B60: 0 | C60: =+registry!C73 -> 0 | D60: =+registry!D73 -> 0 | E60: =+registry!E73 -> 0 | F60: =+registry!F73 -> -2671203.5 | G60: =+registry!G73 -> -435000 | H60: =+registry!H73 -> -1052241.1 | I60: =+registry!I73 -> 0 | J60: =+registry!J73 -> -7309780.3 | ... N60: =+registry!N73 -> 0
A61: CUDA | B61: 0 | C61: =+registry!C99 -> -6050000 | D61: =+registry!D99 -> -1200000 | E61: =+registry!E99 -> 0 | F61: =+registry!F99 -> 0 | G61: =+registry!G99 -> 0 | H61: =+registry!H99 -> 0 | I61: =+registry!I99 -> 0 | J61: =+registry!J99 -> 0 | ... N61: =+registry!N99 -> 0
A62: Total Uses | B62: 0 | C62: =SUM(C58:C61) -> -8148064.7 | D62: =SUM(D58:D61) -> -24800000 | E62: =SUM(E58:E61) -> 0 | F62: =SUM(F58:F61) -> -5871203.5 | G62: =SUM(G58:G61) -> -435000 | H62: =SUM(H58:H61) -> -1052241.1 | I62: =SUM(I58:I61) -> -517878.34 | J62: =SUM(J58:J61) -> -12593944 | ... N62: =SUM(N58:N61) -> 0
A64: Total CF from LGH DEPO | B64: 29662241 | C64: =+C56+C62 -> -1684064.7 | D64: =+D56+D62 -> -957000.15 | E64: =+E56+E62 -> 200000 | F64: =+F56+F62 -> -796203.55 | G64: =+G56+G62 -> 1315000 | H64: =+H56+H62 -> 3947758.9 | I64: =+I56+I62 -> -517878.34 | J64: =+J56+J62 -> 6406056.3 | ... N64: =+N56+N62 -> 0
A66: LGH Other Assets
A68: Total CF from Other Assets | B68: -1540999 | C68: =+registry!C101 -> -531057.56 | D68: =+registry!D101 -> 834926.44 | E68: =+registry!E101 -> 1193547.4 | F68: =+registry!F101 -> 1093901 | G68: =+registry!G101 -> 1641513.7 | H68: =+registry!H101 -> 0 | I68: =+registry!I101 -> 0 | J68: =+registry!J101 -> 0 | ... N68: =+registry!N101 -> 0
A70: LGH Cash Flow | B70: 25047199 | C70: =+C20+C26+C46+C64+C68 -> 2386413.5 | D70: =+D20+D26+D46+D64+D68 -> -3504485 | E70: =+E20+E26+E46+E64+E68 -> -1915705.1 | F70: =+F20+F26+F46+F64+F68 -> 7224319.2 | G70: =+G20+G26+G46+G64+G68 -> 4882603.1 | H70: =+H20+H26+H46+H64+H68 -> 5230811.3 | I70: =+I20+I26+I46+I64+I68 -> -3638916.5 | J70: =+J20+J26+J46+J64+J68 -> -4302998.5 | ... N70: =+N20+N26+N46+N64+N68 -> 3973279.6
A71: Bank Statement Cash Flow | B71: 251128 | F71: 421309.52
A72: yield on cash balance | G72: =F73*lgh_inputs!$D$8/4 -> 3152.322 | H72: =G73*lgh_inputs!$D$8/4 -> 39795.487 | I72: =H73*lgh_inputs!$D$8/4 -> 79325.038 | J72: =I73*lgh_inputs!$D$8/4 -> 52628.102 | K72: =J73*lgh_inputs!$D$8 -> 83001.298 | L72: =K73*lgh_inputs!$D$8 -> 173575.16 | M72: =L73*lgh_inputs!$D$8 -> 392503.35 | N72: =M73*lgh_inputs!$D$8 -> 687253.56
A73: Cumm cash balance (Balance Sheet) | B73: 251128 | C73: =+B73+C70 -> 2637541.5 | D73: =+C73+D70 -> -866943.45 | E73: =+D73+E70 -> -2782648.6 | F73: =+E73+F70-F74 -> 420309.59 | G73: =+F73+G70+G72 -> 5306065 | H73: =+G73+H70+H72 -> 10576672 | I73: =+H73+I70+I72 -> 7017080.3 | J73: =+I73+J70+J72 -> 2766709.9 | K73: =+J73+K70+K72 -> 5785838.6 | L73: =+K73+L70+L72 -> 13083445 | M73: =+L73+M70+M72 -> 22908452 | N73: =+M73+N70+N72 -> 27568985
A74: adj. to match bank statement | F74: 4021361 | G74: manual adjustment by sk to keep 2025 cash equal. Thomas to evaluate historicals to end q1.

Sheet lgh_cuda
A1: CUDA (liability)
A2: Year | B2: 45657 | C2: =+lgh_bs!E2 -> 45747 | D2: =+lgh_bs!F2 -> 45838 | E2: =+lgh_bs!G2 -> 45930 | F2: =+lgh_bs!H2 -> 46022 | G2: =+lgh_bs!I2 -> 46112 | H2: =+lgh_bs!J2 -> 46203 | I2: =+lgh_bs!K2 -> 46295 | J2: =+lgh_bs!L2 -> 46387 | ... N2: =+lgh_bs!P2 -> 47848
A3: Period | B3: Q4 | C3: =+lgh_bs!E3 -> Q1 | D3: =+lgh_bs!F3 -> Q2 | E3: =+lgh_bs!G3 -> Q3 | F3: =+lgh_bs!H3 -> Q4 | G3: =+lgh_bs!I3 -> Q1 | H3: =+lgh_bs!J3 -> Q2 | I3: =+lgh_bs!K3 -> Q3 | J3: =+lgh_bs!L3 -> Q4 | ... N3: =+lgh_bs!P3 -> Q4
A4: Common Unit Distribution Amount (partner participation)
A5: Increase per LLC agreement | B5: 3000000 | C5: =3000000/4 -> 750000
A6: Distribution (cuda for pref) | B6: 6000000 | C6: =-6050000 -> -6050000
A7: Distribution (cash payout to Managing Member) | D7: -1200000
A8: cuda writeoff for discount | D8: -350000
A9: Distribution (kind within other against art) | C9: =-2150000 -> -2150000
A10: total | B10: 9000000 | C10: =SUM(C5:C9) -> -7450000 | D10: =SUM(D5:D9) -> -1550000 | E10: =SUM(E5:E9) -> 0 | F10: =SUM(F5:F9) -> 0 | G10: =SUM(G5:G9) -> 0 | H10: =SUM(H5:H9) -> 0 | I10: =SUM(I5:I9) -> 0 | J10: =SUM(J5:J9) -> 0 | ... N10: =SUM(N5:N9) -> 0
A11: Balance | B11: 9000000 | C11: =+B11+C10 -> 1550000 | D11: =+C11+D10 -> 0 | E11: =+D11+E10 -> 0 | F11: =+E11+F10 -> 0 | G11: =+F11+G10 -> 0 | H11: =+G11+H10 -> 0 | I11: =+H11+I10 -> 0 | J11: =+I11+J10 -> 0 | ... N11: =+M11+N10 -> 0
A13: Cashflows sources and uses
A15: Sources (cash)
A16: Total LGH Other Liabs in(source) after (assets and cuda) | B16: 6000000
A18: Uses (cash)
A19: Total LGH Other Liabs Cashflow out (flow) (assets and cuda) | B19: 0 | C19: =SUM(C6:C7) -> -6050000 | D19: =SUM(D6:D7) -> -1200000 | E19: =SUM(E6:E7) -> 0 | F19: =SUM(F6:F7) -> 0 | G19: =SUM(G6:G7) -> 0 | H19: =SUM(H6:H7) -> 0 | I19: =SUM(I6:I7) -> 0 | J19: =SUM(J6:J7) -> 0 | ... N19: =SUM(N6:N7) -> 0

Sheet lgh_equity
A1: LGH Equity
A2: Year | B2: 45657 | C2: =+lgh_bs!E2 -> 45747 | D2: =+lgh_bs!F2 -> 45838 | E2: =+lgh_bs!G2 -> 45930 | F2: =+lgh_bs!H2 -> 46022 | G2: =+lgh_bs!I2 -> 46112 | H2: =+lgh_bs!J2 -> 46203 | I2: =+lgh_bs!K2 -> 46295 | J2: =+lgh_bs!L2 -> 46387 | ... N2: =+lgh_bs!P2 -> 47848
A3: Period | B3: Q4 | C3: =+lgh_bs!E3 -> Q1 | D3: =+lgh_bs!F3 -> Q2 | E3: =+lgh_bs!G3 -> Q3 | F3: =+lgh_bs!H3 -> Q4 | G3: =+lgh_bs!I3 -> Q1 | H3: =+lgh_bs!J3 -> Q2 | I3: =+lgh_bs!K3 -> Q3 | J3: =+lgh_bs!L3 -> Q4 | ... N3: =+lgh_bs!P3 -> Q4
A5: EQUITY OWNERSHIP (and percent)
A6: Phil Potter
A7: Cambrian | B7: 0 | D7: 23600000 | E7: 0 | F7: =3000000*0 -> 0 | G7: 0 | H7: 0 | I7: 0 | J7: 0 | K7: 0 | L7: 0 | M7: 0 | N7: 0
A8: Arik
A9: Scott | E9: 200000
A10: Balance | B10: 0 | C10: =SUM(C6:C9) -> 0 | D10: =SUM(D6:D9) -> 23600000 | E10: =SUM(E6:E9) -> 200000 | F10: =SUM(F6:F9) -> 0 | G10: =SUM(G6:G9) -> 0 | H10: =SUM(H6:H9) -> 0 | I10: =SUM(I6:I9) -> 0 | J10: =SUM(J6:J9) -> 0 | ... N10: =SUM(N6:N9) -> 0
A12: Sources/In
B13: 0 | C13: =+C10 -> 0 | D13: =+D10 -> 23600000 | E13: =+E10 -> 200000 | F13: =+F10 -> 0 | G13: =+G10 -> 0 | H13: =+H10 -> 0 | I13: =+I10 -> 0 | J13: =+J10 -> 0 | ... N13: =+N10 -> 0
A14: Total sources in | B14: 0 | C14: =SUM(C13) -> 0 | D14: =SUM(D13) -> 23600000 | E14: =SUM(E13) -> 200000 | F14: =SUM(F13) -> 0 | G14: =SUM(G13) -> 0 | H14: =SUM(H13) -> 0 | I14: =SUM(I13) -> 0 | J14: =SUM(J13) -> 0 | ... N14: =SUM(N13) -> 0
A16: Uses/Out
B17: 0 | C17: 0 | D17: -23600000 | E17: 0 | F17: 0 | G17: 0 | H17: 0 | I17: 0 | J17: 0 | K17: 0 | L17: 0 | M17: 0 | N17: 0
A18: Total Uses/Out | B18: 0 | C18: =SUM(C17) -> 0 | D18: =SUM(D17) -> -23600000 | E18: =SUM(E17) -> 0 | F18: =SUM(F17) -> 0 | G18: =SUM(G17) -> 0 | H18: =SUM(H17) -> 0 | I18: =SUM(I17) -> 0 | J18: =SUM(J17) -> 0 | ... N18: =SUM(N17) -> 0
A20: LGH Cash Flow Total | B20: 0 | C20: =+C10+C18 -> 0 | D20: =+D10+D18 -> 0 | E20: =+E10+E18 -> 200000 | F20: =+F10+F18 -> 0 | G20: =+G10+G18 -> 0 | H20: =+H10+H18 -> 0 | I20: =+I10+I18 -> 0 | J20: =+J10+J18 -> 0 | ... N20: =+N10+N18 -> 0
A22: EQUITY PERCENTAGE
A23: Dilution Calculation
A24: new equity raised | B24: 0 | C24: =SUM(C32:C37)-C36 -> 0 | D24: =SUM(D32:D37)-D36 -> 0.236 | E24: =SUM(E32:E37)-E36 -> 0.0032 | F24: =SUM(F32:F37)-F36 -> 0 | G24: =SUM(G32:G37)-G36 -> 0 | H24: =SUM(H32:H37)-H36 -> 0 | I24: =SUM(I32:I37)-I36 -> 0 | J24: =SUM(J32:J37)-J36 -> 0 | ... N24: =SUM(N32:N37)-N36 -> 0
A25: Issued Share % | B25: 0.0099009901 | C25: =(B25+C24)/(1+C24) -> 0.0099009901 | D25: =(C25+D24)/(1+D24) -> 0.19894902 | E25: =(D25+E24)/(1+E24) -> 0.20150421 | F25: =(E25+F24)/(1+F24) -> 0.20150421 | G25: =(F25+G24)/(1+G24) -> 0.20150421 | H25: =(G25+H24)/(1+H24) -> 0.20150421 | I25: =(H25+I24)/(1+I24) -> 0.20150421 | J25: =(I25+J24)/(1+J24) -> 0.20150421 | ... N25: =(M25+N24)/(1+N24) -> 0.20150421
A26: Unissued Share % | B26: 0.98544554 | C26: =B26/(1+C24) -> 0.98544554 | D26: =C26/(1+D24) -> 0.79728604 | E26: =D26/(1+E24) -> 0.79474286 | F26: =E26/(1+F24) -> 0.79474286 | G26: =F26/(1+G24) -> 0.79474286 | H26: =G26/(1+H24) -> 0.79474286 | I26: =H26/(1+I24) -> 0.79474286 | J26: =I26/(1+J24) -> 0.79474286 | ... N26: =M26/(1+N24) -> 0.79474286
A27: pref raised | B27: 0.2706625 | C27: =+C50 -> 0.007685 | D27: =+D50 -> 0 | E27: =+E50 -> 0 | F27: =+F50 -> 0 | G27: =+G50 -> 0.00265 | H27: =+H50 -> 0 | I27: =+I50 -> 0 | J27: =+J50 -> 0 | ... N27: =+N50 -> 0
A28: Pref Share % | B28: 0.36316834 | C28: =B28/(1+C24)+C27 -> 0.37085334 | D28: =C28/(1+D24)+D27 -> 0.30004316 | E28: =D28/(1+E24)+E27 -> 0.29908608 | F28: =E28/(1+F24)+F27 -> 0.29908608 | G28: =F28/(1+G24)+G27 -> 0.30173608 | H28: =G28/(1+H24)+H27 -> 0.30173608 | I28: =H28/(1+I24)+I27 -> 0.30173608 | J28: =I28/(1+J24)+J27 -> 0.30173608 | ... N28: =M28/(1+N24)+N27 -> 0.30173608
A29: Unissued Share % | B29: 0.6222772 | C29: =C26-C28 -> 0.6145922 | D29: =D26-D28 -> 0.49724288 | E29: =E26-E28 -> 0.49565678 | F29: =F26-F28 -> 0.49565678 | G29: =G26-G28 -> 0.49300678 | H29: =H26-H28 -> 0.49300678 | I29: =I26-I28 -> 0.49300678 | J29: =J26-J28 -> 0.49300678 | ... N29: =N26-N28 -> 0.49300678
A31: New Equity Issued
A32: Sk
A33: Huston
A34: potter
A35: Cambrian | D35: 0.236
A36: PFNGT LLC Pref Transfer | D36: 0.25
A37: Scott Bruner | E37: 0.0032
A38: Total | B38: 0 | C38: =SUM(C32:C37) -> 0 | D38: =SUM(D32:D37) -> 0.486 | E38: =SUM(E32:E37) -> 0.0032 | F38: =SUM(F32:F37) -> 0 | G38: =SUM(G32:G37) -> 0 | H38: =SUM(H32:H37) -> 0 | I38: =SUM(I32:I37) -> 0 | J38: =SUM(J32:J37) -> 0 | ... N38: =SUM(N32:N37) -> 0
A39: Common Equity Position
A40: =A32 -> Sk | B40: 0.6222772 | C40: =+C29 -> 0.6145922 | D40: =+D29 -> 0.49724288 | E40: =+E29 -> 0.49565678 | F40: =+F29 -> 0.49565678 | G40: =+G29 -> 0.49300678 | H40: =+H29 -> 0.49300678 | I40: =+I29 -> 0.49300678 | J40: =+J29 -> 0.49300678 | ... N40: =+N29 -> 0.49300678
A41: =A33 -> Huston | B41: 0.0046534653 | C41: {=IF(B41>0,B41/(1+C$24),(SUMPRODUCT(($A41=$A$33:$A$37)*C$33:C$37))/(1+C$24))} -> 0.0046534653 | D41: {=IF(C41>0,C41/(1+D$24),(SUMPRODUCT(($A41=$A$33:$A$37)*D$33:D$37))/(1+D$24))} -> 0.0037649396 | E41: {=IF(D41>0,D41/(1+E$24),(SUMPRODUCT(($A41=$A$33:$A$37)*E$33:E$37))/(1+E$24))} -> 0.0037529302 | F41: {=IF(E41>0,E41/(1+F$24),(SUMPRODUCT(($A41=$A$33:$A$37)*F$33:F$37))/(1+F$24))} -> 0.0037529302 | G41: {=IF(F41>0,F41/(1+G$24),(SUMPRODUCT(($A41=$A$33:$A$37)*G$33:G$37))/(1+G$24))} -> 0.0037529302 | H41: {=IF(G41>0,G41/(1+H$24),(SUMPRODUCT(($A41=$A$33:$A$37)*H$33:H$37))/(1+H$24))} -> 0.0037529302 | I41: {=IF(H41>0,H41/(1+I$24),(SUMPRODUCT(($A41=$A$33:$A$37)*I$33:I$37))/(1+I$24))} -> 0.0037529302 | J41: {=IF(I41>0,I41/(1+J$24),(SUMPRODUCT(($A41=$A$33:$A$37)*J$33:J$37))/(1+J$24))} -> 0.0037529302 | ... N41: {=IF(M41>0,M41/(1+N$24),(SUMPRODUCT(($A41=$A$33:$A$37)*N$33:N$37))/(1+N$24))} -> 0.0037529302
A42: =A34 -> potter | B42: 0.0099009901 | C42: {=IF(B42>0,B42/(1+C$24),(SUMPRODUCT(($A42=$A$33:$A$37)*C$33:C$37))/(1+C$24))} -> 0.0099009901 | D42: {=IF(C42>0,C42/(1+D$24),(SUMPRODUCT(($A42=$A$33:$A$37)*D$33:D$37))/(1+D$24))} -> 0.0080105098 | E42: {=IF(D42>0,D42/(1+E$24),(SUMPRODUCT(($A42=$A$33:$A$37)*E$33:E$37))/(1+E$24))} -> 0.0079849579 | F42: {=IF(E42>0,E42/(1+F$24),(SUMPRODUCT(($A42=$A$33:$A$37)*F$33:F$37))/(1+F$24))} -> 0.0079849579 | G42: {=IF(F42>0,F42/(1+G$24),(SUMPRODUCT(($A42=$A$33:$A$37)*G$33:G$37))/(1+G$24))} -> 0.0079849579 | H42: {=IF(G42>0,G42/(1+H$24),(SUMPRODUCT(($A42=$A$33:$A$37)*H$33:H$37))/(1+H$24))} -> 0.0079849579 | I42: {=IF(H42>0,H42/(1+I$24),(SUMPRODUCT(($A42=$A$33:$A$37)*I$33:I$37))/(1+I$24))} -> 0.0079849579 | J42: {=IF(I42>0,I42/(1+J$24),(SUMPRODUCT(($A42=$A$33:$A$37)*J$33:J$37))/(1+J$24))} -> 0.0079849579 | ... N42: {=IF(M42>0,M42/(1+N$24),(SUMPRODUCT(($A42=$A$33:$A$37)*N$33:N$37))/(1+N$24))} -> 0.0079849579
A43: =A35 -> Cambrian | B43: 0 | C43: {=IF(B43>0,B43/(1+C$24),(SUMPRODUCT(($A43=$A$33:$A$37)*C$33:C$37))/(1+C$24))} -> 0 | D43: {=IF(C43>0,C43/(1+D$24),(SUMPRODUCT(($A43=$A$33:$A$37)*D$33:D$37))/(1+D$24))} -> 0.19093851 | E43: {=IF(D43>0,D43/(1+E$24),(SUMPRODUCT(($A43=$A$33:$A$37)*E$33:E$37))/(1+E$24))} -> 0.19032946 | F43: {=IF(E43>0,E43/(1+F$24),(SUMPRODUCT(($A43=$A$33:$A$37)*F$33:F$37))/(1+F$24))} -> 0.19032946 | G43: {=IF(F43>0,F43/(1+G$24),(SUMPRODUCT(($A43=$A$33:$A$37)*G$33:G$37))/(1+G$24))} -> 0.19032946 | H43: {=IF(G43>0,G43/(1+H$24),(SUMPRODUCT(($A43=$A$33:$A$37)*H$33:H$37))/(1+H$24))} -> 0.19032946 | I43: {=IF(H43>0,H43/(1+I$24),(SUMPRODUCT(($A43=$A$33:$A$37)*I$33:I$37))/(1+I$24))} -> 0.19032946 | J43: {=IF(I43>0,I43/(1+J$24),(SUMPRODUCT(($A43=$A$33:$A$37)*J$33:J$37))/(1+J$24))} -> 0.19032946 | ... N43: {=IF(M43>0,M43/(1+N$24),(SUMPRODUCT(($A43=$A$33:$A$37)*N$33:N$37))/(1+N$24))} -> 0.19032946
A44: =A36 -> PFNGT LLC Pref Transfer | B44: 0 | C44: {=IF(B44>0,B44/(1+C$24),(SUMPRODUCT(($A44=$A$33:$A$37)*C$33:C$37))/(1+C$24))} -> 0 | D44: {=IF(C44>0,C44/(1+D$24),(SUMPRODUCT(($A44=$A$33:$A$37)*D$33:D$37))/(1+D$24))} -> 0.20226537 | E44: {=IF(D44>0,D44/(1+E$24),(SUMPRODUCT(($A44=$A$33:$A$37)*E$33:E$37))/(1+E$24))} -> 0.20162019 | F44: {=IF(E44>0,E44/(1+F$24),(SUMPRODUCT(($A44=$A$33:$A$37)*F$33:F$37))/(1+F$24))} -> 0.20162019 | G44: {=IF(F44>0,F44/(1+G$24),(SUMPRODUCT(($A44=$A$33:$A$37)*G$33:G$37))/(1+G$24))} -> 0.20162019 | H44: {=IF(G44>0,G44/(1+H$24),(SUMPRODUCT(($A44=$A$33:$A$37)*H$33:H$37))/(1+H$24))} -> 0.20162019 | I44: {=IF(H44>0,H44/(1+I$24),(SUMPRODUCT(($A44=$A$33:$A$37)*I$33:I$37))/(1+I$24))} -> 0.20162019 | J44: {=IF(I44>0,I44/(1+J$24),(SUMPRODUCT(($A44=$A$33:$A$37)*J$33:J$37))/(1+J$24))} -> 0.20162019 | ... N44: {=IF(M44>0,M44/(1+N$24),(SUMPRODUCT(($A44=$A$33:$A$37)*N$33:N$37))/(1+N$24))} -> 0.20162019
A45: =A37 -> Scott Bruner | B45: 0 | C45: {=IF(B45>0,B45/(1+C$24),(SUMPRODUCT(($A45=$A$33:$A$37)*C$33:C$37))/(1+C$24))} -> 0 | D45: {=IF(C45>0,C45/(1+D$24),(SUMPRODUCT(($A45=$A$33:$A$37)*D$33:D$37))/(1+D$24))} -> 0 | E45: {=IF(D45>0,D45/(1+E$24),(SUMPRODUCT(($A45=$A$33:$A$37)*E$33:E$37))/(1+E$24))} -> 0.0031897927 | F45: {=IF(E45>0,E45/(1+F$24),(SUMPRODUCT(($A45=$A$33:$A$37)*F$33:F$37))/(1+F$24))} -> 0.0031897927 | G45: {=IF(F45>0,F45/(1+G$24),(SUMPRODUCT(($A45=$A$33:$A$37)*G$33:G$37))/(1+G$24))} -> 0.0031897927 | H45: {=IF(G45>0,G45/(1+H$24),(SUMPRODUCT(($A45=$A$33:$A$37)*H$33:H$37))/(1+H$24))} -> 0.0031897927 | I45: {=IF(H45>0,H45/(1+I$24),(SUMPRODUCT(($A45=$A$33:$A$37)*I$33:I$37))/(1+I$24))} -> 0.0031897927 | J45: {=IF(I45>0,I45/(1+J$24),(SUMPRODUCT(($A45=$A$33:$A$37)*J$33:J$37))/(1+J$24))} -> 0.0031897927 | ... N45: {=IF(M45>0,M45/(1+N$24),(SUMPRODUCT(($A45=$A$33:$A$37)*N$33:N$37))/(1+N$24))} -> 0.0031897927
A47: Total Common Equity | B47: 0.63683166 | C47: =SUM(C40:C45) -> 0.62914666 | D47: =SUM(D40:D45) -> 0.90222222 | E47: =SUM(E40:E45) -> 0.90253411 | F47: =SUM(F40:F45) -> 0.90253411 | G47: =SUM(G40:G45) -> 0.89988411 | H47: =SUM(H40:H45) -> 0.89988411 | I47: =SUM(I40:I45) -> 0.89988411 | J47: =SUM(J40:J45) -> 0.89988411 | ... N47: =SUM(N40:N45) -> 0.89988411
A49: Transfer of Pref to Common | D49: =-D36/(1+D24) -> -0.20226537
A50: New Pref Issued | B50: 0.2706625 | C50: =+lgh_pref_equity!C139 -> 0.007685 | D50: =+lgh_pref_equity!D139 -> 0 | E50: =+lgh_pref_equity!E139 -> 0 | F50: =+lgh_pref_equity!F139 -> 0 | G50: =+lgh_pref_equity!G139 -> 0.00265 | H50: =+lgh_pref_equity!H139 -> 0 | I50: =+lgh_pref_equity!I139 -> 0 | J50: =+lgh_pref_equity!J139 -> 0 | ... N50: =+lgh_pref_equity!N139 -> 0
A51: Prev. Shares Diluted Value | B51: 0.092505842 | C51: =SUM(B50:B51)/(1+C$24)+C49 -> 0.36316834 | D51: =SUM(C50:C51)/(1+D$24)+D49 -> 0.097777784 | E51: =SUM(D50:D51)/(1+E$24)+E49 -> 0.097465894 | F51: =SUM(E50:E51)/(1+F$24)+F49 -> 0.097465894 | G51: =SUM(F50:F51)/(1+G$24)+G49 -> 0.097465894 | H51: =SUM(G50:G51)/(1+H$24)+H49 -> 0.10011589 | I51: =SUM(H50:H51)/(1+I$24)+I49 -> 0.10011589 | J51: =SUM(I50:I51)/(1+J$24)+J49 -> 0.10011589 | ... N51: =SUM(M50:M51)/(1+N$24)+N49 -> 0.10011589
A52: Total % Preferred Equity Participation | B52: 0.36316834 | C52: =+lgh_pref_equity!C142 -> 0.37085334 | D52: =+lgh_pref_equity!D142 -> 0.097777784 | E52: =+lgh_pref_equity!E142 -> 0.097465894 | F52: =+lgh_pref_equity!F142 -> 0.097465894 | G52: =+lgh_pref_equity!G142 -> 0.10011589 | H52: =+lgh_pref_equity!H142 -> 0.10011589 | I52: =+lgh_pref_equity!I142 -> 0.10011589 | J52: =+lgh_pref_equity!J142 -> 0.10011589 | ... N52: =+lgh_pref_equity!N142 -> 0.10011589
A53: Total | B53: 1 | C53: =+C47+C52 -> 1 | D53: =+D47+D52 -> 1 | E53: =+E47+E52 -> 1 | F53: =+F47+F52 -> 1 | G53: =+G47+G52 -> 1 | H53: =+H47+H52 -> 1 | I53: =+I47+I52 -> 1 | J53: =+J47+J52 -> 1 | ... N53: =+N47+N52 -> 1

Sheet lgh_pref_equity
A3: DEBT INFORMATION | I3: 44561 | J3: 44926 | K3: 45291 | L3: 45657 | M3: 45747 | N3: 45838 | O3: 45930 | P3: 46022 | Q3: 46112 | R3: 46203 | S3: 46295 | T3: 46387 | U3: 46752 | V3: 47118 | W3: 47483 | X3: 47848
A4: Pref Equity ID | B4: Investor Name | C4: Principal ($) | D4: Rate (%) | E4: Gross Part. | F4: Start Date | G4: Units | H4: Side letter Part ∆ | I4: 4 | J4: 4 | K4: 4 | L4: 4 | M4: 1 | N4: 2 | O4: 3 | P4: 4 | Q4: 1 | R4: 2 | S4: 3 | T4: 4 | U4: 4 | V4: 4 | W4: 4 | X4: 4 | Y4: PE ID + Name
A5: PE001 | B5: PFNGT LLC | C5: =5000000 -> 5000000 | D5: 0.08 | E5: 0.175 | F5: 44365 | G5: =+C5/lgh_inputs!$D$10 -> 200000 | I5: =IF($F5<I$3,C5*(1+D5)^((I$3-$F$5)/365),0) -> 5210964.4 | J5: =IF(AND(YEAR($F5)=YEAR(J$3),ROUNDUP(MONTH($F5)/3,0)<=J$4),$C5*(1+$D5)^((J$3-$F5)/365),IF(ROUND(I5,0)=0,0,I5*(1+$D5))) -> 5627841.5 | K5: =IF(AND(YEAR($F5)=YEAR(K$3),ROUNDUP(MONTH($F5)/3,0)<=K$4),$C5*(1+$D5)^((K$3-$F5)/365),IF(ROUND(J5,0)=0,0,J5*(1+$D5))) -> 6078068.8 | L5: =IF(AND(YEAR($F5)=YEAR(L$3),ROUNDUP(MONTH($F5)/3,0)<=L$4),$C5*(1+$D5)^((L$3-$F5)/365),IF(ROUND(K5,0)=0,0,K5*(1+$D5))) -> 6564314.3 | M5: =IF(AND(YEAR($F5)=YEAR(M$3),ROUNDUP(MONTH($F5)/3,0)=M$4),$C5*(1+$D5/4)^((M$3-$F5)/91),IF(ROUND(L5,0)=0,0,L5*(1+$D5/4))) -> 6695600.6 | N5: =IF(AND(YEAR($F5)=YEAR(N$3),ROUNDUP(MONTH($F5)/3,0)=N$4),$C5*(1+$D5/4)^((N$3-$F5)/91),IF(ROUND(M5,0)=0,0,M5*(1+$D5/4))) -> 6829512.6 | O5: =IF(AND(YEAR($F5)=YEAR(O$3),ROUNDUP(MONTH($F5)/3,0)=O$4),$C5*(1+$D5/4)^((O$3-$F5)/91),IF(ROUND(N5,0)=0,0,N5*(1+$D5/4))) -> 6966102.9 | P5: =IF(AND(YEAR($F5)=YEAR(P$3),ROUNDUP(MONTH($F5)/3,0)=P$4),$C5*(1+$D5/4)^((P$3-$F5)/91),IF(ROUND(O5,0)=0,0,O5*(1+$D5/4))) -> 7105425 | Q5: =IF(AND(YEAR($F5)=YEAR(Q$3),ROUNDUP(MONTH($F5)/3,0)=Q$4),$C5*(1+$D5/4)^((Q$3-$F5)/91),IF(ROUND(P5,0)=0,0,P5*(1+$D5/4))) -> 7247533.4 | R5: =IF(AND(YEAR($F5)=YEAR(R$3),ROUNDUP(MONTH($F5)/3,0)=R$4),$C5*(1+$D5/4)^((R$3-$F5)/91),IF(ROUND(Q5,0)=0,0,Q5*(1+$D5/4))) -> 7392484.1 | S5: =IF(AND(YEAR($F5)=YEAR(S$3),ROUNDUP(MONTH($F5)/3,0)=S$4),$C5*(1+$D5/4)^((S$3-$F5)/91),IF(ROUND(R5,0)=0,0,R5*(1+$D5/4))) -> 7540333.8 | T5: =IF(AND(YEAR($F5)=YEAR(T$3),ROUNDUP(MONTH($F5)/3,0)=T$4),$C5*(1+$D5/4)^((T$3-$F5)/91),IF(ROUND(S5,0)=0,0,S5*(1+$D5/4))) -> 7691140.5 | U5: =IF(AND(YEAR($F5)=YEAR(U$3),ROUNDUP(MONTH($F5)/3,0)<=U$4),$C5*(1+$D5)^((U$3-$F5)/365),IF(ROUND(T5,0)=0,0,T5*(1+$D5))) -> 8306431.7 | V5: =IF(AND(YEAR($F5)=YEAR(V$3),ROUNDUP(MONTH($F5)/3,0)<=V$4),$C5*(1+$D5)^((V$3-$F5)/365),IF(ROUND(U5,0)=0,0,U5*(1+$D5))) -> 8970946.3 | W5: =IF(AND(YEAR($F5)=YEAR(W$3),ROUNDUP(MONTH($F5)/3,0)<=W$4),$C5*(1+$D5)^((W$3-$F5)/365),IF(ROUND(V5,0)=0,0,V5*(1+$D5))) -> 9688622 | X5: =IF(AND(YEAR($F5)=YEAR(X$3),ROUNDUP(MONTH($F5)/3,0)<=X$4),$C5*(1+$D5)^((X$3-$F5)/365),IF(ROUND(W5,0)=0,0,W5*(1+$D5))) -> 10463712 | Y5: =A5&" "&B5 -> PE001 PFNGT LLC
A6: PE002 | B6: Derivee Capital Advisors, LLC | C6: 3000000 | D6: 0.08 | E6: 0.175 | F6: 44365 | G6: =+C6/lgh_inputs!$D$10 -> 120000 | I6: =IF($F6<I$3,C6*(1+D6)^((I$3-$F$5)/365),0) -> 3126578.6 | J6: =IF(AND(YEAR($F6)=YEAR(J$3),ROUNDUP(MONTH($F6)/3,0)<=J$4),$C6*(1+$D6)^((J$3-$F6)/365),IF(ROUND(I6,0)=0,0,I6*(1+$D6))) -> 3376704.9 | K6: =IF(AND(YEAR($F6)=YEAR(K$3),ROUNDUP(MONTH($F6)/3,0)<=K$4),$C6*(1+$D6)^((K$3-$F6)/365),IF(ROUND(J6,0)=0,0,J6*(1+$D6))) -> 3646841.3 | L6: =IF(AND(YEAR($F6)=YEAR(L$3),ROUNDUP(MONTH($F6)/3,0)<=L$4),$C6*(1+$D6)^((L$3-$F6)/365),IF(ROUND(K6,0)=0,0,K6*(1+$D6))) -> 3938588.6 | M6: =IF(AND(YEAR($F6)=YEAR(M$3),ROUNDUP(MONTH($F6)/3,0)=M$4),$C6*(1+$D6/4)^((M$3-$F6)/91),IF(ROUND(L6,0)=0,0,L6*(1+$D6/4))) -> 4017360.4 | N6: =IF(AND(YEAR($F6)=YEAR(N$3),ROUNDUP(MONTH($F6)/3,0)=N$4),$C6*(1+$D6/4)^((N$3-$F6)/91),IF(ROUND(M6,0)=0,0,M6*(1+$D6/4))) -> 4097707.6 | O6: =IF(AND(YEAR($F6)=YEAR(O$3),ROUNDUP(MONTH($F6)/3,0)=O$4),$C6*(1+$D6/4)^((O$3-$F6)/91),IF(ROUND(N6,0)=0,0,N6*(1+$D6/4))) -> 4179661.7 | P6: =IF(AND(YEAR($F6)=YEAR(P$3),ROUNDUP(MONTH($F6)/3,0)=P$4),$C6*(1+$D6/4)^((P$3-$F6)/91),IF(ROUND(O6,0)=0,0,O6*(1+$D6/4))) -> 4263255 | Q6: =IF(AND(YEAR($F6)=YEAR(Q$3),ROUNDUP(MONTH($F6)/3,0)=Q$4),$C6*(1+$D6/4)^((Q$3-$F6)/91),IF(ROUND(P6,0)=0,0,P6*(1+$D6/4))) -> 4348520.1 | R6: =IF(AND(YEAR($F6)=YEAR(R$3),ROUNDUP(MONTH($F6)/3,0)=R$4),$C6*(1+$D6/4)^((R$3-$F6)/91),IF(ROUND(Q6,0)=0,0,Q6*(1+$D6/4))) -> 4435490.5 | S6: =IF(AND(YEAR($F6)=YEAR(S$3),ROUNDUP(MONTH($F6)/3,0)=S$4),$C6*(1+$D6/4)^((S$3-$F6)/91),IF(ROUND(R6,0)=0,0,R6*(1+$D6/4))) -> 4524200.3 | T6: =IF(AND(YEAR($F6)=YEAR(T$3),ROUNDUP(MONTH($F6)/3,0)=T$4),$C6*(1+$D6/4)^((T$3-$F6)/91),IF(ROUND(S6,0)=0,0,S6*(1+$D6/4))) -> 4614684.3 | U6: =IF(AND(YEAR($F6)=YEAR(U$3),ROUNDUP(MONTH($F6)/3,0)<=U$4),$C6*(1+$D6)^((U$3-$F6)/365),IF(ROUND(T6,0)=0,0,T6*(1+$D6))) -> 4983859 | V6: =IF(AND(YEAR($F6)=YEAR(V$3),ROUNDUP(MONTH($F6)/3,0)<=V$4),$C6*(1+$D6)^((V$3-$F6)/365),IF(ROUND(U6,0)=0,0,U6*(1+$D6))) -> 5382567.8 | W6: =IF(AND(YEAR($F6)=YEAR(W$3),ROUNDUP(MONTH($F6)/3,0)<=W$4),$C6*(1+$D6)^((W$3-$F6)/365),IF(ROUND(V6,0)=0,0,V6*(1+$D6))) -> 5813173.2 | X6: =IF(AND(YEAR($F6)=YEAR(X$3),ROUNDUP(MONTH($F6)/3,0)<=X$4),$C6*(1+$D6)^((X$3-$F6)/365),IF(ROUND(W6,0)=0,0,W6*(1+$D6))) -> 6278227 | Y6: =A6&" "&B6 -> PE002 Derivee Capital Advisors, LLC
A7: PE003 | B7: Derivee Capital Advisors, LLC | C7: 2000000 | D7: 0.08 | E7: 0.175 | F7: 44393 | G7: =+C7/lgh_inputs!$D$10 -> 80000 | I7: =IF($F7<I$3,C7*(1+D7)^((I$3-$F$5)/365),0) -> 2084385.7 | J7: =IF(AND(YEAR($F7)=YEAR(J$3),ROUNDUP(MONTH($F7)/3,0)<=J$4),$C7*(1+$D7)^((J$3-$F7)/365),IF(ROUND(I7,0)=0,0,I7*(1+$D7))) -> 2251136.6 | K7: =IF(AND(YEAR($F7)=YEAR(K$3),ROUNDUP(MONTH($F7)/3,0)<=K$4),$C7*(1+$D7)^((K$3-$F7)/365),IF(ROUND(J7,0)=0,0,J7*(1+$D7))) -> 2431227.5 | L7: =IF(AND(YEAR($F7)=YEAR(L$3),ROUNDUP(MONTH($F7)/3,0)<=L$4),$C7*(1+$D7)^((L$3-$F7)/365),IF(ROUND(K7,0)=0,0,K7*(1+$D7))) -> 2625725.7 | M7: =IF(AND(YEAR($F7)=YEAR(M$3),ROUNDUP(MONTH($F7)/3,0)=M$4),$C7*(1+$D7/4)^((M$3-$F7)/91),IF(ROUND(L7,0)=0,0,L7*(1+$D7/4))) -> 2678240.3 | N7: =IF(AND(YEAR($F7)=YEAR(N$3),ROUNDUP(MONTH($F7)/3,0)=N$4),$C7*(1+$D7/4)^((N$3-$F7)/91),IF(ROUND(M7,0)=0,0,M7*(1+$D7/4))) -> 2731805.1 | O7: =IF(AND(YEAR($F7)=YEAR(O$3),ROUNDUP(MONTH($F7)/3,0)=O$4),$C7*(1+$D7/4)^((O$3-$F7)/91),IF(ROUND(N7,0)=0,0,N7*(1+$D7/4))) -> 2786441.2 | P7: =IF(AND(YEAR($F7)=YEAR(P$3),ROUNDUP(MONTH($F7)/3,0)=P$4),$C7*(1+$D7/4)^((P$3-$F7)/91),IF(ROUND(O7,0)=0,0,O7*(1+$D7/4))) -> 2842170 | Q7: =IF(AND(YEAR($F7)=YEAR(Q$3),ROUNDUP(MONTH($F7)/3,0)=Q$4),$C7*(1+$D7/4)^((Q$3-$F7)/91),IF(ROUND(P7,0)=0,0,P7*(1+$D7/4))) -> 2899013.4 | R7: =IF(AND(YEAR($F7)=YEAR(R$3),ROUNDUP(MONTH($F7)/3,0)=R$4),$C7*(1+$D7/4)^((R$3-$F7)/91),IF(ROUND(Q7,0)=0,0,Q7*(1+$D7/4))) -> 2956993.6 | S7: =IF(AND(YEAR($F7)=YEAR(S$3),ROUNDUP(MONTH($F7)/3,0)=S$4),$C7*(1+$D7/4)^((S$3-$F7)/91),IF(ROUND(R7,0)=0,0,R7*(1+$D7/4))) -> 3016133.5 | T7: =IF(AND(YEAR($F7)=YEAR(T$3),ROUNDUP(MONTH($F7)/3,0)=T$4),$C7*(1+$D7/4)^((T$3-$F7)/91),IF(ROUND(S7,0)=0,0,S7*(1+$D7/4))) -> 3076456.2 | U7: =IF(AND(YEAR($F7)=YEAR(U$3),ROUNDUP(MONTH($F7)/3,0)<=U$4),$C7*(1+$D7)^((U$3-$F7)/365),IF(ROUND(T7,0)=0,0,T7*(1+$D7))) -> 3322572.7 | V7: =IF(AND(YEAR($F7)=YEAR(V$3),ROUNDUP(MONTH($F7)/3,0)<=V$4),$C7*(1+$D7)^((V$3-$F7)/365),IF(ROUND(U7,0)=0,0,U7*(1+$D7))) -> 3588378.5 | W7: =IF(AND(YEAR($F7)=YEAR(W$3),ROUNDUP(MONTH($F7)/3,0)<=W$4),$C7*(1+$D7)^((W$3-$F7)/365),IF(ROUND(V7,0)=0,0,V7*(1+$D7))) -> 3875448.8 | X7: =IF(AND(YEAR($F7)=YEAR(X$3),ROUNDUP(MONTH($F7)/3,0)<=X$4),$C7*(1+$D7)^((X$3-$F7)/365),IF(ROUND(W7,0)=0,0,W7*(1+$D7))) -> 4185484.7 | Y7: =A7&" "&B7 -> PE003 Derivee Capital Advisors, LLC
A8: PE004 | B8: DCAPP Hotel Ventures LLC | C8: 5000000 | D8: 0.08 | E8: 0.14 | F8: 44568 | G8: =+C8/lgh_inputs!$D$10 -> 200000 | I8: =IF($F8<I$3,C8*(1+D8)^((I$3-$F$5)/365),0) -> 0 | J8: =IF(AND(YEAR($F8)=YEAR(J$3),ROUNDUP(MONTH($F8)/3,0)<=J$4),$C8*(1+$D8)^((J$3-$F8)/365),IF(ROUND(I8,0)=0,0,I8*(1+$D8))) -> 5392035.7 | K8: =IF(AND(YEAR($F8)=YEAR(K$3),ROUNDUP(MONTH($F8)/3,0)<=K$4),$C8*(1+$D8)^((K$3-$F8)/365),IF(ROUND(J8,0)=0,0,J8*(1+$D8))) -> 5823398.5 | L8: =IF(AND(YEAR($F8)=YEAR(L$3),ROUNDUP(MONTH($F8)/3,0)<=L$4),$C8*(1+$D8)^((L$3-$F8)/365),IF(ROUND(K8,0)=0,0,K8*(1+$D8))) -> 6289270.4 | M8: =IF(AND(YEAR($F8)=YEAR(M$3),ROUNDUP(MONTH($F8)/3,0)=M$4),$C8*(1+$D8/4)^((M$3-$F8)/91),IF(ROUND(L8,0)=0,0,L8*(1+$D8/4))) -> 6415055.8 | N8: =IF(AND(YEAR($F8)=YEAR(N$3),ROUNDUP(MONTH($F8)/3,0)=N$4),$C8*(1+$D8/4)^((N$3-$F8)/91),IF(ROUND(M8,0)=0,0,M8*(1+$D8/4))) -> 6543356.9 | O8: =IF(AND(YEAR($F8)=YEAR(O$3),ROUNDUP(MONTH($F8)/3,0)=O$4),$C8*(1+$D8/4)^((O$3-$F8)/91),IF(ROUND(N8,0)=0,0,N8*(1+$D8/4))) -> 6674224.1 | P8: =IF(AND(YEAR($F8)=YEAR(P$3),ROUNDUP(MONTH($F8)/3,0)=P$4),$C8*(1+$D8/4)^((P$3-$F8)/91),IF(ROUND(O8,0)=0,0,O8*(1+$D8/4))) -> 6807708.5 | Q8: =IF(AND(YEAR($F8)=YEAR(Q$3),ROUNDUP(MONTH($F8)/3,0)=Q$4),$C8*(1+$D8/4)^((Q$3-$F8)/91),IF(ROUND(P8,0)=0,0,P8*(1+$D8/4))) -> 6943862.7 | R8: =IF(AND(YEAR($F8)=YEAR(R$3),ROUNDUP(MONTH($F8)/3,0)=R$4),$C8*(1+$D8/4)^((R$3-$F8)/91),IF(ROUND(Q8,0)=0,0,Q8*(1+$D8/4))) -> 7082740 | S8: =IF(AND(YEAR($F8)=YEAR(S$3),ROUNDUP(MONTH($F8)/3,0)=S$4),$C8*(1+$D8/4)^((S$3-$F8)/91),IF(ROUND(R8,0)=0,0,R8*(1+$D8/4))) -> 7224394.8 | T8: =IF(AND(YEAR($F8)=YEAR(T$3),ROUNDUP(MONTH($F8)/3,0)=T$4),$C8*(1+$D8/4)^((T$3-$F8)/91),IF(ROUND(S8,0)=0,0,S8*(1+$D8/4))) -> 7368882.7 | U8: =IF(AND(YEAR($F8)=YEAR(U$3),ROUNDUP(MONTH($F8)/3,0)<=U$4),$C8*(1+$D8)^((U$3-$F8)/365),IF(ROUND(T8,0)=0,0,T8*(1+$D8))) -> 7958393.3 | V8: =IF(AND(YEAR($F8)=YEAR(V$3),ROUNDUP(MONTH($F8)/3,0)<=V$4),$C8*(1+$D8)^((V$3-$F8)/365),IF(ROUND(U8,0)=0,0,U8*(1+$D8))) -> 8595064.7 | W8: =IF(AND(YEAR($F8)=YEAR(W$3),ROUNDUP(MONTH($F8)/3,0)<=W$4),$C8*(1+$D8)^((W$3-$F8)/365),IF(ROUND(V8,0)=0,0,V8*(1+$D8))) -> 9282669.9 | X8: =IF(AND(YEAR($F8)=YEAR(X$3),ROUNDUP(MONTH($F8)/3,0)<=X$4),$C8*(1+$D8)^((X$3-$F8)/365),IF(ROUND(W8,0)=0,0,W8*(1+$D8))) -> 10025284 | Y8: =A8&" "&B8 -> PE004 DCAPP Hotel Ventures LLC
A9: PE005 | B9: DCAPP Hotel Ventures LLC | C9: 4000000 | D9: 0.08 | E9: 0.14 | F9: 44568 | G9: =+C9/lgh_inputs!$D$10 -> 160000 | I9: =IF($F9<I$3,C9*(1+D9)^((I$3-$F$5)/365),0) -> 0 | J9: =IF(AND(YEAR($F9)=YEAR(J$3),ROUNDUP(MONTH($F9)/3,0)<=J$4),$C9*(1+$D9)^((J$3-$F9)/365),IF(ROUND(I9,0)=0,0,I9*(1+$D9))) -> 4313628.5 | K9: =IF(AND(YEAR($F9)=YEAR(K$3),ROUNDUP(MONTH($F9)/3,0)<=K$4),$C9*(1+$D9)^((K$3-$F9)/365),IF(ROUND(J9,0)=0,0,J9*(1+$D9))) -> 4658718.8 | L9: =IF(AND(YEAR($F9)=YEAR(L$3),ROUNDUP(MONTH($F9)/3,0)<=L$4),$C9*(1+$D9)^((L$3-$F9)/365),IF(ROUND(K9,0)=0,0,K9*(1+$D9))) -> 5031416.3 | M9: =IF(AND(YEAR($F9)=YEAR(M$3),ROUNDUP(MONTH($F9)/3,0)=M$4),$C9*(1+$D9/4)^((M$3-$F9)/91),IF(ROUND(L9,0)=0,0,L9*(1+$D9/4))) -> 5132044.6 | N9: =IF(AND(YEAR($F9)=YEAR(N$3),ROUNDUP(MONTH($F9)/3,0)=N$4),$C9*(1+$D9/4)^((N$3-$F9)/91),IF(ROUND(M9,0)=0,0,M9*(1+$D9/4))) -> 5234685.5 | O9: =IF(AND(YEAR($F9)=YEAR(O$3),ROUNDUP(MONTH($F9)/3,0)=O$4),$C9*(1+$D9/4)^((O$3-$F9)/91),IF(ROUND(N9,0)=0,0,N9*(1+$D9/4))) -> 5339379.3 | P9: =IF(AND(YEAR($F9)=YEAR(P$3),ROUNDUP(MONTH($F9)/3,0)=P$4),$C9*(1+$D9/4)^((P$3-$F9)/91),IF(ROUND(O9,0)=0,0,O9*(1+$D9/4))) -> 5446166.8 | Q9: =IF(AND(YEAR($F9)=YEAR(Q$3),ROUNDUP(MONTH($F9)/3,0)=Q$4),$C9*(1+$D9/4)^((Q$3-$F9)/91),IF(ROUND(P9,0)=0,0,P9*(1+$D9/4))) -> 5555090.2 | R9: =IF(AND(YEAR($F9)=YEAR(R$3),ROUNDUP(MONTH($F9)/3,0)=R$4),$C9*(1+$D9/4)^((R$3-$F9)/91),IF(ROUND(Q9,0)=0,0,Q9*(1+$D9/4))) -> 5666192 | S9: =IF(AND(YEAR($F9)=YEAR(S$3),ROUNDUP(MONTH($F9)/3,0)=S$4),$C9*(1+$D9/4)^((S$3-$F9)/91),IF(ROUND(R9,0)=0,0,R9*(1+$D9/4))) -> 5779515.8 | T9: =IF(AND(YEAR($F9)=YEAR(T$3),ROUNDUP(MONTH($F9)/3,0)=T$4),$C9*(1+$D9/4)^((T$3-$F9)/91),IF(ROUND(S9,0)=0,0,S9*(1+$D9/4))) -> 5895106.1 | U9: =IF(AND(YEAR($F9)=YEAR(U$3),ROUNDUP(MONTH($F9)/3,0)<=U$4),$C9*(1+$D9)^((U$3-$F9)/365),IF(ROUND(T9,0)=0,0,T9*(1+$D9))) -> 6366714.6 | V9: =IF(AND(YEAR($F9)=YEAR(V$3),ROUNDUP(MONTH($F9)/3,0)<=V$4),$C9*(1+$D9)^((V$3-$F9)/365),IF(ROUND(U9,0)=0,0,U9*(1+$D9))) -> 6876051.8 | W9: =IF(AND(YEAR($F9)=YEAR(W$3),ROUNDUP(MONTH($F9)/3,0)<=W$4),$C9*(1+$D9)^((W$3-$F9)/365),IF(ROUND(V9,0)=0,0,V9*(1+$D9))) -> 7426135.9 | X9: =IF(AND(YEAR($F9)=YEAR(X$3),ROUNDUP(MONTH($F9)/3,0)<=X$4),$C9*(1+$D9)^((X$3-$F9)/365),IF(ROUND(W9,0)=0,0,W9*(1+$D9))) -> 8020226.8 | Y9: =A9&" "&B9 -> PE005 DCAPP Hotel Ventures LLC
A10: PE006 | B10: DCAPP Hotel Ventures LLC | C10: 2000000 | D10: 0.08 | E10: 0.14 | F10: 44630 | G10: =+C10/lgh_inputs!$D$10 -> 80000 | I10: =IF($F10<I$3,C10*(1+D10)^((I$3-$F$5)/365),0) -> 0 | J10: =IF(AND(YEAR($F10)=YEAR(J$3),ROUNDUP(MONTH($F10)/3,0)<=J$4),$C10*(1+$D10)^((J$3-$F10)/365),IF(ROUND(I10,0)=0,0,I10*(1+$D10))) -> 2128802.1 | K10: =IF(AND(YEAR($F10)=YEAR(K$3),ROUNDUP(MONTH($F10)/3,0)<=K$4),$C10*(1+$D10)^((K$3-$F10)/365),IF(ROUND(J10,0)=0,0,J10*(1+$D10))) -> 2299106.3 | L10: =IF(AND(YEAR($F10)=YEAR(L$3),ROUNDUP(MONTH($F10)/3,0)<=L$4),$C10*(1+$D10)^((L$3-$F10)/365),IF(ROUND(K10,0)=0,0,K10*(1+$D10))) -> 2483034.8 | M10: =IF(AND(YEAR($F10)=YEAR(M$3),ROUNDUP(MONTH($F10)/3,0)=M$4),$C10*(1+$D10/4)^((M$3-$F10)/91),IF(ROUND(L10,0)=0,0,L10*(1+$D10/4))) -> 2532695.5 | N10: =IF(AND(YEAR($F10)=YEAR(N$3),ROUNDUP(MONTH($F10)/3,0)=N$4),$C10*(1+$D10/4)^((N$3-$F10)/91),IF(ROUND(M10,0)=0,0,M10*(1+$D10/4))) -> 2583349.4 | O10: =IF(AND(YEAR($F10)=YEAR(O$3),ROUNDUP(MONTH($F10)/3,0)=O$4),$C10*(1+$D10/4)^((O$3-$F10)/91),IF(ROUND(N10,0)=0,0,N10*(1+$D10/4))) -> 2635016.3 | P10: =IF(AND(YEAR($F10)=YEAR(P$3),ROUNDUP(MONTH($F10)/3,0)=P$4),$C10*(1+$D10/4)^((P$3-$F10)/91),IF(ROUND(O10,0)=0,0,O10*(1+$D10/4))) -> 2687716.7 | Q10: =IF(AND(YEAR($F10)=YEAR(Q$3),ROUNDUP(MONTH($F10)/3,0)=Q$4),$C10*(1+$D10/4)^((Q$3-$F10)/91),IF(ROUND(P10,0)=0,0,P10*(1+$D10/4))) -> 2741471 | R10: =IF(AND(YEAR($F10)=YEAR(R$3),ROUNDUP(MONTH($F10)/3,0)=R$4),$C10*(1+$D10/4)^((R$3-$F10)/91),IF(ROUND(Q10,0)=0,0,Q10*(1+$D10/4))) -> 2796300.4 | S10: =IF(AND(YEAR($F10)=YEAR(S$3),ROUNDUP(MONTH($F10)/3,0)=S$4),$C10*(1+$D10/4)^((S$3-$F10)/91),IF(ROUND(R10,0)=0,0,R10*(1+$D10/4))) -> 2852226.4 | T10: =IF(AND(YEAR($F10)=YEAR(T$3),ROUNDUP(MONTH($F10)/3,0)=T$4),$C10*(1+$D10/4)^((T$3-$F10)/91),IF(ROUND(S10,0)=0,0,S10*(1+$D10/4))) -> 2909271 | U10: =IF(AND(YEAR($F10)=YEAR(U$3),ROUNDUP(MONTH($F10)/3,0)<=U$4),$C10*(1+$D10)^((U$3-$F10)/365),IF(ROUND(T10,0)=0,0,T10*(1+$D10))) -> 3142012.6 | V10: =IF(AND(YEAR($F10)=YEAR(V$3),ROUNDUP(MONTH($F10)/3,0)<=V$4),$C10*(1+$D10)^((V$3-$F10)/365),IF(ROUND(U10,0)=0,0,U10*(1+$D10))) -> 3393373.7 | W10: =IF(AND(YEAR($F10)=YEAR(W$3),ROUNDUP(MONTH($F10)/3,0)<=W$4),$C10*(1+$D10)^((W$3-$F10)/365),IF(ROUND(V10,0)=0,0,V10*(1+$D10))) -> 3664843.5 | X10: =IF(AND(YEAR($F10)=YEAR(X$3),ROUNDUP(MONTH($F10)/3,0)<=X$4),$C10*(1+$D10)^((X$3-$F10)/365),IF(ROUND(W10,0)=0,0,W10*(1+$D10))) -> 3958031 | Y10: =A10&" "&B10 -> PE006 DCAPP Hotel Ventures LLC
A11: PE007 | B11: La Pointe Investments LLC | C11: 2500000 | D11: 0.08 | E11: 0.125 | F11: 44700 | G11: =+C11/lgh_inputs!$D$10 -> 100000 | I11: =IF($F11<I$3,C11*(1+D11)^((I$3-$F$5)/365),0) -> 0 | J11: =IF(AND(YEAR($F11)=YEAR(J$3),ROUNDUP(MONTH($F11)/3,0)<=J$4),$C11*(1+$D11)^((J$3-$F11)/365),IF(ROUND(I11,0)=0,0,I11*(1+$D11))) -> 2622015.6 | K11: =IF(AND(YEAR($F11)=YEAR(K$3),ROUNDUP(MONTH($F11)/3,0)<=K$4),$C11*(1+$D11)^((K$3-$F11)/365),IF(ROUND(J11,0)=0,0,J11*(1+$D11))) -> 2831776.8 | L11: =IF(AND(YEAR($F11)=YEAR(L$3),ROUNDUP(MONTH($F11)/3,0)<=L$4),$C11*(1+$D11)^((L$3-$F11)/365),IF(ROUND(K11,0)=0,0,K11*(1+$D11))) -> 3058319 | M11: =IF(AND(YEAR($F11)=YEAR(M$3),ROUNDUP(MONTH($F11)/3,0)=M$4),$C11*(1+$D11/4)^((M$3-$F11)/91),IF(ROUND(L11,0)=0,0,L11*(1+$D11/4))) -> 3119485.3 | N11: =IF(AND(YEAR($F11)=YEAR(N$3),ROUNDUP(MONTH($F11)/3,0)=N$4),$C11*(1+$D11/4)^((N$3-$F11)/91),IF(ROUND(M11,0)=0,0,M11*(1+$D11/4))) -> 3181875 | O11: =IF(AND(YEAR($F11)=YEAR(O$3),ROUNDUP(MONTH($F11)/3,0)=O$4),$C11*(1+$D11/4)^((O$3-$F11)/91),IF(ROUND(N11,0)=0,0,N11*(1+$D11/4))) -> 3245512.5 | P11: =IF(AND(YEAR($F11)=YEAR(P$3),ROUNDUP(MONTH($F11)/3,0)=P$4),$C11*(1+$D11/4)^((P$3-$F11)/91),IF(ROUND(O11,0)=0,0,O11*(1+$D11/4))) -> 3310422.8 | Q11: =IF(AND(YEAR($F11)=YEAR(Q$3),ROUNDUP(MONTH($F11)/3,0)=Q$4),$C11*(1+$D11/4)^((Q$3-$F11)/91),IF(ROUND(P11,0)=0,0,P11*(1+$D11/4))) -> 3376631.2 | R11: =IF(AND(YEAR($F11)=YEAR(R$3),ROUNDUP(MONTH($F11)/3,0)=R$4),$C11*(1+$D11/4)^((R$3-$F11)/91),IF(ROUND(Q11,0)=0,0,Q11*(1+$D11/4))) -> 3444163.9 | S11: =IF(AND(YEAR($F11)=YEAR(S$3),ROUNDUP(MONTH($F11)/3,0)=S$4),$C11*(1+$D11/4)^((S$3-$F11)/91),IF(ROUND(R11,0)=0,0,R11*(1+$D11/4))) -> 3513047.2 | T11: =IF(AND(YEAR($F11)=YEAR(T$3),ROUNDUP(MONTH($F11)/3,0)=T$4),$C11*(1+$D11/4)^((T$3-$F11)/91),IF(ROUND(S11,0)=0,0,S11*(1+$D11/4))) -> 3583308.1 | U11: =IF(AND(YEAR($F11)=YEAR(U$3),ROUNDUP(MONTH($F11)/3,0)<=U$4),$C11*(1+$D11)^((U$3-$F11)/365),IF(ROUND(T11,0)=0,0,T11*(1+$D11))) -> 3869972.7 | V11: =IF(AND(YEAR($F11)=YEAR(V$3),ROUNDUP(MONTH($F11)/3,0)<=V$4),$C11*(1+$D11)^((V$3-$F11)/365),IF(ROUND(U11,0)=0,0,U11*(1+$D11))) -> 4179570.6 | W11: =IF(AND(YEAR($F11)=YEAR(W$3),ROUNDUP(MONTH($F11)/3,0)<=W$4),$C11*(1+$D11)^((W$3-$F11)/365),IF(ROUND(V11,0)=0,0,V11*(1+$D11))) -> 4513936.2 | X11: =IF(AND(YEAR($F11)=YEAR(X$3),ROUNDUP(MONTH($F11)/3,0)<=X$4),$C11*(1+$D11)^((X$3-$F11)/365),IF(ROUND(W11,0)=0,0,W11*(1+$D11))) -> 4875051.1 | Y11: =A11&" "&B11 -> PE007 La Pointe Investments LLC
A12: PE008 | B12: La Pointe Investments LLC | C12: 2500000 | D12: 0.08 | E12: 0.125 | F12: 44882 | G12: =+C12/lgh_inputs!$D$10 -> 100000 | I12: =IF($F12<I$3,C12*(1+D12)^((I$3-$F$5)/365),0) -> 0 | J12: =IF(AND(YEAR($F12)=YEAR(J$3),ROUNDUP(MONTH($F12)/3,0)<=J$4),$C12*(1+$D12)^((J$3-$F12)/365),IF(ROUND(I12,0)=0,0,I12*(1+$D12))) -> 2523301.7 | K12: =IF(AND(YEAR($F12)=YEAR(K$3),ROUNDUP(MONTH($F12)/3,0)<=K$4),$C12*(1+$D12)^((K$3-$F12)/365),IF(ROUND(J12,0)=0,0,J12*(1+$D12))) -> 2725165.8 | L12: =IF(AND(YEAR($F12)=YEAR(L$3),ROUNDUP(MONTH($F12)/3,0)<=L$4),$C12*(1+$D12)^((L$3-$F12)/365),IF(ROUND(K12,0)=0,0,K12*(1+$D12))) -> 2943179.1 | M12: =IF(AND(YEAR($F12)=YEAR(M$3),ROUNDUP(MONTH($F12)/3,0)=M$4),$C12*(1+$D12/4)^((M$3-$F12)/91),IF(ROUND(L12,0)=0,0,L12*(1+$D12/4))) -> 3002042.6 | N12: =IF(AND(YEAR($F12)=YEAR(N$3),ROUNDUP(MONTH($F12)/3,0)=N$4),$C12*(1+$D12/4)^((N$3-$F12)/91),IF(ROUND(M12,0)=0,0,M12*(1+$D12/4))) -> 3062083.5 | O12: =IF(AND(YEAR($F12)=YEAR(O$3),ROUNDUP(MONTH($F12)/3,0)=O$4),$C12*(1+$D12/4)^((O$3-$F12)/91),IF(ROUND(N12,0)=0,0,N12*(1+$D12/4))) -> 3123325.2 | P12: =IF(AND(YEAR($F12)=YEAR(P$3),ROUNDUP(MONTH($F12)/3,0)=P$4),$C12*(1+$D12/4)^((P$3-$F12)/91),IF(ROUND(O12,0)=0,0,O12*(1+$D12/4))) -> 3185791.7 | Q12: =IF(AND(YEAR($F12)=YEAR(Q$3),ROUNDUP(MONTH($F12)/3,0)=Q$4),$C12*(1+$D12/4)^((Q$3-$F12)/91),IF(ROUND(P12,0)=0,0,P12*(1+$D12/4))) -> 3249507.5 | R12: =IF(AND(YEAR($F12)=YEAR(R$3),ROUNDUP(MONTH($F12)/3,0)=R$4),$C12*(1+$D12/4)^((R$3-$F12)/91),IF(ROUND(Q12,0)=0,0,Q12*(1+$D12/4))) -> 3314497.6 | S12: =IF(AND(YEAR($F12)=YEAR(S$3),ROUNDUP(MONTH($F12)/3,0)=S$4),$C12*(1+$D12/4)^((S$3-$F12)/91),IF(ROUND(R12,0)=0,0,R12*(1+$D12/4))) -> 3380787.6 | T12: =IF(AND(YEAR($F12)=YEAR(T$3),ROUNDUP(MONTH($F12)/3,0)=T$4),$C12*(1+$D12/4)^((T$3-$F12)/91),IF(ROUND(S12,0)=0,0,S12*(1+$D12/4))) -> 3448403.4 | U12: =IF(AND(YEAR($F12)=YEAR(U$3),ROUNDUP(MONTH($F12)/3,0)<=U$4),$C12*(1+$D12)^((U$3-$F12)/365),IF(ROUND(T12,0)=0,0,T12*(1+$D12))) -> 3724275.6 | V12: =IF(AND(YEAR($F12)=YEAR(V$3),ROUNDUP(MONTH($F12)/3,0)<=V$4),$C12*(1+$D12)^((V$3-$F12)/365),IF(ROUND(U12,0)=0,0,U12*(1+$D12))) -> 4022217.7 | W12: =IF(AND(YEAR($F12)=YEAR(W$3),ROUNDUP(MONTH($F12)/3,0)<=W$4),$C12*(1+$D12)^((W$3-$F12)/365),IF(ROUND(V12,0)=0,0,V12*(1+$D12))) -> 4343995.1 | X12: =IF(AND(YEAR($F12)=YEAR(X$3),ROUNDUP(MONTH($F12)/3,0)<=X$4),$C12*(1+$D12)^((X$3-$F12)/365),IF(ROUND(W12,0)=0,0,W12*(1+$D12))) -> 4691514.7 | Y12: =A12&" "&B12 -> PE008 La Pointe Investments LLC
A13: PE009 | B13: La Pointe Investments LLC | C13: 1000000 | D13: 0.08 | E13: 0.125 | F13: 45043 | G13: =+C13/lgh_inputs!$D$10 -> 40000 | I13: =IF($F13<I$3,C13*(1+D13)^((I$3-$F$5)/365),0) -> 0 | J13: =IF(AND(YEAR($F13)=YEAR(J$3),ROUNDUP(MONTH($F13)/3,0)<=J$4),$C13*(1+$D13)^((J$3-$F13)/365),IF(ROUND(I13,0)=0,0,I13*(1+$D13))) -> 0 | K13: =IF(AND(YEAR($F13)=YEAR(K$3),ROUNDUP(MONTH($F13)/3,0)<=K$4),$C13*(1+$D13)^((K$3-$F13)/365),IF(ROUND(J13,0)=0,0,J13*(1+$D13))) -> 1053682.7 | L13: =IF(AND(YEAR($F13)=YEAR(L$3),ROUNDUP(MONTH($F13)/3,0)<=L$4),$C13*(1+$D13)^((L$3-$F13)/365),IF(ROUND(K13,0)=0,0,K13*(1+$D13))) -> 1137977.3 | M13: =IF(AND(YEAR($F13)=YEAR(M$3),ROUNDUP(MONTH($F13)/3,0)=M$4),$C13*(1+$D13/4)^((M$3-$F13)/91),IF(ROUND(L13,0)=0,0,L13*(1+$D13/4))) -> 1160736.8 | N13: =IF(AND(YEAR($F13)=YEAR(N$3),ROUNDUP(MONTH($F13)/3,0)=N$4),$C13*(1+$D13/4)^((N$3-$F13)/91),IF(ROUND(M13,0)=0,0,M13*(1+$D13/4))) -> 1183951.6 | O13: =IF(AND(YEAR($F13)=YEAR(O$3),ROUNDUP(MONTH($F13)/3,0)=O$4),$C13*(1+$D13/4)^((O$3-$F13)/91),IF(ROUND(N13,0)=0,0,N13*(1+$D13/4))) -> 1207630.6 | P13: =IF(AND(YEAR($F13)=YEAR(P$3),ROUNDUP(MONTH($F13)/3,0)=P$4),$C13*(1+$D13/4)^((P$3-$F13)/91),IF(ROUND(O13,0)=0,0,O13*(1+$D13/4))) -> 1231783.2 | Q13: =IF(AND(YEAR($F13)=YEAR(Q$3),ROUNDUP(MONTH($F13)/3,0)=Q$4),$C13*(1+$D13/4)^((Q$3-$F13)/91),IF(ROUND(P13,0)=0,0,P13*(1+$D13/4))) -> 1256418.9 | R13: =IF(AND(YEAR($F13)=YEAR(R$3),ROUNDUP(MONTH($F13)/3,0)=R$4),$C13*(1+$D13/4)^((R$3-$F13)/91),IF(ROUND(Q13,0)=0,0,Q13*(1+$D13/4))) -> 1281547.3 | S13: =IF(AND(YEAR($F13)=YEAR(S$3),ROUNDUP(MONTH($F13)/3,0)=S$4),$C13*(1+$D13/4)^((S$3-$F13)/91),IF(ROUND(R13,0)=0,0,R13*(1+$D13/4))) -> 1307178.2 | T13: =IF(AND(YEAR($F13)=YEAR(T$3),ROUNDUP(MONTH($F13)/3,0)=T$4),$C13*(1+$D13/4)^((T$3-$F13)/91),IF(ROUND(S13,0)=0,0,S13*(1+$D13/4))) -> 1333321.8 | U13: =IF(AND(YEAR($F13)=YEAR(U$3),ROUNDUP(MONTH($F13)/3,0)<=U$4),$C13*(1+$D13)^((U$3-$F13)/365),IF(ROUND(T13,0)=0,0,T13*(1+$D13))) -> 1439987.5 | V13: =IF(AND(YEAR($F13)=YEAR(V$3),ROUNDUP(MONTH($F13)/3,0)<=V$4),$C13*(1+$D13)^((V$3-$F13)/365),IF(ROUND(U13,0)=0,0,U13*(1+$D13))) -> 1555186.5 | W13: =IF(AND(YEAR($F13)=YEAR(W$3),ROUNDUP(MONTH($F13)/3,0)<=W$4),$C13*(1+$D13)^((W$3-$F13)/365),IF(ROUND(V13,0)=0,0,V13*(1+$D13))) -> 1679601.4 | X13: =IF(AND(YEAR($F13)=YEAR(X$3),ROUNDUP(MONTH($F13)/3,0)<=X$4),$C13*(1+$D13)^((X$3-$F13)/365),IF(ROUND(W13,0)=0,0,W13*(1+$D13))) -> 1813969.5 | Y13: =A13&" "&B13 -> PE009 La Pointe Investments LLC
A14: PE010 | B14: Benjamin Rego Jr. | C14: 450000 | D14: 0.08 | E14: 0.1 | F14: 44705 | G14: =+C14/lgh_inputs!$D$10 -> 18000 | I14: =IF($F14<I$3,C14*(1+D14)^((I$3-$F$5)/365),0) -> 0 | J14: =IF(AND(YEAR($F14)=YEAR(J$3),ROUNDUP(MONTH($F14)/3,0)<=J$4),$C14*(1+$D14)^((J$3-$F14)/365),IF(ROUND(I14,0)=0,0,I14*(1+$D14))) -> 471465.49 | K14: =IF(AND(YEAR($F14)=YEAR(K$3),ROUNDUP(MONTH($F14)/3,0)<=K$4),$C14*(1+$D14)^((K$3-$F14)/365),IF(ROUND(J14,0)=0,0,J14*(1+$D14))) -> 509182.73 | L14: =IF(AND(YEAR($F14)=YEAR(L$3),ROUNDUP(MONTH($F14)/3,0)<=L$4),$C14*(1+$D14)^((L$3-$F14)/365),IF(ROUND(K14,0)=0,0,K14*(1+$D14))) -> 549917.35 | M14: =IF(AND(YEAR($F14)=YEAR(M$3),ROUNDUP(MONTH($F14)/3,0)=M$4),$C14*(1+$D14/4)^((M$3-$F14)/91),IF(ROUND(L14,0)=0,0,L14*(1+$D14/4))) -> 560915.7 | N14: =IF(AND(YEAR($F14)=YEAR(N$3),ROUNDUP(MONTH($F14)/3,0)=N$4),$C14*(1+$D14/4)^((N$3-$F14)/91),IF(ROUND(M14,0)=0,0,M14*(1+$D14/4))) -> 572134.01 | O14: =IF(AND(YEAR($F14)=YEAR(O$3),ROUNDUP(MONTH($F14)/3,0)=O$4),$C14*(1+$D14/4)^((O$3-$F14)/91),IF(ROUND(N14,0)=0,0,N14*(1+$D14/4))) -> 583576.69 | P14: =IF(AND(YEAR($F14)=YEAR(P$3),ROUNDUP(MONTH($F14)/3,0)=P$4),$C14*(1+$D14/4)^((P$3-$F14)/91),IF(ROUND(O14,0)=0,0,O14*(1+$D14/4))) -> 595248.22 | Q14: =IF(AND(YEAR($F14)=YEAR(Q$3),ROUNDUP(MONTH($F14)/3,0)=Q$4),$C14*(1+$D14/4)^((Q$3-$F14)/91),IF(ROUND(P14,0)=0,0,P14*(1+$D14/4))) -> 607153.19 | R14: =IF(AND(YEAR($F14)=YEAR(R$3),ROUNDUP(MONTH($F14)/3,0)=R$4),$C14*(1+$D14/4)^((R$3-$F14)/91),IF(ROUND(Q14,0)=0,0,Q14*(1+$D14/4))) -> 619296.25 | S14: =IF(AND(YEAR($F14)=YEAR(S$3),ROUNDUP(MONTH($F14)/3,0)=S$4),$C14*(1+$D14/4)^((S$3-$F14)/91),IF(ROUND(R14,0)=0,0,R14*(1+$D14/4))) -> 631682.18 | T14: =IF(AND(YEAR($F14)=YEAR(T$3),ROUNDUP(MONTH($F14)/3,0)=T$4),$C14*(1+$D14/4)^((T$3-$F14)/91),IF(ROUND(S14,0)=0,0,S14*(1+$D14/4))) -> 644315.82 | U14: =IF(AND(YEAR($F14)=YEAR(U$3),ROUNDUP(MONTH($F14)/3,0)<=U$4),$C14*(1+$D14)^((U$3-$F14)/365),IF(ROUND(T14,0)=0,0,T14*(1+$D14))) -> 695861.09 | V14: =IF(AND(YEAR($F14)=YEAR(V$3),ROUNDUP(MONTH($F14)/3,0)<=V$4),$C14*(1+$D14)^((V$3-$F14)/365),IF(ROUND(U14,0)=0,0,U14*(1+$D14))) -> 751529.97 | W14: =IF(AND(YEAR($F14)=YEAR(W$3),ROUNDUP(MONTH($F14)/3,0)<=W$4),$C14*(1+$D14)^((W$3-$F14)/365),IF(ROUND(V14,0)=0,0,V14*(1+$D14))) -> 811652.37 | X14: =IF(AND(YEAR($F14)=YEAR(X$3),ROUNDUP(MONTH($F14)/3,0)<=X$4),$C14*(1+$D14)^((X$3-$F14)/365),IF(ROUND(W14,0)=0,0,W14*(1+$D14))) -> 876584.56 | Y14: =A14&" "&B14 -> PE010 Benjamin Rego Jr.
A15: PE011 | B15: Benjamin Rego Jr. | C15: 50000 | D15: 0.08 | E15: 0.1 | F15: 44706 | G15: =+C15/lgh_inputs!$D$10 -> 2000 | I15: =IF($F15<I$3,C15*(1+D15)^((I$3-$F$5)/365),0) -> 0 | J15: =IF(AND(YEAR($F15)=YEAR(J$3),ROUNDUP(MONTH($F15)/3,0)<=J$4),$C15*(1+$D15)^((J$3-$F15)/365),IF(ROUND(I15,0)=0,0,I15*(1+$D15))) -> 52374.01 | K15: =IF(AND(YEAR($F15)=YEAR(K$3),ROUNDUP(MONTH($F15)/3,0)<=K$4),$C15*(1+$D15)^((K$3-$F15)/365),IF(ROUND(J15,0)=0,0,J15*(1+$D15))) -> 56563.931 | L15: =IF(AND(YEAR($F15)=YEAR(L$3),ROUNDUP(MONTH($F15)/3,0)<=L$4),$C15*(1+$D15)^((L$3-$F15)/365),IF(ROUND(K15,0)=0,0,K15*(1+$D15))) -> 61089.046 | M15: =IF(AND(YEAR($F15)=YEAR(M$3),ROUNDUP(MONTH($F15)/3,0)=M$4),$C15*(1+$D15/4)^((M$3-$F15)/91),IF(ROUND(L15,0)=0,0,L15*(1+$D15/4))) -> 62310.827 | N15: =IF(AND(YEAR($F15)=YEAR(N$3),ROUNDUP(MONTH($F15)/3,0)=N$4),$C15*(1+$D15/4)^((N$3-$F15)/91),IF(ROUND(M15,0)=0,0,M15*(1+$D15/4))) -> 63557.043 | O15: =IF(AND(YEAR($F15)=YEAR(O$3),ROUNDUP(MONTH($F15)/3,0)=O$4),$C15*(1+$D15/4)^((O$3-$F15)/91),IF(ROUND(N15,0)=0,0,N15*(1+$D15/4))) -> 64828.184 | P15: =IF(AND(YEAR($F15)=YEAR(P$3),ROUNDUP(MONTH($F15)/3,0)=P$4),$C15*(1+$D15/4)^((P$3-$F15)/91),IF(ROUND(O15,0)=0,0,O15*(1+$D15/4))) -> 66124.748 | Q15: =IF(AND(YEAR($F15)=YEAR(Q$3),ROUNDUP(MONTH($F15)/3,0)=Q$4),$C15*(1+$D15/4)^((Q$3-$F15)/91),IF(ROUND(P15,0)=0,0,P15*(1+$D15/4))) -> 67447.243 | R15: =IF(AND(YEAR($F15)=YEAR(R$3),ROUNDUP(MONTH($F15)/3,0)=R$4),$C15*(1+$D15/4)^((R$3-$F15)/91),IF(ROUND(Q15,0)=0,0,Q15*(1+$D15/4))) -> 68796.187 | S15: =IF(AND(YEAR($F15)=YEAR(S$3),ROUNDUP(MONTH($F15)/3,0)=S$4),$C15*(1+$D15/4)^((S$3-$F15)/91),IF(ROUND(R15,0)=0,0,R15*(1+$D15/4))) -> 70172.111 | T15: =IF(AND(YEAR($F15)=YEAR(T$3),ROUNDUP(MONTH($F15)/3,0)=T$4),$C15*(1+$D15/4)^((T$3-$F15)/91),IF(ROUND(S15,0)=0,0,S15*(1+$D15/4))) -> 71575.553 | U15: =IF(AND(YEAR($F15)=YEAR(U$3),ROUNDUP(MONTH($F15)/3,0)<=U$4),$C15*(1+$D15)^((U$3-$F15)/365),IF(ROUND(T15,0)=0,0,T15*(1+$D15))) -> 77301.598 | V15: =IF(AND(YEAR($F15)=YEAR(V$3),ROUNDUP(MONTH($F15)/3,0)<=V$4),$C15*(1+$D15)^((V$3-$F15)/365),IF(ROUND(U15,0)=0,0,U15*(1+$D15))) -> 83485.726 | W15: =IF(AND(YEAR($F15)=YEAR(W$3),ROUNDUP(MONTH($F15)/3,0)<=W$4),$C15*(1+$D15)^((W$3-$F15)/365),IF(ROUND(V15,0)=0,0,V15*(1+$D15))) -> 90164.584 | X15: =IF(AND(YEAR($F15)=YEAR(X$3),ROUNDUP(MONTH($F15)/3,0)<=X$4),$C15*(1+$D15)^((X$3-$F15)/365),IF(ROUND(W15,0)=0,0,W15*(1+$D15))) -> 97377.75 | Y15: =A15&" "&B15 -> PE011 Benjamin Rego Jr.
A16: PE012 | B16: Benjamin Rego Jr._1 | C16: 100000 | D16: 0.08 | E16: 0.053 | F16: 45055 | G16: =+C16/lgh_inputs!$D$10 -> 4000 | I16: =IF($F16<I$3,C16*(1+D16)^((I$3-$F$5)/365),0) -> 0 | J16: =IF(AND(YEAR($F16)=YEAR(J$3),ROUNDUP(MONTH($F16)/3,0)<=J$4),$C16*(1+$D16)^((J$3-$F16)/365),IF(ROUND(I16,0)=0,0,I16*(1+$D16))) -> 0 | K16: =IF(AND(YEAR($F16)=YEAR(K$3),ROUNDUP(MONTH($F16)/3,0)<=K$4),$C16*(1+$D16)^((K$3-$F16)/365),IF(ROUND(J16,0)=0,0,J16*(1+$D16))) -> 105102 | L16: =IF(AND(YEAR($F16)=YEAR(L$3),ROUNDUP(MONTH($F16)/3,0)<=L$4),$C16*(1+$D16)^((L$3-$F16)/365),IF(ROUND(K16,0)=0,0,K16*(1+$D16))) -> 113510.16 | M16: =IF(AND(YEAR($F16)=YEAR(M$3),ROUNDUP(MONTH($F16)/3,0)=M$4),$C16*(1+$D16/4)^((M$3-$F16)/91),IF(ROUND(L16,0)=0,0,L16*(1+$D16/4))) -> 115780.36 | N16: =IF(AND(YEAR($F16)=YEAR(N$3),ROUNDUP(MONTH($F16)/3,0)=N$4),$C16*(1+$D16/4)^((N$3-$F16)/91),IF(ROUND(M16,0)=0,0,M16*(1+$D16/4))) -> 118095.97 | O16: =IF(AND(YEAR($F16)=YEAR(O$3),ROUNDUP(MONTH($F16)/3,0)=O$4),$C16*(1+$D16/4)^((O$3-$F16)/91),IF(ROUND(N16,0)=0,0,N16*(1+$D16/4))) -> 120457.89 | P16: =IF(AND(YEAR($F16)=YEAR(P$3),ROUNDUP(MONTH($F16)/3,0)=P$4),$C16*(1+$D16/4)^((P$3-$F16)/91),IF(ROUND(O16,0)=0,0,O16*(1+$D16/4))) -> 122867.05 | Q16: =IF(AND(YEAR($F16)=YEAR(Q$3),ROUNDUP(MONTH($F16)/3,0)=Q$4),$C16*(1+$D16/4)^((Q$3-$F16)/91),IF(ROUND(P16,0)=0,0,P16*(1+$D16/4))) -> 125324.39 | R16: =IF(AND(YEAR($F16)=YEAR(R$3),ROUNDUP(MONTH($F16)/3,0)=R$4),$C16*(1+$D16/4)^((R$3-$F16)/91),IF(ROUND(Q16,0)=0,0,Q16*(1+$D16/4))) -> 127830.88 | S16: =IF(AND(YEAR($F16)=YEAR(S$3),ROUNDUP(MONTH($F16)/3,0)=S$4),$C16*(1+$D16/4)^((S$3-$F16)/91),IF(ROUND(R16,0)=0,0,R16*(1+$D16/4))) -> 130387.49 | T16: =IF(AND(YEAR($F16)=YEAR(T$3),ROUNDUP(MONTH($F16)/3,0)=T$4),$C16*(1+$D16/4)^((T$3-$F16)/91),IF(ROUND(S16,0)=0,0,S16*(1+$D16/4))) -> 132995.24 | U16: =IF(AND(YEAR($F16)=YEAR(U$3),ROUNDUP(MONTH($F16)/3,0)<=U$4),$C16*(1+$D16)^((U$3-$F16)/365),IF(ROUND(T16,0)=0,0,T16*(1+$D16))) -> 143634.86 | V16: =IF(AND(YEAR($F16)=YEAR(V$3),ROUNDUP(MONTH($F16)/3,0)<=V$4),$C16*(1+$D16)^((V$3-$F16)/365),IF(ROUND(U16,0)=0,0,U16*(1+$D16))) -> 155125.65 | W16: =IF(AND(YEAR($F16)=YEAR(W$3),ROUNDUP(MONTH($F16)/3,0)<=W$4),$C16*(1+$D16)^((W$3-$F16)/365),IF(ROUND(V16,0)=0,0,V16*(1+$D16))) -> 167535.7 | X16: =IF(AND(YEAR($F16)=YEAR(X$3),ROUNDUP(MONTH($F16)/3,0)<=X$4),$C16*(1+$D16)^((X$3-$F16)/365),IF(ROUND(W16,0)=0,0,W16*(1+$D16))) -> 180938.56 | Y16: =A16&" "&B16 -> PE012 Benjamin Rego Jr._1
A17: PE013 | B17: Benjamin Rego Jr._1 | C17: 300000 | D17: 0.08 | E17: 0.053 | F17: 45058 | G17: =+C17/lgh_inputs!$D$10 -> 12000 | I17: =IF($F17<I$3,C17*(1+D17)^((I$3-$F$5)/365),0) -> 0 | J17: =IF(AND(YEAR($F17)=YEAR(J$3),ROUNDUP(MONTH($F17)/3,0)<=J$4),$C17*(1+$D17)^((J$3-$F17)/365),IF(ROUND(I17,0)=0,0,I17*(1+$D17))) -> 0 | K17: =IF(AND(YEAR($F17)=YEAR(K$3),ROUNDUP(MONTH($F17)/3,0)<=K$4),$C17*(1+$D17)^((K$3-$F17)/365),IF(ROUND(J17,0)=0,0,J17*(1+$D17))) -> 315106.61 | L17: =IF(AND(YEAR($F17)=YEAR(L$3),ROUNDUP(MONTH($F17)/3,0)<=L$4),$C17*(1+$D17)^((L$3-$F17)/365),IF(ROUND(K17,0)=0,0,K17*(1+$D17))) -> 340315.14 | M17: =IF(AND(YEAR($F17)=YEAR(M$3),ROUNDUP(MONTH($F17)/3,0)=M$4),$C17*(1+$D17/4)^((M$3-$F17)/91),IF(ROUND(L17,0)=0,0,L17*(1+$D17/4))) -> 347121.44 | N17: =IF(AND(YEAR($F17)=YEAR(N$3),ROUNDUP(MONTH($F17)/3,0)=N$4),$C17*(1+$D17/4)^((N$3-$F17)/91),IF(ROUND(M17,0)=0,0,M17*(1+$D17/4))) -> 354063.87 | O17: =IF(AND(YEAR($F17)=YEAR(O$3),ROUNDUP(MONTH($F17)/3,0)=O$4),$C17*(1+$D17/4)^((O$3-$F17)/91),IF(ROUND(N17,0)=0,0,N17*(1+$D17/4))) -> 361145.15 | P17: =IF(AND(YEAR($F17)=YEAR(P$3),ROUNDUP(MONTH($F17)/3,0)=P$4),$C17*(1+$D17/4)^((P$3-$F17)/91),IF(ROUND(O17,0)=0,0,O17*(1+$D17/4))) -> 368368.05 | Q17: =IF(AND(YEAR($F17)=YEAR(Q$3),ROUNDUP(MONTH($F17)/3,0)=Q$4),$C17*(1+$D17/4)^((Q$3-$F17)/91),IF(ROUND(P17,0)=0,0,P17*(1+$D17/4))) -> 375735.41 | R17: =IF(AND(YEAR($F17)=YEAR(R$3),ROUNDUP(MONTH($F17)/3,0)=R$4),$C17*(1+$D17/4)^((R$3-$F17)/91),IF(ROUND(Q17,0)=0,0,Q17*(1+$D17/4))) -> 383250.12 | S17: =IF(AND(YEAR($F17)=YEAR(S$3),ROUNDUP(MONTH($F17)/3,0)=S$4),$C17*(1+$D17/4)^((S$3-$F17)/91),IF(ROUND(R17,0)=0,0,R17*(1+$D17/4))) -> 390915.12 | T17: =IF(AND(YEAR($F17)=YEAR(T$3),ROUNDUP(MONTH($F17)/3,0)=T$4),$C17*(1+$D17/4)^((T$3-$F17)/91),IF(ROUND(S17,0)=0,0,S17*(1+$D17/4))) -> 398733.43 | U17: =IF(AND(YEAR($F17)=YEAR(U$3),ROUNDUP(MONTH($F17)/3,0)<=U$4),$C17*(1+$D17)^((U$3-$F17)/365),IF(ROUND(T17,0)=0,0,T17*(1+$D17))) -> 430632.1 | V17: =IF(AND(YEAR($F17)=YEAR(V$3),ROUNDUP(MONTH($F17)/3,0)<=V$4),$C17*(1+$D17)^((V$3-$F17)/365),IF(ROUND(U17,0)=0,0,U17*(1+$D17))) -> 465082.67 | W17: =IF(AND(YEAR($F17)=YEAR(W$3),ROUNDUP(MONTH($F17)/3,0)<=W$4),$C17*(1+$D17)^((W$3-$F17)/365),IF(ROUND(V17,0)=0,0,V17*(1+$D17))) -> 502289.28 | X17: =IF(AND(YEAR($F17)=YEAR(X$3),ROUNDUP(MONTH($F17)/3,0)<=X$4),$C17*(1+$D17)^((X$3-$F17)/365),IF(ROUND(W17,0)=0,0,W17*(1+$D17))) -> 542472.42 | Y17: =A17&" "&B17 -> PE013 Benjamin Rego Jr._1
... A30: PE026 | B30: James Neuhauser (Jim) | C30: 250000 | D30: 0.08 | E30: 0.053 | F30: 45536 | G30: =+C30/lgh_inputs!$D$10 -> 10000 | I30: =IF($F30<I$3,C30*(1+D30)^((I$3-$F$5)/365),0) -> 0 | J30: =IF(AND(YEAR($F30)=YEAR(J$3),ROUNDUP(MONTH($F30)/3,0)<=J$4),$C30*(1+$D30)^((J$3-$F30)/365),IF(ROUND(I30,0)=0,0,I30*(1+$D30))) -> 0 | K30: =IF(AND(YEAR($F30)=YEAR(K$3),ROUNDUP(MONTH($F30)/3,0)<=K$4),$C30*(1+$D30)^((K$3-$F30)/365),IF(ROUND(J30,0)=0,0,J30*(1+$D30))) -> 0 | L30: =IF(AND(YEAR($F30)=YEAR(L$3),ROUNDUP(MONTH($F30)/3,0)<=L$4),$C30*(1+$D30)^((L$3-$F30)/365),IF(ROUND(K30,0)=0,0,K30*(1+$D30))) -> 256460.34 | M30: =IF(AND(YEAR($F30)=YEAR(M$3),ROUNDUP(MONTH($F30)/3,0)=M$4),$C30*(1+$D30/4)^((M$3-$F30)/91),IF(ROUND(L30,0)=0,0,L30*(1+$D30/4))) -> 261589.55 | N30: =IF(AND(YEAR($F30)=YEAR(N$3),ROUNDUP(MONTH($F30)/3,0)=N$4),$C30*(1+$D30/4)^((N$3-$F30)/91),IF(ROUND(M30,0)=0,0,M30*(1+$D30/4))) -> 266821.34 | O30: =IF(AND(YEAR($F30)=YEAR(O$3),ROUNDUP(MONTH($F30)/3,0)=O$4),$C30*(1+$D30/4)^((O$3-$F30)/91),IF(ROUND(N30,0)=0,0,N30*(1+$D30/4))) -> 272157.76 | P30: =IF(AND(YEAR($F30)=YEAR(P$3),ROUNDUP(MONTH($F30)/3,0)=P$4),$C30*(1+$D30/4)^((P$3-$F30)/91),IF(ROUND(O30,0)=0,0,O30*(1+$D30/4))) -> 277600.92 | Q30: =IF(AND(YEAR($F30)=YEAR(Q$3),ROUNDUP(MONTH($F30)/3,0)=Q$4),$C30*(1+$D30/4)^((Q$3-$F30)/91),IF(ROUND(P30,0)=0,0,P30*(1+$D30/4))) -> 283152.94 | R30: =IF(AND(YEAR($F30)=YEAR(R$3),ROUNDUP(MONTH($F30)/3,0)=R$4),$C30*(1+$D30/4)^((R$3-$F30)/91),IF(ROUND(Q30,0)=0,0,Q30*(1+$D30/4))) -> 288816 | S30: =IF(AND(YEAR($F30)=YEAR(S$3),ROUNDUP(MONTH($F30)/3,0)=S$4),$C30*(1+$D30/4)^((S$3-$F30)/91),IF(ROUND(R30,0)=0,0,R30*(1+$D30/4))) -> 294592.32 | T30: =IF(AND(YEAR($F30)=YEAR(T$3),ROUNDUP(MONTH($F30)/3,0)=T$4),$C30*(1+$D30/4)^((T$3-$F30)/91),IF(ROUND(S30,0)=0,0,S30*(1+$D30/4))) -> 300484.16 | U30: =IF(AND(YEAR($F30)=YEAR(U$3),ROUNDUP(MONTH($F30)/3,0)<=U$4),$C30*(1+$D30)^((U$3-$F30)/365),IF(ROUND(T30,0)=0,0,T30*(1+$D30))) -> 324522.9 | V30: =IF(AND(YEAR($F30)=YEAR(V$3),ROUNDUP(MONTH($F30)/3,0)<=V$4),$C30*(1+$D30)^((V$3-$F30)/365),IF(ROUND(U30,0)=0,0,U30*(1+$D30))) -> 350484.73 | W30: =IF(AND(YEAR($F30)=YEAR(W$3),ROUNDUP(MONTH($F30)/3,0)<=W$4),$C30*(1+$D30)^((W$3-$F30)/365),IF(ROUND(V30,0)=0,0,V30*(1+$D30))) -> 378523.51 | X30: =IF(AND(YEAR($F30)=YEAR(X$3),ROUNDUP(MONTH($F30)/3,0)<=X$4),$C30*(1+$D30)^((X$3-$F30)/365),IF(ROUND(W30,0)=0,0,W30*(1+$D30))) -> 408805.39 | Y30: =A30&" "&B30 -> PE026 James Neuhauser (Jim)
A31: PE027 | B31: PFNGT LLC_side letter part % adj. | E31: 2.5 | F31: 45292 | G31: 200000 | H31: 200000 | I31: =IF($F31<I$3,C31*(1+D31)^((I$3-$F$5)/365),0) -> 0 | J31: =IF(AND(YEAR($F31)=YEAR(J$3),ROUNDUP(MONTH($F31)/3,0)<=J$4),$C31*(1+$D31)^((J$3-$F31)/365),IF(ROUND(I31,0)=0,0,I31*(1+$D31))) -> 0 | K31: =IF(AND(YEAR($F31)=YEAR(K$3),ROUNDUP(MONTH($F31)/3,0)<=K$4),$C31*(1+$D31)^((K$3-$F31)/365),IF(ROUND(J31,0)=0,0,J31*(1+$D31))) -> 0 | L31: =IF(AND(YEAR($F31)=YEAR(L$3),ROUNDUP(MONTH($F31)/3,0)<=L$4),$C31*(1+$D31)^((L$3-$F31)/365),IF(ROUND(K31,0)=0,0,K31*(1+$D31))) -> 0 | M31: =IF(AND(YEAR($F31)=YEAR(M$3),ROUNDUP(MONTH($F31)/3,0)=M$4),$C31*(1+$D31/4)^((M$3-$F31)/91),IF(ROUND(L31,0)=0,0,L31*(1+$D31/4))) -> 0 | N31: =IF(AND(YEAR($F31)=YEAR(N$3),ROUNDUP(MONTH($F31)/3,0)=N$4),$C31*(1+$D31/4)^((N$3-$F31)/91),IF(ROUND(M31,0)=0,0,M31*(1+$D31/4))) -> 0 | O31: =IF(AND(YEAR($F31)=YEAR(O$3),ROUNDUP(MONTH($F31)/3,0)=O$4),$C31*(1+$D31/4)^((O$3-$F31)/91),IF(ROUND(N31,0)=0,0,N31*(1+$D31/4))) -> 0 | P31: =IF(AND(YEAR($F31)=YEAR(P$3),ROUNDUP(MONTH($F31)/3,0)=P$4),$C31*(1+$D31/4)^((P$3-$F31)/91),IF(ROUND(O31,0)=0,0,O31*(1+$D31/4))) -> 0 | Q31: =IF(AND(YEAR($F31)=YEAR(Q$3),ROUNDUP(MONTH($F31)/3,0)=Q$4),$C31*(1+$D31/4)^((Q$3-$F31)/91),IF(ROUND(P31,0)=0,0,P31*(1+$D31/4))) -> 0 | R31: =IF(AND(YEAR($F31)=YEAR(R$3),ROUNDUP(MONTH($F31)/3,0)=R$4),$C31*(1+$D31/4)^((R$3-$F31)/91),IF(ROUND(Q31,0)=0,0,Q31*(1+$D31/4))) -> 0 | S31: =IF(AND(YEAR($F31)=YEAR(S$3),ROUNDUP(MONTH($F31)/3,0)=S$4),$C31*(1+$D31/4)^((S$3-$F31)/91),IF(ROUND(R31,0)=0,0,R31*(1+$D31/4))) -> 0 | T31: =IF(AND(YEAR($F31)=YEAR(T$3),ROUNDUP(MONTH($F31)/3,0)=T$4),$C31*(1+$D31/4)^((T$3-$F31)/91),IF(ROUND(S31,0)=0,0,S31*(1+$D31/4))) -> 0 | U31: =IF(AND(YEAR($F31)=YEAR(U$3),ROUNDUP(MONTH($F31)/3,0)<=U$4),$C31*(1+$D31)^((U$3-$F31)/365),IF(ROUND(T31,0)=0,0,T31*(1+$D31))) -> 0 | V31: =IF(AND(YEAR($F31)=YEAR(V$3),ROUNDUP(MONTH($F31)/3,0)<=V$4),$C31*(1+$D31)^((V$3-$F31)/365),IF(ROUND(U31,0)=0,0,U31*(1+$D31))) -> 0 | W31: =IF(AND(YEAR($F31)=YEAR(W$3),ROUNDUP(MONTH($F31)/3,0)<=W$4),$C31*(1+$D31)^((W$3-$F31)/365),IF(ROUND(V31,0)=0,0,V31*(1+$D31))) -> 0 | X31: =IF(AND(YEAR($F31)=YEAR(X$3),ROUNDUP(MONTH($F31)/3,0)<=X$4),$C31*(1+$D31)^((X$3-$F31)/365),IF(ROUND(W31,0)=0,0,W31*(1+$D31))) -> 0 | Y31: =A31&" "&B31 -> PE027 PFNGT LLC_side letter part % adj.
A32: PE028 | B32: La Pointe Investments LLC | C32: 4000000 | D32: 0.08 | E32: 0.125 | F32: 45575 | G32: 160000 | I32: =IF($F32<I$3,C32*(1+D32)^((I$3-$F$5)/365),0) -> 0 | J32: =IF(AND(YEAR($F32)=YEAR(J$3),ROUNDUP(MONTH($F32)/3,0)<=J$4),$C32*(1+$D32)^((J$3-$F32)/365),IF(ROUND(I32,0)=0,0,I32*(1+$D32))) -> 0 | K32: =IF(AND(YEAR($F32)=YEAR(K$3),ROUNDUP(MONTH($F32)/3,0)<=K$4),$C32*(1+$D32)^((K$3-$F32)/365),IF(ROUND(J32,0)=0,0,J32*(1+$D32))) -> 0 | L32: =IF(AND(YEAR($F32)=YEAR(L$3),ROUNDUP(MONTH($F32)/3,0)<=L$4),$C32*(1+$D32)^((L$3-$F32)/365),IF(ROUND(K32,0)=0,0,K32*(1+$D32))) -> 4069760.9 | N32: =IF(AND(YEAR($F32)=YEAR(N$3),ROUNDUP(MONTH($F32)/3,0)=N$4),$C32*(1+$D32/4)^((N$3-$F32)/91),IF(ROUND(M32,0)=0,0,M32*(1+$D32/4))) -> 0 | O32: =IF(AND(YEAR($F32)=YEAR(O$3),ROUNDUP(MONTH($F32)/3,0)=O$4),$C32*(1+$D32/4)^((O$3-$F32)/91),IF(ROUND(N32,0)=0,0,N32*(1+$D32/4))) -> 0 | P32: =IF(AND(YEAR($F32)=YEAR(P$3),ROUNDUP(MONTH($F32)/3,0)=P$4),$C32*(1+$D32/4)^((P$3-$F32)/91),IF(ROUND(O32,0)=0,0,O32*(1+$D32/4))) -> 0 | Q32: =IF(AND(YEAR($F32)=YEAR(Q$3),ROUNDUP(MONTH($F32)/3,0)=Q$4),$C32*(1+$D32/4)^((Q$3-$F32)/91),IF(ROUND(P32,0)=0,0,P32*(1+$D32/4))) -> 0 | R32: =IF(AND(YEAR($F32)=YEAR(R$3),ROUNDUP(MONTH($F32)/3,0)=R$4),$C32*(1+$D32/4)^((R$3-$F32)/91),IF(ROUND(Q32,0)=0,0,Q32*(1+$D32/4))) -> 0 | S32: =IF(AND(YEAR($F32)=YEAR(S$3),ROUNDUP(MONTH($F32)/3,0)=S$4),$C32*(1+$D32/4)^((S$3-$F32)/91),IF(ROUND(R32,0)=0,0,R32*(1+$D32/4))) -> 0 | T32: =IF(AND(YEAR($F32)=YEAR(T$3),ROUNDUP(MONTH($F32)/3,0)=T$4),$C32*(1+$D32/4)^((T$3-$F32)/91),IF(ROUND(S32,0)=0,0,S32*(1+$D32/4))) -> 0 | U32: =IF(AND(YEAR($F32)=YEAR(U$3),ROUNDUP(MONTH($F32)/3,0)<=U$4),$C32*(1+$D32)^((U$3-$F32)/365),IF(ROUND(T32,0)=0,0,T32*(1+$D32))) -> 0 | V32: =IF(AND(YEAR($F32)=YEAR(V$3),ROUNDUP(MONTH($F32)/3,0)<=V$4),$C32*(1+$D32)^((V$3-$F32)/365),IF(ROUND(U32,0)=0,0,U32*(1+$D32))) -> 0 | W32: =IF(AND(YEAR($F32)=YEAR(W$3),ROUNDUP(MONTH($F32)/3,0)<=W$4),$C32*(1+$D32)^((W$3-$F32)/365),IF(ROUND(V32,0)=0,0,V32*(1+$D32))) -> 0 | X32: =IF(AND(YEAR($F32)=YEAR(X$3),ROUNDUP(MONTH($F32)/3,0)<=X$4),$C32*(1+$D32)^((X$3-$F32)/365),IF(ROUND(W32,0)=0,0,W32*(1+$D32))) -> 0 | Y32: =A32&" "&B32 -> PE028 La Pointe Investments LLC
A33: PE029 | B33: La Pointe Investments LLC | C33: 4000000 | D33: 0.08 | E33: 0.125 | F33: 45621 | G33: 160000 | I33: =IF($F33<I$3,C33*(1+D33)^((I$3-$F$5)/365),0) -> 0 | J33: =IF(AND(YEAR($F33)=YEAR(J$3),ROUNDUP(MONTH($F33)/3,0)<=J$4),$C33*(1+$D33)^((J$3-$F33)/365),IF(ROUND(I33,0)=0,0,I33*(1+$D33))) -> 0 | K33: =IF(AND(YEAR($F33)=YEAR(K$3),ROUNDUP(MONTH($F33)/3,0)<=K$4),$C33*(1+$D33)^((K$3-$F33)/365),IF(ROUND(J33,0)=0,0,J33*(1+$D33))) -> 0 | L33: =IF(AND(YEAR($F33)=YEAR(L$3),ROUNDUP(MONTH($F33)/3,0)<=L$4),$C33*(1+$D33)^((L$3-$F33)/365),IF(ROUND(K33,0)=0,0,K33*(1+$D33))) -> 4030478.2 | N33: =IF(AND(YEAR($F33)=YEAR(N$3),ROUNDUP(MONTH($F33)/3,0)=N$4),$C33*(1+$D33/4)^((N$3-$F33)/91),IF(ROUND(M33,0)=0,0,M33*(1+$D33/4))) -> 0 | O33: =IF(AND(YEAR($F33)=YEAR(O$3),ROUNDUP(MONTH($F33)/3,0)=O$4),$C33*(1+$D33/4)^((O$3-$F33)/91),IF(ROUND(N33,0)=0,0,N33*(1+$D33/4))) -> 0 | P33: =IF(AND(YEAR($F33)=YEAR(P$3),ROUNDUP(MONTH($F33)/3,0)=P$4),$C33*(1+$D33/4)^((P$3-$F33)/91),IF(ROUND(O33,0)=0,0,O33*(1+$D33/4))) -> 0 | Q33: =IF(AND(YEAR($F33)=YEAR(Q$3),ROUNDUP(MONTH($F33)/3,0)=Q$4),$C33*(1+$D33/4)^((Q$3-$F33)/91),IF(ROUND(P33,0)=0,0,P33*(1+$D33/4))) -> 0 | R33: =IF(AND(YEAR($F33)=YEAR(R$3),ROUNDUP(MONTH($F33)/3,0)=R$4),$C33*(1+$D33/4)^((R$3-$F33)/91),IF(ROUND(Q33,0)=0,0,Q33*(1+$D33/4))) -> 0 | S33: =IF(AND(YEAR($F33)=YEAR(S$3),ROUNDUP(MONTH($F33)/3,0)=S$4),$C33*(1+$D33/4)^((S$3-$F33)/91),IF(ROUND(R33,0)=0,0,R33*(1+$D33/4))) -> 0 | T33: =IF(AND(YEAR($F33)=YEAR(T$3),ROUNDUP(MONTH($F33)/3,0)=T$4),$C33*(1+$D33/4)^((T$3-$F33)/91),IF(ROUND(S33,0)=0,0,S33*(1+$D33/4))) -> 0 | U33: =IF(AND(YEAR($F33)=YEAR(U$3),ROUNDUP(MONTH($F33)/3,0)<=U$4),$C33*(1+$D33)^((U$3-$F33)/365),IF(ROUND(T33,0)=0,0,T33*(1+$D33))) -> 0 | V33: =IF(AND(YEAR($F33)=YEAR(V$3),ROUNDUP(MONTH($F33)/3,0)<=V$4),$C33*(1+$D33)^((V$3-$F33)/365),IF(ROUND(U33,0)=0,0,U33*(1+$D33))) -> 0 | W33: =IF(AND(YEAR($F33)=YEAR(W$3),ROUNDUP(MONTH($F33)/3,0)<=W$4),$C33*(1+$D33)^((W$3-$F33)/365),IF(ROUND(V33,0)=0,0,V33*(1+$D33))) -> 0 | X33: =IF(AND(YEAR($F33)=YEAR(X$3),ROUNDUP(MONTH($F33)/3,0)<=X$4),$C33*(1+$D33)^((X$3-$F33)/365),IF(ROUND(W33,0)=0,0,W33*(1+$D33))) -> 0 | Y33: =A33&" "&B33 -> PE029 La Pointe Investments LLC
A34: PE030 | B34: King Partner Pref convert | C34: 6050000 | D34: 0.08 | E34: 0.053 | F34: 45746 | G34: =+C34/lgh_inputs!$D$10 -> 242000 | I34: =IF($F34<I$3,C34*(1+D34)^((I$3-$F$5)/365),0) -> 0 | J34: =IF(AND(YEAR($F34)=YEAR(J$3),ROUNDUP(MONTH($F34)/3,0)<=J$4),$C34*(1+$D34)^((J$3-$F34)/365),IF(ROUND(I34,0)=0,0,I34*(1+$D34))) -> 0 | K34: =IF(AND(YEAR($F34)=YEAR(K$3),ROUNDUP(MONTH($F34)/3,0)<=K$4),$C34*(1+$D34)^((K$3-$F34)/365),IF(ROUND(J34,0)=0,0,J34*(1+$D34))) -> 0 | L34: =IF(AND(YEAR($F34)=YEAR(L$3),ROUNDUP(MONTH($F34)/3,0)<=L$4),$C34*(1+$D34)^((L$3-$F34)/365),IF(ROUND(K34,0)=0,0,K34*(1+$D34))) -> 0 | M34: =IF(AND(YEAR($F34)=YEAR(M$3),ROUNDUP(MONTH($F34)/3,0)=M$4),$C34*(1+$D34/4)^((M$3-$F34)/91),IF(ROUND(L34,0)=0,0,L34*(1+$D34/4))) -> 6051316.7 | N34: =IF(AND(YEAR($F34)=YEAR(N$3),ROUNDUP(MONTH($F34)/3,0)=N$4),$C34*(1+$D34/4)^((N$3-$F34)/91),IF(ROUND(M34,0)=0,0,M34*(1+$D34/4))) -> 6172343 | O34: =IF(AND(YEAR($F34)=YEAR(O$3),ROUNDUP(MONTH($F34)/3,0)=O$4),$C34*(1+$D34/4)^((O$3-$F34)/91),IF(ROUND(N34,0)=0,0,N34*(1+$D34/4))) -> 6295789.9 | P34: =IF(AND(YEAR($F34)=YEAR(P$3),ROUNDUP(MONTH($F34)/3,0)=P$4),$C34*(1+$D34/4)^((P$3-$F34)/91),IF(ROUND(O34,0)=0,0,O34*(1+$D34/4))) -> 6421705.7 | Q34: =IF(AND(YEAR($F34)=YEAR(Q$3),ROUNDUP(MONTH($F34)/3,0)=Q$4),$C34*(1+$D34/4)^((Q$3-$F34)/91),IF(ROUND(P34,0)=0,0,P34*(1+$D34/4))) -> 6550139.8 | R34: =IF(AND(YEAR($F34)=YEAR(R$3),ROUNDUP(MONTH($F34)/3,0)=R$4),$C34*(1+$D34/4)^((R$3-$F34)/91),IF(ROUND(Q34,0)=0,0,Q34*(1+$D34/4))) -> 6681142.6 | S34: =IF(AND(YEAR($F34)=YEAR(S$3),ROUNDUP(MONTH($F34)/3,0)=S$4),$C34*(1+$D34/4)^((S$3-$F34)/91),IF(ROUND(R34,0)=0,0,R34*(1+$D34/4))) -> 6814765.4 | T34: =IF(AND(YEAR($F34)=YEAR(T$3),ROUNDUP(MONTH($F34)/3,0)=T$4),$C34*(1+$D34/4)^((T$3-$F34)/91),IF(ROUND(S34,0)=0,0,S34*(1+$D34/4))) -> 6951060.8 | U34: =IF(AND(YEAR($F34)=YEAR(U$3),ROUNDUP(MONTH($F34)/3,0)<=U$4),$C34*(1+$D34)^((U$3-$F34)/365),IF(ROUND(T34,0)=0,0,T34*(1+$D34))) -> 7507145.6 | V34: =IF(AND(YEAR($F34)=YEAR(V$3),ROUNDUP(MONTH($F34)/3,0)<=V$4),$C34*(1+$D34)^((V$3-$F34)/365),IF(ROUND(U34,0)=0,0,U34*(1+$D34))) -> 8107717.3 | W34: =IF(AND(YEAR($F34)=YEAR(W$3),ROUNDUP(MONTH($F34)/3,0)<=W$4),$C34*(1+$D34)^((W$3-$F34)/365),IF(ROUND(V34,0)=0,0,V34*(1+$D34))) -> 8756334.6 | X34: =IF(AND(YEAR($F34)=YEAR(X$3),ROUNDUP(MONTH($F34)/3,0)<=X$4),$C34*(1+$D34)^((X$3-$F34)/365),IF(ROUND(W34,0)=0,0,W34*(1+$D34))) -> 9456841.4 | Y34: =A34&" "&B34 -> PE030 King Partner Pref convert
A35: PE031 | B35: Edwin2 convert | C35: 1200000 | D35: 0.08 | E35: 0.053 | F35: 46021 | G35: =+C35/lgh_inputs!$D$10 -> 48000 | I35: =IF($F35<I$3,C35*(1+D35)^((I$3-$F$5)/365),0) -> 0 | J35: =IF(AND(YEAR($F35)=YEAR(J$3),ROUNDUP(MONTH($F35)/3,0)<=J$4),$C35*(1+$D35)^((J$3-$F35)/365),IF(ROUND(I35,0)=0,0,I35*(1+$D35))) -> 0 | K35: =IF(AND(YEAR($F35)=YEAR(K$3),ROUNDUP(MONTH($F35)/3,0)<=K$4),$C35*(1+$D35)^((K$3-$F35)/365),IF(ROUND(J35,0)=0,0,J35*(1+$D35))) -> 0 | L35: =IF(AND(YEAR($F35)=YEAR(L$3),ROUNDUP(MONTH($F35)/3,0)<=L$4),$C35*(1+$D35)^((L$3-$F35)/365),IF(ROUND(K35,0)=0,0,K35*(1+$D35))) -> 0 | M35: =IF(AND(YEAR($F35)=YEAR(M$3),ROUNDUP(MONTH($F35)/3,0)=M$4),$C35*(1+$D35/4)^((M$3-$F35)/91),IF(ROUND(L35,0)=0,0,L35*(1+$D35/4))) -> 0 | N35: =IF(AND(YEAR($F35)=YEAR(N$3),ROUNDUP(MONTH($F35)/3,0)=N$4),$C35*(1+$D35/4)^((N$3-$F35)/91),IF(ROUND(M35,0)=0,0,M35*(1+$D35/4))) -> 0 | O35: =IF(AND(YEAR($F35)=YEAR(O$3),ROUNDUP(MONTH($F35)/3,0)=O$4),$C35*(1+$D35/4)^((O$3-$F35)/91),IF(ROUND(N35,0)=0,0,N35*(1+$D35/4))) -> 0 | P35: =IF(AND(YEAR($F35)=YEAR(P$3),ROUNDUP(MONTH($F35)/3,0)=P$4),$C35*(1+$D35/4)^((P$3-$F35)/91),IF(ROUND(O35,0)=0,0,O35*(1+$D35/4))) -> 1200261.2 | Q35: =IF(AND(YEAR($F35)=YEAR(Q$3),ROUNDUP(MONTH($F35)/3,0)=Q$4),$C35*(1+$D35/4)^((Q$3-$F35)/91),IF(ROUND(P35,0)=0,0,P35*(1+$D35/4))) -> 1224266.4 | R35: =IF(AND(YEAR($F35)=YEAR(R$3),ROUNDUP(MONTH($F35)/3,0)=R$4),$C35*(1+$D35/4)^((R$3-$F35)/91),IF(ROUND(Q35,0)=0,0,Q35*(1+$D35/4))) -> 1248751.7 | S35: =IF(AND(YEAR($F35)=YEAR(S$3),ROUNDUP(MONTH($F35)/3,0)=S$4),$C35*(1+$D35/4)^((S$3-$F35)/91),IF(ROUND(R35,0)=0,0,R35*(1+$D35/4))) -> 1273726.7 | T35: =IF(AND(YEAR($F35)=YEAR(T$3),ROUNDUP(MONTH($F35)/3,0)=T$4),$C35*(1+$D35/4)^((T$3-$F35)/91),IF(ROUND(S35,0)=0,0,S35*(1+$D35/4))) -> 1299201.3 | U35: =IF(AND(YEAR($F35)=YEAR(U$3),ROUNDUP(MONTH($F35)/3,0)<=U$4),$C35*(1+$D35)^((U$3-$F35)/365),IF(ROUND(T35,0)=0,0,T35*(1+$D35))) -> 1403137.4 | V35: =IF(AND(YEAR($F35)=YEAR(V$3),ROUNDUP(MONTH($F35)/3,0)<=V$4),$C35*(1+$D35)^((V$3-$F35)/365),IF(ROUND(U35,0)=0,0,U35*(1+$D35))) -> 1515388.4 | W35: =IF(AND(YEAR($F35)=YEAR(W$3),ROUNDUP(MONTH($F35)/3,0)<=W$4),$C35*(1+$D35)^((W$3-$F35)/365),IF(ROUND(V35,0)=0,0,V35*(1+$D35))) -> 1636619.4 | X35: =IF(AND(YEAR($F35)=YEAR(X$3),ROUNDUP(MONTH($F35)/3,0)<=X$4),$C35*(1+$D35)^((X$3-$F35)/365),IF(ROUND(W35,0)=0,0,W35*(1+$D35))) -> 1767549 | Y35: =A35&" "&B35 -> PE031 Edwin2 convert
A36: PE032 | B36: Buddy | C36: 1500000 | D36: 0.08 | E36: 0.053 | F36: 46068 | G36: =+C36/lgh_inputs!$D$10 -> 60000 | I36: =IF($F36<I$3,C36*(1+D36)^((I$3-$F$5)/365),0) -> 0 | J36: =IF(AND(YEAR($F36)=YEAR(J$3),ROUNDUP(MONTH($F36)/3,0)<=J$4),$C36*(1+$D36)^((J$3-$F36)/365),IF(ROUND(I36,0)=0,0,I36*(1+$D36))) -> 0 | K36: =IF(AND(YEAR($F36)=YEAR(K$3),ROUNDUP(MONTH($F36)/3,0)<=K$4),$C36*(1+$D36)^((K$3-$F36)/365),IF(ROUND(J36,0)=0,0,J36*(1+$D36))) -> 0 | L36: =IF(AND(YEAR($F36)=YEAR(L$3),ROUNDUP(MONTH($F36)/3,0)<=L$4),$C36*(1+$D36)^((L$3-$F36)/365),IF(ROUND(K36,0)=0,0,K36*(1+$D36))) -> 0 | M36: =IF(AND(YEAR($F36)=YEAR(M$3),ROUNDUP(MONTH($F36)/3,0)=M$4),$C36*(1+$D36/4)^((M$3-$F36)/91),IF(ROUND(L36,0)=0,0,L36*(1+$D36/4))) -> 0 | N36: =IF(AND(YEAR($F36)=YEAR(N$3),ROUNDUP(MONTH($F36)/3,0)=N$4),$C36*(1+$D36/4)^((N$3-$F36)/91),IF(ROUND(M36,0)=0,0,M36*(1+$D36/4))) -> 0 | O36: =IF(AND(YEAR($F36)=YEAR(O$3),ROUNDUP(MONTH($F36)/3,0)=O$4),$C36*(1+$D36/4)^((O$3-$F36)/91),IF(ROUND(N36,0)=0,0,N36*(1+$D36/4))) -> 0 | P36: =IF(AND(YEAR($F36)=YEAR(P$3),ROUNDUP(MONTH($F36)/3,0)=P$4),$C36*(1+$D36/4)^((P$3-$F36)/91),IF(ROUND(O36,0)=0,0,O36*(1+$D36/4))) -> 0 | Q36: =IF(AND(YEAR($F36)=YEAR(Q$3),ROUNDUP(MONTH($F36)/3,0)=Q$4),$C36*(1+$D36/4)^((Q$3-$F36)/91),IF(ROUND(P36,0)=0,0,P36*(1+$D36/4))) -> 1514431.3 | R36: =IF(AND(YEAR($F36)=YEAR(R$3),ROUNDUP(MONTH($F36)/3,0)=R$4),$C36*(1+$D36/4)^((R$3-$F36)/91),IF(ROUND(Q36,0)=0,0,Q36*(1+$D36/4))) -> 1544720 | S36: =IF(AND(YEAR($F36)=YEAR(S$3),ROUNDUP(MONTH($F36)/3,0)=S$4),$C36*(1+$D36/4)^((S$3-$F36)/91),IF(ROUND(R36,0)=0,0,R36*(1+$D36/4))) -> 1575614.3 | T36: =IF(AND(YEAR($F36)=YEAR(T$3),ROUNDUP(MONTH($F36)/3,0)=T$4),$C36*(1+$D36/4)^((T$3-$F36)/91),IF(ROUND(S36,0)=0,0,S36*(1+$D36/4))) -> 1607126.6 | U36: =IF(AND(YEAR($F36)=YEAR(U$3),ROUNDUP(MONTH($F36)/3,0)<=U$4),$C36*(1+$D36)^((U$3-$F36)/365),IF(ROUND(T36,0)=0,0,T36*(1+$D36))) -> 1735696.8 | V36: =IF(AND(YEAR($F36)=YEAR(V$3),ROUNDUP(MONTH($F36)/3,0)<=V$4),$C36*(1+$D36)^((V$3-$F36)/365),IF(ROUND(U36,0)=0,0,U36*(1+$D36))) -> 1874552.5 | W36: =IF(AND(YEAR($F36)=YEAR(W$3),ROUNDUP(MONTH($F36)/3,0)<=W$4),$C36*(1+$D36)^((W$3-$F36)/365),IF(ROUND(V36,0)=0,0,V36*(1+$D36))) -> 2024516.7 | X36: =IF(AND(YEAR($F36)=YEAR(X$3),ROUNDUP(MONTH($F36)/3,0)<=X$4),$C36*(1+$D36)^((X$3-$F36)/365),IF(ROUND(W36,0)=0,0,W36*(1+$D36))) -> 2186478 | Y36: =A36&" "&B36 -> PE032 Buddy
A37: PE033 | B37: PFNGT LLC | C37: =-C38 -> -1039509 | D37: 0.08 | E37: 0 | F37: 44365 | G37: =+C37/lgh_inputs!$D$10 -> -41580.36 | I37: =IF($F37<I$3,C37*(1+D37)^((I$3-$F$5)/365),0) -> -1083368.9 | J37: =IF(AND(YEAR($F37)=YEAR(J$3),ROUNDUP(MONTH($F37)/3,0)<=J$4),$C37*(1+$D37)^((J$3-$F37)/365),IF(ROUND(I37,0)=0,0,I37*(1+$D37))) -> -1170038.4 | K37: =IF(AND(YEAR($F37)=YEAR(K$3),ROUNDUP(MONTH($F37)/3,0)<=K$4),$C37*(1+$D37)^((K$3-$F37)/365),IF(ROUND(J37,0)=0,0,J37*(1+$D37))) -> -1263641.5 | L37: =IF(AND(YEAR($F37)=YEAR(L$3),ROUNDUP(MONTH($F37)/3,0)<=L$4),$C37*(1+$D37)^((L$3-$F37)/365),IF(ROUND(K37,0)=0,0,K37*(1+$D37))) -> -1364732.8 | M37: =IF(AND(YEAR($F37)=YEAR(M$3),ROUNDUP(MONTH($F37)/3,0)=M$4),$C37*(1+$D37/4)^((M$3-$F37)/91),IF(ROUND(L37,0)=0,0,L37*(1+$D37/4))) -> -1392027.4 | N37: =IF(AND(YEAR($F37)=YEAR(N$3),ROUNDUP(MONTH($F37)/3,0)=N$4),$C37*(1+$D37/4)^((N$3-$F37)/91),IF(ROUND(M37,0)=0,0,M37*(1+$D37/4))) -> -1419868 | O37: =IF(AND(YEAR($F37)=YEAR(O$3),ROUNDUP(MONTH($F37)/3,0)=O$4),$C37*(1+$D37/4)^((O$3-$F37)/91),IF(ROUND(N37,0)=0,0,N37*(1+$D37/4))) -> -1448265.3 | P37: =IF(AND(YEAR($F37)=YEAR(P$3),ROUNDUP(MONTH($F37)/3,0)=P$4),$C37*(1+$D37/4)^((P$3-$F37)/91),IF(ROUND(O37,0)=0,0,O37*(1+$D37/4))) -> -1477230.6 | Q37: =IF(AND(YEAR($F37)=YEAR(Q$3),ROUNDUP(MONTH($F37)/3,0)=Q$4),$C37*(1+$D37/4)^((Q$3-$F37)/91),IF(ROUND(P37,0)=0,0,P37*(1+$D37/4))) -> -1506775.2 | R37: =IF(AND(YEAR($F37)=YEAR(R$3),ROUNDUP(MONTH($F37)/3,0)=R$4),$C37*(1+$D37/4)^((R$3-$F37)/91),IF(ROUND(Q37,0)=0,0,Q37*(1+$D37/4))) -> -1536910.8 | S37: =IF(AND(YEAR($F37)=YEAR(S$3),ROUNDUP(MONTH($F37)/3,0)=S$4),$C37*(1+$D37/4)^((S$3-$F37)/91),IF(ROUND(R37,0)=0,0,R37*(1+$D37/4))) -> -1567649 | T37: =IF(AND(YEAR($F37)=YEAR(T$3),ROUNDUP(MONTH($F37)/3,0)=T$4),$C37*(1+$D37/4)^((T$3-$F37)/91),IF(ROUND(S37,0)=0,0,S37*(1+$D37/4))) -> -1599001.9 | U37: =IF(AND(YEAR($F37)=YEAR(U$3),ROUNDUP(MONTH($F37)/3,0)<=U$4),$C37*(1+$D37)^((U$3-$F37)/365),IF(ROUND(T37,0)=0,0,T37*(1+$D37))) -> -1726922.1 | V37: =IF(AND(YEAR($F37)=YEAR(V$3),ROUNDUP(MONTH($F37)/3,0)<=V$4),$C37*(1+$D37)^((V$3-$F37)/365),IF(ROUND(U37,0)=0,0,U37*(1+$D37))) -> -1865075.9 | W37: =IF(AND(YEAR($F37)=YEAR(W$3),ROUNDUP(MONTH($F37)/3,0)<=W$4),$C37*(1+$D37)^((W$3-$F37)/365),IF(ROUND(V37,0)=0,0,V37*(1+$D37))) -> -2014281.9 | X37: =IF(AND(YEAR($F37)=YEAR(X$3),ROUNDUP(MONTH($F37)/3,0)<=X$4),$C37*(1+$D37)^((X$3-$F37)/365),IF(ROUND(W37,0)=0,0,W37*(1+$D37))) -> -2175424.5 | Y37: =A37&" "&B37 -> PE033 PFNGT LLC
A38: PE034 | B38: Cambrian | C38: 1039509 | D38: 0.08 | E38: 0 | F38: 44365 | G38: =+C38/lgh_inputs!$D$10 -> 41580.36 | I38: =IF($F38<I$3,C38*(1+D38)^((I$3-$F$5)/365),0) -> 1083368.9 | J38: =IF(AND(YEAR($F38)=YEAR(J$3),ROUNDUP(MONTH($F38)/3,0)<=J$4),$C38*(1+$D38)^((J$3-$F38)/365),IF(ROUND(I38,0)=0,0,I38*(1+$D38))) -> 1170038.4 | K38: =IF(AND(YEAR($F38)=YEAR(K$3),ROUNDUP(MONTH($F38)/3,0)<=K$4),$C38*(1+$D38)^((K$3-$F38)/365),IF(ROUND(J38,0)=0,0,J38*(1+$D38))) -> 1263641.5 | L38: =IF(AND(YEAR($F38)=YEAR(L$3),ROUNDUP(MONTH($F38)/3,0)<=L$4),$C38*(1+$D38)^((L$3-$F38)/365),IF(ROUND(K38,0)=0,0,K38*(1+$D38))) -> 1364732.8 | M38: =IF(AND(YEAR($F38)=YEAR(M$3),ROUNDUP(MONTH($F38)/3,0)=M$4),$C38*(1+$D38/4)^((M$3-$F38)/91),IF(ROUND(L38,0)=0,0,L38*(1+$D38/4))) -> 1392027.4 | N38: =IF(AND(YEAR($F38)=YEAR(N$3),ROUNDUP(MONTH($F38)/3,0)=N$4),$C38*(1+$D38/4)^((N$3-$F38)/91),IF(ROUND(M38,0)=0,0,M38*(1+$D38/4))) -> 1419868 | O38: =IF(AND(YEAR($F38)=YEAR(O$3),ROUNDUP(MONTH($F38)/3,0)=O$4),$C38*(1+$D38/4)^((O$3-$F38)/91),IF(ROUND(N38,0)=0,0,N38*(1+$D38/4))) -> 1448265.3 | P38: =IF(AND(YEAR($F38)=YEAR(P$3),ROUNDUP(MONTH($F38)/3,0)=P$4),$C38*(1+$D38/4)^((P$3-$F38)/91),IF(ROUND(O38,0)=0,0,O38*(1+$D38/4))) -> 1477230.6 | Q38: =IF(AND(YEAR($F38)=YEAR(Q$3),ROUNDUP(MONTH($F38)/3,0)=Q$4),$C38*(1+$D38/4)^((Q$3-$F38)/91),IF(ROUND(P38,0)=0,0,P38*(1+$D38/4))) -> 1506775.2 | R38: =IF(AND(YEAR($F38)=YEAR(R$3),ROUNDUP(MONTH($F38)/3,0)=R$4),$C38*(1+$D38/4)^((R$3-$F38)/91),IF(ROUND(Q38,0)=0,0,Q38*(1+$D38/4))) -> 1536910.8 | S38: =IF(AND(YEAR($F38)=YEAR(S$3),ROUNDUP(MONTH($F38)/3,0)=S$4),$C38*(1+$D38/4)^((S$3-$F38)/91),IF(ROUND(R38,0)=0,0,R38*(1+$D38/4))) -> 1567649 | T38: =IF(AND(YEAR($F38)=YEAR(T$3),ROUNDUP(MONTH($F38)/3,0)=T$4),$C38*(1+$D38/4)^((T$3-$F38)/91),IF(ROUND(S38,0)=0,0,S38*(1+$D38/4))) -> 1599001.9 | U38: =IF(AND(YEAR($F38)=YEAR(U$3),ROUNDUP(MONTH($F38)/3,0)<=U$4),$C38*(1+$D38)^((U$3-$F38)/365),IF(ROUND(T38,0)=0,0,T38*(1+$D38))) -> 1726922.1 | V38: =IF(AND(YEAR($F38)=YEAR(V$3),ROUNDUP(MONTH($F38)/3,0)<=V$4),$C38*(1+$D38)^((V$3-$F38)/365),IF(ROUND(U38,0)=0,0,U38*(1+$D38))) -> 1865075.9 | W38: =IF(AND(YEAR($F38)=YEAR(W$3),ROUNDUP(MONTH($F38)/3,0)<=W$4),$C38*(1+$D38)^((W$3-$F38)/365),IF(ROUND(V38,0)=0,0,V38*(1+$D38))) -> 2014281.9 | X38: =IF(AND(YEAR($F38)=YEAR(X$3),ROUNDUP(MONTH($F38)/3,0)<=X$4),$C38*(1+$D38)^((X$3-$F38)/365),IF(ROUND(W38,0)=0,0,W38*(1+$D38))) -> 2175424.5 | Y38: =A38&" "&B38 -> PE034 Cambrian
A39: PE035 | B39: guy | C39: 1000000 | D39: 0.08 | E39: 0.053 | F39: 46115 | G39: =+C39/lgh_inputs!$D$10 -> 40000 | I39: =IF($F39<I$3,C39*(1+D39)^((I$3-$F$5)/365),0) -> 0 | J39: =IF(AND(YEAR($F39)=YEAR(J$3),ROUNDUP(MONTH($F39)/3,0)<=J$4),$C39*(1+$D39)^((J$3-$F39)/365),IF(ROUND(I39,0)=0,0,I39*(1+$D39))) -> 0 | K39: =IF(AND(YEAR($F39)=YEAR(K$3),ROUNDUP(MONTH($F39)/3,0)<=K$4),$C39*(1+$D39)^((K$3-$F39)/365),IF(ROUND(J39,0)=0,0,J39*(1+$D39))) -> 0 | L39: =IF(AND(YEAR($F39)=YEAR(L$3),ROUNDUP(MONTH($F39)/3,0)<=L$4),$C39*(1+$D39)^((L$3-$F39)/365),IF(ROUND(K39,0)=0,0,K39*(1+$D39))) -> 0 | M39: =IF(AND(YEAR($F39)=YEAR(M$3),ROUNDUP(MONTH($F39)/3,0)=M$4),$C39*(1+$D39/4)^((M$3-$F39)/91),IF(ROUND(L39,0)=0,0,L39*(1+$D39/4))) -> 0 | N39: =IF(AND(YEAR($F39)=YEAR(N$3),ROUNDUP(MONTH($F39)/3,0)=N$4),$C39*(1+$D39/4)^((N$3-$F39)/91),IF(ROUND(M39,0)=0,0,M39*(1+$D39/4))) -> 0 | O39: =IF(AND(YEAR($F39)=YEAR(O$3),ROUNDUP(MONTH($F39)/3,0)=O$4),$C39*(1+$D39/4)^((O$3-$F39)/91),IF(ROUND(N39,0)=0,0,N39*(1+$D39/4))) -> 0 | P39: =IF(AND(YEAR($F39)=YEAR(P$3),ROUNDUP(MONTH($F39)/3,0)=P$4),$C39*(1+$D39/4)^((P$3-$F39)/91),IF(ROUND(O39,0)=0,0,O39*(1+$D39/4))) -> 0 | Q39: =IF(AND(YEAR($F39)=YEAR(Q$3),ROUNDUP(MONTH($F39)/3,0)=Q$4),$C39*(1+$D39/4)^((Q$3-$F39)/91),IF(ROUND(P39,0)=0,0,P39*(1+$D39/4))) -> 0 | R39: =IF(AND(YEAR($F39)=YEAR(R$3),ROUNDUP(MONTH($F39)/3,0)=R$4),$C39*(1+$D39/4)^((R$3-$F39)/91),IF(ROUND(Q39,0)=0,0,Q39*(1+$D39/4))) -> 1019334.3 | S39: =IF(AND(YEAR($F39)=YEAR(S$3),ROUNDUP(MONTH($F39)/3,0)=S$4),$C39*(1+$D39/4)^((S$3-$F39)/91),IF(ROUND(R39,0)=0,0,R39*(1+$D39/4))) -> 1039721 | T39: =IF(AND(YEAR($F39)=YEAR(T$3),ROUNDUP(MONTH($F39)/3,0)=T$4),$C39*(1+$D39/4)^((T$3-$F39)/91),IF(ROUND(S39,0)=0,0,S39*(1+$D39/4))) -> 1060515.4 | U39: =IF(AND(YEAR($F39)=YEAR(U$3),ROUNDUP(MONTH($F39)/3,0)<=U$4),$C39*(1+$D39)^((U$3-$F39)/365),IF(ROUND(T39,0)=0,0,T39*(1+$D39))) -> 1145356.7 | V39: =IF(AND(YEAR($F39)=YEAR(V$3),ROUNDUP(MONTH($F39)/3,0)<=V$4),$C39*(1+$D39)^((V$3-$F39)/365),IF(ROUND(U39,0)=0,0,U39*(1+$D39))) -> 1236985.2 | W39: =IF(AND(YEAR($F39)=YEAR(W$3),ROUNDUP(MONTH($F39)/3,0)<=W$4),$C39*(1+$D39)^((W$3-$F39)/365),IF(ROUND(V39,0)=0,0,V39*(1+$D39))) -> 1335944 | X39: =IF(AND(YEAR($F39)=YEAR(X$3),ROUNDUP(MONTH($F39)/3,0)<=X$4),$C39*(1+$D39)^((X$3-$F39)/365),IF(ROUND(W39,0)=0,0,W39*(1+$D39))) -> 1442819.5 | Y39: =A39&" "&B39 -> PE035 guy
A40: PE036 | B40: La Pointe Investments LLC | C40: 3000000 | D40: 0.08 | E40: 0.053 | F40: 46387 | G40: =+C40/lgh_inputs!$D$10 -> 120000 | I40: =IF($F40<I$3,C40*(1+D40)^((I$3-$F$5)/365),0) -> 0 | J40: =IF(AND(YEAR($F40)=YEAR(J$3),ROUNDUP(MONTH($F40)/3,0)<=J$4),$C40*(1+$D40)^((J$3-$F40)/365),IF(ROUND(I40,0)=0,0,I40*(1+$D40))) -> 0 | K40: =IF(AND(YEAR($F40)=YEAR(K$3),ROUNDUP(MONTH($F40)/3,0)<=K$4),$C40*(1+$D40)^((K$3-$F40)/365),IF(ROUND(J40,0)=0,0,J40*(1+$D40))) -> 0 | L40: =IF(AND(YEAR($F40)=YEAR(L$3),ROUNDUP(MONTH($F40)/3,0)<=L$4),$C40*(1+$D40)^((L$3-$F40)/365),IF(ROUND(K40,0)=0,0,K40*(1+$D40))) -> 0 | M40: =IF(AND(YEAR($F40)=YEAR(M$3),ROUNDUP(MONTH($F40)/3,0)=M$4),$C40*(1+$D40/4)^((M$3-$F40)/91),IF(ROUND(L40,0)=0,0,L40*(1+$D40/4))) -> 0 | N40: =IF(AND(YEAR($F40)=YEAR(N$3),ROUNDUP(MONTH($F40)/3,0)=N$4),$C40*(1+$D40/4)^((N$3-$F40)/91),IF(ROUND(M40,0)=0,0,M40*(1+$D40/4))) -> 0 | O40: =IF(AND(YEAR($F40)=YEAR(O$3),ROUNDUP(MONTH($F40)/3,0)=O$4),$C40*(1+$D40/4)^((O$3-$F40)/91),IF(ROUND(N40,0)=0,0,N40*(1+$D40/4))) -> 0 | P40: =IF(AND(YEAR($F40)=YEAR(P$3),ROUNDUP(MONTH($F40)/3,0)=P$4),$C40*(1+$D40/4)^((P$3-$F40)/91),IF(ROUND(O40,0)=0,0,O40*(1+$D40/4))) -> 0 | Q40: =IF(AND(YEAR($F40)=YEAR(Q$3),ROUNDUP(MONTH($F40)/3,0)=Q$4),$C40*(1+$D40/4)^((Q$3-$F40)/91),IF(ROUND(P40,0)=0,0,P40*(1+$D40/4))) -> 0 | R40: =IF(AND(YEAR($F40)=YEAR(R$3),ROUNDUP(MONTH($F40)/3,0)=R$4),$C40*(1+$D40/4)^((R$3-$F40)/91),IF(ROUND(Q40,0)=0,0,Q40*(1+$D40/4))) -> 0 | S40: =IF(AND(YEAR($F40)=YEAR(S$3),ROUNDUP(MONTH($F40)/3,0)=S$4),$C40*(1+$D40/4)^((S$3-$F40)/91),IF(ROUND(R40,0)=0,0,R40*(1+$D40/4))) -> 0 | T40: =IF(AND(YEAR($F40)=YEAR(T$3),ROUNDUP(MONTH($F40)/3,0)=T$4),$C40*(1+$D40/4)^((T$3-$F40)/91),IF(ROUND(S40,0)=0,0,S40*(1+$D40/4))) -> 3000000 | U40: =IF(AND(YEAR($F40)=YEAR(U$3),ROUNDUP(MONTH($F40)/3,0)<=U$4),$C40*(1+$D40)^((U$3-$F40)/365),IF(ROUND(T40,0)=0,0,T40*(1+$D40))) -> 3240000 | V40: =IF(AND(YEAR($F40)=YEAR(V$3),ROUNDUP(MONTH($F40)/3,0)<=V$4),$C40*(1+$D40)^((V$3-$F40)/365),IF(ROUND(U40,0)=0,0,U40*(1+$D40))) -> 3499200 | W40: =IF(AND(YEAR($F40)=YEAR(W$3),ROUNDUP(MONTH($F40)/3,0)<=W$4),$C40*(1+$D40)^((W$3-$F40)/365),IF(ROUND(V40,0)=0,0,V40*(1+$D40))) -> 3779136 | X40: =IF(AND(YEAR($F40)=YEAR(X$3),ROUNDUP(MONTH($F40)/3,0)<=X$4),$C40*(1+$D40)^((X$3-$F40)/365),IF(ROUND(W40,0)=0,0,W40*(1+$D40))) -> 4081466.9 | Y40: =A40&" "&B40 -> PE036 La Pointe Investments LLC
A41: PE037 | G41: =+C41/lgh_inputs!$D$10 -> 0 | I41: =IF($F41<I$3,C41*(1+D41)^((I$3-$F$5)/365),0) -> 0 | J41: =IF(AND(YEAR($F41)=YEAR(J$3),ROUNDUP(MONTH($F41)/3,0)<=J$4),$C41*(1+$D41)^((J$3-$F41)/365),IF(ROUND(I41,0)=0,0,I41*(1+$D41))) -> 0 | K41: =IF(AND(YEAR($F41)=YEAR(K$3),ROUNDUP(MONTH($F41)/3,0)<=K$4),$C41*(1+$D41)^((K$3-$F41)/365),IF(ROUND(J41,0)=0,0,J41*(1+$D41))) -> 0 | L41: =IF(AND(YEAR($F41)=YEAR(L$3),ROUNDUP(MONTH($F41)/3,0)<=L$4),$C41*(1+$D41)^((L$3-$F41)/365),IF(ROUND(K41,0)=0,0,K41*(1+$D41))) -> 0 | M41: =IF(AND(YEAR($F41)=YEAR(M$3),ROUNDUP(MONTH($F41)/3,0)=M$4),$C41*(1+$D41/4)^((M$3-$F41)/91),IF(ROUND(L41,0)=0,0,L41*(1+$D41/4))) -> 0 | N41: =IF(AND(YEAR($F41)=YEAR(N$3),ROUNDUP(MONTH($F41)/3,0)=N$4),$C41*(1+$D41/4)^((N$3-$F41)/91),IF(ROUND(M41,0)=0,0,M41*(1+$D41/4))) -> 0 | O41: =IF(AND(YEAR($F41)=YEAR(O$3),ROUNDUP(MONTH($F41)/3,0)=O$4),$C41*(1+$D41/4)^((O$3-$F41)/91),IF(ROUND(N41,0)=0,0,N41*(1+$D41/4))) -> 0 | P41: =IF(AND(YEAR($F41)=YEAR(P$3),ROUNDUP(MONTH($F41)/3,0)=P$4),$C41*(1+$D41/4)^((P$3-$F41)/91),IF(ROUND(O41,0)=0,0,O41*(1+$D41/4))) -> 0 | Q41: =IF(AND(YEAR($F41)=YEAR(Q$3),ROUNDUP(MONTH($F41)/3,0)=Q$4),$C41*(1+$D41/4)^((Q$3-$F41)/91),IF(ROUND(P41,0)=0,0,P41*(1+$D41/4))) -> 0 | R41: =IF(AND(YEAR($F41)=YEAR(R$3),ROUNDUP(MONTH($F41)/3,0)=R$4),$C41*(1+$D41/4)^((R$3-$F41)/91),IF(ROUND(Q41,0)=0,0,Q41*(1+$D41/4))) -> 0 | S41: =IF(AND(YEAR($F41)=YEAR(S$3),ROUNDUP(MONTH($F41)/3,0)=S$4),$C41*(1+$D41/4)^((S$3-$F41)/91),IF(ROUND(R41,0)=0,0,R41*(1+$D41/4))) -> 0 | T41: =IF(AND(YEAR($F41)=YEAR(T$3),ROUNDUP(MONTH($F41)/3,0)=T$4),$C41*(1+$D41/4)^((T$3-$F41)/91),IF(ROUND(S41,0)=0,0,S41*(1+$D41/4))) -> 0 | U41: =IF(AND(YEAR($F41)=YEAR(U$3),ROUNDUP(MONTH($F41)/3,0)<=U$4),$C41*(1+$D41)^((U$3-$F41)/365),IF(ROUND(T41,0)=0,0,T41*(1+$D41))) -> 0 | V41: =IF(AND(YEAR($F41)=YEAR(V$3),ROUNDUP(MONTH($F41)/3,0)<=V$4),$C41*(1+$D41)^((V$3-$F41)/365),IF(ROUND(U41,0)=0,0,U41*(1+$D41))) -> 0 | W41: =IF(AND(YEAR($F41)=YEAR(W$3),ROUNDUP(MONTH($F41)/3,0)<=W$4),$C41*(1+$D41)^((W$3-$F41)/365),IF(ROUND(V41,0)=0,0,V41*(1+$D41))) -> 0 | X41: =IF(AND(YEAR($F41)=YEAR(X$3),ROUNDUP(MONTH($F41)/3,0)<=X$4),$C41*(1+$D41)^((X$3-$F41)/365),IF(ROUND(W41,0)=0,0,W41*(1+$D41))) -> 0 | Y41: =A41&" "&B41 -> PE037
A42: PE038 | G42: =+C42/lgh_inputs!$D$10 -> 0 | I42: =IF($F42<I$3,C42*(1+D42)^((I$3-$F$5)/365),0) -> 0 | J42: =IF(AND(YEAR($F42)=YEAR(J$3),ROUNDUP(MONTH($F42)/3,0)<=J$4),$C42*(1+$D42)^((J$3-$F42)/365),IF(ROUND(I42,0)=0,0,I42*(1+$D42))) -> 0 | K42: =IF(AND(YEAR($F42)=YEAR(K$3),ROUNDUP(MONTH($F42)/3,0)<=K$4),$C42*(1+$D42)^((K$3-$F42)/365),IF(ROUND(J42,0)=0,0,J42*(1+$D42))) -> 0 | L42: =IF(AND(YEAR($F42)=YEAR(L$3),ROUNDUP(MONTH($F42)/3,0)<=L$4),$C42*(1+$D42)^((L$3-$F42)/365),IF(ROUND(K42,0)=0,0,K42*(1+$D42))) -> 0 | M42: =IF(AND(YEAR($F42)=YEAR(M$3),ROUNDUP(MONTH($F42)/3,0)=M$4),$C42*(1+$D42/4)^((M$3-$F42)/91),IF(ROUND(L42,0)=0,0,L42*(1+$D42/4))) -> 0 | N42: =IF(AND(YEAR($F42)=YEAR(N$3),ROUNDUP(MONTH($F42)/3,0)=N$4),$C42*(1+$D42/4)^((N$3-$F42)/91),IF(ROUND(M42,0)=0,0,M42*(1+$D42/4))) -> 0 | O42: =IF(AND(YEAR($F42)=YEAR(O$3),ROUNDUP(MONTH($F42)/3,0)=O$4),$C42*(1+$D42/4)^((O$3-$F42)/91),IF(ROUND(N42,0)=0,0,N42*(1+$D42/4))) -> 0 | P42: =IF(AND(YEAR($F42)=YEAR(P$3),ROUNDUP(MONTH($F42)/3,0)=P$4),$C42*(1+$D42/4)^((P$3-$F42)/91),IF(ROUND(O42,0)=0,0,O42*(1+$D42/4))) -> 0 | Q42: =IF(AND(YEAR($F42)=YEAR(Q$3),ROUNDUP(MONTH($F42)/3,0)=Q$4),$C42*(1+$D42/4)^((Q$3-$F42)/91),IF(ROUND(P42,0)=0,0,P42*(1+$D42/4))) -> 0 | R42: =IF(AND(YEAR($F42)=YEAR(R$3),ROUNDUP(MONTH($F42)/3,0)=R$4),$C42*(1+$D42/4)^((R$3-$F42)/91),IF(ROUND(Q42,0)=0,0,Q42*(1+$D42/4))) -> 0 | S42: =IF(AND(YEAR($F42)=YEAR(S$3),ROUNDUP(MONTH($F42)/3,0)=S$4),$C42*(1+$D42/4)^((S$3-$F42)/91),IF(ROUND(R42,0)=0,0,R42*(1+$D42/4))) -> 0 | T42: =IF(AND(YEAR($F42)=YEAR(T$3),ROUNDUP(MONTH($F42)/3,0)=T$4),$C42*(1+$D42/4)^((T$3-$F42)/91),IF(ROUND(S42,0)=0,0,S42*(1+$D42/4))) -> 0 | U42: =IF(AND(YEAR($F42)=YEAR(U$3),ROUNDUP(MONTH($F42)/3,0)<=U$4),$C42*(1+$D42)^((U$3-$F42)/365),IF(ROUND(T42,0)=0,0,T42*(1+$D42))) -> 0 | V42: =IF(AND(YEAR($F42)=YEAR(V$3),ROUNDUP(MONTH($F42)/3,0)<=V$4),$C42*(1+$D42)^((V$3-$F42)/365),IF(ROUND(U42,0)=0,0,U42*(1+$D42))) -> 0 | W42: =IF(AND(YEAR($F42)=YEAR(W$3),ROUNDUP(MONTH($F42)/3,0)<=W$4),$C42*(1+$D42)^((W$3-$F42)/365),IF(ROUND(V42,0)=0,0,V42*(1+$D42))) -> 0 | X42: =IF(AND(YEAR($F42)=YEAR(X$3),ROUNDUP(MONTH($F42)/3,0)<=X$4),$C42*(1+$D42)^((X$3-$F42)/365),IF(ROUND(W42,0)=0,0,W42*(1+$D42))) -> 0 | Y42: =A42&" "&B42 -> PE038
G43: =+C43/lgh_inputs!$D$10 -> 0 | I43: =IF($F43<I$3,C43*(1+D43)^((I$3-$F$5)/365),0) -> 0 | J43: =IF(AND(YEAR($F43)=YEAR(J$3),ROUNDUP(MONTH($F43)/3,0)<=J$4),$C43*(1+$D43)^((J$3-$F43)/365),IF(ROUND(I43,0)=0,0,I43*(1+$D43))) -> 0 | K43: =IF(AND(YEAR($F43)=YEAR(K$3),ROUNDUP(MONTH($F43)/3,0)<=K$4),$C43*(1+$D43)^((K$3-$F43)/365),IF(ROUND(J43,0)=0,0,J43*(1+$D43))) -> 0 | L43: =IF(AND(YEAR($F43)=YEAR(L$3),ROUNDUP(MONTH($F43)/3,0)<=L$4),$C43*(1+$D43)^((L$3-$F43)/365),IF(ROUND(K43,0)=0,0,K43*(1+$D43))) -> 0 | M43: =IF(AND(YEAR($F43)=YEAR(M$3),ROUNDUP(MONTH($F43)/3,0)=M$4),$C43*(1+$D43/4)^((M$3-$F43)/91),IF(ROUND(L43,0)=0,0,L43*(1+$D43/4))) -> 0 | N43: =IF(AND(YEAR($F43)=YEAR(N$3),ROUNDUP(MONTH($F43)/3,0)=N$4),$C43*(1+$D43/4)^((N$3-$F43)/91),IF(ROUND(M43,0)=0,0,M43*(1+$D43/4))) -> 0 | O43: =IF(AND(YEAR($F43)=YEAR(O$3),ROUNDUP(MONTH($F43)/3,0)=O$4),$C43*(1+$D43/4)^((O$3-$F43)/91),IF(ROUND(N43,0)=0,0,N43*(1+$D43/4))) -> 0 | P43: =IF(AND(YEAR($F43)=YEAR(P$3),ROUNDUP(MONTH($F43)/3,0)=P$4),$C43*(1+$D43/4)^((P$3-$F43)/91),IF(ROUND(O43,0)=0,0,O43*(1+$D43/4))) -> 0 | Q43: =IF(AND(YEAR($F43)=YEAR(Q$3),ROUNDUP(MONTH($F43)/3,0)=Q$4),$C43*(1+$D43/4)^((Q$3-$F43)/91),IF(ROUND(P43,0)=0,0,P43*(1+$D43/4))) -> 0 | R43: =IF(AND(YEAR($F43)=YEAR(R$3),ROUNDUP(MONTH($F43)/3,0)=R$4),$C43*(1+$D43/4)^((R$3-$F43)/91),IF(ROUND(Q43,0)=0,0,Q43*(1+$D43/4))) -> 0 | S43: =IF(AND(YEAR($F43)=YEAR(S$3),ROUNDUP(MONTH($F43)/3,0)=S$4),$C43*(1+$D43/4)^((S$3-$F43)/91),IF(ROUND(R43,0)=0,0,R43*(1+$D43/4))) -> 0 | T43: =IF(AND(YEAR($F43)=YEAR(T$3),ROUNDUP(MONTH($F43)/3,0)=T$4),$C43*(1+$D43/4)^((T$3-$F43)/91),IF(ROUND(S43,0)=0,0,S43*(1+$D43/4))) -> 0 | U43: =IF(AND(YEAR($F43)=YEAR(U$3),ROUNDUP(MONTH($F43)/3,0)<=U$4),$C43*(1+$D43)^((U$3-$F43)/365),IF(ROUND(T43,0)=0,0,T43*(1+$D43))) -> 0 | V43: =IF(AND(YEAR($F43)=YEAR(V$3),ROUNDUP(MONTH($F43)/3,0)<=V$4),$C43*(1+$D43)^((V$3-$F43)/365),IF(ROUND(U43,0)=0,0,U43*(1+$D43))) -> 0 | W43: =IF(AND(YEAR($F43)=YEAR(W$3),ROUNDUP(MONTH($F43)/3,0)<=W$4),$C43*(1+$D43)^((W$3-$F43)/365),IF(ROUND(V43,0)=0,0,V43*(1+$D43))) -> 0 | X43: =IF(AND(YEAR($F43)=YEAR(X$3),ROUNDUP(MONTH($F43)/3,0)<=X$4),$C43*(1+$D43)^((X$3-$F43)/365),IF(ROUND(W43,0)=0,0,W43*(1+$D43))) -> 0 | Y43: =A43&" "&B43
C44: =SUM(C5:C43) -> 55375000 | G44: =SUM(G5:G39) -> 2295000
A45: QUARTERLY TOTALS: | H45: Accrued Interest | J45: =+J47+SUM($I$54,$J$54) -> 28355192 | K45: =+K47+SUM($I$54,$J$54,$K$54) -> 33699850 | L45: =+L47+SUM($I$54,$J$54,$K$54,L54) -> 37580209
A46: adj. for previous reporting
A47: Balance | C47: =SUM(C5:C43) -> 55375000 | I47: =SUM(I5:I43)+I46 -> 10421929 | J47: =SUM(J5:J43)+J46 -> 33855192 | K47: =SUM(K5:K43)+K46 -> 39199850 | L47: =SUM(L5:L43)+L46 -> 51080209 | M47: =SUM(M5:M43)+M46 -> 49890886 | N47: =SUM(N5:N43)+N46 -> 50888704 | O47: =SUM(O5:O43)+O46 -> 51906478 | P47: =SUM(P5:P43)+P46 -> 54144869 | ... X47: =SUM(X5:X43)+X46 -> 87446502
A48: Number of Active Debts: | C48: =COUNTA(A5:A43)-COUNTBLANK(A5:A43) -> 37 | I48: =COUNTIF(I5:I43,">0") -> 4 | J48: =COUNTIF(J5:J43,">0") -> 19 | K48: =COUNTIF(K5:K43,">0") -> 24 | L48: =COUNTIF(L5:L43,">0") -> 29 | M48: =COUNTIF(M5:M43,">0") -> 28 | N48: =COUNTIF(N5:N43,">0") -> 28 | O48: =COUNTIF(O5:O43,">0") -> 28 | P48: =COUNTIF(P5:P43,">0") -> 29 | ... X48: =COUNTIF(X5:X43,">0") -> 32
A49: Average Interest Rate: | C49: =AVERAGE($D$5:D43) -> 0.08 | L49: =+L47-L45 -> 13500000
A50: WACC | C50: =SUMPRODUCT($C$5:$C14,$D$5:$D14)/SUM($C$5:$C14) -> 0.08
A52: Cashflows Sources and Uses
A53: Sources/In (cash)
A54: adj. for previous reporting (previous fundings) | J54: -5500000 | L54: -8000000
A55: Total LGH Debt sources (money to LGH) | I55: {=SUMPRODUCT((YEAR(I3)=YEAR($F$5:$F42))*(ROUNDUP(MONTH($F$5:$F42)/3,0)=I4)*$C$5:$C42)+I54} -> 0 | J55: {=SUMPRODUCT((YEAR(J3)=YEAR($F$5:$F42))*(ROUNDUP(MONTH($F$5:$F42)/3,0)=J4)*$C$5:$C42)+J54} -> 0 | K55: {=SUMPRODUCT((YEAR(K3)=YEAR($F$5:$F42))*(ROUNDUP(MONTH($F$5:$F42)/3,0)=K4)*$C$5:$C42)+K54} -> 0 | L55: {=SUMPRODUCT((YEAR(L3)=YEAR($F$5:$F42))*(ROUNDUP(MONTH($F$5:$F42)/3,0)=L4)*$C$5:$C42)+L54} -> 0 | M55: {=SUMPRODUCT((YEAR(M3)=YEAR($F$5:$F42))*(ROUNDUP(MONTH($F$5:$F42)/3,0)=M4)*$C$5:$C42)+M54} -> 6050000 | N55: {=SUMPRODUCT((YEAR(N3)=YEAR($F$5:$F42))*(ROUNDUP(MONTH($F$5:$F42)/3,0)=N4)*$C$5:$C42)+N54} -> 0 | O55: {=SUMPRODUCT((YEAR(O3)=YEAR($F$5:$F42))*(ROUNDUP(MONTH($F$5:$F42)/3,0)=O4)*$C$5:$C42)+O54} -> 0 | P55: {=SUMPRODUCT((YEAR(P3)=YEAR($F$5:$F42))*(ROUNDUP(MONTH($F$5:$F42)/3,0)=P4)*$C$5:$C42)+P54} -> 1200000 | ... X55: {=SUMPRODUCT((YEAR(X3)=YEAR($F$5:$F42))*(ROUNDUP(MONTH($F$5:$F42)/3,0)=X4)*$C$5:$C42)+X54} -> 0
H57: =VLOOKUP(B5,B5:F43,5,FALSE) -> 44365 | J57: Dollars | K57: Units
A58: Summary Table | F58: Date: | G58: 45657 | I58: Max Issuance : | J58: 50000000 | K58: 2000000
A60: Entity | B60: Individual | C60: Individual | D60: Year | E60: Notional | F60: Units | G60: Intereset | H60: Balance | I60: Gross Participation | J60: Share | K60: Net Participation (non-diluted)
A61: =Y5 -> PE001 PFNGT LLC | D61: =YEAR(_xlfn.MINIFS($F$5:$F$43,$Y$5:$Y$43,A61)) -> 2021 | E61: {=SUM(IF($A61=$Y$5:$Y$43,$C$5:$C$43,0))} -> 5000000 | F61: {=SUM(IF($A61=$Y$5:$Y$43,$G$5:$G$43,0))} -> 200000 | G61: =INDEX(L$5:L$43,MATCH(A61,Y$5:Y$43,0))-E61 -> 1564314.3 | H61: =+E61+G61 -> 6564314.3 | I61: {=IF(A61>"",SUMPRODUCT((A61=$Y$5:$Y$43)*$E$5:$E$43)/COUNTIF($Y$5:$Y$43,A61),0)} -> 0.175 | J61: =IF($I61>0,$F61/$F$97,"") -> 0.11730205 | K61: =IFERROR($I61*($F$97/$K$58)*100%*$J61,0) -> 0.0175
A62: =Y6 -> PE002 Derivee Capital Advisors, LLC | D62: =YEAR(_xlfn.MINIFS($F$5:$F$43,$Y$5:$Y$43,A62)) -> 2021 | E62: {=SUM(IF($A62=$Y$5:$Y$43,$C$5:$C$43,0))} -> 3000000 | F62: {=SUM(IF($A62=$Y$5:$Y$43,$G$5:$G$43,0))} -> 120000 | G62: =INDEX(L$5:L$43,MATCH(A62,Y$5:Y$43,0))-E62 -> 938588.6 | H62: =+E62+G62 -> 3938588.6 | I62: {=IF(A62>"",SUMPRODUCT((A62=$Y$5:$Y$43)*$E$5:$E$43)/COUNTIF($Y$5:$Y$43,A62),0)} -> 0.175 | J62: =IF($I62>0,$F62/$F$97,"") -> 0.070381232 | K62: =IFERROR($I62*($F$97/$K$58)*100%*$J62,0) -> 0.0105
A63: =Y7 -> PE003 Derivee Capital Advisors, LLC | D63: =YEAR(_xlfn.MINIFS($F$5:$F$43,$Y$5:$Y$43,A63)) -> 2021 | E63: {=SUM(IF($A63=$Y$5:$Y$43,$C$5:$C$43,0))} -> 2000000 | F63: {=SUM(IF($A63=$Y$5:$Y$43,$G$5:$G$43,0))} -> 80000 | G63: =INDEX(L$5:L$43,MATCH(A63,Y$5:Y$43,0))-E63 -> 625725.74 | H63: =+E63+G63 -> 2625725.7 | I63: {=IF(A63>"",SUMPRODUCT((A63=$Y$5:$Y$43)*$E$5:$E$43)/COUNTIF($Y$5:$Y$43,A63),0)} -> 0.175 | J63: =IF($I63>0,$F63/$F$97,"") -> 0.046920821 | K63: =IFERROR($I63*($F$97/$K$58)*100%*$J63,0) -> 0.007
A64: =Y8 -> PE004 DCAPP Hotel Ventures LLC | D64: =YEAR(_xlfn.MINIFS($F$5:$F$43,$Y$5:$Y$43,A64)) -> 2022 | E64: {=SUM(IF($A64=$Y$5:$Y$43,$C$5:$C$43,0))} -> 5000000 | F64: {=SUM(IF($A64=$Y$5:$Y$43,$G$5:$G$43,0))} -> 200000 | G64: =INDEX(L$5:L$43,MATCH(A64,Y$5:Y$43,0))-E64 -> 1289270.4 | H64: =+E64+G64 -> 6289270.4 | I64: {=IF(A64>"",SUMPRODUCT((A64=$Y$5:$Y$43)*$E$5:$E$43)/COUNTIF($Y$5:$Y$43,A64),0)} -> 0.14 | J64: =IF($I64>0,$F64/$F$97,"") -> 0.11730205 | K64: =IFERROR($I64*($F$97/$K$58)*100%*$J64,0) -> 0.014
A65: =Y9 -> PE005 DCAPP Hotel Ventures LLC | D65: =YEAR(_xlfn.MINIFS($F$5:$F$43,$Y$5:$Y$43,A65)) -> 2022 | E65: {=SUM(IF($A65=$Y$5:$Y$43,$C$5:$C$43,0))} -> 4000000 | F65: {=SUM(IF($A65=$Y$5:$Y$43,$G$5:$G$43,0))} -> 160000 | G65: =INDEX(L$5:L$43,MATCH(A65,Y$5:Y$43,0))-E65 -> 1031416.3 | H65: =+E65+G65 -> 5031416.3 | I65: {=IF(A65>"",SUMPRODUCT((A65=$Y$5:$Y$43)*$E$5:$E$43)/COUNTIF($Y$5:$Y$43,A65),0)} -> 0.14 | J65: =IF($I65>0,$F65/$F$97,"") -> 0.093841642 | K65: =IFERROR($I65*($F$97/$K$58)*100%*$J65,0) -> 0.0112
A66: =Y10 -> PE006 DCAPP Hotel Ventures LLC | D66: =YEAR(_xlfn.MINIFS($F$5:$F$43,$Y$5:$Y$43,A66)) -> 2022 | E66: {=SUM(IF($A66=$Y$5:$Y$43,$C$5:$C$43,0))} -> 2000000 | F66: {=SUM(IF($A66=$Y$5:$Y$43,$G$5:$G$43,0))} -> 80000 | G66: =INDEX(L$5:L$43,MATCH(A66,Y$5:Y$43,0))-E66 -> 483034.76 | H66: =+E66+G66 -> 2483034.8 | I66: {=IF(A66>"",SUMPRODUCT((A66=$Y$5:$Y$43)*$E$5:$E$43)/COUNTIF($Y$5:$Y$43,A66),0)} -> 0.14 | J66: =IF($I66>0,$F66/$F$97,"") -> 0.046920821 | K66: =IFERROR($I66*($F$97/$K$58)*100%*$J66,0) -> 0.0056
A67: =Y11 -> PE007 La Pointe Investments LLC | D67: =YEAR(_xlfn.MINIFS($F$5:$F$43,$Y$5:$Y$43,A67)) -> 2022 | E67: {=SUM(IF($A67=$Y$5:$Y$43,$C$5:$C$43,0))} -> 2500000 | F67: {=SUM(IF($A67=$Y$5:$Y$43,$G$5:$G$43,0))} -> 100000 | G67: =INDEX(L$5:L$43,MATCH(A67,Y$5:Y$43,0))-E67 -> 558318.96 | H67: =+E67+G67 -> 3058319 | I67: {=IF(A67>"",SUMPRODUCT((A67=$Y$5:$Y$43)*$E$5:$E$43)/COUNTIF($Y$5:$Y$43,A67),0)} -> 0.125 | J67: =IF($I67>0,$F67/$F$97,"") -> 0.058651026 | K67: =IFERROR($I67*($F$97/$K$58)*100%*$J67,0) -> 0.00625
A68: =Y12 -> PE008 La Pointe Investments LLC | D68: =YEAR(_xlfn.MINIFS($F$5:$F$43,$Y$5:$Y$43,A68)) -> 2022 | E68: {=SUM(IF($A68=$Y$5:$Y$43,$C$5:$C$43,0))} -> 2500000 | F68: {=SUM(IF($A68=$Y$5:$Y$43,$G$5:$G$43,0))} -> 100000 | G68: =INDEX(L$5:L$43,MATCH(A68,Y$5:Y$43,0))-E68 -> 443179.06 | H68: =+E68+G68 -> 2943179.1 | I68: {=IF(A68>"",SUMPRODUCT((A68=$Y$5:$Y$43)*$E$5:$E$43)/COUNTIF($Y$5:$Y$43,A68),0)} -> 0.125 | J68: =IF($I68>0,$F68/$F$97,"") -> 0.058651026 | K68: =IFERROR($I68*($F$97/$K$58)*100%*$J68,0) -> 0.00625
A69: =Y13 -> PE009 La Pointe Investments LLC | D69: =YEAR(_xlfn.MINIFS($F$5:$F$43,$Y$5:$Y$43,A69)) -> 2023 | E69: {=SUM(IF($A69=$Y$5:$Y$43,$C$5:$C$43,0))} -> 1000000 | F69: {=SUM(IF($A69=$Y$5:$Y$43,$G$5:$G$43,0))} -> 40000 | G69: =INDEX(L$5:L$43,MATCH(A69,Y$5:Y$43,0))-E69 -> 137977.29 | H69: =+E69+G69 -> 1137977.3 | I69: {=IF(A69>"",SUMPRODUCT((A69=$Y$5:$Y$43)*$E$5:$E$43)/COUNTIF($Y$5:$Y$43,A69),0)} -> 0.125 | J69: =IF($I69>0,$F69/$F$97,"") -> 0.023460411 | K69: =IFERROR($I69*($F$97/$K$58)*100%*$J69,0) -> 0.0025
A70: =Y14 -> PE010 Benjamin Rego Jr. | D70: =YEAR(_xlfn.MINIFS($F$5:$F$43,$Y$5:$Y$43,A70)) -> 2022 | E70: {=SUM(IF($A70=$Y$5:$Y$43,$C$5:$C$43,0))} -> 450000 | F70: {=SUM(IF($A70=$Y$5:$Y$43,$G$5:$G$43,0))} -> 18000 | G70: =INDEX(L$5:L$43,MATCH(A70,Y$5:Y$43,0))-E70 -> 99917.35 | H70: =+E70+G70 -> 549917.35 | I70: {=IF(A70>"",SUMPRODUCT((A70=$Y$5:$Y$43)*$E$5:$E$43)/COUNTIF($Y$5:$Y$43,A70),0)} -> 0.1 | J70: =IF($I70>0,$F70/$F$97,"") -> 0.010557185 | K70: =IFERROR($I70*($F$97/$K$58)*100%*$J70,0) -> 0.0009
A71: =Y15 -> PE011 Benjamin Rego Jr. | D71: =YEAR(_xlfn.MINIFS($F$5:$F$43,$Y$5:$Y$43,A71)) -> 2022 | E71: {=SUM(IF($A71=$Y$5:$Y$43,$C$5:$C$43,0))} -> 50000 | F71: {=SUM(IF($A71=$Y$5:$Y$43,$G$5:$G$43,0))} -> 2000 | G71: =INDEX(L$5:L$43,MATCH(A71,Y$5:Y$43,0))-E71 -> 11089.046 | H71: =+E71+G71 -> 61089.046 | I71: {=IF(A71>"",SUMPRODUCT((A71=$Y$5:$Y$43)*$E$5:$E$43)/COUNTIF($Y$5:$Y$43,A71),0)} -> 0.1 | J71: =IF($I71>0,$F71/$F$97,"") -> 0.0011730205 | K71: =IFERROR($I71*($F$97/$K$58)*100%*$J71,0) -> 0.0001
A72: =Y16 -> PE012 Benjamin Rego Jr._1 | D72: =YEAR(_xlfn.MINIFS($F$5:$F$43,$Y$5:$Y$43,A72)) -> 2023 | E72: {=SUM(IF($A72=$Y$5:$Y$43,$C$5:$C$43,0))} -> 100000 | F72: {=SUM(IF($A72=$Y$5:$Y$43,$G$5:$G$43,0))} -> 4000 | G72: =INDEX(L$5:L$43,MATCH(A72,Y$5:Y$43,0))-E72 -> 13510.159 | H72: =+E72+G72 -> 113510.16 | I72: {=IF(A72>"",SUMPRODUCT((A72=$Y$5:$Y$43)*$E$5:$E$43)/COUNTIF($Y$5:$Y$43,A72),0)} -> 0.053 | J72: =IF($I72>0,$F72/$F$97,"") -> 0.0023460411 | K72: =IFERROR($I72*($F$97/$K$58)*100%*$J72,0) -> 0.000106
... A95: =Y39 -> PE035 guy | D95: =YEAR(_xlfn.MINIFS($F$5:$F$43,$Y$5:$Y$43,A95)) -> 2026 | E95: {=SUM(IF($A95=$Y$5:$Y$43,$C$5:$C$43,0))} -> 1000000 | F95: {=SUM(IF($A95=$Y$5:$Y$43,$G$5:$G$43,0))} -> 40000 | G95: =INDEX(L$5:L$43,MATCH(A95,Y$5:Y$43,0))-E95 -> -1000000 | H95: =+E95+G95 -> 0 | I95: {=IF(A95>"",SUMPRODUCT((A95=$Y$5:$Y$43)*$E$5:$E$43)/COUNTIF($Y$5:$Y$43,A95),0)} -> 0.053 | J95: =IF($I95>0,$F95/$F$97,"") -> 0.023460411 | K95: =IFERROR($I95*($F$97/$K$58)*100%*$J95,0) -> 0.00106
E97: {=SUMPRODUCT((G58>=F5:F43)*C5:C43)} -> 42625000 | F97: {=SUMPRODUCT((G58>=F5:F43)*G5:G43)-SUMPRODUCT((G58>+F5:F43)*H5:H43)} -> 1705000 | K97: {=SUMPRODUCT((YEAR($G$58)>=$D$61:$D$96)*K61:K96)} -> 0.3640525
A99: Pref Investor Participation in Equity
B100: 2024 | C100: 2025 | D100: 2025 | E100: 2025 | F100: 2025 | G100: 2026 | H100: 2026 | I100: 2026 | J100: 2026 | K100: 2027 | L100: 2028 | M100: 2029 | N100: 2030
C101: Q1 | D101: Q2 | E101: Q3 | F101: Q4 | G101: Q1 | H101: Q2 | I101: Q3 | J101: Q4
A102: =+A61 -> PE001 PFNGT LLC | B102: 0.017326733 | C102: {=IF(SUMPRODUCT(($A102=$Y$5:$Y$43)*(C$100=YEAR($F$5:$F$43)))>=1,SUMPRODUCT(($A102=$A$61:$A$95)*$I$61:$I$95)*((SUMPRODUCT((C$100>=YEAR($F$5:$F$43))*$G$5:$G$43)/$K$58)*100%)*(SUMPRODUCT(($A102=$Y$5:$Y$43)*(C$100>=YEAR($F$5:$F$43))*$G$5:$G$43)/SUMPRODUCT((C$100>=YEAR($F$5:$F$43))*$G$5:$G$43)),IF(B102>0,B102/(1+lgh_equity!C$24),0))} -> 0.017326733 | D102: {=IF(SUMPRODUCT(($A102=$Y$5:$Y$43)*(D$100=YEAR($F$5:$F$43)))>=1,SUMPRODUCT(($A102=$A$61:$A$95)*$I$61:$I$95)*((SUMPRODUCT((D$100>=YEAR($F$5:$F$43))*$G$5:$G$43)/$K$58)*100%)*(SUMPRODUCT(($A102=$Y$5:$Y$43)*(D$100>=YEAR($F$5:$F$43))*$G$5:$G$43)/SUMPRODUCT((D$100>=YEAR($F$5:$F$43))*$G$5:$G$43)),IF(C102>0,C102/(1+lgh_equity!D$24),0))} -> 0.014018392 | E102: {=IF(SUMPRODUCT(($A102=$Y$5:$Y$43)*(E$100=YEAR($F$5:$F$43)))>=1,SUMPRODUCT(($A102=$A$61:$A$95)*$I$61:$I$95)*((SUMPRODUCT((E$100>=YEAR($F$5:$F$43))*$G$5:$G$43)/$K$58)*100%)*(SUMPRODUCT(($A102=$Y$5:$Y$43)*(E$100>=YEAR($F$5:$F$43))*$G$5:$G$43)/SUMPRODUCT((E$100>=YEAR($F$5:$F$43))*$G$5:$G$43)),IF(D102>0,D102/(1+lgh_equity!E$24),0))} -> 0.013973676 | F102: {=IF(SUMPRODUCT(($A102=$Y$5:$Y$43)*(F$100=YEAR($F$5:$F$43)))>=1,SUMPRODUCT(($A102=$A$61:$A$95)*$I$61:$I$95)*((SUMPRODUCT((F$100>=YEAR($F$5:$F$43))*$G$5:$G$43)/$K$58)*100%)*(SUMPRODUCT(($A102=$Y$5:$Y$43)*(F$100>=YEAR($F$5:$F$43))*$G$5:$G$43)/SUMPRODUCT((F$100>=YEAR($F$5:$F$43))*$G$5:$G$43)),IF(E102>0,E102/(1+lgh_equity!F$24),0))} -> 0.013973676 | G102: {=IF(SUMPRODUCT(($A102=$Y$5:$Y$43)*(G$100=YEAR($F$5:$F$43)))>=1,SUMPRODUCT(($A102=$A$61:$A$95)*$I$61:$I$95)*((SUMPRODUCT((G$100>=YEAR($F$5:$F$43))*$G$5:$G$43)/$K$58)*100%)*(SUMPRODUCT(($A102=$Y$5:$Y$43)*(G$100>=YEAR($F$5:$F$43))*$G$5:$G$43)/SUMPRODUCT((G$100>=YEAR($F$5:$F$43))*$G$5:$G$43)),IF(F102>0,F102/(1+lgh_equity!G$24),0))} -> 0.013973676 | H102: {=IF(SUMPRODUCT(($A102=$Y$5:$Y$43)*(H$100=YEAR($F$5:$F$43)))>=1,SUMPRODUCT(($A102=$A$61:$A$95)*$I$61:$I$95)*((SUMPRODUCT((H$100>=YEAR($F$5:$F$43))*$G$5:$G$43)/$K$58)*100%)*(SUMPRODUCT(($A102=$Y$5:$Y$43)*(H$100>=YEAR($F$5:$F$43))*$G$5:$G$43)/SUMPRODUCT((H$100>=YEAR($F$5:$F$43))*$G$5:$G$43)),IF(G102>0,G102/(1+lgh_equity!H$24),0))} -> 0.013973676 | I102: {=IF(SUMPRODUCT(($A102=$Y$5:$Y$43)*(I$100=YEAR($F$5:$F$43)))>=1,SUMPRODUCT(($A102=$A$61:$A$95)*$I$61:$I$95)*((SUMPRODUCT((I$100>=YEAR($F$5:$F$43))*$G$5:$G$43)/$K$58)*100%)*(SUMPRODUCT(($A102=$Y$5:$Y$43)*(I$100>=YEAR($F$5:$F$43))*$G$5:$G$43)/SUMPRODUCT((I$100>=YEAR($F$5:$F$43))*$G$5:$G$43)),IF(H102>0,H102/(1+lgh_equity!I$24),0))} -> 0.013973676 | J102: {=IF(SUMPRODUCT(($A102=$Y$5:$Y$43)*(J$100=YEAR($F$5:$F$43)))>=1,SUMPRODUCT(($A102=$A$61:$A$95)*$I$61:$I$95)*((SUMPRODUCT((J$100>=YEAR($F$5:$F$43))*$G$5:$G$43)/$K$58)*100%)*(SUMPRODUCT(($A102=$Y$5:$Y$43)*(J$100>=YEAR($F$5:$F$43))*$G$5:$G$43)/SUMPRODUCT((J$100>=YEAR($F$5:$F$43))*$G$5:$G$43)),IF(I102>0,I102/(1+lgh_equity!J$24),0))} -> 0.013973676 | ... N102: {=IF(SUMPRODUCT(($A102=$Y$5:$Y$43)*(N$100=YEAR($F$5:$F$43)))>=1,SUMPRODUCT(($A102=$A$61:$A$95)*$I$61:$I$95)*((SUMPRODUCT((N$100>=YEAR($F$5:$F$43))*$G$5:$G$43)/$K$58)*100%)*(SUMPRODUCT(($A102=$Y$5:$Y$43)*(N$100>=YEAR($F$5:$F$43))*$G$5:$G$43)/SUMPRODUCT((N$100>=YEAR($F$5:$F$43))*$G$5:$G$43)),IF(M102>0,M102/(1+lgh_equity!N$24),0))} -> 0.013973676
A103: =+A62 -> PE002 Derivee Capital Advisors, LLC | B103: 0.01039604 | C103: {=IF(SUMPRODUCT(($A103=$Y$5:$Y$43)*(C$100=YEAR($F$5:$F$43)))>=1,SUMPRODUCT(($A103=$A$61:$A$95)*$I$61:$I$95)*((SUMPRODUCT((C$100>=YEAR($F$5:$F$43))*$G$5:$G$43)/$K$58)*100%)*(SUMPRODUCT(($A103=$Y$5:$Y$43)*(C$100>=YEAR($F$5:$F$43))*$G$5:$G$43)/SUMPRODUCT((C$100>=YEAR($F$5:$F$43))*$G$5:$G$43)),IF(B103>0,B103/(1+lgh_equity!C$24),0))} -> 0.01039604 | D103: {=IF(SUMPRODUCT(($A103=$Y$5:$Y$43)*(D$100=YEAR($F$5:$F$43)))>=1,SUMPRODUCT(($A103=$A$61:$A$95)*$I$61:$I$95)*((SUMPRODUCT((D$100>=YEAR($F$5:$F$43))*$G$5:$G$43)/$K$58)*100%)*(SUMPRODUCT(($A103=$Y$5:$Y$43)*(D$100>=YEAR($F$5:$F$43))*$G$5:$G$43)/SUMPRODUCT((D$100>=YEAR($F$5:$F$43))*$G$5:$G$43)),IF(C103>0,C103/(1+lgh_equity!D$24),0))} -> 0.0084110353 | E103: {=IF(SUMPRODUCT(($A103=$Y$5:$Y$43)*(E$100=YEAR($F$5:$F$43)))>=1,SUMPRODUCT(($A103=$A$61:$A$95)*$I$61:$I$95)*((SUMPRODUCT((E$100>=YEAR($F$5:$F$43))*$G$5:$G$43)/$K$58)*100%)*(SUMPRODUCT(($A103=$Y$5:$Y$43)*(E$100>=YEAR($F$5:$F$43))*$G$5:$G$43)/SUMPRODUCT((E$100>=YEAR($F$5:$F$43))*$G$5:$G$43)),IF(D103>0,D103/(1+lgh_equity!E$24),0))} -> 0.0083842058 | F103: {=IF(SUMPRODUCT(($A103=$Y$5:$Y$43)*(F$100=YEAR($F$5:$F$43)))>=1,SUMPRODUCT(($A103=$A$61:$A$95)*$I$61:$I$95)*((SUMPRODUCT((F$100>=YEAR($F$5:$F$43))*$G$5:$G$43)/$K$58)*100%)*(SUMPRODUCT(($A103=$Y$5:$Y$43)*(F$100>=YEAR($F$5:$F$43))*$G$5:$G$43)/SUMPRODUCT((F$100>=YEAR($F$5:$F$43))*$G$5:$G$43)),IF(E103>0,E103/(1+lgh_equity!F$24),0))} -> 0.0083842058 | G103: {=IF(SUMPRODUCT(($A103=$Y$5:$Y$43)*(G$100=YEAR($F$5:$F$43)))>=1,SUMPRODUCT(($A103=$A$61:$A$95)*$I$61:$I$95)*((SUMPRODUCT((G$100>=YEAR($F$5:$F$43))*$G$5:$G$43)/$K$58)*100%)*(SUMPRODUCT(($A103=$Y$5:$Y$43)*(G$100>=YEAR($F$5:$F$43))*$G$5:$G$43)/SUMPRODUCT((G$100>=YEAR($F$5:$F$43))*$G$5:$G$43)),IF(F103>0,F103/(1+lgh_equity!G$24),0))} -> 0.0083842058 | H103: {=IF(SUMPRODUCT(($A103=$Y$5:$Y$43)*(H$100=YEAR($F$5:$F$43)))>=1,SUMPRODUCT(($A103=$A$61:$A$95)*$I$61:$I$95)*((SUMPRODUCT((H$100>=YEAR($F$5:$F$43))*$G$5:$G$43)/$K$58)*100%)*(SUMPRODUCT(($A103=$Y$5:$Y$43)*(H$100>=YEAR($F$5:$F$43))*$G$5:$G$43)/SUMPRODUCT((H$100>=YEAR($F$5:$F$43))*$G$5:$G$43)),IF(G103>0,G103/(1+lgh_equity!H$24),0))} -> 0.0083842058 | I103: {=IF(SUMPRODUCT(($A103=$Y$5:$Y$43)*(I$100=YEAR($F$5:$F$43)))>=1,SUMPRODUCT(($A103=$A$61:$A$95)*$I$61:$I$95)*((SUMPRODUCT((I$100>=YEAR($F$5:$F$43))*$G$5:$G$43)/$K$58)*100%)*(SUMPRODUCT(($A103=$Y$5:$Y$43)*(I$100>=YEAR($F$5:$F$43))*$G$5:$G$43)/SUMPRODUCT((I$100>=YEAR($F$5:$F$43))*$G$5:$G$43)),IF(H103>0,H103/(1+lgh_equity!I$24),0))} -> 0.0083842058 | J103: {=IF(SUMPRODUCT(($A103=$Y$5:$Y$43)*(J$100=YEAR($F$5:$F$43)))>=1,SUMPRODUCT(($A103=$A$61:$A$95)*$I$61:$I$95)*((SUMPRODUCT((J$100>=YEAR($F$5:$F$43))*$G$5:$G$43)/$K$58)*100%)*(SUMPRODUCT(($A103=$Y$5:$Y$43)*(J$100>=YEAR($F$5:$F$43))*$G$5:$G$43)/SUMPRODUCT((J$100>=YEAR($F$5:$F$43))*$G$5:$G$43)),IF(I103>0,I103/(1+lgh_equity!J$24),0))} -> 0.0083842058 | ... N103: {=IF(SUMPRODUCT(($A103=$Y$5:$Y$43)*(N$100=YEAR($F$5:$F$43)))>=1,SUMPRODUCT(($A103=$A$61:$A$95)*$I$61:$I$95)*((SUMPRODUCT((N$100>=YEAR($F$5:$F$43))*$G$5:$G$43)/$K$58)*100%)*(SUMPRODUCT(($A103=$Y$5:$Y$43)*(N$100>=YEAR($F$5:$F$43))*$G$5:$G$43)/SUMPRODUCT((N$100>=YEAR($F$5:$F$43))*$G$5:$G$43)),IF(M103>0,M103/(1+lgh_equity!N$24),0))} -> 0.0083842058
A104: =+A63 -> PE003 Derivee Capital Advisors, LLC | B104: 0.0069306931 | C104: {=IF(SUMPRODUCT(($A104=$Y$5:$Y$43)*(C$100=YEAR($F$5:$F$43)))>=1,SUMPRODUCT(($A104=$A$61:$A$95)*$I$61:$I$95)*((SUMPRODUCT((C$100>=YEAR($F$5:$F$43))*$G$5:$G$43)/$K$58)*100%)*(SUMPRODUCT(($A104=$Y$5:$Y$43)*(C$100>=YEAR($F$5:$F$43))*$G$5:$G$43)/SUMPRODUCT((C$100>=YEAR($F$5:$F$43))*$G$5:$G$43)),IF(B104>0,B104/(1+lgh_equity!C$24),0))} -> 0.0069306931 | D104: {=IF(SUMPRODUCT(($A104=$Y$5:$Y$43)*(D$100=YEAR($F$5:$F$43)))>=1,SUMPRODUCT(($A104=$A$61:$A$95)*$I$61:$I$95)*((SUMPRODUCT((D$100>=YEAR($F$5:$F$43))*$G$5:$G$43)/$K$58)*100%)*(SUMPRODUCT(($A104=$Y$5:$Y$43)*(D$100>=YEAR($F$5:$F$43))*$G$5:$G$43)/SUMPRODUCT((D$100>=YEAR($F$5:$F$43))*$G$5:$G$43)),IF(C104>0,C104/(1+lgh_equity!D$24),0))} -> 0.0056073569 | E104: {=IF(SUMPRODUCT(($A104=$Y$5:$Y$43)*(E$100=YEAR($F$5:$F$43)))>=1,SUMPRODUCT(($A104=$A$61:$A$95)*$I$61:$I$95)*((SUMPRODUCT((E$100>=YEAR($F$5:$F$43))*$G$5:$G$43)/$K$58)*100%)*(SUMPRODUCT(($A104=$Y$5:$Y$43)*(E$100>=YEAR($F$5:$F$43))*$G$5:$G$43)/SUMPRODUCT((E$100>=YEAR($F$5:$F$43))*$G$5:$G$43)),IF(D104>0,D104/(1+lgh_equity!E$24),0))} -> 0.0055894705 | F104: {=IF(SUMPRODUCT(($A104=$Y$5:$Y$43)*(F$100=YEAR($F$5:$F$43)))>=1,SUMPRODUCT(($A104=$A$61:$A$95)*$I$61:$I$95)*((SUMPRODUCT((F$100>=YEAR($F$5:$F$43))*$G$5:$G$43)/$K$58)*100%)*(SUMPRODUCT(($A104=$Y$5:$Y$43)*(F$100>=YEAR($F$5:$F$43))*$G$5:$G$43)/SUMPRODUCT((F$100>=YEAR($F$5:$F$43))*$G$5:$G$43)),IF(E104>0,E104/(1+lgh_equity!F$24),0))} -> 0.0055894705 | G104: {=IF(SUMPRODUCT(($A104=$Y$5:$Y$43)*(G$100=YEAR($F$5:$F$43)))>=1,SUMPRODUCT(($A104=$A$61:$A$95)*$I$61:$I$95)*((SUMPRODUCT((G$100>=YEAR($F$5:$F$43))*$G$5:$G$43)/$K$58)*100%)*(SUMPRODUCT(($A104=$Y$5:$Y$43)*(G$100>=YEAR($F$5:$F$43))*$G$5:$G$43)/SUMPRODUCT((G$100>=YEAR($F$5:$F$43))*$G$5:$G$43)),IF(F104>0,F104/(1+lgh_equity!G$24),0))} -> 0.0055894705 | H104: {=IF(SUMPRODUCT(($A104=$Y$5:$Y$43)*(H$100=YEAR($F$5:$F$43)))>=1,SUMPRODUCT(($A104=$A$61:$A$95)*$I$61:$I$95)*((SUMPRODUCT((H$100>=YEAR($F$5:$F$43))*$G$5:$G$43)/$K$58)*100%)*(SUMPRODUCT(($A104=$Y$5:$Y$43)*(H$100>=YEAR($F$5:$F$43))*$G$5:$G$43)/SUMPRODUCT((H$100>=YEAR($F$5:$F$43))*$G$5:$G$43)),IF(G104>0,G104/(1+lgh_equity!H$24),0))} -> 0.0055894705 | I104: {=IF(SUMPRODUCT(($A104=$Y$5:$Y$43)*(I$100=YEAR($F$5:$F$43)))>=1,SUMPRODUCT(($A104=$A$61:$A$95)*$I$61:$I$95)*((SUMPRODUCT((I$100>=YEAR($F$5:$F$43))*$G$5:$G$43)/$K$58)*100%)*(SUMPRODUCT(($A104=$Y$5:$Y$43)*(I$100>=YEAR($F$5:$F$43))*$G$5:$G$43)/SUMPRODUCT((I$100>=YEAR($F$5:$F$43))*$G$5:$G$43)),IF(H104>0,H104/(1+lgh_equity!I$24),0))} -> 0.0055894705 | J104: {=IF(SUMPRODUCT(($A104=$Y$5:$Y$43)*(J$100=YEAR($F$5:$F$43)))>=1,SUMPRODUCT(($A104=$A$61:$A$95)*$I$61:$I$95)*((SUMPRODUCT((J$100>=YEAR($F$5:$F$43))*$G$5:$G$43)/$K$58)*100%)*(SUMPRODUCT(($A104=$Y$5:$Y$43)*(J$100>=YEAR($F$5:$F$43))*$G$5:$G$43)/SUMPRODUCT((J$100>=YEAR($F$5:$F$43))*$G$5:$G$43)),IF(I104>0,I104/(1+lgh_equity!J$24),0))} -> 0.0055894705 | ... N104: {=IF(SUMPRODUCT(($A104=$Y$5:$Y$43)*(N$100=YEAR($F$5:$F$43)))>=1,SUMPRODUCT(($A104=$A$61:$A$95)*$I$61:$I$95)*((SUMPRODUCT((N$100>=YEAR($F$5:$F$43))*$G$5:$G$43)/$K$58)*100%)*(SUMPRODUCT(($A104=$Y$5:$Y$43)*(N$100>=YEAR($F$5:$F$43))*$G$5:$G$43)/SUMPRODUCT((N$100>=YEAR($F$5:$F$43))*$G$5:$G$43)),IF(M104>0,M104/(1+lgh_equity!N$24),0))} -> 0.0055894705
